Workbook
Name ds: #REF!
Name ds: #REF!
Name ds: #REF!
Name ds: #REF!
Name ds: #REF!
Name ds: #REF!
Name InfImp22: #REF!
Name InfImp22: #REF!
Name InfImp22: #REF!
Name InfImp22: #REF!
Name InfImp22: '[1]Dados Complementares'!$F$11
Name InfImp22: #REF!
Name InfImp23: #REF!
Name InfImp23: #REF!
Name InfImp23: #REF!
Name InfImp23: #REF!
Name InfImp23: '[1]Dados Complementares'!$G$11
Name InfImp23: #REF!
Name InfImp24: #REF!
Name InfImp24: #REF!
Name InfImp24: #REF!
Name InfImp24: #REF!
Name InfImp24: '[1]Dados Complementares'!$H$11
Name InfImp24: #REF!
Name InfImp25: #REF!
Name InfImp25: #REF!
Name InfImp25: #REF!
Name InfImp25: #REF!
Name InfImp25: '[1]Dados Complementares'!$I$11
Name InfImp25: #REF!
Name InfImp26: #REF!
Name InfImp26: #REF!
Name InfImp26: #REF!
Name InfImp26: #REF!
Name InfImp26: '[1]Dados Complementares'!$J$11
Name InfImp26: #REF!
Name InfImp27: #REF!
Name InfImp27: #REF!
Name InfImp27: #REF!
Name InfImp27: #REF!
Name InfImp27: '[1]Dados Complementares'!$K$11
Name InfImp27: #REF!
Name InfImp28: #REF!
Name InfImp28: #REF!
Name InfImp28: #REF!
Name InfImp28: #REF!
Name InfImp28: '[1]Dados Complementares'!$L$11
Name InfImp28: #REF!
Name InfImp29: #REF!
Name InfImp29: #REF!
Name InfImp29: #REF!
Name InfImp29: #REF!
Name InfImp29: '[1]Dados Complementares'!$M$11
Name InfImp29: #REF!
Name InfImp30: #REF!
Name InfImp30: #REF!
Name InfImp30: #REF!
Name InfImp30: #REF!
Name InfImp30: '[1]Dados Complementares'!$N$11
Name InfImp30: #REF!

Sheet Dashboard
J4: Banco da Amazônia ($BAZA3)
A7: Páginas
A8: Dashboard
A9: Ke | E9: Trimestre Atual | F9: 2 | H9: Custo de Capital Próprio (Ke) | I9: =I10-0.5% -> 0.13949346 | J9: =1000*(SUM(NPV($I9,'DRE + DCF'!$N$36:$U$36,SUM('DRE + DCF'!$V$36,Perpetuidade!G10*(1+J$18)/($I9-J$18))),'DRE + DCF'!$L$36)/((1+$I9)^((5-$F$9)*3/12)))/$F$11 -> 193.66991 | K9: =1000*(SUM(NPV($I9,'DRE + DCF'!$N$36:$U$36,SUM('DRE + DCF'!$V$36,Perpetuidade!H10*(1+K$18)/($I9-K$18))),'DRE + DCF'!$L$36)/((1+$I9)^((5-$F$9)*3/12)))/$F$11 -> 194.53158 | L9: =1000*(SUM(NPV($I9,'DRE + DCF'!$N$36:$U$36,SUM('DRE + DCF'!$V$36,Perpetuidade!I10*(1+L$18)/($I9-L$18))),'DRE + DCF'!$L$36)/((1+$I9)^((5-$F$9)*3/12)))/$F$11 -> 195.43785 | M9: =1000*(SUM(NPV($I9,'DRE + DCF'!$N$36:$U$36,SUM('DRE + DCF'!$V$36,Perpetuidade!J10*(1+M$18)/($I9-M$18))),'DRE + DCF'!$L$36)/((1+$I9)^((5-$F$9)*3/12)))/$F$11 -> 196.39363 | N9: =1000*(SUM(NPV($I9,'DRE + DCF'!$N$36:$U$36,SUM('DRE + DCF'!$V$36,Perpetuidade!K10*(1+N$18)/($I9-N$18))),'DRE + DCF'!$L$36)/((1+$I9)^((5-$F$9)*3/12)))/$F$11 -> 197.40453 | O9: =1000*(SUM(NPV($I9,'DRE + DCF'!$N$36:$U$36,SUM('DRE + DCF'!$V$36,Perpetuidade!L10*(1+O$18)/($I9-O$18))),'DRE + DCF'!$L$36)/((1+$I9)^((5-$F$9)*3/12)))/$F$11 -> 198.47708 | P9: =1000*(SUM(NPV($I9,'DRE + DCF'!$N$36:$U$36,SUM('DRE + DCF'!$V$36,Perpetuidade!M10*(1+P$18)/($I9-P$18))),'DRE + DCF'!$L$36)/((1+$I9)^((5-$F$9)*3/12)))/$F$11 -> 199.61885 | Q9: =1000*(SUM(NPV($I9,'DRE + DCF'!$N$36:$U$36,SUM('DRE + DCF'!$V$36,Perpetuidade!N10*(1+Q$18)/($I9-Q$18))),'DRE + DCF'!$L$36)/((1+$I9)^((5-$F$9)*3/12)))/$F$11 -> 200.83874 | ... S9: =1000*(SUM(NPV($I9,'DRE + DCF'!$N$36:$U$36,SUM('DRE + DCF'!$V$36,Perpetuidade!P10*(1+S$18)/($I9-S$18))),'DRE + DCF'!$L$36)/((1+$I9)^((5-$F$9)*3/12)))/$F$11 -> 203.55671
A10: DRE + DCF | E10: Ticker | F10: BAZA3 | I10: =I11-0.5% -> 0.14449346 | J10: =1000*(SUM(NPV($I10,'DRE + DCF'!$N$36:$U$36,SUM('DRE + DCF'!$V$36,Perpetuidade!G11*(1+J$18)/($I10-J$18))),'DRE + DCF'!$L$36)/((1+$I10)^((5-$F$9)*3/12)))/$F$11 -> 181.64686 | K10: =1000*(SUM(NPV($I10,'DRE + DCF'!$N$36:$U$36,SUM('DRE + DCF'!$V$36,Perpetuidade!H11*(1+K$18)/($I10-K$18))),'DRE + DCF'!$L$36)/((1+$I10)^((5-$F$9)*3/12)))/$F$11 -> 182.30733 | L10: =1000*(SUM(NPV($I10,'DRE + DCF'!$N$36:$U$36,SUM('DRE + DCF'!$V$36,Perpetuidade!I11*(1+L$18)/($I10-L$18))),'DRE + DCF'!$L$36)/((1+$I10)^((5-$F$9)*3/12)))/$F$11 -> 182.99714 | M10: =1000*(SUM(NPV($I10,'DRE + DCF'!$N$36:$U$36,SUM('DRE + DCF'!$V$36,Perpetuidade!J11*(1+M$18)/($I10-M$18))),'DRE + DCF'!$L$36)/((1+$I10)^((5-$F$9)*3/12)))/$F$11 -> 183.71927 | N10: =1000*(SUM(NPV($I10,'DRE + DCF'!$N$36:$U$36,SUM('DRE + DCF'!$V$36,Perpetuidade!K11*(1+N$18)/($I10-N$18))),'DRE + DCF'!$L$36)/((1+$I10)^((5-$F$9)*3/12)))/$F$11 -> 184.47714 | O10: =1000*(SUM(NPV($I10,'DRE + DCF'!$N$36:$U$36,SUM('DRE + DCF'!$V$36,Perpetuidade!L11*(1+O$18)/($I10-O$18))),'DRE + DCF'!$L$36)/((1+$I10)^((5-$F$9)*3/12)))/$F$11 -> 185.27467 | P10: =1000*(SUM(NPV($I10,'DRE + DCF'!$N$36:$U$36,SUM('DRE + DCF'!$V$36,Perpetuidade!M11*(1+P$18)/($I10-P$18))),'DRE + DCF'!$L$36)/((1+$I10)^((5-$F$9)*3/12)))/$F$11 -> 186.11636 | Q10: =1000*(SUM(NPV($I10,'DRE + DCF'!$N$36:$U$36,SUM('DRE + DCF'!$V$36,Perpetuidade!N11*(1+Q$18)/($I10-Q$18))),'DRE + DCF'!$L$36)/((1+$I10)^((5-$F$9)*3/12)))/$F$11 -> 187.00744 | ... S10: =1000*(SUM(NPV($I10,'DRE + DCF'!$N$36:$U$36,SUM('DRE + DCF'!$V$36,Perpetuidade!P11*(1+S$18)/($I10-S$18))),'DRE + DCF'!$L$36)/((1+$I10)^((5-$F$9)*3/12)))/$F$11 -> 188.96312
A11: DRE - Cosif | E11: Ações Emitidas (Ex-Treasury) | F11: 56058315 | I11: =I12-0.5% -> 0.14949346 | J11: =1000*(SUM(NPV($I11,'DRE + DCF'!$N$36:$U$36,SUM('DRE + DCF'!$V$36,Perpetuidade!G12*(1+J$18)/($I11-J$18))),'DRE + DCF'!$L$36)/((1+$I11)^((5-$F$9)*3/12)))/$F$11 -> 170.8731 | K11: =1000*(SUM(NPV($I11,'DRE + DCF'!$N$36:$U$36,SUM('DRE + DCF'!$V$36,Perpetuidade!H12*(1+K$18)/($I11-K$18))),'DRE + DCF'!$L$36)/((1+$I11)^((5-$F$9)*3/12)))/$F$11 -> 171.37871 | L11: =1000*(SUM(NPV($I11,'DRE + DCF'!$N$36:$U$36,SUM('DRE + DCF'!$V$36,Perpetuidade!I12*(1+L$18)/($I11-L$18))),'DRE + DCF'!$L$36)/((1+$I11)^((5-$F$9)*3/12)))/$F$11 -> 171.90306 | M11: =1000*(SUM(NPV($I11,'DRE + DCF'!$N$36:$U$36,SUM('DRE + DCF'!$V$36,Perpetuidade!J12*(1+M$18)/($I11-M$18))),'DRE + DCF'!$L$36)/((1+$I11)^((5-$F$9)*3/12)))/$F$11 -> 172.44793 | N11: =1000*(SUM(NPV($I11,'DRE + DCF'!$N$36:$U$36,SUM('DRE + DCF'!$V$36,Perpetuidade!K12*(1+N$18)/($I11-N$18))),'DRE + DCF'!$L$36)/((1+$I11)^((5-$F$9)*3/12)))/$F$11 -> 173.01534 | O11: =1000*(SUM(NPV($I11,'DRE + DCF'!$N$36:$U$36,SUM('DRE + DCF'!$V$36,Perpetuidade!L12*(1+O$18)/($I11-O$18))),'DRE + DCF'!$L$36)/((1+$I11)^((5-$F$9)*3/12)))/$F$11 -> 173.60762 | P11: =1000*(SUM(NPV($I11,'DRE + DCF'!$N$36:$U$36,SUM('DRE + DCF'!$V$36,Perpetuidade!M12*(1+P$18)/($I11-P$18))),'DRE + DCF'!$L$36)/((1+$I11)^((5-$F$9)*3/12)))/$F$11 -> 174.22737 | Q11: =1000*(SUM(NPV($I11,'DRE + DCF'!$N$36:$U$36,SUM('DRE + DCF'!$V$36,Perpetuidade!N12*(1+Q$18)/($I11-Q$18))),'DRE + DCF'!$L$36)/((1+$I11)^((5-$F$9)*3/12)))/$F$11 -> 174.87761 | ... S11: =1000*(SUM(NPV($I11,'DRE + DCF'!$N$36:$U$36,SUM('DRE + DCF'!$V$36,Perpetuidade!P12*(1+S$18)/($I11-S$18))),'DRE + DCF'!$L$36)/((1+$I11)^((5-$F$9)*3/12)))/$F$11 -> 176.28398
A12: Balanço Patrimonial | E12: Valor do Equity (Em milhões) | F12: =SUM('DRE + DCF'!L38,'DRE + DCF'!N38:W38) -> 8775603.2 | I12: =I13-0.5% -> 0.15449346 | J12: =1000*(SUM(NPV($I12,'DRE + DCF'!$N$36:$U$36,SUM('DRE + DCF'!$V$36,Perpetuidade!G13*(1+J$18)/($I12-J$18))),'DRE + DCF'!$L$36)/((1+$I12)^((5-$F$9)*3/12)))/$F$11 -> 161.16517 | K12: =1000*(SUM(NPV($I12,'DRE + DCF'!$N$36:$U$36,SUM('DRE + DCF'!$V$36,Perpetuidade!H13*(1+K$18)/($I12-K$18))),'DRE + DCF'!$L$36)/((1+$I12)^((5-$F$9)*3/12)))/$F$11 -> 161.55055 | L12: =1000*(SUM(NPV($I12,'DRE + DCF'!$N$36:$U$36,SUM('DRE + DCF'!$V$36,Perpetuidade!I13*(1+L$18)/($I12-L$18))),'DRE + DCF'!$L$36)/((1+$I12)^((5-$F$9)*3/12)))/$F$11 -> 161.94726 | M12: =1000*(SUM(NPV($I12,'DRE + DCF'!$N$36:$U$36,SUM('DRE + DCF'!$V$36,Perpetuidade!J13*(1+M$18)/($I12-M$18))),'DRE + DCF'!$L$36)/((1+$I12)^((5-$F$9)*3/12)))/$F$11 -> 162.35632 | N12: =1000*(SUM(NPV($I12,'DRE + DCF'!$N$36:$U$36,SUM('DRE + DCF'!$V$36,Perpetuidade!K13*(1+N$18)/($I12-N$18))),'DRE + DCF'!$L$36)/((1+$I12)^((5-$F$9)*3/12)))/$F$11 -> 162.77887 | O12: =1000*(SUM(NPV($I12,'DRE + DCF'!$N$36:$U$36,SUM('DRE + DCF'!$V$36,Perpetuidade!L13*(1+O$18)/($I12-O$18))),'DRE + DCF'!$L$36)/((1+$I12)^((5-$F$9)*3/12)))/$F$11 -> 163.2162 | P12: =1000*(SUM(NPV($I12,'DRE + DCF'!$N$36:$U$36,SUM('DRE + DCF'!$V$36,Perpetuidade!M13*(1+P$18)/($I12-P$18))),'DRE + DCF'!$L$36)/((1+$I12)^((5-$F$9)*3/12)))/$F$11 -> 163.66977 | Q12: =1000*(SUM(NPV($I12,'DRE + DCF'!$N$36:$U$36,SUM('DRE + DCF'!$V$36,Perpetuidade!N13*(1+Q$18)/($I12-Q$18))),'DRE + DCF'!$L$36)/((1+$I12)^((5-$F$9)*3/12)))/$F$11 -> 164.14123 | ... S12: =1000*(SUM(NPV($I12,'DRE + DCF'!$N$36:$U$36,SUM('DRE + DCF'!$V$36,Perpetuidade!P13*(1+S$18)/($I12-S$18))),'DRE + DCF'!$L$36)/((1+$I12)^((5-$F$9)*3/12)))/$F$11 -> 165.14571
A13: Projeções - NIM | E13: Valor da Ação | F13: =F12*1000/F11 -> 156.54418 | I13: =AVERAGE(Ke!F16:O16) -> 0.15949346 | J13: =1000*(SUM(NPV($I13,'DRE + DCF'!$N$36:$U$36,SUM('DRE + DCF'!$V$36,Perpetuidade!G14*(1+J$18)/($I13-J$18))),'DRE + DCF'!$L$36)/((1+$I13)^((5-$F$9)*3/12)))/$F$11 -> 152.37465 | K13: =1000*(SUM(NPV($I13,'DRE + DCF'!$N$36:$U$36,SUM('DRE + DCF'!$V$36,Perpetuidade!H14*(1+K$18)/($I13-K$18))),'DRE + DCF'!$L$36)/((1+$I13)^((5-$F$9)*3/12)))/$F$11 -> 152.66603 | L13: =1000*(SUM(NPV($I13,'DRE + DCF'!$N$36:$U$36,SUM('DRE + DCF'!$V$36,Perpetuidade!I14*(1+L$18)/($I13-L$18))),'DRE + DCF'!$L$36)/((1+$I13)^((5-$F$9)*3/12)))/$F$11 -> 152.96354 | M13: =1000*(SUM(NPV($I13,'DRE + DCF'!$N$36:$U$36,SUM('DRE + DCF'!$V$36,Perpetuidade!J14*(1+M$18)/($I13-M$18))),'DRE + DCF'!$L$36)/((1+$I13)^((5-$F$9)*3/12)))/$F$11 -> 153.2677 | N13: =1000*(SUM(NPV($I13,'DRE + DCF'!$N$36:$U$36,SUM('DRE + DCF'!$V$36,Perpetuidade!K14*(1+N$18)/($I13-N$18))),'DRE + DCF'!$L$36)/((1+$I13)^((5-$F$9)*3/12)))/$F$11 -> 153.5791 | O13: =1000*(SUM(NPV($I13,'DRE + DCF'!$N$36:$U$36,SUM('DRE + DCF'!$V$36,Perpetuidade!L14*(1+O$18)/($I13-O$18))),'DRE + DCF'!$L$36)/((1+$I13)^((5-$F$9)*3/12)))/$F$11 -> 153.89838 | P13: =1000*(SUM(NPV($I13,'DRE + DCF'!$N$36:$U$36,SUM('DRE + DCF'!$V$36,Perpetuidade!M14*(1+P$18)/($I13-P$18))),'DRE + DCF'!$L$36)/((1+$I13)^((5-$F$9)*3/12)))/$F$11 -> 154.22628 | Q13: =1000*(SUM(NPV($I13,'DRE + DCF'!$N$36:$U$36,SUM('DRE + DCF'!$V$36,Perpetuidade!N14*(1+Q$18)/($I13-Q$18))),'DRE + DCF'!$L$36)/((1+$I13)^((5-$F$9)*3/12)))/$F$11 -> 154.56361 | ... S13: =1000*(SUM(NPV($I13,'DRE + DCF'!$N$36:$U$36,SUM('DRE + DCF'!$V$36,Perpetuidade!P14*(1+S$18)/($I13-S$18))),'DRE + DCF'!$L$36)/((1+$I13)^((5-$F$9)*3/12)))/$F$11 -> 155.27046
A14: Projeções Trimestrais | E14: Cotação | F14: 96.99 | I14: =I13+0.5% -> 0.16449346 | J14: =1000*(SUM(NPV($I14,'DRE + DCF'!$N$36:$U$36,SUM('DRE + DCF'!$V$36,Perpetuidade!G15*(1+J$18)/($I14-J$18))),'DRE + DCF'!$L$36)/((1+$I14)^((5-$F$9)*3/12)))/$F$11 -> 144.37998 | K14: =1000*(SUM(NPV($I14,'DRE + DCF'!$N$36:$U$36,SUM('DRE + DCF'!$V$36,Perpetuidade!H15*(1+K$18)/($I14-K$18))),'DRE + DCF'!$L$36)/((1+$I14)^((5-$F$9)*3/12)))/$F$11 -> 144.59743 | L14: =1000*(SUM(NPV($I14,'DRE + DCF'!$N$36:$U$36,SUM('DRE + DCF'!$V$36,Perpetuidade!I15*(1+L$18)/($I14-L$18))),'DRE + DCF'!$L$36)/((1+$I14)^((5-$F$9)*3/12)))/$F$11 -> 144.81737 | M14: =1000*(SUM(NPV($I14,'DRE + DCF'!$N$36:$U$36,SUM('DRE + DCF'!$V$36,Perpetuidade!J15*(1+M$18)/($I14-M$18))),'DRE + DCF'!$L$36)/((1+$I14)^((5-$F$9)*3/12)))/$F$11 -> 145.03999 | N14: =1000*(SUM(NPV($I14,'DRE + DCF'!$N$36:$U$36,SUM('DRE + DCF'!$V$36,Perpetuidade!K15*(1+N$18)/($I14-N$18))),'DRE + DCF'!$L$36)/((1+$I14)^((5-$F$9)*3/12)))/$F$11 -> 145.26552 | O14: =1000*(SUM(NPV($I14,'DRE + DCF'!$N$36:$U$36,SUM('DRE + DCF'!$V$36,Perpetuidade!L15*(1+O$18)/($I14-O$18))),'DRE + DCF'!$L$36)/((1+$I14)^((5-$F$9)*3/12)))/$F$11 -> 145.4942 | P14: =1000*(SUM(NPV($I14,'DRE + DCF'!$N$36:$U$36,SUM('DRE + DCF'!$V$36,Perpetuidade!M15*(1+P$18)/($I14-P$18))),'DRE + DCF'!$L$36)/((1+$I14)^((5-$F$9)*3/12)))/$F$11 -> 145.72631 | Q14: =1000*(SUM(NPV($I14,'DRE + DCF'!$N$36:$U$36,SUM('DRE + DCF'!$V$36,Perpetuidade!N15*(1+Q$18)/($I14-Q$18))),'DRE + DCF'!$L$36)/((1+$I14)^((5-$F$9)*3/12)))/$F$11 -> 145.96216 | ... S14: =1000*(SUM(NPV($I14,'DRE + DCF'!$N$36:$U$36,SUM('DRE + DCF'!$V$36,Perpetuidade!P15*(1+S$18)/($I14-S$18))),'DRE + DCF'!$L$36)/((1+$I14)^((5-$F$9)*3/12)))/$F$11 -> 146.4465
A15: Painel de Índices | E15: Upside | F15: =F13/F14-1 -> 0.61402396 | I15: =I14+0.5% -> 0.16949346 | J15: =1000*(SUM(NPV($I15,'DRE + DCF'!$N$36:$U$36,SUM('DRE + DCF'!$V$36,Perpetuidade!G16*(1+J$18)/($I15-J$18))),'DRE + DCF'!$L$36)/((1+$I15)^((5-$F$9)*3/12)))/$F$11 -> 137.0805 | K15: =1000*(SUM(NPV($I15,'DRE + DCF'!$N$36:$U$36,SUM('DRE + DCF'!$V$36,Perpetuidade!H16*(1+K$18)/($I15-K$18))),'DRE + DCF'!$L$36)/((1+$I15)^((5-$F$9)*3/12)))/$F$11 -> 137.23955 | L15: =1000*(SUM(NPV($I15,'DRE + DCF'!$N$36:$U$36,SUM('DRE + DCF'!$V$36,Perpetuidade!I16*(1+L$18)/($I15-L$18))),'DRE + DCF'!$L$36)/((1+$I15)^((5-$F$9)*3/12)))/$F$11 -> 137.39853 | M15: =1000*(SUM(NPV($I15,'DRE + DCF'!$N$36:$U$36,SUM('DRE + DCF'!$V$36,Perpetuidade!J16*(1+M$18)/($I15-M$18))),'DRE + DCF'!$L$36)/((1+$I15)^((5-$F$9)*3/12)))/$F$11 -> 137.55744 | N15: =1000*(SUM(NPV($I15,'DRE + DCF'!$N$36:$U$36,SUM('DRE + DCF'!$V$36,Perpetuidade!K16*(1+N$18)/($I15-N$18))),'DRE + DCF'!$L$36)/((1+$I15)^((5-$F$9)*3/12)))/$F$11 -> 137.71628 | O15: =1000*(SUM(NPV($I15,'DRE + DCF'!$N$36:$U$36,SUM('DRE + DCF'!$V$36,Perpetuidade!L16*(1+O$18)/($I15-O$18))),'DRE + DCF'!$L$36)/((1+$I15)^((5-$F$9)*3/12)))/$F$11 -> 137.87503 | P15: =1000*(SUM(NPV($I15,'DRE + DCF'!$N$36:$U$36,SUM('DRE + DCF'!$V$36,Perpetuidade!M16*(1+P$18)/($I15-P$18))),'DRE + DCF'!$L$36)/((1+$I15)^((5-$F$9)*3/12)))/$F$11 -> 138.0337 | Q15: =1000*(SUM(NPV($I15,'DRE + DCF'!$N$36:$U$36,SUM('DRE + DCF'!$V$36,Perpetuidade!N16*(1+Q$18)/($I15-Q$18))),'DRE + DCF'!$L$36)/((1+$I15)^((5-$F$9)*3/12)))/$F$11 -> 138.19227 | ... S15: =1000*(SUM(NPV($I15,'DRE + DCF'!$N$36:$U$36,SUM('DRE + DCF'!$V$36,Perpetuidade!P16*(1+S$18)/($I15-S$18))),'DRE + DCF'!$L$36)/((1+$I15)^((5-$F$9)*3/12)))/$F$11 -> 138.50909
E16: TIR | F16: =VLOOKUP(MIN(TIR!C13:C3382),TIR!C13:D3382,2,FALSE) -> 0.20785 | I16: =I15+0.5% -> 0.17449346 | J16: =1000*(SUM(NPV($I16,'DRE + DCF'!$N$36:$U$36,SUM('DRE + DCF'!$V$36,Perpetuidade!G17*(1+J$18)/($I16-J$18))),'DRE + DCF'!$L$36)/((1+$I16)^((5-$F$9)*3/12)))/$F$11 -> 130.39203 | K16: =1000*(SUM(NPV($I16,'DRE + DCF'!$N$36:$U$36,SUM('DRE + DCF'!$V$36,Perpetuidade!H17*(1+K$18)/($I16-K$18))),'DRE + DCF'!$L$36)/((1+$I16)^((5-$F$9)*3/12)))/$F$11 -> 130.50479 | L16: =1000*(SUM(NPV($I16,'DRE + DCF'!$N$36:$U$36,SUM('DRE + DCF'!$V$36,Perpetuidade!I17*(1+L$18)/($I16-L$18))),'DRE + DCF'!$L$36)/((1+$I16)^((5-$F$9)*3/12)))/$F$11 -> 130.61572 | M16: =1000*(SUM(NPV($I16,'DRE + DCF'!$N$36:$U$36,SUM('DRE + DCF'!$V$36,Perpetuidade!J17*(1+M$18)/($I16-M$18))),'DRE + DCF'!$L$36)/((1+$I16)^((5-$F$9)*3/12)))/$F$11 -> 130.72467 | N16: =1000*(SUM(NPV($I16,'DRE + DCF'!$N$36:$U$36,SUM('DRE + DCF'!$V$36,Perpetuidade!K17*(1+N$18)/($I16-N$18))),'DRE + DCF'!$L$36)/((1+$I16)^((5-$F$9)*3/12)))/$F$11 -> 130.83151 | O16: =1000*(SUM(NPV($I16,'DRE + DCF'!$N$36:$U$36,SUM('DRE + DCF'!$V$36,Perpetuidade!L17*(1+O$18)/($I16-O$18))),'DRE + DCF'!$L$36)/((1+$I16)^((5-$F$9)*3/12)))/$F$11 -> 130.93608 | P16: =1000*(SUM(NPV($I16,'DRE + DCF'!$N$36:$U$36,SUM('DRE + DCF'!$V$36,Perpetuidade!M17*(1+P$18)/($I16-P$18))),'DRE + DCF'!$L$36)/((1+$I16)^((5-$F$9)*3/12)))/$F$11 -> 131.03819 | Q16: =1000*(SUM(NPV($I16,'DRE + DCF'!$N$36:$U$36,SUM('DRE + DCF'!$V$36,Perpetuidade!N17*(1+Q$18)/($I16-Q$18))),'DRE + DCF'!$L$36)/((1+$I16)^((5-$F$9)*3/12)))/$F$11 -> 131.13765 | ... S16: =1000*(SUM(NPV($I16,'DRE + DCF'!$N$36:$U$36,SUM('DRE + DCF'!$V$36,Perpetuidade!P17*(1+S$18)/($I16-S$18))),'DRE + DCF'!$L$36)/((1+$I16)^((5-$F$9)*3/12)))/$F$11 -> 131.32773
I17: =I16+0.5% -> 0.17949346 | J17: =1000*(SUM(NPV($I17,'DRE + DCF'!$N$36:$U$36,SUM('DRE + DCF'!$V$36,Perpetuidade!G18*(1+J$18)/($I17-J$18))),'DRE + DCF'!$L$36)/((1+$I17)^((5-$F$9)*3/12)))/$F$11 -> 124.24361 | K17: =1000*(SUM(NPV($I17,'DRE + DCF'!$N$36:$U$36,SUM('DRE + DCF'!$V$36,Perpetuidade!H18*(1+K$18)/($I17-K$18))),'DRE + DCF'!$L$36)/((1+$I17)^((5-$F$9)*3/12)))/$F$11 -> 124.31959 | L17: =1000*(SUM(NPV($I17,'DRE + DCF'!$N$36:$U$36,SUM('DRE + DCF'!$V$36,Perpetuidade!I18*(1+L$18)/($I17-L$18))),'DRE + DCF'!$L$36)/((1+$I17)^((5-$F$9)*3/12)))/$F$11 -> 124.39254 | M17: =1000*(SUM(NPV($I17,'DRE + DCF'!$N$36:$U$36,SUM('DRE + DCF'!$V$36,Perpetuidade!J18*(1+M$18)/($I17-M$18))),'DRE + DCF'!$L$36)/((1+$I17)^((5-$F$9)*3/12)))/$F$11 -> 124.46223 | N17: =1000*(SUM(NPV($I17,'DRE + DCF'!$N$36:$U$36,SUM('DRE + DCF'!$V$36,Perpetuidade!K18*(1+N$18)/($I17-N$18))),'DRE + DCF'!$L$36)/((1+$I17)^((5-$F$9)*3/12)))/$F$11 -> 124.52843 | O17: =1000*(SUM(NPV($I17,'DRE + DCF'!$N$36:$U$36,SUM('DRE + DCF'!$V$36,Perpetuidade!L18*(1+O$18)/($I17-O$18))),'DRE + DCF'!$L$36)/((1+$I17)^((5-$F$9)*3/12)))/$F$11 -> 124.5909 | P17: =1000*(SUM(NPV($I17,'DRE + DCF'!$N$36:$U$36,SUM('DRE + DCF'!$V$36,Perpetuidade!M18*(1+P$18)/($I17-P$18))),'DRE + DCF'!$L$36)/((1+$I17)^((5-$F$9)*3/12)))/$F$11 -> 124.64936 | Q17: =1000*(SUM(NPV($I17,'DRE + DCF'!$N$36:$U$36,SUM('DRE + DCF'!$V$36,Perpetuidade!N18*(1+Q$18)/($I17-Q$18))),'DRE + DCF'!$L$36)/((1+$I17)^((5-$F$9)*3/12)))/$F$11 -> 124.7035 | ... S17: =1000*(SUM(NPV($I17,'DRE + DCF'!$N$36:$U$36,SUM('DRE + DCF'!$V$36,Perpetuidade!P18*(1+S$18)/($I17-S$18))),'DRE + DCF'!$L$36)/((1+$I17)^((5-$F$9)*3/12)))/$F$11 -> 124.79743
J18: =K18-0.25% -> 0.06355 | K18: =L18-0.25% -> 0.06605 | L18: =M18-0.25% -> 0.06855 | M18: =N18-0.25% -> 0.07105 | N18: ='DRE + DCF'!Y31 -> 0.07355 | O18: =N18+0.25% -> 0.07605 | P18: =O18+0.25% -> 0.07855 | Q18: =P18+0.25% -> 0.08105 | R18: =Q18+0.25% -> 0.08355 | S18: =R18+0.25% -> 0.08605
J19: Growth
E22: Preço Teto | F22: =TIR!E12 -> 145.17173

Sheet Ke
K4: =Dashboard!J4 -> Banco da Amazônia ($BAZA3)
A7: Páginas
A8: Dashboard
A9: Ke | E9: Atualizado em: 03/04/2024 | F9: =2024 -> 2024 | G9: =F9+1 -> 2025 | H9: =G9+1 -> 2026 | I9: =H9+1 -> 2027 | J9: =I9+1 -> 2028 | K9: =J9+1 -> 2029 | L9: =K9+1 -> 2030 | M9: =L9+1 -> 2031 | N9: =M9+1 -> 2032 | O9: =N9+1 -> 2033 | P9: Descrição
A10: DRE + DCF | E10: DI | F10: 0.1033 | G10: 0.10535 | H10: 0.1087 | I10: 0.1116 | J10: 0.11365 | K10: 0.115 | L10: 0.11584 | M10: 0.1163 | N10: 0.11651 | O10: 0.1166 | P10: A taxa livre de risco no Brasil pode partir do DI, que é equivalente ao prêmio de um titulo IPCA+ do governo de mesmo prazo somado à inflação implicita.
A11: DRE - Cosif | E11: CDS | F11: 0.003747246 | G11: 0.006508793 | H11: 0.009973829 | I11: 0.013900747 | J11: 0.018056148 | K11: 0.021600431 | L11: 0.024344638 | M11: 0.026174447 | N11: 0.026975536 | O11: 0.026633585 | P11: Credit Default Swap (CDS)
A12: Balanço Patrimonial | E12: Inflação Implícita | F12: 0.04052 | G12: 0.03862 | H12: 0.0437 | I12: 0.04665 | J12: 0.04879 | K12: 0.05009 | L12: 0.05168 | M12: 0.05226 | N12: 0.05233 | O12: 0.0525
A13: Projeções - NIM | E13: Taxa Livre de Risco | F13: =F10-F11 -> 0.099552754 | G13: =G10-G11 -> 0.098841207 | H13: =H10-H11 -> 0.098726171 | I13: =I10-I11 -> 0.097699253 | J13: =J10-J11 -> 0.095593852 | K13: =K10-K11 -> 0.093399569 | L13: =L10-L11 -> 0.091495362 | M13: =M10-M11 -> 0.090125553 | ... O13: =O10-O11 -> 0.089966415
A14: Projeções Trimestrais | E14: Beta | F14: 1 | G14: =F14 -> 1 | H14: =G14 -> 1 | I14: =H14 -> 1 | J14: =I14 -> 1 | K14: =J14 -> 1 | L14: =K14 -> 1 | M14: =L14 -> 1 | N14: =M14 -> 1 | O14: =N14 -> 1 | P14: Utilizamos Beta igual a 1 como forma conservadora. O Beta Clássico de BAZA3 é por volta de 0,2 e o Beta Clássico do setor é por volta de1,07.
A15: Painel de Índices | E15: Prêmio de Risco | F15: 0.065 | G15: 0.065 | H15: 0.065 | I15: 0.065 | J15: 0.065 | K15: 0.065 | L15: 0.065 | M15: 0.065 | N15: 0.065 | O15: 0.065 | P15: Dados Alternativos FGV: https://goo.gl/bBfwGq
E16: Custo de Capital Próprio (Ke) | F16: =F13+F14*F15 -> 0.16455275 | G16: =G13+G14*G15 -> 0.16384121 | H16: =H13+H14*H15 -> 0.16372617 | I16: =I13+I14*I15 -> 0.16269925 | J16: =J13+J14*J15 -> 0.16059385 | K16: =K13+K14*K15 -> 0.15839957 | L16: =L13+L14*L15 -> 0.15649536 | M16: =M13+M14*M15 -> 0.15512555 | ... O16: =O13+O14*O15 -> 0.15496641
E17: Desconto | F17: =(1+F16)^((5-Dashboard!$F$9)*3/12) -> 1.1210355 | G17: =F17*(1+G16) -> 1.3047073 | H17: =G17*(1+H16) -> 1.5183221 | I17: =H17*(1+I16) -> 1.7653519 | J17: =I17*(1+J16) -> 2.0488566 | K17: =J17*(1+K16) -> 2.3733946 | L17: =K17*(1+L16) -> 2.7448199 | M17: =L17*(1+M16) -> 3.1706116 | N17: =M17*(1+N16) -> 3.6605803 | O17: =N17*(1+O16) -> 4.2278473
E21: Data | F21: Preço BAZA3 | G21: IBOV | H21: Variação BAZA3 | I21: Variação IBOV | K21: Data | L21: Índice do setor (IFNC) | M21: IBOV | N21: Variação BAZA3 | O21: Variação IBOV
E22: 44333 | F22: 28.98008 | G22: 122938 | H22: - | I22: - | K22: 28.98008 | L22: 11770.95 | M22: 122938 | N22: - | O22: -
E23: 44334 | F23: 28.833345 | G23: 122980 | H23: =F23/F22-1 -> -0.0050633056 | I23: =G23/G22-1 -> 0.00034163562 | K23: 28.833345 | L23: 11776.55 | M23: 122980 | N23: =L23/L22-1 -> 0.0004757475 | O23: =M23/M22-1 -> 0.00034163562
E24: 44335 | F24: 29.346916 | G24: 122636 | H24: =F24/F23-1 -> 0.017811704 | I24: =G24/G23-1 -> -0.0027972028 | K24: 29.346916 | L24: 11835.54 | M24: 122636 | N24: =L24/L23-1 -> 0.0050091071 | O24: =M24/M23-1 -> -0.0027972028
E25: 44336 | F25: 29.376265 | G25: 122701 | H25: =F25/F24-1 -> 0.001000071 | I25: =G25/G24-1 -> 0.00053002381 | K25: 29.376265 | L25: 11948.15 | M25: 122701 | N25: =L25/L24-1 -> 0.0095145638 | O25: =M25/M24-1 -> 0.00053002381
E26: 44337 | F26: 29.346916 | G26: 122592 | H26: =F26/F25-1 -> -0.00099907187 | I26: =G26/G25-1 -> -0.00088833832 | K26: 29.346916 | L26: 11961.07 | M26: 122592 | N26: =L26/L25-1 -> 0.001081339 | O26: =M26/M25-1 -> -0.00088833832
E27: 44340 | F27: 29.346916 | G27: 124032 | H27: =F27/F26-1 -> 0 | I27: =G27/G26-1 -> 0.01174628 | K27: 29.346916 | L27: 12161.71 | M27: 124032 | N27: =L27/L26-1 -> 0.016774419 | O27: =M27/M26-1 -> 0.01174628
E28: 44341 | F28: 29.376265 | G28: 122988 | H28: =F28/F27-1 -> 0.001000071 | I28: =G28/G27-1 -> -0.0084171827 | K28: 29.376265 | L28: 11986.58 | M28: 122988 | N28: =L28/L27-1 -> -0.014400113 | O28: =M28/M27-1 -> -0.0084171827
E29: 44342 | F29: 29.302896 | G29: 123989 | H29: =F29/F28-1 -> -0.0024975605 | I29: =G29/G28-1 -> 0.0081390054 | K29: 29.302896 | L29: 12109.22 | M29: 123989 | N29: =L29/L28-1 -> 0.010231442 | O29: =M29/M28-1 -> 0.0081390054
E30: 44343 | F30: 29.412949 | G30: 124367 | H30: =F30/F29-1 -> 0.0037557039 | I30: =G30/G29-1 -> 0.0030486575 | K30: 29.412949 | L30: 12104.33 | M30: 124367 | N30: =L30/L29-1 -> -0.00040382452 | O30: =M30/M29-1 -> 0.0030486575
E31: 44344 | F31: 29.493652 | G31: 125561 | H31: =F31/F30-1 -> 0.0027437915 | I31: =G31/G30-1 -> 0.0096006175 | K31: 29.493652 | L31: 12227.83 | M31: 125561 | N31: =L31/L30-1 -> 0.01020296 | O31: =M31/M30-1 -> 0.0096006175
E32: 44347 | F32: 29.493652 | G32: 126216 | H32: =F32/F31-1 -> 0 | I32: =G32/G31-1 -> 0.005216588 | K32: 29.493652 | L32: 12248.19 | M32: 126216 | N32: =L32/L31-1 -> 0.0016650542 | O32: =M32/M31-1 -> 0.005216588
E33: 44348 | F33: 30.007223 | G33: 128267 | H33: =F33/F32-1 -> 0.017412933 | I33: =G33/G32-1 -> 0.016249921 | K33: 30.007223 | L33: 12466.89 | M33: 128267 | N33: =L33/L32-1 -> 0.017855699 | O33: =M33/M32-1 -> 0.016249921
E34: 44349 | F34: 30.080593 | G34: 129601 | H34: =F34/F33-1 -> 0.002445078 | I34: =G34/G33-1 -> 0.010400181 | K34: 30.080593 | L34: 12620.23 | M34: 129601 | N34: =L34/L33-1 -> 0.01229978 | O34: =M34/M33-1 -> 0.010400181
... E768: 45426 | F768: 99.949997 | G768: 128515 | H768: =F768/F767-1 -> -0.010298059 | I768: =G768/G767-1 -> 0.0028090984 | K768: 99.949997 | L768: 12815.96 | M768: 128515 | N768: =L768/L767-1 -> 0.0093325752 | O768: =M768/M767-1 -> 0.0028090984
E769: 45427 | F769: 100.4 | G769: 128028 | H769: =F769/F768-1 -> 0.0045023013 | I769: =G769/G768-1 -> -0.0037894409 | K769: 100.4 | L769: 12813.06 | M769: 128028 | N769: 0.0093325752 | O769: 0.0028090984
H770: Beta | I770: =SLOPE(H23:H769,I23:I769) -> 0.19471485 | N770: Beta | O770: =SLOPE(N23:N769,O23:O769) -> 1.0669481

Sheet Perpetuidade
I4: =Dashboard!I4 -> 0
A7: Páginas
A8: Dashboard
A9: Ke
A10: DRE + DCF | E10: Custo de Capital Próprio (Ke) | F10: =Dashboard!I9 -> 0.13949346 | G10: =AVERAGE(SUM('DRE + DCF'!$W$31,'DRE + DCF'!$W$32,-'DRE + DCF'!$W$32*('DRE + DCF'!$V$33+G$21)/'DRE + DCF'!$V$33,-'DRE + DCF'!$V$56*G$19),'DRE + DCF'!$W$31*(1-G$19/$F10)) -> 1639519.7 | H10: =AVERAGE(SUM('DRE + DCF'!$W$31,'DRE + DCF'!$W$32,-'DRE + DCF'!$W$32*('DRE + DCF'!$V$33+H$21)/'DRE + DCF'!$V$33,-'DRE + DCF'!$V$56*H$19),'DRE + DCF'!$W$31*(1-H$19/$F10)) -> 1593717.3 | I10: =AVERAGE(SUM('DRE + DCF'!$W$31,'DRE + DCF'!$W$32,-'DRE + DCF'!$W$32*('DRE + DCF'!$V$33+I$21)/'DRE + DCF'!$V$33,-'DRE + DCF'!$V$56*I$19),'DRE + DCF'!$W$31*(1-I$19/$F10)) -> 1547915 | J10: =AVERAGE(SUM('DRE + DCF'!$W$31,'DRE + DCF'!$W$32,-'DRE + DCF'!$W$32*('DRE + DCF'!$V$33+J$21)/'DRE + DCF'!$V$33,-'DRE + DCF'!$V$56*J$19),'DRE + DCF'!$W$31*(1-J$19/$F10)) -> 1502112.6 | K10: =AVERAGE(SUM('DRE + DCF'!$W$31,'DRE + DCF'!$W$32,-'DRE + DCF'!$W$32*('DRE + DCF'!$V$33+K$21)/'DRE + DCF'!$V$33,-'DRE + DCF'!$V$56*K$19),'DRE + DCF'!$W$31*(1-K$19/$F10)) -> 1456310.3 | L10: =AVERAGE(SUM('DRE + DCF'!$W$31,'DRE + DCF'!$W$32,-'DRE + DCF'!$W$32*('DRE + DCF'!$V$33+L$21)/'DRE + DCF'!$V$33,-'DRE + DCF'!$V$56*L$19),'DRE + DCF'!$W$31*(1-L$19/$F10)) -> 1410507.9 | M10: =AVERAGE(SUM('DRE + DCF'!$W$31,'DRE + DCF'!$W$32,-'DRE + DCF'!$W$32*('DRE + DCF'!$V$33+M$21)/'DRE + DCF'!$V$33,-'DRE + DCF'!$V$56*M$19),'DRE + DCF'!$W$31*(1-M$19/$F10)) -> 1364705.6 | N10: =AVERAGE(SUM('DRE + DCF'!$W$31,'DRE + DCF'!$W$32,-'DRE + DCF'!$W$32*('DRE + DCF'!$V$33+N$21)/'DRE + DCF'!$V$33,-'DRE + DCF'!$V$56*N$19),'DRE + DCF'!$W$31*(1-N$19/$F10)) -> 1318903.2 | ... P10: =AVERAGE(SUM('DRE + DCF'!$W$31,'DRE + DCF'!$W$32,-'DRE + DCF'!$W$32*('DRE + DCF'!$V$33+P$21)/'DRE + DCF'!$V$33,-'DRE + DCF'!$V$56*P$19),'DRE + DCF'!$W$31*(1-P$19/$F10)) -> 1227298.5
A11: DRE - Cosif | F11: =Dashboard!I10 -> 0.14449346 | G11: =AVERAGE(SUM('DRE + DCF'!$W$31,'DRE + DCF'!$W$32,-'DRE + DCF'!$W$32*('DRE + DCF'!$V$33+G$21)/'DRE + DCF'!$V$33,-'DRE + DCF'!$V$56*G$19),'DRE + DCF'!$W$31*(1-G$19/$F11)) -> 1661524.1 | H11: =AVERAGE(SUM('DRE + DCF'!$W$31,'DRE + DCF'!$W$32,-'DRE + DCF'!$W$32*('DRE + DCF'!$V$33+H$21)/'DRE + DCF'!$V$33,-'DRE + DCF'!$V$56*H$19),'DRE + DCF'!$W$31*(1-H$19/$F11)) -> 1616587.4 | I11: =AVERAGE(SUM('DRE + DCF'!$W$31,'DRE + DCF'!$W$32,-'DRE + DCF'!$W$32*('DRE + DCF'!$V$33+I$21)/'DRE + DCF'!$V$33,-'DRE + DCF'!$V$56*I$19),'DRE + DCF'!$W$31*(1-I$19/$F11)) -> 1571650.7 | J11: =AVERAGE(SUM('DRE + DCF'!$W$31,'DRE + DCF'!$W$32,-'DRE + DCF'!$W$32*('DRE + DCF'!$V$33+J$21)/'DRE + DCF'!$V$33,-'DRE + DCF'!$V$56*J$19),'DRE + DCF'!$W$31*(1-J$19/$F11)) -> 1526714 | K11: =AVERAGE(SUM('DRE + DCF'!$W$31,'DRE + DCF'!$W$32,-'DRE + DCF'!$W$32*('DRE + DCF'!$V$33+K$21)/'DRE + DCF'!$V$33,-'DRE + DCF'!$V$56*K$19),'DRE + DCF'!$W$31*(1-K$19/$F11)) -> 1481777.2 | L11: =AVERAGE(SUM('DRE + DCF'!$W$31,'DRE + DCF'!$W$32,-'DRE + DCF'!$W$32*('DRE + DCF'!$V$33+L$21)/'DRE + DCF'!$V$33,-'DRE + DCF'!$V$56*L$19),'DRE + DCF'!$W$31*(1-L$19/$F11)) -> 1436840.5 | M11: =AVERAGE(SUM('DRE + DCF'!$W$31,'DRE + DCF'!$W$32,-'DRE + DCF'!$W$32*('DRE + DCF'!$V$33+M$21)/'DRE + DCF'!$V$33,-'DRE + DCF'!$V$56*M$19),'DRE + DCF'!$W$31*(1-M$19/$F11)) -> 1391903.8 | N11: =AVERAGE(SUM('DRE + DCF'!$W$31,'DRE + DCF'!$W$32,-'DRE + DCF'!$W$32*('DRE + DCF'!$V$33+N$21)/'DRE + DCF'!$V$33,-'DRE + DCF'!$V$56*N$19),'DRE + DCF'!$W$31*(1-N$19/$F11)) -> 1346967.1 | ... P11: =AVERAGE(SUM('DRE + DCF'!$W$31,'DRE + DCF'!$W$32,-'DRE + DCF'!$W$32*('DRE + DCF'!$V$33+P$21)/'DRE + DCF'!$V$33,-'DRE + DCF'!$V$56*P$19),'DRE + DCF'!$W$31*(1-P$19/$F11)) -> 1257093.7
A12: Balanço Patrimonial | F12: =Dashboard!I11 -> 0.14949346 | G12: =AVERAGE(SUM('DRE + DCF'!$W$31,'DRE + DCF'!$W$32,-'DRE + DCF'!$W$32*('DRE + DCF'!$V$33+G$21)/'DRE + DCF'!$V$33,-'DRE + DCF'!$V$56*G$19),'DRE + DCF'!$W$31*(1-G$19/$F12)) -> 1682056.6 | H12: =AVERAGE(SUM('DRE + DCF'!$W$31,'DRE + DCF'!$W$32,-'DRE + DCF'!$W$32*('DRE + DCF'!$V$33+H$21)/'DRE + DCF'!$V$33,-'DRE + DCF'!$V$56*H$19),'DRE + DCF'!$W$31*(1-H$19/$F12)) -> 1637927.6 | I12: =AVERAGE(SUM('DRE + DCF'!$W$31,'DRE + DCF'!$W$32,-'DRE + DCF'!$W$32*('DRE + DCF'!$V$33+I$21)/'DRE + DCF'!$V$33,-'DRE + DCF'!$V$56*I$19),'DRE + DCF'!$W$31*(1-I$19/$F12)) -> 1593798.6 | J12: =AVERAGE(SUM('DRE + DCF'!$W$31,'DRE + DCF'!$W$32,-'DRE + DCF'!$W$32*('DRE + DCF'!$V$33+J$21)/'DRE + DCF'!$V$33,-'DRE + DCF'!$V$56*J$19),'DRE + DCF'!$W$31*(1-J$19/$F12)) -> 1549669.7 | K12: =AVERAGE(SUM('DRE + DCF'!$W$31,'DRE + DCF'!$W$32,-'DRE + DCF'!$W$32*('DRE + DCF'!$V$33+K$21)/'DRE + DCF'!$V$33,-'DRE + DCF'!$V$56*K$19),'DRE + DCF'!$W$31*(1-K$19/$F12)) -> 1505540.7 | L12: =AVERAGE(SUM('DRE + DCF'!$W$31,'DRE + DCF'!$W$32,-'DRE + DCF'!$W$32*('DRE + DCF'!$V$33+L$21)/'DRE + DCF'!$V$33,-'DRE + DCF'!$V$56*L$19),'DRE + DCF'!$W$31*(1-L$19/$F12)) -> 1461411.7 | M12: =AVERAGE(SUM('DRE + DCF'!$W$31,'DRE + DCF'!$W$32,-'DRE + DCF'!$W$32*('DRE + DCF'!$V$33+M$21)/'DRE + DCF'!$V$33,-'DRE + DCF'!$V$56*M$19),'DRE + DCF'!$W$31*(1-M$19/$F12)) -> 1417282.7 | N12: =AVERAGE(SUM('DRE + DCF'!$W$31,'DRE + DCF'!$W$32,-'DRE + DCF'!$W$32*('DRE + DCF'!$V$33+N$21)/'DRE + DCF'!$V$33,-'DRE + DCF'!$V$56*N$19),'DRE + DCF'!$W$31*(1-N$19/$F12)) -> 1373153.7 | ... P12: =AVERAGE(SUM('DRE + DCF'!$W$31,'DRE + DCF'!$W$32,-'DRE + DCF'!$W$32*('DRE + DCF'!$V$33+P$21)/'DRE + DCF'!$V$33,-'DRE + DCF'!$V$56*P$19),'DRE + DCF'!$W$31*(1-P$19/$F12)) -> 1284895.7
A13: Projeções - NIM | F13: =Dashboard!I12 -> 0.15449346 | G13: =AVERAGE(SUM('DRE + DCF'!$W$31,'DRE + DCF'!$W$32,-'DRE + DCF'!$W$32*('DRE + DCF'!$V$33+G$21)/'DRE + DCF'!$V$33,-'DRE + DCF'!$V$56*G$19),'DRE + DCF'!$W$31*(1-G$19/$F13)) -> 1701260.1 | H13: =AVERAGE(SUM('DRE + DCF'!$W$31,'DRE + DCF'!$W$32,-'DRE + DCF'!$W$32*('DRE + DCF'!$V$33+H$21)/'DRE + DCF'!$V$33,-'DRE + DCF'!$V$56*H$19),'DRE + DCF'!$W$31*(1-H$19/$F13)) -> 1657886.6 | I13: =AVERAGE(SUM('DRE + DCF'!$W$31,'DRE + DCF'!$W$32,-'DRE + DCF'!$W$32*('DRE + DCF'!$V$33+I$21)/'DRE + DCF'!$V$33,-'DRE + DCF'!$V$56*I$19),'DRE + DCF'!$W$31*(1-I$19/$F13)) -> 1614513 | J13: =AVERAGE(SUM('DRE + DCF'!$W$31,'DRE + DCF'!$W$32,-'DRE + DCF'!$W$32*('DRE + DCF'!$V$33+J$21)/'DRE + DCF'!$V$33,-'DRE + DCF'!$V$56*J$19),'DRE + DCF'!$W$31*(1-J$19/$F13)) -> 1571139.5 | K13: =AVERAGE(SUM('DRE + DCF'!$W$31,'DRE + DCF'!$W$32,-'DRE + DCF'!$W$32*('DRE + DCF'!$V$33+K$21)/'DRE + DCF'!$V$33,-'DRE + DCF'!$V$56*K$19),'DRE + DCF'!$W$31*(1-K$19/$F13)) -> 1527765.9 | L13: =AVERAGE(SUM('DRE + DCF'!$W$31,'DRE + DCF'!$W$32,-'DRE + DCF'!$W$32*('DRE + DCF'!$V$33+L$21)/'DRE + DCF'!$V$33,-'DRE + DCF'!$V$56*L$19),'DRE + DCF'!$W$31*(1-L$19/$F13)) -> 1484392.4 | M13: =AVERAGE(SUM('DRE + DCF'!$W$31,'DRE + DCF'!$W$32,-'DRE + DCF'!$W$32*('DRE + DCF'!$V$33+M$21)/'DRE + DCF'!$V$33,-'DRE + DCF'!$V$56*M$19),'DRE + DCF'!$W$31*(1-M$19/$F13)) -> 1441018.9 | N13: =AVERAGE(SUM('DRE + DCF'!$W$31,'DRE + DCF'!$W$32,-'DRE + DCF'!$W$32*('DRE + DCF'!$V$33+N$21)/'DRE + DCF'!$V$33,-'DRE + DCF'!$V$56*N$19),'DRE + DCF'!$W$31*(1-N$19/$F13)) -> 1397645.3 | ... P13: =AVERAGE(SUM('DRE + DCF'!$W$31,'DRE + DCF'!$W$32,-'DRE + DCF'!$W$32*('DRE + DCF'!$V$33+P$21)/'DRE + DCF'!$V$33,-'DRE + DCF'!$V$56*P$19),'DRE + DCF'!$W$31*(1-P$19/$F13)) -> 1310898.3
A14: Projeções Trimestrais | F14: =Dashboard!I13 -> 0.15949346 | G14: =AVERAGE(SUM('DRE + DCF'!$W$31,'DRE + DCF'!$W$32,-'DRE + DCF'!$W$32*('DRE + DCF'!$V$33+G$21)/'DRE + DCF'!$V$33,-'DRE + DCF'!$V$56*G$19),'DRE + DCF'!$W$31*(1-G$19/$F14)) -> 1719259.6 | H14: =AVERAGE(SUM('DRE + DCF'!$W$31,'DRE + DCF'!$W$32,-'DRE + DCF'!$W$32*('DRE + DCF'!$V$33+H$21)/'DRE + DCF'!$V$33,-'DRE + DCF'!$V$56*H$19),'DRE + DCF'!$W$31*(1-H$19/$F14)) -> 1676594.1 | I14: =AVERAGE(SUM('DRE + DCF'!$W$31,'DRE + DCF'!$W$32,-'DRE + DCF'!$W$32*('DRE + DCF'!$V$33+I$21)/'DRE + DCF'!$V$33,-'DRE + DCF'!$V$56*I$19),'DRE + DCF'!$W$31*(1-I$19/$F14)) -> 1633928.6 | J14: =AVERAGE(SUM('DRE + DCF'!$W$31,'DRE + DCF'!$W$32,-'DRE + DCF'!$W$32*('DRE + DCF'!$V$33+J$21)/'DRE + DCF'!$V$33,-'DRE + DCF'!$V$56*J$19),'DRE + DCF'!$W$31*(1-J$19/$F14)) -> 1591263.2 | K14: =AVERAGE(SUM('DRE + DCF'!$W$31,'DRE + DCF'!$W$32,-'DRE + DCF'!$W$32*('DRE + DCF'!$V$33+K$21)/'DRE + DCF'!$V$33,-'DRE + DCF'!$V$56*K$19),'DRE + DCF'!$W$31*(1-K$19/$F14)) -> 1548597.7 | L14: =AVERAGE(SUM('DRE + DCF'!$W$31,'DRE + DCF'!$W$32,-'DRE + DCF'!$W$32*('DRE + DCF'!$V$33+L$21)/'DRE + DCF'!$V$33,-'DRE + DCF'!$V$56*L$19),'DRE + DCF'!$W$31*(1-L$19/$F14)) -> 1505932.3 | M14: =AVERAGE(SUM('DRE + DCF'!$W$31,'DRE + DCF'!$W$32,-'DRE + DCF'!$W$32*('DRE + DCF'!$V$33+M$21)/'DRE + DCF'!$V$33,-'DRE + DCF'!$V$56*M$19),'DRE + DCF'!$W$31*(1-M$19/$F14)) -> 1463266.8 | N14: =AVERAGE(SUM('DRE + DCF'!$W$31,'DRE + DCF'!$W$32,-'DRE + DCF'!$W$32*('DRE + DCF'!$V$33+N$21)/'DRE + DCF'!$V$33,-'DRE + DCF'!$V$56*N$19),'DRE + DCF'!$W$31*(1-N$19/$F14)) -> 1420601.4 | ... P14: =AVERAGE(SUM('DRE + DCF'!$W$31,'DRE + DCF'!$W$32,-'DRE + DCF'!$W$32*('DRE + DCF'!$V$33+P$21)/'DRE + DCF'!$V$33,-'DRE + DCF'!$V$56*P$19),'DRE + DCF'!$W$31*(1-P$19/$F14)) -> 1335270.5
A15: Painel de Índices | F15: =Dashboard!I14 -> 0.16449346 | G15: =AVERAGE(SUM('DRE + DCF'!$W$31,'DRE + DCF'!$W$32,-'DRE + DCF'!$W$32*('DRE + DCF'!$V$33+G$21)/'DRE + DCF'!$V$33,-'DRE + DCF'!$V$56*G$19),'DRE + DCF'!$W$31*(1-G$19/$F15)) -> 1736164.8 | H15: =AVERAGE(SUM('DRE + DCF'!$W$31,'DRE + DCF'!$W$32,-'DRE + DCF'!$W$32*('DRE + DCF'!$V$33+H$21)/'DRE + DCF'!$V$33,-'DRE + DCF'!$V$56*H$19),'DRE + DCF'!$W$31*(1-H$19/$F15)) -> 1694164.4 | I15: =AVERAGE(SUM('DRE + DCF'!$W$31,'DRE + DCF'!$W$32,-'DRE + DCF'!$W$32*('DRE + DCF'!$V$33+I$21)/'DRE + DCF'!$V$33,-'DRE + DCF'!$V$56*I$19),'DRE + DCF'!$W$31*(1-I$19/$F15)) -> 1652163.9 | J15: =AVERAGE(SUM('DRE + DCF'!$W$31,'DRE + DCF'!$W$32,-'DRE + DCF'!$W$32*('DRE + DCF'!$V$33+J$21)/'DRE + DCF'!$V$33,-'DRE + DCF'!$V$56*J$19),'DRE + DCF'!$W$31*(1-J$19/$F15)) -> 1610163.5 | K15: =AVERAGE(SUM('DRE + DCF'!$W$31,'DRE + DCF'!$W$32,-'DRE + DCF'!$W$32*('DRE + DCF'!$V$33+K$21)/'DRE + DCF'!$V$33,-'DRE + DCF'!$V$56*K$19),'DRE + DCF'!$W$31*(1-K$19/$F15)) -> 1568163.1 | L15: =AVERAGE(SUM('DRE + DCF'!$W$31,'DRE + DCF'!$W$32,-'DRE + DCF'!$W$32*('DRE + DCF'!$V$33+L$21)/'DRE + DCF'!$V$33,-'DRE + DCF'!$V$56*L$19),'DRE + DCF'!$W$31*(1-L$19/$F15)) -> 1526162.7 | M15: =AVERAGE(SUM('DRE + DCF'!$W$31,'DRE + DCF'!$W$32,-'DRE + DCF'!$W$32*('DRE + DCF'!$V$33+M$21)/'DRE + DCF'!$V$33,-'DRE + DCF'!$V$56*M$19),'DRE + DCF'!$W$31*(1-M$19/$F15)) -> 1484162.3 | N15: =AVERAGE(SUM('DRE + DCF'!$W$31,'DRE + DCF'!$W$32,-'DRE + DCF'!$W$32*('DRE + DCF'!$V$33+N$21)/'DRE + DCF'!$V$33,-'DRE + DCF'!$V$56*N$19),'DRE + DCF'!$W$31*(1-N$19/$F15)) -> 1442161.8 | ... P15: =AVERAGE(SUM('DRE + DCF'!$W$31,'DRE + DCF'!$W$32,-'DRE + DCF'!$W$32*('DRE + DCF'!$V$33+P$21)/'DRE + DCF'!$V$33,-'DRE + DCF'!$V$56*P$19),'DRE + DCF'!$W$31*(1-P$19/$F15)) -> 1358161
F16: =Dashboard!I15 -> 0.16949346 | G16: =AVERAGE(SUM('DRE + DCF'!$W$31,'DRE + DCF'!$W$32,-'DRE + DCF'!$W$32*('DRE + DCF'!$V$33+G$21)/'DRE + DCF'!$V$33,-'DRE + DCF'!$V$56*G$19),'DRE + DCF'!$W$31*(1-G$19/$F16)) -> 1752072.6 | H16: =AVERAGE(SUM('DRE + DCF'!$W$31,'DRE + DCF'!$W$32,-'DRE + DCF'!$W$32*('DRE + DCF'!$V$33+H$21)/'DRE + DCF'!$V$33,-'DRE + DCF'!$V$56*H$19),'DRE + DCF'!$W$31*(1-H$19/$F16)) -> 1710698 | I16: =AVERAGE(SUM('DRE + DCF'!$W$31,'DRE + DCF'!$W$32,-'DRE + DCF'!$W$32*('DRE + DCF'!$V$33+I$21)/'DRE + DCF'!$V$33,-'DRE + DCF'!$V$56*I$19),'DRE + DCF'!$W$31*(1-I$19/$F16)) -> 1669323.4 | J16: =AVERAGE(SUM('DRE + DCF'!$W$31,'DRE + DCF'!$W$32,-'DRE + DCF'!$W$32*('DRE + DCF'!$V$33+J$21)/'DRE + DCF'!$V$33,-'DRE + DCF'!$V$56*J$19),'DRE + DCF'!$W$31*(1-J$19/$F16)) -> 1627948.7 | K16: =AVERAGE(SUM('DRE + DCF'!$W$31,'DRE + DCF'!$W$32,-'DRE + DCF'!$W$32*('DRE + DCF'!$V$33+K$21)/'DRE + DCF'!$V$33,-'DRE + DCF'!$V$56*K$19),'DRE + DCF'!$W$31*(1-K$19/$F16)) -> 1586574.1 | L16: =AVERAGE(SUM('DRE + DCF'!$W$31,'DRE + DCF'!$W$32,-'DRE + DCF'!$W$32*('DRE + DCF'!$V$33+L$21)/'DRE + DCF'!$V$33,-'DRE + DCF'!$V$56*L$19),'DRE + DCF'!$W$31*(1-L$19/$F16)) -> 1545199.5 | M16: =AVERAGE(SUM('DRE + DCF'!$W$31,'DRE + DCF'!$W$32,-'DRE + DCF'!$W$32*('DRE + DCF'!$V$33+M$21)/'DRE + DCF'!$V$33,-'DRE + DCF'!$V$56*M$19),'DRE + DCF'!$W$31*(1-M$19/$F16)) -> 1503824.9 | N16: =AVERAGE(SUM('DRE + DCF'!$W$31,'DRE + DCF'!$W$32,-'DRE + DCF'!$W$32*('DRE + DCF'!$V$33+N$21)/'DRE + DCF'!$V$33,-'DRE + DCF'!$V$56*N$19),'DRE + DCF'!$W$31*(1-N$19/$F16)) -> 1462450.3 | ... P16: =AVERAGE(SUM('DRE + DCF'!$W$31,'DRE + DCF'!$W$32,-'DRE + DCF'!$W$32*('DRE + DCF'!$V$33+P$21)/'DRE + DCF'!$V$33,-'DRE + DCF'!$V$56*P$19),'DRE + DCF'!$W$31*(1-P$19/$F16)) -> 1379701
F17: =Dashboard!I16 -> 0.17449346 | G17: =AVERAGE(SUM('DRE + DCF'!$W$31,'DRE + DCF'!$W$32,-'DRE + DCF'!$W$32*('DRE + DCF'!$V$33+G$21)/'DRE + DCF'!$V$33,-'DRE + DCF'!$V$56*G$19),'DRE + DCF'!$W$31*(1-G$19/$F17)) -> 1767068.8 | H17: =AVERAGE(SUM('DRE + DCF'!$W$31,'DRE + DCF'!$W$32,-'DRE + DCF'!$W$32*('DRE + DCF'!$V$33+H$21)/'DRE + DCF'!$V$33,-'DRE + DCF'!$V$56*H$19),'DRE + DCF'!$W$31*(1-H$19/$F17)) -> 1726284.1 | I17: =AVERAGE(SUM('DRE + DCF'!$W$31,'DRE + DCF'!$W$32,-'DRE + DCF'!$W$32*('DRE + DCF'!$V$33+I$21)/'DRE + DCF'!$V$33,-'DRE + DCF'!$V$56*I$19),'DRE + DCF'!$W$31*(1-I$19/$F17)) -> 1685499.4 | J17: =AVERAGE(SUM('DRE + DCF'!$W$31,'DRE + DCF'!$W$32,-'DRE + DCF'!$W$32*('DRE + DCF'!$V$33+J$21)/'DRE + DCF'!$V$33,-'DRE + DCF'!$V$56*J$19),'DRE + DCF'!$W$31*(1-J$19/$F17)) -> 1644714.7 | K17: =AVERAGE(SUM('DRE + DCF'!$W$31,'DRE + DCF'!$W$32,-'DRE + DCF'!$W$32*('DRE + DCF'!$V$33+K$21)/'DRE + DCF'!$V$33,-'DRE + DCF'!$V$56*K$19),'DRE + DCF'!$W$31*(1-K$19/$F17)) -> 1603930 | L17: =AVERAGE(SUM('DRE + DCF'!$W$31,'DRE + DCF'!$W$32,-'DRE + DCF'!$W$32*('DRE + DCF'!$V$33+L$21)/'DRE + DCF'!$V$33,-'DRE + DCF'!$V$56*L$19),'DRE + DCF'!$W$31*(1-L$19/$F17)) -> 1563145.3 | M17: =AVERAGE(SUM('DRE + DCF'!$W$31,'DRE + DCF'!$W$32,-'DRE + DCF'!$W$32*('DRE + DCF'!$V$33+M$21)/'DRE + DCF'!$V$33,-'DRE + DCF'!$V$56*M$19),'DRE + DCF'!$W$31*(1-M$19/$F17)) -> 1522360.7 | N17: =AVERAGE(SUM('DRE + DCF'!$W$31,'DRE + DCF'!$W$32,-'DRE + DCF'!$W$32*('DRE + DCF'!$V$33+N$21)/'DRE + DCF'!$V$33,-'DRE + DCF'!$V$56*N$19),'DRE + DCF'!$W$31*(1-N$19/$F17)) -> 1481576 | ... P17: =AVERAGE(SUM('DRE + DCF'!$W$31,'DRE + DCF'!$W$32,-'DRE + DCF'!$W$32*('DRE + DCF'!$V$33+P$21)/'DRE + DCF'!$V$33,-'DRE + DCF'!$V$56*P$19),'DRE + DCF'!$W$31*(1-P$19/$F17)) -> 1400006.6
F18: =Dashboard!I17 -> 0.17949346 | G18: =AVERAGE(SUM('DRE + DCF'!$W$31,'DRE + DCF'!$W$32,-'DRE + DCF'!$W$32*('DRE + DCF'!$V$33+G$21)/'DRE + DCF'!$V$33,-'DRE + DCF'!$V$56*G$19),'DRE + DCF'!$W$31*(1-G$19/$F18)) -> 1781229.5 | H18: =AVERAGE(SUM('DRE + DCF'!$W$31,'DRE + DCF'!$W$32,-'DRE + DCF'!$W$32*('DRE + DCF'!$V$33+H$21)/'DRE + DCF'!$V$33,-'DRE + DCF'!$V$56*H$19),'DRE + DCF'!$W$31*(1-H$19/$F18)) -> 1741001.8 | I18: =AVERAGE(SUM('DRE + DCF'!$W$31,'DRE + DCF'!$W$32,-'DRE + DCF'!$W$32*('DRE + DCF'!$V$33+I$21)/'DRE + DCF'!$V$33,-'DRE + DCF'!$V$56*I$19),'DRE + DCF'!$W$31*(1-I$19/$F18)) -> 1700774.2 | J18: =AVERAGE(SUM('DRE + DCF'!$W$31,'DRE + DCF'!$W$32,-'DRE + DCF'!$W$32*('DRE + DCF'!$V$33+J$21)/'DRE + DCF'!$V$33,-'DRE + DCF'!$V$56*J$19),'DRE + DCF'!$W$31*(1-J$19/$F18)) -> 1660546.6 | K18: =AVERAGE(SUM('DRE + DCF'!$W$31,'DRE + DCF'!$W$32,-'DRE + DCF'!$W$32*('DRE + DCF'!$V$33+K$21)/'DRE + DCF'!$V$33,-'DRE + DCF'!$V$56*K$19),'DRE + DCF'!$W$31*(1-K$19/$F18)) -> 1620319 | L18: =AVERAGE(SUM('DRE + DCF'!$W$31,'DRE + DCF'!$W$32,-'DRE + DCF'!$W$32*('DRE + DCF'!$V$33+L$21)/'DRE + DCF'!$V$33,-'DRE + DCF'!$V$56*L$19),'DRE + DCF'!$W$31*(1-L$19/$F18)) -> 1580091.4 | M18: =AVERAGE(SUM('DRE + DCF'!$W$31,'DRE + DCF'!$W$32,-'DRE + DCF'!$W$32*('DRE + DCF'!$V$33+M$21)/'DRE + DCF'!$V$33,-'DRE + DCF'!$V$56*M$19),'DRE + DCF'!$W$31*(1-M$19/$F18)) -> 1539863.8 | N18: =AVERAGE(SUM('DRE + DCF'!$W$31,'DRE + DCF'!$W$32,-'DRE + DCF'!$W$32*('DRE + DCF'!$V$33+N$21)/'DRE + DCF'!$V$33,-'DRE + DCF'!$V$56*N$19),'DRE + DCF'!$W$31*(1-N$19/$F18)) -> 1499636.2 | ... P18: =AVERAGE(SUM('DRE + DCF'!$W$31,'DRE + DCF'!$W$32,-'DRE + DCF'!$W$32*('DRE + DCF'!$V$33+P$21)/'DRE + DCF'!$V$33,-'DRE + DCF'!$V$56*P$19),'DRE + DCF'!$W$31*(1-P$19/$F18)) -> 1419180.9
G19: =Dashboard!J18 -> 0.06355 | H19: =Dashboard!K18 -> 0.06605 | I19: =Dashboard!L18 -> 0.06855 | J19: =Dashboard!M18 -> 0.07105 | K19: =Dashboard!N18 -> 0.07355 | L19: =Dashboard!O18 -> 0.07605 | M19: =Dashboard!P18 -> 0.07855 | N19: =Dashboard!Q18 -> 0.08105 | ... P19: =Dashboard!S18 -> 0.08605
G20: Growth
F21: Crescimento Real | G21: =(1+G19)/(1+Ke!$O$12)-1 -> 0.010498812 | H21: =(1+H19)/(1+Ke!$O$12)-1 -> 0.012874109 | I21: =(1+I19)/(1+Ke!$O$12)-1 -> 0.015249406 | J21: =(1+J19)/(1+Ke!$O$12)-1 -> 0.017624703 | K21: =(1+K19)/(1+Ke!$O$12)-1 -> 0.02 | L21: =(1+L19)/(1+Ke!$O$12)-1 -> 0.022375297 | M21: =(1+M19)/(1+Ke!$O$12)-1 -> 0.024750594 | N21: =(1+N19)/(1+Ke!$O$12)-1 -> 0.027125891 | ... P21: =(1+P19)/(1+Ke!$O$12)-1 -> 0.031876485

Sheet TIR
I4: =Dashboard!I4 -> 0
A7: Páginas
A8: Dashboard
A9: Ke
A10: DRE + DCF | C10: Delta | D10: TIR | E10: Preço Justo | F10: Valor da Perpetuidade | G10: Lucro Líquido | H10: Depreciação e Amortização | I10: CAPEX | J10: Capital Regulatório | K10: g real | L10: Growth
A11: DRE - Cosif | M11: 2024 | N11: 2025 | O11: 2026 | P11: 2027 | Q11: 2028 | R11: 2029 | S11: 2030 | T11: 2031 | U11: 2032 | V11: 2033
A12: Balanço Patrimonial | C12: Preço Teto | D12: =MAX(Ke!$F$16:$O$16) -> 0.16455275 | E12: {=1000*SUM('DRE + DCF'!$L$36/M12,'DRE + DCF'!$N$36:$V$36/N12:V12,F12/V12)/Dashboard!$F$11} -> 145.17173 | F12: =AVERAGE(SUM(G12:J12)*(1+L12)/(D12-L12),G12*(1+L12)*(1-L12/D12)/(D12-L12)) -> 18502110 | G12: ='DRE + DCF'!$W$31 -> 2791623.4 | H12: ='DRE + DCF'!$W$32 -> 81081.932 | I12: =-H12*('DRE + DCF'!$V$33+K12)/'DRE + DCF'!$V$33 -> -90858.802 | J12: =-'DRE + DCF'!$V$56*L12 -> -1188924.4 | K12: =(1+L12)/(1+Ke!$O$12)-1 -> 0.02 | L12: ='DRE + DCF'!$Y$31 -> 0.07355 | M12: =(1+D12)^((5-Dashboard!$F$9)*3/12) -> 1.1210355 | N12: =M12*(1+$D12) -> 1.305505 | O12: =N12*(1+$D12) -> 1.5203295 | P12: =O12*(1+$D12) -> 1.7705038 | Q12: =P12*(1+$D12) -> 2.0618451 | R12: =Q12*(1+$D12) -> 2.4011274 | S12: =R12*(1+$D12) -> 2.7962396 | T12: =S12*(1+$D12) -> 3.2563685 | U12: =T12*(1+$D12) -> 3.7922129 | V12: =U12*(1+$D12) -> 4.416232
A13: Projeções - NIM | C13: =ABS(E13-Dashboard!$F$14) -> 15394.386 | D13: ='DRE + DCF'!Y31+0.0005 -> 0.07405 | E13: {=1000*SUM('DRE + DCF'!$L$36/M13,'DRE + DCF'!$N$36:$V$36/N13:V13,F13/V13)/Dashboard!$F$11} -> 15491.376 | F13: =AVERAGE(SUM(G13:J13)*(1+L13)/(D13-L13),G13*(1+L13)*(1-L13/D13)/(D13-L13)) -> 1.7303174e+09 | G13: ='DRE + DCF'!$W$31 -> 2791623.4 | H13: ='DRE + DCF'!$W$32 -> 81081.932 | I13: =-H13*('DRE + DCF'!$V$33+K13)/'DRE + DCF'!$V$33 -> -90858.802 | J13: =-'DRE + DCF'!$V$56*L13 -> -1188924.4 | K13: =(1+L13)/(1+Ke!$O$12)-1 -> 0.02 | L13: ='DRE + DCF'!$Y$31 -> 0.07355 | M13: =(1+D13)^((5-Dashboard!$F$9)*3/12) -> 1.0550387 | N13: =M13*(1+$D13) -> 1.1331643 | O13: =N13*(1+$D13) -> 1.2170751 | P13: =O13*(1+$D13) -> 1.3071995 | Q13: =P13*(1+$D13) -> 1.4039976 | R13: =Q13*(1+$D13) -> 1.5079636 | S13: =R13*(1+$D13) -> 1.6196284 | T13: =S13*(1+$D13) -> 1.7395618 | U13: =T13*(1+$D13) -> 1.8683764 | V13: =U13*(1+$D13) -> 2.0067297
A14: Projeções Trimestrais | C14: =ABS(E14-Dashboard!$F$14) -> 12848.836 | D14: =D13+0.0001 -> 0.07415 | E14: {=1000*SUM('DRE + DCF'!$L$36/M14,'DRE + DCF'!$N$36:$V$36/N14:V14,F14/V14)/Dashboard!$F$11} -> 12945.826 | F14: =AVERAGE(SUM(G14:J14)*(1+L14)/(D14-L14),G14*(1+L14)*(1-L14/D14)/(D14-L14)) -> 1.4452766e+09 | G14: ='DRE + DCF'!$W$31 -> 2791623.4 | H14: ='DRE + DCF'!$W$32 -> 81081.932 | I14: =-H14*('DRE + DCF'!$V$33+K14)/'DRE + DCF'!$V$33 -> -90858.802 | J14: =-'DRE + DCF'!$V$56*L14 -> -1188924.4 | K14: =(1+L14)/(1+Ke!$O$12)-1 -> 0.02 | L14: ='DRE + DCF'!$Y$31 -> 0.07355 | M14: =(1+D14)^((5-Dashboard!$F$9)*3/12) -> 1.0551123 | N14: =M14*(1+$D14) -> 1.1333489 | O14: =N14*(1+$D14) -> 1.2173867 | P14: =O14*(1+$D14) -> 1.307656 | Q14: =P14*(1+$D14) -> 1.4046187 | R14: =Q14*(1+$D14) -> 1.5087711 | S14: =R14*(1+$D14) -> 1.6206465 | T14: =S14*(1+$D14) -> 1.7408174 | U14: =T14*(1+$D14) -> 1.8698991 | V14: =U14*(1+$D14) -> 2.0085521
A15: Painel de Índices | C15: =ABS(E15-Dashboard!$F$14) -> 11030.463 | D15: =D14+0.0001 -> 0.07425 | E15: {=1000*SUM('DRE + DCF'!$L$36/M15,'DRE + DCF'!$N$36:$V$36/N15:V15,F15/V15)/Dashboard!$F$11} -> 11127.453 | F15: =AVERAGE(SUM(G15:J15)*(1+L15)/(D15-L15),G15*(1+L15)*(1-L15/D15)/(D15-L15)) -> 1.2416682e+09 | G15: ='DRE + DCF'!$W$31 -> 2791623.4 | H15: ='DRE + DCF'!$W$32 -> 81081.932 | I15: =-H15*('DRE + DCF'!$V$33+K15)/'DRE + DCF'!$V$33 -> -90858.802 | J15: =-'DRE + DCF'!$V$56*L15 -> -1188924.4 | K15: =(1+L15)/(1+Ke!$O$12)-1 -> 0.02 | L15: ='DRE + DCF'!$Y$31 -> 0.07355 | M15: =(1+D15)^((5-Dashboard!$F$9)*3/12) -> 1.055186 | N15: =M15*(1+$D15) -> 1.1335336 | O15: =N15*(1+$D15) -> 1.2176984 | P15: =O15*(1+$D15) -> 1.3081125 | Q15: =P15*(1+$D15) -> 1.4052399 | R15: =Q15*(1+$D15) -> 1.509579 | S15: =R15*(1+$D15) -> 1.6216652 | T15: =S15*(1+$D15) -> 1.7420738 | U15: =T15*(1+$D15) -> 1.8714228 | V15: =U15*(1+$D15) -> 2.010376
C16: =ABS(E16-Dashboard!$F$14) -> 9666.5782 | D16: =D15+0.0001 -> 0.07435 | E16: {=1000*SUM('DRE + DCF'!$L$36/M16,'DRE + DCF'!$N$36:$V$36/N16:V16,F16/V16)/Dashboard!$F$11} -> 9763.5682 | F16: =AVERAGE(SUM(G16:J16)*(1+L16)/(D16-L16),G16*(1+L16)*(1-L16/D16)/(D16-L16)) -> 1.0889552e+09 | G16: ='DRE + DCF'!$W$31 -> 2791623.4 | H16: ='DRE + DCF'!$W$32 -> 81081.932 | I16: =-H16*('DRE + DCF'!$V$33+K16)/'DRE + DCF'!$V$33 -> -90858.802 | J16: =-'DRE + DCF'!$V$56*L16 -> -1188924.4 | K16: =(1+L16)/(1+Ke!$O$12)-1 -> 0.02 | L16: ='DRE + DCF'!$Y$31 -> 0.07355 | M16: =(1+D16)^((5-Dashboard!$F$9)*3/12) -> 1.0552597 | N16: =M16*(1+$D16) -> 1.1337182 | O16: =N16*(1+$D16) -> 1.2180102 | P16: =O16*(1+$D16) -> 1.3085692 | Q16: =P16*(1+$D16) -> 1.4058614 | R16: =Q16*(1+$D16) -> 1.5103871 | S16: =R16*(1+$D16) -> 1.6226844 | T16: =S16*(1+$D16) -> 1.743331 | U16: =T16*(1+$D16) -> 1.8729477 | V16: =U16*(1+$D16) -> 2.0122013
C17: =ABS(E17-Dashboard!$F$14) -> 8605.6848 | D17: =D16+0.0001 -> 0.07445 | E17: {=1000*SUM('DRE + DCF'!$L$36/M17,'DRE + DCF'!$N$36:$V$36/N17:V17,F17/V17)/Dashboard!$F$11} -> 8702.6748 | F17: =AVERAGE(SUM(G17:J17)*(1+L17)/(D17-L17),G17*(1+L17)*(1-L17/D17)/(D17-L17)) -> 9.7017251e+08 | G17: ='DRE + DCF'!$W$31 -> 2791623.4 | H17: ='DRE + DCF'!$W$32 -> 81081.932 | I17: =-H17*('DRE + DCF'!$V$33+K17)/'DRE + DCF'!$V$33 -> -90858.802 | J17: =-'DRE + DCF'!$V$56*L17 -> -1188924.4 | K17: =(1+L17)/(1+Ke!$O$12)-1 -> 0.02 | L17: ='DRE + DCF'!$Y$31 -> 0.07355 | M17: =(1+D17)^((5-Dashboard!$F$9)*3/12) -> 1.0553333 | N17: =M17*(1+$D17) -> 1.1339029 | O17: =N17*(1+$D17) -> 1.218322 | P17: =O17*(1+$D17) -> 1.309026 | Q17: =P17*(1+$D17) -> 1.406483 | R17: =Q17*(1+$D17) -> 1.5111957 | S17: =R17*(1+$D17) -> 1.6237042 | T17: =S17*(1+$D17) -> 1.744589 | U17: =T17*(1+$D17) -> 1.8744736 | V17: =U17*(1+$D17) -> 2.0140282
C18: =ABS(E18-Dashboard!$F$14) -> 7756.886 | D18: =D17+0.0001 -> 0.07455 | E18: {=1000*SUM('DRE + DCF'!$L$36/M18,'DRE + DCF'!$N$36:$V$36/N18:V18,F18/V18)/Dashboard!$F$11} -> 7853.876 | F18: =AVERAGE(SUM(G18:J18)*(1+L18)/(D18-L18),G18*(1+L18)*(1-L18/D18)/(D18-L18)) -> 8.7514099e+08 | G18: ='DRE + DCF'!$W$31 -> 2791623.4 | H18: ='DRE + DCF'!$W$32 -> 81081.932 | I18: =-H18*('DRE + DCF'!$V$33+K18)/'DRE + DCF'!$V$33 -> -90858.802 | J18: =-'DRE + DCF'!$V$56*L18 -> -1188924.4 | K18: =(1+L18)/(1+Ke!$O$12)-1 -> 0.02 | L18: ='DRE + DCF'!$Y$31 -> 0.07355 | M18: =(1+D18)^((5-Dashboard!$F$9)*3/12) -> 1.055407 | N18: =M18*(1+$D18) -> 1.1340876 | O18: =N18*(1+$D18) -> 1.2186338 | P18: =O18*(1+$D18) -> 1.309483 | Q18: =P18*(1+$D18) -> 1.4071049 | R18: =Q18*(1+$D18) -> 1.5120046 | S18: =R18*(1+$D18) -> 1.6247245 | T18: =S18*(1+$D18) -> 1.7458478 | U18: =T18*(1+$D18) -> 1.8760007 | V18: =U18*(1+$D18) -> 2.0158566
C19: =ABS(E19-Dashboard!$F$14) -> 7062.3382 | D19: =D18+0.0001 -> 0.07465 | E19: {=1000*SUM('DRE + DCF'!$L$36/M19,'DRE + DCF'!$N$36:$V$36/N19:V19,F19/V19)/Dashboard!$F$11} -> 7159.3282 | F19: =AVERAGE(SUM(G19:J19)*(1+L19)/(D19-L19),G19*(1+L19)*(1-L19/D19)/(D19-L19)) -> 7.9738309e+08 | G19: ='DRE + DCF'!$W$31 -> 2791623.4 | H19: ='DRE + DCF'!$W$32 -> 81081.932 | I19: =-H19*('DRE + DCF'!$V$33+K19)/'DRE + DCF'!$V$33 -> -90858.802 | J19: =-'DRE + DCF'!$V$56*L19 -> -1188924.4 | K19: =(1+L19)/(1+Ke!$O$12)-1 -> 0.02 | L19: ='DRE + DCF'!$Y$31 -> 0.07355 | M19: =(1+D19)^((5-Dashboard!$F$9)*3/12) -> 1.0554807 | N19: =M19*(1+$D19) -> 1.1342723 | O19: =N19*(1+$D19) -> 1.2189457 | P19: =O19*(1+$D19) -> 1.30994 | Q19: =P19*(1+$D19) -> 1.407727 | R19: =Q19*(1+$D19) -> 1.5128139 | S19: =R19*(1+$D19) -> 1.6257454 | T19: =S19*(1+$D19) -> 1.7471073 | U19: =T19*(1+$D19) -> 1.8775289 | V19: =U19*(1+$D19) -> 2.0176864
C20: =ABS(E20-Dashboard!$F$14) -> 6483.4789 | D20: =D19+0.0001 -> 0.07475 | E20: {=1000*SUM('DRE + DCF'!$L$36/M20,'DRE + DCF'!$N$36:$V$36/N20:V20,F20/V20)/Dashboard!$F$11} -> 6580.4689 | F20: =AVERAGE(SUM(G20:J20)*(1+L20)/(D20-L20),G20*(1+L20)*(1-L20/D20)/(D20-L20)) -> 7.3258042e+08 | G20: ='DRE + DCF'!$W$31 -> 2791623.4 | H20: ='DRE + DCF'!$W$32 -> 81081.932 | I20: =-H20*('DRE + DCF'!$V$33+K20)/'DRE + DCF'!$V$33 -> -90858.802 | J20: =-'DRE + DCF'!$V$56*L20 -> -1188924.4 | K20: =(1+L20)/(1+Ke!$O$12)-1 -> 0.02 | L20: ='DRE + DCF'!$Y$31 -> 0.07355 | M20: =(1+D20)^((5-Dashboard!$F$9)*3/12) -> 1.0555543 | N20: =M20*(1+$D20) -> 1.134457 | O20: =N20*(1+$D20) -> 1.2192577 | P20: =O20*(1+$D20) -> 1.3103972 | Q20: =P20*(1+$D20) -> 1.4083494 | R20: =Q20*(1+$D20) -> 1.5136235 | S20: =R20*(1+$D20) -> 1.6267668 | T20: =S20*(1+$D20) -> 1.7483677 | U20: =T20*(1+$D20) -> 1.8790582 | V20: =U20*(1+$D20) -> 2.0195177
C21: =ABS(E21-Dashboard!$F$14) -> 5993.6111 | D21: =D20+0.0001 -> 0.07485 | E21: {=1000*SUM('DRE + DCF'!$L$36/M21,'DRE + DCF'!$N$36:$V$36/N21:V21,F21/V21)/Dashboard!$F$11} -> 6090.6011 | F21: =AVERAGE(SUM(G21:J21)*(1+L21)/(D21-L21),G21*(1+L21)*(1-L21/D21)/(D21-L21)) -> 6.7774333e+08 | G21: ='DRE + DCF'!$W$31 -> 2791623.4 | H21: ='DRE + DCF'!$W$32 -> 81081.932 | I21: =-H21*('DRE + DCF'!$V$33+K21)/'DRE + DCF'!$V$33 -> -90858.802 | J21: =-'DRE + DCF'!$V$56*L21 -> -1188924.4 | K21: =(1+L21)/(1+Ke!$O$12)-1 -> 0.02 | L21: ='DRE + DCF'!$Y$31 -> 0.07355 | M21: =(1+D21)^((5-Dashboard!$F$9)*3/12) -> 1.055628 | N21: =M21*(1+$D21) -> 1.1346417 | O21: =N21*(1+$D21) -> 1.2195697 | P21: =O21*(1+$D21) -> 1.3108545 | Q21: =P21*(1+$D21) -> 1.4089719 | R21: =Q21*(1+$D21) -> 1.5144335 | S21: =R21*(1+$D21) -> 1.6277888 | T21: =S21*(1+$D21) -> 1.7496288 | U21: =T21*(1+$D21) -> 1.8805885 | V21: =U21*(1+$D21) -> 2.0213506
C22: =ABS(E22-Dashboard!$F$14) -> 5573.6654 | D22: =D21+0.0001 -> 0.07495 | E22: {=1000*SUM('DRE + DCF'!$L$36/M22,'DRE + DCF'!$N$36:$V$36/N22:V22,F22/V22)/Dashboard!$F$11} -> 5670.6554 | F22: =AVERAGE(SUM(G22:J22)*(1+L22)/(D22-L22),G22*(1+L22)*(1-L22/D22)/(D22-L22)) -> 6.3073636e+08 | G22: ='DRE + DCF'!$W$31 -> 2791623.4 | H22: ='DRE + DCF'!$W$32 -> 81081.932 | I22: =-H22*('DRE + DCF'!$V$33+K22)/'DRE + DCF'!$V$33 -> -90858.802 | J22: =-'DRE + DCF'!$V$56*L22 -> -1188924.4 | K22: =(1+L22)/(1+Ke!$O$12)-1 -> 0.02 | L22: ='DRE + DCF'!$Y$31 -> 0.07355 | M22: =(1+D22)^((5-Dashboard!$F$9)*3/12) -> 1.0557016 | N22: =M22*(1+$D22) -> 1.1348265 | O22: =N22*(1+$D22) -> 1.2198817 | P22: =O22*(1+$D22) -> 1.3113119 | Q22: =P22*(1+$D22) -> 1.4095947 | R22: =Q22*(1+$D22) -> 1.5152438 | S22: =R22*(1+$D22) -> 1.6288113 | T22: =S22*(1+$D22) -> 1.7508907 | U22: =T22*(1+$D22) -> 1.88212 | V22: =U22*(1+$D22) -> 2.0231849
C23: =ABS(E23-Dashboard!$F$14) -> 5209.6577 | D23: =D22+0.0001 -> 0.07505 | E23: {=1000*SUM('DRE + DCF'!$L$36/M23,'DRE + DCF'!$N$36:$V$36/N23:V23,F23/V23)/Dashboard!$F$11} -> 5306.6477 | F23: =AVERAGE(SUM(G23:J23)*(1+L23)/(D23-L23),G23*(1+L23)*(1-L23/D23)/(D23-L23)) -> 5.899935e+08 | G23: ='DRE + DCF'!$W$31 -> 2791623.4 | H23: ='DRE + DCF'!$W$32 -> 81081.932 | I23: =-H23*('DRE + DCF'!$V$33+K23)/'DRE + DCF'!$V$33 -> -90858.802 | J23: =-'DRE + DCF'!$V$56*L23 -> -1188924.4 | K23: =(1+L23)/(1+Ke!$O$12)-1 -> 0.02 | L23: ='DRE + DCF'!$Y$31 -> 0.07355 | M23: =(1+D23)^((5-Dashboard!$F$9)*3/12) -> 1.0557753 | N23: =M23*(1+$D23) -> 1.1350112 | O23: =N23*(1+$D23) -> 1.2201938 | P23: =O23*(1+$D23) -> 1.3117694 | Q23: =P23*(1+$D23) -> 1.4102177 | R23: =Q23*(1+$D23) -> 1.5160545 | S23: =R23*(1+$D23) -> 1.6298344 | T23: =S23*(1+$D23) -> 1.7521535 | U23: =T23*(1+$D23) -> 1.8836526 | V23: =U23*(1+$D23) -> 2.0250207
C24: =ABS(E24-Dashboard!$F$14) -> 4891.0997 | D24: =D23+0.0001 -> 0.07515 | E24: {=1000*SUM('DRE + DCF'!$L$36/M24,'DRE + DCF'!$N$36:$V$36/N24:V24,F24/V24)/Dashboard!$F$11} -> 4988.0897 | F24: =AVERAGE(SUM(G24:J24)*(1+L24)/(D24-L24),G24*(1+L24)*(1-L24/D24)/(D24-L24)) -> 5.5434023e+08 | G24: ='DRE + DCF'!$W$31 -> 2791623.4 | H24: ='DRE + DCF'!$W$32 -> 81081.932 | I24: =-H24*('DRE + DCF'!$V$33+K24)/'DRE + DCF'!$V$33 -> -90858.802 | J24: =-'DRE + DCF'!$V$56*L24 -> -1188924.4 | K24: =(1+L24)/(1+Ke!$O$12)-1 -> 0.02 | L24: ='DRE + DCF'!$Y$31 -> 0.07355 | M24: =(1+D24)^((5-Dashboard!$F$9)*3/12) -> 1.055849 | N24: =M24*(1+$D24) -> 1.135196 | O24: =N24*(1+$D24) -> 1.220506 | P24: =O24*(1+$D24) -> 1.312227 | Q24: =P24*(1+$D24) -> 1.4108409 | R24: =Q24*(1+$D24) -> 1.5168656 | S24: =R24*(1+$D24) -> 1.630858 | T24: =S24*(1+$D24) -> 1.753417 | U24: =T24*(1+$D24) -> 1.8851863 | V24: =U24*(1+$D24) -> 2.026858
C25: =ABS(E25-Dashboard!$F$14) -> 4609.9713 | D25: =D24+0.0001 -> 0.07525 | E25: {=1000*SUM('DRE + DCF'!$L$36/M25,'DRE + DCF'!$N$36:$V$36/N25:V25,F25/V25)/Dashboard!$F$11} -> 4706.9613 | F25: =AVERAGE(SUM(G25:J25)*(1+L25)/(D25-L25),G25*(1+L25)*(1-L25/D25)/(D25-L25)) -> 5.2287841e+08 | G25: ='DRE + DCF'!$W$31 -> 2791623.4 | H25: ='DRE + DCF'!$W$32 -> 81081.932 | I25: =-H25*('DRE + DCF'!$V$33+K25)/'DRE + DCF'!$V$33 -> -90858.802 | J25: =-'DRE + DCF'!$V$56*L25 -> -1188924.4 | K25: =(1+L25)/(1+Ke!$O$12)-1 -> 0.02 | L25: ='DRE + DCF'!$Y$31 -> 0.07355 | M25: =(1+D25)^((5-Dashboard!$F$9)*3/12) -> 1.0559226 | N25: =M25*(1+$D25) -> 1.1353808 | O25: =N25*(1+$D25) -> 1.2208182 | P25: =O25*(1+$D25) -> 1.3126848 | Q25: =P25*(1+$D25) -> 1.4114643 | R25: =Q25*(1+$D25) -> 1.517677 | S25: =R25*(1+$D25) -> 1.6318822 | T25: =S25*(1+$D25) -> 1.7546813 | U25: =T25*(1+$D25) -> 1.8867211 | V25: =U25*(1+$D25) -> 2.0286968
C26: =ABS(E26-Dashboard!$F$14) -> 4360.0342 | D26: =D25+0.0001 -> 0.07535 | E26: {=1000*SUM('DRE + DCF'!$L$36/M26,'DRE + DCF'!$N$36:$V$36/N26:V26,F26/V26)/Dashboard!$F$11} -> 4457.0242 | F26: =AVERAGE(SUM(G26:J26)*(1+L26)/(D26-L26),G26*(1+L26)*(1-L26/D26)/(D26-L26)) -> 4.9490948e+08 | G26: ='DRE + DCF'!$W$31 -> 2791623.4 | H26: ='DRE + DCF'!$W$32 -> 81081.932 | I26: =-H26*('DRE + DCF'!$V$33+K26)/'DRE + DCF'!$V$33 -> -90858.802 | J26: =-'DRE + DCF'!$V$56*L26 -> -1188924.4 | K26: =(1+L26)/(1+Ke!$O$12)-1 -> 0.02 | L26: ='DRE + DCF'!$Y$31 -> 0.07355 | M26: =(1+D26)^((5-Dashboard!$F$9)*3/12) -> 1.0559963 | N26: =M26*(1+$D26) -> 1.1355656 | O26: =N26*(1+$D26) -> 1.2211304 | P26: =O26*(1+$D26) -> 1.3131426 | Q26: =P26*(1+$D26) -> 1.4120879 | R26: =Q26*(1+$D26) -> 1.5184887 | S26: =R26*(1+$D26) -> 1.6329069 | T26: =S26*(1+$D26) -> 1.7559464 | U26: =T26*(1+$D26) -> 1.888257 | V26: =U26*(1+$D26) -> 2.0305371
C27: =ABS(E27-Dashboard!$F$14) -> 4136.3638 | D27: =D26+0.0001 -> 0.07545 | E27: {=1000*SUM('DRE + DCF'!$L$36/M27,'DRE + DCF'!$N$36:$V$36/N27:V27,F27/V27)/Dashboard!$F$11} -> 4233.3538 | F27: =AVERAGE(SUM(G27:J27)*(1+L27)/(D27-L27),G27*(1+L27)*(1-L27/D27)/(D27-L27)) -> 4.6988193e+08 | G27: ='DRE + DCF'!$W$31 -> 2791623.4 | H27: ='DRE + DCF'!$W$32 -> 81081.932 | I27: =-H27*('DRE + DCF'!$V$33+K27)/'DRE + DCF'!$V$33 -> -90858.802 | J27: =-'DRE + DCF'!$V$56*L27 -> -1188924.4 | K27: =(1+L27)/(1+Ke!$O$12)-1 -> 0.02 | L27: ='DRE + DCF'!$Y$31 -> 0.07355 | M27: =(1+D27)^((5-Dashboard!$F$9)*3/12) -> 1.0560699 | N27: =M27*(1+$D27) -> 1.1357504 | O27: =N27*(1+$D27) -> 1.2214427 | P27: =O27*(1+$D27) -> 1.3136006 | Q27: =P27*(1+$D27) -> 1.4127118 | R27: =Q27*(1+$D27) -> 1.5193009 | S27: =R27*(1+$D27) -> 1.6339321 | T27: =S27*(1+$D27) -> 1.7572123 | U27: =T27*(1+$D27) -> 1.889794 | V27: =U27*(1+$D27) -> 2.0323789
... C3382: =ABS(E3382-Dashboard!$F$14) -> 63.454932 | D3382: =D3381+0.0001 -> 0.41095 | E3382: {=1000*SUM('DRE + DCF'!$L$36/M3382,'DRE + DCF'!$N$36:$V$36/N3382:V3382,F3382/V3382)/Dashboard!$F$11} -> 33.535068 | F3382: =AVERAGE(SUM(G3382:J3382)*(1+L3382)/(D3382-L3382),G3382*(1+L3382)*(1-L3382/D3382)/(D3382-L3382)) -> 6180569.7 | G3382: ='DRE + DCF'!$W$31 -> 2791623.4 | H3382: ='DRE + DCF'!$W$32 -> 81081.932 | I3382: =-H3382*('DRE + DCF'!$V$33+K3382)/'DRE + DCF'!$V$33 -> -90858.802 | J3382: =-'DRE + DCF'!$V$56*L3382 -> -1188924.4 | K3382: =(1+L3382)/(1+Ke!$O$12)-1 -> 0.02 | L3382: ='DRE + DCF'!$Y$31 -> 0.07355 | M3382: =(1+D3382)^((5-Dashboard!$F$9)*3/12) -> 1.2945944 | N3382: =M3382*(1+$D3382) -> 1.8266079 | O3382: =N3382*(1+$D3382) -> 2.5772525 | P3382: =O3382*(1+$D3382) -> 3.6363744 | Q3382: =P3382*(1+$D3382) -> 5.1307424 | R3382: =Q3382*(1+$D3382) -> 7.239221 | S3382: =R3382*(1+$D3382) -> 10.214179 | T3382: =S3382*(1+$D3382) -> 14.411696 | U3382: =T3382*(1+$D3382) -> 20.334182 | V3382: =U3382*(1+$D3382) -> 28.690514

Sheet DRE + DCF
J4: =Dashboard!J4 -> Banco da Amazônia ($BAZA3)
A7: Páginas
A8: Dashboard
A9: Ke | F9: 2020 | G9: 2021 | H9: 2022 | I9: 2023 | J9: 1T24 | K9: YTD24 | L9: YTG24 | M9: 2024 | N9: 2025 | O9: 2026 | P9: 2027 | Q9: 2028 | R9: 2029 | S9: 2030 | T9: 2031 | U9: 2032 | V9: 2033
A10: DRE + DCF | E10: Margem Financeira Líquida | F10: ='Projeções - NIM'!F30 -> 360543 | G10: ='Projeções - NIM'!G30 -> 517628 | H10: ='Projeções - NIM'!H30 -> 1061209 | I10: ='Projeções - NIM'!I30 -> 1068160 | J10: ='Projeções - NIM'!J30 -> 90674.552 | K10: ='Projeções - NIM'!K30 -> 90674.552 | L10: ='Projeções - NIM'!L30 -> 1087904.2 | M10: ='Projeções - NIM'!M30 -> 1178578.7 | ... V10: ='Projeções - NIM'!V30 -> 2898419.4
A11: DRE - Cosif | E11: Crescimento da Margem Financeira Líquida (YoY)¹ | F11: - | G11: =G10/F10-1 -> 0.43569006 | H11: =H10/G10-1 -> 1.0501383 | I11: =I10/H10-1 -> 0.0065500764 | M11: =M10/I10-1 -> 0.10337285 | N11: =N10/M10-1 -> 0.37996689 | O11: =O10/N10-1 -> 0.096122128 | P11: =P10/O10-1 -> 0.089555928 | Q11: =Q10/P10-1 -> 0.081634904 | R11: =R10/Q10-1 -> 0.075126751 | S11: =S10/R10-1 -> 0.069621031 | T11: =T10/S10-1 -> 0.06593892 | U11: =U10/T10-1 -> 0.062341052 | V11: =V10/U10-1 -> 0.059397411
A12: Balanço Patrimonial | E12: Receitas de Prestação de Serviços | F12: ='DRE - Cosif'!F19 -> 1760424 | G12: ='DRE - Cosif'!G19 -> 2197525 | H12: ='DRE - Cosif'!H19 -> 2950511 | I12: ='DRE - Cosif'!I19 -> 2853777 | J12: ='DRE - Cosif'!J19 -> 708102.46 | K12: ='DRE - Cosif'!K19 -> 708102.46 | L12: ='DRE - Cosif'!L19 -> 2301613.6 | M12: ='DRE - Cosif'!M19 -> 3009716 | ... V12: ='DRE - Cosif'!V19 -> 6856155.8
A13: Projeções - NIM | E13: Crescimento das Receitas de Prestação de Serviços (YoY)¹ | F13: - | G13: =G12/F12-1 -> 0.24829302 | H13: =H12/G12-1 -> 0.34265185 | I13: =I12/H12-1 -> -0.032785507 | M13: =M12/I12-1 -> 0.054643035 | N13: =N12/M12-1 -> 0.12291021 | O13: =O12/N12-1 -> 0.10957454 | P13: =P12/O12-1 -> 0.10418411 | Q13: =Q12/P12-1 -> 0.098033888 | R13: =R12/Q12-1 -> 0.092903716 | S13: =S12/R12-1 -> 0.088353582 | T13: =T12/S12-1 -> 0.085355387 | U13: =U12/T12-1 -> 0.082168553 | V13: =V12/U12-1 -> 0.079388072
A14: Projeções Trimestrais | E14: Despesas Operacionais | F14: ='DRE - Cosif'!F47 -> -1037069 | G14: ='DRE - Cosif'!G47 -> -1092748 | H14: ='DRE - Cosif'!H47 -> -1292488 | I14: ='DRE - Cosif'!I47 -> -1649120 | J14: ='DRE - Cosif'!J47 -> -356691.89 | K14: ='DRE - Cosif'!K47 -> -356691.89 | L14: ='DRE - Cosif'!L47 -> -1210324.5 | M14: ='DRE - Cosif'!M47 -> -1567016.4 | ... V14: ='DRE - Cosif'!V47 -> -3104342.5
A15: Painel de Índices | E15: Crescimento das Despesas Operacionais (YoY)¹ | F15: - | G15: =G14/F14-1 -> 0.05368881 | H15: =H14/G14-1 -> 0.18278688 | I15: =I14/H14-1 -> 0.27592674 | M15: =M14/I14-1 -> -0.049786306 | N15: =N14/M14-1 -> 0.085094923 | O15: =O14/N14-1 -> 0.077326218 | P15: =P14/O14-1 -> 0.078404329 | Q15: =Q14/P14-1 -> 0.078715008 | R15: =R14/Q14-1 -> 0.078601805 | S15: =S14/R14-1 -> 0.078675326 | T15: =T14/S14-1 -> 0.078399049 | U15: =U14/T14-1 -> 0.077785188 | V15: =V14/U14-1 -> 0.077281478
E16: Despesas de Provisão | F16: ='DRE - Cosif'!F57 -> -679835 | G16: ='DRE - Cosif'!G57 -> -495926 | H16: ='DRE - Cosif'!H57 -> -768605 | I16: ='DRE - Cosif'!I57 -> -631744 | J16: ='DRE - Cosif'!J57 -> -180181.92 | K16: ='DRE - Cosif'!K57 -> -180181.92 | L16: ='DRE - Cosif'!L57 -> -522197.53 | M16: ='DRE - Cosif'!M57 -> -702379.45 | ... V16: ='DRE - Cosif'!V57 -> -1803437
E17: Crescimento das Despesas de Provisão (YoY)¹ | F17: - | G17: =G16/F16-1 -> -0.27052005 | H17: =H16/G16-1 -> 0.54983808 | I17: =I16/H16-1 -> -0.17806416 | M17: =M16/I16-1 -> 0.11181025 | N17: =N16/M16-1 -> 0.12335804 | O17: =O16/N16-1 -> 0.11572178 | P17: =P16/O16-1 -> 0.11513621 | Q17: =Q16/P16-1 -> 0.11293143 | R17: =R16/Q16-1 -> 0.11035832 | S17: =S16/R16-1 -> 0.1078271 | T17: =T16/S16-1 -> 0.10561757 | U17: =U16/T16-1 -> 0.10293543 | V17: =V16/U16-1 -> 0.10044563
E18: Resultado Operacional | F18: =SUM(F10,F12,F14,F16) -> 404063 | G18: =SUM(G10,G12,G14,G16) -> 1126479 | H18: =SUM(H10,H12,H14,H16) -> 1950627 | I18: =SUM(I10,I12,I14,I16) -> 1641073 | J18: =SUM(J10,J12,J14,J16) -> 261903.2 | K18: =SUM(K10,K12,K14,K16) -> 261903.2 | L18: =SUM(L10,L12,L14,L16) -> 1656995.7 | M18: =SUM(M10,M12,M14,M16) -> 1918898.9 | ... V18: =SUM(V10,V12,V14,V16) -> 4846795.6
E19: Crescimento do Resultado Operacional (YoY)¹ | F19: - | G19: =G18/F18-1 -> 1.7878796 | H19: =H18/G18-1 -> 0.73161417 | I19: =I18/H18-1 -> -0.15869461 | M19: =M18/I18-1 -> 0.16929528 | N19: =N18/M18-1 -> 0.31151013 | O19: =O18/N18-1 -> 0.12074193 | P19: =P18/O18-1 -> 0.10826312 | Q19: =Q18/P18-1 -> 0.09537413 | R19: =R18/Q18-1 -> 0.085327292 | S19: =S18/R18-1 -> 0.076596421 | T19: =T18/S18-1 -> 0.071134449 | U19: =U18/T18-1 -> 0.065787319 | V19: =V18/U18-1 -> 0.061186672
E20: Resultado Não Operacional | F20: ='DRE - Cosif'!F68 -> 1175 | G20: ='DRE - Cosif'!G68 -> 234689 | H20: ='DRE - Cosif'!H68 -> 27610 | I20: ='DRE - Cosif'!I68 -> 7326 | J20: ='DRE - Cosif'!J68 -> 177.08662 | K20: ='DRE - Cosif'!K68 -> 177.08662 | L20: ='DRE - Cosif'!L68 -> 0 | M20: ='DRE - Cosif'!M68 -> 177.08662 | ... V20: ='DRE - Cosif'!V68 -> 0
E21: Resultado Antes do IR | F21: =SUM(F18,F20) -> 405238 | G21: =SUM(G18,G20) -> 1361168 | H21: =SUM(H18,H20) -> 1978237 | I21: =SUM(I18,I20) -> 1648399 | J21: =SUM(J18,J20) -> 262080.28 | K21: =SUM(K18,K20) -> 262080.28 | L21: =SUM(L18,L20) -> 1656995.7 | M21: =SUM(M18,M20) -> 1919076 | ... V21: =SUM(V18,V20) -> 4846795.6
E22: Imposto de Renda e Contribuição Social | F22: =SUM('DRE - Cosif'!F70,'DRE - Cosif'!F72,'DRE - Cosif'!F74) -> -119622 | G22: =SUM('DRE - Cosif'!G70,'DRE - Cosif'!G72,'DRE - Cosif'!G74) -> -573074 | H22: =SUM('DRE - Cosif'!H70,'DRE - Cosif'!H72,'DRE - Cosif'!H74) -> -780323 | I22: =SUM('DRE - Cosif'!I70,'DRE - Cosif'!I72,'DRE - Cosif'!I74) -> -212986 | J22: =SUM('DRE - Cosif'!J70,'DRE - Cosif'!J72,'DRE - Cosif'!J74) -> -55308 | K22: =SUM('DRE - Cosif'!K70,'DRE - Cosif'!K72,'DRE - Cosif'!K74) -> -55308 | L22: =SUM('DRE - Cosif'!L70,'DRE - Cosif'!L72,'DRE - Cosif'!L74) -> -609527.57 | M22: =SUM('DRE - Cosif'!M70,'DRE - Cosif'!M72,'DRE - Cosif'!M74) -> -664835.57 | ... V22: =SUM('DRE - Cosif'!V70,'DRE - Cosif'!V72,'DRE - Cosif'!V74) -> -1827388.5
E23: Imposto de Renda e Contribuição Social como % do Resultado Operacional | F23: =F22/F18 -> -0.29604789 | G23: =G22/G18 -> -0.5087303 | H23: =H22/H18 -> -0.40003701 | I23: =I22/I18 -> -0.1297846 | J23: =J22/J18 -> -0.21117726 | K23: =K22/K18 -> -0.21117726 | L23: =L22/L18 -> -0.36785102 | M23: =M22/M18 -> -0.34646722 | ... V23: =V22/V18 -> -0.37703025
E24: Resultado Antes de Participações Estatutárias | F24: =SUM(F21:F22) -> 285616 | G24: =SUM(G21:G22) -> 788094 | H24: =SUM(H21:H22) -> 1197914 | I24: =SUM(I21:I22) -> 1435413 | J24: =SUM(J21:J22) -> 206772.28 | K24: =SUM(K21:K22) -> 206772.28 | L24: =SUM(L21:L22) -> 1047468.2 | M24: =SUM(M21:M22) -> 1254240.4 | ... V24: =SUM(V21:V22) -> 3019407.1
E25: Participações Estatutárias no Lucro | F25: ='DRE - Cosif'!F77 -> -20048 | G25: ='DRE - Cosif'!G77 -> -50255 | H25: ='DRE - Cosif'!H77 -> -75600 | I25: ='DRE - Cosif'!I77 -> -90262 | J25: ='DRE - Cosif'!J77 -> 0 | K25: ='DRE - Cosif'!K77 -> 0 | L25: ='DRE - Cosif'!L77 -> -104006.84 | M25: ='DRE - Cosif'!M77 -> -104006.84 | ... V25: ='DRE - Cosif'!V77 -> -227783.73
E26: Lucro Líquido | F26: =SUM(F24:F25) -> 265568 | G26: =SUM(G24:G25) -> 737839 | H26: =SUM(H24:H25) -> 1122314 | I26: =SUM(I24:I25) -> 1345151 | J26: =SUM(J24:J25) -> 206772.28 | K26: =SUM(K24:K25) -> 206772.28 | L26: =SUM(L24:L25) -> 943461.31 | M26: =SUM(M24:M25) -> 1150233.6 | ... V26: =SUM(V24:V25) -> 2791623.4
E27: Crescimento Lucro Líquido dos Acionistas Controladoresl (YoY)¹ | F27: - | G27: =G26/F26-1 -> 1.778343 | H27: =H26/G26-1 -> 0.52108251 | I27: =I26/H26-1 -> 0.19855139 | M27: =M26/I26-1 -> -0.14490374 | N27: =N26/M26-1 -> 0.23454563 | O27: =O26/N26-1 -> 0.12396563 | P27: =P26/O26-1 -> 0.11043608 | Q27: =Q26/P26-1 -> 0.097909195 | R27: =R26/Q26-1 -> 0.087992531 | S27: =S26/R26-1 -> 0.079430596 | T27: =T26/S26-1 -> 0.073960262 | U27: =U26/T26-1 -> 0.068767023 | V27: =V26/U26-1 -> 0.064286892
E28: 1 - Ano a Ano
F30: =F9 -> 2020 | G30: =G9 -> 2021 | H30: =H9 -> 2022 | I30: =I$9 -> 2023 | J30: =J$9 -> 1T24 | K30: =K$9 -> YTD24 | L30: =L$9 -> YTG24 | M30: =M9 -> 2024 | N30: =N9 -> 2025 | O30: =O9 -> 2026 | P30: =P9 -> 2027 | Q30: =Q9 -> 2028 | R30: =R9 -> 2029 | S30: =S9 -> 2030 | T30: =T9 -> 2031 | ... V30: =V9 -> 2033 | W30: Perpetuidade | X30: ROE Perp. | Y30: Growth
E31: Lucro Líquido Total | F31: =F26 -> 265568 | G31: =G26 -> 737839 | H31: =H26 -> 1122314 | I31: =I26 -> 1345151 | J31: =J26 -> 206772.28 | K31: =K26 -> 206772.28 | L31: =L26 -> 943461.31 | M31: =M26 -> 1150233.6 | ... V31: =V26 -> 2791623.4 | W31: =V31+'DRE - Cosif'!V229+'DRE - Cosif'!V230 -> 2791623.4 | X31: =Ke!O16 -> 0.15496641 | Y31: ='Projeções - NIM'!K198 -> 0.07355
E32: Depreciação e Amortização | F32: - | G32: ='Balanço Patrimonial - Contábil'!F61-'Balanço Patrimonial - Contábil'!G61 -> 50715 | H32: ='Balanço Patrimonial - Contábil'!G61-'Balanço Patrimonial - Contábil'!H61 -> 49752 | I32: ='Balanço Patrimonial - Contábil'!H61-'Balanço Patrimonial - Contábil'!I61 -> 43830 | J32: ='Balanço Patrimonial - Contábil'!I61-'Balanço Patrimonial - Contábil'!J61 -> 10263.744 | K32: =J32 -> 10263.744 | L32: ='Balanço Patrimonial - Contábil'!K61-'Balanço Patrimonial - Contábil'!L61 -> 113280.78 | M32: ='Balanço Patrimonial - Contábil'!I61-'Balanço Patrimonial - Contábil'!M61 -> 123544.52 | N32: ='Balanço Patrimonial - Contábil'!M61-'Balanço Patrimonial - Contábil'!N61 -> 80415.384 | O32: ='Balanço Patrimonial - Contábil'!N61-'Balanço Patrimonial - Contábil'!O61 -> 71073.569 | P32: ='Balanço Patrimonial - Contábil'!O61-'Balanço Patrimonial - Contábil'!P61 -> 73068.735 | Q32: ='Balanço Patrimonial - Contábil'!P61-'Balanço Patrimonial - Contábil'!Q61 -> 73834.335 | R32: ='Balanço Patrimonial - Contábil'!Q61-'Balanço Patrimonial - Contábil'!R61 -> 74799.216 | S32: ='Balanço Patrimonial - Contábil'!R61-'Balanço Patrimonial - Contábil'!S61 -> 75722.313 | T32: ='Balanço Patrimonial - Contábil'!S61-'Balanço Patrimonial - Contábil'!T61 -> 77798.7 | U32: ='Balanço Patrimonial - Contábil'!T61-'Balanço Patrimonial - Contábil'!U61 -> 79366.026 | V32: ='Balanço Patrimonial - Contábil'!U61-'Balanço Patrimonial - Contábil'!V61 -> 81081.932 | W32: =V32 -> 81081.932
E33: Depreciação e Amortização como % dos Ativos Permanentes | F33: - | G33: =G32/'Balanço Patrimonial - Contábil'!G56 -> 0.22697775 | H33: =H32/'Balanço Patrimonial - Contábil'!H56 -> 0.23353142 | I33: =I32/'Balanço Patrimonial - Contábil'!I56 -> 0.21293858 | J33: =J32/'Balanço Patrimonial - Contábil'!J56 -> 0.050672582 | K33: =K32/'Balanço Patrimonial - Contábil'!K56 -> 0.050672582 | L33: =L32/'Balanço Patrimonial - Contábil'!L56 -> 0.46604694 | M33: =M32/'Balanço Patrimonial - Contábil'!M56 -> 0.50827287 | N33: =N32/'Balanço Patrimonial - Contábil'!N56 -> 0.29583031 | ... V33: =V32/'Balanço Patrimonial - Contábil'!V56 -> 0.16586481
E34: Capex (Projeção: ∆ (Intangível + Imobilizado de Uso + Investimentos)) | L34: =SUM('Balanço Patrimonial - Contábil'!K57,'Balanço Patrimonial - Contábil'!K59)-SUM('Balanço Patrimonial - Contábil'!L57,'Balanço Patrimonial - Contábil'!L59) -> -155402.76 | N34: =SUM('Balanço Patrimonial - Contábil'!M57,'Balanço Patrimonial - Contábil'!M59)-SUM('Balanço Patrimonial - Contábil'!N57,'Balanço Patrimonial - Contábil'!N59) -> -110316.8 | O34: =SUM('Balanço Patrimonial - Contábil'!N57,'Balanço Patrimonial - Contábil'!N59)-SUM('Balanço Patrimonial - Contábil'!O57,'Balanço Patrimonial - Contábil'!O59) -> -97501.352 | P34: =SUM('Balanço Patrimonial - Contábil'!O57,'Balanço Patrimonial - Contábil'!O59)-SUM('Balanço Patrimonial - Contábil'!P57,'Balanço Patrimonial - Contábil'!P59) -> -100238.39 | Q34: =SUM('Balanço Patrimonial - Contábil'!P57,'Balanço Patrimonial - Contábil'!P59)-SUM('Balanço Patrimonial - Contábil'!Q57,'Balanço Patrimonial - Contábil'!Q59) -> -101288.67 | R34: =SUM('Balanço Patrimonial - Contábil'!Q57,'Balanço Patrimonial - Contábil'!Q59)-SUM('Balanço Patrimonial - Contábil'!R57,'Balanço Patrimonial - Contábil'!R59) -> -102612.33 | S34: =SUM('Balanço Patrimonial - Contábil'!R57,'Balanço Patrimonial - Contábil'!R59)-SUM('Balanço Patrimonial - Contábil'!S57,'Balanço Patrimonial - Contábil'!S59) -> -103878.67 | T34: =SUM('Balanço Patrimonial - Contábil'!S57,'Balanço Patrimonial - Contábil'!S59)-SUM('Balanço Patrimonial - Contábil'!T57,'Balanço Patrimonial - Contábil'!T59) -> -106727.14 | U34: =SUM('Balanço Patrimonial - Contábil'!T57,'Balanço Patrimonial - Contábil'!T59)-SUM('Balanço Patrimonial - Contábil'!U57,'Balanço Patrimonial - Contábil'!U59) -> -108877.25 | V34: =SUM('Balanço Patrimonial - Contábil'!U57,'Balanço Patrimonial - Contábil'!U59)-SUM('Balanço Patrimonial - Contábil'!V57,'Balanço Patrimonial - Contábil'!V59) -> -111231.19 | W34: =-W32*(V33+((1+Y31)/(1+Ke!O12)-1))/V33 -> -90858.802
E35: Investimento em Capital Regulatório (Projeção: ∆ Patrimônio de Referência) | L35: =-L56+K56 -> -510245.9 | N35: =-N56+M56 -> -949259.08 | O35: =-O56+N56 -> -895485.31 | P35: =-P56+O56 -> -952795.51 | Q35: =-Q56+P56 -> -999352.17 | R35: =-R56+Q56 -> -1049428.9 | S35: =-S56+R56 -> -1100583.8 | T35: =-T56+S56 -> -1166316.6 | U35: =-U56+T56 -> -1228615.7 | V35: =-V56+U56 -> -1294780 | W35: =-Y31*V56 -> -1188924.4
E36: FCFE Pertencente aos Acionistas | L36: =SUM(L31:L32,L34:L35) -> 391093.43 | N36: =SUM(N31:N32,N34:N35) -> 440855.37 | O36: =SUM(O31:O32,O34:O35) -> 674135.93 | P36: =SUM(P31:P32,P34:P35) -> 792345.26 | Q36: =SUM(Q31:Q32,Q34:Q35) -> 919029.41 | R36: =SUM(R31:R32,R34:R35) -> 1039812.9 | S36: =SUM(S31:S32,S34:S35) -> 1156473.7 | T36: =SUM(T31:T32,T34:T35) -> 1258983.9 | U36: =SUM(U31:U32,U34:U35) -> 1364872 | V36: =SUM(V31:V32,V34:V35) -> 1466694.1 | W36: =AVERAGE(SUM(W31:W32,W34:W35)*(1+Y31)/(Ke!O16-'DRE + DCF'!Y31),W31*(1+Y31)*(1-Y31/W39)/(Ke!O16-Y31)) -> 20171735
E37: Desconto Acumulado | L37: =Ke!F17 -> 1.1210355 | N37: =Ke!G17 -> 1.3047073 | O37: =Ke!H17 -> 1.5183221 | P37: =Ke!I17 -> 1.7653519 | Q37: =Ke!J17 -> 2.0488566 | R37: =Ke!K17 -> 2.3733946 | S37: =Ke!L17 -> 2.7448199 | T37: =Ke!M17 -> 3.1706116 | U37: =Ke!N17 -> 3.6605803 | V37: =Ke!O17 -> 4.2278473 | W37: =V37 -> 4.2278473
E38: FCFE Descontado | L38: =L36/L37 -> 348868.01 | N38: =N36/N37 -> 337895.99 | O38: =O36/O37 -> 444000.61 | P38: =P36/P37 -> 448831.33 | Q38: =Q36/Q37 -> 448557.21 | R38: =R36/R37 -> 438112.09 | S38: =S36/S37 -> 421329.55 | T38: =T36/T37 -> 397079.18 | U38: =U36/U37 -> 372856.72 | ... W38: =W36/W37 -> 4771159.8
E39: ROE | F39: =F31/F52 -> 0.10988428 | G39: =G31/G52 -> 0.25054356 | H39: =H31/H52 -> 0.23181696 | I39: =I31/I52 -> 0.22863789 | M39: =M31/M52 -> 0.17499758 | N39: =N31/N52 -> 0.18605429 | O39: =O31/O52 -> 0.18504373 | P39: =P31/P52 -> 0.18312233 | Q39: =Q31/Q52 -> 0.18052222 | R39: =R31/R52 -> 0.17744199 | S39: =S31/S52 -> 0.17397326 | T39: =T31/T52 -> 0.17033231 | ... V39: =V31/V52 -> 0.16275809 | W39: =X31 -> 0.15496641
F42: 2020 | G42: 2021 | H42: 2022 | I42: 2023 | J42: =J$9 -> 1T24 | K42: =K$9 -> YTD24 | L42: =L$9 -> YTG24 | M42: 2024 | N42: 2025 | O42: 2026 | P42: 2027 | Q42: 2028 | R42: 2029 | S42: 2030 | T42: 2031 | U42: 2032 | V42: 2033
E43: Lucro Líquido por Ação | F43: 8.95798 | G43: 24.888833 | H43: 29.95943 | I43: 23.9956 | J43: 3.6885085 | K43: =J43 -> 3.6885085 | L43: =1000*L26/Dashboard!$F$11 -> 16.829998 | M43: =K43+L43 -> 20.518506 | N43: =1000*N26/Dashboard!$F$11 -> 25.331048 | O43: =1000*O26/Dashboard!$F$11 -> 28.471227 | P43: =1000*P26/Dashboard!$F$11 -> 31.615478 | Q43: =1000*Q26/Dashboard!$F$11 -> 34.710924 | R43: =1000*R26/Dashboard!$F$11 -> 37.765226 | S43: =1000*S26/Dashboard!$F$11 -> 40.76494 | T43: =1000*T26/Dashboard!$F$11 -> 43.779926 | U43: =1000*U26/Dashboard!$F$11 -> 46.790541 | V43: =1000*V26/Dashboard!$F$11 -> 49.79856
E44: Índice Payout | F44: =F46/F43 -> 0.28798457 | G44: =G46/G43 -> 0.26629011 | H44: =H46/H43 -> 0.17790192 | I44: =I46/I43 -> 0.26613587 | J44: =J46/J43 -> 0 | K44: =K46/K43 -> 0 | L44: =L46/L43 -> 0.41453044 | M44: =M46/M43 -> 0.34001239 | ... V44: =V46/V43 -> 0.5253911
E45: Índice Reinvestimento | F45: =1-F44 -> 0.71201543 | G45: =1-G44 -> 0.73370989 | H45: =1-H44 -> 0.82209808 | I45: =1-I44 -> 0.73386413 | J45: =1-J44 -> 1 | K45: =1-K44 -> 1 | L45: =1-L44 -> 0.58546956 | M45: =1-M44 -> 0.65998761 | ... V45: =1-V44 -> 0.4746089
E46: Proventos por Ação | F46: =SUM(F47:F48) -> 2.57976 | G46: =SUM(G47:G48) -> 6.62765 | H46: =SUM(H47:H48) -> 5.32984 | I46: =SUM(I47:I48) -> 6.38609 | J46: =SUM(J47:J48) -> 0 | K46: =SUM(K47:K48) -> 0 | L46: =1000*L36/Dashboard!$F$11 -> 6.9765463 | M46: =SUM(M47:M48) -> 6.9765463 | N46: =1000*N36/Dashboard!$F$11 -> 7.864228 | O46: =1000*O36/Dashboard!$F$11 -> 12.025619 | P46: =1000*P36/Dashboard!$F$11 -> 14.134304 | Q46: =1000*Q36/Dashboard!$F$11 -> 16.394168 | R46: =1000*R36/Dashboard!$F$11 -> 18.548771 | S46: =1000*S36/Dashboard!$F$11 -> 20.629834 | T46: =1000*T36/Dashboard!$F$11 -> 22.458468 | U46: =1000*U36/Dashboard!$F$11 -> 24.34736 | V46: =1000*V36/Dashboard!$F$11 -> 26.16372
E47: JCP Distribuído | F47: 2.57976 | G47: 4.78946 | H47: 4.20369 | I47: 6.38609 | J47: 0 | K47: =J47 -> 0 | L47: =1000*('DRE - Cosif'!L238/0.45)/Dashboard!$F$11 -> 6.0724518 | M47: =K47+L47 -> 6.0724518 | N47: =1000*('DRE - Cosif'!N238/0.45)/Dashboard!$F$11 -> 7.5208065 | O47: =1000*('DRE - Cosif'!O238/0.45)/Dashboard!$F$11 -> 8.8360884 | P47: =1000*('DRE - Cosif'!P238/0.45)/Dashboard!$F$11 -> 10.086539 | Q47: =1000*('DRE - Cosif'!Q238/0.45)/Dashboard!$F$11 -> 11.397966 | R47: =1000*('DRE - Cosif'!R238/0.45)/Dashboard!$F$11 -> 12.752838 | S47: =1000*('DRE - Cosif'!S238/0.45)/Dashboard!$F$11 -> 14.156254 | T47: =1000*('DRE - Cosif'!T238/0.45)/Dashboard!$F$11 -> 15.609724 | U47: =1000*('DRE - Cosif'!U238/0.45)/Dashboard!$F$11 -> 17.134767 | V47: =1000*('DRE - Cosif'!V238/0.45)/Dashboard!$F$11 -> 18.731046
E48: Dividendos Distribuídos | F48: 0 | G48: 1.83819 | H48: 1.12615 | I48: 0 | J48: 0 | K48: =J48 -> 0 | L48: =L46-L47 -> 0.90409451 | M48: =K48+L48 -> 0.90409451 | N48: =N46-N47 -> 0.34342154 | O48: =O46-O47 -> 3.1895304 | P48: =P46-P47 -> 4.0477647 | Q48: =Q46-Q47 -> 4.9962019 | R48: =R46-R47 -> 5.7959332 | S48: =S46-S47 -> 6.4735802 | T48: =T46-T47 -> 6.8487434 | U48: =U46-U47 -> 7.2125927 | V48: =V46-V47 -> 7.4326741
F51: =F42 -> 2020 | G51: =G42 -> 2021 | H51: =H42 -> 2022 | I51: =I42 -> 2023 | J51: =J$9 -> 1T24 | K51: =K$9 -> YTD24 | L51: =L$9 -> YTG24 | M51: =M42 -> 2024 | N51: =N42 -> 2025 | O51: =O42 -> 2026 | P51: =P42 -> 2027 | Q51: =Q42 -> 2028 | R51: =R42 -> 2029 | S51: =S42 -> 2030 | T51: =T42 -> 2031 | ... V51: =V42 -> 2033 | W51: Premissa
E52: Patrimônio Líquido | F52: ='Balanço Patrimonial - Contábil'!F125 -> 2416797 | G52: ='Balanço Patrimonial - Contábil'!G125 -> 2944953 | H52: ='Balanço Patrimonial - Contábil'!H125 -> 4841380 | I52: ='Balanço Patrimonial - Contábil'!I125 -> 5883325 | J52: ='Balanço Patrimonial - Contábil'!J125 -> 5907205.7 | K52: ='Balanço Patrimonial - Contábil'!K125 -> 5907205.7 | L52: ='Balanço Patrimonial - Contábil'!L125 -> 6572854.4 | M52: ='Balanço Patrimonial - Contábil'!M125 -> 6572854.4 | ... V52: ='Balanço Patrimonial - Contábil'!V125 -> 17151979 | W52: Soma entre o PL anterior e o Lucro reinvestido
E53: Exposição da Carteira de Crédito | F53: ='Projeções - NIM'!F104 -> 14500000 | G53: ='Projeções - NIM'!G104 -> 24500000 | H53: ='Projeções - NIM'!H104 -> 32600000 | I53: ='Projeções - NIM'!I104 -> 37500000 | J53: ='Projeções - NIM'!J104 -> 37500000 | K53: ='Projeções - NIM'!K104 -> 37500000 | L53: ='Projeções - NIM'!L104 -> 47001290 | M53: ='Projeções - NIM'!M104 -> 47001290 | ... V53: ='Projeções - NIM'!V104 -> 1.0227178e+08
E54: Ativos Ponderados pelo Risco (RWA) | F54: 25044849 | G54: 29349575 | H54: 37294000 | I54: 44365000 | J54: 45327956 | K54: =J54 -> 45327956 | L54: ='Projeções Trimestrais'!J40*1000 -> 51001788 | M54: =L54 -> 51001788 | N54: =N55*N53 -> 58177218 | O54: =O55*O53 -> 64877111 | P54: =P55*P53 -> 71964502 | Q54: =Q55*Q53 -> 79352014 | R54: =R55*R53 -> 87062944 | S54: =S55*S53 -> 95101593 | T54: =T55*T53 -> 1.0357469e+08 | U54: =U55*U53 -> 1.1245106e+08 | V54: =V55*V53 -> 1.2175498e+08
E55: RWA como % Exposição da Carteira de Crédito | F55: =F54/F53 -> 1.727231 | G55: =G54/G53 -> 1.1979418 | H55: =H54/H53 -> 1.1439877 | I55: =I54/I53 -> 1.1830667 | J55: =J54/J53 -> 1.2087455 | K55: =K54/K53 -> 1.2087455 | L55: =L54/L53 -> 1.0851146 | M55: =M54/M53 -> 1.0851146 | N55: =M55+(($V$55-$M$55)/9) -> 1.0968246 | O55: =N55+(($V$55-$M$55)/9) -> 1.1085346 | P55: =O55+(($V$55-$M$55)/9) -> 1.1202445 | Q55: =P55+(($V$55-$M$55)/9) -> 1.1319545 | R55: =Q55+(($V$55-$M$55)/9) -> 1.1436644 | S55: =R55+(($V$55-$M$55)/9) -> 1.1553744 | T55: =S55+(($V$55-$M$55)/9) -> 1.1670843 | U55: =T55+(($V$55-$M$55)/9) -> 1.1787943 | V55: =MEDIAN(F55:I55) -> 1.1905043 | W55: Crescerá linearmente até atingir o índice de mediano da série histórica.
E56: Patrimônio de Referência | F56: 2901780.6 | G56: 3556562.3 | H56: 4585000 | I56: 5782000 | J56: 6017983 | K56: =J56 -> 6017983 | L56: =L58*L54 -> 6528228.9 | M56: =L56 -> 6528228.9 | N56: =N58*N54 -> 7477488 | O56: =O58*O54 -> 8372973.3 | P56: =P58*P54 -> 9325768.8 | Q56: =Q58*Q54 -> 10325121 | R56: =R58*R54 -> 11374550 | S56: =S58*S54 -> 12475134 | T56: =T58*T54 -> 13641450 | U56: =U58*U54 -> 14870066 | V56: =V58*V54 -> 16164846
E57: Patrimônio de Referência como % do PL | F57: =F56/F52 -> 1.2006721 | G57: =G56/G52 -> 1.2076805 | H57: =H56/H52 -> 0.94704402 | I57: =I56/I52 -> 0.9827776 | J57: =J56/J52 -> 1.0187529 | K57: =K56/K52 -> 1.0187529 | L57: =L56/L52 -> 0.99321064 | M57: =M56/M52 -> 0.99321064 | ... V57: =V56/V52 -> 0.94244785
E58: Índice de Basileia | F58: =F56/F54 -> 0.11586337 | G58: =G56/G54 -> 0.12117935 | H58: =H56/H54 -> 0.12294203 | I58: =I56/I54 -> 0.13032796 | J58: =J56/J54 -> 0.13276537 | K58: =K56/K54 -> 0.13276537 | L58: 0.128 | M58: =M56/M54 -> 0.128 | N58: =M58+(($V$58-$M$58)/9) -> 0.12852949 | O58: =N58+(($V$58-$M$58)/9) -> 0.12905897 | P58: =O58+(($V$58-$M$58)/9) -> 0.12958846 | Q58: =P58+(($V$58-$M$58)/9) -> 0.13011794 | R58: =Q58+(($V$58-$M$58)/9) -> 0.13064743 | S58: =R58+(($V$58-$M$58)/9) -> 0.13117692 | T58: =S58+(($V$58-$M$58)/9) -> 0.1317064 | U58: =T58+(($V$58-$M$58)/9) -> 0.13223589 | V58: =MAX(F58:J58) -> 0.13276537 | W58: Crescerá linearmente até atingir o maior índice da série histórica.
F62: 2018 | G62: 2019 | H62: 2020 | I62: 2021 | J62: =J$9 -> 1T24 | K62: =K$9 -> YTD24 | L62: =L$9 -> YTG24 | M62: 2024 | N62: 2025 | O62: 2026 | P62: 2027 | Q62: 2028 | R62: 2029 | S62: 2030 | T62: 2031 | U62: 2032 | V62: 2033
E63: ∆ Resultado Operacional | F63: 0 | G63: 0 | H63: 0 | I63: 0 | M63: =M18/I18-1 -> 0.16929528 | N63: =N18/M18-1 -> 0.31151013 | O63: =O18/N18-1 -> 0.12074193 | P63: =P18/O18-1 -> 0.10826312 | Q63: =Q18/P18-1 -> 0.09537413 | R63: =R18/Q18-1 -> 0.085327292 | S63: =S18/R18-1 -> 0.076596421 | T63: =T18/S18-1 -> 0.071134449 | U63: =U18/T18-1 -> 0.065787319 | V63: =V18/U18-1 -> 0.061186672
E64: Taxa de Reinvestimento | F64: 0 | G64: 0 | H64: 0 | I64: 0 | M64: =M45 -> 0.65998761 | N64: =N45 -> 0.68954194 | O64: =O45 -> 0.57762204 | P64: =P45 -> 0.55293088 | Q64: =Q45 -> 0.52769429 | R64: =R45 -> 0.50883992 | S64: =S45 -> 0.49393195 | T64: =T45 -> 0.48701449 | ... V64: =V45 -> 0.4746089
E65: ROE Necessário | F65: 0 | G65: 0 | H65: 0 | I65: 0 | M65: =Ke!F12+(M63-Ke!F12)/M64 -> 0.23563773 | N65: =Ke!G12+(N63-Ke!G12)/N64 -> 0.43437566 | O65: =Ke!H12+(O63-Ke!H12)/O64 -> 0.17707776 | P65: =Ke!I12+(P63-Ke!I12)/P64 -> 0.15808006 | Q65: =Ke!J12+(Q63-Ke!J12)/Q64 -> 0.13706863 | R65: =Ke!K12+(R63-Ke!K12)/R64 -> 0.11934025 | S65: =Ke!L12+(S63-Ke!L12)/S64 -> 0.10212505 | T65: =Ke!M12+(T63-Ke!M12)/T64 -> 0.091015415 | ... V65: =Ke!O12+(V63-Ke!O12)/V64 -> 0.070802801

Sheet DRE - Cosif
L4: =Dashboard!J4 -> Banco da Amazônia ($BAZA3)
A7: Páginas
A8: Dashboard
A9: Ke
A10: DRE + DCF | F10: 2020 | G10: 2021 | H10: 2022 | I10: 2023 | J10: 1T24 | K10: YTD24 | L10: YTG24 | M10: 2024 | N10: 2025 | O10: 2026 | P10: 2027 | Q10: 2028 | R10: 2029 | S10: 2030 | T10: 2031 | U10: 2032 | V10: 2033 | W10: Premissas
A11: DRE - Cosif | E11: Margem Financeira Bruta | F11: ='Projeções - NIM'!F18 -> 479196 | G11: ='Projeções - NIM'!G18 -> 699559 | H11: ='Projeções - NIM'!H18 -> 1448757 | I11: ='Projeções - NIM'!I18 -> 1579027 | J11: ='Projeções - NIM'!J18 -> 384800.97 | K11: ='Projeções - NIM'!K18 -> 384800.97 | L11: ='Projeções - NIM'!L18 -> 1489355.2 | M11: ='Projeções - NIM'!M18 -> 1874156.2 | ... V11: ='Projeções - NIM'!V18 -> 4142297.4 | W11: Calculado na aba "Projeçoes - NIM"
A12: Balanço Patrimonial | E12: Despesa de Provisão (PCLD) | F12: ='Projeções - NIM'!F24 -> -118653 | G12: ='Projeções - NIM'!G24 -> -181931 | H12: ='Projeções - NIM'!H24 -> -387548 | I12: ='Projeções - NIM'!I24 -> -510867 | J12: ='Projeções - NIM'!J24 -> -294126.41 | K12: ='Projeções - NIM'!K24 -> -294126.41 | L12: ='Projeções - NIM'!L24 -> -401451.02 | M12: ='Projeções - NIM'!M24 -> -695577.44 | ... V12: ='Projeções - NIM'!V24 -> -1243878 | W12: Calculado na aba "Projeçoes - NIM"
A13: Projeções - NIM | E13: Margem Financeira Líquida (Resultado de Intermediação Financeira) | F13: =F11+F12 -> 360543 | G13: =G11+G12 -> 517628 | H13: =H11+H12 -> 1061209 | I13: =I11+I12 -> 1068160 | J13: =J11+J12 -> 90674.552 | K13: =K11+K12 -> 90674.552 | L13: =L11+L12 -> 1087904.2 | M13: =M11+M12 -> 1178578.7 | ... V13: =V11+V12 -> 2898419.4
A14: Projeções Trimestrais
A15: Painel de Índices
F17: =F$10 -> 2020 | G17: =G$10 -> 2021 | H17: =H$10 -> 2022 | I17: =I$10 -> 2023 | J17: =J$10 -> 1T24 | K17: =K$10 -> YTD24 | L17: =L$10 -> YTG24 | M17: =M$10 -> 2024 | ... V17: =V$10 -> 2033 | W17: CAGR 2020-2023 | X17: Premissas
E18: Resultado Líquido da Intermediação Financeira | F18: =F13 -> 360543 | G18: =G13 -> 517628 | H18: =H13 -> 1061209 | I18: =I13 -> 1068160 | J18: =J13 -> 90674.552 | K18: =K13 -> 90674.552 | L18: =L13 -> 1087904.2 | M18: =M13 -> 1178578.7 | ... V18: =V13 -> 2898419.4 | W18: =(I18/F18)^(1/3)-1 -> 0.436238
E19: Receita de Serviços | F19: =SUM(F21,F31,F33,F39,F41,F43,F45) -> 1760424 | G19: =SUM(G21,G31,G33,G39,G41,G43,G45) -> 2197525 | H19: =SUM(H21,H31,H33,H39,H41,H43,H45) -> 2950511 | I19: =SUM(I21,I31,I33,I39,I41,I43,I45) -> 2853777 | J19: =SUM(J21,J31,J33,J39,J41,J43,J45) -> 708102.46 | K19: =SUM(K21,K31,K33,K39,K41,K43,K45) -> 708102.46 | L19: =SUM(L21,L31,L33,L39,L41,L43,L45) -> 2301613.6 | M19: =SUM(M21,M31,M33,M39,M41,M43,M45) -> 3009716 | ... V19: =SUM(V21,V31,V33,V39,V41,V43,V45) -> 6856155.8 | W19: =(I19/F19)^(1/3)-1 -> 0.1747197
E20: Crescimento (%) | F20: - | G20: =G19/F19-1 -> 0.24829302 | H20: =H19/G19-1 -> 0.34265185 | I20: =I19/H19-1 -> -0.032785507 | M20: =M19/I19-1 -> 0.054643035 | N20: =N19/M19-1 -> 0.12291021 | O20: =O19/N19-1 -> 0.10957454 | P20: =P19/O19-1 -> 0.10418411 | Q20: =Q19/P19-1 -> 0.098033888 | R20: =R19/Q19-1 -> 0.092903716 | S20: =S19/R19-1 -> 0.088353582 | T20: =T19/S19-1 -> 0.085355387 | U20: =U19/T19-1 -> 0.082168553 | V20: =V19/U19-1 -> 0.079388072
E21: Administração de Fundos e Programas | F21: =SUM(F23,F25,F27,F29) -> 626682 | G21: =SUM(G23,G25,G27,G29) -> 670208 | H21: =SUM(H23,H25,H27,H29) -> 773225 | I21: =SUM(I23,I25,I27,I29) -> 497536 | J21: =SUM(J23,J25,J27,J29) -> 121774 | K21: =SUM(K23,K25,K27,K29) -> 121774 | L21: =SUM(L23,L25,L27,L29) -> 325921.28 | M21: =SUM(M23,M25,M27,M29) -> 447695.28 | ... V21: =SUM(V23,V25,V27,V29) -> 791558.72 | W21: =(I21/F21)^(1/3)-1 -> -0.074039566
E22: Crescimento (%) | F22: - | G22: =G21/F21-1 -> 0.069454684 | H22: =H21/G21-1 -> 0.153709 | I22: =I21/H21-1 -> -0.35654434 | M22: =M21/I21-1 -> -0.10017511 | N22: =N21/M21-1 -> 0.060657334 | O22: =O21/N21-1 -> 0.0576245 | P22: =P21/O21-1 -> 0.0622227 | Q22: =Q21/P21-1 -> 0.06476577 | R22: =R21/Q21-1 -> 0.066611749 | S22: =S21/R21-1 -> 0.067707429 | T22: =T21/S21-1 -> 0.069184708 | U22: =U21/T21-1 -> 0.069699217 | V22: =V21/U21-1 -> 0.069920033
E23: FNO | F23: 611945 | G23: 656285 | H23: 756947 | I23: 479979 | J23: 117224 | K23: =J23 -> 117224 | L23: ='Projeções Trimestrais'!J83 -> 311334.37 | M23: =SUM(K23,L23) -> 428558.37 | N23: =N84 -> 454842.02 | O23: =O84 -> 481856.18 | P23: =P84 -> 512971.56 | Q23: =Q84 -> 547639.72 | R23: =R84 -> 585846.24 | S23: =S84 -> 627495.11 | T23: =T84 -> 673122.54 | U23: =U84 -> 722465.92 | V23: =V84 -> 775603.29 | W23: =(I23/F23)^(1/3)-1 -> -0.077775586 | X23: Projetado na Tabela de "Projeção da Receita com Administração de Fundos e Programas".
E24: Crescimento (%) | F24: - | G24: =G23/F23-1 -> 0.072457492 | H24: =H23/G23-1 -> 0.15338153 | I24: =I23/H23-1 -> -0.36590144 | M24: =M23/I23-1 -> -0.107131 | N24: =N23/M23-1 -> 0.0613304 | O24: =O23/N23-1 -> 0.0593924 | P24: =P23/O23-1 -> 0.064574 | Q24: =Q23/P23-1 -> 0.067583 | R24: =R23/Q23-1 -> 0.0697658 | S24: =S23/R23-1 -> 0.0710918 | T24: =T23/S23-1 -> 0.0727136 | U24: =U23/T23-1 -> 0.0733052 | V24: =V23/U23-1 -> 0.07355
E25: Art. 19 da Lei nº 8.167/91 | F25: 1674 | G25: 140 | H25: 830 | I25: 743 | J25: 4 | K25: =J25 -> 4 | L25: ='Projeções Trimestrais'!J94 -> 11.957503 | M25: =SUM(K25,L25) -> 15.957503 | N25: =N85 -> 17.845753 | O25: =O85 -> 19.514645 | P25: =P85 -> 21.230386 | Q25: =Q85 -> 22.964104 | R25: =R85 -> 24.720479 | S25: =S85 -> 26.49853 | T25: =T85 -> 28.325336 | U25: =U85 -> 30.188945 | V25: =V85 -> 32.092846 | W25: =(I25/F25)^(1/3)-1 -> -0.23719923 | X25: Projetado na Tabela de "Projeção da Receita com Administração de Fundos e Programas".
E26: Crescimento (%) | F26: - | G26: =G25/F25-1 -> -0.91636798 | H26: =H25/G25-1 -> 4.9285714 | I26: =I25/H25-1 -> -0.10481928 | M26: =M25/I25-1 -> -0.97852288 | N26: =N25/M25-1 -> 0.11832987 | O26: =O25/N25-1 -> 0.093517619 | P26: =P25/O25-1 -> 0.087920697 | Q26: =Q25/P25-1 -> 0.081662123 | R26: =R25/Q25-1 -> 0.076483494 | S26: =S25/R25-1 -> 0.071926209 | T26: =T25/S25-1 -> 0.068939916 | U26: =U25/T25-1 -> 0.065793009 | V26: =V25/U25-1 -> 0.063066152
E27: Finam | F27: 11828 | G27: 12829 | H27: 14719 | I27: 16324 | J27: 4451 | K27: =J27 -> 4451 | L27: ='Projeções Trimestrais'!J105 -> 14254.504 | M27: =SUM(K27,L27) -> 18705.504 | N27: =N86 -> 19578.424 | O27: =O86 -> 19943.493 | P27: =P86 -> 20102.2 | Q27: =Q86 -> 20018.82 | R27: =R86 -> 19693.029 | S27: =S86 -> 19119.014 | T27: =T86 -> 18309.396 | U27: =U86 -> 17246.357 | V27: =V86 -> 15923.337 | W27: =(I27/F27)^(1/3)-1 -> 0.1133672 | X27: Projetado na Tabela de "Projeção da Receita com Administração de Fundos e Programas".
E28: Crescimento (%) | F28: - | G28: =G27/F27-1 -> 0.084629692 | H28: =H27/G27-1 -> 0.14732247 | I28: =I27/H27-1 -> 0.10904273 | M28: =M27/I27-1 -> 0.14588971 | N28: =N27/M27-1 -> 0.046666522 | O28: =O27/N27-1 -> 0.018646462 | P28: =P27/O27-1 -> 0.0079578405 | Q28: =Q27/P27-1 -> -0.0041478092 | R28: =R27/Q27-1 -> -0.016274222 | S28: =S27/R27-1 -> -0.029148124 | T28: =T27/S27-1 -> -0.042346257 | U28: =U27/T27-1 -> -0.058059715 | V28: =V27/U27-1 -> -0.076713026
E29: Outras - FDA | F29: 1235 | G29: 954 | H29: 729 | I29: 490 | J29: 95 | K29: =J29 -> 95 | L29: ='Projeções Trimestrais'!J116 -> 320.44681 | M29: =SUM(K29,L29) -> 415.44681 | N29: =N87 -> 412.98362 | O29: =O87 -> 395.15426 | P29: =P87 -> 368.48271 | Q29: =Q87 -> 332.14483 | R29: =R87 -> 286.03874 | S29: =S87 -> 229.95931 | T29: =T87 -> 163.87513 | U29: =U87 -> 87.328482 | V29: =V87 -> 0 | W29: =(I29/F29)^(1/3)-1 -> -0.26518777 | X29: Projetado na Tabela de "Projeção da Receita com Administração de Fundos e Programas".
E30: Crescimento (%) | F30: - | G30: =G29/F29-1 -> -0.22753036 | H30: =H29/G29-1 -> -0.23584906 | I30: =I29/H29-1 -> -0.32784636 | M30: =M29/I29-1 -> -0.15214937 | N30: =N29/M29-1 -> -0.005929005 | O30: =O29/N29-1 -> -0.043172083 | P30: =P29/O29-1 -> -0.067496545 | Q30: =Q29/P29-1 -> -0.098614898 | R30: =R29/Q29-1 -> -0.1388132 | S30: =S29/R29-1 -> -0.19605534 | T30: =T29/S29-1 -> -0.28737339 | U30: =U29/T29-1 -> -0.4671035 | V30: =V29/U29-1 -> -1
E31: Outros Serviços | F31: 25005 | G31: 24756 | H31: 30202 | I31: 36955 | J31: 16090 | K31: =J31 -> 16090 | L31: ='Projeções Trimestrais'!J127 -> 46457.987 | M31: =SUM(K31,L31) -> 62547.987 | N31: =N127 -> 42925.839 | O31: =O127 -> 47529.553 | P31: =P127 -> 52371.57 | Q31: =Q127 -> 57385.69 | R31: =R127 -> 62586.357 | S31: =S127 -> 67974.455 | T31: =T127 -> 73623.359 | U31: =U127 -> 79507.909 | V31: =V127 -> 85642.553 | W31: =(I31/F31)^(1/3)-1 -> 0.13906572 | X31: Projetado na Tabela "Projeção da Receita com Outros Serviços e com Demais Receitas Operacionais".
E32: Crescimento (%) | F32: - | G32: =G31/F31-1 -> -0.0099580084 | H32: =H31/G31-1 -> 0.21998707 | I32: =I31/H31-1 -> 0.22359446 | M32: =M31/I31-1 -> 0.69254465 | N32: =N31/M31-1 -> -0.3137135 | O32: =O31/N31-1 -> 0.10724809 | P32: =P31/O31-1 -> 0.10187381 | Q32: =Q31/P31-1 -> 0.095741255 | R32: =R31/Q31-1 -> 0.090626549 | S32: =S31/R31-1 -> 0.086090611 | T32: =T31/S31-1 -> 0.083103333 | U32: =U31/T31-1 -> 0.079927761 | V32: =V31/U31-1 -> 0.077157655
E33: Rendas de Tarifas Bancárias | F33: =SUM(F35,F37) -> 167777 | G33: =SUM(G35,G37) -> 193528 | H33: =SUM(H35,H37) -> 206610 | I33: =SUM(I35,I37) -> 248535 | J33: =SUM(J35,J37) -> 51694 | K33: =SUM(K35,K37) -> 51694 | L33: =SUM(L35,L37) -> 213125.34 | M33: =SUM(M35,M37) -> 264819.34 | ... V33: =SUM(V35,V37) -> 370081.2 | W33: =(I33/F33)^(1/3)-1 -> 0.13994801
E34: Crescimento (%) | F34: - | G34: =G33/F33-1 -> 0.15348349 | H34: =H33/G33-1 -> 0.067597454 | I34: =I33/H33-1 -> 0.20291854 | M34: =M33/I33-1 -> 0.065521305 | N34: =N33/M33-1 -> 0.080414855 | O34: =O33/N33-1 -> 0.055142789 | P34: =P33/O33-1 -> 0.048353757 | Q34: =Q33/P33-1 -> 0.040838058 | R34: =R33/Q33-1 -> 0.034261334 | S34: =S33/R33-1 -> 0.028166437 | T34: =T33/S33-1 -> 0.023444785 | U34: =U33/T33-1 -> 0.018415375 | V34: =V33/U33-1 -> 0.013611322
E35: Pessoa Física | F35: 92508 | G35: 120628 | H35: 130587 | I35: 159629 | J35: 27379 | K35: =J35 -> 27379 | L35: ='Projeções Trimestrais'!J138 -> 114334.28 | M35: =SUM(K35,L35) -> 141713.28 | N35: =N98 -> 153512.76 | O35: =O98 -> 162434.74 | P35: =P98 -> 170804.18 | Q35: =Q98 -> 178357.69 | R35: =R98 -> 185115.3 | S35: =S98 -> 191051 | T35: =T98 -> 196334.4 | U35: =U98 -> 200845.24 | V35: =V98 -> 204575.01 | W35: =(I35/F35)^(1/3)-1 -> 0.19943716 | X35: Projetado na Tabela "Projeção da Receita com Tarifas Bancárias".
E36: Crescimento (%) | F36: - | G36: =G35/F35-1 -> 0.30397371 | H36: =H35/G35-1 -> 0.082559605 | I36: =I35/H35-1 -> 0.2223958 | M36: =M35/I35-1 -> -0.11223348 | N36: =N35/M35-1 -> 0.083263046 | O36: =O35/N35-1 -> 0.05811884 | P36: =P35/O35-1 -> 0.051524914 | Q36: =Q35/P35-1 -> 0.044223218 | R36: =R35/Q35-1 -> 0.037887951 | S36: =S35/R35-1 -> 0.032064898 | T36: =T35/S35-1 -> 0.027654385 | U36: =U35/T35-1 -> 0.022975277 | V36: =V35/U35-1 -> 0.018570374
E37: Pessoa Jurídica | F37: 75269 | G37: 72900 | H37: 76023 | I37: 88906 | J37: 24315 | K37: =J37 -> 24315 | L37: ='Projeções Trimestrais'!J149 -> 98791.057 | M37: =SUM(K37,L37) -> 123106.06 | N37: =N99 -> 132601.99 | O37: =O99 -> 139457.17 | P37: =P99 -> 145685.34 | Q37: =Q99 -> 151056.65 | R37: =R99 -> 155585.21 | S37: =S99 -> 159245.83 | T37: =T99 -> 162175.07 | U37: =U99 -> 164266.31 | V37: =V99 -> 165506.19 | W37: =(I37/F37)^(1/3)-1 -> 0.057072988 | X37: Projetado na Tabela "Projeção da Receita com Tarifas Bancárias".
E38: Crescimento (%) | F38: - | G38: =G37/F37-1 -> -0.031473781 | H38: =H37/G37-1 -> 0.042839506 | I38: =I37/H37-1 -> 0.16946187 | M38: =M37/I37-1 -> 0.38467659 | N38: =N37/M37-1 -> 0.077136165 | O38: =O37/N37-1 -> 0.051697427 | P38: =P37/O37-1 -> 0.044660106 | Q38: =Q37/P37-1 -> 0.036869234 | R38: =R37/Q37-1 -> 0.029979265 | S38: =S37/R37-1 -> 0.023528048 | T38: =T37/S37-1 -> 0.018394426 | U38: =U37/T37-1 -> 0.012895008 | V38: =V37/U37-1 -> 0.0075479849
E39: Del Credere FNO | F39: 766966 | G39: 988248 | H39: 1326661 | I39: 1570602 | J39: 436914.27 | K39: =J39 -> 436914.27 | L39: ='Projeções Trimestrais'!J156 -> 1492176.4 | M39: =SUM(K39,L39) -> 1929090.7 | N39: =N109 -> 2222835.9 | O39: =O109 -> 2494115.7 | P39: =P109 -> 2778568.9 | Q39: =Q109 -> 3072650.1 | R39: =R109 -> 3377309.6 | S39: =S109 -> 3692722.6 | T39: =T109 -> 4023074.5 | U39: =U109 -> 4367094.5 | V39: =V109 -> 4725687.1 | W39: =(I39/F39)^(1/3)-1 -> 0.26988193 | X39: Projetado na Tabela "Projeção da Receita com o FNO".
E40: Crescimento (%) | F40: - | G40: =G39/F39-1 -> 0.28851605 | H40: =H39/G39-1 -> 0.34243732 | I40: =I39/H39-1 -> 0.18387591 | M40: =M39/I39-1 -> 0.2282492 | N40: =N39/M39-1 -> 0.15227133 | O40: =O39/N39-1 -> 0.12204221 | P40: =P39/O39-1 -> 0.11404973 | Q40: =Q39/P39-1 -> 0.10583908 | R40: =R39/Q39-1 -> 0.099152061 | S40: =S39/R39-1 -> 0.093391778 | T40: =T39/S39-1 -> 0.089460268 | U40: =U39/T39-1 -> 0.0855117 | V40: =V39/U39-1 -> 0.082112394
E41: Recuperação de Rendas FNO | F41: 64244 | G41: 98024 | H41: 338002 | I41: 195726 | J41: 62739.665 | K41: =J41 -> 62739.665 | L41: ='Projeções Trimestrais'!J163 -> 119353.01 | M41: =SUM(K41,L41) -> 182092.67 | N41: =N110 -> 212437.93 | O41: =O110 -> 241242.06 | P41: =P110 -> 271897.3 | Q41: =Q110 -> 304079.84 | R41: =R110 -> 337899.2 | S41: =S110 -> 373390 | T41: =T110 -> 410996.64 | U41: =U110 -> 450617.02 | V41: =V110 -> 492369.49 | W41: =(I41/F41)^(1/3)-1 -> 0.44967945 | X41: Projetado na Tabela "Projeção da Receita com o FNO".
E42: Crescimento (%) | F42: - | G42: =G41/F41-1 -> 0.52580786 | H42: =H41/G41-1 -> 2.4481556 | I42: =I41/H41-1 -> -0.42093242 | M42: =M41/I41-1 -> -0.069655166 | N42: =N41/M41-1 -> 0.16664732 | O42: =O41/N41-1 -> 0.13558846 | P42: =P41/O41-1 -> 0.12707254 | Q42: =Q41/P41-1 -> 0.11836284 | R42: =R41/Q41-1 -> 0.1112187 | S42: =S41/R41-1 -> 0.10503368 | T42: =T41/S41-1 -> 0.10071679 | U42: =U41/T41-1 -> 0.096400733 | V42: =V41/U41-1 -> 0.092656223
E43: Recuperação de Encargos e Despesas | F43: 14581 | G43: 32367 | H43: 64660 | I43: 9731 | J43: 700.2836 | K43: =J43 -> 700.2836 | L43: ='Projeções Trimestrais'!J170 -> 14615.433 | M43: =SUM(K43,L43) -> 15315.717 | N43: =N120 -> 11184.952 | O43: =O120 -> 11950.975 | P43: =P120 -> 12791.952 | Q43: =Q120 -> 13709.003 | R43: =R120 -> 14702.075 | S43: =S120 -> 15780.879 | T43: =T120 -> 16942.983 | U43: =U120 -> 18189.339 | V43: =V120 -> 19527.165 | W43: =(I43/F43)^(1/3)-1 -> -0.1261101 | X43: Projetado na Tabela "Projeção da Receita com Recuperação de Encargos e Despesas".
E44: Crescimento (%) | F44: - | G44: =G43/F43-1 -> 1.2198066 | H44: =H43/G43-1 -> 0.99771372 | I44: =I43/H43-1 -> -0.8495051 | M44: =M43/I43-1 -> 0.57390987 | N44: =N43/M43-1 -> -0.26970757 | O44: =O43/N43-1 -> 0.06848692 | P44: =P43/O43-1 -> 0.0703689 | Q44: =Q43/P43-1 -> 0.071689643 | R44: =R43/Q43-1 -> 0.072439407 | S44: =S43/R43-1 -> 0.073377734 | T44: =T43/S43-1 -> 0.073639973 | U44: =U43/T43-1 -> 0.073561785 | V44: =V43/U43-1 -> 0.07355
E45: Demais Receitas Operacionais | F45: 95169 | G45: 190394 | H45: 211151 | I45: 294692 | J45: 18190.237 | K45: =J45 -> 18190.237 | L45: ='Projeções Trimestrais'!J177 -> 89964.151 | M45: =SUM(K45,L45) -> 108154.39 | N45: =N128 -> 129290.27 | O45: =O128 -> 151018.95 | P45: =P128 -> 175067.36 | Q45: =Q128 -> 201321.52 | R45: =R128 -> 229919.9 | S45: =S128 -> 260958.47 | T45: =T128 -> 294824.09 | U45: =U128 -> 331541.26 | V45: =V128 -> 371289.57 | W45: =(I45/F45)^(1/3)-1 -> 0.45755275 | X45: Projetado na Tabela "Projeção da Receita com Outros Serviços e com Demais Receitas Operacionais".
E46: Crescimento (%) | F46: - | G46: =G45/F45-1 -> 1.0005884 | H46: =H45/G45-1 -> 0.10902129 | I46: =I45/H45-1 -> 0.39564577 | M46: =M45/I45-1 -> -0.63299177 | N46: =N45/M45-1 -> 0.19542324 | O46: =O45/N45-1 -> 0.16806122 | P46: =P45/O45-1 -> 0.159241 | Q46: =Q45/P45-1 -> 0.14996604 | R46: =R45/Q45-1 -> 0.14205328 | S46: =S45/R45-1 -> 0.13499734 | T46: =T45/S45-1 -> 0.12977396 | U46: =U45/T45-1 -> 0.12453926 | V46: =V45/U45-1 -> 0.11988948
E47: Despesas Operacionais | F47: =SUM(F49,F51,F53,F55) -> -1037069 | G47: =SUM(G49,G51,G53,G55) -> -1092748 | H47: =SUM(H49,H51,H53,H55) -> -1292488 | I47: =SUM(I49,I51,I53,I55) -> -1649120 | J47: =SUM(J49,J51,J53,J55) -> -356691.89 | K47: =SUM(K49,K51,K53,K55) -> -356691.89 | L47: =SUM(L49,L51,L53,L55) -> -1210324.5 | M47: =SUM(M49,M51,M53,M55) -> -1567016.4 | ... V47: =SUM(V49,V51,V53,V55) -> -3104342.5
E48: Crescimento (%) | F48: - | G48: =G47/F47-1 -> 0.05368881 | H48: =H47/G47-1 -> 0.18278688 | I48: =I47/H47-1 -> 0.27592674 | M48: =M47/I47-1 -> -0.049786306 | N48: =N47/M47-1 -> 0.085094923 | O48: =O47/N47-1 -> 0.077326218 | P48: =P47/O47-1 -> 0.078404329 | Q48: =Q47/P47-1 -> 0.078715008 | R48: =R47/Q47-1 -> 0.078601805 | S48: =S47/R47-1 -> 0.078675326 | T48: =T47/S47-1 -> 0.078399049 | U48: =U47/T47-1 -> 0.077785188 | V48: =V47/U47-1 -> 0.077281478
E49: Despesas de Pessoal | F49: -577278 | G49: -585373 | H49: -663047 | I49: -712282 | J49: -182230.48 | K49: =J49 -> -182230.48 | L49: ='Projeções Trimestrais'!J184 -> -587263.11 | M49: =SUM(K49,L49) -> -769493.59 | N49: =M49*(1+N50) -> -815195.66 | O49: =N49*(1+O50) -> -867836.11 | P49: =O49*(1+P50) -> -926487.08 | Q49: =P49*(1+Q50) -> -991124.19 | R49: =Q49*(1+R50) -> -1061585 | S49: =R49*(1+S50) -> -1138776.7 | T49: =S49*(1+T50) -> -1222254.9 | U49: =T49*(1+U50) -> -1311939.8 | V49: =U49*(1+V50) -> -1408433 | W49: =(I49/F49)^(1/3)-1 -> 0.072561789 | X49: Crescerá em linha com o PIB Nominal.
E50: Crescimento (%) | F50: - | G50: =G49/F49-1 -> 0.014022707 | H50: =H49/G49-1 -> 0.13269146 | I50: =I49/H49-1 -> 0.074255671 | M50: =M49/I49-1 -> 0.080321546 | N50: =(1+2%)*(1+Ke!G$12)-1 -> 0.0593924 | O50: =(1+2%)*(1+Ke!H$12)-1 -> 0.064574 | P50: =(1+2%)*(1+Ke!I$12)-1 -> 0.067583 | Q50: =(1+2%)*(1+Ke!J$12)-1 -> 0.0697658 | R50: =(1+2%)*(1+Ke!K$12)-1 -> 0.0710918 | S50: =(1+2%)*(1+Ke!L$12)-1 -> 0.0727136 | T50: =(1+2%)*(1+Ke!M$12)-1 -> 0.0733052 | U50: =(1+2%)*(1+Ke!N$12)-1 -> 0.0733766 | V50: =(1+2%)*(1+Ke!O$12)-1 -> 0.07355
E51: Despesas Administrativas | F51: -293647 | G51: -295304 | H51: -313554 | I51: -362855 | J51: -88439.208 | K51: =J51 -> -88439.208 | L51: ='Projeções Trimestrais'!J191 -> -302279.97 | M51: =SUM(K51,L51) -> -390719.17 | N51: =M51*(1+N52) -> -420582.36 | O51: =N51*(1+O52) -> -452576.54 | P51: =O51*(1+P52) -> -486841.56 | Q51: =P51*(1+Q52) -> -523525.47 | R51: =Q51*(1+R52) -> -562784.99 | S51: =R51*(1+S52) -> -604785.92 | T51: =S51*(1+T52) -> -649703.56 | U51: =T51*(1+U52) -> -697723.26 | V51: =U51*(1+V52) -> -749040.81 | W51: =(I51/F51)^(1/3)-1 -> 0.073089259 | X51: Cairá até atingir o PIB Nominal na perpetuidade.
E52: Crescimento (%) | F52: - | G52: =G51/F51-1 -> 0.0056428297 | H52: =H51/G51-1 -> 0.061800721 | I52: =I51/H51-1 -> 0.15723288 | M52: =M51/I51-1 -> 0.076791484 | N52: =M52+(($V52-$M52)/9) -> 0.076431319 | O52: =N52+(($V52-$M52)/9) -> 0.076071155 | P52: =O52+(($V52-$M52)/9) -> 0.07571099 | Q52: =P52+(($V52-$M52)/9) -> 0.075350825 | R52: =Q52+(($V52-$M52)/9) -> 0.07499066 | S52: =R52+(($V52-$M52)/9) -> 0.074630495 | T52: =S52+(($V52-$M52)/9) -> 0.07427033 | U52: =T52+(($V52-$M52)/9) -> 0.073910165 | V52: ='Projeções - NIM'!$K$198 -> 0.07355
E53: Despesas Tributárias | F53: -115418 | G53: -139467 | H53: -178719 | I53: -170696 | J53: -41511.576 | K53: =J53 -> -41511.576 | L53: ='Projeções Trimestrais'!J198 -> -125963.78 | M53: =SUM(K53,L53) -> -167475.36 | N53: =N136 -> -204889.63 | O53: =O136 -> -231656.38 | P53: =P136 -> -260429.32 | Q53: =Q136 -> -290858.17 | R53: =R136 -> -323054.02 | S53: =S136 -> -357075.65 | T53: =T136 -> -393367.79 | U53: =U136 -> -431872.01 | V53: =V136 -> -472746.73 | W53: =(I53/F53)^(1/3)-1 -> 0.13933105 | X53: Projetado na Tabela "Projeção das Despesas Tributárias".
E54: Crescimento (%) | F54: - | G54: =G53/F53-1 -> 0.20836438 | H54: =H53/G53-1 -> 0.28144292 | I54: =I53/H53-1 -> -0.044891701 | M54: =M53/I53-1 -> -0.018867692 | N54: =N53/M53-1 -> 0.22340161 | O54: =O53/N53-1 -> 0.13063985 | P54: =P53/O53-1 -> 0.12420528 | Q54: =Q53/P53-1 -> 0.11684109 | R54: =R53/Q53-1 -> 0.11069261 | S54: =S53/R53-1 -> 0.10531251 | T54: =T53/S53-1 -> 0.10163712 | U54: =U53/T53-1 -> 0.097883513 | V54: =V53/U53-1 -> 0.094645451
E55: Demais Despesas Operacionais | F55: -50726 | G55: -72604 | H55: -137168 | I55: -403287 | J55: -44510.63 | K55: =J55 -> -44510.63 | L55: ='Projeções Trimestrais'!J205 -> -194817.65 | M55: =SUM(K55,L55) -> -239328.28 | N55: =N143 -> -259693.9 | O55: =O143 -> -279775.05 | P55: =P143 -> -301710.62 | Q55: =Q143 -> -325459.78 | R55: =R143 -> -351041.5 | S55: =S143 -> -378659.81 | T55: =T143 -> -408346.38 | U55: =U143 -> -440109.68 | V55: =V143 -> -474122.01 | W55: =(I55/F55)^(1/3)-1 -> 0.99584986 | X55: Projetado na Tabela "Projeção das Demais Despesas Operacionais".
E56: Crescimento (%) | F56: - | G56: =G55/F55-1 -> 0.43129756 | H56: =H55/G55-1 -> 0.8892623 | I56: =I55/H55-1 -> 1.9400954 | M56: =M55/I55-1 -> -0.40655593 | N56: =N55/M55-1 -> 0.085094923 | O56: =O55/N55-1 -> 0.077326218 | P56: =P55/O55-1 -> 0.078404329 | Q56: =Q55/P55-1 -> 0.078715008 | R56: =R55/Q55-1 -> 0.078601805 | S56: =S55/R55-1 -> 0.078675326 | T56: =T55/S55-1 -> 0.078399049 | U56: =U55/T55-1 -> 0.077785188 | V56: =V55/U55-1 -> 0.077281478
E57: Despesas de Provisão | F57: =SUM(F59,F61,F63,F65) -> -679835 | G57: =SUM(G59,G61,G63,G65) -> -495926 | H57: =SUM(H59,H61,H63,H65) -> -768605 | I57: =SUM(I59,I61,I63,I65) -> -631744 | J57: =SUM(J59,J61,J63,J65) -> -180181.92 | K57: =SUM(K59,K61,K63,K65) -> -180181.92 | L57: =SUM(L59,L61,L63,L65) -> -522197.53 | M57: =SUM(M59,M61,M63,M65) -> -702379.45 | ... V57: =SUM(V59,V61,V63,V65) -> -1803437 | W57: =(I57/F57)^(1/3)-1 -> -0.024158683
E58: Crescimento (%) | F58: - | G58: =G57/F57-1 -> -0.27052005 | H58: =H57/G57-1 -> 0.54983808 | I58: =I57/H57-1 -> -0.17806416 | M58: =M57/I57-1 -> 0.11181025 | N58: =N57/M57-1 -> 0.12335804 | O58: =O57/N57-1 -> 0.11572178 | P58: =P57/O57-1 -> 0.11513621 | Q58: =Q57/P57-1 -> 0.11293143 | R58: =R57/Q57-1 -> 0.11035832 | S58: =S57/R57-1 -> 0.1078271 | T58: =T57/S57-1 -> 0.10561757 | U58: =U57/T57-1 -> 0.10293543 | V58: =V57/U57-1 -> 0.10044563
E59: Garantia Financeira Prestada | F59: -375000 | G59: -152705 | H59: -309744 | I59: -256106 | J59: -98635.402 | K59: =J59 -> -98635.402 | L59: ='Projeções Trimestrais'!J212 -> -234646.3 | M59: =SUM(K59,L59) -> -333281.7 | N59: =N150 -> -405671.3 | O59: =O150 -> -480226.01 | P59: =P150 -> -562919.08 | Q59: =Q150 -> -653350.82 | R59: =R150 -> -751923.45 | S59: =S150 -> -858896.29 | T59: =T150 -> -975491.16 | U59: =U150 -> -1101732 | V59: =V150 -> -1238147.4 | W59: =(I59/F59)^(1/3)-1 -> -0.11936455 | X59: Projetado na Tabela "Projeção das Despesas com Provisão das Garantias Financeiras Prestadas".
E60: Crescimento (%) | F60: - | G60: =G59/F59-1 -> -0.59278667 | H60: =H59/G59-1 -> 1.0283815 | I60: =I59/H59-1 -> -0.17316881 | M60: =M59/I59-1 -> 0.30134279 | N60: =N59/M59-1 -> 0.21720244 | O60: =O59/N59-1 -> 0.1837811 | P60: =P59/O59-1 -> 0.17219613 | Q60: =Q59/P59-1 -> 0.16064786 | R60: =R59/Q59-1 -> 0.15087244 | S60: =S59/R59-1 -> 0.14226559 | T60: =T59/S59-1 -> 0.13574966 | U60: =U59/T59-1 -> 0.12941255 | V60: =V59/U59-1 -> 0.12381904
E61: Passivo Autarial | F61: -172860 | G61: -189396 | H61: -208105 | I61: -170371 | J61: -38858.759 | K61: =J61 -> -38858.759 | L61: ='Projeções Trimestrais'!J219 -> -142961.93 | M61: =SUM(K61,L61) -> -181820.69 | N61: =M61*(1+N62) -> -188842.6 | O61: =N61*(1+O62) -> -197095.02 | P61: =O61*(1+P62) -> -206289.51 | Q61: =P61*(1+Q62) -> -216354.37 | R61: =Q61*(1+R62) -> -227191.56 | S61: =R61*(1+S62) -> -238932.82 | T61: =S61*(1+T62) -> -251419.45 | U61: =T61*(1+U62) -> -264576.23 | V61: =U61*(1+V62) -> -278466.48 | W61: =(I61/F61)^(1/3)-1 -> -0.0048228678 | X61: Crescerá em linha com a inflação.
E62: Crescimento (%) | F62: - | G62: =G61/F61-1 -> 0.095661229 | H62: =H61/G61-1 -> 0.098782445 | I62: =I61/H61-1 -> -0.18132193 | M62: =M61/I61-1 -> 0.067204434 | N62: =Ke!G$12 -> 0.03862 | O62: =Ke!H$12 -> 0.0437 | P62: =Ke!I$12 -> 0.04665 | Q62: =Ke!J$12 -> 0.04879 | R62: =Ke!K$12 -> 0.05009 | S62: =Ke!L$12 -> 0.05168 | T62: =Ke!M$12 -> 0.05226 | U62: =Ke!N$12 -> 0.05233 | V62: =Ke!O$12 -> 0.0525
E63: Demandas Judiciais | F63: -74502 | G63: -68187 | H63: -195403 | I63: -168682 | J63: -31387.605 | K63: =J63 -> -31387.605 | L63: ='Projeções Trimestrais'!J226 -> -127283.61 | M63: =SUM(K63,L63) -> -158671.22 | N63: =M63*(1+N64) -> -164799.1 | O63: =N63*(1+O64) -> -172000.82 | P63: =O63*(1+P64) -> -180024.66 | Q63: =P63*(1+Q64) -> -188808.06 | R63: =Q63*(1+R64) -> -198265.46 | S63: =R63*(1+S64) -> -208511.81 | T63: =S63*(1+T64) -> -219408.64 | U63: =T63*(1+U64) -> -230890.3 | V63: =U63*(1+V64) -> -243012.04 | W63: =(I63/F63)^(1/3)-1 -> 0.31310746 | X63: Crescerá em linha com a inflação.
E64: Crescimento (%) | F64: - | G64: =G63/F63-1 -> -0.084762825 | H64: =H63/G63-1 -> 1.8656929 | I64: =I63/H63-1 -> -0.13674816 | M64: =M63/I63-1 -> -0.059347079 | N64: =Ke!G$12 -> 0.03862 | O64: =Ke!H$12 -> 0.0437 | P64: =Ke!I$12 -> 0.04665 | Q64: =Ke!J$12 -> 0.04879 | R64: =Ke!K$12 -> 0.05009 | S64: =Ke!L$12 -> 0.05168 | T64: =Ke!M$12 -> 0.05226 | U64: =Ke!N$12 -> 0.05233 | V64: =Ke!O$12 -> 0.0525
E65: Planos Saldados | F65: -57473 | G65: -85638 | H65: -55353 | I65: -36585 | J65: -11300.158 | K65: =J65 -> -11300.158 | L65: ='Projeções Trimestrais'!J233 -> -17305.695 | M65: =SUM(K65,L65) -> -28605.853 | N65: =M65*(1+N66) -> -29710.611 | O65: =N65*(1+O66) -> -31008.964 | P65: =O65*(1+P66) -> -32455.533 | Q65: =P65*(1+Q66) -> -34039.038 | R65: =Q65*(1+R66) -> -35744.053 | S65: =R65*(1+S66) -> -37591.306 | T65: =S65*(1+T66) -> -39555.828 | U65: =T65*(1+U66) -> -41625.784 | V65: =U65*(1+V66) -> -43811.138 | W65: =(I65/F65)^(1/3)-1 -> -0.13977301 | X65: Crescerá em linha com a inflação.
E66: Crescimento (%) | F66: - | G66: =G65/F65-1 -> 0.4900562 | H66: =H65/G65-1 -> -0.35363974 | I66: =I65/H65-1 -> -0.33906021 | M66: =M65/I65-1 -> -0.21809887 | N66: =Ke!G$12 -> 0.03862 | O66: =Ke!H$12 -> 0.0437 | P66: =Ke!I$12 -> 0.04665 | Q66: =Ke!J$12 -> 0.04879 | R66: =Ke!K$12 -> 0.05009 | S66: =Ke!L$12 -> 0.05168 | T66: =Ke!M$12 -> 0.05226 | U66: =Ke!N$12 -> 0.05233 | V66: =Ke!O$12 -> 0.0525
E67: Resultado Operacional | F67: =SUM(F18,F19,F47,F57) -> 404063 | G67: =SUM(G18,G19,G47,G57) -> 1126479 | H67: =SUM(H18,H19,H47,H57) -> 1950627 | I67: =SUM(I18,I19,I47,I57) -> 1641073 | J67: =SUM(J18,J19,J47,J57) -> 261903.2 | K67: =SUM(K18,K19,K47,K57) -> 261903.2 | L67: =SUM(L18,L19,L47,L57) -> 1656995.7 | M67: =SUM(M18,M19,M47,M57) -> 1918898.9 | ... V67: =SUM(V18,V19,V47,V57) -> 4846795.6 | W67: =(I67/F67)^(1/3)-1 -> 0.59548578
E68: Resultado Não Operacional | F68: 1175 | G68: 234689 | H68: 27610 | I68: 7326 | J68: 177.08662 | K68: =J68 -> 177.08662 | L68: 0 | M68: =K68+L68 -> 177.08662 | N68: 0 | O68: 0 | P68: 0 | Q68: 0 | R68: 0 | S68: 0 | T68: 0 | U68: 0
E69: Resultado Antes da Tributação sobre Lucros | F69: =SUM(F67,F68) -> 405238 | G69: =SUM(G67,G68) -> 1361168 | H69: =SUM(H67,H68) -> 1978237 | I69: =SUM(I67,I68) -> 1648399 | J69: =SUM(J67,J68) -> 262080.28 | K69: =SUM(K67,K68) -> 262080.28 | L69: =SUM(L67,L68) -> 1656995.7 | M69: =SUM(M67:M68) -> 1919076 | N69: =SUM(N67:N68) -> 2516655.4 | O69: =SUM(O67:O68) -> 2820521.2 | P69: =SUM(P67:P68) -> 3125879.6 | Q69: =SUM(Q67:Q68) -> 3424007.7 | R69: =SUM(R67:R68) -> 3716169 | S69: =SUM(S67:S68) -> 4000814.2 | T69: =SUM(T67:T68) -> 4285409.9 | ... V69: =SUM(V67:V68) -> 4846795.6
E70: Provisão para Imposto de Renda | F70: =-SUM(F216,F221,F226) -> -87712 | G70: =-SUM(G216,G221,G226) -> -240015 | H70: =-SUM(H216,H221,H226) -> -354765 | I70: =-SUM(I216,I221,I226) -> -152904 | J70: =-SUM(J216,J221,J226) -> -79915 | K70: =-SUM(K216,K221,K226) -> -79915 | L70: =-SUM(L216,L221,L226) -> -332970.93 | M70: =-SUM(M216,M221,M226) -> -412885.93 | ... V70: =-SUM(V216,V221,V226) -> -1008589.3 | X70: Projetado na Tabela "Projeção de Valores Devidos: IR e CSLL".
E71: Provisão para Imposto de Renda como % do Resultado Antes da Tributação | F71: =F70/F69 -> -0.21644564 | G71: =G70/G69 -> -0.17633018 | H71: =H70/H69 -> -0.17933392 | I71: =I70/I69 -> -0.092759095 | J71: =J70/J69 -> -0.30492565 | K71: =K70/K69 -> -0.30492565 | L71: =L70/L69 -> -0.20094858 | M71: =M70/M69 -> -0.2151483 | ... V71: =V70/V69 -> -0.20809403
E72: Provisão para Contribuição Social | F72: =-SUM(F218,F223,F227) -> -67975 | G72: =-SUM(G218,G223,G227) -> -208149 | H72: =-SUM(H218,H223,H227) -> -299380 | I72: =-SUM(I218,I223,I227) -> -127241 | J72: =-SUM(J218,J223,J227) -> -65684 | K72: =-SUM(K218,K223,K227) -> -65684 | L72: =-SUM(L218,L223,L227) -> -276556.63 | M72: =-SUM(M218,M223,M227) -> -342240.63 | ... V72: =-SUM(V218,V223,V227) -> -818799.29 | X72: Projetado na Tabela "Projeção de Valores Devidos: IR e CSLL".
E73: Provisão para Contribuição Social como % do Resultado Antes da Tributação | F73: =F72/F69 -> -0.16774093 | G73: =G72/G69 -> -0.1529194 | H73: =H72/H69 -> -0.15133677 | I73: =I72/I69 -> -0.077190656 | J73: =J72/J69 -> -0.25062549 | K73: =K72/K69 -> -0.25062549 | L73: =L72/L69 -> -0.16690244 | M73: =M72/M69 -> -0.17833615 | ... V73: =V72/V69 -> -0.16893621
E74: Ativo Fiscal Diferido | F74: =-SUM(F229,F230) -> 36065 | G74: =-SUM(G229,G230) -> -124910 | H74: =-SUM(H229,H230) -> -126178 | I74: =-SUM(I229,I230) -> 67159 | J74: =-SUM(J229,J230) -> 90291 | K74: =-SUM(K229,K230) -> 90291 | L74: =-SUM(L229,L230) -> 0 | M74: =-SUM(M229,M230) -> 90291 | ... U74: =-SUM(U229,U230) -> 0 | X74: Projetado na Tabela "Projeção de Valores Devidos: IR e CSLL".
E75: Ativo Fiscal Diferido como % do Resultado Antes da Tributação | F75: =F74/F69 -> 0.088997083 | G75: =G74/G69 -> -0.091766777 | H75: =H74/H69 -> -0.063783055 | I75: =I74/I69 -> 0.040741956 | J75: =J74/J69 -> 0.34451657 | K75: =K74/K69 -> 0.34451657 | L75: =L74/L69 -> 0 | M75: =M74/M69 -> 0.047049205 | ... V75: =V74/V69 -> 0
E76: Resultado Antes das Participações | F76: =SUM(F69,F70,F72,F74) -> 285616 | G76: =SUM(G69,G70,G72,G74) -> 788094 | H76: =SUM(H69,H70,H72,H74) -> 1197914 | I76: =SUM(I69,I70,I72,I74) -> 1435413 | J76: =SUM(J69,J70,J72,J74) -> 206772.28 | K76: =SUM(K69,K70,K72,K74) -> 206772.28 | L76: =SUM(L69,L70,L72,L74) -> 1047468.2 | M76: =SUM(M69,M70,M72,M74) -> 1254240.4 | ... V76: =SUM(V69,V70,V72,V74) -> 3019407.1 | W76: =(I76/F76)^(1/3)-1 -> 0.71289778
E77: Participação sobre Lucro | F77: -20048 | G77: -50255 | H77: -75600 | I77: -90262 | J77: 0 | K77: =J77 -> 0 | L77: =L168 -> -104006.84 | M77: =K77+L77 -> -104006.84 | N77: =N168 -> -134391.43 | O77: =O168 -> -148360.27 | P77: =P168 -> -161919.94 | Q77: =Q168 -> -174621.97 | R77: =R168 -> -186547.18 | S77: =S168 -> -197633.36 | T77: =T168 -> -208261.4 | U77: =U168 -> -218306.19 | V77: =V168 -> -227783.73 | W77: =(I77/F77)^(1/3)-1 -> 0.65124418 | X77: Projetado na Tabela "Projeção da Participação sobre o Lucro".
E78: Participações sobre Lucro como % do Resultado Antes das Participações | F78: =F77/F76 -> -0.070192146 | G78: =G77/G76 -> -0.063767774 | H78: =H77/H76 -> -0.063109706 | I78: =I77/I76 -> -0.062882251 | J78: =J77/J76 -> 0 | K78: =K77/K76 -> 0 | L78: =L77/L76 -> -0.09929356 | M78: =M77/M76 -> -0.082924166 | ... V78: =V77/V76 -> -0.075439888
E79: Lucro Líquido Recorrente | F79: =SUM(F76,F77) -> 265568 | G79: =SUM(G76,G77) -> 737839 | H79: =SUM(H76,H77) -> 1122314 | I79: =SUM(I76,I77) -> 1345151 | J79: =SUM(J76,J77) -> 206772.28 | K79: =SUM(K76,K77) -> 206772.28 | L79: =SUM(L76,L77) -> 943461.31 | M79: =SUM(M76,M77) -> 1150233.6 | ... V79: =SUM(V76,V77) -> 2791623.4 | W79: =(I79/F79)^(1/3)-1 -> 0.71737485
E83: Ano | F83: =F$10 -> 2020 | G83: =G$10 -> 2021 | H83: =H$10 -> 2022 | I83: =I$10 -> 2023 | J83: =J$10 -> 1T24 | K83: =K$10 -> YTD24 | L83: =L$10 -> YTG24 | M83: =M$10 -> 2024 | ... V83: =V$10 -> 2033 | W83: Premissas
E84: FNO | F84: =F23 -> 611945 | G84: =G23 -> 656285 | H84: =H23 -> 756947 | I84: =I23 -> 479979 | J84: =J23 -> 117224 | K84: =K23 -> 117224 | L84: =L23 -> 311334.37 | M84: =M23 -> 428558.37 | N84: =N88*N89 -> 454842.02 | O84: =O88*O89 -> 481856.18 | P84: =P88*P89 -> 512971.56 | Q84: =Q88*Q89 -> 547639.72 | R84: =R88*R89 -> 585846.24 | S84: =S88*S89 -> 627495.11 | T84: =T88*T89 -> 673122.54 | U84: =U88*U89 -> 722465.92 | V84: =V88*V89 -> 775603.29
E85: Art. 19 da Lei nº 8.167/91 | F85: =F25 -> 1674 | G85: =G25 -> 140 | H85: =H25 -> 830 | I85: =I25 -> 743 | J85: =J25 -> 4 | K85: =K25 -> 4 | L85: =L25 -> 11.957503 | M85: =M25 -> 15.957503 | N85: =N90*N91 -> 17.845753 | O85: =O90*O91 -> 19.514645 | P85: =P90*P91 -> 21.230386 | Q85: =Q90*Q91 -> 22.964104 | R85: =R90*R91 -> 24.720479 | S85: =S90*S91 -> 26.49853 | T85: =T90*T91 -> 28.325336 | U85: =U90*U91 -> 30.188945 | V85: =V90*V91 -> 32.092846
E86: Finam | F86: =F27 -> 11828 | G86: =G27 -> 12829 | H86: =H27 -> 14719 | I86: =I27 -> 16324 | J86: =J27 -> 4451 | K86: =K27 -> 4451 | L86: =L27 -> 14254.504 | M86: =M27 -> 18705.504 | N86: =N92*N90 -> 19578.424 | O86: =O92*O90 -> 19943.493 | P86: =P92*P90 -> 20102.2 | Q86: =Q92*Q90 -> 20018.82 | R86: =R92*R90 -> 19693.029 | S86: =S92*S90 -> 19119.014 | T86: =T92*T90 -> 18309.396 | U86: =U92*U90 -> 17246.357 | V86: =V92*V90 -> 15923.337
E87: Outras - FDA | F87: =F29 -> 1235 | G87: =G29 -> 954 | H87: =H29 -> 729 | I87: =I29 -> 490 | J87: =J29 -> 95 | K87: =K29 -> 95 | L87: =L29 -> 320.44681 | M87: =M29 -> 415.44681 | N87: =N93*N90 -> 412.98362 | O87: =O93*O90 -> 395.15426 | P87: =P93*P90 -> 368.48271 | Q87: =Q93*Q90 -> 332.14483 | R87: =R93*R90 -> 286.03874 | S87: =S93*S90 -> 229.95931 | T87: =T93*T90 -> 163.87513 | U87: =U93*U90 -> 87.328482 | V87: =V93*V90 -> 0
E88: Carteira Ativa: FNO | F88: ='Projeções - NIM'!F181*10^6 -> 26700000 | G88: ='Projeções - NIM'!G181*10^6 -> 33000000 | H88: ='Projeções - NIM'!H181*10^6 -> 39500000 | I88: ='Projeções - NIM'!I181*10^6 -> 42800000 | J88: ='Projeções - NIM'!J181*10^6 -> 44400000 | K88: ='Projeções - NIM'!K181*10^6 -> 44400000 | L88: ='Projeções - NIM'!L181*10^6 -> 48354454 | M88: ='Projeções - NIM'!M181*10^6 -> 48354454 | ... V88: ='Projeções - NIM'!V181*10^6 -> 87511705
E89: FNO / Carteira Ativa: FNO | F89: =F84/F88 -> 0.022919288 | G89: =G84/G88 -> 0.019887424 | H89: =H84/H88 -> 0.019163215 | I89: =I84/I88 -> 0.011214463 | J89: =J84/J88 -> 0.0026401802 | K89: =K84/K88 -> 0.0026401802 | L89: =L84/L88 -> 0.0064385872 | M89: =M84/M88 -> 0.008862852 | N89: =M89 -> 0.008862852 | O89: =N89 -> 0.008862852 | P89: =O89 -> 0.008862852 | Q89: =P89 -> 0.008862852 | R89: =Q89 -> 0.008862852 | S89: =R89 -> 0.008862852 | T89: =S89 -> 0.008862852 | U89: =T89 -> 0.008862852 | V89: =U89 -> 0.008862852 | W89: Manterá o percentual igual ao do último ano.
E90: Depósitos Especiais com Remuneração | F90: ='Projeções - NIM'!F76 -> 1318693 | G90: ='Projeções - NIM'!G76 -> 1677854 | H90: ='Projeções - NIM'!H76 -> 3788271 | I90: ='Projeções - NIM'!I76 -> 5363550 | J90: ='Projeções - NIM'!J76 -> 6285008 | K90: ='Projeções - NIM'!K76 -> 6285008 | L90: ='Projeções - NIM'!L76 -> 7540523.6 | M90: ='Projeções - NIM'!M76 -> 7540523.6 | ... V90: ='Projeções - NIM'!V76 -> 15165083
E91: Art. 19 da Lei nº 8.167/91 / Depósitos Especiais com Remuneração | F91: =F85/F90 -> 0.0012694388 | G91: =G85/G90 -> 8.3439918e-05 | H91: =H85/H90 -> 0.00021909731 | I91: =I85/I90 -> 0.00013852765 | J91: =J85/J90 -> 6.3643515e-07 | K91: =K85/K90 -> 6.3643515e-07 | L91: =L85/L90 -> 1.5857657e-06 | M91: =M85/M90 -> 2.1162328e-06 | N91: =M91 -> 2.1162328e-06 | O91: =N91 -> 2.1162328e-06 | P91: =O91 -> 2.1162328e-06 | Q91: =P91 -> 2.1162328e-06 | R91: =Q91 -> 2.1162328e-06 | S91: =R91 -> 2.1162328e-06 | T91: =S91 -> 2.1162328e-06 | U91: =T91 -> 2.1162328e-06 | V91: =U91 -> 2.1162328e-06 | W91: Manterá o percentual igual ao do último ano.
E92: Finam / Depósitos Especiais com Remuneração | F92: =F86/F90 -> 0.0089694872 | G92: =G86/G90 -> 0.0076460765 | H92: =H86/H90 -> 0.0038854137 | I92: =I86/I90 -> 0.0030435066 | J92: =J86/J90 -> 0.00070819321 | K92: =K86/K90 -> 0.00070819321 | L92: =L86/L90 -> 0.0018903865 | M92: =M86/M90 -> 0.0024806638 | N92: =M92+(($V$92-$M$92)/9) -> 0.0023217011 | O92: =N92+(($V$92-$M$92)/9) -> 0.0021627385 | P92: =O92+(($V$92-$M$92)/9) -> 0.0020037759 | Q92: =P92+(($V$92-$M$92)/9) -> 0.0018448132 | R92: =Q92+(($V$92-$M$92)/9) -> 0.0016858506 | S92: =R92+(($V$92-$M$92)/9) -> 0.0015268879 | T92: =S92+(($V$92-$M$92)/9) -> 0.0013679253 | U92: =T92+(($V$92-$M$92)/9) -> 0.0012089626 | V92: 0.00105 | W92: Cairá até atingir 0.11% na perpetuidade. É um valor arbitrário para refletir a queda dos últimos 4 anos.
E93: Outros - FDA / Depósitos Especiais com Remuneração | F93: =F87/F90 -> 0.00093653337 | G93: =G87/G90 -> 0.00056858344 | H93: =H87/H90 -> 0.00019243607 | I93: =I87/I90 -> 9.1357403e-05 | J93: =J87/J90 -> 1.5115335e-05 | K93: =K87/K90 -> 1.5115335e-05 | L93: =L87/L90 -> 4.2496626e-05 | M93: =M87/M90 -> 5.509522e-05 | N93: =M93+(($V$93-$M$93)/9) -> 4.8973529e-05 | O93: =N93+(($V$93-$M$93)/9) -> 4.2851838e-05 | P93: =O93+(($V$93-$M$93)/9) -> 3.6730147e-05 | Q93: =P93+(($V$93-$M$93)/9) -> 3.0608456e-05 | R93: =Q93+(($V$93-$M$93)/9) -> 2.4486765e-05 | S93: =R93+(($V$93-$M$93)/9) -> 1.8365073e-05 | T93: =S93+(($V$93-$M$93)/9) -> 1.2243382e-05 | U93: =T93+(($V$93-$M$93)/9) -> 6.1216911e-06 | V93: 0 | W93: Cairá até atingir 0% na perpetuidade.
E97: Ano | F97: =F$10 -> 2020 | G97: =G$10 -> 2021 | H97: =H$10 -> 2022 | I97: =I$10 -> 2023 | J97: =J$10 -> 1T24 | K97: =K$10 -> YTD24 | L97: =L$10 -> YTG24 | M97: =M$10 -> 2024 | ... V97: =V$10 -> 2033 | W97: Premissas
E98: Pessoa Física | F98: =F35 -> 92508 | G98: =G35 -> 120628 | H98: =H35 -> 130587 | I98: =I35 -> 159629 | J98: =J35 -> 27379 | K98: =K35 -> 27379 | L98: =L35 -> 114334.28 | M98: =M35 -> 141713.28 | N98: =N103*N100 -> 153512.76 | O98: =O103*O100 -> 162434.74 | P98: =P103*P100 -> 170804.18 | Q98: =Q103*Q100 -> 178357.69 | R98: =R103*R100 -> 185115.3 | S98: =S103*S100 -> 191051 | T98: =T103*T100 -> 196334.4 | U98: =U103*U100 -> 200845.24 | V98: =V103*V100 -> 204575.01
E99: Pessoa Jurídica | F99: =F37 -> 75269 | G99: =G37 -> 72900 | H99: =H37 -> 76023 | I99: =I37 -> 88906 | J99: =J37 -> 24315 | K99: =K37 -> 24315 | L99: =L37 -> 98791.057 | M99: =M37 -> 123106.06 | N99: =N104*N100 -> 132601.99 | O99: =O104*O100 -> 139457.17 | P99: =P104*P100 -> 145685.34 | Q99: =Q104*Q100 -> 151056.65 | R99: =R104*R100 -> 155585.21 | S99: =S104*S100 -> 159245.83 | T99: =T104*T100 -> 162175.07 | U99: =U104*U100 -> 164266.31 | V99: =V104*V100 -> 165506.19
E100: Depósitos | F100: =SUM(F101,F102) -> 2868099 | G100: =SUM(G101,G102) -> 2793706 | H100: =SUM(H101,H102) -> 2534872 | I100: =SUM(I101,I102) -> 3075388 | J100: =SUM(J101,J102) -> 2628624 | K100: =SUM(K101,K102) -> 2628624 | L100: =SUM(L101,L102) -> 3153727.3 | M100: =SUM(M101,M102) -> 3153727.3 | ... V100: =SUM(V101,V102) -> 6342601.5
E101: Depósitos à Vista | F101: ='Projeções - NIM'!F66 -> 2101873 | G101: ='Projeções - NIM'!G66 -> 2000942 | H101: ='Projeções - NIM'!H66 -> 1785604 | I101: ='Projeções - NIM'!I66 -> 2349405 | J101: ='Projeções - NIM'!J66 -> 1905651 | K101: ='Projeções - NIM'!K66 -> 1905651 | L101: ='Projeções - NIM'!L66 -> 2286330.6 | M101: ='Projeções - NIM'!M66 -> 2286330.6 | ... V101: ='Projeções - NIM'!V66 -> 4598141.4
E102: Depósitos de Poupança | F102: ='Projeções - NIM'!F68 -> 766226 | G102: ='Projeções - NIM'!G68 -> 792764 | H102: ='Projeções - NIM'!H68 -> 749268 | I102: ='Projeções - NIM'!I68 -> 725983 | J102: ='Projeções - NIM'!J68 -> 722973 | K102: ='Projeções - NIM'!K68 -> 722973 | L102: ='Projeções - NIM'!L68 -> 867396.66 | M102: ='Projeções - NIM'!M68 -> 867396.66 | ... V102: ='Projeções - NIM'!V68 -> 1744460.1
E103: Pessoa Física / Depósitos | F103: =F98/F100 -> 0.032254117 | G103: =G98/G100 -> 0.043178488 | H103: =H98/H100 -> 0.051516211 | I103: =I98/I100 -> 0.051905321 | J103: =J98/J100 -> 0.010415716 | K103: =K98/K100 -> 0.010415716 | L103: =L98/L100 -> 0.0362537 | M103: =M98/M100 -> 0.044935173 | N103: =M103+(($V$103-$M$103)/9) -> 0.043526167 | O103: =N103+(($V$103-$M$103)/9) -> 0.042117161 | P103: =O103+(($V$103-$M$103)/9) -> 0.040708154 | Q103: =P103+(($V$103-$M$103)/9) -> 0.039299148 | R103: =Q103+(($V$103-$M$103)/9) -> 0.037890142 | S103: =R103+(($V$103-$M$103)/9) -> 0.036481136 | T103: =S103+(($V$103-$M$103)/9) -> 0.035072129 | U103: =T103+(($V$103-$M$103)/9) -> 0.033663123 | V103: =MIN(F103:I103) -> 0.032254117 | W103: Cairá até atingir o percentual mínimo na perpetuidade.
E104: Pessoa Jurídica / Depósitos | F104: =F99/F100 -> 0.026243515 | G104: =G99/G100 -> 0.026094371 | H104: =H99/H100 -> 0.029990863 | I104: =I99/I100 -> 0.028908873 | J104: =J99/J100 -> 0.0092500867 | K104: =K99/K100 -> 0.0092500867 | L104: =L99/L100 -> 0.031325174 | M104: =M99/M100 -> 0.039035099 | N104: =M104+(($V$104-$M$104)/9) -> 0.03759724 | O104: =N104+(($V$104-$M$104)/9) -> 0.036159382 | P104: =O104+(($V$104-$M$104)/9) -> 0.034721523 | Q104: =P104+(($V$104-$M$104)/9) -> 0.033283664 | R104: =Q104+(($V$104-$M$104)/9) -> 0.031845806 | S104: =R104+(($V$104-$M$104)/9) -> 0.030407947 | T104: =S104+(($V$104-$M$104)/9) -> 0.028970088 | U104: =T104+(($V$104-$M$104)/9) -> 0.027532229 | V104: =MIN(F104:I104) -> 0.026094371 | W104: Cairá até atingir o percentual mínimo na perpetuidade.
E108: Ano | F108: =F$10 -> 2020 | G108: =G$10 -> 2021 | H108: =H$10 -> 2022 | I108: =I$10 -> 2023 | J108: =J$10 -> 1T24 | K108: =K$10 -> YTD24 | L108: =L$10 -> YTG24 | M108: =M$10 -> 2024 | ... V108: =V$10 -> 2033 | W108: Premissas
E109: Del Credere FNO | F109: =F39 -> 766966 | G109: =G39 -> 988248 | H109: =H39 -> 1326661 | I109: =I39 -> 1570602 | J109: =J39 -> 436914.27 | K109: =K39 -> 436914.27 | L109: =L39 -> 1492176.4 | M109: =M39 -> 1929090.7 | N109: =N114*N111 -> 2222835.9 | O109: =O114*O111 -> 2494115.7 | P109: =P114*P111 -> 2778568.9 | Q109: =Q114*Q111 -> 3072650.1 | R109: =R114*R111 -> 3377309.6 | S109: =S114*S111 -> 3692722.6 | T109: =T114*T111 -> 4023074.5 | U109: =U114*U111 -> 4367094.5 | V109: =V114*V111 -> 4725687.1
E110: Recuperação de Renda FNO | F110: =F41 -> 64244 | G110: =G41 -> 98024 | H110: =H41 -> 338002 | I110: =I41 -> 195726 | J110: =J41 -> 62739.665 | K110: =K41 -> 62739.665 | L110: =L41 -> 119353.01 | M110: =M41 -> 182092.67 | N110: =N115*N111 -> 212437.93 | O110: =O115*O111 -> 241242.06 | P110: =P115*P111 -> 271897.3 | Q110: =Q115*Q111 -> 304079.84 | R110: =R115*R111 -> 337899.2 | S110: =S115*S111 -> 373390 | T110: =T115*T111 -> 410996.64 | U110: =U115*U111 -> 450617.02 | V110: =V115*V111 -> 492369.49
E111: Exposição da Carteira FNO | F111: =SUM(F112,F113*0.5) -> 0 | G111: =SUM(G112,G113*0.5) -> 17800000 | H111: =SUM(H112,H113*0.5) -> 25100000 | I111: =SUM(I112,I113*0.5) -> 29400000 | J111: =SUM(J112,J113*0.5) -> 30400000 | K111: =SUM(K112,K113*0.5) -> 30400000 | L111: =SUM(L112,L113*0.5) -> 39893697 | M111: =SUM(M112,M113*0.5) -> 39893697 | ... V111: =SUM(V112,V113*0.5) -> 89408482
E112: Carteira FNO que o BASA assume 100% do Risco | F112: - | G112: =('Projeções - NIM'!G181-'Projeções - NIM'!G189)*10^6 -> 2600000 | H112: =('Projeções - NIM'!H181-'Projeções - NIM'!H189)*10^6 -> 10700000 | I112: =('Projeções - NIM'!I181-'Projeções - NIM'!I189)*10^6 -> 16000000 | J112: =('Projeções - NIM'!J181-'Projeções - NIM'!J189)*10^6 -> 16400000 | K112: =('Projeções - NIM'!K181-'Projeções - NIM'!K189)*10^6 -> 16400000 | L112: =('Projeções - NIM'!L181-'Projeções - NIM'!L189)*10^6 -> 31432941 | M112: =('Projeções - NIM'!M181-'Projeções - NIM'!M189)*10^6 -> 31432941 | N112: =('Projeções - NIM'!N181-'Projeções - NIM'!N189)*10^6 -> 39675933 | ... V112: =('Projeções - NIM'!V181-'Projeções - NIM'!V189)*10^6 -> 91305258
E113: Carteira FNO que o BASA assume 50% do Risco | F113: ='Projeções - NIM'!F189*10^6 -> 0 | G113: ='Projeções - NIM'!G189*10^6 -> 30400000 | H113: ='Projeções - NIM'!H189*10^6 -> 28800000 | I113: ='Projeções - NIM'!I189*10^6 -> 26800000 | J113: ='Projeções - NIM'!J189*10^6 -> 28000000 | K113: ='Projeções - NIM'!K189*10^6 -> 28000000 | L113: ='Projeções - NIM'!L189*10^6 -> 16921513 | M113: ='Projeções - NIM'!M189*10^6 -> 16921513 | ... V113: ='Projeções - NIM'!V189*10^6 -> -3793553.8 | W113: Assumimos que todo o crédito em que o BASA assume 50% do Risco é do FNO.
E114: Del Credere FNO / Exposição da Carteira FNO | F114: - | G114: =G109/G111 -> 0.055519551 | H114: =H109/H111 -> 0.05285502 | I114: =I109/I111 -> 0.053421837 | J114: =J109/J111 -> 0.01437218 | K114: =K109/K111 -> 0.01437218 | L114: =L109/L111 -> 0.037403813 | M114: =M109/M111 -> 0.048355775 | N114: =M114+(($V114-$M114)/9) -> 0.048855691 | O114: =N114+(($V114-$M114)/9) -> 0.049355607 | P114: =O114+(($V114-$M114)/9) -> 0.049855523 | Q114: =P114+(($V114-$M114)/9) -> 0.05035544 | R114: =Q114+(($V114-$M114)/9) -> 0.050855356 | S114: =R114+(($V114-$M114)/9) -> 0.051355272 | T114: =S114+(($V114-$M114)/9) -> 0.051855188 | U114: =T114+(($V114-$M114)/9) -> 0.052355104 | V114: =MIN(G114:I114) -> 0.05285502 | W114: Crescerá linearmente até atinir o menor percentual histórico, o de 2022
E115: Recuperação de Renda FNO / Exposição da Carteira FNO | F115: - | G115: =G110/G111 -> 0.0055069663 | H115: =H110/H111 -> 0.013466215 | I115: =I110/I111 -> 0.0066573469 | J115: =J110/J111 -> 0.0020638048 | K115: =K110/K111 -> 0.0020638048 | L115: =L110/L111 -> 0.0029917761 | M115: =M110/M111 -> 0.0045644472 | N115: =M115+(($V115-$M115)/9) -> 0.0046691715 | O115: =N115+(($V115-$M115)/9) -> 0.0047738959 | P115: =O115+(($V115-$M115)/9) -> 0.0048786202 | Q115: =P115+(($V115-$M115)/9) -> 0.0049833446 | R115: =Q115+(($V115-$M115)/9) -> 0.0050880689 | S115: =R115+(($V115-$M115)/9) -> 0.0051927932 | T115: =S115+(($V115-$M115)/9) -> 0.0052975176 | U115: =T115+(($V115-$M115)/9) -> 0.0054022419 | V115: =MIN(G115:I115) -> 0.0055069663 | W115: Crescerá linearmente até atinir o menor percentual histórico, o de 2021
...

Sheet Balanço Patrimonial - Contábil
L4: =Dashboard!J4 -> Banco da Amazônia ($BAZA3)
A7: Páginas
A8: Dashboard
A9: Ke
A10: DRE + DCF | E10: Data do Último Resultado: 14/03/2024 | F10: 2020 | G10: 2021 | H10: 2022 | I10: 2023 | J10: 1T24 | K10: YTD24 | L10: YTG24 | M10: 2024 | N10: 2025 | O10: 2026 | P10: 2027 | Q10: 2028 | R10: 2029 | S10: 2030 | T10: 2031 | U10: 2032 | V10: 2033 | W10: Premissas
A11: DRE - Cosif | E11: Ativos Remuneráveis | F11: =SUM(F16) -> 19168331 | G11: =SUM(G16) -> 24531447 | H11: =SUM(H16) -> 33584145 | I11: =SUM(I16) -> 44413381 | J11: =SUM(J16) -> 47477178 | K11: =SUM(K16) -> 47477178 | L11: ='Projeções - NIM'!L38 -> 56974260 | M11: ='Projeções - NIM'!M38 -> 56974260 | N11: ='Projeções - NIM'!N38 -> 63716016 | O11: ='Projeções - NIM'!O38 -> 69674586 | P11: ='Projeções - NIM'!P38 -> 75800425 | Q11: ='Projeções - NIM'!Q38 -> 81990448 | R11: ='Projeções - NIM'!R38 -> 88261364 | S11: ='Projeções - NIM'!S38 -> 94609670 | ... V11: ='Projeções - NIM'!V38 -> 1.1458347e+08
A12: Balanço Patrimonial | E12: Ativo Total | F12: =SUM(F13,F56) -> 20815709 | G12: =SUM(G13,G56) -> 25952485 | H12: =SUM(H13,H56) -> 34595899 | I12: =SUM(I13,I56) -> 45212324 | J12: =SUM(J13,J56) -> 48194840 | K12: =SUM(K13,K56) -> 48194840 | L12: =SUM(L13,L56) -> 57835478 | M12: =SUM(M13,M56) -> 57835478 | ... V12: =SUM(V13,V56) -> 1.1631551e+08
A13: Projeções - NIM | E13: Ativo Circulante e Realizável a Longo Prazo | F13: =SUM(F14,F16,F45,F50,F52) -> 20567453 | G13: =SUM(G14,G16,G45,G50,G52) -> 25729049 | H13: =SUM(H14,H16,H45,H50,H52) -> 34382857 | I13: =SUM(I14,I16,I45,I50,I52) -> 45006490 | J13: =SUM(J14,J16,J45,J50,J52) -> 47992289 | K13: =SUM(K14,K16,K45,K50,K52) -> 47992289 | L13: =SUM(L14,L16,L45,L50,L52) -> 57592410 | M13: =SUM(M14,M16,M45,M50,M52) -> 57592410 | ... V13: =SUM(V14,V16,V45,V50,V52) -> 1.1582666e+08
A14: Projeções Trimestrais | E14: Disponibilidades | F14: 73593 | G14: 75723 | H14: 64740 | I14: 61049 | J14: 54837.75 | K14: =J14 -> 54837.75 | L14: =L15*L$11 -> 65807.2 | M14: =M15*M$11 -> 65807.2 | N14: =N15*N$11 -> 73594.157 | O14: =O15*O$11 -> 80476.508 | P14: =P15*P$11 -> 87552.058 | Q14: =Q15*Q$11 -> 94701.745 | R14: =R15*R$11 -> 101944.87 | S14: =S15*S$11 -> 109277.37 | ... V14: =V15*V$11 -> 132347.79
A15: Painel de Índices | E15: % dos Ativos Remuneráveis | F15: =F14/F$11 -> 0.0038393014 | G15: =G14/G$11 -> 0.0030867727 | H15: =H14/H$11 -> 0.0019276953 | I15: =I14/I$11 -> 0.0013745632 | J15: =J14/J$11 -> 0.0011550339 | K15: =K14/K$11 -> 0.0011550339 | L15: =K15 -> 0.0011550339 | M15: =L15 -> 0.0011550339 | N15: =M15 -> 0.0011550339 | O15: =N15 -> 0.0011550339 | P15: =O15 -> 0.0011550339 | Q15: =P15 -> 0.0011550339 | R15: =Q15 -> 0.0011550339 | S15: =R15 -> 0.0011550339 | ... V15: =U15 -> 0.0011550339
E16: Instrumentos Financeiros | F16: =SUM(F17,F19,F31,F33,F39,F41,F43) -> 19168331 | G16: =SUM(G17,G19,G31,G33,G39,G41,G43) -> 24531447 | H16: =SUM(H17,H19,H31,H33,H39,H41,H43) -> 33584145 | I16: =SUM(I17,I19,I31,I33,I39,I41,I43) -> 44413381 | J16: =SUM(J17,J19,J31,J33,J39,J41,J43) -> 47477178 | K16: =SUM(K17,K19,K31,K33,K39,K41,K43) -> 47477178 | L16: =SUM(L17,L19,L31,L33,L39,L41,L43) -> 56974260 | M16: =SUM(M17,M19,M31,M33,M39,M41,M43) -> 56974260 | ... V16: =SUM(V17,V19,V31,V33,V39,V41,V43) -> 1.1458347e+08
E17: Aplicações Interfinanceiras de Liquidez | F17: 585878 | G17: 1948260 | H17: 1112159 | I17: 1509359 | J17: 2324426.1 | K17: =J17 -> 2324426.1 | L17: ='Projeções - NIM'!L48 -> 2789391.9 | M17: ='Projeções - NIM'!M48 -> 2789391.9 | N17: ='Projeções - NIM'!N48 -> 3119460.3 | O17: ='Projeções - NIM'!O48 -> 3411184.8 | P17: ='Projeções - NIM'!P48 -> 3711098.6 | Q17: ='Projeções - NIM'!Q48 -> 4014154.7 | R17: ='Projeções - NIM'!R48 -> 4321171.3 | S17: ='Projeções - NIM'!S48 -> 4631976.8 | ... V17: ='Projeções - NIM'!V48 -> 5609870.4 | W17: Projetado na aba "Projeções - NIM".
E18: % dos Ativos Remuneráveis | F18: =F17/F$11 -> 0.030564894 | G18: =G17/G$11 -> 0.079418878 | H18: =H17/H$11 -> 0.033115597 | I18: =I17/I$11 -> 0.03398433 | J18: =J17/J$11 -> 0.04895881 | K18: =K17/K$11 -> 0.04895881 | L18: =L17/L$11 -> 0.04895881 | M18: =M17/M$11 -> 0.04895881 | ... V18: =V17/V$11 -> 0.04895881
E19: TVM e Instrumentos Financeiros Derivativos | F19: =SUM(F21:F30) -> 12801260 | G19: =SUM(G21:G30) -> 10631360 | H19: =SUM(H21:H30) -> 11608795 | I19: =SUM(I21:I30) -> 16099767 | J19: =SUM(J21:J30) -> 17226438 | K19: =SUM(K21:K30) -> 17226438 | L19: =SUM('Projeções - NIM'!L50,'Projeções - NIM'!L52,'Projeções - NIM'!L54) -> 20672323 | M19: =SUM('Projeções - NIM'!M50,'Projeções - NIM'!M52,'Projeções - NIM'!M54) -> 20672323 | N19: =SUM('Projeções - NIM'!N50,'Projeções - NIM'!N52,'Projeções - NIM'!N54) -> 23118476 | O19: =SUM('Projeções - NIM'!O50,'Projeções - NIM'!O52,'Projeções - NIM'!O54) -> 25280461 | P19: =SUM('Projeções - NIM'!P50,'Projeções - NIM'!P52,'Projeções - NIM'!P54) -> 27503136 | Q19: =SUM('Projeções - NIM'!Q50,'Projeções - NIM'!Q52,'Projeções - NIM'!Q54) -> 29749101 | R19: =SUM('Projeções - NIM'!R50,'Projeções - NIM'!R52,'Projeções - NIM'!R54) -> 32024416 | S19: =SUM('Projeções - NIM'!S50,'Projeções - NIM'!S52,'Projeções - NIM'!S54) -> 34327811 | ... V19: =SUM('Projeções - NIM'!V50,'Projeções - NIM'!V52,'Projeções - NIM'!V54) -> 41575029
E20: % dos Ativos Remuneráveis | F20: =F19/F$11 -> 0.66783383 | G20: =G19/G$11 -> 0.4333768 | H20: =H19/H$11 -> 0.34566296 | I20: =I19/I$11 -> 0.36249812 | J20: =J19/J$11 -> 0.36283618 | K20: =K19/K$11 -> 0.36283618 | L20: =L19/L$11 -> 0.36283618 | M20: =M19/M$11 -> 0.36283618 | ... V20: =V19/V$11 -> 0.36283618 | W20: Projetado na aba "Projeções - NIM".
E21: Títulos Públicos | F21: 9175911 | G21: 6986931 | H21: 8389137 | I21: 13386348 | J21: 14559576 | K21: =J21 -> 14559576 | L21: - | M21: - | N21: - | O21: - | P21: - | Q21: - | R21: - | S21: - | T21: - | U21: - | V21: -
E22: Debêntures | F22: 725655 | G22: 839488 | H22: 734695 | I22: 520122 | J22: 474075 | K22: =J22 -> 474075 | L22: - | M22: - | N22: - | O22: - | P22: - | Q22: - | R22: - | S22: - | T22: - | U22: - | V22: -
E23: Cotas de FIDC | F23: 88995 | G23: 39518 | H23: 39495 | I23: 40134 | J23: 40896 | K23: =J23 -> 40896 | L23: - | M23: - | N23: - | O23: - | P23: - | Q23: - | R23: - | S23: - | T23: - | U23: - | V23: -
E24: Cotas de Fundos de Renda Fixa | F24: 38062 | G24: 40649 | H24: 46452 | I24: 51825 | J24: 53586 | K24: =J24 -> 53586 | L24: - | M24: - | N24: - | O24: - | P24: - | Q24: - | R24: - | S24: - | T24: - | U24: - | V24: -
E25: Cotas de Fundos REF | F25: 36878 | G25: 39071 | H25: 794 | I25: 900 | J25: 849 | K25: =J25 -> 849 | L25: - | M25: - | N25: - | O25: - | P25: - | Q25: - | R25: - | S25: - | T25: - | U25: - | V25: -
E26: Letras Financeiras | F26: 1716461 | G26: 1840210 | H26: 1684242 | I26: 1535027 | J26: 1517984 | K26: =J26 -> 1517984 | L26: - | M26: - | N26: - | O26: - | P26: - | Q26: - | R26: - | S26: - | T26: - | U26: - | V26: -
E27: Ações | F27: 0 | G27: 0 | H27: 18646 | I27: 0 | J27: 0 | K27: =J27 -> 0 | L27: - | M27: - | N27: - | O27: - | P27: - | Q27: - | R27: - | S27: - | T27: - | U27: - | V27: -
E28: Cotas de Renda Variável | F28: 0 | G28: 0 | H28: 259 | I28: 0 | J28: 0 | K28: =J28 -> 0 | L28: - | M28: - | N28: - | O28: - | P28: - | Q28: - | R28: - | S28: - | T28: - | U28: - | V28: -
E29: Vinculados a Operações Compromissadas | F29: 252073 | G29: 200144 | H29: 70080 | I29: 0 | J29: 100187 | K29: =J29 -> 100187 | L29: - | M29: - | N29: - | O29: - | P29: - | Q29: - | R29: - | S29: - | T29: - | U29: - | V29: -
E30: Vinculados a Prestação de Garantia | F30: 767225 | G30: 645349 | H30: 624995 | I30: 565411 | J30: 479285 | K30: =J30 -> 479285 | L30: - | M30: - | N30: - | O30: - | P30: - | Q30: - | R30: - | S30: - | T30: - | U30: - | V30: -
E31: Relações Interfinanceiras e Interdependências | F31: 543523 | G31: 499289 | H31: 927618 | I31: 805425 | J31: 826763.73 | K31: =J31 -> 826763.73 | L31: ='Projeções - NIM'!L56 -> 992145.13 | M31: ='Projeções - NIM'!M56 -> 992145.13 | N31: ='Projeções - NIM'!N56 -> 1109545.5 | O31: ='Projeções - NIM'!O56 -> 1213307.6 | P31: ='Projeções - NIM'!P56 -> 1319982.4 | Q31: ='Projeções - NIM'!Q56 -> 1427775 | R31: ='Projeções - NIM'!R56 -> 1536976.2 | S31: ='Projeções - NIM'!S56 -> 1647525.1 | ... V31: ='Projeções - NIM'!V56 -> 1995347.3 | W31: Projetado na aba "Projeções - NIM".
E32: % dos Ativos Remuneráveis | F32: =F31/F$11 -> 0.02835526 | G32: =G31/G$11 -> 0.020353019 | H32: =H31/H$11 -> 0.027620712 | I32: =I31/I$11 -> 0.018134737 | J32: =J31/J$11 -> 0.017413919 | K32: =K31/K$11 -> 0.017413919 | L32: =L31/L$11 -> 0.017413919 | M32: =M31/M$11 -> 0.017413919 | ... V32: =V31/V$11 -> 0.017413919
E33: Operações de Crédito | F33: =SUM(F35:F38) -> 5032252 | G33: =SUM(G35:G38) -> 11224831 | H33: =SUM(H35:H38) -> 19699806 | I33: =SUM(I35:I38) -> 25792751 | J33: =SUM(J35:J38) -> 26885958 | K33: =SUM(K35:K38) -> 26885958 | L33: =SUM(L35:L38) -> 32264081 | M33: =SUM(M35:M38) -> 32264081 | ... V33: =SUM(V35:V38) -> 64887732
E34: % dos Ativos Remuneráveis | F34: =F33/F$11 -> 0.26252948 | G34: =G33/G$11 -> 0.45756905 | H34: =H33/H$11 -> 0.58658054 | I34: =I33/I$11 -> 0.58074279 | J34: =J33/J$11 -> 0.56629225 | K34: =K33/K$11 -> 0.56629225 | L34: =L33/L11 -> 0.56629225 | M34: =M33/M11 -> 0.56629225 | N34: =N33/N11 -> 0.56629225 | O34: =O33/O11 -> 0.56629225 | P34: =P33/P11 -> 0.56629225 | Q34: =Q33/Q11 -> 0.56629225 | R34: =R33/R11 -> 0.56629225 | S34: =S33/S11 -> 0.56629225 | ... V34: =V33/V11 -> 0.56629225
E35: Empréstimos | F35: 1993626 | G35: 2439446 | H35: 2886738 | I35: 3099444 | J35: 2878763 | K35: =J35 -> 2878763 | L35: ='Projeções - NIM'!L40 -> 3454615.4 | M35: ='Projeções - NIM'!M40 -> 3454615.4 | N35: ='Projeções - NIM'!N40 -> 3863399.6 | O35: ='Projeções - NIM'!O40 -> 4224695.5 | P35: ='Projeções - NIM'!P40 -> 4596133.7 | Q35: ='Projeções - NIM'!Q40 -> 4971463.7 | R35: ='Projeções - NIM'!R40 -> 5351698.6 | S35: ='Projeções - NIM'!S40 -> 5736626 | ... V35: ='Projeções - NIM'!V40 -> 6947730.9 | W35: Projetado na aba "Projeções - NIM".
E36: Direitos Creditórios Descontados | F36: 6270 | G36: 11857 | H36: 5879 | I36: 8746 | J36: 10638 | K36: =J36 -> 10638 | L36: ='Projeções - NIM'!L42 -> 12765.969 | M36: ='Projeções - NIM'!M42 -> 12765.969 | N36: ='Projeções - NIM'!N42 -> 14276.564 | O36: ='Projeções - NIM'!O42 -> 15611.674 | P36: ='Projeções - NIM'!P42 -> 16984.264 | Q36: ='Projeções - NIM'!Q42 -> 18371.235 | R36: ='Projeções - NIM'!R42 -> 19776.331 | S36: ='Projeções - NIM'!S42 -> 21198.767 | ... V36: ='Projeções - NIM'!V42 -> 25674.208 | W36: Projetado na aba "Projeções - NIM".
E37: Financiamentos | F37: 1290886 | G37: 2601194 | H37: 5222618 | I37: 7583131 | J37: 8169088 | K37: =J37 -> 8169088 | L37: ='Projeções - NIM'!L44 -> 9803188.7 | M37: ='Projeções - NIM'!M44 -> 9803188.7 | N37: ='Projeções - NIM'!N44 -> 10963199 | O37: ='Projeções - NIM'!O44 -> 11988451 | P37: ='Projeções - NIM'!P44 -> 13042484 | Q37: ='Projeções - NIM'!Q44 -> 14107561 | R37: ='Projeções - NIM'!R44 -> 15186556 | S37: ='Projeções - NIM'!S44 -> 16278868 | ... V37: ='Projeções - NIM'!V44 -> 19715630 | W37: Projetado na aba "Projeções - NIM".
E38: Financiamentos Rurais | F38: 1741470 | G38: 6172334 | H38: 11584571 | I38: 15101430 | J38: 15827469 | K38: =J38 -> 15827469 | L38: ='Projeções - NIM'!L46 -> 18993511 | M38: ='Projeções - NIM'!M46 -> 18993511 | N38: ='Projeções - NIM'!N46 -> 21241011 | O38: ='Projeções - NIM'!O46 -> 23227420 | P38: ='Projeções - NIM'!P46 -> 25269591 | Q38: ='Projeções - NIM'!Q46 -> 27333159 | R38: ='Projeções - NIM'!R46 -> 29423695 | S38: ='Projeções - NIM'!S46 -> 31540030 | ... V38: ='Projeções - NIM'!V46 -> 38198697 | W38: Projetado na aba "Projeções - NIM".
E39: Carteira de Câmbio | F39: 53248 | G39: 61990 | H39: 42771 | I39: 31150 | J39: 46877.307 | K39: =J39 -> 46877.307 | L39: ='Projeções - NIM'!L58 -> 56254.393 | M39: ='Projeções - NIM'!M58 -> 56254.393 | N39: ='Projeções - NIM'!N58 -> 62910.968 | O39: ='Projeções - NIM'!O58 -> 68794.252 | P39: ='Projeções - NIM'!P58 -> 74842.691 | Q39: ='Projeções - NIM'!Q58 -> 80954.504 | R39: ='Projeções - NIM'!R58 -> 87146.187 | S39: ='Projeções - NIM'!S58 -> 93414.282 | ... V39: ='Projeções - NIM'!V58 -> 113135.72 | W39: Projetado na aba "Projeções - NIM".
E40: % dos Ativos Remuneráveis | F40: =F39/F$11 -> 0.0027779153 | G40: =G39/G$11 -> 0.0025269606 | H40: =H39/H$11 -> 0.0012735474 | I40: =I39/I$11 -> 0.0007013652 | J40: =J39/J$11 -> 0.00098736506 | K40: =K39/K$11 -> 0.00098736506 | L40: =L39/L$11 -> 0.00098736506 | M40: =M39/M$11 -> 0.00098736506 | ... V40: =V39/V$11 -> 0.00098736506
E41: Outros Créditos | F41: 208 | G41: 0 | H41: 0 | I41: 0 | J41: 0 | K41: =J41 -> 0 | L41: ='Projeções - NIM'!L60 -> 0 | M41: ='Projeções - NIM'!M60 -> 0 | N41: ='Projeções - NIM'!N60 -> 0 | O41: ='Projeções - NIM'!O60 -> 0 | P41: ='Projeções - NIM'!P60 -> 0 | Q41: ='Projeções - NIM'!Q60 -> 0 | R41: ='Projeções - NIM'!R60 -> 0 | S41: ='Projeções - NIM'!S60 -> 0 | ... V41: ='Projeções - NIM'!V60 -> 0 | W41: Projetado na aba "-Projeções - NIM".
E42: % dos Ativos Remuneráveis | F42: =F41/F$11 -> 1.0851232e-05 | G42: =G41/G$11 -> 0 | H42: =H41/H$11 -> 0 | I42: =I41/I$11 -> 0 | J42: =J41/J$11 -> 0 | L42: =L41/L$11 -> 0 | M42: =M41/M$11 -> 0 | N42: =N41/N$11 -> 0 | O42: =O41/O$11 -> 0 | P42: =P41/P$11 -> 0 | Q42: =Q41/Q$11 -> 0 | R42: =R41/R$11 -> 0 | S42: =S41/S$11 -> 0 | ... V42: =V41/V$11 -> 0
E43: Outros Instrumentos Financeiros | F43: 151962 | G43: 165717 | H43: 192996 | I43: 174929 | J43: 166715.3 | K43: =J43 -> 166715.3 | L43: ='Projeções - NIM'!L62 -> 200064.14 | M43: ='Projeções - NIM'!M62 -> 200064.14 | N43: ='Projeções - NIM'!N62 -> 223737.71 | O43: ='Projeções - NIM'!O62 -> 244661.12 | P43: ='Projeções - NIM'!P62 -> 266171.9 | Q43: ='Projeções - NIM'!Q62 -> 287908.06 | R43: ='Projeções - NIM'!R62 -> 309928.28 | S43: ='Projeções - NIM'!S62 -> 332220.24 | ... V43: ='Projeções - NIM'!V62 -> 402357.91 | W43: Projetado na aba "-Projeções - NIM".
E44: % dos Ativos Remuneráveis | F44: =F43/F$11 -> 0.0079277638 | G44: =G43/G$11 -> 0.0067552884 | H44: =H43/H$11 -> 0.0057466403 | I44: =I43/I$11 -> 0.0039386553 | J44: =J43/J$11 -> 0.003511483 | K44: =K43/K$11 -> 0.003511483 | L44: =L43/L$11 -> 0.003511483 | M44: =M43/M$11 -> 0.003511483 | ... V44: =V43/V$11 -> 0.003511483
E45: Provisões para Perdas Associadas ao Risco de Crédito | F45: =SUM(F47:F49) -> -294094 | G45: =SUM(G47:G49) -> -371331 | H45: =SUM(H47:H49) -> -603555 | I45: =SUM(I47:I49) -> -749908 | J45: =SUM(J47:J49) -> -910522.58 | K45: =SUM(K47:K49) -> -910522.58 | L45: =L46*L$11 -> -1092658.6 | M45: =M46*M$11 -> -1092658.6 | N45: =N46*N$11 -> -1221952.8 | O45: =O46*O$11 -> -1336226.9 | P45: =P46*P$11 -> -1453708.9 | Q45: =Q46*Q$11 -> -1572421.9 | R45: =R46*R$11 -> -1692686.2 | S45: =S46*S$11 -> -1814434.7 | ... V45: =V46*V$11 -> -2197494.5
E46: % dos Ativos Remuneráveis | F46: =F45/F$11 -> -0.015342703 | G46: =G45/G$11 -> -0.015136938 | H46: =H45/H$11 -> -0.017971427 | I46: =I45/I$11 -> -0.016884731 | J46: =J45/J$11 -> -0.019178111 | K46: =K45/K$11 -> -0.019178111 | L46: =K46 -> -0.019178111 | M46: =L46 -> -0.019178111 | N46: =M46 -> -0.019178111 | O46: =N46 -> -0.019178111 | P46: =O46 -> -0.019178111 | Q46: =P46 -> -0.019178111 | R46: =Q46 -> -0.019178111 | S46: =R46 -> -0.019178111 | ... V46: =U46 -> -0.019178111 | W46: O percentual se manterá constante igual ao último ano.
E47: Provisão para Operações de Crédito | F47: -285614 | G47: -363093 | H47: -588039 | I47: -748734 | J47: -909187.42 | K47: =J47 -> -909187.42 | L47: - | M47: - | N47: - | O47: - | P47: - | Q47: - | R47: - | S47: - | T47: - | U47: - | V47: - | W47: .
E48: Provisão para Outros Créditos | F48: -63 | G48: 0 | H48: 0 | I48: 0 | J48: 0 | K48: =J48 -> 0 | L48: - | M48: - | N48: - | O48: - | P48: - | Q48: - | R48: - | S48: - | T48: - | U48: - | V48: -
E49: Provisão para Câmbio | F49: -8417 | G49: -8238 | H49: -15516 | I49: -1174 | J49: -1335.1571 | K49: =J49 -> -1335.1571 | L49: - | M49: - | N49: - | O49: - | P49: - | Q49: - | R49: - | S49: - | T49: - | U49: - | V49: -
E50: Outros Ativos | F50: 50587 | G50: 47744 | H50: 54855 | I50: 59565 | J50: 79007 | K50: =J50 -> 79007 | L50: =L51*L$11 -> 94811.138 | M50: =M51*M$11 -> 94811.138 | N50: =N51*N$11 -> 106030.13 | O50: =O51*O$11 -> 115945.81 | P50: =P51*P$11 -> 126139.85 | Q50: =Q51*Q$11 -> 136440.7 | R50: =R51*R$11 -> 146876.16 | S50: =S51*S$11 -> 157440.4 | ... V50: =V51*V$11 -> 190678.9
E51: % dos Ativos Remuneráveis | F51: =F50/F$11 -> 0.0026390926 | G51: =G50/G$11 -> 0.0019462366 | H51: =H50/H$11 -> 0.00163336 | I51: =I50/I$11 -> 0.0013411499 | J51: =J50/J$11 -> 0.0016641048 | K51: =K50/K$11 -> 0.0016641048 | L51: =K51 -> 0.0016641048 | M51: =L51 -> 0.0016641048 | N51: =M51 -> 0.0016641048 | O51: =N51 -> 0.0016641048 | P51: =O51 -> 0.0016641048 | Q51: =P51 -> 0.0016641048 | R51: =Q51 -> 0.0016641048 | S51: =R51 -> 0.0016641048 | ... V51: =U51 -> 0.0016641048
E52: Ativos Fiscais Correntes e Diferidos | F52: =SUM(F54:F55) -> 1569036 | G52: =SUM(G54:G55) -> 1445466 | H52: =SUM(H54:H55) -> 1282672 | I52: =SUM(I54:I55) -> 1222403 | J52: =SUM(J54:J55) -> 1291788.6 | K52: =SUM(K54:K55) -> 1291788.6 | L52: =L53*L$11 -> 1550191.1 | M52: =M53*M$11 -> 1550191.1 | N52: =N53*N$11 -> 1733625.1 | O52: =O53*O$11 -> 1895749.5 | P52: =P53*P$11 -> 2062425.2 | Q52: =Q53*Q$11 -> 2230847.2 | R52: =R53*R$11 -> 2401470.2 | S52: =S53*S$11 -> 2574198.8 | ... V52: =V53*V$11 -> 3117658.5 | W52: O percentual se manterá constante igual ao último ano.
E53: % dos Ativos Remuneráveis | F53: =F52/F$11 -> 0.08185564 | G53: =G52/G$11 -> 0.058922982 | H53: =H52/H$11 -> 0.038192784 | I53: =I52/I$11 -> 0.027523304 | J53: =J52/J$11 -> 0.027208623 | K53: =K52/K$11 -> 0.027208623 | L53: =K53 -> 0.027208623 | M53: =L53 -> 0.027208623 | N53: =M53 -> 0.027208623 | O53: =N53 -> 0.027208623 | P53: =O53 -> 0.027208623 | Q53: =P53 -> 0.027208623 | R53: =Q53 -> 0.027208623 | S53: =R53 -> 0.027208623 | ... V53: =U53 -> 0.027208623
E54: Crédito Tributário | F54: 1473792 | G54: 1346769 | H54: 1187580 | I54: 1210630 | J54: 1278936.1 | K54: =J54 -> 1278936.1 | L54: - | M54: - | N54: - | O54: - | P54: - | Q54: - | R54: - | S54: - | T54: - | U54: - | V54: -
E55: Impostos e Contribuição a Compensar | F55: 95244 | G55: 98697 | H55: 95092 | I55: 11773 | J55: 12852.568 | K55: =J55 -> 12852.568 | L55: - | M55: - | N55: - | O55: - | P55: - | Q55: - | R55: - | S55: - | T55: - | U55: - | V55: -
E56: Permanente | F56: =SUM(F57,F59,F61,F65) -> 248256 | G56: =SUM(G57,G59,G61,G65) -> 223436 | H56: =SUM(H57,H59,H61,H65) -> 213042 | I56: =SUM(I57,I59,I61,I65) -> 205834 | J56: =SUM(J57,J59,J61,J65) -> 202550.24 | K56: =SUM(K57,K59,K61,K65) -> 202550.24 | L56: =SUM(L57,L59,L61,L65) -> 243067.31 | M56: =SUM(M57,M59,M61,M65) -> 243067.31 | ... V56: =SUM(V57,V59,V61,V65) -> 488843.5
E57: Imobilizado de Uso | F57: 354232 | G57: 359187 | H57: 371210 | I57: 381417 | J57: 387978.99 | K57: =J57 -> 387978.99 | L57: =L58*L$11 -> 465588.24 | M57: =M58*M$11 -> 465588.24 | N57: =N58*N$11 -> 520681.23 | O57: =O58*O$11 -> 569374.1 | P57: =P58*P$11 -> 619433.87 | Q57: =Q58*Q$11 -> 670018.16 | R57: =R58*R$11 -> 721263.49 | S57: =S58*S$11 -> 773141.24 | ... V57: =V58*V$11 -> 936365.25
E58: % dos Ativos Remuneráveis | F58: =F57/F$11 -> 0.018480065 | G58: =G57/G$11 -> 0.0146419 | H58: =H57/H$11 -> 0.011053132 | I58: =I57/I$11 -> 0.0085878848 | J58: =J57/J$11 -> 0.008171905 | K58: =K57/K$11 -> 0.008171905 | L58: =K58 -> 0.008171905 | M58: =L58 -> 0.008171905 | N58: =M58 -> 0.008171905 | O58: =N58 -> 0.008171905 | P58: =O58 -> 0.008171905 | Q58: =P58 -> 0.008171905 | R58: =Q58 -> 0.008171905 | S58: =R58 -> 0.008171905 | ... V58: =U58 -> 0.008171905 | W58: O percentual se manterá constante igual ao último ano.
E59: Intangível | F59: 326598 | G59: 344168 | H59: 371503 | I59: 388482 | J59: 388900.18 | K59: =J59 -> 388900.18 | L59: =L60*L$11 -> 466693.7 | M59: =M60*M$11 -> 466693.7 | N59: =N60*N$11 -> 521917.5 | O59: =O60*O$11 -> 570725.98 | P59: =P60*P$11 -> 620904.61 | Q59: =Q60*Q$11 -> 671609 | R59: =R60*R$11 -> 722976 | S59: =S60*S$11 -> 774976.93 | ... V59: =V60*V$11 -> 938588.49
E60: % dos Ativos Remuneráveis | F60: =F59/F$11 -> 0.017038416 | G60: =G59/G$11 -> 0.014029666 | H60: =H59/H$11 -> 0.011061857 | I60: =I59/I$11 -> 0.0087469585 | J60: =J59/J$11 -> 0.0081913078 | K60: =K59/K$11 -> 0.0081913078 | L60: =K60 -> 0.0081913078 | M60: =L60 -> 0.0081913078 | N60: =M60 -> 0.0081913078 | O60: =N60 -> 0.0081913078 | P60: =O60 -> 0.0081913078 | Q60: =P60 -> 0.0081913078 | R60: =Q60 -> 0.0081913078 | S60: =R60 -> 0.0081913078 | ... V60: =U60 -> 0.0081913078 | W60: O percentual se manterá constante igual ao último ano.
E61: Depreciações e Amortizações | F61: =SUM(F63:F64) -> -411745 | G61: =SUM(G63:G64) -> -462460 | H61: =SUM(H63:H64) -> -512212 | I61: =SUM(I63:I64) -> -556042 | J61: =SUM(J63:J64) -> -566305.74 | K61: =SUM(K63:K64) -> -566305.74 | L61: =L62*L$11 -> -679586.52 | M61: =M62*M$11 -> -679586.52 | N61: =N62*N$11 -> -760001.9 | O61: =O62*O$11 -> -831075.47 | P61: =P62*P$11 -> -904144.21 | Q61: =Q62*Q$11 -> -977978.54 | R61: =R62*R$11 -> -1052777.8 | S61: =S62*S$11 -> -1128500.1 | ... V61: =V62*V$11 -> -1366746.7
E62: % dos Ativos Remuneráveis | F62: =F61/F$11 -> -0.021480483 | G62: =G61/G$11 -> -0.018851721 | H62: =H61/H$11 -> -0.015251602 | I62: =I61/I$11 -> -0.012519695 | J62: =J61/J$11 -> -0.011927957 | K62: =K61/K$11 -> -0.011927957 | L62: =K62 -> -0.011927957 | M62: =L62 -> -0.011927957 | N62: =M62 -> -0.011927957 | O62: =N62 -> -0.011927957 | P62: =O62 -> -0.011927957 | Q62: =P62 -> -0.011927957 | R62: =Q62 -> -0.011927957 | S62: =R62 -> -0.011927957 | ... V62: =U62 -> -0.011927957 | W62: O percentual se manterá constante igual ao último ano.
E63: Depreciação Acumulada de Imobilizado de Uso | F63: -208899 | G63: -230102 | H63: -251396 | I63: -269271 | J63: -273400.04 | K63: =J63 -> -273400.04 | L63: - | M63: - | N63: - | O63: - | P63: - | Q63: - | R63: - | S63: - | T63: - | U63: - | V63: -
E64: Amortização Acumulada de Intangível | F64: -202846 | G64: -232358 | H64: -260816 | I64: -286771 | J64: -292905.7 | K64: =J64 -> -292905.7 | L64: - | M64: - | N64: - | O64: - | P64: - | Q64: - | R64: - | S64: - | T64: - | U64: - | V64: -
E65: Provisão para Redução ao Valor Recuperável de Ativos | F65: =F67 -> -20829 | G65: =G67 -> -17459 | H65: =H67 -> -17459 | I65: =I67 -> -8023 | J65: =J67 -> -8023.1927 | K65: =K67 -> -8023.1927 | L65: =L66*L$11 -> -9628.1093 | M65: =M66*M$11 -> -9628.1093 | N65: =N66*N$11 -> -10767.402 | O65: =O66*O$11 -> -11774.344 | P65: =P66*P$11 -> -12809.553 | Q65: =Q66*Q$11 -> -13855.608 | R65: =R66*R$11 -> -14915.333 | S65: =S66*S$11 -> -15988.137 | ... V65: =V66*V$11 -> -19363.52
E66: % dos Ativos Remuneráveis | F66: =F65/F$11 -> -0.0010866361 | G66: =G65/G$11 -> -0.00071169874 | H66: =H65/H$11 -> -0.0005198584 | I66: =I65/I$11 -> -0.00018064376 | J66: =J65/J$11 -> -0.00016899051 | K66: =K65/K$11 -> -0.00016899051 | L66: =K66 -> -0.00016899051 | M66: =L66 -> -0.00016899051 | N66: =M66 -> -0.00016899051 | O66: =N66 -> -0.00016899051 | P66: =O66 -> -0.00016899051 | Q66: =P66 -> -0.00016899051 | R66: =Q66 -> -0.00016899051 | S66: =R66 -> -0.00016899051 | ... V66: =U66 -> -0.00016899051 | W66: O percentual se manterá constante igual ao último ano.
E67: Provisão para Perdas em Aplicações Interfinanceiras de Liquidez | F67: -20829 | G67: -17459 | H67: -17459 | I67: -8023 | J67: -8023.1927 | K67: =J67 -> -8023.1927 | L67: =L65 -> -9628.1093 | M67: =M65 -> -9628.1093 | N67: =N65 -> -10767.402 | O67: =O65 -> -11774.344 | P67: =P65 -> -12809.553 | Q67: =Q65 -> -13855.608 | R67: =R65 -> -14915.333 | S67: =S65 -> -15988.137 | ... V67: =V65 -> -19363.52
E68: Passivo Total | F68: =F69+F124 -> 18398912 | G68: =G69 -> 23007532 | H68: =H69 -> 29754519 | I68: =I69 -> 39328999 | J68: =J69 -> 42287634 | K68: =K69 -> 42287634 | L68: =L12-L125 -> 51262623 | M68: =M12-M125 -> 51262623 | N68: =N12-N125 -> 57046876 | O68: =O12-O125 -> 62102529 | P68: =P12-P125 -> 67267931 | Q68: =Q12-Q125 -> 72450881 | R68: =R12-R125 -> 77664547 | S68: =S12-S125 -> 82904350 | ... V68: =V12-V125 -> 99163527
E69: Circulante e Exigível a Longo Prazo | F69: =SUM(F70,F112,F120,F124) -> 18398912 | G69: =SUM(G70,G112,G120,G124) -> 23007532 | H69: =SUM(H70,H112,H120,H124) -> 29754519 | I69: =SUM(I70,I112,I120,I124) -> 39328999 | J69: =SUM(J70,J112,J120,J124) -> 42287634 | K69: =SUM(K70,K112,K120,K124) -> 42287634 | L69: =SUM(L70,L112,L120,L124) -> 51262623 | M69: =SUM(M70,M112,M120,M124) -> 51262623 | ... V69: =SUM(V70,V112,V120,V124) -> 99163527
E70: Depósitos e Demais Instrumentos Financeiros | F70: =SUM(F72,F84,F86,F88,F90,F92,F94,F96,F98,F100,F106,F108,F110) -> 14472736 | G70: =SUM(G72,G84,G86,G88,G90,G92,G94,G96,G98,G100,G106,G108,G110) -> 19267380 | H70: =SUM(H72,H84,H86,H88,H90,H92,H94,H96,H98,H100,H106,H108,H110) -> 25656298 | I70: =SUM(I72,I84,I86,I88,I90,I92,I94,I96,I98,I100,I106,I108,I110) -> 35490828 | J70: =SUM(J72,J84,J86,J88,J90,J92,J94,J96,J98,J100,J106,J108,J110) -> 38512124 | K70: =SUM(K72,K84,K86,K88,K90,K92,K94,K96,K98,K100,K106,K108,K110) -> 38512124 | L70: =SUM(L72,L84,L86,L88,L90,L92,L94,L96,L98,L100,L106,L108,L110) -> 46205443 | M70: =SUM(M72,M84,M86,M88,M90,M92,M94,M96,M98,M100,M106,M108,M110) -> 46205443 | ... V70: =SUM(V72,V84,V86,V88,V90,V92,V94,V96,V98,V100,V106,V108,V110) -> 92925826
E71: % dos Ativos Remuneráveis | F71: =F70/F$11 -> 0.75503371 | G71: =G70/G$11 -> 0.78541555 | H71: =H70/H$11 -> 0.76394078 | I71: =I70/I$11 -> 0.79910214 | J71: =J70/J$11 -> 0.81117129 | K71: =K70/K$11 -> 0.81117129 | L71: =L70/L$11 -> 0.81098804 | M71: =M70/M$11 -> 0.81098804 | ... V71: =V70/V$11 -> 0.81098804
E72: Depósitos | F72: =SUM(F74:F77) -> 5829618 | G72: =SUM(G74:G77) -> 6420521 | H72: =SUM(H74:H77) -> 8338410 | I72: =SUM(I74:I77) -> 11322771 | J72: =SUM(J74:J77) -> 12068645 | K72: =SUM(K74:K77) -> 12068645 | L72: =SUM(L74:L77) -> 14479520 | M72: =SUM(M74:M77) -> 14479520 | ... V72: =SUM(V74:V77) -> 29120409
E73: % dos Ativos Remuneráveis | F73: =F72/F$11 -> 0.30412757 | G73: =G72/G$11 -> 0.26172614 | H73: =H72/H$11 -> 0.24828412 | I73: =I72/I$11 -> 0.25494053 | J73: =J72/J$11 -> 0.25419887 | K73: =K72/K$11 -> 0.25419887 | L73: =L72/L$11 -> 0.25414144 | M73: =M72/M$11 -> 0.25414144 | ... V73: =V72/V$11 -> 0.25414144
E74: Depósitos à Vista | F74: 2101873 | G74: 2000942 | H74: 1785604 | I74: 2349405 | J74: 1905651 | K74: =J74 -> 1905651 | L74: ='Projeções - NIM'!L66 -> 2286330.6 | M74: ='Projeções - NIM'!M66 -> 2286330.6 | N74: ='Projeções - NIM'!N66 -> 2556871.8 | O74: ='Projeções - NIM'!O66 -> 2795984.4 | P74: ='Projeções - NIM'!P66 -> 3041809.3 | Q74: ='Projeções - NIM'!Q66 -> 3290209.9 | R74: ='Projeções - NIM'!R66 -> 3541856.6 | S74: ='Projeções - NIM'!S66 -> 3796609 | ... V74: ='Projeções - NIM'!V66 -> 4598141.4 | W74: Projetado na aba "Projeções - NIM".
E75: Depósitos de Poupança | F75: 766226 | G75: 792764 | H75: 749268 | I75: 725983 | J75: 722973 | K75: =J75 -> 722973 | L75: ='Projeções - NIM'!L68 -> 867396.66 | M75: ='Projeções - NIM'!M68 -> 867396.66 | N75: ='Projeções - NIM'!N68 -> 970035.59 | O75: ='Projeções - NIM'!O68 -> 1060751 | P75: ='Projeções - NIM'!P68 -> 1154013 | Q75: ='Projeções - NIM'!Q68 -> 1248252.1 | R75: ='Projeções - NIM'!R68 -> 1343722.8 | S75: ='Projeções - NIM'!S68 -> 1440371.7 | ... V75: ='Projeções - NIM'!V68 -> 1744460.1 | W75: Projetado na aba "Projeções - NIM".
E76: Depósitos Interfinanceiros | F76: 7505 | G76: 41672 | H76: 43885 | I76: 379287 | J76: 362389 | K76: =J76 -> 362389 | L76: ='Projeções - NIM'!L70 -> 434781.12 | M76: ='Projeções - NIM'!M70 -> 434781.12 | N76: ='Projeções - NIM'!N70 -> 486228.71 | O76: ='Projeções - NIM'!O70 -> 531699.66 | P76: ='Projeções - NIM'!P70 -> 578447.06 | Q76: ='Projeções - NIM'!Q70 -> 625684.28 | R76: ='Projeções - NIM'!R70 -> 673538.8 | S76: ='Projeções - NIM'!S70 -> 721983.89 | ... V76: ='Projeções - NIM'!V70 -> 874407.67 | W76: Projetado na aba "Projeções - NIM".
E77: Depósitos a Prazo | F77: =SUM(F78:F80) -> 2954014 | G77: =SUM(G78:G80) -> 3585143 | H77: =SUM(H78:H80) -> 5759653 | I77: =SUM(I78:I80) -> 7868096 | J77: =SUM(J78:J80) -> 9077632 | K77: =SUM(K78:K80) -> 9077632 | L77: =SUM(L78:L80) -> 10891012 | M77: =SUM(M78:M80) -> 10891012 | ... V77: =SUM(V78:V80) -> 21903400
E78: Depósitos a Prazo | F78: 1551955 | G78: 1842803 | H78: 1903078 | I78: 2430848 | J78: 2716567 | K78: =J78 -> 2716567 | L78: ='Projeções - NIM'!L72 -> 3259238.1 | M78: ='Projeções - NIM'!M72 -> 3259238.1 | N78: ='Projeções - NIM'!N72 -> 3644903.3 | O78: ='Projeções - NIM'!O72 -> 3985766 | P78: ='Projeções - NIM'!P72 -> 4336197.3 | Q78: ='Projeções - NIM'!Q72 -> 4690300.4 | R78: ='Projeções - NIM'!R72 -> 5049030.9 | S78: ='Projeções - NIM'!S72 -> 5412188.6 | ... V78: ='Projeções - NIM'!V72 -> 6554798.9 | W78: Projetado na aba "Projeções - NIM".
E79: Depósitos Judiciais com Remuneração | F79: 83366 | G79: 64486 | H79: 68304 | I79: 73698 | J79: 76057 | K79: =J79 -> 76057 | L79: ='Projeções - NIM'!L74 -> 91250.417 | M79: ='Projeções - NIM'!M74 -> 91250.417 | N79: ='Projeções - NIM'!N74 -> 102048.07 | O79: ='Projeções - NIM'!O74 -> 111591.36 | P79: ='Projeções - NIM'!P74 -> 121402.55 | Q79: ='Projeções - NIM'!Q74 -> 131316.54 | R79: ='Projeções - NIM'!R74 -> 141360.09 | S79: ='Projeções - NIM'!S74 -> 151527.58 | ... V79: ='Projeções - NIM'!V74 -> 183517.78 | W79: Projetado na aba "Projeções - NIM".
E80: Depósitos Especiais com Remuneração | F80: =SUM(F81:F83) -> 1318693 | G80: =SUM(G81:G83) -> 1677854 | H80: =SUM(H81:H83) -> 3788271 | I80: =SUM(I81:I83) -> 5363550 | J80: =SUM(J81:J83) -> 6285008 | K80: =SUM(K81:K83) -> 6285008 | L80: ='Projeções - NIM'!L76 -> 7540523.6 | M80: ='Projeções - NIM'!M76 -> 7540523.6 | N80: ='Projeções - NIM'!N76 -> 8432792.7 | O80: ='Projeções - NIM'!O76 -> 9221407.4 | P80: ='Projeções - NIM'!P76 -> 10032160 | Q80: ='Projeções - NIM'!Q76 -> 10851407 | R80: ='Projeções - NIM'!R76 -> 11681361 | S80: ='Projeções - NIM'!S76 -> 12521557 | ... V80: ='Projeções - NIM'!V76 -> 15165083 | W80: Projetado na aba "Projeções - NIM".
E81: Sudam | F81: 780922 | G81: 1026339 | H81: 3056401 | I81: 4487338 | J81: 5388808 | K81: =J81 -> 5388808 | L81: - | M81: - | N81: - | O81: - | P81: - | Q81: - | R81: - | S81: - | T81: - | U81: - | V81: -
E82: Finam | F82: 522636 | G82: 631034 | H82: 704354 | I82: 840666 | J82: 859412 | K82: =J82 -> 859412 | L82: - | M82: - | N82: - | O82: - | P82: - | Q82: - | R82: - | S82: - | T82: - | U82: - | V82: -
E83: Outros | F83: 15135 | G83: 20481 | H83: 27516 | I83: 35546 | J83: 36788 | K83: =J83 -> 36788 | L83: - | M83: - | N83: - | O83: - | P83: - | Q83: - | R83: - | S83: - | T83: - | U83: - | V83: -
E84: Captações no Mercado Aberto | F84: 251713 | G84: 200018 | H84: 70041 | I84: 0 | J84: 99993.602 | K84: =J84 -> 99993.602 | L84: ='Projeções - NIM'!L78 -> 119968.68 | M84: ='Projeções - NIM'!M78 -> 119968.68 | N84: ='Projeções - NIM'!N78 -> 134164.56 | O84: ='Projeções - NIM'!O78 -> 146711.31 | P84: ='Projeções - NIM'!P78 -> 159610.27 | Q84: ='Projeções - NIM'!Q78 -> 172644.38 | R84: ='Projeções - NIM'!R78 -> 185848.83 | S84: ='Projeções - NIM'!S78 -> 199216.23 | ... V84: ='Projeções - NIM'!V78 -> 241274.36
E85: % dos Ativos Remuneráveis | F85: =F84/F$11 -> 0.013131712 | G85: =G84/G$11 -> 0.0081535345 | H85: =H84/H$11 -> 0.0020855377 | I85: =I84/I$11 -> 0 | J85: =J84/J$11 -> 0.0021061404 | K85: =K84/K$11 -> 0.0021061404 | L85: =L84/L$11 -> 0.0021056646 | M85: =M84/M$11 -> 0.0021056646 | ... V85: =V84/V$11 -> 0.0021056646
E86: Letra de Crédito do Agronegócio | F86: 213703 | G86: 251192 | H86: 319315 | I86: 778601 | J86: 813705.69 | K86: =J86 -> 813705.69 | L86: ='Projeções - NIM'!L80 -> 976254.44 | M86: ='Projeções - NIM'!M80 -> 976254.44 | N86: ='Projeções - NIM'!N80 -> 1091774.5 | O86: ='Projeções - NIM'!O80 -> 1193874.6 | P86: ='Projeções - NIM'!P80 -> 1298840.9 | Q86: ='Projeções - NIM'!Q80 -> 1404907 | R86: ='Projeções - NIM'!R80 -> 1512359.2 | S86: ='Projeções - NIM'!S80 -> 1621137.5 | ... V86: ='Projeções - NIM'!V80 -> 1963388.8 | W86: Projetado na aba "Projeções - NIM".
E87: % dos Ativos Remuneráveis | F87: =F86/F$11 -> 0.011148754 | G87: =G86/G$11 -> 0.010239592 | H87: =H86/H$11 -> 0.0095079092 | I87: =I86/I$11 -> 0.017530775 | J87: =J86/J$11 -> 0.017138881 | K87: =K86/K$11 -> 0.017138881 | L87: =L86/L$11 -> 0.017135009 | M87: =M86/M$11 -> 0.017135009 | ... V87: =V86/V$11 -> 0.017135009
E88: Relações Interfinanceiras e Interdependências | F88: 9033 | G88: 4792 | H88: 10514 | I88: 9210 | J88: 29121.58 | K88: =J88 -> 29121.58 | L88: ='Projeções - NIM'!L82 -> 34939.011 | M88: ='Projeções - NIM'!M82 -> 34939.011 | N88: ='Projeções - NIM'!N82 -> 39073.339 | O88: ='Projeções - NIM'!O82 -> 42727.385 | P88: ='Projeções - NIM'!P82 -> 46484.006 | Q88: ='Projeções - NIM'!Q82 -> 50279.989 | R88: ='Projeções - NIM'!R82 -> 54125.578 | S88: ='Projeções - NIM'!S82 -> 58018.626 | ... V88: ='Projeções - NIM'!V82 -> 70267.401 | W88: Projetado na aba "Projeções - NIM".
E89: % dos Ativos Remuneráveis | F89: =F88/F$11 -> 0.00047124604 | G89: =G88/G$11 -> 0.00019534111 | H89: =H88/H$11 -> 0.00031306439 | I89: =I88/I$11 -> 0.00020736994 | J89: =J88/J$11 -> 0.0006133806 | K89: =K88/K$11 -> 0.0006133806 | L89: =L88/L$11 -> 0.00061324203 | M89: =M88/M$11 -> 0.00061324203 | ... V89: =V88/V$11 -> 0.00061324203
E90: Obrigações por Empréstimo | F90: 54454 | G90: 71095 | H90: 44758 | I90: 30892 | J90: 46713.626 | K90: =J90 -> 46713.626 | L90: ='Projeções - NIM'!L84 -> 56045.306 | M90: ='Projeções - NIM'!M84 -> 56045.306 | N90: ='Projeções - NIM'!N84 -> 62677.139 | O90: ='Projeções - NIM'!O84 -> 68538.556 | P90: ='Projeções - NIM'!P84 -> 74564.514 | Q90: ='Projeções - NIM'!Q84 -> 80653.61 | R90: ='Projeções - NIM'!R84 -> 86822.28 | S90: ='Projeções - NIM'!S84 -> 93067.078 | ... V90: ='Projeções - NIM'!V84 -> 112715.21 | W90: Projetado na aba "Projeções - NIM".
E91: % dos Ativos Remuneráveis | F91: =F90/F$68 -> 0.0029596315 | G91: =G90/G$68 -> 0.003090075 | H91: =H90/H$68 -> 0.0015042421 | I91: =I90/I$68 -> 0.00078547639 | J91: =J90/J$68 -> 0.001104664 | K91: =K90/K$68 -> 0.001104664 | L91: =L90/L$68 -> 0.0010932977 | M91: =M90/M$68 -> 0.0010932977 | ... V91: =V90/V$68 -> 0.00113666
E92: Obrigações por Repasses do País-Instituições Oficiais | F92: 736754 | G92: 666289 | H92: 600079 | I92: 438216 | J92: 422872.77 | K92: =J92 -> 422872.77 | L92: ='Projeções - NIM'!L86 -> 507347.34 | M92: ='Projeções - NIM'!M86 -> 507347.34 | N92: ='Projeções - NIM'!N86 -> 567381.69 | O92: ='Projeções - NIM'!O86 -> 620441.87 | P92: ='Projeções - NIM'!P86 -> 674991.55 | Q92: ='Projeções - NIM'!Q86 -> 730112.79 | R92: ='Projeções - NIM'!R86 -> 785954.37 | S92: ='Projeções - NIM'!S86 -> 842485.09 | ... V92: ='Projeções - NIM'!V86 -> 1020348.8 | W92: Projetado na aba "Projeções - NIM".
E93: % dos Ativos Remuneráveis | F93: =F92/F$11 -> 0.038436002 | G93: =G92/G$11 -> 0.027160607 | H93: =H92/H$11 -> 0.017867925 | I93: =I92/I$11 -> 0.0098667561 | J93: =J92/J$11 -> 0.008906864 | K93: =K92/K$11 -> 0.008906864 | L93: =L92/L$11 -> 0.0089048519 | M93: =M92/M$11 -> 0.0089048519 | ... V93: =V92/V$11 -> 0.0089048519
E94: Cobrança de Arrecadação de Tributos e Assemelhados | F94: 1568 | G94: 2787 | H94: 3220 | I94: 3392 | J94: 4906.5243 | K94: =J94 -> 4906.5243 | L94: ='Projeções - NIM'!L88 -> 5886.669 | M94: ='Projeções - NIM'!M88 -> 5886.669 | N94: ='Projeções - NIM'!N88 -> 6583.2378 | O94: ='Projeções - NIM'!O88 -> 7198.8865 | P94: ='Projeções - NIM'!P88 -> 7831.8177 | Q94: ='Projeções - NIM'!Q88 -> 8471.3805 | R94: ='Projeções - NIM'!R88 -> 9119.3013 | S94: ='Projeções - NIM'!S88 -> 9775.2181 | ... V94: ='Projeções - NIM'!V88 -> 11838.942 | W94: Projetado na aba "Projeções - NIM".
E95: % dos Ativos Remuneráveis | F95: =F94/F$11 -> 8.1801592e-05 | G95: =G94/G$11 -> 0.00011360928 | H95: =H94/H$11 -> 9.5878576e-05 | I95: =I94/I$11 -> 7.6373379e-05 | J95: =J94/J$11 -> 0.0001033449 | K95: =K94/K$11 -> 0.0001033449 | L95: =L94/L$11 -> 0.00010332155 | M95: =M94/M$11 -> 0.00010332155 | ... V95: =V94/V$11 -> 0.00010332155
E96: Carteira de Câmbio | F96: 54 | G96: 1 | H96: 0 | I96: 0 | J96: 0 | K96: =J96 -> 0 | L96: ='Projeções - NIM'!L90 -> 0 | M96: ='Projeções - NIM'!M90 -> 0 | N96: ='Projeções - NIM'!N90 -> 0 | O96: ='Projeções - NIM'!O90 -> 0 | P96: ='Projeções - NIM'!P90 -> 0 | Q96: ='Projeções - NIM'!Q90 -> 0 | R96: ='Projeções - NIM'!R90 -> 0 | S96: ='Projeções - NIM'!S90 -> 0 | ... V96: ='Projeções - NIM'!V90 -> 0 | W96: Projetado na aba "Projeções - NIM".
E97: % dos Ativos Remuneráveis | F97: =F96/F$11 -> 2.8171467e-06 | G97: =G96/G$11 -> 4.0764004e-08 | H97: =H96/H$11 -> 0 | I97: =I96/I$11 -> 0 | J97: =J96/J$11 -> 0 | K97: =K96/K$11 -> 0 | L97: =L96/L$11 -> 0 | M97: =M96/M$11 -> 0 | ... V97: =V96/V$11 -> 0
E98: Sociais e Estatutárias | F98: 100326 | G98: 250682 | H98: 377990 | I98: 452062 | J98: 458259.8 | K98: =J98 -> 458259.8 | L98: ='Projeções - NIM'!L92 -> 549803.4 | M98: ='Projeções - NIM'!M92 -> 549803.4 | N98: ='Projeções - NIM'!N92 -> 614861.57 | O98: ='Projeções - NIM'!O92 -> 672361.96 | P98: ='Projeções - NIM'!P92 -> 731476.49 | Q98: ='Projeções - NIM'!Q92 -> 791210.41 | R98: ='Projeções - NIM'!R92 -> 851724.95 | S98: ='Projeções - NIM'!S92 -> 912986.3 | ... V98: ='Projeções - NIM'!V92 -> 1105734.1 | W98: Projetado na aba "Projeções - NIM".
E99: % dos Ativos Remuneráveis | F99: =F98/F$11 -> 0.0052339455 | G99: =G98/G$11 -> 0.010218802 | H99: =H98/H$11 -> 0.011255013 | I99: =I98/I$11 -> 0.010178509 | J99: =J98/J$11 -> 0.0096522121 | K99: =K98/K$11 -> 0.0096522121 | L99: =L98/L$11 -> 0.0096500316 | M99: =M98/M$11 -> 0.0096500316 | ... V99: =V98/V$11 -> 0.0096500316
E100: Fundos Financeiros e de Desenvolvimento | F100: =SUM(F102:F105) -> 6135762 | G100: =SUM(G102:G105) -> 9253604 | H100: =SUM(H102:H105) -> 15738193 | I100: =SUM(I102:I105) -> 22300619 | J100: =SUM(J102:J105) -> 24418444 | K100: =SUM(K102:K105) -> 24418444 | L100: ='Projeções - NIM'!L94 -> 29296359 | M100: ='Projeções - NIM'!M94 -> 29296359 | N100: ='Projeções - NIM'!N94 -> 32762994 | O100: ='Projeções - NIM'!O94 -> 35826911 | P100: ='Projeções - NIM'!P94 -> 38976838 | Q100: ='Projeções - NIM'!Q94 -> 42159769 | R100: ='Projeções - NIM'!R94 -> 45384295 | S100: ='Projeções - NIM'!S94 -> 48648616 | ... V100: ='Projeções - NIM'!V94 -> 58919213 | W100: Projetado na aba "Projeções - NIM".
E101: % dos Ativos Remuneráveis | F101: =F100/F$11 -> 0.32009892 | G101: =G100/G$11 -> 0.37721395 | H101: =H100/H$11 -> 0.46861973 | I101: =I100/I$11 -> 0.50211487 | J101: =J100/J$11 -> 0.51431961 | K101: =K100/K$11 -> 0.51431961 | L101: =L100/L$11 -> 0.51420342 | M101: =M100/M$11 -> 0.51420342 | ... V101: =V100/V$11 -> 0.51420342
E102: Constitucional de Financiamento do Norte (FNO) | F102: 5821928 | G102: 9074375 | H102: 15587883 | I102: 22176613 | J102: 24300006 | K102: =J102 -> 24300006 | L102: - | M102: - | N102: - | O102: - | P102: - | Q102: - | R102: - | S102: - | T102: - | U102: - | V102: -
E103: Marinha Mercante (FMM) | F103: 225343 | G103: 99058 | H103: 78296 | I103: 60081 | J103: 58778 | K103: =J103 -> 58778 | L103: - | M103: - | N103: - | O103: - | P103: - | Q103: - | R103: - | S103: - | T103: - | U103: - | V103: -
E104: Fundo de Desenvolvimento da Amazônia (FDA) | F104: 88413 | G104: 80093 | H104: 71936 | I104: 63847 | J104: 59582 | K104: =J104 -> 59582 | L104: - | M104: - | N104: - | O104: - | P104: - | Q104: - | R104: - | S104: - | T104: - | U104: - | V104: -
E105: Outros | F105: 78 | G105: 78 | H105: 78 | I105: 78 | J105: 78 | K105: =J105 -> 78 | L105: - | M105: - | N105: - | O105: - | P105: - | Q105: - | R105: - | S105: - | T105: - | U105: - | V105: -
...

Sheet Projeções - NIM
K4: =Dashboard!J4 -> Banco da Amazônia ($BAZA3)
A7: Páginas
A8: Dashboard
A9: Ke | E9: Ano | F9: 2020 | G9: 2021 | H9: 2022 | I9: 2023 | J9: 1T24 | K9: YTD24 | L9: YTG24 | M9: 2024 | N9: 2025 | O9: 2026 | P9: 2027 | Q9: 2028 | R9: 2029 | S9: 2030 | T9: 2031 | U9: 2032 | V9: 2033
A10: DRE + DCF | E10: Selic Acumulada | F10: 0.0276 | G10: 0.0442 | H10: 0.1233 | I10: 0.13028231 | J10: =(1+11.3506217851116%)^(1/4)-1 -> 0.027242932 | K10: =J10 -> 0.027242932 | L10: =(1+Ke!F10)^(3/4)-1 -> 0.076515317 | M10: =(1+K10)*(1+L10)-1 -> 0.10584275 | N10: =Ke!G10 -> 0.10535 | O10: =Ke!H10 -> 0.1087 | P10: =Ke!I10 -> 0.1116 | Q10: =Ke!J10 -> 0.11365 | R10: =Ke!K10 -> 0.115 | S10: =Ke!L10 -> 0.11584 | T10: =Ke!M10 -> 0.1163 | U10: =Ke!N10 -> 0.11651 | V10: =Ke!O10 -> 0.1166
A11: DRE - Cosif | E11: Inflação | F11: 0.0452 | G11: 0.1006 | H11: 0.0579 | I11: 0.046211139 | J11: =(1+0.42%)*(1+0.83%)*(1+0.16%)-1 -> 0.014154916 | K11: =J11 -> 0.014154916 | L11: =(1+M11)/(1+K11)-1 -> 0.025997097 | M11: =Ke!F12 -> 0.04052 | N11: =Ke!G12 -> 0.03862 | O11: =Ke!H12 -> 0.0437 | P11: =Ke!I12 -> 0.04665 | Q11: =Ke!J12 -> 0.04879 | R11: =Ke!K12 -> 0.05009 | S11: =Ke!L12 -> 0.05168 | T11: =Ke!M12 -> 0.05226 | ... V11: =Ke!O12 -> 0.0525
A12: Balanço Patrimonial | E12: Net Interest Margin (NIM) | F12: =F18/F38 -> 0.02499936 | G12: =G18/G38 -> 0.028516826 | H12: =H18/H38 -> 0.043138124 | I12: =I18/I38 -> 0.035552956 | J12: =J18/J38 -> 0.008104967 | K12: =K18/K38 -> 0.008104967 | L12: =L18/L38 -> 0.026140844 | M12: =M18/M38 -> 0.032894788 | ... V12: =V18/V38 -> 0.036150916
A13: Projeções - NIM | E13: Taxa de Juros de Longo Prazo (TJLP) | F13: 0.048443304 | G13: 0.048129775 | H13: 0.067714173 | I13: 0.070585229 | J13: =(1+6.54870868514916%)^(1/4)-1 -> 0.015984419 | K13: =J13 -> 0.015984419 | L13: =$F$226+$G$226*L10 -> 0.057626471 | M13: =(1+K13)*(1+L13)-1 -> 0.074532015 | N13: =$F$226+$G$226*N10 -> 0.064143174 | O13: =$F$226+$G$226*O10 -> 0.064900281 | P13: =$F$226+$G$226*P10 -> 0.065555688 | Q13: =$F$226+$G$226*Q10 -> 0.066018992 | R13: =$F$226+$G$226*R10 -> 0.066324095 | S13: =$F$226+$G$226*S10 -> 0.066513937 | T13: =$F$226+$G$226*T10 -> 0.066617898 | U13: =$F$226+$G$226*U10 -> 0.066665358 | V13: =$F$226+$G$226*V10 -> 0.066685699
A14: Projeções Trimestrais
A15: Painel de Índices
E17: Ano | F17: 2020 | G17: 2021 | H17: 2022 | I17: 2023 | J17: =J$9 -> 1T24 | K17: =K$9 -> YTD24 | L17: =L$9 -> YTG24 | M17: 2024 | N17: 2025 | O17: 2026 | P17: 2027 | Q17: 2028 | R17: 2029 | S17: 2030 | T17: 2031 | U17: 2032 | V17: 2033 | W17: CAGR 2020-2023 | X17: Premissas
E18: Margem Financeira Bruta | F18: =SUM(F20,F22) -> 479196 | G18: =SUM(G20,G22) -> 699559 | H18: =SUM(H20,H22) -> 1448757 | I18: =SUM(I20,I22) -> 1579027 | J18: =SUM(J20,J22) -> 384800.97 | K18: =SUM(K20,K22) -> 384800.97 | L18: =SUM(L20,L22) -> 1489355.2 | M18: =SUM(M20,M22) -> 1874156.2 | ... V18: =SUM(V20,V22) -> 4142297.4 | W18: =(I18/F18)^(1/3)-1 -> 0.48807718
E19: Margem Liquida de Juros | F19: =F18/F38 -> 0.02499936 | G19: =G18/G38 -> 0.028516826 | H19: =H18/H38 -> 0.043138124 | I19: =I18/I38 -> 0.035552956 | J19: =J18/J38 -> 0.008104967 | K19: =K18/K38 -> 0.008104967 | L19: =L18/L38 -> 0.026140844 | M19: =M18/M38 -> 0.032894788 | ... V19: =V18/V38 -> 0.036150916
E20: Receita de Juros | F20: =F113 -> 950361 | G20: =G113 -> 1411897 | H20: =H113 -> 3201712 | I20: =I113 -> 4124175 | J20: =J113 -> 1122727 | K20: =K113 -> 1122727 | L20: =L113 -> 3663504.2 | M20: =M113 -> 4786231.2 | ... V20: =V113 -> 10450711 | W20: =(I20/F20)^(1/3)-1 -> 0.63110841 | X20: Projetado na Tabela "Juros"
E21: Rentabilidade Média dos Ativos | F21: =F20/F38 -> 0.049579747 | G21: =G20/G38 -> 0.057554575 | H21: =H20/H38 -> 0.095334033 | I21: =I20/I38 -> 0.092858839 | J21: =J20/J38 -> 0.023647719 | K21: =K20/K38 -> 0.023647719 | L21: =L20/L38 -> 0.064301041 | M21: =M20/M38 -> 0.084006904 | ... V21: =V20/V38 -> 0.091206092
E22: Despesas de Juros | F22: =F130 -> -471165 | G22: =G130 -> -712338 | H22: =H130 -> -1752955 | I22: =I130 -> -2545148 | J22: =J130 -> -737926 | K22: =K130 -> -737926 | L22: =L130 -> -2174149 | M22: =M130 -> -2912075 | ... V22: =V130 -> -6308413.3 | W22: =(I22/F22)^(1/3)-1 -> 0.7546076 | X22: Projetado na Tabela "Juros"
E23: Custo Médio dos Passivos | F23: =F22/F64 -> -0.032555351 | G23: =G22/G64 -> -0.036971192 | H23: =H22/H64 -> -0.068324549 | I23: =I22/I64 -> -0.071712838 | J23: =J22/J64 -> -0.019160875 | K23: =K22/K64 -> -0.019160875 | L23: =L22/L64 -> -0.047053958 | M23: =M22/M64 -> -0.063024501 | ... V23: =V22/V64 -> -0.067886545
E24: Provisões para Perdas Esperadas Associadas ao Risco de Crédito (PCLD) | F24: =SUM(F26:F29) -> -118653 | G24: =SUM(G26:G29) -> -181931 | H24: =SUM(H26:H29) -> -387548 | I24: =SUM(I26:I29) -> -510867 | J24: =SUM(J26:J29) -> -294126.41 | K24: =SUM(K26:K29) -> -294126.41 | L24: =L25*L104 -> -401451.02 | M24: =K24+L24 -> -695577.44 | N24: =N25*N104 -> -613252.33 | O24: =O25*O104 -> -687121.73 | P24: =P25*P104 -> -764165.89 | Q24: =Q25*Q104 -> -841568.36 | R24: =R25*R104 -> -919380.31 | S24: =S25*S104 -> -997781.65 | T24: =T25*T104 -> -1077956 | U24: =U25*U104 -> -1159780.7 | V24: =V25*V104 -> -1243878 | W24: =(I24/F24)^(1/3)-1 -> 0.62683326
E25: PCLD como % da Exposição da Carteira de Crédito | F25: =F24/F104 -> -0.0081829655 | G25: =G24/G104 -> -0.0074257551 | H25: =H24/H104 -> -0.011887975 | I25: =I24/I104 -> -0.01362312 | J25: =J24/J104 -> -0.007843371 | K25: =K24/K104 -> -0.007843371 | L25: =((1+$F$225)^(3/4)-1)+$G$225*L10 -> -0.0085412766 | M25: =M24/M104 -> -0.014799114 | N25: =$F$225+$G$225*N10 -> -0.011561746 | O25: =$F$225+$G$225*O10 -> -0.01174063 | P25: =$F$225+$G$225*P10 -> -0.011895485 | Q25: =$F$225+$G$225*Q10 -> -0.012004951 | R25: =$F$225+$G$225*R10 -> -0.012077039 | S25: =$F$225+$G$225*S10 -> -0.012121893 | T25: =$F$225+$G$225*T10 -> -0.012146456 | U25: =$F$225+$G$225*U10 -> -0.01215767 | V25: =$F$225+$G$225*V10 -> -0.012162476 | X25: Calculado através de um modelo oriundo de uma regressão lienear entre o a taxa selic e o PCLD como % da Exposição da Carteira de Crédito.
E26: Provisão para Operações de Crédito | F26: -109860 | G26: -181214 | H26: -371688 | I26: -513268 | J26: -293965.43 | K26: =J26 -> -293965.43 | L26: - | M26: -
E27: Provisão para Repasses Interfinanceiros | F27: -156 | G27: 63 | H27: -3462 | I27: 3523 | J27: -0.15123 | K27: =J27 -> -0.15123 | L27: - | M27: - | N27: - | O27: - | P27: - | Q27: - | R27: - | S27: - | T27: - | U27: - | V27: -
E28: Provisão para Outros Créditos | F28: -55 | G28: 62 | H28: 0 | I28: 0 | J28: 0 | K28: =J28 -> 0 | L28: - | M28: - | N28: - | O28: - | P28: - | Q28: - | R28: - | S28: - | T28: - | U28: - | V28: -
E29: Provisão para Câmbio | F29: -8582 | G29: -842 | H29: -12398 | I29: -1122 | J29: -160.83226 | K29: =J29 -> -160.83226 | L29: - | M29: - | N29: - | O29: - | P29: - | Q29: - | R29: - | S29: - | T29: - | U29: - | V29: -
E30: Margem Financeira Líquida | F30: =SUM(F18,F24) -> 360543 | G30: =SUM(G18,G24) -> 517628 | H30: =SUM(H18,H24) -> 1061209 | I30: =SUM(I18,I24) -> 1068160 | J30: =SUM(J18,J24) -> 90674.552 | K30: =SUM(K18,K24) -> 90674.552 | L30: =SUM(L18,L24) -> 1087904.2 | M30: =SUM(M18,M24) -> 1178578.7 | ... V30: =SUM(V18,V24) -> 2898419.4 | W30: =(I30/F30)^(1/3)-1 -> 0.436238
E31: Margem Financeira Líquida como % da Margem Financeira Bruta | F31: =F30/F18 -> 0.75239151 | G31: =G30/G18 -> 0.73993473 | H31: =H30/H18 -> 0.7324962 | I31: =I30/I18 -> 0.67646722 | J31: =J30/J18 -> 0.23564014 | K31: =K30/K18 -> 0.23564014 | L31: =L30/L18 -> 0.73045314 | M31: =M30/M18 -> 0.62885834 | ... V31: =V30/V18 -> 0.69971301
E32: Spread Global | F32: =F30/F38 -> 0.018809306 | G32: =G30/G38 -> 0.02110059 | H32: =H30/H38 -> 0.031598512 | I32: =I30/I38 -> 0.024050409 | J32: =J30/J38 -> 0.0019098555 | K32: =K30/K38 -> 0.0019098555 | L32: =L30/L38 -> 0.019094661 | M32: =M30/M38 -> 0.020686162 | ... V32: =V30/V38 -> 0.025295266
E37: Ano | F37: 2020 | G37: 2021 | H37: 2022 | I37: 2023 | J37: =J$9 -> 1T24 | K37: =K$9 -> YTD24 | L37: =L$9 -> YTG24 | M37: 2024 | N37: 2025 | O37: 2026 | P37: 2027 | Q37: 2028 | R37: 2029 | S37: 2030 | T37: 2031 | U37: 2032 | V37: 2033 | W37: CAGR 2020-2023 | X37: Premissas
E38: Ativos Rentáveis | F38: =SUM(F40,F42,F44,F46,F48,F50,F52,F54,F56,F58,F60,F62) -> 19168331 | G38: =SUM(G40,G42,G44,G46,G48,G50,G52,G54,G56,G58,G60,G62) -> 24531447 | H38: =SUM(H40,H42,H44,H46,H48,H50,H52,H54,H56,H58,H60,H62) -> 33584145 | I38: =SUM(I40,I42,I44,I46,I48,I50,I52,I54,I56,I58,I60,I62) -> 44413381 | J38: =SUM(J40,J42,J44,J46,J48,J50,J52,J54,J56,J58,J60,J62) -> 47477178 | K38: =SUM(K40,K42,K44,K46,K48,K50,K52,K54,K56,K58,K60,K62) -> 47477178 | L38: ='Projeções Trimestrais'!J26 -> 56974260 | M38: =L38 -> 56974260 | N38: =N104/N106 -> 63716016 | O38: =O104/O106 -> 69674586 | P38: =P104/P106 -> 75800425 | Q38: =Q104/Q106 -> 81990448 | R38: =R104/R106 -> 88261364 | S38: =S104/S106 -> 94609670 | T38: =T104/T106 -> 1.0113205e+08 | U38: =U104/U106 -> 1.0778583e+08 | V38: =V104/V106 -> 1.1458347e+08 | W38: =(I38/F38)^(1/3)-1 -> 0.32325389
E39: Crescimento dos Ativos Rentáveis | F39: - | G39: =G38/F38-1 -> 0.27979045 | H39: =H38/G38-1 -> 0.36902422 | I39: =I38/H38-1 -> 0.32245085 | M39: =M38/I38-1 -> 0.28281744 | N39: =N38/M38-1 -> 0.11832987 | O39: =O38/N38-1 -> 0.093517619 | P39: =P38/O38-1 -> 0.087920697 | Q39: =Q38/P38-1 -> 0.081662123 | R39: =R38/Q38-1 -> 0.076483494 | S39: =S38/R38-1 -> 0.071926209 | T39: =T38/S38-1 -> 0.068939916 | U39: =U38/T38-1 -> 0.065793009 | V39: =V38/U38-1 -> 0.063066152
E40: Empréstimos | F40: ='Balanço Patrimonial - Contábil'!F35 -> 1993626 | G40: ='Balanço Patrimonial - Contábil'!G35 -> 2439446 | H40: ='Balanço Patrimonial - Contábil'!H35 -> 2886738 | I40: ='Balanço Patrimonial - Contábil'!I35 -> 3099444 | J40: ='Balanço Patrimonial - Contábil'!J35 -> 2878763 | K40: ='Balanço Patrimonial - Contábil'!K35 -> 2878763 | L40: =L41*L$38 -> 3454615.4 | M40: =L40 -> 3454615.4 | N40: =N41*N$38 -> 3863399.6 | O40: =O41*O$38 -> 4224695.5 | P40: =P41*P$38 -> 4596133.7 | Q40: =Q41*Q$38 -> 4971463.7 | R40: =R41*R$38 -> 5351698.6 | S40: =S41*S$38 -> 5736626 | T40: =T41*T$38 -> 6132108.5 | U40: =U41*U$38 -> 6535558.4 | V40: =V41*V$38 -> 6947730.9 | W40: =(I40/F40)^(1/3)-1 -> 0.15845731
E41: % dos Ativos Rentáveis | F41: =F40/F$38 -> 0.10400624 | G41: =G40/G$38 -> 0.099441586 | H41: =H40/H$38 -> 0.085955382 | I41: =I40/I$38 -> 0.069786266 | J41: =J40/J$38 -> 0.060634669 | K41: =K40/K$38 -> 0.060634669 | L41: =K41 -> 0.060634669 | M41: =M40/M$38 -> 0.060634669 | N41: =M41 -> 0.060634669 | O41: =N41 -> 0.060634669 | P41: =O41 -> 0.060634669 | Q41: =P41 -> 0.060634669 | R41: =Q41 -> 0.060634669 | S41: =R41 -> 0.060634669 | T41: =S41 -> 0.060634669 | U41: =T41 -> 0.060634669 | V41: =U41 -> 0.060634669 | X41: Se manterá constante igual ao último ano.
E42: Direitos Creditórios Descontados | F42: ='Balanço Patrimonial - Contábil'!F36 -> 6270 | G42: ='Balanço Patrimonial - Contábil'!G36 -> 11857 | H42: ='Balanço Patrimonial - Contábil'!H36 -> 5879 | I42: ='Balanço Patrimonial - Contábil'!I36 -> 8746 | J42: ='Balanço Patrimonial - Contábil'!J36 -> 10638 | K42: ='Balanço Patrimonial - Contábil'!K36 -> 10638 | L42: =L43*L$38 -> 12765.969 | M42: =L42 -> 12765.969 | N42: =N43*N$38 -> 14276.564 | O42: =O43*O$38 -> 15611.674 | P42: =P43*P$38 -> 16984.264 | Q42: =Q43*Q$38 -> 18371.235 | R42: =R43*R$38 -> 19776.331 | S42: =S43*S$38 -> 21198.767 | T42: =T43*T$38 -> 22660.209 | U42: =U43*U$38 -> 24151.092 | V42: =V43*V$38 -> 25674.208 | W42: =(I42/F42)^(1/3)-1 -> 0.1173279
E43: % dos Ativos Rentáveis | F43: =F42/F$38 -> 0.00032710203 | G43: =G42/G$38 -> 0.00048333879 | H43: =H42/H$38 -> 0.00017505284 | I43: =I42/I$38 -> 0.00019692263 | J43: =J42/J$38 -> 0.00022406555 | K43: =K42/K$38 -> 0.00022406555 | L43: =K43 -> 0.00022406555 | M43: =M42/M$38 -> 0.00022406555 | N43: =M43 -> 0.00022406555 | O43: =N43 -> 0.00022406555 | P43: =O43 -> 0.00022406555 | Q43: =P43 -> 0.00022406555 | R43: =Q43 -> 0.00022406555 | S43: =R43 -> 0.00022406555 | T43: =S43 -> 0.00022406555 | U43: =T43 -> 0.00022406555 | V43: =U43 -> 0.00022406555 | X43: Se manterá constante igual ao último ano.
E44: Financiamentos | F44: ='Balanço Patrimonial - Contábil'!F37 -> 1290886 | G44: ='Balanço Patrimonial - Contábil'!G37 -> 2601194 | H44: ='Balanço Patrimonial - Contábil'!H37 -> 5222618 | I44: ='Balanço Patrimonial - Contábil'!I37 -> 7583131 | J44: ='Balanço Patrimonial - Contábil'!J37 -> 8169088 | K44: ='Balanço Patrimonial - Contábil'!K37 -> 8169088 | L44: =L45*L$38 -> 9803188.7 | M44: =L44 -> 9803188.7 | N44: =N45*N$38 -> 10963199 | O44: =O45*O$38 -> 11988451 | P44: =P45*P$38 -> 13042484 | Q44: =Q45*Q$38 -> 14107561 | R44: =R45*R$38 -> 15186556 | S44: =S45*S$38 -> 16278868 | T44: =T45*T$38 -> 17401132 | U44: =U45*U$38 -> 18546004 | V44: =V45*V$38 -> 19715630 | W44: =(I44/F44)^(1/3)-1 -> 0.80434767
E45: % dos Ativos Rentáveis | F45: =F44/F$38 -> 0.067344726 | G45: =G44/G$38 -> 0.10603508 | H45: =H44/H$38 -> 0.15550844 | I45: =I44/I$38 -> 0.17073978 | J45: =J44/J$38 -> 0.17206347 | K45: =K44/K$38 -> 0.17206347 | L45: =K45 -> 0.17206347 | M45: =M44/M$38 -> 0.17206347 | N45: =M45 -> 0.17206347 | O45: =N45 -> 0.17206347 | P45: =O45 -> 0.17206347 | Q45: =P45 -> 0.17206347 | R45: =Q45 -> 0.17206347 | S45: =R45 -> 0.17206347 | T45: =S45 -> 0.17206347 | U45: =T45 -> 0.17206347 | V45: =U45 -> 0.17206347 | X45: Se manterá constante igual ao último ano.
E46: Financiamentos Rurais | F46: ='Balanço Patrimonial - Contábil'!F38 -> 1741470 | G46: ='Balanço Patrimonial - Contábil'!G38 -> 6172334 | H46: ='Balanço Patrimonial - Contábil'!H38 -> 11584571 | I46: ='Balanço Patrimonial - Contábil'!I38 -> 15101430 | J46: ='Balanço Patrimonial - Contábil'!J38 -> 15827469 | K46: ='Balanço Patrimonial - Contábil'!K38 -> 15827469 | L46: =L47*L$38 -> 18993511 | M46: =L46 -> 18993511 | N46: =N47*N$38 -> 21241011 | O46: =O47*O$38 -> 23227420 | P46: =P47*P$38 -> 25269591 | Q46: =Q47*Q$38 -> 27333159 | R46: =R47*R$38 -> 29423695 | S46: =S47*S$38 -> 31540030 | T46: =T47*T$38 -> 33714397 | U46: =U47*U$38 -> 35932568 | V46: =V47*V$38 -> 38198697 | W46: =(I46/F46)^(1/3)-1 -> 1.0544742
E47: % dos Ativos Rentáveis | F47: =F46/F$38 -> 0.090851415 | G47: =G46/G$38 -> 0.25160905 | H47: =H46/H$38 -> 0.34494167 | I47: =I46/I$38 -> 0.34001982 | J47: =J46/J$38 -> 0.33337004 | K47: =K46/K$38 -> 0.33337004 | L47: =K47 -> 0.33337004 | M47: =M46/M$38 -> 0.33337004 | N47: =M47 -> 0.33337004 | O47: =N47 -> 0.33337004 | P47: =O47 -> 0.33337004 | Q47: =P47 -> 0.33337004 | R47: =Q47 -> 0.33337004 | S47: =R47 -> 0.33337004 | T47: =S47 -> 0.33337004 | U47: =T47 -> 0.33337004 | V47: =U47 -> 0.33337004 | X47: Se manterá constante igual ao último ano.
E48: Aplicações Interfinanceiras de Liquidez | F48: ='Balanço Patrimonial - Contábil'!F17 -> 585878 | G48: ='Balanço Patrimonial - Contábil'!G17 -> 1948260 | H48: ='Balanço Patrimonial - Contábil'!H17 -> 1112159 | I48: ='Balanço Patrimonial - Contábil'!I17 -> 1509359 | J48: ='Balanço Patrimonial - Contábil'!J17 -> 2324426.1 | K48: ='Balanço Patrimonial - Contábil'!K17 -> 2324426.1 | L48: =L49*L$38 -> 2789391.9 | M48: =L48 -> 2789391.9 | N48: =N49*N$38 -> 3119460.3 | O48: =O49*O$38 -> 3411184.8 | P48: =P49*P$38 -> 3711098.6 | Q48: =Q49*Q$38 -> 4014154.7 | R48: =R49*R$38 -> 4321171.3 | S48: =S49*S$38 -> 4631976.8 | T48: =T49*T$38 -> 4951304.9 | U48: =U49*U$38 -> 5277066.1 | V48: =V49*V$38 -> 5609870.4 | W48: =(I48/F48)^(1/3)-1 -> 0.37086636
E49: % dos Ativos Rentáveis | F49: =F48/F$38 -> 0.030564894 | G49: =G48/G$38 -> 0.079418878 | H49: =H48/H$38 -> 0.033115597 | I49: =I48/I$38 -> 0.03398433 | J49: =J48/J$38 -> 0.04895881 | K49: =K48/K$38 -> 0.04895881 | L49: =K49 -> 0.04895881 | M49: =M48/M$38 -> 0.04895881 | N49: =M49 -> 0.04895881 | O49: =N49 -> 0.04895881 | P49: =O49 -> 0.04895881 | Q49: =P49 -> 0.04895881 | R49: =Q49 -> 0.04895881 | S49: =R49 -> 0.04895881 | T49: =S49 -> 0.04895881 | U49: =T49 -> 0.04895881 | V49: =U49 -> 0.04895881 | X49: Se manterá constante igual ao último ano.
E50: Títulos de Renda Fixa | F50: =SUM('Balanço Patrimonial - Contábil'!F21,'Balanço Patrimonial - Contábil'!F22,'Balanço Patrimonial - Contábil'!F26,'Balanço Patrimonial - Contábil'!F29,'Balanço Patrimonial - Contábil'!F30) -> 12637325 | G50: =SUM('Balanço Patrimonial - Contábil'!G21,'Balanço Patrimonial - Contábil'!G22,'Balanço Patrimonial - Contábil'!G26,'Balanço Patrimonial - Contábil'!G29,'Balanço Patrimonial - Contábil'!G30) -> 10512122 | H50: =SUM('Balanço Patrimonial - Contábil'!H21,'Balanço Patrimonial - Contábil'!H22,'Balanço Patrimonial - Contábil'!H26,'Balanço Patrimonial - Contábil'!H29,'Balanço Patrimonial - Contábil'!H30) -> 11503149 | I50: =SUM('Balanço Patrimonial - Contábil'!I21,'Balanço Patrimonial - Contábil'!I22,'Balanço Patrimonial - Contábil'!I26,'Balanço Patrimonial - Contábil'!I29,'Balanço Patrimonial - Contábil'!I30) -> 16006908 | J50: =SUM('Balanço Patrimonial - Contábil'!J21,'Balanço Patrimonial - Contábil'!J22,'Balanço Patrimonial - Contábil'!J26,'Balanço Patrimonial - Contábil'!J29,'Balanço Patrimonial - Contábil'!J30) -> 17131107 | K50: =SUM('Balanço Patrimonial - Contábil'!K21,'Balanço Patrimonial - Contábil'!K22,'Balanço Patrimonial - Contábil'!K26,'Balanço Patrimonial - Contábil'!K29,'Balanço Patrimonial - Contábil'!K30) -> 17131107 | L50: =L51*L$38 -> 20557922 | M50: =L50 -> 20557922 | N50: =N51*N$38 -> 22990538 | O50: =O51*O$38 -> 25140559 | P50: =P51*P$38 -> 27350934 | Q50: =Q51*Q$38 -> 29584470 | R50: =R51*R$38 -> 31847193 | S50: =S51*S$38 -> 34137841 | T50: =T51*T$38 -> 36491301 | U50: =U51*U$38 -> 38892173 | V50: =V51*V$38 -> 41344953 | W50: =(I50/F50)^(1/3)-1 -> 0.081975511
E51: % dos Ativos Rentáveis | F51: =F50/F$38 -> 0.65928145 | G51: =G50/G$38 -> 0.42851618 | H51: =H50/H$38 -> 0.34251725 | I51: =I50/I$38 -> 0.36040733 | J51: =J50/J$38 -> 0.36082825 | K51: =K50/K$38 -> 0.36082825 | L51: =K51 -> 0.36082825 | M51: =M50/M$38 -> 0.36082825 | N51: =M51 -> 0.36082825 | O51: =N51 -> 0.36082825 | P51: =O51 -> 0.36082825 | Q51: =P51 -> 0.36082825 | R51: =Q51 -> 0.36082825 | S51: =R51 -> 0.36082825 | T51: =S51 -> 0.36082825 | U51: =T51 -> 0.36082825 | V51: =U51 -> 0.36082825 | X51: Se manterá constante igual ao último ano.
E52: Fundos de Investimentos | F52: =SUM('Balanço Patrimonial - Contábil'!F23,'Balanço Patrimonial - Contábil'!F24,'Balanço Patrimonial - Contábil'!F25,'Balanço Patrimonial - Contábil'!F28) -> 163935 | G52: =SUM('Balanço Patrimonial - Contábil'!G23,'Balanço Patrimonial - Contábil'!G24,'Balanço Patrimonial - Contábil'!G25,'Balanço Patrimonial - Contábil'!G28) -> 119238 | H52: =SUM('Balanço Patrimonial - Contábil'!H23,'Balanço Patrimonial - Contábil'!H24,'Balanço Patrimonial - Contábil'!H25,'Balanço Patrimonial - Contábil'!H28) -> 87000 | I52: =SUM('Balanço Patrimonial - Contábil'!I23,'Balanço Patrimonial - Contábil'!I24,'Balanço Patrimonial - Contábil'!I25,'Balanço Patrimonial - Contábil'!I28) -> 92859 | J52: =SUM('Balanço Patrimonial - Contábil'!J23,'Balanço Patrimonial - Contábil'!J24,'Balanço Patrimonial - Contábil'!J25,'Balanço Patrimonial - Contábil'!J28) -> 95331 | K52: =SUM('Balanço Patrimonial - Contábil'!K23,'Balanço Patrimonial - Contábil'!K24,'Balanço Patrimonial - Contábil'!K25,'Balanço Patrimonial - Contábil'!K28) -> 95331 | L52: =L53*L$38 -> 114400.5 | M52: =L52 -> 114400.5 | N52: =N53*N$38 -> 127937.5 | O52: =O53*O$38 -> 139901.91 | P52: =P53*P$38 -> 152202.18 | Q52: =Q53*Q$38 -> 164631.34 | R52: =R53*R$38 -> 177222.92 | S52: =S53*S$38 -> 189969.89 | T52: =T53*T$38 -> 203066.4 | U52: =U53*U$38 -> 216426.75 | V52: =V53*V$38 -> 230075.95 | W52: =(I52/F52)^(1/3)-1 -> -0.17259634
E53: % dos Ativos Rentáveis | F53: =F52/F$38 -> 0.0085523878 | G53: =G52/G$38 -> 0.0048606183 | H53: =H52/H$38 -> 0.0025905081 | I53: =I52/I$38 -> 0.0020907888 | J53: =J52/J$38 -> 0.0020079331 | K53: =K52/K$38 -> 0.0020079331 | L53: =K53 -> 0.0020079331 | M53: =M52/M$38 -> 0.0020079331 | N53: =M53 -> 0.0020079331 | O53: =N53 -> 0.0020079331 | P53: =O53 -> 0.0020079331 | Q53: =P53 -> 0.0020079331 | R53: =Q53 -> 0.0020079331 | S53: =R53 -> 0.0020079331 | T53: =S53 -> 0.0020079331 | U53: =T53 -> 0.0020079331 | V53: =U53 -> 0.0020079331 | X53: Se manterá constante igual ao último ano.
E54: Ações | F54: ='Balanço Patrimonial - Contábil'!F27 -> 0 | G54: ='Balanço Patrimonial - Contábil'!G27 -> 0 | H54: ='Balanço Patrimonial - Contábil'!H27 -> 18646 | I54: ='Balanço Patrimonial - Contábil'!I27 -> 0 | J54: ='Balanço Patrimonial - Contábil'!J27 -> 0 | K54: ='Balanço Patrimonial - Contábil'!K27 -> 0 | L54: =L55*L$38 -> 0 | M54: =L54 -> 0 | N54: =N55*N$38 -> 0 | O54: =O55*O$38 -> 0 | P54: =P55*P$38 -> 0 | Q54: =Q55*Q$38 -> 0 | R54: =R55*R$38 -> 0 | S54: =S55*S$38 -> 0 | T54: =T55*T$38 -> 0 | U54: =U55*U$38 -> 0 | V54: =V55*V$38 -> 0 | W54: -
E55: % dos Ativos Rentáveis | F55: =F54/F$38 -> 0 | G55: =G54/G$38 -> 0 | H55: =H54/H$38 -> 0.00055520246 | I55: =I54/I$38 -> 0 | J55: =J54/J$38 -> 0 | K55: =K54/K$38 -> 0 | L55: =K55 -> 0 | M55: =M54/M$38 -> 0 | N55: =M55 -> 0 | O55: =N55 -> 0 | P55: =O55 -> 0 | Q55: =P55 -> 0 | R55: =Q55 -> 0 | S55: =R55 -> 0 | T55: =S55 -> 0 | U55: =T55 -> 0 | V55: =U55 -> 0 | X55: Se manterá constante igual ao último ano.
E56: Relações Interfinanceiras e Interdependências | F56: ='Balanço Patrimonial - Contábil'!F31 -> 543523 | G56: ='Balanço Patrimonial - Contábil'!G31 -> 499289 | H56: ='Balanço Patrimonial - Contábil'!H31 -> 927618 | I56: ='Balanço Patrimonial - Contábil'!I31 -> 805425 | J56: ='Balanço Patrimonial - Contábil'!J31 -> 826763.73 | K56: ='Balanço Patrimonial - Contábil'!K31 -> 826763.73 | L56: =L57*L$38 -> 992145.13 | M56: =L56 -> 992145.13 | N56: =N57*N$38 -> 1109545.5 | O56: =O57*O$38 -> 1213307.6 | P56: =P57*P$38 -> 1319982.4 | Q56: =Q57*Q$38 -> 1427775 | R56: =R57*R$38 -> 1536976.2 | S56: =S57*S$38 -> 1647525.1 | T56: =T57*T$38 -> 1761105.3 | U56: =U57*U$38 -> 1876973.8 | V56: =V57*V$38 -> 1995347.3 | W56: =(I56/F56)^(1/3)-1 -> 0.14008105
E57: % dos Ativos Rentáveis | F57: =F56/F$38 -> 0.02835526 | G57: =G56/G$38 -> 0.020353019 | H57: =H56/H$38 -> 0.027620712 | I57: =I56/I$38 -> 0.018134737 | J57: =J56/J$38 -> 0.017413919 | K57: =K56/K$38 -> 0.017413919 | L57: =K57 -> 0.017413919 | M57: =M56/M$38 -> 0.017413919 | N57: =M57 -> 0.017413919 | O57: =N57 -> 0.017413919 | P57: =O57 -> 0.017413919 | Q57: =P57 -> 0.017413919 | R57: =Q57 -> 0.017413919 | S57: =R57 -> 0.017413919 | T57: =S57 -> 0.017413919 | U57: =T57 -> 0.017413919 | V57: =U57 -> 0.017413919 | X57: Se manterá constante igual ao último ano.
E58: Carteira de Câmbio | F58: ='Balanço Patrimonial - Contábil'!F39 -> 53248 | G58: ='Balanço Patrimonial - Contábil'!G39 -> 61990 | H58: ='Balanço Patrimonial - Contábil'!H39 -> 42771 | I58: ='Balanço Patrimonial - Contábil'!I39 -> 31150 | J58: ='Balanço Patrimonial - Contábil'!J39 -> 46877.307 | K58: ='Balanço Patrimonial - Contábil'!K39 -> 46877.307 | L58: =L59*L$38 -> 56254.393 | M58: =L58 -> 56254.393 | N58: =N59*N$38 -> 62910.968 | O58: =O59*O$38 -> 68794.252 | P58: =P59*P$38 -> 74842.691 | Q58: =Q59*Q$38 -> 80954.504 | R58: =R59*R$38 -> 87146.187 | S58: =S59*S$38 -> 93414.282 | T58: =T59*T$38 -> 99854.255 | U58: =U59*U$38 -> 106423.97 | V58: =V59*V$38 -> 113135.72 | W58: =(I58/F58)^(1/3)-1 -> -0.16365606
E59: % dos Ativos Rentáveis | F59: =F58/F$38 -> 0.0027779153 | G59: =G58/G$38 -> 0.0025269606 | H59: =H58/H$38 -> 0.0012735474 | I59: =I58/I$38 -> 0.0007013652 | J59: =J58/J$38 -> 0.00098736506 | K59: =K58/K$38 -> 0.00098736506 | L59: =K59 -> 0.00098736506 | M59: =M58/M$38 -> 0.00098736506 | N59: =M59 -> 0.00098736506 | O59: =N59 -> 0.00098736506 | P59: =O59 -> 0.00098736506 | Q59: =P59 -> 0.00098736506 | R59: =Q59 -> 0.00098736506 | S59: =R59 -> 0.00098736506 | T59: =S59 -> 0.00098736506 | U59: =T59 -> 0.00098736506 | V59: =U59 -> 0.00098736506 | X59: Se manterá constante igual ao último ano.
E60: Outros Créditos | F60: ='Balanço Patrimonial - Contábil'!F41 -> 208 | G60: ='Balanço Patrimonial - Contábil'!G41 -> 0 | H60: ='Balanço Patrimonial - Contábil'!H41 -> 0 | I60: ='Balanço Patrimonial - Contábil'!I41 -> 0 | J60: ='Balanço Patrimonial - Contábil'!J41 -> 0 | K60: ='Balanço Patrimonial - Contábil'!K41 -> 0 | L60: =L61*L$38 -> 0 | M60: =L60 -> 0 | N60: =N61*N$38 -> 0 | O60: =O61*O$38 -> 0 | P60: =P61*P$38 -> 0 | Q60: =Q61*Q$38 -> 0 | R60: =R61*R$38 -> 0 | S60: =S61*S$38 -> 0 | T60: =T61*T$38 -> 0 | U60: =U61*U$38 -> 0 | V60: =V61*V$38 -> 0 | W60: =(I60/F60)^(1/3)-1 -> -1
E61: % dos Ativos Rentáveis | F61: =F60/F$38 -> 1.0851232e-05 | G61: =G60/G$38 -> 0 | H61: =H60/H$38 -> 0 | I61: =I60/I$38 -> 0 | J61: =J60/J$38 -> 0 | K61: =K60/K$38 -> 0 | L61: =K61 -> 0 | M61: =M60/M$38 -> 0 | N61: =M61 -> 0 | O61: =N61 -> 0 | P61: =O61 -> 0 | Q61: =P61 -> 0 | R61: =Q61 -> 0 | S61: =R61 -> 0 | T61: =S61 -> 0 | U61: =T61 -> 0 | V61: =U61 -> 0 | X61: Se manterá constante igual ao último ano.
E62: Outros Instrumentos Financeiros | F62: ='Balanço Patrimonial - Contábil'!F43 -> 151962 | G62: ='Balanço Patrimonial - Contábil'!G43 -> 165717 | H62: ='Balanço Patrimonial - Contábil'!H43 -> 192996 | I62: ='Balanço Patrimonial - Contábil'!I43 -> 174929 | J62: ='Balanço Patrimonial - Contábil'!J43 -> 166715.3 | K62: ='Balanço Patrimonial - Contábil'!K43 -> 166715.3 | L62: =L63*L$38 -> 200064.14 | M62: =L62 -> 200064.14 | N62: =N63*N$38 -> 223737.71 | O62: =O63*O$38 -> 244661.12 | P62: =P63*P$38 -> 266171.9 | Q62: =Q63*Q$38 -> 287908.06 | R62: =R63*R$38 -> 309928.28 | S62: =S63*S$38 -> 332220.24 | T62: =T63*T$38 -> 355123.48 | U62: =U63*U$38 -> 378488.12 | V62: =V63*V$38 -> 402357.91 | W62: =(I62/F62)^(1/3)-1 -> 0.04803456
E63: % dos Ativos Rentáveis | F63: =F62/F$38 -> 0.0079277638 | G63: =G62/G$38 -> 0.0067552884 | H63: =H62/H$38 -> 0.0057466403 | I63: =I62/I$38 -> 0.0039386553 | J63: =J62/J$38 -> 0.003511483 | K63: =K62/K$38 -> 0.003511483 | L63: =K63 -> 0.003511483 | M63: =M62/M$38 -> 0.003511483 | N63: =M63 -> 0.003511483 | O63: =N63 -> 0.003511483 | P63: =O63 -> 0.003511483 | Q63: =P63 -> 0.003511483 | R63: =Q63 -> 0.003511483 | S63: =R63 -> 0.003511483 | T63: =S63 -> 0.003511483 | U63: =T63 -> 0.003511483 | V63: =U63 -> 0.003511483 | X63: Se manterá constante igual ao último ano.
E64: Passivos Onerosos | F64: =SUM(F66,F68,F70,F72,F74,F76,F78,F80,F82,F84,F86,F88,F90,F92,F94,F96,F98,F100) -> 14472736 | G64: =SUM(G66,G68,G70,G72,G74,G76,G78,G80,G82,G84,G86,G88,G90,G92,G94,G96,G98,G100) -> 19267380 | H64: =SUM(H66,H68,H70,H72,H74,H76,H78,H80,H82,H84,H86,H88,H90,H92,H94,H96,H98,H100) -> 25656298 | I64: =SUM(I66,I68,I70,I72,I74,I76,I78,I80,I82,I84,I86,I88,I90,I92,I94,I96,I98,I100) -> 35490828 | J64: =SUM(J66,J68,J70,J72,J74,J76,J78,J80,J82,J84,J86,J88,J90,J92,J94,J96,J98,J100) -> 38512124 | K64: =SUM(K66,K68,K70,K72,K74,K76,K78,K80,K82,K84,K86,K88,K90,K92,K94,K96,K98,K100) -> 38512124 | L64: ='Projeções Trimestrais'!J48 -> 46205443 | M64: =L64 -> 46205443 | N64: =N38*N108 -> 51672927 | O64: =O38*O108 -> 56505256 | P64: =P38*P108 -> 61473238 | Q64: =Q38*Q108 -> 66493273 | R64: =R38*R108 -> 71578911 | S64: =S38*S108 -> 76727311 | T64: =T38*T108 -> 82016885 | U64: =U38*U108 -> 87413023 | V64: =V38*V108 -> 92925826 | W64: =(I64/F64)^(1/3)-1 -> 0.34851308
E65: Crescimento dos Passivos Rentáveis | F65: - | G65: =G64/F64-1 -> 0.33128802 | H65: =H64/G64-1 -> 0.33159246 | I65: =I64/H64-1 -> 0.38331836 | M65: =M64/I64-1 -> 0.30189815 | N65: =N64/M64-1 -> 0.11832987 | O65: =O64/N64-1 -> 0.093517619 | P65: =P64/O64-1 -> 0.087920697 | Q65: =Q64/P64-1 -> 0.081662123 | R65: =R64/Q64-1 -> 0.076483494 | S65: =S64/R64-1 -> 0.071926209 | T65: =T64/S64-1 -> 0.068939916 | U65: =U64/T64-1 -> 0.065793009 | V65: =V64/U64-1 -> 0.063066152
E66: Depósitos à Vista | F66: ='Balanço Patrimonial - Contábil'!F74 -> 2101873 | G66: ='Balanço Patrimonial - Contábil'!G74 -> 2000942 | H66: ='Balanço Patrimonial - Contábil'!H74 -> 1785604 | I66: ='Balanço Patrimonial - Contábil'!I74 -> 2349405 | J66: ='Balanço Patrimonial - Contábil'!J74 -> 1905651 | K66: ='Balanço Patrimonial - Contábil'!K74 -> 1905651 | L66: =L67*L$64 -> 2286330.6 | M66: =L66 -> 2286330.6 | N66: =N67*N$64 -> 2556871.8 | O66: =O67*O$64 -> 2795984.4 | P66: =P67*P$64 -> 3041809.3 | Q66: =Q67*Q$64 -> 3290209.9 | R66: =R67*R$64 -> 3541856.6 | S66: =S67*S$64 -> 3796609 | T66: =T67*T$64 -> 4058346.9 | U66: =U67*U$64 -> 4325357.7 | V66: =V67*V$64 -> 4598141.4 | W66: =(I66/F66)^(1/3)-1 -> 0.037808299
E67: % dos Passivos Onerosos | F67: =F66/F$64 -> 0.14522983 | G67: =G66/G$64 -> 0.10385128 | H67: =H66/H$64 -> 0.069597102 | I67: =I66/I$64 -> 0.066197526 | J67: =J66/J$64 -> 0.049481846 | K67: =K66/K$64 -> 0.049481846 | L67: =K67 -> 0.049481846 | M67: =M66/M$64 -> 0.049481846 | N67: =M67 -> 0.049481846 | O67: =N67 -> 0.049481846 | P67: =O67 -> 0.049481846 | Q67: =P67 -> 0.049481846 | R67: =Q67 -> 0.049481846 | S67: =R67 -> 0.049481846 | T67: =S67 -> 0.049481846 | U67: =T67 -> 0.049481846 | V67: =U67 -> 0.049481846 | X67: Se manterá constante igual ao último ano.
E68: Depósitos de Poupança | F68: ='Balanço Patrimonial - Contábil'!F75 -> 766226 | G68: ='Balanço Patrimonial - Contábil'!G75 -> 792764 | H68: ='Balanço Patrimonial - Contábil'!H75 -> 749268 | I68: ='Balanço Patrimonial - Contábil'!I75 -> 725983 | J68: ='Balanço Patrimonial - Contábil'!J75 -> 722973 | K68: ='Balanço Patrimonial - Contábil'!K75 -> 722973 | L68: =L69*L$64 -> 867396.66 | M68: =L68 -> 867396.66 | N68: =N69*N$64 -> 970035.59 | O68: =O69*O$64 -> 1060751 | P68: =P69*P$64 -> 1154013 | Q68: =Q69*Q$64 -> 1248252.1 | R68: =R69*R$64 -> 1343722.8 | S68: =S69*S$64 -> 1440371.7 | T68: =T69*T$64 -> 1539670.8 | U68: =U69*U$64 -> 1640970.4 | V68: =V69*V$64 -> 1744460.1 | W68: =(I68/F68)^(1/3)-1 -> -0.017822784
E69: % dos Passivos Onerosos | F69: =F68/F$64 -> 0.052942719 | G69: =G68/G$64 -> 0.041145397 | H69: =H68/H$64 -> 0.029204057 | I69: =I68/I$64 -> 0.02045551 | J69: =J68/J$64 -> 0.018772608 | K69: =K68/K$64 -> 0.018772608 | L69: =K69 -> 0.018772608 | M69: =M68/M$64 -> 0.018772608 | N69: =M69 -> 0.018772608 | O69: =N69 -> 0.018772608 | P69: =O69 -> 0.018772608 | Q69: =P69 -> 0.018772608 | R69: =Q69 -> 0.018772608 | S69: =R69 -> 0.018772608 | T69: =S69 -> 0.018772608 | U69: =T69 -> 0.018772608 | V69: =U69 -> 0.018772608 | X69: Se manterá constante igual ao último ano.
E70: Depósitos Interfinanceiros | F70: ='Balanço Patrimonial - Contábil'!F76 -> 7505 | G70: ='Balanço Patrimonial - Contábil'!G76 -> 41672 | H70: ='Balanço Patrimonial - Contábil'!H76 -> 43885 | I70: ='Balanço Patrimonial - Contábil'!I76 -> 379287 | J70: ='Balanço Patrimonial - Contábil'!J76 -> 362389 | K70: ='Balanço Patrimonial - Contábil'!K76 -> 362389 | L70: =L71*L$64 -> 434781.12 | M70: =L70 -> 434781.12 | N70: =N71*N$64 -> 486228.71 | O70: =O71*O$64 -> 531699.66 | P70: =P71*P$64 -> 578447.06 | Q70: =Q71*Q$64 -> 625684.28 | R70: =R71*R$64 -> 673538.8 | S70: =S71*S$64 -> 721983.89 | T70: =T71*T$64 -> 771757.4 | U70: =U71*U$64 -> 822533.64 | V70: =V71*V$64 -> 874407.67 | W70: =(I70/F70)^(1/3)-1 -> 2.6971955
E71: % dos Passivos Onerosos | F71: =F70/F$64 -> 0.00051856125 | G71: =G70/G$64 -> 0.0021628265 | H71: =H70/H$64 -> 0.0017104962 | I71: =I70/I$64 -> 0.010686902 | J71: =J70/J$64 -> 0.009409738 | K71: =K70/K$64 -> 0.009409738 | L71: =K71 -> 0.009409738 | M71: =M70/M$64 -> 0.009409738 | N71: =M71 -> 0.009409738 | O71: =N71 -> 0.009409738 | P71: =O71 -> 0.009409738 | Q71: =P71 -> 0.009409738 | R71: =Q71 -> 0.009409738 | S71: =R71 -> 0.009409738 | T71: =S71 -> 0.009409738 | U71: =T71 -> 0.009409738 | V71: =U71 -> 0.009409738 | X71: Se manterá constante igual ao último ano.
E72: Depósitos a Prazo | F72: ='Balanço Patrimonial - Contábil'!F78 -> 1551955 | G72: ='Balanço Patrimonial - Contábil'!G78 -> 1842803 | H72: ='Balanço Patrimonial - Contábil'!H78 -> 1903078 | I72: ='Balanço Patrimonial - Contábil'!I78 -> 2430848 | J72: ='Balanço Patrimonial - Contábil'!J78 -> 2716567 | K72: ='Balanço Patrimonial - Contábil'!K78 -> 2716567 | L72: =L73*L$64 -> 3259238.1 | M72: =L72 -> 3259238.1 | N72: =N73*N$64 -> 3644903.3 | O72: =O73*O$64 -> 3985766 | P72: =P73*P$64 -> 4336197.3 | Q72: =Q73*Q$64 -> 4690300.4 | R72: =R73*R$64 -> 5049030.9 | S72: =S73*S$64 -> 5412188.6 | T72: =T73*T$64 -> 5785304.4 | U72: =U73*U$64 -> 6165937 | V72: =V73*V$64 -> 6554798.9 | W72: =(I72/F72)^(1/3)-1 -> 0.16134047
E73: % dos Passivos Onerosos | F73: =F72/F$64 -> 0.10723301 | G73: =G72/G$64 -> 0.095643673 | H73: =H72/H$64 -> 0.074175861 | I73: =I72/I$64 -> 0.068492288 | J73: =J72/J$64 -> 0.070537968 | K73: =K72/K$64 -> 0.070537968 | L73: =K73 -> 0.070537968 | M73: =M72/M$64 -> 0.070537968 | N73: =M73 -> 0.070537968 | O73: =N73 -> 0.070537968 | P73: =O73 -> 0.070537968 | Q73: =P73 -> 0.070537968 | R73: =Q73 -> 0.070537968 | S73: =R73 -> 0.070537968 | T73: =S73 -> 0.070537968 | U73: =T73 -> 0.070537968 | V73: =U73 -> 0.070537968 | X73: Se manterá constante igual ao último ano.
E74: Depósitos Judiciais com Remuneração | F74: ='Balanço Patrimonial - Contábil'!F79 -> 83366 | G74: ='Balanço Patrimonial - Contábil'!G79 -> 64486 | H74: ='Balanço Patrimonial - Contábil'!H79 -> 68304 | I74: ='Balanço Patrimonial - Contábil'!I79 -> 73698 | J74: ='Balanço Patrimonial - Contábil'!J79 -> 76057 | K74: ='Balanço Patrimonial - Contábil'!K79 -> 76057 | L74: =L75*L$64 -> 91250.417 | M74: =L74 -> 91250.417 | N74: =N75*N$64 -> 102048.07 | O74: =O75*O$64 -> 111591.36 | P74: =P75*P$64 -> 121402.55 | Q74: =Q75*Q$64 -> 131316.54 | R74: =R75*R$64 -> 141360.09 | S74: =S75*S$64 -> 151527.58 | T74: =T75*T$64 -> 161973.88 | U74: =U75*U$64 -> 172630.63 | V74: =V75*V$64 -> 183517.78 | W74: =(I74/F74)^(1/3)-1 -> -0.040255616
E75: % dos Passivos Onerosos | F75: =F74/F$64 -> 0.0057602101 | G75: =G74/G$64 -> 0.0033469003 | H75: =H74/H$64 -> 0.0026622703 | I75: =I74/I$64 -> 0.0020765365 | J75: =J74/J$64 -> 0.0019748846 | K75: =K74/K$64 -> 0.0019748846 | L75: =K75 -> 0.0019748846 | M75: =M74/M$64 -> 0.0019748846 | N75: =M75 -> 0.0019748846 | O75: =N75 -> 0.0019748846 | P75: =O75 -> 0.0019748846 | Q75: =P75 -> 0.0019748846 | R75: =Q75 -> 0.0019748846 | S75: =R75 -> 0.0019748846 | T75: =S75 -> 0.0019748846 | U75: =T75 -> 0.0019748846 | V75: =U75 -> 0.0019748846 | X75: Se manterá constante igual ao último ano.
E76: Depósitos Especiais com Remuneração | F76: ='Balanço Patrimonial - Contábil'!F80 -> 1318693 | G76: ='Balanço Patrimonial - Contábil'!G80 -> 1677854 | H76: ='Balanço Patrimonial - Contábil'!H80 -> 3788271 | I76: ='Balanço Patrimonial - Contábil'!I80 -> 5363550 | J76: ='Balanço Patrimonial - Contábil'!J80 -> 6285008 | K76: ='Balanço Patrimonial - Contábil'!K80 -> 6285008 | L76: =L77*L$64 -> 7540523.6 | M76: =L76 -> 7540523.6 | N76: =N77*N$64 -> 8432792.7 | O76: =O77*O$64 -> 9221407.4 | P76: =P77*P$64 -> 10032160 | Q76: =Q77*Q$64 -> 10851407 | R76: =R77*R$64 -> 11681361 | S76: =S77*S$64 -> 12521557 | T76: =T77*T$64 -> 13384792 | U76: =U77*U$64 -> 14265418 | V76: =V77*V$64 -> 15165083 | W76: =(I76/F76)^(1/3)-1 -> 0.59625723
