Workbook

Sheet Dashboard
H3: SIMPAR (SIMH3)
A7: Páginas
A8: Dashboard
A9: WACC | E9: Ticker | F9: SIMH3 | G9: WACC | H9: =H10-0.5% -> 0.14112663 | I9: =(((NPV($H9,'DRE + DCF'!$U$36,'DRE + DCF'!$W$36:$Z$36)*((1+$H9)^((12-3)/12))+('DRE + DCF'!$AA$36*(1+I$18)/(($H9-I$18)*(1+$H9)^(COUNT('DRE + DCF'!$V$22:$Z$22)-((12-3)/12)))))+SUM($F$12:$F$17)))/$F$10-(((NPV($H9,'DRE + DCF'!$U$36,'DRE + DCF'!$W$36:$Z$36)*((1+$H9)^((12-3)/12))+('DRE + DCF'!$AA$36*(1+I$18)/(($H9-I$18)*(1+$H9)^(COUNT('DRE + DCF'!$V$22:$Z$22)-((12-3)/12)))))*$F$40+$F$42)*(1-$F$39))/$F$10 -> 13.507825 | J9: =(((NPV($H9,'DRE + DCF'!$U$36,'DRE + DCF'!$W$36:$Z$36)*((1+$H9)^((12-3)/12))+('DRE + DCF'!$AA$36*(1+J$18)/(($H9-J$18)*(1+$H9)^(COUNT('DRE + DCF'!$V$22:$Z$22)-((12-3)/12)))))+SUM($F$12:$F$17)))/$F$10-(((NPV($H9,'DRE + DCF'!$U$36,'DRE + DCF'!$W$36:$Z$36)*((1+$H9)^((12-3)/12))+('DRE + DCF'!$AA$36*(1+J$18)/(($H9-J$18)*(1+$H9)^(COUNT('DRE + DCF'!$V$22:$Z$22)-((12-3)/12)))))*$F$40+$F$42)*(1-$F$39))/$F$10 -> 13.783559 | K9: =(((NPV($H9,'DRE + DCF'!$U$36,'DRE + DCF'!$W$36:$Z$36)*((1+$H9)^((12-3)/12))+('DRE + DCF'!$AA$36*(1+K$18)/(($H9-K$18)*(1+$H9)^(COUNT('DRE + DCF'!$V$22:$Z$22)-((12-3)/12)))))+SUM($F$12:$F$17)))/$F$10-(((NPV($H9,'DRE + DCF'!$U$36,'DRE + DCF'!$W$36:$Z$36)*((1+$H9)^((12-3)/12))+('DRE + DCF'!$AA$36*(1+K$18)/(($H9-K$18)*(1+$H9)^(COUNT('DRE + DCF'!$V$22:$Z$22)-((12-3)/12)))))*$F$40+$F$42)*(1-$F$39))/$F$10 -> 14.079224 | L9: =(((NPV($H9,'DRE + DCF'!$U$36,'DRE + DCF'!$W$36:$Z$36)*((1+$H9)^((12-3)/12))+('DRE + DCF'!$AA$36*(1+L$18)/(($H9-L$18)*(1+$H9)^(COUNT('DRE + DCF'!$V$22:$Z$22)-((12-3)/12)))))+SUM($F$12:$F$17)))/$F$10-(((NPV($H9,'DRE + DCF'!$U$36,'DRE + DCF'!$W$36:$Z$36)*((1+$H9)^((12-3)/12))+('DRE + DCF'!$AA$36*(1+L$18)/(($H9-L$18)*(1+$H9)^(COUNT('DRE + DCF'!$V$22:$Z$22)-((12-3)/12)))))*$F$40+$F$42)*(1-$F$39))/$F$10 -> 14.397063 | M9: =(((NPV($H9,'DRE + DCF'!$U$36,'DRE + DCF'!$W$36:$Z$36)*((1+$H9)^((12-3)/12))+('DRE + DCF'!$AA$36*(1+M$18)/(($H9-M$18)*(1+$H9)^(COUNT('DRE + DCF'!$V$22:$Z$22)-((12-3)/12)))))+SUM($F$12:$F$17)))/$F$10-(((NPV($H9,'DRE + DCF'!$U$36,'DRE + DCF'!$W$36:$Z$36)*((1+$H9)^((12-3)/12))+('DRE + DCF'!$AA$36*(1+M$18)/(($H9-M$18)*(1+$H9)^(COUNT('DRE + DCF'!$V$22:$Z$22)-((12-3)/12)))))*$F$40+$F$42)*(1-$F$39))/$F$10 -> 14.739668 | N9: =(((NPV($H9,'DRE + DCF'!$U$36,'DRE + DCF'!$W$36:$Z$36)*((1+$H9)^((12-3)/12))+('DRE + DCF'!$AA$36*(1+N$18)/(($H9-N$18)*(1+$H9)^(COUNT('DRE + DCF'!$V$22:$Z$22)-((12-3)/12)))))+SUM($F$12:$F$17)))/$F$10-(((NPV($H9,'DRE + DCF'!$U$36,'DRE + DCF'!$W$36:$Z$36)*((1+$H9)^((12-3)/12))+('DRE + DCF'!$AA$36*(1+N$18)/(($H9-N$18)*(1+$H9)^(COUNT('DRE + DCF'!$V$22:$Z$22)-((12-3)/12)))))*$F$40+$F$42)*(1-$F$39))/$F$10 -> 15.110049 | O9: =(((NPV($H9,'DRE + DCF'!$U$36,'DRE + DCF'!$W$36:$Z$36)*((1+$H9)^((12-3)/12))+('DRE + DCF'!$AA$36*(1+O$18)/(($H9-O$18)*(1+$H9)^(COUNT('DRE + DCF'!$V$22:$Z$22)-((12-3)/12)))))+SUM($F$12:$F$17)))/$F$10-(((NPV($H9,'DRE + DCF'!$U$36,'DRE + DCF'!$W$36:$Z$36)*((1+$H9)^((12-3)/12))+('DRE + DCF'!$AA$36*(1+O$18)/(($H9-O$18)*(1+$H9)^(COUNT('DRE + DCF'!$V$22:$Z$22)-((12-3)/12)))))*$F$40+$F$42)*(1-$F$39))/$F$10 -> 15.51173 | P9: =(((NPV($H9,'DRE + DCF'!$U$36,'DRE + DCF'!$W$36:$Z$36)*((1+$H9)^((12-3)/12))+('DRE + DCF'!$AA$36*(1+P$18)/(($H9-P$18)*(1+$H9)^(COUNT('DRE + DCF'!$V$22:$Z$22)-((12-3)/12)))))+SUM($F$12:$F$17)))/$F$10-(((NPV($H9,'DRE + DCF'!$U$36,'DRE + DCF'!$W$36:$Z$36)*((1+$H9)^((12-3)/12))+('DRE + DCF'!$AA$36*(1+P$18)/(($H9-P$18)*(1+$H9)^(COUNT('DRE + DCF'!$V$22:$Z$22)-((12-3)/12)))))*$F$40+$F$42)*(1-$F$39))/$F$10 -> 15.94885 | ... R9: =(((NPV($H9,'DRE + DCF'!$U$36,'DRE + DCF'!$W$36:$Z$36)*((1+$H9)^((12-3)/12))+('DRE + DCF'!$AA$36*(1+R$18)/(($H9-R$18)*(1+$H9)^(COUNT('DRE + DCF'!$V$22:$Z$22)-((12-3)/12)))))+SUM($F$12:$F$17)))/$F$10-(((NPV($H9,'DRE + DCF'!$U$36,'DRE + DCF'!$W$36:$Z$36)*((1+$H9)^((12-3)/12))+('DRE + DCF'!$AA$36*(1+R$18)/(($H9-R$18)*(1+$H9)^(COUNT('DRE + DCF'!$V$22:$Z$22)-((12-3)/12)))))*$F$40+$F$42)*(1-$F$39))/$F$10 -> 16.949989
A10: DRE Consolidado | E10: Ações Emitidas (mil) | F10: 838407.91 | H10: =H11-0.5% -> 0.14612663 | I10: =(((NPV($H10,'DRE + DCF'!$U$36,'DRE + DCF'!$W$36:$Z$36)*((1+$H10)^((12-3)/12))+('DRE + DCF'!$AA$36*(1+I$18)/(($H10-I$18)*(1+$H10)^(COUNT('DRE + DCF'!$V$22:$Z$22)-((12-3)/12)))))+SUM($F$12:$F$17)))/$F$10-(((NPV($H10,'DRE + DCF'!$U$36,'DRE + DCF'!$W$36:$Z$36)*((1+$H10)^((12-3)/12))+('DRE + DCF'!$AA$36*(1+I$18)/(($H10-I$18)*(1+$H10)^(COUNT('DRE + DCF'!$V$22:$Z$22)-((12-3)/12)))))*$F$40+$F$42)*(1-$F$39))/$F$10 -> 12.877401 | J10: =(((NPV($H10,'DRE + DCF'!$U$36,'DRE + DCF'!$W$36:$Z$36)*((1+$H10)^((12-3)/12))+('DRE + DCF'!$AA$36*(1+J$18)/(($H10-J$18)*(1+$H10)^(COUNT('DRE + DCF'!$V$22:$Z$22)-((12-3)/12)))))+SUM($F$12:$F$17)))/$F$10-(((NPV($H10,'DRE + DCF'!$U$36,'DRE + DCF'!$W$36:$Z$36)*((1+$H10)^((12-3)/12))+('DRE + DCF'!$AA$36*(1+J$18)/(($H10-J$18)*(1+$H10)^(COUNT('DRE + DCF'!$V$22:$Z$22)-((12-3)/12)))))*$F$40+$F$42)*(1-$F$39))/$F$10 -> 13.115468 | K10: =(((NPV($H10,'DRE + DCF'!$U$36,'DRE + DCF'!$W$36:$Z$36)*((1+$H10)^((12-3)/12))+('DRE + DCF'!$AA$36*(1+K$18)/(($H10-K$18)*(1+$H10)^(COUNT('DRE + DCF'!$V$22:$Z$22)-((12-3)/12)))))+SUM($F$12:$F$17)))/$F$10-(((NPV($H10,'DRE + DCF'!$U$36,'DRE + DCF'!$W$36:$Z$36)*((1+$H10)^((12-3)/12))+('DRE + DCF'!$AA$36*(1+K$18)/(($H10-K$18)*(1+$H10)^(COUNT('DRE + DCF'!$V$22:$Z$22)-((12-3)/12)))))*$F$40+$F$42)*(1-$F$39))/$F$10 -> 13.369583 | L10: =(((NPV($H10,'DRE + DCF'!$U$36,'DRE + DCF'!$W$36:$Z$36)*((1+$H10)^((12-3)/12))+('DRE + DCF'!$AA$36*(1+L$18)/(($H10-L$18)*(1+$H10)^(COUNT('DRE + DCF'!$V$22:$Z$22)-((12-3)/12)))))+SUM($F$12:$F$17)))/$F$10-(((NPV($H10,'DRE + DCF'!$U$36,'DRE + DCF'!$W$36:$Z$36)*((1+$H10)^((12-3)/12))+('DRE + DCF'!$AA$36*(1+L$18)/(($H10-L$18)*(1+$H10)^(COUNT('DRE + DCF'!$V$22:$Z$22)-((12-3)/12)))))*$F$40+$F$42)*(1-$F$39))/$F$10 -> 13.641426 | M10: =(((NPV($H10,'DRE + DCF'!$U$36,'DRE + DCF'!$W$36:$Z$36)*((1+$H10)^((12-3)/12))+('DRE + DCF'!$AA$36*(1+M$18)/(($H10-M$18)*(1+$H10)^(COUNT('DRE + DCF'!$V$22:$Z$22)-((12-3)/12)))))+SUM($F$12:$F$17)))/$F$10-(((NPV($H10,'DRE + DCF'!$U$36,'DRE + DCF'!$W$36:$Z$36)*((1+$H10)^((12-3)/12))+('DRE + DCF'!$AA$36*(1+M$18)/(($H10-M$18)*(1+$H10)^(COUNT('DRE + DCF'!$V$22:$Z$22)-((12-3)/12)))))*$F$40+$F$42)*(1-$F$39))/$F$10 -> 13.93292 | N10: =(((NPV($H10,'DRE + DCF'!$U$36,'DRE + DCF'!$W$36:$Z$36)*((1+$H10)^((12-3)/12))+('DRE + DCF'!$AA$36*(1+N$18)/(($H10-N$18)*(1+$H10)^(COUNT('DRE + DCF'!$V$22:$Z$22)-((12-3)/12)))))+SUM($F$12:$F$17)))/$F$10-(((NPV($H10,'DRE + DCF'!$U$36,'DRE + DCF'!$W$36:$Z$36)*((1+$H10)^((12-3)/12))+('DRE + DCF'!$AA$36*(1+N$18)/(($H10-N$18)*(1+$H10)^(COUNT('DRE + DCF'!$V$22:$Z$22)-((12-3)/12)))))*$F$40+$F$42)*(1-$F$39))/$F$10 -> 14.246275 | O10: =(((NPV($H10,'DRE + DCF'!$U$36,'DRE + DCF'!$W$36:$Z$36)*((1+$H10)^((12-3)/12))+('DRE + DCF'!$AA$36*(1+O$18)/(($H10-O$18)*(1+$H10)^(COUNT('DRE + DCF'!$V$22:$Z$22)-((12-3)/12)))))+SUM($F$12:$F$17)))/$F$10-(((NPV($H10,'DRE + DCF'!$U$36,'DRE + DCF'!$W$36:$Z$36)*((1+$H10)^((12-3)/12))+('DRE + DCF'!$AA$36*(1+O$18)/(($H10-O$18)*(1+$H10)^(COUNT('DRE + DCF'!$V$22:$Z$22)-((12-3)/12)))))*$F$40+$F$42)*(1-$F$39))/$F$10 -> 14.584046 | P10: =(((NPV($H10,'DRE + DCF'!$U$36,'DRE + DCF'!$W$36:$Z$36)*((1+$H10)^((12-3)/12))+('DRE + DCF'!$AA$36*(1+P$18)/(($H10-P$18)*(1+$H10)^(COUNT('DRE + DCF'!$V$22:$Z$22)-((12-3)/12)))))+SUM($F$12:$F$17)))/$F$10-(((NPV($H10,'DRE + DCF'!$U$36,'DRE + DCF'!$W$36:$Z$36)*((1+$H10)^((12-3)/12))+('DRE + DCF'!$AA$36*(1+P$18)/(($H10-P$18)*(1+$H10)^(COUNT('DRE + DCF'!$V$22:$Z$22)-((12-3)/12)))))*$F$40+$F$42)*(1-$F$39))/$F$10 -> 14.949202 | ... R10: =(((NPV($H10,'DRE + DCF'!$U$36,'DRE + DCF'!$W$36:$Z$36)*((1+$H10)^((12-3)/12))+('DRE + DCF'!$AA$36*(1+R$18)/(($H10-R$18)*(1+$H10)^(COUNT('DRE + DCF'!$V$22:$Z$22)-((12-3)/12)))))+SUM($F$12:$F$17)))/$F$10-(((NPV($H10,'DRE + DCF'!$U$36,'DRE + DCF'!$W$36:$Z$36)*((1+$H10)^((12-3)/12))+('DRE + DCF'!$AA$36*(1+R$18)/(($H10-R$18)*(1+$H10)^(COUNT('DRE + DCF'!$V$22:$Z$22)-((12-3)/12)))))*$F$40+$F$42)*(1-$F$39))/$F$10 -> 15.776168
A11: DRE + DCF | E11: Valor da Empresa (mil) | F11: =SUM('DRE + DCF'!U38:AA38) -> 8157123.4 | H11: =H12-0.5% -> 0.15112663 | I11: =(((NPV($H11,'DRE + DCF'!$U$36,'DRE + DCF'!$W$36:$Z$36)*((1+$H11)^((12-3)/12))+('DRE + DCF'!$AA$36*(1+I$18)/(($H11-I$18)*(1+$H11)^(COUNT('DRE + DCF'!$V$22:$Z$22)-((12-3)/12)))))+SUM($F$12:$F$17)))/$F$10-(((NPV($H11,'DRE + DCF'!$U$36,'DRE + DCF'!$W$36:$Z$36)*((1+$H11)^((12-3)/12))+('DRE + DCF'!$AA$36*(1+I$18)/(($H11-I$18)*(1+$H11)^(COUNT('DRE + DCF'!$V$22:$Z$22)-((12-3)/12)))))*$F$40+$F$42)*(1-$F$39))/$F$10 -> 12.320962 | J11: =(((NPV($H11,'DRE + DCF'!$U$36,'DRE + DCF'!$W$36:$Z$36)*((1+$H11)^((12-3)/12))+('DRE + DCF'!$AA$36*(1+J$18)/(($H11-J$18)*(1+$H11)^(COUNT('DRE + DCF'!$V$22:$Z$22)-((12-3)/12)))))+SUM($F$12:$F$17)))/$F$10-(((NPV($H11,'DRE + DCF'!$U$36,'DRE + DCF'!$W$36:$Z$36)*((1+$H11)^((12-3)/12))+('DRE + DCF'!$AA$36*(1+J$18)/(($H11-J$18)*(1+$H11)^(COUNT('DRE + DCF'!$V$22:$Z$22)-((12-3)/12)))))*$F$40+$F$42)*(1-$F$39))/$F$10 -> 12.528224 | K11: =(((NPV($H11,'DRE + DCF'!$U$36,'DRE + DCF'!$W$36:$Z$36)*((1+$H11)^((12-3)/12))+('DRE + DCF'!$AA$36*(1+K$18)/(($H11-K$18)*(1+$H11)^(COUNT('DRE + DCF'!$V$22:$Z$22)-((12-3)/12)))))+SUM($F$12:$F$17)))/$F$10-(((NPV($H11,'DRE + DCF'!$U$36,'DRE + DCF'!$W$36:$Z$36)*((1+$H11)^((12-3)/12))+('DRE + DCF'!$AA$36*(1+K$18)/(($H11-K$18)*(1+$H11)^(COUNT('DRE + DCF'!$V$22:$Z$22)-((12-3)/12)))))*$F$40+$F$42)*(1-$F$39))/$F$10 -> 12.748576 | L11: =(((NPV($H11,'DRE + DCF'!$U$36,'DRE + DCF'!$W$36:$Z$36)*((1+$H11)^((12-3)/12))+('DRE + DCF'!$AA$36*(1+L$18)/(($H11-L$18)*(1+$H11)^(COUNT('DRE + DCF'!$V$22:$Z$22)-((12-3)/12)))))+SUM($F$12:$F$17)))/$F$10-(((NPV($H11,'DRE + DCF'!$U$36,'DRE + DCF'!$W$36:$Z$36)*((1+$H11)^((12-3)/12))+('DRE + DCF'!$AA$36*(1+L$18)/(($H11-L$18)*(1+$H11)^(COUNT('DRE + DCF'!$V$22:$Z$22)-((12-3)/12)))))*$F$40+$F$42)*(1-$F$39))/$F$10 -> 12.983298 | M11: =(((NPV($H11,'DRE + DCF'!$U$36,'DRE + DCF'!$W$36:$Z$36)*((1+$H11)^((12-3)/12))+('DRE + DCF'!$AA$36*(1+M$18)/(($H11-M$18)*(1+$H11)^(COUNT('DRE + DCF'!$V$22:$Z$22)-((12-3)/12)))))+SUM($F$12:$F$17)))/$F$10-(((NPV($H11,'DRE + DCF'!$U$36,'DRE + DCF'!$W$36:$Z$36)*((1+$H11)^((12-3)/12))+('DRE + DCF'!$AA$36*(1+M$18)/(($H11-M$18)*(1+$H11)^(COUNT('DRE + DCF'!$V$22:$Z$22)-((12-3)/12)))))*$F$40+$F$42)*(1-$F$39))/$F$10 -> 13.233844 | N11: =(((NPV($H11,'DRE + DCF'!$U$36,'DRE + DCF'!$W$36:$Z$36)*((1+$H11)^((12-3)/12))+('DRE + DCF'!$AA$36*(1+N$18)/(($H11-N$18)*(1+$H11)^(COUNT('DRE + DCF'!$V$22:$Z$22)-((12-3)/12)))))+SUM($F$12:$F$17)))/$F$10-(((NPV($H11,'DRE + DCF'!$U$36,'DRE + DCF'!$W$36:$Z$36)*((1+$H11)^((12-3)/12))+('DRE + DCF'!$AA$36*(1+N$18)/(($H11-N$18)*(1+$H11)^(COUNT('DRE + DCF'!$V$22:$Z$22)-((12-3)/12)))))*$F$40+$F$42)*(1-$F$39))/$F$10 -> 13.501868 | O11: =(((NPV($H11,'DRE + DCF'!$U$36,'DRE + DCF'!$W$36:$Z$36)*((1+$H11)^((12-3)/12))+('DRE + DCF'!$AA$36*(1+O$18)/(($H11-O$18)*(1+$H11)^(COUNT('DRE + DCF'!$V$22:$Z$22)-((12-3)/12)))))+SUM($F$12:$F$17)))/$F$10-(((NPV($H11,'DRE + DCF'!$U$36,'DRE + DCF'!$W$36:$Z$36)*((1+$H11)^((12-3)/12))+('DRE + DCF'!$AA$36*(1+O$18)/(($H11-O$18)*(1+$H11)^(COUNT('DRE + DCF'!$V$22:$Z$22)-((12-3)/12)))))*$F$40+$F$42)*(1-$F$39))/$F$10 -> 13.789267 | P11: =(((NPV($H11,'DRE + DCF'!$U$36,'DRE + DCF'!$W$36:$Z$36)*((1+$H11)^((12-3)/12))+('DRE + DCF'!$AA$36*(1+P$18)/(($H11-P$18)*(1+$H11)^(COUNT('DRE + DCF'!$V$22:$Z$22)-((12-3)/12)))))+SUM($F$12:$F$17)))/$F$10-(((NPV($H11,'DRE + DCF'!$U$36,'DRE + DCF'!$W$36:$Z$36)*((1+$H11)^((12-3)/12))+('DRE + DCF'!$AA$36*(1+P$18)/(($H11-P$18)*(1+$H11)^(COUNT('DRE + DCF'!$V$22:$Z$22)-((12-3)/12)))))*$F$40+$F$42)*(1-$F$39))/$F$10 -> 14.09822 | ... R11: =(((NPV($H11,'DRE + DCF'!$U$36,'DRE + DCF'!$W$36:$Z$36)*((1+$H11)^((12-3)/12))+('DRE + DCF'!$AA$36*(1+R$18)/(($H11-R$18)*(1+$H11)^(COUNT('DRE + DCF'!$V$22:$Z$22)-((12-3)/12)))))+SUM($F$12:$F$17)))/$F$10-(((NPV($H11,'DRE + DCF'!$U$36,'DRE + DCF'!$W$36:$Z$36)*((1+$H11)^((12-3)/12))+('DRE + DCF'!$AA$36*(1+R$18)/(($H11-R$18)*(1+$H11)^(COUNT('DRE + DCF'!$V$22:$Z$22)-((12-3)/12)))))*$F$40+$F$42)*(1-$F$39))/$F$10 -> 14.791273
A12: DRE - Contas Abertas | E12: Dívida (mil) | F12: =-F36 -> -9232802 | H12: =H13-0.5% -> 0.15612663 | I12: =(((NPV($H12,'DRE + DCF'!$U$36,'DRE + DCF'!$W$36:$Z$36)*((1+$H12)^((12-3)/12))+('DRE + DCF'!$AA$36*(1+I$18)/(($H12-I$18)*(1+$H12)^(COUNT('DRE + DCF'!$V$22:$Z$22)-((12-3)/12)))))+SUM($F$12:$F$17)))/$F$10-(((NPV($H12,'DRE + DCF'!$U$36,'DRE + DCF'!$W$36:$Z$36)*((1+$H12)^((12-3)/12))+('DRE + DCF'!$AA$36*(1+I$18)/(($H12-I$18)*(1+$H12)^(COUNT('DRE + DCF'!$V$22:$Z$22)-((12-3)/12)))))*$F$40+$F$42)*(1-$F$39))/$F$10 -> 11.82609 | J12: =(((NPV($H12,'DRE + DCF'!$U$36,'DRE + DCF'!$W$36:$Z$36)*((1+$H12)^((12-3)/12))+('DRE + DCF'!$AA$36*(1+J$18)/(($H12-J$18)*(1+$H12)^(COUNT('DRE + DCF'!$V$22:$Z$22)-((12-3)/12)))))+SUM($F$12:$F$17)))/$F$10-(((NPV($H12,'DRE + DCF'!$U$36,'DRE + DCF'!$W$36:$Z$36)*((1+$H12)^((12-3)/12))+('DRE + DCF'!$AA$36*(1+J$18)/(($H12-J$18)*(1+$H12)^(COUNT('DRE + DCF'!$V$22:$Z$22)-((12-3)/12)))))*$F$40+$F$42)*(1-$F$39))/$F$10 -> 12.007866 | K12: =(((NPV($H12,'DRE + DCF'!$U$36,'DRE + DCF'!$W$36:$Z$36)*((1+$H12)^((12-3)/12))+('DRE + DCF'!$AA$36*(1+K$18)/(($H12-K$18)*(1+$H12)^(COUNT('DRE + DCF'!$V$22:$Z$22)-((12-3)/12)))))+SUM($F$12:$F$17)))/$F$10-(((NPV($H12,'DRE + DCF'!$U$36,'DRE + DCF'!$W$36:$Z$36)*((1+$H12)^((12-3)/12))+('DRE + DCF'!$AA$36*(1+K$18)/(($H12-K$18)*(1+$H12)^(COUNT('DRE + DCF'!$V$22:$Z$22)-((12-3)/12)))))*$F$40+$F$42)*(1-$F$39))/$F$10 -> 12.200439 | L12: =(((NPV($H12,'DRE + DCF'!$U$36,'DRE + DCF'!$W$36:$Z$36)*((1+$H12)^((12-3)/12))+('DRE + DCF'!$AA$36*(1+L$18)/(($H12-L$18)*(1+$H12)^(COUNT('DRE + DCF'!$V$22:$Z$22)-((12-3)/12)))))+SUM($F$12:$F$17)))/$F$10-(((NPV($H12,'DRE + DCF'!$U$36,'DRE + DCF'!$W$36:$Z$36)*((1+$H12)^((12-3)/12))+('DRE + DCF'!$AA$36*(1+L$18)/(($H12-L$18)*(1+$H12)^(COUNT('DRE + DCF'!$V$22:$Z$22)-((12-3)/12)))))*$F$40+$F$42)*(1-$F$39))/$F$10 -> 12.404802 | M12: =(((NPV($H12,'DRE + DCF'!$U$36,'DRE + DCF'!$W$36:$Z$36)*((1+$H12)^((12-3)/12))+('DRE + DCF'!$AA$36*(1+M$18)/(($H12-M$18)*(1+$H12)^(COUNT('DRE + DCF'!$V$22:$Z$22)-((12-3)/12)))))+SUM($F$12:$F$17)))/$F$10-(((NPV($H12,'DRE + DCF'!$U$36,'DRE + DCF'!$W$36:$Z$36)*((1+$H12)^((12-3)/12))+('DRE + DCF'!$AA$36*(1+M$18)/(($H12-M$18)*(1+$H12)^(COUNT('DRE + DCF'!$V$22:$Z$22)-((12-3)/12)))))*$F$40+$F$42)*(1-$F$39))/$F$10 -> 12.622072 | N12: =(((NPV($H12,'DRE + DCF'!$U$36,'DRE + DCF'!$W$36:$Z$36)*((1+$H12)^((12-3)/12))+('DRE + DCF'!$AA$36*(1+N$18)/(($H12-N$18)*(1+$H12)^(COUNT('DRE + DCF'!$V$22:$Z$22)-((12-3)/12)))))+SUM($F$12:$F$17)))/$F$10-(((NPV($H12,'DRE + DCF'!$U$36,'DRE + DCF'!$W$36:$Z$36)*((1+$H12)^((12-3)/12))+('DRE + DCF'!$AA$36*(1+N$18)/(($H12-N$18)*(1+$H12)^(COUNT('DRE + DCF'!$V$22:$Z$22)-((12-3)/12)))))*$F$40+$F$42)*(1-$F$39))/$F$10 -> 12.853511 | O12: =(((NPV($H12,'DRE + DCF'!$U$36,'DRE + DCF'!$W$36:$Z$36)*((1+$H12)^((12-3)/12))+('DRE + DCF'!$AA$36*(1+O$18)/(($H12-O$18)*(1+$H12)^(COUNT('DRE + DCF'!$V$22:$Z$22)-((12-3)/12)))))+SUM($F$12:$F$17)))/$F$10-(((NPV($H12,'DRE + DCF'!$U$36,'DRE + DCF'!$W$36:$Z$36)*((1+$H12)^((12-3)/12))+('DRE + DCF'!$AA$36*(1+O$18)/(($H12-O$18)*(1+$H12)^(COUNT('DRE + DCF'!$V$22:$Z$22)-((12-3)/12)))))*$F$40+$F$42)*(1-$F$39))/$F$10 -> 13.100552 | P12: =(((NPV($H12,'DRE + DCF'!$U$36,'DRE + DCF'!$W$36:$Z$36)*((1+$H12)^((12-3)/12))+('DRE + DCF'!$AA$36*(1+P$18)/(($H12-P$18)*(1+$H12)^(COUNT('DRE + DCF'!$V$22:$Z$22)-((12-3)/12)))))+SUM($F$12:$F$17)))/$F$10-(((NPV($H12,'DRE + DCF'!$U$36,'DRE + DCF'!$W$36:$Z$36)*((1+$H12)^((12-3)/12))+('DRE + DCF'!$AA$36*(1+P$18)/(($H12-P$18)*(1+$H12)^(COUNT('DRE + DCF'!$V$22:$Z$22)-((12-3)/12)))))*$F$40+$F$42)*(1-$F$39))/$F$10 -> 13.364828 | ... R12: =(((NPV($H12,'DRE + DCF'!$U$36,'DRE + DCF'!$W$36:$Z$36)*((1+$H12)^((12-3)/12))+('DRE + DCF'!$AA$36*(1+R$18)/(($H12-R$18)*(1+$H12)^(COUNT('DRE + DCF'!$V$22:$Z$22)-((12-3)/12)))))+SUM($F$12:$F$17)))/$F$10-(((NPV($H12,'DRE + DCF'!$U$36,'DRE + DCF'!$W$36:$Z$36)*((1+$H12)^((12-3)/12))+('DRE + DCF'!$AA$36*(1+R$18)/(($H12-R$18)*(1+$H12)^(COUNT('DRE + DCF'!$V$22:$Z$22)-((12-3)/12)))))*$F$40+$F$42)*(1-$F$39))/$F$10 -> 13.952838
A13: Balanço Patrimonial | E13: Ativos/Passivos Não-Operacionais | F13: =F29 -> 1773707.9 | H13: =WACC!P20 -> 0.16112663 | I13: =(((NPV($H13,'DRE + DCF'!$U$36,'DRE + DCF'!$W$36:$Z$36)*((1+$H13)^((12-3)/12))+('DRE + DCF'!$AA$36*(1+I$18)/(($H13-I$18)*(1+$H13)^(COUNT('DRE + DCF'!$V$22:$Z$22)-((12-3)/12)))))+SUM($F$12:$F$17)))/$F$10-(((NPV($H13,'DRE + DCF'!$U$36,'DRE + DCF'!$W$36:$Z$36)*((1+$H13)^((12-3)/12))+('DRE + DCF'!$AA$36*(1+I$18)/(($H13-I$18)*(1+$H13)^(COUNT('DRE + DCF'!$V$22:$Z$22)-((12-3)/12)))))*$F$40+$F$42)*(1-$F$39))/$F$10 -> 11.383005 | J13: =(((NPV($H13,'DRE + DCF'!$U$36,'DRE + DCF'!$W$36:$Z$36)*((1+$H13)^((12-3)/12))+('DRE + DCF'!$AA$36*(1+J$18)/(($H13-J$18)*(1+$H13)^(COUNT('DRE + DCF'!$V$22:$Z$22)-((12-3)/12)))))+SUM($F$12:$F$17)))/$F$10-(((NPV($H13,'DRE + DCF'!$U$36,'DRE + DCF'!$W$36:$Z$36)*((1+$H13)^((12-3)/12))+('DRE + DCF'!$AA$36*(1+J$18)/(($H13-J$18)*(1+$H13)^(COUNT('DRE + DCF'!$V$22:$Z$22)-((12-3)/12)))))*$F$40+$F$42)*(1-$F$39))/$F$10 -> 11.543474 | K13: =(((NPV($H13,'DRE + DCF'!$U$36,'DRE + DCF'!$W$36:$Z$36)*((1+$H13)^((12-3)/12))+('DRE + DCF'!$AA$36*(1+K$18)/(($H13-K$18)*(1+$H13)^(COUNT('DRE + DCF'!$V$22:$Z$22)-((12-3)/12)))))+SUM($F$12:$F$17)))/$F$10-(((NPV($H13,'DRE + DCF'!$U$36,'DRE + DCF'!$W$36:$Z$36)*((1+$H13)^((12-3)/12))+('DRE + DCF'!$AA$36*(1+K$18)/(($H13-K$18)*(1+$H13)^(COUNT('DRE + DCF'!$V$22:$Z$22)-((12-3)/12)))))*$F$40+$F$42)*(1-$F$39))/$F$10 -> 11.712941 | L13: =(((NPV($H13,'DRE + DCF'!$U$36,'DRE + DCF'!$W$36:$Z$36)*((1+$H13)^((12-3)/12))+('DRE + DCF'!$AA$36*(1+L$18)/(($H13-L$18)*(1+$H13)^(COUNT('DRE + DCF'!$V$22:$Z$22)-((12-3)/12)))))+SUM($F$12:$F$17)))/$F$10-(((NPV($H13,'DRE + DCF'!$U$36,'DRE + DCF'!$W$36:$Z$36)*((1+$H13)^((12-3)/12))+('DRE + DCF'!$AA$36*(1+L$18)/(($H13-L$18)*(1+$H13)^(COUNT('DRE + DCF'!$V$22:$Z$22)-((12-3)/12)))))*$F$40+$F$42)*(1-$F$39))/$F$10 -> 11.892185 | M13: =(((NPV($H13,'DRE + DCF'!$U$36,'DRE + DCF'!$W$36:$Z$36)*((1+$H13)^((12-3)/12))+('DRE + DCF'!$AA$36*(1+M$18)/(($H13-M$18)*(1+$H13)^(COUNT('DRE + DCF'!$V$22:$Z$22)-((12-3)/12)))))+SUM($F$12:$F$17)))/$F$10-(((NPV($H13,'DRE + DCF'!$U$36,'DRE + DCF'!$W$36:$Z$36)*((1+$H13)^((12-3)/12))+('DRE + DCF'!$AA$36*(1+M$18)/(($H13-M$18)*(1+$H13)^(COUNT('DRE + DCF'!$V$22:$Z$22)-((12-3)/12)))))*$F$40+$F$42)*(1-$F$39))/$F$10 -> 12.082076 | N13: =(((NPV($H13,'DRE + DCF'!$U$36,'DRE + DCF'!$W$36:$Z$36)*((1+$H13)^((12-3)/12))+('DRE + DCF'!$AA$36*(1+N$18)/(($H13-N$18)*(1+$H13)^(COUNT('DRE + DCF'!$V$22:$Z$22)-((12-3)/12)))))+SUM($F$12:$F$17)))/$F$10-(((NPV($H13,'DRE + DCF'!$U$36,'DRE + DCF'!$W$36:$Z$36)*((1+$H13)^((12-3)/12))+('DRE + DCF'!$AA$36*(1+N$18)/(($H13-N$18)*(1+$H13)^(COUNT('DRE + DCF'!$V$22:$Z$22)-((12-3)/12)))))*$F$40+$F$42)*(1-$F$39))/$F$10 -> 12.283593 | O13: =(((NPV($H13,'DRE + DCF'!$U$36,'DRE + DCF'!$W$36:$Z$36)*((1+$H13)^((12-3)/12))+('DRE + DCF'!$AA$36*(1+O$18)/(($H13-O$18)*(1+$H13)^(COUNT('DRE + DCF'!$V$22:$Z$22)-((12-3)/12)))))+SUM($F$12:$F$17)))/$F$10-(((NPV($H13,'DRE + DCF'!$U$36,'DRE + DCF'!$W$36:$Z$36)*((1+$H13)^((12-3)/12))+('DRE + DCF'!$AA$36*(1+O$18)/(($H13-O$18)*(1+$H13)^(COUNT('DRE + DCF'!$V$22:$Z$22)-((12-3)/12)))))*$F$40+$F$42)*(1-$F$39))/$F$10 -> 12.497837 | P13: =(((NPV($H13,'DRE + DCF'!$U$36,'DRE + DCF'!$W$36:$Z$36)*((1+$H13)^((12-3)/12))+('DRE + DCF'!$AA$36*(1+P$18)/(($H13-P$18)*(1+$H13)^(COUNT('DRE + DCF'!$V$22:$Z$22)-((12-3)/12)))))+SUM($F$12:$F$17)))/$F$10-(((NPV($H13,'DRE + DCF'!$U$36,'DRE + DCF'!$W$36:$Z$36)*((1+$H13)^((12-3)/12))+('DRE + DCF'!$AA$36*(1+P$18)/(($H13-P$18)*(1+$H13)^(COUNT('DRE + DCF'!$V$22:$Z$22)-((12-3)/12)))))*$F$40+$F$42)*(1-$F$39))/$F$10 -> 12.726052 | ... R13: =(((NPV($H13,'DRE + DCF'!$U$36,'DRE + DCF'!$W$36:$Z$36)*((1+$H13)^((12-3)/12))+('DRE + DCF'!$AA$36*(1+R$18)/(($H13-R$18)*(1+$H13)^(COUNT('DRE + DCF'!$V$22:$Z$22)-((12-3)/12)))))+SUM($F$12:$F$17)))/$F$10-(((NPV($H13,'DRE + DCF'!$U$36,'DRE + DCF'!$W$36:$Z$36)*((1+$H13)^((12-3)/12))+('DRE + DCF'!$AA$36*(1+R$18)/(($H13-R$18)*(1+$H13)^(COUNT('DRE + DCF'!$V$22:$Z$22)-((12-3)/12)))))*$F$40+$F$42)*(1-$F$39))/$F$10 -> 13.230248
A14: Painel de Índices | E14: Empresas de Capital Aberto | F14: =K29 -> 12801997 | H14: =H13+0.5% -> 0.16612663 | I14: =(((NPV($H14,'DRE + DCF'!$U$36,'DRE + DCF'!$W$36:$Z$36)*((1+$H14)^((12-3)/12))+('DRE + DCF'!$AA$36*(1+I$18)/(($H14-I$18)*(1+$H14)^(COUNT('DRE + DCF'!$V$22:$Z$22)-((12-3)/12)))))+SUM($F$12:$F$17)))/$F$10-(((NPV($H14,'DRE + DCF'!$U$36,'DRE + DCF'!$W$36:$Z$36)*((1+$H14)^((12-3)/12))+('DRE + DCF'!$AA$36*(1+I$18)/(($H14-I$18)*(1+$H14)^(COUNT('DRE + DCF'!$V$22:$Z$22)-((12-3)/12)))))*$F$40+$F$42)*(1-$F$39))/$F$10 -> 10.983895 | J14: =(((NPV($H14,'DRE + DCF'!$U$36,'DRE + DCF'!$W$36:$Z$36)*((1+$H14)^((12-3)/12))+('DRE + DCF'!$AA$36*(1+J$18)/(($H14-J$18)*(1+$H14)^(COUNT('DRE + DCF'!$V$22:$Z$22)-((12-3)/12)))))+SUM($F$12:$F$17)))/$F$10-(((NPV($H14,'DRE + DCF'!$U$36,'DRE + DCF'!$W$36:$Z$36)*((1+$H14)^((12-3)/12))+('DRE + DCF'!$AA$36*(1+J$18)/(($H14-J$18)*(1+$H14)^(COUNT('DRE + DCF'!$V$22:$Z$22)-((12-3)/12)))))*$F$40+$F$42)*(1-$F$39))/$F$10 -> 11.126389 | K14: =(((NPV($H14,'DRE + DCF'!$U$36,'DRE + DCF'!$W$36:$Z$36)*((1+$H14)^((12-3)/12))+('DRE + DCF'!$AA$36*(1+K$18)/(($H14-K$18)*(1+$H14)^(COUNT('DRE + DCF'!$V$22:$Z$22)-((12-3)/12)))))+SUM($F$12:$F$17)))/$F$10-(((NPV($H14,'DRE + DCF'!$U$36,'DRE + DCF'!$W$36:$Z$36)*((1+$H14)^((12-3)/12))+('DRE + DCF'!$AA$36*(1+K$18)/(($H14-K$18)*(1+$H14)^(COUNT('DRE + DCF'!$V$22:$Z$22)-((12-3)/12)))))*$F$40+$F$42)*(1-$F$39))/$F$10 -> 11.276448 | L14: =(((NPV($H14,'DRE + DCF'!$U$36,'DRE + DCF'!$W$36:$Z$36)*((1+$H14)^((12-3)/12))+('DRE + DCF'!$AA$36*(1+L$18)/(($H14-L$18)*(1+$H14)^(COUNT('DRE + DCF'!$V$22:$Z$22)-((12-3)/12)))))+SUM($F$12:$F$17)))/$F$10-(((NPV($H14,'DRE + DCF'!$U$36,'DRE + DCF'!$W$36:$Z$36)*((1+$H14)^((12-3)/12))+('DRE + DCF'!$AA$36*(1+L$18)/(($H14-L$18)*(1+$H14)^(COUNT('DRE + DCF'!$V$22:$Z$22)-((12-3)/12)))))*$F$40+$F$42)*(1-$F$39))/$F$10 -> 11.434691 | M14: =(((NPV($H14,'DRE + DCF'!$U$36,'DRE + DCF'!$W$36:$Z$36)*((1+$H14)^((12-3)/12))+('DRE + DCF'!$AA$36*(1+M$18)/(($H14-M$18)*(1+$H14)^(COUNT('DRE + DCF'!$V$22:$Z$22)-((12-3)/12)))))+SUM($F$12:$F$17)))/$F$10-(((NPV($H14,'DRE + DCF'!$U$36,'DRE + DCF'!$W$36:$Z$36)*((1+$H14)^((12-3)/12))+('DRE + DCF'!$AA$36*(1+M$18)/(($H14-M$18)*(1+$H14)^(COUNT('DRE + DCF'!$V$22:$Z$22)-((12-3)/12)))))*$F$40+$F$42)*(1-$F$39))/$F$10 -> 11.601808 | N14: =(((NPV($H14,'DRE + DCF'!$U$36,'DRE + DCF'!$W$36:$Z$36)*((1+$H14)^((12-3)/12))+('DRE + DCF'!$AA$36*(1+N$18)/(($H14-N$18)*(1+$H14)^(COUNT('DRE + DCF'!$V$22:$Z$22)-((12-3)/12)))))+SUM($F$12:$F$17)))/$F$10-(((NPV($H14,'DRE + DCF'!$U$36,'DRE + DCF'!$W$36:$Z$36)*((1+$H14)^((12-3)/12))+('DRE + DCF'!$AA$36*(1+N$18)/(($H14-N$18)*(1+$H14)^(COUNT('DRE + DCF'!$V$22:$Z$22)-((12-3)/12)))))*$F$40+$F$42)*(1-$F$39))/$F$10 -> 11.778566 | O14: =(((NPV($H14,'DRE + DCF'!$U$36,'DRE + DCF'!$W$36:$Z$36)*((1+$H14)^((12-3)/12))+('DRE + DCF'!$AA$36*(1+O$18)/(($H14-O$18)*(1+$H14)^(COUNT('DRE + DCF'!$V$22:$Z$22)-((12-3)/12)))))+SUM($F$12:$F$17)))/$F$10-(((NPV($H14,'DRE + DCF'!$U$36,'DRE + DCF'!$W$36:$Z$36)*((1+$H14)^((12-3)/12))+('DRE + DCF'!$AA$36*(1+O$18)/(($H14-O$18)*(1+$H14)^(COUNT('DRE + DCF'!$V$22:$Z$22)-((12-3)/12)))))*$F$40+$F$42)*(1-$F$39))/$F$10 -> 11.965824 | P14: =(((NPV($H14,'DRE + DCF'!$U$36,'DRE + DCF'!$W$36:$Z$36)*((1+$H14)^((12-3)/12))+('DRE + DCF'!$AA$36*(1+P$18)/(($H14-P$18)*(1+$H14)^(COUNT('DRE + DCF'!$V$22:$Z$22)-((12-3)/12)))))+SUM($F$12:$F$17)))/$F$10-(((NPV($H14,'DRE + DCF'!$U$36,'DRE + DCF'!$W$36:$Z$36)*((1+$H14)^((12-3)/12))+('DRE + DCF'!$AA$36*(1+P$18)/(($H14-P$18)*(1+$H14)^(COUNT('DRE + DCF'!$V$22:$Z$22)-((12-3)/12)))))*$F$40+$F$42)*(1-$F$39))/$F$10 -> 12.164547 | ... R14: =(((NPV($H14,'DRE + DCF'!$U$36,'DRE + DCF'!$W$36:$Z$36)*((1+$H14)^((12-3)/12))+('DRE + DCF'!$AA$36*(1+R$18)/(($H14-R$18)*(1+$H14)^(COUNT('DRE + DCF'!$V$22:$Z$22)-((12-3)/12)))))+SUM($F$12:$F$17)))/$F$10-(((NPV($H14,'DRE + DCF'!$U$36,'DRE + DCF'!$W$36:$Z$36)*((1+$H14)^((12-3)/12))+('DRE + DCF'!$AA$36*(1+R$18)/(($H14-R$18)*(1+$H14)^(COUNT('DRE + DCF'!$V$22:$Z$22)-((12-3)/12)))))*$F$40+$F$42)*(1-$F$39))/$F$10 -> 12.60087
A15: Projeções - Receita e EBIT | E15: Valor do Equity da Automob que não pertence à Simpar | F15: =-F44 -> -1145069.8 | H15: =H14+0.5% -> 0.17112663 | I15: =(((NPV($H15,'DRE + DCF'!$U$36,'DRE + DCF'!$W$36:$Z$36)*((1+$H15)^((12-3)/12))+('DRE + DCF'!$AA$36*(1+I$18)/(($H15-I$18)*(1+$H15)^(COUNT('DRE + DCF'!$V$22:$Z$22)-((12-3)/12)))))+SUM($F$12:$F$17)))/$F$10-(((NPV($H15,'DRE + DCF'!$U$36,'DRE + DCF'!$W$36:$Z$36)*((1+$H15)^((12-3)/12))+('DRE + DCF'!$AA$36*(1+I$18)/(($H15-I$18)*(1+$H15)^(COUNT('DRE + DCF'!$V$22:$Z$22)-((12-3)/12)))))*$F$40+$F$42)*(1-$F$39))/$F$10 -> 10.622452 | J15: =(((NPV($H15,'DRE + DCF'!$U$36,'DRE + DCF'!$W$36:$Z$36)*((1+$H15)^((12-3)/12))+('DRE + DCF'!$AA$36*(1+J$18)/(($H15-J$18)*(1+$H15)^(COUNT('DRE + DCF'!$V$22:$Z$22)-((12-3)/12)))))+SUM($F$12:$F$17)))/$F$10-(((NPV($H15,'DRE + DCF'!$U$36,'DRE + DCF'!$W$36:$Z$36)*((1+$H15)^((12-3)/12))+('DRE + DCF'!$AA$36*(1+J$18)/(($H15-J$18)*(1+$H15)^(COUNT('DRE + DCF'!$V$22:$Z$22)-((12-3)/12)))))*$F$40+$F$42)*(1-$F$39))/$F$10 -> 10.749653 | K15: =(((NPV($H15,'DRE + DCF'!$U$36,'DRE + DCF'!$W$36:$Z$36)*((1+$H15)^((12-3)/12))+('DRE + DCF'!$AA$36*(1+K$18)/(($H15-K$18)*(1+$H15)^(COUNT('DRE + DCF'!$V$22:$Z$22)-((12-3)/12)))))+SUM($F$12:$F$17)))/$F$10-(((NPV($H15,'DRE + DCF'!$U$36,'DRE + DCF'!$W$36:$Z$36)*((1+$H15)^((12-3)/12))+('DRE + DCF'!$AA$36*(1+K$18)/(($H15-K$18)*(1+$H15)^(COUNT('DRE + DCF'!$V$22:$Z$22)-((12-3)/12)))))*$F$40+$F$42)*(1-$F$39))/$F$10 -> 10.883268 | L15: =(((NPV($H15,'DRE + DCF'!$U$36,'DRE + DCF'!$W$36:$Z$36)*((1+$H15)^((12-3)/12))+('DRE + DCF'!$AA$36*(1+L$18)/(($H15-L$18)*(1+$H15)^(COUNT('DRE + DCF'!$V$22:$Z$22)-((12-3)/12)))))+SUM($F$12:$F$17)))/$F$10-(((NPV($H15,'DRE + DCF'!$U$36,'DRE + DCF'!$W$36:$Z$36)*((1+$H15)^((12-3)/12))+('DRE + DCF'!$AA$36*(1+L$18)/(($H15-L$18)*(1+$H15)^(COUNT('DRE + DCF'!$V$22:$Z$22)-((12-3)/12)))))*$F$40+$F$42)*(1-$F$39))/$F$10 -> 11.023794 | M15: =(((NPV($H15,'DRE + DCF'!$U$36,'DRE + DCF'!$W$36:$Z$36)*((1+$H15)^((12-3)/12))+('DRE + DCF'!$AA$36*(1+M$18)/(($H15-M$18)*(1+$H15)^(COUNT('DRE + DCF'!$V$22:$Z$22)-((12-3)/12)))))+SUM($F$12:$F$17)))/$F$10-(((NPV($H15,'DRE + DCF'!$U$36,'DRE + DCF'!$W$36:$Z$36)*((1+$H15)^((12-3)/12))+('DRE + DCF'!$AA$36*(1+M$18)/(($H15-M$18)*(1+$H15)^(COUNT('DRE + DCF'!$V$22:$Z$22)-((12-3)/12)))))*$F$40+$F$42)*(1-$F$39))/$F$10 -> 11.171781 | N15: =(((NPV($H15,'DRE + DCF'!$U$36,'DRE + DCF'!$W$36:$Z$36)*((1+$H15)^((12-3)/12))+('DRE + DCF'!$AA$36*(1+N$18)/(($H15-N$18)*(1+$H15)^(COUNT('DRE + DCF'!$V$22:$Z$22)-((12-3)/12)))))+SUM($F$12:$F$17)))/$F$10-(((NPV($H15,'DRE + DCF'!$U$36,'DRE + DCF'!$W$36:$Z$36)*((1+$H15)^((12-3)/12))+('DRE + DCF'!$AA$36*(1+N$18)/(($H15-N$18)*(1+$H15)^(COUNT('DRE + DCF'!$V$22:$Z$22)-((12-3)/12)))))*$F$40+$F$42)*(1-$F$39))/$F$10 -> 11.327839 | O15: =(((NPV($H15,'DRE + DCF'!$U$36,'DRE + DCF'!$W$36:$Z$36)*((1+$H15)^((12-3)/12))+('DRE + DCF'!$AA$36*(1+O$18)/(($H15-O$18)*(1+$H15)^(COUNT('DRE + DCF'!$V$22:$Z$22)-((12-3)/12)))))+SUM($F$12:$F$17)))/$F$10-(((NPV($H15,'DRE + DCF'!$U$36,'DRE + DCF'!$W$36:$Z$36)*((1+$H15)^((12-3)/12))+('DRE + DCF'!$AA$36*(1+O$18)/(($H15-O$18)*(1+$H15)^(COUNT('DRE + DCF'!$V$22:$Z$22)-((12-3)/12)))))*$F$40+$F$42)*(1-$F$39))/$F$10 -> 11.492648 | P15: =(((NPV($H15,'DRE + DCF'!$U$36,'DRE + DCF'!$W$36:$Z$36)*((1+$H15)^((12-3)/12))+('DRE + DCF'!$AA$36*(1+P$18)/(($H15-P$18)*(1+$H15)^(COUNT('DRE + DCF'!$V$22:$Z$22)-((12-3)/12)))))+SUM($F$12:$F$17)))/$F$10-(((NPV($H15,'DRE + DCF'!$U$36,'DRE + DCF'!$W$36:$Z$36)*((1+$H15)^((12-3)/12))+('DRE + DCF'!$AA$36*(1+P$18)/(($H15-P$18)*(1+$H15)^(COUNT('DRE + DCF'!$V$22:$Z$22)-((12-3)/12)))))*$F$40+$F$42)*(1-$F$39))/$F$10 -> 11.666965 | ... R15: =(((NPV($H15,'DRE + DCF'!$U$36,'DRE + DCF'!$W$36:$Z$36)*((1+$H15)^((12-3)/12))+('DRE + DCF'!$AA$36*(1+R$18)/(($H15-R$18)*(1+$H15)^(COUNT('DRE + DCF'!$V$22:$Z$22)-((12-3)/12)))))+SUM($F$12:$F$17)))/$F$10-(((NPV($H15,'DRE + DCF'!$U$36,'DRE + DCF'!$W$36:$Z$36)*((1+$H15)^((12-3)/12))+('DRE + DCF'!$AA$36*(1+R$18)/(($H15-R$18)*(1+$H15)^(COUNT('DRE + DCF'!$V$22:$Z$22)-((12-3)/12)))))*$F$40+$F$42)*(1-$F$39))/$F$10 -> 12.047616
A16: Projeções - CG + Capex | E16: Desconto de Holding | F16: =('Projeções - Receita e EBIT'!U115)/((WACC!P20)-3.5%)/'DRE + DCF'!Z37 -> -1046115.4 | H16: =H15+0.5% -> 0.17612663 | I16: =(((NPV($H16,'DRE + DCF'!$U$36,'DRE + DCF'!$W$36:$Z$36)*((1+$H16)^((12-3)/12))+('DRE + DCF'!$AA$36*(1+I$18)/(($H16-I$18)*(1+$H16)^(COUNT('DRE + DCF'!$V$22:$Z$22)-((12-3)/12)))))+SUM($F$12:$F$17)))/$F$10-(((NPV($H16,'DRE + DCF'!$U$36,'DRE + DCF'!$W$36:$Z$36)*((1+$H16)^((12-3)/12))+('DRE + DCF'!$AA$36*(1+I$18)/(($H16-I$18)*(1+$H16)^(COUNT('DRE + DCF'!$V$22:$Z$22)-((12-3)/12)))))*$F$40+$F$42)*(1-$F$39))/$F$10 -> 10.293519 | J16: =(((NPV($H16,'DRE + DCF'!$U$36,'DRE + DCF'!$W$36:$Z$36)*((1+$H16)^((12-3)/12))+('DRE + DCF'!$AA$36*(1+J$18)/(($H16-J$18)*(1+$H16)^(COUNT('DRE + DCF'!$V$22:$Z$22)-((12-3)/12)))))+SUM($F$12:$F$17)))/$F$10-(((NPV($H16,'DRE + DCF'!$U$36,'DRE + DCF'!$W$36:$Z$36)*((1+$H16)^((12-3)/12))+('DRE + DCF'!$AA$36*(1+J$18)/(($H16-J$18)*(1+$H16)^(COUNT('DRE + DCF'!$V$22:$Z$22)-((12-3)/12)))))*$F$40+$F$42)*(1-$F$39))/$F$10 -> 10.407615 | K16: =(((NPV($H16,'DRE + DCF'!$U$36,'DRE + DCF'!$W$36:$Z$36)*((1+$H16)^((12-3)/12))+('DRE + DCF'!$AA$36*(1+K$18)/(($H16-K$18)*(1+$H16)^(COUNT('DRE + DCF'!$V$22:$Z$22)-((12-3)/12)))))+SUM($F$12:$F$17)))/$F$10-(((NPV($H16,'DRE + DCF'!$U$36,'DRE + DCF'!$W$36:$Z$36)*((1+$H16)^((12-3)/12))+('DRE + DCF'!$AA$36*(1+K$18)/(($H16-K$18)*(1+$H16)^(COUNT('DRE + DCF'!$V$22:$Z$22)-((12-3)/12)))))*$F$40+$F$42)*(1-$F$39))/$F$10 -> 10.527186 | L16: =(((NPV($H16,'DRE + DCF'!$U$36,'DRE + DCF'!$W$36:$Z$36)*((1+$H16)^((12-3)/12))+('DRE + DCF'!$AA$36*(1+L$18)/(($H16-L$18)*(1+$H16)^(COUNT('DRE + DCF'!$V$22:$Z$22)-((12-3)/12)))))+SUM($F$12:$F$17)))/$F$10-(((NPV($H16,'DRE + DCF'!$U$36,'DRE + DCF'!$W$36:$Z$36)*((1+$H16)^((12-3)/12))+('DRE + DCF'!$AA$36*(1+L$18)/(($H16-L$18)*(1+$H16)^(COUNT('DRE + DCF'!$V$22:$Z$22)-((12-3)/12)))))*$F$40+$F$42)*(1-$F$39))/$F$10 -> 10.652639 | M16: =(((NPV($H16,'DRE + DCF'!$U$36,'DRE + DCF'!$W$36:$Z$36)*((1+$H16)^((12-3)/12))+('DRE + DCF'!$AA$36*(1+M$18)/(($H16-M$18)*(1+$H16)^(COUNT('DRE + DCF'!$V$22:$Z$22)-((12-3)/12)))))+SUM($F$12:$F$17)))/$F$10-(((NPV($H16,'DRE + DCF'!$U$36,'DRE + DCF'!$W$36:$Z$36)*((1+$H16)^((12-3)/12))+('DRE + DCF'!$AA$36*(1+M$18)/(($H16-M$18)*(1+$H16)^(COUNT('DRE + DCF'!$V$22:$Z$22)-((12-3)/12)))))*$F$40+$F$42)*(1-$F$39))/$F$10 -> 10.784416 | N16: =(((NPV($H16,'DRE + DCF'!$U$36,'DRE + DCF'!$W$36:$Z$36)*((1+$H16)^((12-3)/12))+('DRE + DCF'!$AA$36*(1+N$18)/(($H16-N$18)*(1+$H16)^(COUNT('DRE + DCF'!$V$22:$Z$22)-((12-3)/12)))))+SUM($F$12:$F$17)))/$F$10-(((NPV($H16,'DRE + DCF'!$U$36,'DRE + DCF'!$W$36:$Z$36)*((1+$H16)^((12-3)/12))+('DRE + DCF'!$AA$36*(1+N$18)/(($H16-N$18)*(1+$H16)^(COUNT('DRE + DCF'!$V$22:$Z$22)-((12-3)/12)))))*$F$40+$F$42)*(1-$F$39))/$F$10 -> 10.923009 | O16: =(((NPV($H16,'DRE + DCF'!$U$36,'DRE + DCF'!$W$36:$Z$36)*((1+$H16)^((12-3)/12))+('DRE + DCF'!$AA$36*(1+O$18)/(($H16-O$18)*(1+$H16)^(COUNT('DRE + DCF'!$V$22:$Z$22)-((12-3)/12)))))+SUM($F$12:$F$17)))/$F$10-(((NPV($H16,'DRE + DCF'!$U$36,'DRE + DCF'!$W$36:$Z$36)*((1+$H16)^((12-3)/12))+('DRE + DCF'!$AA$36*(1+O$18)/(($H16-O$18)*(1+$H16)^(COUNT('DRE + DCF'!$V$22:$Z$22)-((12-3)/12)))))*$F$40+$F$42)*(1-$F$39))/$F$10 -> 11.068961 | P16: =(((NPV($H16,'DRE + DCF'!$U$36,'DRE + DCF'!$W$36:$Z$36)*((1+$H16)^((12-3)/12))+('DRE + DCF'!$AA$36*(1+P$18)/(($H16-P$18)*(1+$H16)^(COUNT('DRE + DCF'!$V$22:$Z$22)-((12-3)/12)))))+SUM($F$12:$F$17)))/$F$10-(((NPV($H16,'DRE + DCF'!$U$36,'DRE + DCF'!$W$36:$Z$36)*((1+$H16)^((12-3)/12))+('DRE + DCF'!$AA$36*(1+P$18)/(($H16-P$18)*(1+$H16)^(COUNT('DRE + DCF'!$V$22:$Z$22)-((12-3)/12)))))*$F$40+$F$42)*(1-$F$39))/$F$10 -> 11.222874 | ... R16: =(((NPV($H16,'DRE + DCF'!$U$36,'DRE + DCF'!$W$36:$Z$36)*((1+$H16)^((12-3)/12))+('DRE + DCF'!$AA$36*(1+R$18)/(($H16-R$18)*(1+$H16)^(COUNT('DRE + DCF'!$V$22:$Z$22)-((12-3)/12)))))+SUM($F$12:$F$17)))/$F$10-(((NPV($H16,'DRE + DCF'!$U$36,'DRE + DCF'!$W$36:$Z$36)*((1+$H16)^((12-3)/12))+('DRE + DCF'!$AA$36*(1+R$18)/(($H16-R$18)*(1+$H16)^(COUNT('DRE + DCF'!$V$22:$Z$22)-((12-3)/12)))))*$F$40+$F$42)*(1-$F$39))/$F$10 -> 11.557337
A17: Projeções 2023 | E17: Passivo Judicial Capital Fechado | F17: =IF(F54>=0,0,F54) -> 0 | H17: =H16+0.5% -> 0.18112663 | I17: =(((NPV($H17,'DRE + DCF'!$U$36,'DRE + DCF'!$W$36:$Z$36)*((1+$H17)^((12-3)/12))+('DRE + DCF'!$AA$36*(1+I$18)/(($H17-I$18)*(1+$H17)^(COUNT('DRE + DCF'!$V$22:$Z$22)-((12-3)/12)))))+SUM($F$12:$F$17)))/$F$10-(((NPV($H17,'DRE + DCF'!$U$36,'DRE + DCF'!$W$36:$Z$36)*((1+$H17)^((12-3)/12))+('DRE + DCF'!$AA$36*(1+I$18)/(($H17-I$18)*(1+$H17)^(COUNT('DRE + DCF'!$V$22:$Z$22)-((12-3)/12)))))*$F$40+$F$42)*(1-$F$39))/$F$10 -> 9.9928438 | J17: =(((NPV($H17,'DRE + DCF'!$U$36,'DRE + DCF'!$W$36:$Z$36)*((1+$H17)^((12-3)/12))+('DRE + DCF'!$AA$36*(1+J$18)/(($H17-J$18)*(1+$H17)^(COUNT('DRE + DCF'!$V$22:$Z$22)-((12-3)/12)))))+SUM($F$12:$F$17)))/$F$10-(((NPV($H17,'DRE + DCF'!$U$36,'DRE + DCF'!$W$36:$Z$36)*((1+$H17)^((12-3)/12))+('DRE + DCF'!$AA$36*(1+J$18)/(($H17-J$18)*(1+$H17)^(COUNT('DRE + DCF'!$V$22:$Z$22)-((12-3)/12)))))*$F$40+$F$42)*(1-$F$39))/$F$10 -> 10.095631 | K17: =(((NPV($H17,'DRE + DCF'!$U$36,'DRE + DCF'!$W$36:$Z$36)*((1+$H17)^((12-3)/12))+('DRE + DCF'!$AA$36*(1+K$18)/(($H17-K$18)*(1+$H17)^(COUNT('DRE + DCF'!$V$22:$Z$22)-((12-3)/12)))))+SUM($F$12:$F$17)))/$F$10-(((NPV($H17,'DRE + DCF'!$U$36,'DRE + DCF'!$W$36:$Z$36)*((1+$H17)^((12-3)/12))+('DRE + DCF'!$AA$36*(1+K$18)/(($H17-K$18)*(1+$H17)^(COUNT('DRE + DCF'!$V$22:$Z$22)-((12-3)/12)))))*$F$40+$F$42)*(1-$F$39))/$F$10 -> 10.203125 | L17: =(((NPV($H17,'DRE + DCF'!$U$36,'DRE + DCF'!$W$36:$Z$36)*((1+$H17)^((12-3)/12))+('DRE + DCF'!$AA$36*(1+L$18)/(($H17-L$18)*(1+$H17)^(COUNT('DRE + DCF'!$V$22:$Z$22)-((12-3)/12)))))+SUM($F$12:$F$17)))/$F$10-(((NPV($H17,'DRE + DCF'!$U$36,'DRE + DCF'!$W$36:$Z$36)*((1+$H17)^((12-3)/12))+('DRE + DCF'!$AA$36*(1+L$18)/(($H17-L$18)*(1+$H17)^(COUNT('DRE + DCF'!$V$22:$Z$22)-((12-3)/12)))))*$F$40+$F$42)*(1-$F$39))/$F$10 -> 10.315658 | M17: =(((NPV($H17,'DRE + DCF'!$U$36,'DRE + DCF'!$W$36:$Z$36)*((1+$H17)^((12-3)/12))+('DRE + DCF'!$AA$36*(1+M$18)/(($H17-M$18)*(1+$H17)^(COUNT('DRE + DCF'!$V$22:$Z$22)-((12-3)/12)))))+SUM($F$12:$F$17)))/$F$10-(((NPV($H17,'DRE + DCF'!$U$36,'DRE + DCF'!$W$36:$Z$36)*((1+$H17)^((12-3)/12))+('DRE + DCF'!$AA$36*(1+M$18)/(($H17-M$18)*(1+$H17)^(COUNT('DRE + DCF'!$V$22:$Z$22)-((12-3)/12)))))*$F$40+$F$42)*(1-$F$39))/$F$10 -> 10.433593 | N17: =(((NPV($H17,'DRE + DCF'!$U$36,'DRE + DCF'!$W$36:$Z$36)*((1+$H17)^((12-3)/12))+('DRE + DCF'!$AA$36*(1+N$18)/(($H17-N$18)*(1+$H17)^(COUNT('DRE + DCF'!$V$22:$Z$22)-((12-3)/12)))))+SUM($F$12:$F$17)))/$F$10-(((NPV($H17,'DRE + DCF'!$U$36,'DRE + DCF'!$W$36:$Z$36)*((1+$H17)^((12-3)/12))+('DRE + DCF'!$AA$36*(1+N$18)/(($H17-N$18)*(1+$H17)^(COUNT('DRE + DCF'!$V$22:$Z$22)-((12-3)/12)))))*$F$40+$F$42)*(1-$F$39))/$F$10 -> 10.557327 | O17: =(((NPV($H17,'DRE + DCF'!$U$36,'DRE + DCF'!$W$36:$Z$36)*((1+$H17)^((12-3)/12))+('DRE + DCF'!$AA$36*(1+O$18)/(($H17-O$18)*(1+$H17)^(COUNT('DRE + DCF'!$V$22:$Z$22)-((12-3)/12)))))+SUM($F$12:$F$17)))/$F$10-(((NPV($H17,'DRE + DCF'!$U$36,'DRE + DCF'!$W$36:$Z$36)*((1+$H17)^((12-3)/12))+('DRE + DCF'!$AA$36*(1+O$18)/(($H17-O$18)*(1+$H17)^(COUNT('DRE + DCF'!$V$22:$Z$22)-((12-3)/12)))))*$F$40+$F$42)*(1-$F$39))/$F$10 -> 10.6873 | P17: =(((NPV($H17,'DRE + DCF'!$U$36,'DRE + DCF'!$W$36:$Z$36)*((1+$H17)^((12-3)/12))+('DRE + DCF'!$AA$36*(1+P$18)/(($H17-P$18)*(1+$H17)^(COUNT('DRE + DCF'!$V$22:$Z$22)-((12-3)/12)))))+SUM($F$12:$F$17)))/$F$10-(((NPV($H17,'DRE + DCF'!$U$36,'DRE + DCF'!$W$36:$Z$36)*((1+$H17)^((12-3)/12))+('DRE + DCF'!$AA$36*(1+P$18)/(($H17-P$18)*(1+$H17)^(COUNT('DRE + DCF'!$V$22:$Z$22)-((12-3)/12)))))*$F$40+$F$42)*(1-$F$39))/$F$10 -> 10.823996 | ... R17: =(((NPV($H17,'DRE + DCF'!$U$36,'DRE + DCF'!$W$36:$Z$36)*((1+$H17)^((12-3)/12))+('DRE + DCF'!$AA$36*(1+R$18)/(($H17-R$18)*(1+$H17)^(COUNT('DRE + DCF'!$V$22:$Z$22)-((12-3)/12)))))+SUM($F$12:$F$17)))/$F$10-(((NPV($H17,'DRE + DCF'!$U$36,'DRE + DCF'!$W$36:$Z$36)*((1+$H17)^((12-3)/12))+('DRE + DCF'!$AA$36*(1+R$18)/(($H17-R$18)*(1+$H17)^(COUNT('DRE + DCF'!$V$22:$Z$22)-((12-3)/12)))))*$F$40+$F$42)*(1-$F$39))/$F$10 -> 11.119755
A18: Processos | E18: Valor da Ação | F18: =SUM($F$11:$F$17)/$F$10 -> 13.488472 | I18: =J18-0.25% -> 0.0669568 | J18: =K18-0.25% -> 0.0694568 | K18: =L18-0.25% -> 0.0719568 | L18: =M18-0.25% -> 0.0744568 | M18: ='DRE + DCF'!AC23 -> 0.0769568 | N18: =M18+0.25% -> 0.0794568 | O18: =N18+0.25% -> 0.0819568 | P18: =O18+0.25% -> 0.0844568 | Q18: =P18+0.25% -> 0.0869568 | R18: =Q18+0.25% -> 0.0894568
E19: Cotação | F19: 7.46 | I19: Growth
E20: =IF(F20=0,"",IF(F20>0,"Upside","Downside")) -> Upside | F20: =IF(F18<0,"-",F18/F19-1) -> 0.80810614
E21: TIR | F21: 0.2395
N24: Preço Teto | O24: 12.93 | P24: 11.31 | Q24: =O24/P24-1 -> 0.14323607
E25: Total Holding | F25: =SUM('Balanço Patrimonial'!O21,'Balanço Patrimonial'!O37) -> 7079945.4 | H25: Empresa | I25: Valor do Equity | J25: Participação Simpar | K25: Valor da Participação da Simpar | O25: =F18*(1-Q24) -> 11.556436
E26: JSL | F26: 1178080 | H26: JSL | I26: 4192902 | J26: 0.7242 | K26: =I26*J26 -> 3036499.6
E27: Movida | F27: 1771126.3 | H27: Movida | I27: 4765369 | J27: 0.6519 | K27: =I27*J27 -> 3106544
E28: Vamos | F28: 2357031.2 | H28: Vamos | I28: 9642272.9 | J28: 0.6906 | K28: =I28*J28 -> 6658953.7
E29: Holding excluindo empresas de capital aberto | F29: =F25-SUM(F26:F28) -> 1773707.9 | H29: Total | K29: =SUM(K26:K28) -> 12801997
E32: Total Holding | F32: =WACC!F19 -> 41596826 | H32: Empresa | I32: Market Cap | J32: Participação Simpar | K32: Valor de mercado da Participação
E33: JSL | F33: -6324340 | H33: JSL | I33: 2497679 | J33: =J26 -> 0.7242 | K33: =I33*J33 -> 1808819.1
E34: Movida | F34: -13731980 | H34: Movida | I34: 3623020.9 | J34: =J27 -> 0.6519 | K34: =I34*J34 -> 2361847.3
E35: Vamos | F35: -12307704 | H35: Vamos | I35: 9850575.2 | J35: =J28 -> 0.6906 | K35: =I35*J35 -> 6802807.2
E36: Holding excluindo empresas de capital aberto | F36: =SUM(F32:F35) -> 9232802 | H36: Holding + Empresas de Capital Fechado | K36: =K37-SUM(K33:K35) -> -4718950.6
H37: Simpar | I37: =F19*F10 -> 6254523 | J37: 1 | K37: =J37*I37 -> 6254523
E39: Participação da Simpar na Automob | F39: 0.794
E40: % médio do EBIT projetado que vem da Automob | F40: =AVERAGE('Projeções - Receita e EBIT'!$Q$57:$U$57) -> 0.55262022
E41: Valor da Empresa da Automob baseado no EBIT | F41: =F11*F40 -> 4507791.3
E42: Dívida Líquida Automob | F42: 1050800
E43: Valor do Equity Automob | F43: =F41+F42 -> 5558591.3
E44: Valor do Equity da Automob que não pertence à Simpar | F44: =F43*(1-$F$39) -> 1145069.8
E48: Total Holding | F48: =WACC!F35 -> 0
E49: JSL | F49: -596787
E50: Movida | F50: 0
E51: Vamos | F51: -86952
E52: Holding excluindo empresas de capital aberto | F52: =SUM(F48:F51) -> -683739
E53: Holding Total | F53: =('Balanço Patrimonial'!O82-'Balanço Patrimonial'!O42)*-1 -> -679970
E54: Total Holding | F54: =F53-F52 -> 3769

Sheet WACC
F3: =Dashboard!$H$3 -> SIMPAR (SIMH3)
A7: Páginas
A8: Dashboard
A9: WACC | E9: Atualizado em: 08/11/2023 | F9: 2023 | G9: =F9+1 -> 2024 | H9: =G9+1 -> 2025 | I9: =H9+1 -> 2026 | J9: =I9+1 -> 2027 | K9: =J9+1 -> 2028 | L9: =K9+1 -> 2029 | M9: =L9+1 -> 2030 | N9: =M9+1 -> 2031 | ... P9: =O9+1 -> 2033
A10: DRE Consolidado | E10: DI | F10: 0.12008 | G10: 0.1082 | H10: 0.1062 | I10: 0.10765 | J10: 0.10959 | K10: 0.1113 | L10: 0.11248 | M10: 0.1132 | N10: 0.11362 | O10: 0.1139 | P10: 0.1139
A11: DRE + DCF | E11: CDS | F11: 0.0039 | G11: 0.003834174 | H11: 0.006638106 | I11: 0.009806918 | J11: 0.013433968 | K11: 0.017234112 | L11: 0.0206891 | M11: 0.023531264 | N11: 0.025541019 | O11: 0.02649878 | P11: 0.026184965
A12: DRE - Contas Abertas | E12: Inflação Implícita | F12: 0.0418 | G12: 0.04217 | H12: 0.04334 | I12: 0.04552 | J12: 0.04854 | K12: 0.05087 | L12: 0.05238 | M12: 0.0543 | N12: 0.05521 | O12: 0.05562 | P12: 0.05584
A13: Balanço Patrimonial | E13: Taxa Livre de Risco | F13: =F10-F11 -> 0.11618 | G13: =G10-G11 -> 0.10436583 | H13: =H10-H11 -> 0.099561894 | I13: =I10-I11 -> 0.097843082 | J13: =J10-J11 -> 0.096156032 | K13: =K10-K11 -> 0.094065888 | L13: =L10-L11 -> 0.0917909 | M13: =M10-M11 -> 0.089668736 | ... P13: =P10-P11 -> 0.087715035
A14: Painel de Índices | E14: Beta | F14: 2 | G14: =F14 -> 2 | H14: =G14 -> 2 | I14: =H14 -> 2 | J14: =I14 -> 2 | K14: =J14 -> 2 | L14: =K14 -> 2 | M14: =L14 -> 2 | N14: =M14 -> 2 | ... P14: =O14 -> 2
A15: Projeções - Receita e EBIT | E15: Prêmio de Risco | F15: 0.065 | G15: 0.065 | H15: 0.065 | I15: 0.065 | J15: 0.065 | K15: 0.065 | L15: 0.065 | M15: 0.065 | N15: 0.065 | O15: 0.065 | P15: 0.065
A16: Projeções - CG + Capex | E16: Custo de Capital Próprio (Ke) | F16: =F13+(F14*F15) -> 0.24618 | G16: =G13+(G14*G15) -> 0.23436583 | H16: =H13+(H14*H15) -> 0.22956189 | I16: =I13+(I14*I15) -> 0.22784308 | J16: =J13+(J14*J15) -> 0.22615603 | K16: =K13+(K14*K15) -> 0.22406589 | L16: =L13+(L14*L15) -> 0.2217909 | M16: =M13+(M14*M15) -> 0.21966874 | ... P16: =P13+(P14*P15) -> 0.21771504
A17: Projeções 2023 | E17: Valor Justo do Equity (R$ Mil) | F17: 11192746 | G17: =F17 -> 11192746 | H17: =G17 -> 11192746 | I17: =H17 -> 11192746 | J17: =I17 -> 11192746 | K17: =J17 -> 11192746 | L17: =K17 -> 11192746 | M17: =L17 -> 11192746 | N17: =M17 -> 11192746 | ... P17: =O17 -> 11192746
A18: Processos | E18: Custo de Capital de Terceiros (Kd) | F18: =F10+3.2% -> 0.15208 | G18: =G10+3.2% -> 0.1402 | H18: =H10+3.2% -> 0.1382 | I18: =I10+3.2% -> 0.13965 | J18: =J10+3.2% -> 0.14159 | K18: =K10+3.2% -> 0.1433 | L18: =L10+3.2% -> 0.14448 | M18: =M10+3.2% -> 0.1452 | ... P18: =P10+3.2% -> 0.1459
E19: Dívida Bruta (R$ Mil) | F19: =SUM('Balanço Patrimonial'!O55:O60,'Balanço Patrimonial'!O74:O77) -> 41596826 | G19: =F19 -> 41596826 | H19: =G19 -> 41596826 | I19: =H19 -> 41596826 | J19: =I19 -> 41596826 | K19: =J19 -> 41596826 | L19: =K19 -> 41596826 | M19: =L19 -> 41596826 | N19: =M19 -> 41596826 | ... P19: =O19 -> 41596826
E20: WACC | F20: =((F16*F17)+(F18*F19))/(F17+F19) -> 0.17203162 | G20: =((G16*G17)+(G18*G19))/(G17+G19) -> 0.16016557 | H20: =((H16*H17)+(H18*H19))/(H17+H19) -> 0.15757107 | I20: =((I16*I17)+(I18*I19))/(I17+I19) -> 0.1583492 | J20: =((J16*J17)+(J18*J19))/(J17+J19) -> 0.15952017 | K20: =((K16*K17)+(K18*K19))/(K17+K19) -> 0.16042444 | L20: =((L16*L17)+(L18*L19))/(L17+L19) -> 0.1608719 | M20: =((M16*M17)+(M18*M19))/(M17+M19) -> 0.16098929 | ... P20: =((P16*P17)+(P18*P19))/(P17+P19) -> 0.16112663
E21: Desconto | F21: =1*(1+F20)^((12-9)/12) -> 1.0404826 | G21: =F21*(1+G20) -> 1.2071321 | H21: =G21*(1+H20) -> 1.3973412 | I21: =H21*(1+I20) -> 1.6186091 | J21: =I21*(1+J20) -> 1.8768099 | K21: =J21*(1+K20) -> 2.1778961 | L21: =K21*(1+L20) -> 2.5282583 | M21: =L21*(1+M20) -> 2.9352808 | N21: =M21*(1+N20) -> 3.4078116 | ... P21: =O21*(1+P20) -> 4.5941997

Sheet DRE Consolidado
K2: =Dashboard!H3 -> SIMPAR (SIMH3)
A7: Páginas
A8: Dashboard
A9: WACC
A10: DRE Consolidado
A11: DRE + DCF
A12: DRE - Contas Abertas | E12: Data do Último Resultado: | K12: 2014 | L12: 2015 | M12: 2016 | N12: 2017 | O12: 2018 | P12: 2019 | Q12: 2020 | R12: 2021 | S12: 2022 | T12: YTD 2023 | U12: YTG 2023E | V12: 2023 | W12: 2024 | X12: 2025 | Y12: 2026 | Z12: 2027
A13: Balanço Patrimonial | E13: Receita Bruta | K13: 6079086.1 | L13: 6561486.7 | M13: 7403983 | N13: 8199829 | O13: 9203466 | P13: 10734355 | Q13: 10874860 | R13: 15453380 | S13: 26844012
A14: Painel de Índices | E14: Deduções | K14: =-(K13-K16) -> -539892.08 | L14: =-(L13-L16) -> -571574.68 | M14: =-(M13-M16) -> -880867 | N14: =-(N13-N16) -> -944025 | O14: =-(O13-O16) -> -1128077 | P14: =-(P13-P16) -> -1048146.5 | Q14: =-(Q13-Q16) -> -1067803 | R14: =-(R13-R16) -> -1587161 | S14: -2462220.7
A15: Projeções - Receita e EBIT | E15: % da Receita Bruta | K15: =-K14/K13 -> 0.088811389 | L15: =-L14/L13 -> 0.087110545 | M15: =-M14/M13 -> 0.11897205 | N15: =-N14/N13 -> 0.1151274 | O15: =-O14/O13 -> 0.12257089 | P15: =-P14/P13 -> 0.097644102 | Q15: =-Q14/Q13 -> 0.098190046 | R15: =-R14/R13 -> 0.1027064 | S15: =-S14/S13 -> 0.091723277
A16: Projeções - CG + Capex | E16: Receita Líquida | K16: 5539194 | L16: 5989912 | M16: 6523116 | N16: 7255804 | O16: 8075389 | P16: 9686209 | Q16: 9807057 | R16: 13866219 | S16: 24381791 | T16: 23321789 | U16: =V16-SUM(T16:T16) -> 8336165.1 | V16: ='Projeções - Receita e EBIT'!Q10 -> 31657954 | W16: ='Projeções - Receita e EBIT'!R10 -> 39929183 | X16: ='Projeções - Receita e EBIT'!S10 -> 47076707 | Y16: ='Projeções - Receita e EBIT'!T10 -> 52864437 | Z16: ='Projeções - Receita e EBIT'!U10 -> 58805341
A17: Projeções 2023 | E17: Crescimento da Receita (YoY)¹ | K17: 0 | L17: =L16/K16-1 -> 0.081368878 | M17: =M16/L16-1 -> 0.089017001 | N17: =N16/M16-1 -> 0.11232178 | O17: =O16/N16-1 -> 0.11295578 | P17: =P16/O16-1 -> 0.19947274 | Q17: =Q16/P16-1 -> 0.012476295 | R17: =R16/Q16-1 -> 0.41390215 | S17: =S16/R16-1 -> 0.758359 | V17: =V16/S16-1 -> 0.29842611 | W17: =W16/V16-1 -> 0.26126858 | X17: =X16/W16-1 -> 0.17900502 | Y17: =Y16/X16-1 -> 0.12294253 | Z17: =Z16/Y16-1 -> 0.11237998
A18: Processos | E18: Custos das Vendas e Serviços | K18: -3865141 | L18: -3974936 | M18: -3936687 | N18: -4032052 | O18: -4699220 | P18: -5102646 | Q18: -5168883 | R18: -7304534 | S18: -12624428 | T18: -12628498
E19: Custo de Construção | F19: Custo de Construção | T19: -82622
A20: Gráficos | E20: Custo de Venda de Ativos Desmobilizados | K20: -681231 | L20: -877618 | M20: -1289069 | N20: -1737637 | O20: -1609867 | P20: -2524180 | Q20: -2618101 | R20: -2077780 | S20: -4166192 | T20: -4104310
E21: Lucro Bruto | K21: =K16+K18+K20 -> 992822 | L21: =L16+L18+L20 -> 1137358 | M21: =M16+M18+M20 -> 1297360 | N21: =N16+N18+N20 -> 1486115 | O21: =O16+O18+O20 -> 1766302 | P21: =P16+P18+P20 -> 2059383 | Q21: =Q16+Q18+Q20 -> 2020073 | R21: =R16+R18+R20 -> 4483905 | S21: =S16+S18+S20 -> 7591171 | T21: =T16+T18+T19+T20 -> 6506359
E22: Margem Bruta | K22: =K21/K16 -> 0.17923582 | L22: =L21/L16 -> 0.18987892 | M22: =M21/M16 -> 0.19888654 | N22: =N21/N16 -> 0.20481741 | O22: =O21/O16 -> 0.21872655 | P22: =P21/P16 -> 0.2126098 | Q22: =Q21/Q16 -> 0.20598157 | R22: =R21/R16 -> 0.32336897 | ... T22: =T21/T16 -> 0.27898199
E23: Despesas/ Receitas Operacionais | K23: =SUM(K24,K26,K28,K29,K32) -> -532720 | L23: =SUM(L24,L26,L28,L29,L32) -> -553903 | M23: =SUM(M24,M26,M28,M29,M32) -> -798577 | N23: =SUM(N24,N26,N28,N29,N32) -> -781645 | O23: =SUM(O24,O26,O28,O29,O32) -> -805585 | P23: =SUM(P24,P26,P28,P29,P32) -> -860218 | Q23: =SUM(Q24,Q26,Q28,Q29,Q32) -> -990091 | R23: =SUM(R24,R26,R28,R29,R32) -> -1353354 | ... T23: =SUM(T24,T26,T28,T29,T32) -> -2233284
E24: Despesas Tributárias | K24: -8093 | L24: -9584 | M24: 0 | N24: 0 | O24: 0 | P24: 0 | Q24: 0 | R24: 0 | S24: 0 | T24: 0
E25: (%) da Receita Líquida | K25: =-K24/K16 -> 0.0014610429 | L25: =-L24/L16 -> 0.0016000235 | M25: =-M24/M16 -> 0 | N25: =-N24/N16 -> 0 | O25: =-O24/O16 -> 0 | P25: =-P24/P16 -> 0 | Q25: =-Q24/Q16 -> 0 | R25: =-R24/R16 -> 0 | ... T25: =-T24/T16 -> 0
E26: Despesas Comerciais Gerais e Administrativas | K26: -491535 | L26: -510134 | M26: -684175 | N26: -746102 | O26: -794421 | P26: =-571098-293107 -> -864205 | Q26: -896692 | R26: -1398455 | S26: =-884377-1397532 -> -2281909 | T26: =-880719-1344926 -> -2225645
E27: (%) da Receita Líquida | K27: =-K26/K16 -> 0.088737639 | L27: =-L26/L16 -> 0.085165525 | M27: =-M26/M16 -> 0.10488469 | N27: =-N26/N16 -> 0.1028283 | O27: =-O26/O16 -> 0.098375571 | P27: =-P26/P16 -> 0.089220148 | Q27: =-Q26/Q16 -> 0.091433342 | R27: =-R26/R16 -> 0.10085338 | ... T27: =-T26/T16 -> 0.095432001
E28: Perdas pela Não Recuperabilidade de Ativos | K28: 0 | L28: 0 | M28: 0 | N28: 0 | O28: -9146 | P28: -32527 | Q28: -78667 | R28: -56164 | S28: -127315 | T28: -153092
E29: Resultado Operacional Outros | K29: =SUM(K30:K31) -> -33186 | L29: =SUM(L30:L31) -> -34256 | M29: =SUM(M30:M31) -> -114402 | N29: =SUM(N30:N31) -> -35543 | O29: =SUM(O30:O31) -> -1058 | P29: =SUM(P30:P31) -> 37715 | Q29: =SUM(Q30:Q31) -> -14217 | R29: =SUM(R30:R31) -> 102799 | ... T29: =SUM(T30:T31) -> 142529
E30: Outras Receitas Operacionais | K30: -33186 | L30: -34256 | M30: -114402 | N30: -35543 | O30: -1058 | P30: 37715 | Q30: -14217 | R30: 102799 | S30: 0 | T30: 142529
E31: Outras Despesas Operacionais | K31: 0 | L31: 0 | M31: 0 | N31: 0 | O31: 0 | P31: 0 | Q31: 0 | R31: 0 | S31: -67941 | T31: 0
E32: Resultado de Equivalência Patrimonial | K32: 94 | L32: 71 | M32: 0 | N32: 0 | O32: -960 | P32: -1201 | Q32: -515 | R32: -1534 | S32: 2810 | T32: 2924
E33: EBITDA | K33: =K34+K55+'Projeções - CG + Capex'!K57 -> 868967 | L33: =L34+L55+'Projeções - CG + Capex'!L57 -> 1092081 | M33: =M34+M55+'Projeções - CG + Capex'!M57 -> 1045970 | N33: =N34+N55+'Projeções - CG + Capex'!N57 -> 1230201 | O33: =O34+O55+'Projeções - CG + Capex'!O57 -> 1597534 | P33: =P34+P55+'Projeções - CG + Capex'!P57 -> 2115909 | Q33: =Q34+Q55+'Projeções - CG + Capex'!Q57 -> 2141935 | R33: =R34+R55+'Projeções - CG + Capex'!R57 -> 4189665 | ... T33: =T34+T55+'Projeções - CG + Capex'!T57 -> 6316302
E34: EBIT | K34: =K21+K23 -> 460102 | L34: =L21+L23 -> 583455 | M34: =M21+M23 -> 498783 | N34: =N21+N23 -> 704470 | O34: =O21+O23 -> 960717 | P34: =P21+P23 -> 1199165 | Q34: =Q21+Q23 -> 1029982 | R34: =R21+R23 -> 3130551 | ... T34: =T21+T23 -> 4273075 | U34: =U16*U37 -> 1444175.9
E35: Eventos não Recorrentes | K35: ='DRE - Contas Abertas'!F56 -> -24516 | L35: ='DRE - Contas Abertas'!I56 -> 34204 | M35: ='DRE - Contas Abertas'!J56 -> 30444 | N35: ='DRE - Contas Abertas'!I56 -> 34204 | O35: ='DRE - Contas Abertas'!J56 -> 30444 | P35: ='DRE - Contas Abertas'!K56 -> -929 | Q35: ='DRE - Contas Abertas'!L56 -> -141683 | R35: ='DRE - Contas Abertas'!M56 -> 107566 | S35: ='DRE - Contas Abertas'!N56 -> 12526 | T35: ='DRE - Contas Abertas'!O56+254800 -> 232756
E36: EBIT Recorrente | K36: =SUM(K34-K35) -> 484618 | L36: =SUM(L34-L35) -> 549251 | M36: =SUM(M34-M35) -> 468339 | N36: =SUM(N34-N35) -> 670266 | O36: =SUM(O34-O35) -> 930273 | P36: =SUM(P34-P35) -> 1200094 | Q36: =SUM(Q34-Q35) -> 1171665 | R36: =SUM(R34-R35) -> 3022985 | ... T36: =SUM(T34-T35) -> 4040319 | U36: =U34 -> 1444175.9
E37: Margem EBIT | K37: =K36/K16 -> 0.087488902 | L37: =L36/L16 -> 0.091696005 | M37: =M36/M16 -> 0.071796822 | N37: =N36/N16 -> 0.092376531 | O37: =O36/O16 -> 0.11519854 | P37: =P36/P16 -> 0.12389718 | Q37: =Q36/Q16 -> 0.11947162 | R37: =R36/R16 -> 0.21801076 | ... T37: =T36/T16 -> 0.17324224 | U37: =T37 -> 0.17324224
E38: Resultado Financeiro | K38: =SUM(K39:K40) -> -348965 | L38: =SUM(L39:L40) -> -516233 | M38: =SUM(M39:M40) -> -748253 | N38: =SUM(N39:N40) -> -670541 | O38: =SUM(O39:O40) -> -681219 | P38: =SUM(P39:P40) -> -768039 | Q38: =SUM(Q39:Q40) -> -374776 | R38: =SUM(R39:R40) -> -1217593 | ... T38: =SUM(T39:T40) -> -4352447
E39: Receitas Financeiras | K39: 109484 | L39: 198480 | M39: 201723 | N39: 209555 | O39: 317809 | P39: 365336 | Q39: 679426 | R39: 736362 | S39: 1229042 | T39: 837998
E40: Despesas Financeiras | K40: -458449 | L40: -714713 | M40: -949976 | N40: -880096 | O40: -999028 | P40: -1133375 | Q40: -1054202 | R40: -1953955 | S40: -5358473 | T40: -5190445
E41: Resultado Antes dos Tributos Sobre o Lucro | K41: =K34+K38 -> 111137 | L41: =L34+L38 -> 67222 | M41: =M34+M38 -> -249470 | N41: =N34+N38 -> 33929 | O41: =O34+O38 -> 279498 | P41: =P34+P38 -> 431126 | Q41: =Q34+Q38 -> 655206 | R41: =R34+R38 -> 1912958 | ... T41: =T34+T38 -> -79372
E42: Imposto de Renda e CSLL | K42: =K43+K44 -> -38697 | L42: =L43+L44 -> -20461 | M42: =M43+M44 -> 66296 | N42: =N43+N44 -> -17211 | O42: =O43+O44 -> -90328 | P42: =P43+P44 -> -112501 | Q42: =Q43+Q44 -> -229167 | R42: =R43+R44 -> -584008 | ... T42: =T43+T44 -> 145549
E43: Corrente | K43: -19885 | L43: -13925 | M43: -21844 | N43: -30178 | O43: -72495 | P43: -68869 | Q43: -177605 | R43: -126774 | S43: -117262 | T43: -86034
E44: Diferido | K44: -18812 | L44: -6536 | M44: 88140 | N44: 12967 | O44: -17833 | P44: -43632 | Q44: -51562 | R44: -457234 | S44: 70584 | T44: 231583
E45: Resultado Líquido de Operações Continuadas | K45: =K41+K42 -> 72440 | L45: =L41+L42 -> 46761 | M45: =M41+M42 -> -183174 | N45: =N41+N42 -> 16718 | O45: =O41+O42 -> 189170 | P45: =P41+P42 -> 318625 | Q45: =Q41+Q42 -> 426039 | R45: =R41+R42 -> 1328950 | ... T45: =T41+T42 -> 66177
E46: Lucro das operações descontinuadas, líquido de impostos | F46: Atribuído a Sócios da Empresa Controladora | K46: 0 | L46: 0 | M46: 0 | N46: 0 | O46: 0 | P46: 0 | Q46: -28539 | R46: 0
E47: Participação de não controladores | K47: 1 | L47: 1 | M47: 0 | N47: 0 | O47: 0 | P47: 0 | Q47: 0 | R47: 0
E48: Lucro Líquido do exercício | K48: =SUM(K45:K47) -> 72441 | L48: =SUM(L45:L47) -> 46762 | M48: =SUM(M45:M47) -> -183174 | N48: =SUM(N45:N47) -> 16718 | O48: =SUM(O45:O47) -> 189170 | P48: =SUM(P45:P47) -> 318625 | Q48: =SUM(Q45:Q47) -> 397500 | R48: =SUM(R45:R47) -> 1328950 | ... T48: =SUM(T45:T47) -> 66177
E49: Margem Líquida | K49: =K45/K16 -> 0.013077715 | L49: =L45/L16 -> 0.0078066255 | M49: =M45/M16 -> -0.028080752 | N49: =N45/N16 -> 0.0023040865 | O49: =O45/O16 -> 0.023425497 | P49: =P45/P16 -> 0.032894706 | Q49: =Q45/Q16 -> 0.043442085 | R49: =R45/R16 -> 0.095840834 | ... T49: =T45/T16 -> 0.002837561
K53: 2014 | L53: 2015 | M53: 2016 | N53: 2017 | O53: 2018 | P53: 2019 | Q53: 2020 | R53: 2021 | S53: 2022 | T53: YTD 2023 | U53: YTG 2023E | V53: 2023 | W53: 2024 | X53: 2025 | Y53: 2026 | Z53: 2027
E54: Alíquota Efetiva | F54: 0.030034188 | G54: -0.02092541 | H54: -0.043315116 | I54: 0.13811998 | J54: -0.59211219 | K54: =IFERROR(IF(K34>0,-K42/K34,"-"),"-") -> 0.084105264 | L54: =IFERROR(IF(L34>0,-L42/L34,"-"),"-") -> 0.035068686 | M54: =IFERROR(IF(M34>0,-M42/M34,"-"),"-") -> -0.13291552 | N54: =IFERROR(IF(N34>0,-N42/N34,"-"),"-") -> 0.024431133 | O54: =IFERROR(IF(O34>0,-O42/O34,"-"),"-") -> 0.094021444 | P54: =IFERROR(IF(P34>0,-P42/P34,"-"),"-") -> 0.093816114 | Q54: =IFERROR(IF(Q34>0,-Q42/Q34,"-"),"-") -> 0.22249612 | R54: =IFERROR(IF(R34>0,-R42/R34,"-"),"-") -> 0.18655119 | ... U54: =IFERROR(IF(U34>0,-U42/U34,"-"),"-") -> 0 | V54: =AVERAGE($P$54:$S$54) -> 0.12799647
E55: D&A do Arrendamento | P55: ='Projeções - CG + Capex'!P48 -> 127308 | Q55: ='Projeções - CG + Capex'!Q48 -> 129146 | R55: ='Projeções - CG + Capex'!R48 -> 186383 | S55: ='Projeções - CG + Capex'!S48 -> 199519 | T55: ='Projeções - CG + Capex'!T48 -> 304173 | U55: ='Projeções - CG + Capex'!U48 -> 0 | V55: =V56*V16 -> 419503.97
E56: D&A do Arrendamento como (%) da Receita | K56: =K55/K16 -> 0 | L56: =L55/L16 -> 0 | M56: =M55/M16 -> 0 | N56: =N55/N16 -> 0 | O56: =O55/O16 -> 0 | P56: =P55/P16 -> 0.013143222 | Q56: =Q55/Q16 -> 0.01316868 | R56: =R55/R16 -> 0.013441516 | ... U56: =U55/U16 -> 0 | V56: =AVERAGE(P56:R56) -> 0.01325114
E57: NOPAT | F57: 215718 | G57: 230388 | H57: 181530 | I57: -272310 | J57: -42610 | K57: =K36+K42+K55 -> 445921 | L57: =L36+L42+L55 -> 528790 | M57: =M36+M42+M55 -> 534635 | N57: =N36+N42+N55 -> 653055 | O57: =O36+O42+O55 -> 839945 | P57: =P36+P42+P55 -> 1214901 | Q57: =Q36+Q42+Q55 -> 1071644 | R57: =R36+R42+R55 -> 2625360 | ... U57: =U36+U42+U55 -> 1444175.9
K61: 2014 | L61: 2015 | M61: 2016 | N61: 2017 | O61: 2018 | P61: 2019 | Q61: 2020 | R61: 2021 | S61: 2022 | T61: YTD 2023 | U61: YTG 2023E | V61: 2023 | W61: 2024 | X61: 2025 | Y61: 2026 | Z61: 2027
E62: JSL | F62: 0.030034188 | G62: -0.02092541 | H62: -0.043315116 | I62: 0.13811998 | J62: -0.59211219 | N62: ='[1]DRE + DCF'!K61 -> 569446 | O62: ='[1]DRE + DCF'!L61 -> 479168.73 | P62: ='[1]DRE + DCF'!M61 -> 171363.26 | Q62: ='[1]DRE + DCF'!N61 -> 43916.532 | R62: ='[1]DRE + DCF'!O61 -> -883487.04 | S62: ='[1]DRE + DCF'!P61 -> -56785.488 | T62: ='[1]DRE + DCF'!Q61 -> -219286.59 | U62: ='[1]DRE + DCF'!R61 -> -702244.05 | ... Y62: ='[1]DRE + DCF'!V61 -> 53410.305 | Z62: 1110462.8
E63: Movida | N63: ='[2]DRE + DCF'!M62 -> -478120.25 | O63: ='[2]DRE + DCF'!N62 -> -575059.4 | P63: ='[2]DRE + DCF'!O62 -> -682431.13 | Q63: ='[2]DRE + DCF'!P62 -> -773022 | R63: ='[2]DRE + DCF'!Q62 -> -3740226 | S63: ='[2]DRE + DCF'!R62 -> -3112013.1 | T63: ='[2]DRE + DCF'!S62 -> 1426707.1 | U63: ='[2]DRE + DCF'!T62 -> 456183.39 | ... Y63: ='[2]DRE + DCF'!X62 -> -143424.27 | Z63: -26076.631
E64: Vamos | N64: ='[3]DRE + DCF'!L61 -> 18384.976 | O64: ='[3]DRE + DCF'!M61 -> -78986.538 | P64: ='[3]DRE + DCF'!N61 -> -280288.13 | Q64: ='[3]DRE + DCF'!O61 -> -10630.655 | R64: ='[3]DRE + DCF'!P61 -> -2176840.3 | S64: ='[3]DRE + DCF'!Q61 -> -2191445.7 | T64: ='[3]DRE + DCF'!R61 -> -4824831.6 | U64: ='[3]DRE + DCF'!S61 -> -565018.2 | ... Y64: ='[3]DRE + DCF'!W61 -> -121163.41 | Z64: 319387.74
E65: Capital Fechado | O65: ='DRE + DCF'!O36 -> -129493.34 | P65: ='DRE + DCF'!P36 -> -141557 | Q65: ='DRE + DCF'!Q36 -> 1214.0085 | R65: ='DRE + DCF'!R36 -> -225151.37 | S65: ='DRE + DCF'!S36 -> -1200461.1 | T65: ='DRE + DCF'!T36 -> -456434.73 | U65: ='DRE + DCF'!U36 -> -344974.06 | V65: ='DRE + DCF'!V36 -> -801408.79 | ... Z65: ='DRE + DCF'!Z36 -> 1274247.5
E66: Total | F66: 215718 | G66: 230388 | H66: 181530 | I66: -272310 | J66: -42610 | N66: =SUM(N62:N65) -> 109710.73 | O66: =SUM(O62:O65) -> -304370.54 | P66: =SUM(P62:P65) -> -932912.99 | Q66: =SUM(Q62:Q65) -> -738522.11 | R66: =SUM(R62:R65) -> -7025704.7 | S66: =SUM(S62:S65) -> -6560705.3 | T66: =SUM(T62:T65) -> -4073845.8 | U66: =SUM(U62:U65) -> -1156052.9 | ... Z66: =SUM(Z62:Z65) -> 2678021.5
K70: 2014 | L70: 2015 | M70: 2016 | N70: 2017 | O70: 2018 | P70: 2019 | Q70: 2020 | R70: 2021 | S70: 2022 | T70: YTD 2023 | U70: YTG 2023E | V70: 2023 | W70: 2024 | X70: 2025 | Y70: 2026 | Z70: 2027
E71: JSL | F71: 0.030034188 | G71: -0.02092541 | H71: -0.043315116 | I71: 0.13811998 | J71: -0.59211219 | N71: ='[1]DRE + DCF'!K28 -> 378729 | O71: ='[1]DRE + DCF'!L28 -> 406833.83 | P71: ='[1]DRE + DCF'!M28 -> 512702.29 | Q71: ='[1]DRE + DCF'!N28 -> 431386 | R71: ='[1]DRE + DCF'!O28 -> 758072.49 | S71: ='[1]DRE + DCF'!P28 -> 1079820 | T71: ='[1]DRE + DCF'!Q28 -> 1312338 | U71: ='[1]DRE + DCF'!R28 -> 0 | ... Y71: ='[1]DRE + DCF'!V28 -> 2131679.3 | Z71: 2348770.9
E72: Movida | N72: ='[2]DRE + DCF'!M27 -> 326351 | O72: ='[2]DRE + DCF'!N27 -> 481738 | P72: ='[2]DRE + DCF'!O27 -> 743193 | Q72: ='[2]DRE + DCF'!P27 -> 717181 | R72: ='[2]DRE + DCF'!Q27 -> 2082987 | S72: ='[2]DRE + DCF'!R27 -> 3551973 | T72: ='[2]DRE + DCF'!S27 -> 2633259 | U72: ='[2]DRE + DCF'!T27 -> 878057.78 | ... Y72: ='[2]DRE + DCF'!X27 -> 4764926.8 | Z72: 5031132.4
E73: Vamos | N73: ='[3]DRE + DCF'!L28 -> 304993 | O73: ='[3]DRE + DCF'!M28 -> 426119 | P73: ='[3]DRE + DCF'!N28 -> 527624 | Q73: ='[3]DRE + DCF'!O28 -> 638774 | R73: ='[3]DRE + DCF'!P28 -> 1049744 | S73: ='[3]DRE + DCF'!Q28 -> 1933140 | T73: ='[3]DRE + DCF'!R28 -> 2007122 | U73: ='[3]DRE + DCF'!S28 -> 619106.99 | ... Y73: ='[3]DRE + DCF'!W28 -> 5332492.5 | Z73: 5917441.1
E74: Capital Fechado | O74: ='DRE + DCF'!O14 -> 278146 | P74: ='DRE + DCF'!P14 -> 339526 | Q74: ='DRE + DCF'!Q14 -> 354594 | R74: ='DRE + DCF'!R14 -> 298861 | S74: ='DRE + DCF'!S14 -> 590052 | T74: ='DRE + DCF'!T14 -> 363582 | U74: ='DRE + DCF'!U14 -> 348859.95 | V74: ='DRE + DCF'!V14 -> 712441.95 | ... Z74: ='DRE + DCF'!Z14 -> 1725128
E75: Total | F75: 215718 | G75: 230388 | H75: 181530 | I75: -272310 | J75: -42610 | N75: =SUM(N71:N74) -> 1010073 | O75: =SUM(O71:O74) -> 1592836.8 | P75: =SUM(P71:P74) -> 2123045.3 | Q75: =SUM(Q71:Q74) -> 2141935 | R75: =SUM(R71:R74) -> 4189664.5 | S75: =SUM(S71:S74) -> 7154985 | T75: =SUM(T71:T74) -> 6316301 | U75: =SUM(U71:U74) -> 1846024.7 | ... Z75: =SUM(Z71:Z74) -> 15022472
E77: ¹- "YoY", ou "year over year", significa "de um ano pro outro".

Sheet DRE + DCF
K2: =Dashboard!H3 -> SIMPAR (SIMH3)
A7: Páginas
A8: Dashboard
A9: WACC
A10: DRE Consolidado
A11: DRE + DCF
A12: DRE - Contas Abertas | K12: 2014 | L12: 2015 | M12: 2016 | N12: 2017 | O12: 2018 | P12: 2019 | Q12: 2020 | R12: 2021 | S12: 2022 | T12: YTD 2023 | U12: YTG 2023E | V12: 2023 | W12: 2024 | X12: 2025 | Y12: 2026 | Z12: 2027E
A13: Balanço Patrimonial | E13: Receita Líquida Ex empresas de capital aberto | O13: =SUM('Projeções - Receita e EBIT'!J16:J21) -> 1415123 | P13: =SUM('Projeções - Receita e EBIT'!K16:K21) -> 1536679 | Q13: =SUM('Projeções - Receita e EBIT'!L16:L21) -> 1381814 | R13: =SUM('Projeções - Receita e EBIT'!M16:M21) -> 1414123 | S13: =SUM('Projeções - Receita e EBIT'!N16:N21) -> 3845902 | T13: =SUM('Projeções - Receita e EBIT'!O16:O21) -> 5427196 | U13: =V13-T13 -> 1810933.6 | V13: =SUM('Projeções - Receita e EBIT'!Q16:Q21) -> 7238129.6 | W13: =SUM('Projeções - Receita e EBIT'!R16:R21) -> 9847123 | X13: =SUM('Projeções - Receita e EBIT'!S16:S21) -> 10473362 | Y13: =SUM('Projeções - Receita e EBIT'!T16:T21) -> 11109057 | Z13: =SUM('Projeções - Receita e EBIT'!U16:U21) -> 11828495
E14: EBITDA Excluindo Empresas de Capital Aberto | O14: =O15+O24+O32 -> 278146 | P14: =P15+P24+P32 -> 339526 | Q14: =Q15+Q24+Q32 -> 354594 | R14: =R15+R24+R32 -> 298861 | S14: =S15+S24+S32 -> 590052 | T14: =T15+T24+T32 -> 363582 | U14: =U15+U24+U32 -> 348859.95 | V14: =V15+V24+V32 -> 712441.95 | ... Z14: =Z15+Z24+Z32 -> 1725128
A15: Painel de Índices | E15: EBIT Recorrente Excluindo Empresas de Capital Aberto | O15: =SUM('Projeções - Receita e EBIT'!J37+'Projeções - Receita e EBIT'!J56+'Projeções - Receita e EBIT'!J75+'Projeções - Receita e EBIT'!J98+'Projeções - Receita e EBIT'!J115+'Projeções - Receita e EBIT'!J133) -> 127598 | P15: =SUM('Projeções - Receita e EBIT'!K37+'Projeções - Receita e EBIT'!K56+'Projeções - Receita e EBIT'!K75+'Projeções - Receita e EBIT'!K98+'Projeções - Receita e EBIT'!K115+'Projeções - Receita e EBIT'!K133) -> 164843 | Q15: =SUM('Projeções - Receita e EBIT'!L37+'Projeções - Receita e EBIT'!L56+'Projeções - Receita e EBIT'!L75+'Projeções - Receita e EBIT'!L98+'Projeções - Receita e EBIT'!L115+'Projeções - Receita e EBIT'!L133) -> 160737 | R15: =SUM('Projeções - Receita e EBIT'!M37+'Projeções - Receita e EBIT'!M56+'Projeções - Receita e EBIT'!M75+'Projeções - Receita e EBIT'!M98+'Projeções - Receita e EBIT'!M115+'Projeções - Receita e EBIT'!M133) -> 186246 | S15: =SUM('Projeções - Receita e EBIT'!N37+'Projeções - Receita e EBIT'!N56+'Projeções - Receita e EBIT'!N75+'Projeções - Receita e EBIT'!N98+'Projeções - Receita e EBIT'!N115+'Projeções - Receita e EBIT'!N133) -> 320049 | T15: =SUM('Projeções - Receita e EBIT'!O37+'Projeções - Receita e EBIT'!O56+'Projeções - Receita e EBIT'!O75+'Projeções - Receita e EBIT'!O98+'Projeções - Receita e EBIT'!O115+'Projeções - Receita e EBIT'!O133) -> 236261 | U15: =V15-T15 -> 306375.79 | V15: =SUM('Projeções - Receita e EBIT'!Q37,'Projeções - Receita e EBIT'!Q56,'Projeções - Receita e EBIT'!Q75,'Projeções - Receita e EBIT'!Q98) -> 542636.79 | W15: =SUM('Projeções - Receita e EBIT'!R37,'Projeções - Receita e EBIT'!R56,'Projeções - Receita e EBIT'!R75,'Projeções - Receita e EBIT'!R98) -> 792913.18 | X15: =SUM('Projeções - Receita e EBIT'!S37,'Projeções - Receita e EBIT'!S56,'Projeções - Receita e EBIT'!S75,'Projeções - Receita e EBIT'!S98) -> 862708.77 | Y15: =SUM('Projeções - Receita e EBIT'!T37,'Projeções - Receita e EBIT'!T56,'Projeções - Receita e EBIT'!T75,'Projeções - Receita e EBIT'!T98) -> 915996.11 | Z15: =SUM('Projeções - Receita e EBIT'!U37,'Projeções - Receita e EBIT'!U56,'Projeções - Receita e EBIT'!U75,'Projeções - Receita e EBIT'!U98) -> 975272.8
A16: Projeções - Receita e EBIT | E16: Margem EBIT Excluindo Empresas de Capital Aberto | O16: =O15/O13 -> 0.090167427 | P16: =P15/P13 -> 0.10727224 | Q16: =Q15/Q13 -> 0.11632318 | R16: =R15/R13 -> 0.13170424 | S16: =S15/S13 -> 0.083218189 | T16: =T15/T13 -> 0.043532793 | V16: =V15/V13 -> 0.074969201 | W16: =W15/W13 -> 0.080522319 | X16: =X15/X13 -> 0.082371715 | Y16: =Y15/Y13 -> 0.082454896 | Z16: =Z15/Z13 -> 0.082451133
A17: Projeções - CG + Capex | E17: Imposto de Renda e CSLL Ex empresas de capital aberto | M17: ='DRE Consolidado'!M42-SUM('DRE - Contas Abertas'!H146:H148) -> 125739 | N17: ='DRE Consolidado'!N42-SUM('DRE - Contas Abertas'!I146:I148) -> -9835 | O17: ='DRE Consolidado'!O42-SUM('DRE - Contas Abertas'!J146:J148) -> -8702 | P17: ='DRE Consolidado'!P42-SUM('DRE - Contas Abertas'!K146:K148) -> -14799 | Q17: ='DRE Consolidado'!Q42-SUM('DRE - Contas Abertas'!L146:L148) -> -151261 | R17: ='DRE Consolidado'!R42-SUM('DRE - Contas Abertas'!M146:M148) -> 5761 | S17: ='DRE Consolidado'!S42-SUM('DRE - Contas Abertas'!N146:N148) -> 196898 | T17: ='DRE Consolidado'!T42-SUM('DRE - Contas Abertas'!O146:O148) -> 191113 | U17: =V17-T17 -> -191113 | V17: =-V23*V15 -> 0 | W17: =-W23*W15 -> -62630.188 | X17: =-X23*X15 -> -68143.163 | Y17: =-Y23*Y15 -> -72352.194 | Z17: =-Z23*Z15 -> -77034.308
A18: Projeções 2023
A19: Processos
A20: Gráficos
K22: 2014 | L22: 2015 | M22: 2016 | N22: 2017 | O22: 2018 | P22: 2019 | Q22: 2020 | R22: 2021 | S22: 2022 | T22: YTD 2023 | U22: YTG 2023E | V22: 2023 | W22: 2024 | X22: 2025 | Y22: 2026 | Z22: 2027 | AA22: Perpetuidade | AB22: ROIC Perp. | AC22: Growth
E23: Alíquota Efetiva Ex Empresas de Capital Aberto | F23: 0.030034188 | G23: -0.02092541 | H23: -0.043315116 | I23: 0.13811998 | J23: -0.59211219 | K23: =IFERROR(IF(K15>0,-K17/K15,"-"),"-") -> - | L23: =IFERROR(IF(L15>0,-L17/L15,"-"),"-") -> - | M23: =IFERROR(IF(M15>0,-M17/M15,"-"),"-") -> - | N23: =IFERROR(IF(N15>0,-N17/N15,"-"),"-") -> - | O23: =IFERROR(IF('DRE Consolidado'!O36>0,-O17/O15,"-"),"-") -> 0.068198561 | P23: =IFERROR(IF('DRE Consolidado'!P36>0,-P17/P15,"-"),"-") -> 0.089776333 | Q23: =IFERROR(IF('DRE Consolidado'!Q36>0,-Q17/Q15,"-"),"-") -> 0.94104655 | R23: =IFERROR(IF('DRE Consolidado'!R36>0,-R17/R15,"-"),"-") -> -0.030932208 | S23: =IFERROR(IF('DRE Consolidado'!S36>0,-S17/S15,"-"),"-") -> -0.61521205 | T23: =IFERROR(IF('DRE Consolidado'!T36>0,-T17/T15,"-"),"-") -> -0.80890625 | U23: =IFERROR(IF(#REF!>0,-#REF!/#REF!,"-"),"-") -> - | V23: 0 | W23: =AVERAGE($O$23:$P$23) -> 0.078987447 | X23: =AVERAGE($O$23:$P$23) -> 0.078987447 | Y23: =AVERAGE($O$23:$P$23) -> 0.078987447 | Z23: =AVERAGE($O$23:$P$23) -> 0.078987447 | AB23: =WACC!P20 -> 0.16112663 | AC23: =(1+'Projeções - CG + Capex'!U37)*(1+'Projeções - CG + Capex'!U38)-1 -> 0.0769568
E24: D&A do Arrendamento Ex empresas de capital aberto | P24: ='Projeções - CG + Capex'!P48-SUM('Projeções - CG + Capex'!P45:P47) -> 17522 | Q24: ='Projeções - CG + Capex'!Q48-SUM('Projeções - CG + Capex'!Q45:Q47) -> -29457 | R24: ='Projeções - CG + Capex'!R48-SUM('Projeções - CG + Capex'!R45:R47) -> 18427 | S24: ='Projeções - CG + Capex'!S48-SUM('Projeções - CG + Capex'!S45:S47) -> -87846 | T24: ='Projeções - CG + Capex'!T48-SUM('Projeções - CG + Capex'!T45:T47) -> 97812 | U24: =V24-SUM(T24:T24) -> 32637.671 | V24: =V25*V13 -> 130449.67 | W24: =W25*W13 -> 139355.73 | X24: =X25*X13 -> 148218.21 | Y24: =Y25*Y13 -> 157214.51 | Z24: =Z25*Z13 -> 167395.95
E25: D&A do Arrendamento como (%) da Receita das empresas de Capital Fechado | P25: =P24/P13 -> 0.011402512 | Q25: =Q24/Q13 -> -0.02131763 | R25: =R24/R13 -> 0.013030691 | S25: =S24/S13 -> -0.022841456 | T25: =T24/T13 -> 0.018022566 | U25: =U24/U13 -> 0.018022566 | V25: =T25 -> 0.018022566 | W25: =AVERAGE($P$25,$R$25,$T$25) -> 0.014151923 | X25: =AVERAGE($P$25,$R$25,$T$25) -> 0.014151923 | Y25: =AVERAGE($P$25,$R$25,$T$25) -> 0.014151923 | Z25: =AVERAGE($P$25,$R$25,$T$25) -> 0.014151923
E26: NOPAT Ex Empresas de Capital Aberto | F26: 215718 | G26: 230388 | H26: 181530 | I26: -272310 | J26: -42610 | O26: =O15+O17+O24 -> 118896 | P26: =P15+P17+P24 -> 167566 | Q26: =Q15+Q17+Q24 -> -19981 | R26: =R15+R17+R24 -> 210434 | S26: =S15+S17+S24 -> 429101 | T26: =T15+T17+T24 -> 525186 | U26: =V26-SUM(T26:T26) -> 147900.46 | V26: =V15*(1-V23)+V24 -> 673086.46 | W26: =W15*(1-W23)+W24 -> 869638.72 | X26: =X15*(1-X23)+X24 -> 942783.82 | Y26: =Y15*(1-Y23)+Y24 -> 1000858.4 | Z26: =Z15*(1-Z23)+Z24 -> 1065634.4 | AA26: =Z26 -> 1065634.4
E27: Taxa de Reinvestimento | O27: =IFERROR(SUM(O28,O34)/O26,0) -> 2.0891311 | P27: =IFERROR(SUM(P28,P34)/P26,0) -> 1.8447835 | Q27: =IFERROR(SUM(Q28,Q34)/Q26,0) -> 1.0607581 | R27: =IFERROR(SUM(R28,R34)/R26,0) -> 2.0699382 | S27: =IFERROR(SUM(S28,S34)/S26,0) -> 3.7976189 | T27: =IFERROR(SUM(T28,T34)/T26,0) -> 1.8690916 | U27: =IFERROR(SUM(U28,U34)/U26,0) -> 3.3324746 | V27: =IFERROR(SUM(V28,V34)/V26,0) -> 2.1906476 | ... Z27: =IFERROR(SUM(Z28,Z34)/Z26,0) -> -0.19576424 | AA27: =(AC23-'Projeções - CG + Capex'!U37)/('DRE + DCF'!AB23-'Projeções - CG + Capex'!U37) -> 0.20056487
E28: CAPEX Líquido Ex Empresas de Capital Aberto | F28: 0 | G28: 0 | H28: 0 | I28: 0 | J28: 0 | O28: =O29-O32 -> 254518.96 | P28: =P29-P32 -> 248153.71 | Q28: =Q29-Q32 -> 208490.23 | R28: =R29-R32 -> 570893.55 | S28: =S29-S32 -> 976579 | T28: =T29-T32 -> 219007.66 | U28: =V28-SUM(T28:T28) -> 238670.16 | V28: =V29-V32 -> 457677.82 | W28: =W29-W32 -> -157759.2 | X28: =X29-X32 -> -338639.43 | Y28: =Y29-Y32 -> -427419.28 | Z28: =Z29-Z32 -> -456544.67
E29: CAPEX Bruto (Ex empresas de Capital Aberto) | F29: 0 | G29: 0 | H29: 0 | I29: 0 | J29: 0 | O29: ='Projeções - CG + Capex'!O32 -> 405066.96 | P29: ='Projeções - CG + Capex'!P32 -> 405314.71 | Q29: ='Projeções - CG + Capex'!Q32 -> 431804.23 | R29: ='Projeções - CG + Capex'!R32 -> 665081.55 | S29: ='Projeções - CG + Capex'!S32 -> 1334428 | T29: =V29/2 -> 248516.66 | U29: =V29-SUM(T29:T29) -> 248516.66 | V29: ='Projeções - CG + Capex'!T32 -> 497033.31 | W29: ='Projeções - CG + Capex'!U32 -> 327133.22 | X29: ='Projeções - CG + Capex'!V32 -> 177090.26 | Y29: ='Projeções - CG + Capex'!W32 -> 119613.32 | Z29: ='Projeções - CG + Capex'!X32 -> 125914.54
E30: Crescimento do Capex Bruto (YoY)¹ | O30: 0 | P30: =(P29-O29)/O29 -> 0.00061163483 | Q30: =(Q29-P29)/P29 -> 0.065355445 | R30: =(R29-Q29)/Q29 -> 0.54023861 | S30: =(S29-R29)/R29 -> 1.0064126 | V30: =V29/S29-1 -> -0.62753081 | W30: =W29/V29-1 -> -0.34182838 | X30: =X29/W29-1 -> -0.45866011 | Y30: =Y29/X29-1 -> -0.32456294 | Z30: =Z29/Y29-1 -> 0.052679905
E31: (%) da Receita Líquida | O31: =O29/O13 -> 0.28624152 | P31: =P29/P13 -> 0.26376017 | Q31: =Q29/Q13 -> 0.31249085 | R31: =R29/R13 -> 0.4703138 | S31: =S29/S13 -> 0.346974 | U31: =U29/U13 -> 0.13723124 | V31: =V29/V13 -> 0.06866875 | W31: =W29/W13 -> 0.033221197 | X31: =X29/X13 -> 0.016908636 | Y31: =Y29/Y13 -> 0.01076719 | Z31: =Z29/Z13 -> 0.010645018
E32: Depreciação & Amortização Ex empresas de capital aberto | F32: 0 | G32: 0 | H32: 0 | I32: 0 | J32: 0 | O32: ='Projeções - CG + Capex'!O57-SUM('Projeções - CG + Capex'!O54:O56) -> 150548 | P32: ='Projeções - CG + Capex'!P57-SUM('Projeções - CG + Capex'!P54:P56) -> 157161 | Q32: ='Projeções - CG + Capex'!Q57-SUM('Projeções - CG + Capex'!Q54:Q56) -> 223314 | R32: ='Projeções - CG + Capex'!R57-SUM('Projeções - CG + Capex'!R54:R56) -> 94188 | S32: ='Projeções - CG + Capex'!S57-SUM('Projeções - CG + Capex'!S54:S56) -> 357849 | T32: ='Projeções - CG + Capex'!T57-SUM('Projeções - CG + Capex'!T54:T56) -> 29509 | U32: =V32-T32 -> 9846.4916 | V32: =V33*V13 -> 39355.492 | W32: =W33*W13 -> 484892.42 | X32: =X33*X13 -> 515729.69 | Y32: =Y33*Y13 -> 547032.6 | Z32: =Z33*Z13 -> 582459.21
E33: (%) da Receita Líquida | O33: =O32/O13 -> 0.1063851 | P33: =P32/P13 -> 0.10227315 | Q33: =Q32/Q13 -> 0.1616093 | R33: =R32/R13 -> 0.066605239 | S33: =S32/S13 -> 0.093046833 | T33: =T32/T13 -> 0.005437246 | U33: =U32/U13 -> 0.005437246 | V33: =T33 -> 0.005437246 | W33: =AVERAGE($S$33:$T$33) -> 0.049242039 | X33: =AVERAGE($S$33:$T$33) -> 0.049242039 | Y33: =AVERAGE($S$33:$T$33) -> 0.049242039 | Z33: =AVERAGE($S$33:$T$33) -> 0.049242039
E34: ∆ Capital de Giro Ex empresas de capital aberto | F34: 0 | G34: -122636.72 | H34: 147702.64 | I34: -36069.72 | J34: -41836.44 | O34: ='Projeções - CG + Capex'!O66-SUM('Projeções - CG + Capex'!O63:O65) -> -6129.6207 | P34: ='Projeções - CG + Capex'!P66-SUM('Projeções - CG + Capex'!P63:P65) -> 60969.288 | Q34: ='Projeções - CG + Capex'!Q66-SUM('Projeções - CG + Capex'!Q63:Q65) -> -229685.24 | R34: ='Projeções - CG + Capex'!R66-SUM('Projeções - CG + Capex'!R63:R65) -> -135308.19 | S34: ='Projeções - CG + Capex'!S66-SUM('Projeções - CG + Capex'!S63:S65) -> 652983.08 | T34: =V34/4*3 -> 762613.08 | U34: =V34-SUM(T34:T34) -> 254204.36 | V34: =('Projeções - CG + Capex'!T10-'Projeções - CG + Capex'!S10)*V35 -> 1016817.4 | W34: =('Projeções - CG + Capex'!U10-'Projeções - CG + Capex'!T10)*W35 -> 345182.9 | X34: =('Projeções - CG + Capex'!V10-'Projeções - CG + Capex'!U10)*X35 -> 298287.38 | Y34: =('Projeções - CG + Capex'!W10-'Projeções - CG + Capex'!V10)*Y35 -> 241539.11 | Z34: =('Projeções - CG + Capex'!X10-'Projeções - CG + Capex'!W10)*Z35 -> 247931.55
E35: ∆ Capital de Giro Ex empresas de capital aberto % da ∆ Capital de Giro do Grupo todo | F35: 0 | G35: -122636.72 | H35: 147702.64 | I35: -36069.72 | J35: -41836.44 | O35: =O34/'Projeções - CG + Capex'!O66 -> 0.042996363 | P35: =P34/'Projeções - CG + Capex'!P66 -> 0.26612929 | Q35: =Q34/'Projeções - CG + Capex'!Q66 -> 0.33025912 | R35: =R34/'Projeções - CG + Capex'!R66 -> 0.71211856 | S35: =S34/'Projeções - CG + Capex'!S66 -> 1.1406109 | T35: =T34/'Projeções - CG + Capex'!T66 -> 0.15064745 | V35: =AVERAGE($O$35:$S$35) -> 0.49842285 | W35: =AVERAGE($O$35:$S$35) -> 0.49842285 | X35: =AVERAGE($O$35:$S$35) -> 0.49842285 | Y35: =AVERAGE($O$35:$S$35) -> 0.49842285 | Z35: =AVERAGE($O$35:$S$35) -> 0.49842285
E36: FCFF Ex Empresas de Capital Aberto | O36: =O26*(1-O27) -> -129493.34 | P36: =P26*(1-P27) -> -141557 | Q36: =Q26*(1-Q27) -> 1214.0085 | R36: =R26*(1-R27) -> -225151.37 | S36: =S26*(1-S27) -> -1200461.1 | T36: =T26*(1-T27) -> -456434.73 | U36: =V36-SUM(T36:T36) -> -344974.06 | V36: =V26*(1-V27) -> -801408.79 | W36: =W26*(1-W27) -> 682215.02 | X36: =X26*(1-X27) -> 983135.87 | Y36: =Y26*(1-Y27) -> 1186738.6 | Z36: =Z26*(1-Z27) -> 1274247.5 | AA36: =AA26*(1-AA27) -> 851905.6
E37: Desconto | U37: =WACC!F21 -> 1.0404826 | W37: =WACC!G21 -> 1.2071321 | X37: =WACC!H21 -> 1.3973412 | Y37: =WACC!I21 -> 1.6186091 | Z37: =WACC!J21 -> 1.8768099
E38: FCFF Descontado Ex Empresas de Capital Aberto | U38: =U36/U37 -> -331551.97 | W38: =W36/W37 -> 565153.57 | X38: =X36/X37 -> 703576.09 | Y38: =Y36/Y37 -> 733184.19 | Z38: =Z36/Z37 -> 678943.33 | AA38: =(AA36*(1+AC23))/(WACC!P20-AC23)/'DRE + DCF'!Z37 -> 5807818.2
E39: ROIC - Simpar Consolidado | F39: 0.19812982 | G39: 0.1966132 | H39: 0.14196039 | I39: -0.20916931 | J39: -0.040922008 | K39: ='DRE Consolidado'!K57/(SUM('Balanço Patrimonial'!F55:F60,'Balanço Patrimonial'!F74:F77,'Balanço Patrimonial'!F89,-'Balanço Patrimonial'!F19,-'Balanço Patrimonial'!F37)) -> 0.087496051 | L39: ='DRE Consolidado'!L57/(SUM('Balanço Patrimonial'!G55:G60,'Balanço Patrimonial'!G74:G77,'Balanço Patrimonial'!G89,-'Balanço Patrimonial'!G19,-'Balanço Patrimonial'!G37)) -> 0.0927418 | M39: ='DRE Consolidado'!M57/(SUM('Balanço Patrimonial'!H55:H60,'Balanço Patrimonial'!H74:H77,'Balanço Patrimonial'!H89,-'Balanço Patrimonial'!H19,-'Balanço Patrimonial'!H37)) -> 0.090692945 | N39: ='DRE Consolidado'!N57/(SUM('Balanço Patrimonial'!I55:I60,'Balanço Patrimonial'!I74:I77,'Balanço Patrimonial'!I89,-'Balanço Patrimonial'!I19,-'Balanço Patrimonial'!I37)) -> 0.092089722 | O39: ='DRE Consolidado'!O57/(SUM('Balanço Patrimonial'!J55:J60,'Balanço Patrimonial'!J74:J77,'Balanço Patrimonial'!J89,-'Balanço Patrimonial'!J19,-'Balanço Patrimonial'!J37)) -> 0.098681459 | P39: ='DRE Consolidado'!P57/(SUM('Balanço Patrimonial'!K55:K60,'Balanço Patrimonial'!K74:K77,'Balanço Patrimonial'!K89,-'Balanço Patrimonial'!K19,-'Balanço Patrimonial'!K37)) -> 0.10811252 | Q39: ='DRE Consolidado'!Q57/(SUM('Balanço Patrimonial'!L55:L60,'Balanço Patrimonial'!L74:L77,'Balanço Patrimonial'!L89,-'Balanço Patrimonial'!L19,-'Balanço Patrimonial'!L37)) -> 0.084555268 | R39: ='DRE Consolidado'!R57/(SUM('Balanço Patrimonial'!M55:M60,'Balanço Patrimonial'!M74:M77,'Balanço Patrimonial'!M89,-'Balanço Patrimonial'!M19,-'Balanço Patrimonial'!M37)) -> 0.12089622 | S39: ='DRE Consolidado'!S57/(SUM('Balanço Patrimonial'!N55:N60,'Balanço Patrimonial'!N74:N77,'Balanço Patrimonial'!N89,-'Balanço Patrimonial'!N19,-'Balanço Patrimonial'!N37)) -> 0.15951948
E41: ¹- "YoY", ou "year over year", significa "de um ano pro outro".

Sheet DRE - Contas Abertas
F3: =Dashboard!$H$3 -> SIMPAR (SIMH3)
A7: Páginas
A8: Dashboard
A9: WACC | F9: 2014 | G9: 2015 | H9: 2016 | I9: 2017 | J9: 2018 | K9: 2019 | L9: 2020 | M9: 2021 | N9: 2022 | O9: YTD 2023
A10: DRE Consolidado | E10: Custo de venda de veículos novos e usados | L10: -1019754 | M10: -1899550 | N10: -4817452 | O10: -5633059
A11: DRE + DCF | E11: Custo de venda de veículos novos | F11: -592675 | G11: -427897 | H11: -281566 | I11: -319150 | J11: -535727 | K11: -586574
A12: DRE - Contas Abertas | E12: Custo de venda de veículos usados | F12: -280455 | G12: -285571 | H12: -275399 | I12: -251561 | J12: -254716 | K12: -282749
A13: Balanço Patrimonial | E13: Custo de venda de peças | F13: -110505 | H13: -90706 | I13: -77717 | J13: -111711 | K13: -122657
A14: Painel de Índices | E14: Custo de Construção | O14: -82622
A15: Projeções - Receita e EBIT | E15: Custo / despesas com frota | F15: -148406 | H15: -247034 | I15: -224258 | J15: -177630 | K15: -271440 | L15: -279687 | M15: -405447 | N15: -522589 | O15: -372364
A16: Projeções - CG + Capex | E16: Custo de venda de ativos desmobilizados | F16: -681231 | G16: -877618 | H16: -1289069 | I16: -1584813 | J16: -1609867 | K16: -2524180 | L16: -2618101 | M16: -2077780 | N16: -4166192 | O16: -4104310
A17: Projeções 2023 | E17: Pessoal | F17: =-1045800-228365 -> -1274165 | G17: -1299564 | H17: -1365077 | I17: -1399487 | J17: -1510200 | K17: -1603040 | L17: -1477812 | M17: -2278160 | N17: -3291385 | O17: -3029391
A18: Processos | E18: Agregados e terceiros | F18: -656182 | G18: -656004 | H18: -721429 | I18: -900896 | J18: -996936 | K18: -952975 | L18: -854451 | M18: -1149724 | N18: -1382969 | O18: -1206899
E19: Depreciação e amortização (i) | F19: =-391194-17671 -> -408865 | G19: -508626 | H19: -547187 | I19: -525731 | J19: -636817 | K19: -916744 | L19: -1111953 | M19: -1059114 | N19: -1886277 | O19: -2043227
E20: Peças, pneus e manutenções | F20: -260230 | G20: -394413 | H20: -348746 | I20: -424460 | J20: -438912 | K20: -498789 | L20: -489633 | M20: -701562 | N20: -1015445 | O20: -973798
E21: Combustíveis e lubrificantes | F21: -233123 | G21: -256416 | H21: -271274 | I21: -244744 | J21: -256323 | K21: -236111 | L21: -214393 | M21: -494957 | N21: -899084 | O21: -698804
E22: Propaganda e publicidade | F22: -14836 | H22: -4418 | I22: -5213 | J22: -17297 | K22: -11895 | L22: -43158 | M22: -65288 | N22: -115364 | O22: -105991
E23: Prestação de serviços | F23: =-18944-62100 -> -81044 | G23: -93764 | H23: -175477 | I23: -184196 | J23: -241971 | K23: -271413 | L23: -285556 | M23: -444935 | N23: -657511 | O23: -655393
E24: Reversão (provisão) de perdas esperadas ("impairment") de contas a receber | F24: -3352 | H24: -27025 | I24: 2249 | J24: -9146 | K24: -32527 | L24: -78667 | M24: -56164 | N24: -127315 | O24: -153092
E25: Provisão para perdas de valor recuperável ("Impairment") | L25: -145249 | M25: - | N25: -9498 | O25: 0
E26: Indenizações judiciais | F26: -24516 | G26: -6205 | H26: -34755 | I26: -48724 | J26: -32345 | K26: -48635 | L26: -56253 | M26: -41436 | N26: -49176 | O26: -47299
E27: Energia elétrica | H27: -25250 | I27: -23879 | J27: -26243 | K27: -33047 | L27: -29820 | M27: -39861 | N27: -52864 | O27: -41544
E28: Resultado na venda de veículos avariados (ii) | H28: -45447 | I28: -77445 | J28: -80763 | K28: -42601 | L28: -37135 | M28: -58698 | N28: -169869 | O28: -161197
E29: Alugueis de imóveis (nota 4.1.(d)) (i) | F29: =-65505-46743 -> -112248 | G29: -38650 | H29: -161059 | I29: -161048 | J29: -152328 | K29: -45151 | L29: -21769 | M29: -2215 | N29: -30761 | O29: -16481
E30: Aluguéis de veículos, máquinas e equipamentos | G30: -95354 | H30: -86129 | I30: -24727 | J30: -36851 | K30: -27051 | L30: -25913 | M30: -43100 | N30: -88637 | O30: -59939
E31: Recuperação de PIS e COFINS | H31: 216301 | I31: 260766 | J31: 285022 | K31: 366861 | L31: 398061 | M31: 562762 | N31: 1101761 | O31: 866539
E32: Crédito de impostos extemporâneos | H32: - | I32: 82928 | J32: 62789 | K32: 47706 | L32: 59819 | M32: 149002 | N32: 71200 | O32: 25255
E33: Provisão para perdas tributárias ICMS RJ | G33: - | H33: -27466 | I33: -
E34: Perdas estimadas com créditos de liquidação duvidosa | F34: -18540 | G34: -32258 | H34: -68409 | I34: -60680
E35: Material de embalagem | H35: -9437 | I35: -9255 | J35: -10804 | K35: -5710
E36: Comunicação | F36: -623 | G36: -5277 | H36: -35206 | I36: -35876 | J36: -35528 | K36: -27144
E37: Telefones | F37: -11744
E38: Viagens, refeições e estadias | F38: -5267 | G38: -4816 | H38: -8732 | I38: -10206 | J38: -13677 | K38: -17160
E39: Baixa da mais valia de ativo vendido | H39: -25653 | I39: -55061
E40: Despesas tributárias | H40: -13822 | I40: -13208 | J40: -17120 | K40: -8573
E41: Manutenção Predial | F41: -5514
E42: Impostos, manutenção e conservação de automóveis | F42: -20532
E43: Provisão para demandas judiciais e administrativas | F43: -12038 | O43: 0
E44: Gasto com infraestrutura das filiais | G44: -90307
E45: Outros custos | F45: =-62122-52880 -> -115002 | G45: -324204 | H45: -54862 | I45: -234942 | J45: -258611 | K45: -334244 | L45: -445136 | M45: -627907 | N45: -1158358 | O45: -558022
E46: Equivalência Patrimonial | F46: ='DRE Consolidado'!K32 -> 94 | G46: ='DRE Consolidado'!L32 -> 71 | H46: ='DRE Consolidado'!M32 -> 0 | I46: ='DRE Consolidado'!N32 -> 0 | J46: ='DRE Consolidado'!O32 -> -960 | K46: ='DRE Consolidado'!P32 -> -1201 | L46: ='DRE Consolidado'!Q32 -> -515 | M46: ='DRE Consolidado'!R32 -> -1534 | N46: 0 | O46: 0
E47: Total: | F47: =SUM(F10:F46) -> -5070999 | G47: =SUM(G10:G46) -> -5396873 | H47: =SUM(H10:H46) -> -6024333 | I47: =SUM(I10:I46) -> -6551334 | J47: =SUM(J10:J46) -> -7114672 | K47: =SUM(K10:K46) -> -8487044 | L47: =SUM(L10:L46) -> -8777075 | M47: =SUM(M10:M46) -> -10735668 | ... O47: =SUM(O10:O46) -> -19051638
F51: 2014 | G51: 2015 | H51: 2016 | I51: 2017 | J51: 2018 | K51: 2019 | L51: 2020 | M51: 2021 | N51: 2022 | O51: YTD 2023
E52: Receita Líquida | F52: ='DRE Consolidado'!K16 -> 5539194 | G52: ='DRE Consolidado'!L16 -> 5989912 | H52: ='DRE Consolidado'!M16 -> 6523116 | I52: ='DRE Consolidado'!N16 -> 7255804 | J52: ='DRE Consolidado'!O16 -> 8075389 | K52: ='DRE Consolidado'!P16 -> 9686209 | L52: ='DRE Consolidado'!Q16 -> 9807057 | M52: ='DRE Consolidado'!R16 -> 13866219 | ... O52: ='DRE Consolidado'!T16 -> 23321789
E53: Custos das Vendas e Serviços + Despesas | F53: ='DRE Consolidado'!K18+'DRE Consolidado'!K20+'DRE Consolidado'!K23 -> -5079092 | G53: ='DRE Consolidado'!L18+'DRE Consolidado'!L20+'DRE Consolidado'!L23 -> -5406457 | H53: ='DRE Consolidado'!M18+'DRE Consolidado'!M20+'DRE Consolidado'!M23 -> -6024333 | I53: ='DRE Consolidado'!N18+'DRE Consolidado'!N20+'DRE Consolidado'!N23 -> -6551334 | J53: ='DRE Consolidado'!O18+'DRE Consolidado'!O20+'DRE Consolidado'!O23 -> -7114672 | K53: ='DRE Consolidado'!P18+'DRE Consolidado'!P20+'DRE Consolidado'!P23 -> -8487044 | L53: ='DRE Consolidado'!Q18+'DRE Consolidado'!Q20+'DRE Consolidado'!Q23 -> -8777075 | M53: ='DRE Consolidado'!R18+'DRE Consolidado'!R20+'DRE Consolidado'!R23 -> -10735668 | ... O53: ='DRE Consolidado'!T18+'DRE Consolidado'!T20+'DRE Consolidado'!T23 -> -18966092
E54: EBIT | F54: =SUM(F52:F53) -> 460102 | G54: =SUM(G52:G53) -> 583455 | H54: =SUM(H52:H53) -> 498783 | I54: =SUM(I52:I53) -> 704470 | J54: =SUM(J52:J53) -> 960717 | K54: =SUM(K52:K53) -> 1199165 | L54: =SUM(L52:L53) -> 1029982 | M54: =SUM(M52:M53) -> 3130551 | ... O54: =SUM(O52:O53) -> 4355697
E55: Margem EBIT | F55: =F54/F52 -> 0.083062987 | G55: =G54/G52 -> 0.097406272 | H55: =H54/H52 -> 0.076463917 | I55: =I54/I52 -> 0.09709055 | J55: =J54/J52 -> 0.11896851 | K55: =K54/K52 -> 0.12380127 | L55: =L54/L52 -> 0.10502458 | M55: =M54/M52 -> 0.22576818 | ... O55: =O54/O52 -> 0.18676513
E56: Eventos não recorrentes | F56: =SUM(F25,F26,F32,F33) -> -24516 | G56: =SUM(G25,G26,G32,G33) -> -6205 | H56: =SUM(H25,H26,H32,H33) -> -62221 | I56: =SUM(I25,I26,I32,I33) -> 34204 | J56: =SUM(J25,J26,J32,J33) -> 30444 | K56: =SUM(K25,K26,K32,K33) -> -929 | L56: =SUM(L25,L26,L32,L33) -> -141683 | M56: =SUM(M25,M26,M32,M33) -> 107566 | ... O56: =SUM(O25,O26,O32,O33) -> -22044
E57: EBIT recorrente | F57: =F54-F56 -> 484618 | G57: =G54-G56 -> 589660 | H57: =H54-H56 -> 561004 | I57: =I54-I56 -> 670266 | J57: =J54-J56 -> 930273 | K57: =K54-K56 -> 1200094 | L57: =L54-L56 -> 1171665 | M57: =M54-M56 -> 3022985 | ... O57: =O54-O56 -> 4377741
E58: Margem EBIT recorrente | F58: =F57/F52 -> 0.087488902 | G58: =G57/G52 -> 0.098442181 | H58: =H57/H52 -> 0.086002456 | I58: =I57/I52 -> 0.092376531 | J58: =J57/J52 -> 0.11519854 | K58: =K57/K52 -> 0.12389718 | L58: =L57/L52 -> 0.11947162 | M58: =M57/M52 -> 0.21801076 | ... O58: =O57/O52 -> 0.18771034
E59: Incentivos Fiscais | F59: =F128/34% -> 0 | G59: =G128/34% -> 0 | H59: =H128/34% -> 0 | I59: =I128/34% -> 0 | J59: =J128/34% -> 0 | K59: =K128/34% -> 31564.706 | L59: =L128/34% -> 29579.412 | M59: =M128/34% -> 34847.059 | ... O59: =O128/34% -> 0
E60: Ebit Recorrente sem incentivos | F60: =F57-F59 -> 484618 | G60: =G57-G59 -> 589660 | H60: =H57-H59 -> 561004 | I60: =I57-I59 -> 670266 | J60: =J57-J59 -> 930273 | K60: =K57-K59 -> 1168529.3 | L60: =L57-L59 -> 1142085.6 | M60: =M57-M59 -> 2988137.9 | ... O60: =O57-O59 -> 4377741
E61: Margem EBIT recorrente sem Incentivos | F61: =F60/F52 -> 0.087488902 | G61: =G60/G52 -> 0.098442181 | H61: =H60/H52 -> 0.086002456 | I61: =I60/I52 -> 0.092376531 | J61: =J60/J52 -> 0.11519854 | K61: =K60/K52 -> 0.12063846 | L61: =L60/L52 -> 0.11645549 | M61: =M60/M52 -> 0.21549767 | ... O61: =O60/O52 -> 0.18771034
F65: 2014 | G65: 2015 | H65: 2016 | I65: 2017 | J65: 2018 | K65: 2019 | L65: 2020 | M65: 2021 | N65: 2022 | O65: YTD 2023
E66: Juros sobre empréstimos, financiamentos e debêntures | F66: -380589 | G66: -555934 | H66: -669521 | I66: -699233 | J66: -869284 | K66: -969381 | L66: -1005078 | M66: -2001424 | N66: -3631554 | O66: -2988159
E67: Juros e encargos bancários sobre arrendamento mercantil | G67: -35548 | H67: -48855 | I67: -33007 | J67: -20929 | K67: -23157 | L67: -15836 | M67: -17783 | N67: -29761 | O67: -22970
E68: Juros de risco sacado - montadoras | H68: -75695 | I68: -84455 | J68: -304207 | K68: -186 | L68: -24253 | M68: -1030 | N68: -3926 | O68: -4934
E69: Variação monetária | F69: -9996
E70: Variação cambial | F70: -7602 | H70: 48741 | I70: 1171 | J70: 293586 | K70: -175092 | L70: -637087 | M70: -95625 | N70: 394836 | O70: 323735
E71: Resultado na apuração dos swaps, líquido | H71: -106105 | I71: 13379 | K71: 172610 | L71: 723440 | M71: 326352 | N71: -1547875 | O71: -1545973
E72: Juros sobre arrendamentos a pagar por direito de uso
E73: Juros passivos | F73: -32661
E74: Juros de alongamento | G74: -66177 | J74: -17661
E75: Despesas com captação | N75: -108446 | O75: -105803
E76: Despesas bancárias | F76: -2587
E77: Descontos | F77: -4161
E78: IOF | F78: -1245
E79: Outras despesas financeiras | G79: -67062
E80: Despesa total do serviço da dívida | F80: =SUM(F66:F79) -> -438841 | G80: =SUM(G66:G79) -> -724721 | H80: =SUM(H66:H79) -> -851435 | I80: =SUM(I66:I79) -> -802145 | J80: =SUM(J66:J79) -> -918495 | K80: =SUM(K66:K79) -> -995206 | L80: =SUM(L66:L79) -> -958814 | M80: =SUM(M66:M79) -> -1789510 | ... O80: =SUM(O66:O79) -> -4344104
E81: Juros sobre arrendamento por direito de uso | F81: 0 | H81: 0 | J81: - | K81: -49557 | L81: -52448 | M81: -69956 | N81: -122010 | O81: -122444
E82: Juros passivos | F82: 0 | H82: 0 | J82: -34062 | K82: -23203 | L82: -21276 | M82: -46006 | N82: -116992 | O82: -502188
E83: Juros sobre cessão de direitos creditórios | O83: 0
E84: Outras despesas financeiras | F84: -4706 | H84: -98541 | I84: -77951 | J84: -46471 | K84: -65409 | L84: -21664 | M84: -48483 | N84: -192745 | O84: -221709
E85: Total: | F85: =SUM(F80:F84) -> -443547 | G85: =SUM(G80:G84) -> -724721 | H85: =SUM(H80:H84) -> -949976 | I85: =SUM(I80:I84) -> -880096 | J85: =SUM(J80:J84) -> -999028 | K85: =SUM(K80:K84) -> -1133375 | L85: =SUM(L80:L84) -> -1054202 | M85: =SUM(M80:M84) -> -1953955 | ... O85: =SUM(O80:O84) -> -5190445
F89: 2014 | G89: 2015 | H89: 2016 | I89: 2017 | J89: 2018 | K89: 2019 | L89: 2020 | M89: 2021 | N89: 2022 | O89: YTD 2023
E90: Aplicações financeiras | F90: 55763 | G90: 155709 | H90: 161024 | I90: 148535 | J90: 262955 | K90: 295995 | L90: 345166 | M90: 660349 | N90: 1189610 | O90: 633497
E91: Receita de variação monetária | F91: 124 | G91: 16613 | H91: 9797 | I91: 31542 | J91: 22565 | K91: 24623 | L91: 12880 | M91: 13557 | N91: 4812
E92: AVP | F92: 23075
E93: Juros recebidos | F93: 6126 | H93: 8373 | I93: 13920 | J93: 11798 | K93: 17934 | L93: 28408 | M93: 33229 | N93: 33971 | O93: 21229
E94: Descontos | F94: 2367
E95: Ganho na liquidação antecipada de swaps | L95: 281440 | M95: -
E96: Receita de financiamentos e produtos de créditos concedidos | O96: 87397
E97: Atualização Monetária de impostos a recuperar e depósitos judiciais | O97: 50749
E98: Outras receitas financeiras | F98: 2170 | G98: 13733 | H98: 22529 | I98: 15558 | J98: 20491 | K98: 26784 | L98: 11532 | M98: 29227 | N98: 649 | O98: 45126
E99: Total: | F99: =SUM(F90:F98) -> 89625 | G99: =SUM(G90:G98) -> 186055 | H99: =SUM(H90:H98) -> 201723 | I99: =SUM(I90:I98) -> 209555 | J99: =SUM(J90:J98) -> 317809 | K99: =SUM(K90:K98) -> 365336 | L99: =SUM(L90:L98) -> 679426 | M99: =SUM(M90:M98) -> 736362 | ... O99: =SUM(O90:O98) -> 837998
F103: 2014 | G103: 2015 | H103: 2016 | I103: 2017 | J103: 2018 | K103: 2019 | L103: 2020 | M103: 2021 | N103: 2022 | O103: YTD 2023
E104: EBIT Recorrente | F104: =F57 -> 484618 | G104: =G57 -> 589660 | H104: =H57 -> 561004 | I104: =I57 -> 670266 | J104: =J57 -> 930273 | K104: =K57 -> 1200094 | L104: =L57 -> 1171665 | M104: =M57 -> 3022985 | ... O104: =O57 -> 4377741
E105: EBIT Recorrente sem Incentivos | F105: =F60 -> 484618 | G105: =G60 -> 589660 | H105: =H60 -> 561004 | I105: =I60 -> 670266 | J105: =J60 -> 930273 | K105: =K60 -> 1168529.3 | L105: =L60 -> 1142085.6 | M105: =M60 -> 2988137.9 | ... O105: =O60 -> 4377741
E106: Lucro antes do IR Não Recorrente | F106: ='DRE Consolidado'!K41 -> 111137 | G106: ='DRE Consolidado'!L41 -> 67222 | H106: ='DRE Consolidado'!M41 -> -249470 | I106: ='DRE Consolidado'!N41 -> 33929 | J106: ='DRE Consolidado'!O41 -> 279498 | K106: ='DRE Consolidado'!P41 -> 431126 | L106: ='DRE Consolidado'!Q41 -> 655206 | M106: ='DRE Consolidado'!R41 -> 1912958 | ... O106: ='DRE Consolidado'!T41 -> -79372
E107: Eventos não recorrentes | F107: =F56 -> -24516 | G107: =G56 -> -6205 | H107: =H56 -> -62221 | I107: =I56 -> 34204 | J107: =J56 -> 30444 | K107: =K56 -> -929 | L107: =L56 -> -141683 | M107: =M56 -> 107566 | ... O107: =O56 -> -22044
E108: Lucro Antes do IR Recorrente | F108: =F106-F107 -> 135653 | G108: =G106-G107 -> 73427 | H108: =H106-H107 -> -187249 | I108: =I106-I107 -> -275 | J108: =J106-J107 -> 249054 | K108: =K106-K107 -> 432055 | L108: =L106-L107 -> 796889 | M108: =M106-M107 -> 1805392 | ... O108: =O106-O107 -> -57328
E109: Lucro Antes do IR Recorrente sem Incentivos | F109: =F105+F99+F85 -> 130696 | G109: =G105+G99+G85 -> 50994 | H109: =H105+H99+H85 -> -187249 | I109: =I105+I99+I85 -> -275 | J109: =J105+J99+J85 -> 249054 | K109: =K105+K99+K85 -> 400490.29 | L109: =L105+L99+L85 -> 767309.59 | M109: =M105+M99+M85 -> 1770544.9 | ... O109: =O105+O99+O85 -> 25294
F113: 2014 | G113: 2015 | H113: 2016 | I113: 2017 | J113: 2018 | K113: 2019 | L113: 2020 | M113: 2021 | N113: 2022 | O113: YTD 2023
E114: Lucro (prejuízo) líquido antes de imposto Recorrente e da CSLL | F114: =F108 -> 135653 | G114: =G108 -> 73427 | H114: =H108 -> -187249 | I114: =I108 -> -275 | J114: =J108 -> 249054 | K114: =K108 -> 432055 | L114: =L108 -> 796889 | M114: =M108 -> 1805392 | ... O114: =O108 -> -57328
E115: Alíquota Vigente | F115: 0.34 | G115: 0.34 | H115: 0.34 | I115: 0.34 | J115: 0.34 | K115: 0.34 | L115: 0.34 | M115: 0.34 | N115: 0.34 | O115: 0.34
E116: IRPJ e CSLL calculados às aliquotas nominais | F116: =-F115*F114 -> -46122.02 | G116: =-G115*G114 -> -24965.18 | H116: =-H115*H114 -> 63664.66 | I116: =-I115*I114 -> 93.5 | J116: =-J115*J114 -> -84678.36 | K116: =-K115*K114 -> -146898.7 | L116: =-L115*L114 -> -270942.26 | M116: =-M115*M114 -> -613833.28 | ... O116: =-O115*O114 -> 19491.52
E117: Efeito Fiscal das adiçoes e exclusões permanentes:
E118: Equivalência Patrimonial | F118: 32 | G118: 24 | H118: 0 | I118: 0 | J118: -610 | K118: -2759 | L118: -175 | M118: -522 | N118: 955 | O118: 994
E119: Incentivos fiscais – PAT | F119: 725 | G119: 261 | H119: 421 | I119: 380 | J119: 825 | K119: 2074 | L119: 2347 | M119: 3536 | N119: 269 | O119: 1870
E120: Juros sobre capital próprio | F120: 5361 | G120: 3400 | H120: 0 | I120: 2144 | J120: 18764 | K120: 27044 | L120: 16045 | M120: 51852 | N120: 102594 | O120: -2704
...

Sheet Balanço Patrimonial
F9: =Dashboard!H3 -> SIMPAR (SIMH3)
A13: Páginas
A14: Dashboard
A15: WACC | E15: Data do Último Resultado: | F15: 2014 | G15: 2015 | H15: 2016 | I15: 2017 | J15: 2018 | K15: 2019 | L15: 2020 | M15: 2021 | N15: 2022 | O15: YTD 2023
A16: DRE Consolidado | E16: Capital de Giro | F16: =SUM(F20,F24:F30,F33:F34)-SUM(F54,F62:F67,F70,F61) -> 1054514.9 | G16: =SUM(G20,G24:G30,G33:G34)-SUM(G54,G62:G67,G70,G61) -> 903808.8 | H16: =SUM(H20,H24:H30,H33:H34)-SUM(H54,H62:H67,H70,H61) -> 420797.9 | I16: =SUM(I20,I24:I30,I33:I34)-SUM(I54,I62:I67,I70,I61) -> 837109.1 | J16: =SUM(J20,J24:J30,J33:J34)-SUM(J54,J62:J67,J70,J61) -> 694547.73 | K16: =SUM(K20,K24:K30,K33:K34)-SUM(K54,K62:K67,K70,K61) -> 923644.23 | L16: =SUM(L20,L24:L30,L33:L34)-SUM(L54,L62:L67,L70,L61) -> 228174.42 | M16: =SUM(M20,M24:M30,M33:M34)-SUM(M54,M62:M67,M70,M61) -> 38166.475 | ... O16: =SUM(O20,O24:O30,O33:O34)-SUM(O54,O62:O67,O70,O61) -> 5672888.6
A17: DRE + DCF | E17: Ativo Total | F17: =SUM(F18,F36) -> 7465231 | G17: =SUM(G18,G36) -> 8742595 | H17: =SUM(H18,H36) -> 8868383 | I17: =SUM(I18,I36) -> 11500924 | J17: =SUM(J18,J36) -> 15873954 | K17: =SUM(K18,K36) -> 20248234 | L17: =SUM(L18,L36) -> 25562248 | M17: =SUM(M18,M36) -> 47968194 | ... O17: =SUM(O18,O36) -> 62697615
A18: DRE - Contas Abertas | E18: Ativo Circulante | F18: =SUM(F19,F24:F35) -> 2854393 | G18: =SUM(G19,G24:G35) -> 3371043 | H18: =SUM(H19,H24:H35) -> 2716700 | I18: =SUM(I19,I24:I35) -> 4488461 | J18: =SUM(J19,J24:J35) -> 7191320 | K18: =SUM(K19,K24:K35) -> 8890832 | L18: =SUM(L19,L24:L35) -> 11495872 | M18: =SUM(M19,M24:M35) -> 23561250 | ... O18: =SUM(O19,O24:O35) -> 19524883
A19: Balanço Patrimonial | E19: Caixa e equivalentes de caixa | F19: =SUM(F22:F23) -> 1205846 | G19: =SUM(G22:G23) -> 1676261 | H19: =SUM(H22:H23) -> 1043220 | I19: =SUM(I22:I23) -> 2433254 | J19: =SUM(J22:J23) -> 4827233 | K19: =SUM(K22:K23) -> 5773825 | L19: =SUM(L22:L23) -> 8328381 | M19: =SUM(M22:M23) -> 18652225 | ... O19: =SUM(O22:O23) -> 7960291
A20: Painel de Índices | E20: Caixa Operacional | F20: =IF(F19>2.5%*'DRE Consolidado'!K16,2.5%*'DRE Consolidado'!K16,'Balanço Patrimonial'!F19) -> 138479.85 | G20: =IF(G19>2.5%*'DRE Consolidado'!L16,2.5%*'DRE Consolidado'!L16,'Balanço Patrimonial'!G19) -> 149747.8 | H20: =IF(H19>2.5%*'DRE Consolidado'!M16,2.5%*'DRE Consolidado'!M16,'Balanço Patrimonial'!H19) -> 163077.9 | I20: =IF(I19>2.5%*'DRE Consolidado'!N16,2.5%*'DRE Consolidado'!N16,'Balanço Patrimonial'!I19) -> 181395.1 | J20: =IF(J19>2.5%*'DRE Consolidado'!O16,2.5%*'DRE Consolidado'!O16,'Balanço Patrimonial'!J19) -> 201884.73 | K20: =IF(K19>2.5%*'DRE Consolidado'!P16,2.5%*'DRE Consolidado'!P16,'Balanço Patrimonial'!K19) -> 242155.23 | L20: =IF(L19>2.5%*'DRE Consolidado'!Q16,2.5%*'DRE Consolidado'!Q16,'Balanço Patrimonial'!L19) -> 245176.43 | M20: =IF(M19>2.5%*'DRE Consolidado'!R16,2.5%*'DRE Consolidado'!R16,'Balanço Patrimonial'!M19) -> 346655.48 | N20: =IF(N19>2.5%*'DRE Consolidado'!V16,2.5%*'DRE Consolidado'!V16,'Balanço Patrimonial'!N19) -> 791448.85 | O20: =IF(O19>2.5%*'DRE Consolidado'!W16,2.5%*'DRE Consolidado'!W16,'Balanço Patrimonial'!O19) -> 998229.57
A21: Projeções - Receita e EBIT | E21: Excesso de Caixa | F21: =F19-F20 -> 1067366.1 | G21: =G19-G20 -> 1526513.2 | H21: =H19-H20 -> 880142.1 | I21: =I19-I20 -> 2251858.9 | J21: =J19-J20 -> 4625348.3 | K21: =K19-K20 -> 5531669.8 | L21: =L19-L20 -> 8083204.6 | M21: =M19-M20 -> 18305570 | ... O21: =O19-O20 -> 6962061.4
A22: Projeções - CG + Capex | E22: Caixa | F22: 372047 | G22: 951166 | H22: 585920 | I22: 714734 | J22: 690324 | K22: 591815 | L22: 409601 | M22: 1029383 | N22: 1718025 | O22: 1636283
A23: Projeções 2023 | E23: Títulos, valores mobiliários e aplicações financeiras | F23: 833799 | G23: 725095 | H23: 457300 | I23: 1718520 | J23: 4136909 | K23: 5182010 | L23: 7918780 | M23: 17622842 | N23: 11024128 | O23: 6324008
A24: Processos | E24: Instrumentos financeiros derivativos | F24: 0 | G24: 0 | H24: 0 | I24: 0 | J24: 22013 | K24: 32233 | L24: 80380 | M24: 147 | N24: 86 | O24: 2725
E25: Contas a receber | F25: 930511 | G25: 1007831 | H25: 1021422 | I25: 1211836 | J25: 1334813 | K25: 1755137 | L25: 1934446 | M25: 3260329 | N25: 4433345 | O25: 5708641
E26: Estoques | F26: 293987 | G26: 199270 | H26: 164626 | I26: 246147 | J26: 261987 | K26: 306037 | L26: 213017 | M26: 525950 | N26: 1694320 | O26: 2549583
E27: Ativo imobilizado disponibilizado para venda | F27: 172786 | G27: 226336 | H27: 331249 | I27: 313390 | J27: 397784 | K27: 541188 | L27: 320879 | M27: 431962 | N27: 1527738 | O27: 1515064
E28: Tributos a recuperar | F28: 156041 | G28: 178817 | H28: 45573 | I28: 125015 | J28: 117507 | K28: 155284 | L28: 160490 | M28: 325496 | N28: 361125 | O28: 431689
E29: Imposto de renda e contribuição social a recuperar | F29: 0 | G29: 0 | H29: 50027 | I29: 97196 | J29: 110149 | K29: 147266 | L29: 298451 | M29: 227643 | N29: 577912 | O29: 683055
E30: Despesas antecipadas | F30: 36070 | G30: 28290 | H30: 12891 | I30: 18673 | J30: 25583 | K30: 42874 | L30: 58314 | M30: 67977 | N30: 98457 | O30: 264295
E31: Dividendos a receber | F31: 0 | G31: 0 | H31: 0 | I31: 0 | J31: 0 | K31: 0 | L31: 0 | M31: 0 | N31: 0 | O31: 0
E32: Partes relacionadas | F32: 0 | G32: 0 | H32: 0 | I32: 0 | J32: 0 | K32: 0 | L32: 0 | M32: 0 | N32: 253 | O32: 253
E33: Adiantamentos a terceiros | F33: 0 | G33: 0 | H33: 29420 | I33: 27687 | J33: 58763 | K33: 82420 | L33: 43689 | M33: 69140 | N33: 111317 | O33: 349270
E34: Outros créditos | F34: 59152 | G34: 54238 | H34: 18272 | I34: 15263 | J34: 35488 | K34: 54568 | L34: 57825 | M34: 381 | N34: 86140 | O34: 60017
E35: Ativos mantidos para distribuição aos proprietários | F35: 0 | G35: 0 | H35: 0 | I35: 0 | J35: 0 | K35: 0 | L35: 0 | M35: 0 | N35: 0 | O35: 0
E36: Ativo Não Circulante | F36: =SUM(F37:F51) -> 4610838 | G36: =SUM(G37:G51) -> 5371552 | H36: =SUM(H37:H51) -> 6151683 | I36: =SUM(I37:I51) -> 7012463 | J36: =SUM(J37:J51) -> 8682634 | K36: =SUM(K37:K51) -> 11357402 | L36: =SUM(L37:L51) -> 14066376 | M36: =SUM(M37:M51) -> 24406944 | ... O36: =SUM(O37:O51) -> 43172732
E37: Títulos. valores mobiliários e aplicações financeiras | F37: 19746 | G37: 10376 | H37: 0 | I37: 5584 | J37: 4532 | K37: 655 | L37: 149483 | M37: 9264 | N37: 160116 | O37: 117884
E38: Instrumentos financeiros derivativos | F38: 9906 | G38: 71462 | H38: 36037 | I38: 108252 | J38: 438160 | K38: 638400 | L38: 334642 | M38: 58733 | N38: 184154 | O38: 288348
E39: Contas a receber | F39: 74085 | G39: 15792 | H39: 108356 | I39: 120603 | J39: 111868 | K39: 88321 | L39: 104684 | M39: 134627 | N39: 190197 | O39: 216245
E40: Tributos a recuperar | F40: 32440 | G40: 23518 | H40: 42604 | I40: 61930 | J40: 114222 | K40: 138466 | L40: 151909 | M40: 231145 | N40: 448366 | O40: 396259
E41: Imposto de renda e contribuição social a recuperar | F41: 0 | G41: 0 | H41: 19864 | I41: 20307 | J41: 24312 | K41: 34929 | L41: 66664 | M41: 127733 | N41: 155806 | O41: 110420
E42: Depósitos judiciais | F42: 44175 | G42: 42309 | H42: 120704 | I42: 62335 | J42: 73400 | K42: 76353 | L42: 75532 | M42: 103303 | N42: 105475 | O42: 119997
E43: Fundos para capitalizações de concessionárias | F43: 0 | G43: 0 | H43: 52642 | I43: 39692 | J43: 0 | K43: 0 | L43: 0 | M43: 0 | N43: 0 | O43: 0
E44: Imposto de renda e contribuição social diferidos | F44: 13727 | G44: 15635 | H44: 31438 | I44: 60626 | J44: 83620 | K44: 138431 | L44: 161215 | M44: 407120 | N44: 1177823 | O44: 1511049
E45: Despesas antecipadas | F45: 7400 | G45: 0 | H45: 0 | I45: 0 | J45: 0 | K45: 0 | L45: 0 | M45: 0 | N45: 0 | O45: 0
E46: Partes relacionadas | F46: 67 | G46: 410 | H46: 76 | I46: 188 | J46: 346 | K46: 0 | L46: 0 | M46: 0 | N46: 791 | O46: 942
E47: Ativo de indenização por combinação de negócios | F47: 0 | G47: 0 | H47: 0 | I47: 0 | J47: 0 | K47: 0 | L47: 103783 | M47: 281432 | N47: 299342 | O47: 630133
E48: Outros créditos | F48: 72381 | G48: 64463 | H48: 6035 | I48: 3634 | J48: 64437 | K48: 82391 | L48: 82984 | M48: 108782 | N48: 112804 | O48: 154700
... E51: Intangível | F51: 330469 | G51: 361790 | H51: 346029 | I51: 471719 | J51: 484576 | K51: 537735 | L51: 1071420 | M51: 1346837 | N51: 3026787 | O51: 3452474
E52: Passivo Total | F52: =SUM(F53,F73) -> 6420352 | G52: =SUM(G53,G73) -> 7722722 | H52: =SUM(H53,H73) -> 8259394 | I52: =SUM(I53,I73) -> 10311604 | J52: =SUM(J53,J73) -> 14625455 | K52: =SUM(K53,K73) -> 17888271 | L52: =SUM(L53,L73) -> 22338398 | M52: =SUM(M53,M73) -> 42143934 | ... O52: =SUM(O53,O73) -> 55746293
E53: Passivo Circulante | F53: =SUM(F54:F72) -> 1871356 | G53: =SUM(G54:G72) -> 2414240 | H53: =SUM(H54:H72) -> 3194162 | I53: =SUM(I54:I72) -> 3129688 | J53: =SUM(J54:J72) -> 4035478 | K53: =SUM(K54:K72) -> 4678968 | L53: =SUM(L54:L72) -> 5524858 | M53: =SUM(M54:M72) -> 7137334 | ... O53: =SUM(O54:O72) -> 11150737
E54: Fornecedores | F54: 316952 | G54: 505199 | H54: 992368 | I54: 878274 | J54: 1195407 | K54: 1691713 | L54: 2135298 | M54: 3374264 | N54: 5724420 | O54: 3268350
E55: Floor plan | F55: 56313 | G55: 33982 | H55: 28387 | I55: 72051 | J55: 93588 | K55: 106735 | L55: 71844 | M55: 175536 | N55: 378753 | O55: 361836
E56: Risco sacado a pagar - montadoras | F56: 378610 | G56: 625195 | H56: 551359 | I56: 248148 | J56: 0 | K56: 12051 | L56: 157923 | M56: 0 | N56: 72920 | O56: 120328
E57: Empréstimos e financiamentos | F57: 405601 | G57: 526829 | H57: 888916 | I57: 982697 | J57: 1495151 | K57: 1171988 | L57: 1284761 | M57: 765352 | N57: 1427853 | O57: 1947454
E58: Debêntures | F58: 164041 | G58: 126794 | H58: 142242 | I58: 284417 | J58: 483667 | K58: 694901 | L58: 592595 | M58: 661877 | N58: 2361078 | O58: 1137672
E59: Arrendamentos a pagar | F59: 134279 | G59: 160719 | H59: 165716 | I59: 142329 | J59: 91402 | K59: 140850 | L59: 131092 | M59: 118833 | N59: 71637 | O59: 117473
E60: Arrendamentos por direito de uso | F60: 0 | G60: 0 | H60: 0 | I60: 0 | J60: 0 | K60: 113869 | L60: 101600 | M60: 197769 | N60: 291430 | O60: 342244
E61: Cessão de direitos creditórios | F61: 0 | G61: 0 | H61: 0 | I61: 6043 | J61: 7410 | K61: 6043 | L61: 6043 | M61: 6043 | N61: 698404 | O61: 548015
E62: Obrigações sociais e trabalhistas | F62: 163623 | G62: 163687 | H62: 179418 | I62: 211652 | J62: 238034 | K62: 231374 | L62: 270006 | M62: 408154 | N62: 625156 | O62: 919264
E63: Imposto de renda e contribuição social a recolher | F63: 3851 | G63: 3625 | H63: 11528 | I63: 8907 | J63: 12356 | K63: 3094 | L63: 18679 | M63: 45865 | N63: 99818 | O63: 61086
E64: Instrumentos financeiros derivativos | F64: 0 | G64: 0 | H64: 0 | I64: 0 | J64: 0 | K64: 0 | L64: 0 | M64: 271251 | N64: 561290 | O64: 611279
E65: Tributos a recolher | F65: =44840-F63 -> 40989 | G65: =56608-3625 -> 52983 | H65: 51968 | I65: 76093 | J65: 75856 | K65: 83162 | L65: 103291 | M65: 220213 | N65: 385329 | O65: 361706
E66: Dividendos e juros sobre capital próprio a pagar | F66: 17205 | G66: 11106 | H66: 0 | I66: 0 | J66: 27541 | K66: 70587 | L66: 97856 | M66: 263280 | N66: 259201 | O66: 4123
E67: Adiantamentos de clientes | F67: 105144 | G67: 83747 | H67: 29101 | I67: 50844 | J67: 139345 | K67: 175700 | L67: 177170 | M67: 207720 | N67: 428469 | O67: 770594
E68: Compra de Ações Controlada a Termo | F68: 0 | G68: 0 | H68: 0 | I68: 0 | J68: 0 | K68: 0 | L68: 0 | M68: 0 | N68: 130606 | O68: 0
E69: Partes relacionadas | F69: 0 | G69: 0 | H69: 1782 | I69: 553 | J69: 246 | K69: 3056 | L69: 550 | M69: 453 | N69: 499 | O69: 396
E70: Outras contas a pagar | F70: 84748 | G70: 120374 | H70: 151377 | I70: 167680 | J70: 175475 | K70: 173845 | L70: 376150 | M70: 420724 | N70: 289150 | O70: 345263
E71: Obrigações a pagar por aquisição de emrpesas | N71: 153852 | O71: 233654
E72: Passivos mantidos para distribuição aos proprietários | F72: 0 | G72: 0 | H72: 0 | I72: 0 | J72: 0 | K72: 0 | L72: 0 | M72: 0 | N72: 0 | O72: 0
E73: Passivo Não Circulante | F73: =SUM(F74:F88) -> 4548996 | G73: =SUM(G74:G88) -> 5308482 | H73: =SUM(H74:H88) -> 5065232 | I73: =SUM(I74:I88) -> 7181916 | J73: =SUM(J74:J88) -> 10589977 | K73: =SUM(K74:K88) -> 13209303 | L73: =SUM(L74:L88) -> 16813540 | M73: =SUM(M74:M88) -> 35006600 | ... O73: =SUM(O74:O88) -> 44595556
E74: Empréstimos e financiamentos | F74: 2734029 | G74: 3213632 | H74: 2957220 | I74: 4809871 | J74: 7092551 | K74: 7050051 | L74: 9046647 | M74: 17962499 | N74: 15397022 | O74: 17095761
E75: Debêntures | F75: 1264377 | G75: 1487751 | H75: 1406375 | I75: 1731065 | J75: 2687075 | K75: 4676855 | L75: 5968161 | M75: 13874041 | N75: 18714687 | O75: 18890792
E76: Arrendamentos a pagar | F76: 139933 | G76: 193606 | H76: 189017 | I76: 70448 | J76: 151512 | K76: 260762 | L76: 182314 | M76: 137126 | N76: 161623 | O76: 154207
E77: Arrendamentos por direito de uso | F77: 0 | G77: 0 | H77: 0 | I77: 0 | J77: 0 | K77: 403831 | L77: 390965 | M77: 660011 | N77: 1399556 | O77: 1429059
E78: Instrumentos financeiros derivativos | F78: 3188 | G78: 0 | H78: 12223 | I78: 0 | J78: 0 | K78: 0 | L78: 0 | M78: 409000 | N78: 2670500 | O78: 1889413
E79: Partes relacionadas | F79: 525 | G79: 1017 | H79: 0 | I79: 0 | J79: 0 | K79: 0 | L79: 528 | M79: 528 | N79: 28047 | O79: 25554
E80: Cessão de direitos creditórios | F80: 0 | G80: 0 | H80: 0 | I80: 24171 | J80: 16761 | K80: 12085 | L80: 6043 | M80: 0 | N80: 1318613 | O80: 1634679
E81: Tributos a recolher | F81: 2021 | G81: 1805 | H81: 2701 | I81: 1705 | J81: 1103 | K81: 1095 | L81: 15992 | M81: 26995 | N81: 32945 | O81: 36742
E82: Provisão para demandas judiciais e administrativas | F82: 45131 | G82: 43354 | H82: 73712 | I82: 71463 | J82: 75563 | K82: 67829 | L82: 181865 | M82: 356544 | N82: 415333 | O82: 799967
E83: Imposto de renda e contribuição social diferidos | F83: 254860 | G83: 269451 | H83: 197088 | I83: 288893 | J83: 361234 | K83: 574120 | L83: 621467 | M83: 1038582 | N83: 1205986 | O83: 1513034
E84: Obrigações por aquisições de empresas | F84: 0 | G84: 0 | H84: 0 | I84: 0 | J84: 0 | K84: 93077 | L84: 0 | M84: 0 | N84: 641975 | O84: 978671
E85: Aterro sanitário – custo de encerramento | F85: 0 | G85: 0 | H85: 0 | I85: 0 | J85: 0 | K85: 0 | L85: - | M85: 105024 | N85: 9693 | O85: 11168
E86: Obrigações sociais e trabalhistas | O86: 14285
E87: Compra de ações de controladas a termo | F87: 0 | G87: 0 | H87: 0 | I87: 0 | J87: 0 | K87: 0 | L87: 0 | M87: 0 | N87: 0 | O87: 0
E88: Outras contas a pagar | F88: 104932 | G88: 97866 | H88: 226896 | I88: 184300 | J88: 204178 | K88: 69598 | L88: 399558 | M88: 436250 | N88: 121916 | O88: 122224
E89: Patrimônio Líquido | F89: =SUM(F90:F98) -> 1044879 | G89: =SUM(G90:G98) -> 1019873 | H89: =SUM(H90:H98) -> 608989 | I89: =SUM(I90:I98) -> 1189320 | J89: =SUM(J90:J98) -> 1248499 | K89: =SUM(K90:K98) -> 2379963 | L89: =SUM(L90:L98) -> 3223850 | M89: =SUM(M90:M98) -> 5824260 | ... O89: =SUM(O90:O98) -> 6951450
E90: Capital social | F90: 660495 | G90: 660395 | H90: 660395 | I90: 660395 | J90: 681202 | K90: 695069 | L90: 713975 | M90: 1164330 | N90: 1174362 | O90: 1174362
E91: Reservas de capital | F91: 6196 | G91: 8789 | H91: 14060 | I91: 21961 | J91: 33731 | K91: 50951 | L91: 575114 | M91: 1633343 | N91: 1903189 | O91: 2252861
E92: Ações em tesouraria | F92: -53509 | G92: -54133 | H92: -3741 | I92: -460 | J92: -103925 | K92: -460 | L92: -10503 | M92: -151633 | N92: -148114 | O92: -151047
E93: Reservas de lucros | F93: 424344 | G93: 400167 | H93: 0 | I93: 0 | J93: 17841 | K93: 159121 | L93: 262336 | M93: 877940 | N93: 925757 | O93: 807761
E94: Prejuízos Acumulados | F94: 0 | G94: 0 | H94: -66359 | I94: -72329 | J94: 0 | K94: 0 | L94: 0 | M94: 0 | N94: 0 | O94: 0
E95: Outros resultados abrangentes | F95: 0 | G95: 0 | H95: 0 | I95: -5400 | J95: -8273 | K95: 158635 | L95: 2103 | M95: -255956 | N95: -769101 | O95: -807191
E96: Ajustes de avaliação patrimonial | F96: 7327 | G96: 4634 | H96: 4634 | I96: 82621 | J96: 132569 | K96: 286760 | L96: 470044 | M96: 517257 | N96: 517257 | O96: 534968
E97: Outros ajustes patrimoniais reflexos de controladas | F97: 0 | G97: 0 | H97: 0 | I97: 0 | J97: 0 | K97: -3031 | L97: -120471 | M97: -269203 | N97: -721574 | O97: -313146
E98: Participações de não controladores | F98: 26 | G98: 21 | H98: 0 | I98: 502532 | J98: 495354 | K98: 1032918 | L98: 1331252 | M98: 2308182 | N98: 2699977 | O98: 3452882

Sheet Painel de Índices
E3: =Dashboard!H3 -> SIMPAR (SIMH3)
A7: Páginas
A8: Dashboard
A9: WACC | F9: 2014 | G9: 2015 | H9: 2016 | I9: 2017 | J9: 2018 | K9: 2019 | L9: 2020 | M9: 2021 | N9: 2022 | O9: 2023
A10: DRE Consolidado | E10: Liquidez Geral | F10: ='Balanço Patrimonial'!F17/'Balanço Patrimonial'!F52 -> 1.1627448 | G10: ='Balanço Patrimonial'!G17/'Balanço Patrimonial'!G52 -> 1.1320613 | H10: ='Balanço Patrimonial'!H17/'Balanço Patrimonial'!H52 -> 1.0737329 | I10: ='Balanço Patrimonial'!I17/'Balanço Patrimonial'!I52 -> 1.115338 | J10: ='Balanço Patrimonial'!J17/'Balanço Patrimonial'!J52 -> 1.0853648 | K10: ='Balanço Patrimonial'!K17/'Balanço Patrimonial'!K52 -> 1.131928 | L10: ='Balanço Patrimonial'!L17/'Balanço Patrimonial'!L52 -> 1.1443188 | M10: ='Balanço Patrimonial'!M17/'Balanço Patrimonial'!M52 -> 1.1381992 | ... O10: ='Balanço Patrimonial'!O17/'Balanço Patrimonial'!O52 -> 1.1246957
A11: DRE + DCF | E11: Liquidez Corrente | F11: ='Balanço Patrimonial'!F18/'Balanço Patrimonial'!F53 -> 1.5253073 | G11: ='Balanço Patrimonial'!G18/'Balanço Patrimonial'!G53 -> 1.3963164 | H11: ='Balanço Patrimonial'!H18/'Balanço Patrimonial'!H53 -> 0.85052042 | I11: ='Balanço Patrimonial'!I18/'Balanço Patrimonial'!I53 -> 1.4341561 | J11: ='Balanço Patrimonial'!J18/'Balanço Patrimonial'!J53 -> 1.7820243 | K11: ='Balanço Patrimonial'!K18/'Balanço Patrimonial'!K53 -> 1.9001694 | L11: ='Balanço Patrimonial'!L18/'Balanço Patrimonial'!L53 -> 2.0807543 | M11: ='Balanço Patrimonial'!M18/'Balanço Patrimonial'!M53 -> 3.3011276 | ... O11: ='Balanço Patrimonial'!O18/'Balanço Patrimonial'!O53 -> 1.7509948
A12: DRE - Contas Abertas | E12: Liquidez Seca | F12: =('Balanço Patrimonial'!F18-'Balanço Patrimonial'!F26)/'Balanço Patrimonial'!F53 -> 1.3682089 | G12: =('Balanço Patrimonial'!G18-'Balanço Patrimonial'!G26)/'Balanço Patrimonial'!G53 -> 1.313777 | H12: =('Balanço Patrimonial'!H18-'Balanço Patrimonial'!H26)/'Balanço Patrimonial'!H53 -> 0.79898077 | I12: =('Balanço Patrimonial'!I18-'Balanço Patrimonial'!I26)/'Balanço Patrimonial'!I53 -> 1.355507 | J12: =('Balanço Patrimonial'!J18-'Balanço Patrimonial'!J26)/'Balanço Patrimonial'!J53 -> 1.7171034 | K12: =('Balanço Patrimonial'!K18-'Balanço Patrimonial'!K26)/'Balanço Patrimonial'!K53 -> 1.8347625 | L12: =('Balanço Patrimonial'!L18-'Balanço Patrimonial'!L26)/'Balanço Patrimonial'!L53 -> 2.0421982 | M12: =('Balanço Patrimonial'!M18-'Balanço Patrimonial'!M26)/'Balanço Patrimonial'!M53 -> 3.2274376 | N12: =('Balanço Patrimonial'!L18-'Balanço Patrimonial'!N26)/'Balanço Patrimonial'!N53 -> 0.7021237 | O12: =('Balanço Patrimonial'!M18-'Balanço Patrimonial'!O26)/'Balanço Patrimonial'!O53 -> 1.8843299
A13: Balanço Patrimonial | E13: Liquidez Imediata | F13: =('Balanço Patrimonial'!F19+'Balanço Patrimonial'!F23)/'Balanço Patrimonial'!F53 -> 1.0899289 | G13: =('Balanço Patrimonial'!G19+'Balanço Patrimonial'!G23)/'Balanço Patrimonial'!G53 -> 0.99466333 | H13: =('Balanço Patrimonial'!H19+'Balanço Patrimonial'!H23)/'Balanço Patrimonial'!H53 -> 0.46976954 | I13: =('Balanço Patrimonial'!I19+'Balanço Patrimonial'!I23)/'Balanço Patrimonial'!I53 -> 1.3265776 | J13: =('Balanço Patrimonial'!J19+'Balanço Patrimonial'!J23)/'Balanço Patrimonial'!J53 -> 2.2213334 | K13: =('Balanço Patrimonial'!K19+'Balanço Patrimonial'!K23)/'Balanço Patrimonial'!K53 -> 2.3415067 | L13: =('Balanço Patrimonial'!L19+'Balanço Patrimonial'!L23)/'Balanço Patrimonial'!L53 -> 2.9407382 | M13: =('Balanço Patrimonial'!M19+'Balanço Patrimonial'!M23)/'Balanço Patrimonial'!M53 -> 5.0824393 | ... O13: =('Balanço Patrimonial'!O19+'Balanço Patrimonial'!O23)/'Balanço Patrimonial'!O53 -> 1.2810184
A14: Painel de Índices
A15: Projeções - Receita e EBIT
A16: Projeções - CG + Capex
A17: Projeções 2023 | F17: 2014 | G17: 2015 | H17: 2016 | I17: 2017 | J17: 2018 | K17: 2019 | L17: 2020 | M17: 2021 | N17: 2022
A18: Processos | E18: Retorno sobre o Equity (ROE) | F18: ='DRE Consolidado'!K45/'Balanço Patrimonial'!F89 -> 0.069328602 | G18: ='DRE Consolidado'!L45/'Balanço Patrimonial'!G89 -> 0.045849826 | H18: ='DRE Consolidado'!M45/'Balanço Patrimonial'!H89 -> -0.30078376 | I18: ='DRE Consolidado'!N45/'Balanço Patrimonial'!I89 -> 0.014056772 | J18: ='DRE Consolidado'!O45/'Balanço Patrimonial'!J89 -> 0.15151794 | K18: ='DRE Consolidado'!P45/'Balanço Patrimonial'!K89 -> 0.13387813 | L18: ='DRE Consolidado'!Q45/'Balanço Patrimonial'!L89 -> 0.13215224 | M18: ='DRE Consolidado'!R45/'Balanço Patrimonial'!M89 -> 0.22817491 | N18: ='DRE Consolidado'!S45/'Balanço Patrimonial'!N89 -> 0.16853254
E19: Retorno sobre o Ativo (ROA) | F19: ='DRE Consolidado'!K45/'Balanço Patrimonial'!F17 -> 0.0097036515 | G19: ='DRE Consolidado'!L45/'Balanço Patrimonial'!G17 -> 0.0053486408 | H19: ='DRE Consolidado'!M45/'Balanço Patrimonial'!H17 -> -0.020654724 | I19: ='DRE Consolidado'!N45/'Balanço Patrimonial'!I17 -> 0.0014536223 | J19: ='DRE Consolidado'!O45/'Balanço Patrimonial'!J17 -> 0.011917006 | K19: ='DRE Consolidado'!P45/'Balanço Patrimonial'!K17 -> 0.01573594 | L19: ='DRE Consolidado'!Q45/'Balanço Patrimonial'!L17 -> 0.016666727 | M19: ='DRE Consolidado'!R45/'Balanço Patrimonial'!M17 -> 0.027704816 | N19: ='DRE Consolidado'!S45/'Balanço Patrimonial'!N17 -> 0.015256478
E20: ROIC | F20: ='DRE + DCF'!K39 -> 0.087496051 | G20: ='DRE + DCF'!L39 -> 0.0927418 | H20: ='DRE + DCF'!M39 -> 0.090692945 | I20: ='DRE + DCF'!N39 -> 0.092089722 | J20: ='DRE + DCF'!O39 -> 0.098681459 | K20: ='DRE + DCF'!P39 -> 0.10811252 | L20: ='DRE + DCF'!Q39 -> 0.084555268 | M20: ='DRE + DCF'!R39 -> 0.12089622 | N20: ='DRE + DCF'!S39 -> 0.15951948
J23: -624650
F24: 2014 | G24: 2015 | H24: 2016 | I24: 2017 | J24: 2018 | K24: 2019 | L24: 2020 | M24: 2021 | N24: 2022
E25: Divida Líquida/EBITDA | F25: =SUM('Balanço Patrimonial'!F55:F60,'Balanço Patrimonial'!F74:F77,-'Balanço Patrimonial'!F19,-'Balanço Patrimonial'!F23,-'Balanço Patrimonial'!F37)/('DRE Consolidado'!K34+'Projeções - CG + Capex'!K57+'DRE Consolidado'!K55) -> 3.7030083 | G25: =SUM('Balanço Patrimonial'!G55:G60,'Balanço Patrimonial'!G74:G77,-'Balanço Patrimonial'!G19,-'Balanço Patrimonial'!G23,-'Balanço Patrimonial'!G37)/('DRE Consolidado'!L34+'Projeções - CG + Capex'!L57+'DRE Consolidado'!L55) -> 3.6231525 | H25: =SUM('Balanço Patrimonial'!H55:H60,'Balanço Patrimonial'!H74:H77,-'Balanço Patrimonial'!H19,-'Balanço Patrimonial'!H23,-'Balanço Patrimonial'!H37)/('DRE Consolidado'!M34+'Projeções - CG + Capex'!M57+'DRE Consolidado'!M55) -> 4.6164919 | I25: =SUM('Balanço Patrimonial'!I55:I60,'Balanço Patrimonial'!I74:I77,-'Balanço Patrimonial'!I19,-'Balanço Patrimonial'!I23,-'Balanço Patrimonial'!I37)/('DRE Consolidado'!N34+'Projeções - CG + Capex'!N57+'DRE Consolidado'!N55) -> 3.4008004 | J25: =SUM('Balanço Patrimonial'!J55:J60,'Balanço Patrimonial'!J74:J77,-'Balanço Patrimonial'!J19,-'Balanço Patrimonial'!J23,-'Balanço Patrimonial'!J37)/('DRE Consolidado'!O34+'Projeções - CG + Capex'!O57+'DRE Consolidado'!O55) -> 1.9569361 | K25: =SUM('Balanço Patrimonial'!K55:K60,'Balanço Patrimonial'!K74:K77,-'Balanço Patrimonial'!K19,-'Balanço Patrimonial'!K23,-'Balanço Patrimonial'!K37)/('DRE Consolidado'!P34+'Projeções - CG + Capex'!P57+'DRE Consolidado'!P55) -> 1.7370326 | L25: =SUM('Balanço Patrimonial'!L55:L60,'Balanço Patrimonial'!L74:L77,-'Balanço Patrimonial'!L19,-'Balanço Patrimonial'!L23,-'Balanço Patrimonial'!L37)/('DRE Consolidado'!Q34+'Projeções - CG + Capex'!Q57+'DRE Consolidado'!Q55) -> 0.71489471 | M25: =SUM('Balanço Patrimonial'!M55:M60,'Balanço Patrimonial'!M74:M77,-'Balanço Patrimonial'!M19,-'Balanço Patrimonial'!M23,-'Balanço Patrimonial'!M37)/('DRE Consolidado'!R34+'Projeções - CG + Capex'!R57+'DRE Consolidado'!R55) -> -0.41322803 | N25: =SUM('Balanço Patrimonial'!N55:N60,'Balanço Patrimonial'!N74:N77,-'Balanço Patrimonial'!N19,-'Balanço Patrimonial'!N23,-'Balanço Patrimonial'!N37)/('DRE Consolidado'!S34+'Projeções - CG + Capex'!S57+'DRE Consolidado'!S55) -> 2.3347058
E26: Cobertura de Juros | F26: =-'DRE Consolidado'!K34/'DRE Consolidado'!K40 -> 1.0036056 | G26: =-'DRE Consolidado'!L34/'DRE Consolidado'!L40 -> 0.81634866 | H26: =-'DRE Consolidado'!M34/'DRE Consolidado'!M40 -> 0.525048 | I26: =-'DRE Consolidado'!N34/'DRE Consolidado'!N40 -> 0.80044677 | J26: =-'DRE Consolidado'!O34/'DRE Consolidado'!O40 -> 0.96165173 | K26: =-'DRE Consolidado'!P34/'DRE Consolidado'!P40 -> 1.0580479 | L26: =-'DRE Consolidado'!Q34/'DRE Consolidado'!Q40 -> 0.97702528 | M26: =-'DRE Consolidado'!R34/'DRE Consolidado'!R40 -> 1.6021613 | N26: =-'DRE Consolidado'!S34/'DRE Consolidado'!S40 -> 0.95490189
E27: Dívida/Ativo | F27: =SUM('Balanço Patrimonial'!F55:F60,'Balanço Patrimonial'!F74:F77)/'Balanço Patrimonial'!F17 -> 0.7069015 | G27: =SUM('Balanço Patrimonial'!G55:G60,'Balanço Patrimonial'!G74:G77)/'Balanço Patrimonial'!G17 -> 0.72844596 | H27: =SUM('Balanço Patrimonial'!H55:H60,'Balanço Patrimonial'!H74:H77)/'Balanço Patrimonial'!H17 -> 0.71368501 | I27: =SUM('Balanço Patrimonial'!I55:I60,'Balanço Patrimonial'!I74:I77)/'Balanço Patrimonial'!I17 -> 0.72524834 | J27: =SUM('Balanço Patrimonial'!J55:J60,'Balanço Patrimonial'!J74:J77)/'Balanço Patrimonial'!J17 -> 0.76193657 | K27: =SUM('Balanço Patrimonial'!K55:K60,'Balanço Patrimonial'!K74:K77)/'Balanço Patrimonial'!K17 -> 0.72262564 | L27: =SUM('Balanço Patrimonial'!L55:L60,'Balanço Patrimonial'!L74:L77)/'Balanço Patrimonial'!L17 -> 0.70134293 | M27: =SUM('Balanço Patrimonial'!M55:M60,'Balanço Patrimonial'!M74:M77)/'Balanço Patrimonial'!M17 -> 0.72033239 | N27: =SUM('Balanço Patrimonial'!N55:N60,'Balanço Patrimonial'!N74:N77)/'Balanço Patrimonial'!N17 -> 0.65320915
E28: Dívida/Patrimônio Líquido | F28: =SUM('Balanço Patrimonial'!F55:F60,'Balanço Patrimonial'!F74:F77)/'Balanço Patrimonial'!F89 -> 5.0505207 | G28: =SUM('Balanço Patrimonial'!G55:G60,'Balanço Patrimonial'!G74:G77)/'Balanço Patrimonial'!G89 -> 6.2444128 | H28: =SUM('Balanço Patrimonial'!H55:H60,'Balanço Patrimonial'!H74:H77)/'Balanço Patrimonial'!H89 -> 10.393015 | I28: =SUM('Balanço Patrimonial'!I55:I60,'Balanço Patrimonial'!I74:I77)/'Balanço Patrimonial'!I89 -> 7.0132731 | J28: =SUM('Balanço Patrimonial'!J55:J60,'Balanço Patrimonial'!J74:J77)/'Balanço Patrimonial'!J89 -> 9.6875897 | K28: =SUM('Balanço Patrimonial'!K55:K60,'Balanço Patrimonial'!K74:K77)/'Balanço Patrimonial'!K89 -> 6.1479498 | L28: =SUM('Balanço Patrimonial'!L55:L60,'Balanço Patrimonial'!L74:L77)/'Balanço Patrimonial'!L89 -> 5.5610224 | M28: =SUM('Balanço Patrimonial'!M55:M60,'Balanço Patrimonial'!M74:M77)/'Balanço Patrimonial'!M89 -> 5.9326067 | N28: =SUM('Balanço Patrimonial'!N55:N60,'Balanço Patrimonial'!N74:N77)/'Balanço Patrimonial'!N89 -> 7.2157544
E29: Dívida/(Dívida + Patrimônio Líquido) | F29: =SUM('Balanço Patrimonial'!F55:F60,'Balanço Patrimonial'!F74:F77)/(SUM('Balanço Patrimonial'!F55:F60,'Balanço Patrimonial'!F74:F77)+'Balanço Patrimonial'!F89) -> 0.83472497 | G29: =SUM('Balanço Patrimonial'!G55:G60,'Balanço Patrimonial'!G74:G77)/(SUM('Balanço Patrimonial'!G55:G60,'Balanço Patrimonial'!G74:G77)+'Balanço Patrimonial'!G89) -> 0.86196259 | H29: =SUM('Balanço Patrimonial'!H55:H60,'Balanço Patrimonial'!H74:H77)/(SUM('Balanço Patrimonial'!H55:H60,'Balanço Patrimonial'!H74:H77)+'Balanço Patrimonial'!H89) -> 0.91222692 | I29: =SUM('Balanço Patrimonial'!I55:I60,'Balanço Patrimonial'!I74:I77)/(SUM('Balanço Patrimonial'!I55:I60,'Balanço Patrimonial'!I74:I77)+'Balanço Patrimonial'!I89) -> 0.87520705 | J29: =SUM('Balanço Patrimonial'!J55:J60,'Balanço Patrimonial'!J74:J77)/(SUM('Balanço Patrimonial'!J55:J60,'Balanço Patrimonial'!J74:J77)+'Balanço Patrimonial'!J89) -> 0.90643353 | K29: =SUM('Balanço Patrimonial'!K55:K60,'Balanço Patrimonial'!K74:K77)/(SUM('Balanço Patrimonial'!K55:K60,'Balanço Patrimonial'!K74:K77)+'Balanço Patrimonial'!K89) -> 0.86009974 | L29: =SUM('Balanço Patrimonial'!L55:L60,'Balanço Patrimonial'!L74:L77)/(SUM('Balanço Patrimonial'!L55:L60,'Balanço Patrimonial'!L74:L77)+'Balanço Patrimonial'!L89) -> 0.84758473 | M29: =SUM('Balanço Patrimonial'!M55:M60,'Balanço Patrimonial'!M74:M77)/(SUM('Balanço Patrimonial'!M55:M60,'Balanço Patrimonial'!M74:M77)+'Balanço Patrimonial'!M89) -> 0.85575411 | N29: =SUM('Balanço Patrimonial'!N55:N60,'Balanço Patrimonial'!N74:N77)/(SUM('Balanço Patrimonial'!N55:N60,'Balanço Patrimonial'!N74:N77)+'Balanço Patrimonial'!N89) -> 0.87828263
K32: -67020
F33: 2014 | G33: 2015 | H33: 2016 | I33: 2017 | J33: 2018 | K33: 2019 | L33: 2020 | M33: 2021 | N33: 2022
E34: Prazo Médio de Recebimento | F34: ='Balanço Patrimonial'!F25*365/'DRE Consolidado'!K13 -> 55.869667 | G34: ='Balanço Patrimonial'!G25*365/'DRE Consolidado'!L13 -> 56.063257 | H34: ='Balanço Patrimonial'!H25*365/'DRE Consolidado'!M13 -> 50.353847 | I34: ='Balanço Patrimonial'!I25*365/'DRE Consolidado'!N13 -> 53.942605 | J34: ='Balanço Patrimonial'!J25*365/'DRE Consolidado'!O13 -> 52.937311 | K34: ='Balanço Patrimonial'!K25*365/'DRE Consolidado'!P13 -> 59.679876 | L34: ='Balanço Patrimonial'!L25*365/'DRE Consolidado'!Q13 -> 64.927069 | M34: ='Balanço Patrimonial'!M25*365/'DRE Consolidado'!R13 -> 77.007107 | N34: ='Balanço Patrimonial'!N25*365/'DRE Consolidado'!S13 -> 60.280518
E35: Prazo Médio de Estoques | F35: ='Balanço Patrimonial'!F26*365/-'DRE Consolidado'!K18 -> 27.762313 | G35: ='Balanço Patrimonial'!G26*365/-'DRE Consolidado'!L18 -> 18.298043 | H35: ='Balanço Patrimonial'!H26*365/-'DRE Consolidado'!M18 -> 15.26372 | I35: ='Balanço Patrimonial'!I26*365/-'DRE Consolidado'!N18 -> 22.282365 | J35: ='Balanço Patrimonial'!J26*365/-'DRE Consolidado'!O18 -> 20.349176 | K35: ='Balanço Patrimonial'!K26*365/-'DRE Consolidado'!P18 -> 21.89129 | L35: ='Balanço Patrimonial'!L26*365/-'DRE Consolidado'!Q18 -> 15.042168 | M35: ='Balanço Patrimonial'!M26*365/-'DRE Consolidado'!R18 -> 26.281177 | N35: ='Balanço Patrimonial'!N26*365/-'DRE Consolidado'!S18 -> 48.98652
E36: Prazo Médio de Compras | F36: =-('Balanço Patrimonial'!F54+'Balanço Patrimonial'!F62)*365/('DRE Consolidado'!K18+'DRE Consolidado'!K23+'DRE Consolidado'!K55+'Projeções - CG + Capex'!K57) -> 43.97344 | G36: =-('Balanço Patrimonial'!G54+'Balanço Patrimonial'!G62)*365/('DRE Consolidado'!L18+'DRE Consolidado'!L23+'DRE Consolidado'!L55+'Projeções - CG + Capex'!L57) -> 60.728969 | H36: =-('Balanço Patrimonial'!H54+'Balanço Patrimonial'!H62)*365/('DRE Consolidado'!M18+'DRE Consolidado'!M23+'DRE Consolidado'!M55+'Projeções - CG + Capex'!M57) -> 102.12369 | I36: =-('Balanço Patrimonial'!I54+'Balanço Patrimonial'!I62)*365/('DRE Consolidado'!N18+'DRE Consolidado'!N23+'DRE Consolidado'!N55+'Projeções - CG + Capex'!N57) -> 92.776619 | J36: =-('Balanço Patrimonial'!J54+'Balanço Patrimonial'!J62)*365/('DRE Consolidado'!O18+'DRE Consolidado'!O23+'DRE Consolidado'!O55+'Projeções - CG + Capex'!O57) -> 107.47889 | K36: =-('Balanço Patrimonial'!K54+'Balanço Patrimonial'!K62)*365/('DRE Consolidado'!P18+'DRE Consolidado'!P23+'DRE Consolidado'!P55+'Projeções - CG + Capex'!P57) -> 139.10227 | L36: =-('Balanço Patrimonial'!L54+'Balanço Patrimonial'!L62)*365/('DRE Consolidado'!Q18+'DRE Consolidado'!Q23+'DRE Consolidado'!Q55+'Projeções - CG + Capex'!Q57) -> 173.95132 | M36: =-('Balanço Patrimonial'!M54+'Balanço Patrimonial'!M62)*365/('DRE Consolidado'!R18+'DRE Consolidado'!R23+'DRE Consolidado'!R55+'Projeções - CG + Capex'!R57) -> 181.68491 | N36: =-('Balanço Patrimonial'!N54+'Balanço Patrimonial'!N62)*365/('DRE Consolidado'!S18+'DRE Consolidado'!S23+'DRE Consolidado'!S55+'Projeções - CG + Capex'!S57) -> 175.40921
E37: Ciclo de Caixa | F37: =F34+F35-F36 -> 39.658541 | G37: =G34+G35-G36 -> 13.632331 | H37: =H34+H35-H36 -> -36.506125 | I37: =I34+I35-I36 -> -16.551649 | J37: =J34+J35-J36 -> -34.192406 | K37: =K34+K35-K36 -> -57.531105 | L37: =L34+L35-L36 -> -93.982082 | M37: =M34+M35-M36 -> -78.396626 | N37: =N34+N35-N36 -> -66.142172
F41: 2014 | G41: 2015 | H41: 2016 | I41: 2017 | J41: 2018 | K41: 2019 | L41: 2020 | M41: 2021 | N41: 2022
E42: Proventos por ação | F42: 0 | I42: 0 | J42: 0 | K42: 0 | L42: 0 | M42: 0.52083224 | N42: 0
E43: Dividend Yield (12 meses) | F43: 0 | I43: 0 | J43: 0 | K43: 0 | L43: 0 | M43: 0.034152934 | N43: 0
E44: Payout | F44: 0 | I44: 0 | J44: 0 | K44: 0 | L44: 0 | M44: 0.22965084 | N44: 0
H48: -624650
F49: 2023E | G49: 2024E | H49: 2025E | I49: 2026E | J49: 2027E
E50: EBITDA | F50: ='DRE Consolidado'!V75 -> 8301930.7 | G50: ='DRE Consolidado'!W75 -> 10656367 | H50: ='DRE Consolidado'!X75 -> 12582615 | I50: ='DRE Consolidado'!Y75 -> 13849342 | J50: ='DRE Consolidado'!Z75 -> 15022472
E51: EBITDA - A | F51: 13683300
E52: Dívida Líquida para Covenant dos Bonds | F52: =30916700-F56-F57 -> 32248565
E53: Dívida Líquida Para Covenant Local | F53: 31605200 | G53: =F53-SUM(G54,G56) -> 36283869 | H53: =G53-SUM(H54,H56) -> 40217726 | I53: =H53-SUM(I54,I56) -> 44722333 | J53: =I53-SUM(J54,J56) -> 47997365
E54: Resultado Financeiro Líquido Total | F54: =F55+F57 -> -4982331.3 | G54: =SUM(G55,G57) -> -4461496.6 | H54: =SUM(H55,H57) -> -4883227.6 | I54: =SUM(I55,I57) -> -5480168.3 | J54: =SUM(J55,J57) -> -5953054
E55: Resultado Financeiro Sobre Dívida Líquida | F55: =-F53*WACC!F18 -> -4806518.8 | G55: =-F53*WACC!G18 -> -4431049 | H55: =-G53*WACC!H18 -> -5014430.6 | I55: =-H53*WACC!I18 -> -5616405.4 | J55: =-I53*WACC!J18 -> -6332235.1
E56: FCFF | F56: ='DRE Consolidado'!U66 -> -1156052.9 | G56: ='DRE Consolidado'!W66 -> -217172.08 | H56: ='DRE Consolidado'!X66 -> 949370.63 | I56: ='DRE Consolidado'!Y66 -> 975561.22 | J56: ='DRE Consolidado'!Z66 -> 2678021.5
E57: Resultado Financeiro Sobre Variação de Caixa | F57: =F56*WACC!F18 -> -175812.53 | G57: =G56*WACC!G18 -> -30447.525 | H57: =H56*WACC!H18 -> 131203.02 | I57: =I56*WACC!I18 -> 136237.12 | J57: =J56*WACC!J18 -> 379181.06
E58: Dívida Líquida Máxima Bonds | F58: =F50*4 -> 33207723 | G58: =G50*4 -> 42625469 | H58: =H50*4 -> 50330459 | I58: =I50*4 -> 55397367 | J58: =J50*4 -> 60089889
E59: Dívida Líquida Máxima Local | F59: =F51*3.5 -> 47891550 | G59: =G51*3.5 -> 0 | H59: =H51*3.5 -> 0 | I59: =I51*3.5 -> 0 | J59: =J51*3.5 -> 0
E60: Resultado Financeiro Máximo | F60: =-F51*2 -> -27366600 | G60: =-G51*2 -> 0 | H60: =-H51*2 -> 0 | I60: =-I51*2 -> 0 | J60: =-J51*2 -> 0
E61: Divida Líquida/EBITDA Bonds | F61: =F52/F50 -> 3.8844657 | G61: =G53/G50 -> 3.4049004 | H61: =H53/H50 -> 3.1962931 | I61: =I53/I50 -> 3.2292028 | J61: =J53/J50 -> 3.1950377
E62: Divida Líquida/EBITDA Local | F62: =F53/F51 -> 2.3097645
E63: Cobertura de Juros | F63: =-F51/F54 -> 2.7463649 | G63: =-G50/G54 -> 2.3885185 | H63: =-H50/H54 -> 2.5767005 | I63: =-I50/I54 -> 2.5271745 | J63: =-J50/J54 -> 2.52349

Sheet Projeções - Receita e EBIT
Q3: =Dashboard!H3 -> SIMPAR (SIMH3)
A7: Páginas
A8: Dashboard
A9: WACC | F9: 2014 | G9: 2015 | H9: 2016 | I9: 2017 | J9: 2018 | K9: 2019 | L9: 2020 | M9: 2021 | N9: 2022 | O9: YTD 2023 | P9: YTG2023 | Q9: 2023 | R9: 2024 | S9: 2025 | T9: 2026 | U9: 2027 | V9: Premissa | W9: Nível de Otimismo (0-5) | X9: CAGR (2018 a 2022) | Y9: CAGR (2023 a 2027)
A10: DRE Consolidado | E10: Receita Líquida | J10: =SUM(J13:J21) -> 8031044.8 | K10: =SUM(K13:K21) -> 9686209.3 | L10: =SUM(L13:L21) -> 9807057 | M10: =SUM(M13:M21) -> 13866219 | N10: =SUM(N13:N21) -> 24381790 | O10: =SUM(O13:O21) -> 23321789 | P10: =Q10-O10 -> 8336165.1 | Q10: =SUM(Q13:Q21) -> 31657954 | R10: =SUM(R13:R21) -> 39929183 | S10: =SUM(S13:S21) -> 47076707 | T10: =SUM(T13:T21) -> 52864437 | U10: =SUM(U13:U21) -> 58805341 | X10: =(N10/J10)^(1/4)-1 -> 0.31999834 | Y10: =(U10/Q10)^(1/4)-1 -> 0.16743708
A11: DRE + DCF | E11: Crescimento da Receita (YoY)¹ | K11: =K10/J10-1 -> 0.20609578 | L11: =L10/K10-1 -> 0.012476264 | M11: =M10/L10-1 -> 0.4139022 | N11: =N10/M10-1 -> 0.75835887 | Q11: =Q10/M10-1 -> 1.2830992 | R11: =R10/Q10-1 -> 0.26126858 | S11: =S10/R10-1 -> 0.17900502 | T11: =T10/S10-1 -> 0.12294253 | U11: =U10/T10-1 -> 0.11237998
E12: Receita Líquida Ex Eliminações | J12: =SUM(J13:J19) -> 8178993.8 | K12: =SUM(K13:K19) -> 9861984.3 | L12: =SUM(L13:L19) -> 9934256 | M12: =SUM(M13:M19) -> 14060748 | N12: =SUM(N13:N19) -> 24921822 | O12: =SUM(O13:O19) -> 23757858 | P12: =SUM(P13:P19) -> 8494603.6 | Q12: =SUM(Q13:Q19) -> 32252462 | ... U12: =SUM(U13:U19) -> 59909652
A13: DRE - Contas Abertas | E13: JSL | J13: 3138376.8 | K13: 3101978.3 | L13: 2826797 | M13: 4295978.5 | N13: 6022405 | O13: 5413278 | P13: 2168879 | Q13: 7582157 | R13: 9238433.2 | S13: 10801504 | T13: 12266093 | U13: 13515280
A14: Balanço Patrimonial | E14: Movida | J14: 2538599 | K14: 3836044 | L14: 4085259 | M14: 5332623 | N14: 9600029 | O14: 7848570 | P14: 2569024.9 | Q14: 10417595 | R14: 12558572 | S14: 15971455 | T14: 18093643 | U14: 20469175
A15: Painel de Índices | E15: Vamos | J15: 938946 | K15: 1211508 | L15: 1513187 | M15: 2823495 | N15: 4913454 | O15: 4632745 | P15: 1787327.7 | Q15: 6420072.7 | R15: 8285054.3 | S15: 9830385.9 | T15: 11395644 | U15: 12992391
A16: Projeções - Receita e EBIT | E16: BBC | J16: =J25 -> 31855 | K16: =K25 -> 40031 | L16: =L25 -> 45426 | M16: =M25 -> 43267 | N16: =N25 -> 78351 | O16: =O25 -> 10184 | P16: =Q16-O16 -> 10184 | Q16: =Q25 -> 20368 | R16: =R25 -> 25507.337 | S16: =S25 -> 31943.452 | T16: =T25 -> 40003.555 | U16: =U25 -> 50097.415
A17: Projeções - CG + Capex | E17: Automob | J17: =J43 -> 702486 | K17: =K43 -> 821472 | L17: =L43 -> 617777 | M17: =M43 -> 731758 | N17: =N43 -> 3189039 | O17: =O43 -> 4805544 | P17: =Q17-O17 -> 1601848 | Q17: =Q43 -> 6407392 | R17: =R43 -> 9000000 | S17: =S43 -> 9577861.2 | T17: =T43 -> 10214122 | U17: =U43 -> 10924114
A18: Projeções 2023 | E18: CS Brasil | J18: =J62 -> 828731 | K18: =K62 -> 850951 | L18: =L62 -> 845810 | M18: =M62 -> 833627 | N18: =N62 -> 717399 | O18: =O62 -> 528340 | P18: =Q18-O18 -> 228014.91 | Q18: =Q62 -> 756354.91 | R18: =R62 -> 800074.16 | S18: =S62 -> 851444.36 | T18: =T62 -> 908006.15 | U18: =U62 -> 971122.38
A19: Processos | E19: CS Infra | J19: =J81 -> 0 | K19: =K81 -> 0 | L19: =L81 -> 0 | M19: =M81 -> 0 | N19: =N81 -> 401145 | O19: =O81 -> 519197 | P19: =Q19-O19 -> 129325.15 | Q19: =Q81 -> 648522.15 | R19: =R81 -> 771375.12 | S19: =S81 -> 896170.32 | T19: =T81 -> 939670.43 | U19: =U81 -> 987471.46
E20: Holding | N20: =N104 -> 63286 | O20: =O104 -> 61935 | P20: =Q20-O20 -> -61935 | Q20: =Q104 -> 0 | R20: =R104 -> 0 | S20: =S104 -> 0 | T20: =T104 -> 0 | U20: =U104 -> 0
E21: Eliminações | J21: -147949 | K21: -175775 | L21: =L120 -> -127199 | M21: =M120 -> -194529 | N21: =N120 -> -603318 | O21: =O120 -> -498004 | P21: =Q21-O21 -> -96503.463 | Q21: =Q120 -> -594507.46 | R21: =R120 -> -749833.59 | S21: =S120 -> -884057.56 | T21: =T120 -> -992745.84 | U21: =U120 -> -1104310.6
F24: 2014 | G24: 2015 | H24: 2016 | I24: 2017 | J24: 2018 | K24: 2019 | L24: 2020 | M24: 2021 | N24: 2022 | O24: YTD 2023 | P24: YTG2023 | Q24: 2023 | R24: 2024 | S24: 2025 | T24: 2026 | U24: 2027 | V24: Premissa | W24: Nível de Otimismo (0-5) | X24: CAGR (2015 a 2022) | Y24: CAGR (2018 a 2022)
E25: Receita Líquida | F25: 184.59 | G25: 5389 | H25: 28166 | I25: 23983 | J25: 31855 | K25: 40031 | L25: 45426 | M25: 43267 | N25: 78351 | O25: 10184 | P25: =Q25-O25 -> 10184 | Q25: =O25*2 -> 20368 | R25: =Q25*(1+$Y$25) -> 25507.337 | S25: =R25*(1+$Y$25) -> 31943.452 | T25: =S25*(1+$Y$25) -> 40003.555 | U25: =T25*(1+$Y$25) -> 50097.415 | V25: Crescimento com base no CAGR histórico de 2018 a 2022, cuja operação é mais parecida com a atual. | W25: 3 | X25: =(N25/G25)^(1/7)-1 -> 0.46580643 | Y25: =(N25/J25)^(1/4)-1 -> 0.25232409
E26: Crescimento da Receita (YoY)¹ | F26: 0 | G26: =G25/F25-1 -> 28.194431 | H26: =H25/G25-1 -> 4.2265726 | I26: =I25/H25-1 -> -0.14851239 | J26: =J25/I25-1 -> 0.3282325 | K26: =K25/J25-1 -> 0.256663 | L26: =L25/K25-1 -> 0.13477055 | M26: =M25/L25-1 -> -0.047527847 | N26: =N25/M25-1 -> 0.81087203 | Q26: =$Y$25 -> 0.25232409 | R26: =$Y$25 -> 0.25232409 | S26: =$Y$25 -> 0.25232409 | T26: =$Y$25 -> 0.25232409 | U26: =$Y$25 -> 0.25232409
E27: Custos das Vendas e Serviços | F27: -417.345 | G27: -4656 | H27: -21161 | I27: -9488 | J27: -10409 | K27: -11295 | L27: -10872 | M27: -8190 | N27: -17107 | O27: -4400
E28: Custo de Venda de Ativos Desmobilizados | J28: 0 | K28: 0
E29: Lucro Bruto | F29: =SUM(F25,F27:F28) -> -232.755 | G29: =SUM(G25,G27:G28) -> 733 | H29: =SUM(H25,H27:H28) -> 7005 | I29: =SUM(I25,I27:I28) -> 14495 | J29: =SUM(J25,J27:J28) -> 21446 | K29: =SUM(K25,K27:K28) -> 28736 | L29: =SUM(L25,L27:L28) -> 34554 | M29: =SUM(M25,M27:M28) -> 35077 | ... O29: =SUM(O25,O27:O28) -> 5784
E30: Margem Bruta | F30: =F29/F25 -> -1.2609296 | G30: =G29/G25 -> 0.13601781 | H30: =H29/H25 -> 0.24870411 | I30: =I29/I25 -> 0.60438644 | J30: =J29/J25 -> 0.67323811 | K30: =K29/K25 -> 0.71784367 | L30: =L29/L25 -> 0.7606657 | M30: =M29/M25 -> 0.81071024 | N30: =N29/N25 -> 0.78166201
E31: Despesas/ Receitas Operacionais | F31: =SUM(F33:F36) -> -5951 | G31: =SUM(G33:G36) -> -7780 | H31: =SUM(H33:H36) -> -8684 | I31: =SUM(I33:I36) -> -10297 | J31: =SUM(J33:J36) -> -12390 | K31: =SUM(K33:K36) -> -15687 | L31: =SUM(L33:L36) -> -18706 | M31: =SUM(M33:M36) -> -18295 | ... O31: =SUM(O33:O36) -> -45739
E32: (%) da Receita Líquida | F32: =-F31/F25 -> 32.239016 | G32: =-G31/G25 -> 1.4436816 | H32: =-H31/H25 -> 0.30831499 | I32: =-I31/I25 -> 0.42934579 | J32: =-J31/J25 -> 0.38894993 | K32: =-K31/K25 -> 0.3918713 | L32: =-L31/L25 -> 0.4117906 | M32: =-M31/M25 -> 0.42283958 | N32: =-N31/N25 -> 0.68158671 | O32: =O31/O25 -> -4.4912608
E33: Despesas Comerciais Gerais e Administrativas | F33: =-5919-9 -> -5928 | G33: =-7707-26 -> -7733 | H33: =-8588-75 -> -8663 | I33: -10232 | J33: -10585 | K33: =-340-11697 -> -12037 | L33: =-231-11019 -> -11250 | M33: =-8-12736 -> -12744 | N33: =-5352-38878 -> -44230 | O33: =-3178-31329 -> -34507
E34: Perdas pela Não Recuperabilidade de Ativos | J34: -1833 | K34: -3921 | L34: -9140 | M34: -6664 | N34: -13080 | O34: -12604
E35: Resultado Operacional Outros | F35: -23 | G35: -47 | H35: -21 | I35: -65 | J35: 28 | K35: 271 | L35: 1684 | M35: 1109 | N35: 3907 | O35: 1372
E36: Resultado de Equivalência Patrimonial | M36: 4 | N36: 0 | O36: 0
E37: EBIT | F37: =SUM(F29,F31) -> -6183.755 | G37: =SUM(G29,G31) -> -7047 | H37: =SUM(H29,H31) -> -1679 | I37: =SUM(I29,I31) -> 4198 | J37: =SUM(J29,J31) -> 9056 | K37: =SUM(K29,K31) -> 13049 | L37: =SUM(L29,L31) -> 15848 | M37: =SUM(M29,M31) -> 16782 | ... O37: =SUM(O29,O31) -> -39955 | P37: =Q37-O37 -> 39955 | Q37: =Q25*Q38 -> 0 | R37: =R38*R25 -> 0 | S37: =S38*S25 -> 0 | T37: =T38*T25 -> 0 | U37: =U38*U25 -> 0
E38: Margem EBIT | F38: =F37/F25 -> -33.499946 | G38: =G37/G25 -> -1.3076638 | H38: =H37/H25 -> -0.059610878 | I38: =I37/I25 -> 0.17504065 | J38: =J37/J25 -> 0.28428818 | K38: =K37/K25 -> 0.32597237 | L38: =L37/L25 -> 0.34887509 | M38: =M37/M25 -> 0.38787066 | ... O38: =O37/O25 -> -3.9233111 | Q38: 0 | R38: 0 | S38: 0 | T38: 0 | U38: 0
F42: 2014 | G42: 2015 | H42: 2016 | I42: 2017 | J42: 2018 | K42: 2019 | L42: 2020 | M42: 2021 | N42: 2022 | O42: YTD 2023 | P42: YTG2023 | Q42: 2023 | R42: 2024 | S42: 2025 | T42: 2026 | U42: 2027 | V42: Premissa | W42: Nível de Otimismo (0-5) | X42: CAGR (2017 a 2022) | Y42: CAGR (2023 a 2027)
E43: Receita Líquida | I43: 597682.38 | J43: 702486 | K43: 821472 | L43: 617777 | M43: 731758 | N43: 3189039 | O43: 4805544 | P43: =Q43-O43 -> 1601848 | Q43: =O43/3*4 -> 6407392 | R43: 9000000 | S43: =R43*(1+S44) -> 9577861.2 | T43: =S43*(1+T44) -> 10214122 | U43: =T43*(1+U44) -> 10924114 | V43: Crescimento com o PIB. Difícil projetar Automob agora, depois das últimas aquisições. Por isso, usamos um modelo de crescimento bem conservador. | W43: 2 | X43: =(N43/I43)^(1/5)-1 -> 0.39777695 | Y43: =(U43/Q43)^(1/4)-1 -> 0.14268423
E44: Crescimento da Receita (YoY)¹ | I44: 0 | J44: =J43/I43-1 -> 0.17535002 | K44: =K43/J43-1 -> 0.16937846 | L44: =L43/K43-1 -> -0.24796341 | M44: =M43/L43-1 -> 0.18450185 | N44: =N43/M43-1 -> 3.3580514 | Q44: =Q43/N43-1 -> 1.0091921 | R44: =R43/O43-1 -> 0.87283687 | S44: ='Projeções - CG + Capex'!M39 -> 0.0642068 | T44: ='Projeções - CG + Capex'!N39 -> 0.0664304 | U44: ='Projeções - CG + Capex'!O39 -> 0.0695108
E45: Custos das Vendas e Serviços | I45: -485163 | J45: -589249 | K45: -688206 | L45: -505964 | M45: -589455 | N45: -2647230 | O45: -4037006
E46: Custo de Venda de Ativos Desmobilizados | I46: -13455 | J46: -5157 | K46: -6611 | L46: -4517 | M46: -1155 | N46: -11457 | O46: -34403 | Q46: =-Q47*Q43 -> -52671.059 | R46: =-R47*R43 -> -73983.225 | S46: =-S47*S43 -> -78733.452 | T46: =-T47*T43 -> -83963.746 | U46: =-U47*U43 -> -89800.133
E47: % da Receita | I47: =-I46/I43 -> 0.022511957 | J47: =-J46/J43 -> 0.0073410716 | K47: =-K46/K43 -> 0.0080477484 | L47: =-L46/L43 -> 0.0073116999 | M47: =-M46/M43 -> 0.0015783907 | N47: =-N46/N43 -> 0.0035926183 | O47: =-O46/O43 -> 0.007159023 | Q47: =AVERAGE($I$47:$O$47) -> 0.0082203584 | R47: =AVERAGE($I$47:$O$47) -> 0.0082203584 | S47: =AVERAGE($I$47:$O$47) -> 0.0082203584 | T47: =AVERAGE($I$47:$O$47) -> 0.0082203584 | U47: =AVERAGE($I$47:$O$47) -> 0.0082203584
E48: Lucro Bruto | I48: =SUM(I43,I45:I46) -> 99064.383 | J48: =SUM(J43,J45:J46) -> 108080 | K48: =SUM(K43,K45:K46) -> 126655 | L48: =SUM(L43,L45:L46) -> 107296 | M48: =SUM(M43,M45:M46) -> 141148 | N48: =SUM(N43,N45:N46) -> 530352 | O48: =SUM(O43,O45:O46) -> 734135
E49: Margem Bruta | I49: =I48/I43 -> 0.16574754 | J49: =J48/J43 -> 0.1538536 | K49: =K48/K43 -> 0.15418054 | L49: =L48/L43 -> 0.17368079 | M49: =M48/M43 -> 0.19288891 | N49: =N48/N43 -> 0.16630465 | O49: =O48/O43 -> 0.15276834
E50: Despesas/ Receitas Operacionais | I50: =SUM(I52:I55) -> -81992 | J50: =SUM(J52:J55) -> -94262 | K50: =SUM(K52:K55) -> -104013 | L50: =SUM(L52:L55) -> -87199 | M50: =SUM(M52:M55) -> -90691 | N50: =SUM(N52:N55) -> -387044 | O50: =SUM(O52:O55) -> -526934
E51: (%) da Receita Líquida | I51: =-I50/I43 -> 0.13718323 | J51: =-J50/J43 -> 0.13418346 | K51: =-K50/K43 -> 0.12661783 | L51: =-L50/L43 -> 0.14114964 | M51: =-M50/M43 -> 0.12393578 | N51: =-N50/N43 -> 0.12136697 | O51: =-O50/O43 -> 0.10965127
E52: Despesas Comerciais Gerais e Administrativas | I52: =-87439-7926 -> -95365 | J52: =-7776-89544 -> -97320 | K52: =-16460-89599 -> -106059 | L52: =-32038-57039 -> -89077 | M52: =-43502-66412 -> -109914 | N52: =-184076-195167 -> -379243 | O52: =-279451-273514 -> -552965
E53: Perdas pela Não Recuperabilidade de Ativos | I53: -97 | J53: -98 | K53: -944 | L53: 581 | M53: 97 | N53: -3076 | O53: -5481
E54: Resultado Operacional Outros | I54: 13470 | J54: 3156 | K54: 2990 | L54: 1297 | M54: 19126 | N54: -4747 | O54: 31468
E55: Resultado de Equivalência Patrimonial | N55: 22 | O55: 44
E56: EBIT | I56: =SUM(I48,I50) -> 17072.383 | J56: =SUM(J48,J50) -> 13818 | K56: =SUM(K48,K50) -> 22642 | L56: =SUM(L48,L50) -> 20097 | M56: =SUM(M48,M50) -> 50457 | N56: =SUM(N48,N50) -> 143308 | O56: =SUM(O48,O50) -> 207201 | P56: =Q56-O56 -> 105526.62 | Q56: =Q58*Q43 -> 312727.62 | R56: =R58*R43 -> 439265.87 | S56: =S58*S43 -> 467469.72 | T56: =T58*T43 -> 498523.92 | U56: =U58*U43 -> 533176.72
E57: % EBIT Simpar Capital Fechado | J57: =J56/'DRE + DCF'!O15 -> 0.10829323 | K57: =K56/'DRE + DCF'!P15 -> 0.13735494 | L57: =L56/'DRE + DCF'!Q15 -> 0.12503033 | M57: =M56/'DRE + DCF'!R15 -> 0.27091589 | N57: =N56/'DRE + DCF'!S15 -> 0.44776894 | O57: =O56/'DRE + DCF'!T15 -> 0.87700044 | P57: =P56/'DRE + DCF'!U15 -> 0.34443525 | Q57: =Q56/'DRE + DCF'!V15 -> 0.57631113 | ... U57: =U56/'DRE + DCF'!Z15 -> 0.54669496
E58: Margem EBIT | I58: =I56/I43 -> 0.028564307 | J58: =J56/J43 -> 0.019670143 | K58: =K56/K43 -> 0.027562717 | L58: =L56/L43 -> 0.032531156 | M58: =M56/M43 -> 0.068953124 | N58: =N56/N43 -> 0.044937676 | O58: =O56/O43 -> 0.043117075 | P58: =P56/P43 -> 0.06587805 | Q58: =AVERAGE($L$58:$N$58) -> 0.048807318 | R58: =AVERAGE($L$58:$N$58) -> 0.048807318 | S58: =AVERAGE($L$58:$N$58) -> 0.048807318 | T58: =AVERAGE($L$58:$N$58) -> 0.048807318 | U58: =AVERAGE($L$58:$N$58) -> 0.048807318
F61: 2014 | G61: 2015 | H61: 2016 | I61: 2017 | J61: 2018 | K61: 2019 | L61: 2020 | M61: 2021 | N61: 2022 | O61: YTD 2023 | P61: YTG2023 | Q61: 2023 | R61: 2024 | S61: 2025 | T61: 2026 | U61: 2027 | V61: Premissa | W61: Nível de Otimismo (0-5) | X61: CAGR (2018 a 2022) | Y61: CAGR (2023 a 2027)
E62: Receita Líquida | J62: 828731 | K62: 850951 | L62: 845810 | M62: 833627 | N62: 717399 | O62: 528340 | P62: =Q62-O62 -> 228014.91 | Q62: =N62*(1+Q63) -> 756354.91 | R62: =Q62*(1+R63) -> 800074.16 | S62: =R62*(1+S63) -> 851444.36 | T62: =S62*(1+T63) -> 908006.15 | U62: =T62*(1+U63) -> 971122.38 | V62: Crescimento com o PIB. Difícil projetar CS Brasil agora, depois das últimas transformações. Por isso, usamos um modelo de crescimento bem conservador. | W62: 4 | X62: =(N62/J62)^(1/4)-1 -> -0.035423237 | Y62: =(U62/Q62)^(1/4)-1 -> 0.064478962
E63: Crescimento da Receita (YoY)¹ | J63: 0 | K63: =K62/J62-1 -> 0.026812078 | L63: =L62/K62-1 -> -0.0060414759 | M63: =M62/L62-1 -> -0.014403944 | N63: =N62/M62-1 -> -0.13942447 | Q63: ='Projeções - CG + Capex'!K39 -> 0.0543016 | R63: ='Projeções - CG + Capex'!L39 -> 0.05780255 | S63: ='Projeções - CG + Capex'!M39 -> 0.0642068 | T63: ='Projeções - CG + Capex'!N39 -> 0.0664304 | U63: ='Projeções - CG + Capex'!O39 -> 0.0695108
E64: Custos das Vendas e Serviços | J64: -580962 | K64: -558867 | L64: -469196 | M64: -444164 | N64: -530566 | O64: -301260
E65: Custo de Venda de Ativos Desmobilizados | J65: -131843 | K65: -139194 | L65: -171242 | M65: -158843 | N65: -43083 | O65: -117672 | Q65: =-Q66*Q62 -> -125862.9 | R65: =-R66*R62 -> -133138.09 | S65: =-S66*S62 -> -141686.47 | T65: =-T66*T62 -> -151098.75 | U65: =-U66*U62 -> -161601.75
E66: % da Receita | J66: =-J65/J62 -> 0.15909022 | K66: =-K65/K62 -> 0.16357464 | L66: =-L65/L62 -> 0.20245918 | M66: =-M65/M62 -> 0.19054445 | N66: =-N65/N62 -> 0.060054447 | O66: =-O65/O62 -> 0.22272022 | Q66: =AVERAGE($J$66:$O$66) -> 0.16640719 | R66: =AVERAGE($J$66:$O$66) -> 0.16640719 | S66: =AVERAGE($J$66:$O$66) -> 0.16640719 | T66: =AVERAGE($J$66:$O$66) -> 0.16640719 | U66: =AVERAGE($J$66:$O$66) -> 0.16640719
E67: Lucro Bruto | J67: =SUM(J62,J64:J65) -> 115926 | K67: =SUM(K62,K64:K65) -> 152890 | L67: =SUM(L62,L64:L65) -> 205372 | M67: =SUM(M62,M64:M65) -> 230620 | N67: =SUM(N62,N64:N65) -> 143750 | O67: =SUM(O62,O64:O65) -> 109408
E68: Margem Bruta | J68: =J67/J62 -> 0.13988375 | K68: =K67/K62 -> 0.17966957 | L68: =L67/L62 -> 0.24281103 | M68: =M67/M62 -> 0.27664651 | N68: =N67/N62 -> 0.20037664 | O68: =O67/O62 -> 0.20707878
E69: Despesas/ Receitas Operacionais | J69: =SUM(J71:J74) -> -32939 | K69: =SUM(K71:K74) -> -15212 | L69: =SUM(L71:L74) -> -39199 | M69: =SUM(M71:M74) -> -48879 | N69: =SUM(N71:N74) -> -10417 | O69: =SUM(O71:O74) -> -28010
E70: (%) da Receita Líquida | J70: =J69/J62 -> -0.039746311 | K70: =K69/K62 -> -0.01787647 | L70: =L69/L62 -> -0.046344924 | M70: =M69/M62 -> -0.058634137 | N70: =N69/N62 -> -0.014520511 | O70: =O69/O62 -> -0.053015104
E71: Despesas Comerciais Gerais e Administrativas | J71: =-2517-40311 -> -42828 | K71: =-3658-31369 -> -35027 | L71: =-2557-36106 -> -38663 | M71: =-4290-41322 -> -45612 | N71: =-2391-45440 -> -47831 | O71: =-1136-26752 -> -27888
E72: Perdas pela Não Recuperabilidade de Ativos | J72: 2636 | K72: -1246 | L72: -2122 | M72: 160 | N72: -2965 | O72: -2591
E73: Resultado Operacional Outros | J73: 8225 | K73: 22262 | L73: 2101 | M73: -1936 | N73: 37598 | O73: -411
E74: Resultado de Equivalência Patrimonial | J74: -972 | K74: -1201 | L74: -515 | M74: -1491 | N74: 2781 | O74: 2880
E75: EBIT | J75: =SUM(J67,J69) -> 82987 | K75: =SUM(K67,K69) -> 137678 | L75: =SUM(L67,L69) -> 166173 | M75: =SUM(M67,M69) -> 181741 | N75: =SUM(N67,N69) -> 133333 | O75: =SUM(O67,O69) -> 81398 | P75: =Q75-O75 -> 69957.344 | Q75: =Q62*Q76 -> 151355.34 | R75: =R62*R76 -> 160104.07 | S75: =S62*S76 -> 170383.84 | T75: =T62*T76 -> 181702.51 | U75: =U62*U76 -> 194332.79
E76: Margem EBIT | J76: =J75/J62 -> 0.10013744 | K76: =K75/K62 -> 0.1617931 | L76: =L75/L62 -> 0.19646611 | M76: =M75/M62 -> 0.21801237 | N76: =N75/N62 -> 0.18585613 | O76: =O75/O62 -> 0.15406367 | P76: =P75/P62 -> 0.30681039 | Q76: =AVERAGE($L$76:$N$76) -> 0.20011154 | R76: =AVERAGE($L$76:$N$76) -> 0.20011154 | S76: =AVERAGE($L$76:$N$76) -> 0.20011154 | T76: =AVERAGE($L$76:$N$76) -> 0.20011154 | U76: =AVERAGE($L$76:$N$76) -> 0.20011154
F80: 2014 | G80: 2015 | H80: 2016 | I80: 2017 | J80: 2018 | K80: 2019 | L80: 2020 | M80: 2021 | N80: 2022 | O80: YTD 2023 | P80: YTG2023 | Q80: 2023 | R80: 2024 | S80: 2025 | T80: 2026 | U80: 2027 | V80: Premissa | W80: Nível de Otimismo (0-5) | Y80: CAGR (2023 a 2027)
E81: Receita Líquida | N81: 401145 | O81: 519197 | P81: =Q81-O81 -> 129325.15 | Q81: =SUM(Q82:Q85) -> 648522.15 | R81: =SUM(R82:R85) -> 771375.12 | S81: =SUM(S82:S85) -> 896170.32 | T81: =S81*(1+'Projeções - CG + Capex'!O37) -> 939670.43 | U81: =T81*(1+'Projeções - CG + Capex'!P37) -> 987471.46 | V81: Crescemos a Receita conforme calendário de maturidade das concessões fornecidos pela Simpar. Daí em diante, crescemos a Receita com a inflação, por se tratarem de concessões com preços regulados. | W81: 3 | Y81: =(U81/Q81)^(1/4)-1 -> 0.11083597
E82: Portos | Q82: 156500 | R82: =S82*3/4 -> 234750 | S82: 313000
E83: Transcerrados | Q83: 24333.333 | R83: =S83*2/3 -> 48666.667 | S83: 73000
E84: BRT | Q84: 88688.82 | R84: =Q84*(1+'Projeções - CG + Capex'!M37) -> 92532.593 | S84: =R84*(1+'Projeções - CG + Capex'!N37) -> 96744.677
E85: Ciclus | Q85: 379000 | R85: =Q85*(1+'Projeções - CG + Capex'!M37) -> 395425.86 | S85: =R85*(1+'Projeções - CG + Capex'!N37) -> 413425.65
E86: Crescimento da Receita (YoY)¹ | Q86: =Q81/N81-1 -> 0.61667764 | R86: =R81/Q81-1 -> 0.18943527 | S86: =S81/R81-1 -> 0.16178277 | T86: =T81/S81-1 -> 0.04854 | U86: =U81/T81-1 -> 0.05087
E87: Custos das Vendas e Serviços | N87: -279667 | O87: -320612
E88: Custo de Construção | N88: 0 | O88: -82622
E89: Custo de Venda de Ativos Desmobilizados | N89: 0 | O89: 0
E90: Lucro Bruto | N90: =SUM(N81,N87:N89) -> 121478 | O90: =SUM(O81,O87:O89) -> 115963
E91: Margem Bruta | N91: =N90/N81 -> 0.30282815 | O91: =O90/O81 -> 0.22335067
E92: Despesas/ Receitas Operacionais | N92: =SUM(N94:N97) -> -20828 | O92: =SUM(O94:O97) -> -53074
E93: (%) da Receita Líquida | N93: =N92/N81 -> -0.051921375 | O93: =O92/O81 -> -0.10222324
E94: Despesas Comerciais Gerais e Administrativas | N94: =-44-24016 -> -24060 | O94: =-481-53280 -> -53761
E95: Perdas pela Não Recuperabilidade de Ativos | N95: 0 | O95: 49
E96: Resultado Operacional Outros | N96: 3232 | O96: 638
E97: Resultado de Equivalência Patrimonial | N97: 0 | O97: 0
E98: EBIT | N98: =SUM(N90,N92) -> 100650 | O98: =SUM(O90,O92) -> 62889 | P98: =Q98-O98 -> 15664.824 | Q98: =Q99*Q81 -> 78553.824 | R98: =R99*R81 -> 193543.25 | S98: =S99*S81 -> 224855.21 | T98: =T99*T81 -> 235769.68 | U98: =U99*U81 -> 247763.28
E99: Margem EBIT | N99: =N98/N81 -> 0.25090678 | O99: =O98/O81 -> 0.12112743 | P99: =P98/P81 -> 0.12112743 | Q99: =O99 -> 0.12112743 | R99: =N99 -> 0.25090678 | S99: =R99 -> 0.25090678 | T99: =S99 -> 0.25090678 | U99: =T99 -> 0.25090678
F103: 2014 | G103: 2015 | H103: 2016 | I103: 2017 | J103: 2018 | K103: 2019 | L103: 2020 | M103: 2021 | N103: 2022 | O103: YTD 2023 | P103: YTG2023 | Q103: 2023 | R103: 2024 | S103: 2025 | T103: 2026 | U103: 2027 | V103: Premissa | W103: Nível de Otimismo (0-5) | X103: CAGR (2018 a 2022) | Y103: CAGR (2023 a 2027)
E104: Receita Líquida | J104: 0 | K104: 0 | L104: 0 | M104: 0 | N104: 63286 | O104: 61935
E105: Custos das Vendas e Serviços | J105: 0 | K105: 0 | L105: 0 | M105: 0 | N105: -9026 | O105: -8597
E106: Custo de Venda de Ativos Desmobilizados | J106: 0 | K106: 0 | L106: 0 | M106: 0 | N106: -28484 | O106: -44814
E107: Lucro Bruto | J107: =SUM(J104,J105:J106) -> 0 | K107: =SUM(K104,K105:K106) -> 0 | L107: =SUM(L104,L105:L106) -> 0 | M107: =SUM(M104,M105:M106) -> 0 | N107: =SUM(N104,N105:N106) -> 25776 | O107: =SUM(O104,O105:O106) -> 8524
E108: Margem Bruta | J108: 0 | K108: 0 | L108: 0 | M108: 0 | N108: =N107/N104 -> 0.40729387 | O108: =O107/O104 -> 0.13762816
E109: Despesas/ Receitas Operacionais | J109: =SUM(J110,J112:J114) -> 21737 | K109: =SUM(K110,K112:K114) -> -8508 | L109: =SUM(L110,L112:L114) -> -51066 | M109: =SUM(M110,M112:M114) -> -57183 | N109: =SUM(N110,N112:N114) -> -88803 | O109: =SUM(O110,O112:O114) -> -53610
E110: Despesas Comerciais Gerais e Administrativas | J110: -4138 | K110: =-27-4863 -> -4890 | L110: -47407 | M110: -78506 | N110: -98210 | O110: =-751-53368 -> -54119 | Q110: =Q111*'DRE Consolidado'!V16 -> -133313.08 | R110: =R111*'DRE Consolidado'!W16 -> -168143.6 | S110: =S111*'DRE Consolidado'!X16 -> -198242.14 | T110: =T111*'DRE Consolidado'!Y16 -> -222614.54 | U110: =U111*'DRE Consolidado'!Z16 -> -247631.95 | V110: Custos cálculados com base na média histórica, em cima da Receita Líquida do grupo todo. | W110: 5 | X110: =(N110/J110)^(1/3)-1 -> 1.8737903 | Y110: =(U110/Q110)^(1/4)-1 -> 0.16743708
E111: % da Receita | J111: =J110/'DRE Consolidado'!O16 -> -0.00051242114 | K111: =K110/'DRE Consolidado'!P16 -> -0.00050484147 | L111: =L110/'DRE Consolidado'!Q16 -> -0.004833968 | M111: =M110/'DRE Consolidado'!R16 -> -0.0056616732 | N111: =N110/'DRE Consolidado'!S16 -> -0.004028006 | O111: =O110/'DRE Consolidado'!T16 -> -0.0023205338 | Q111: =AVERAGE($L$111:$O$111) -> -0.0042110452 | R111: =AVERAGE($L$111:$O$111) -> -0.0042110452 | S111: =AVERAGE($L$111:$O$111) -> -0.0042110452 | T111: =AVERAGE($L$111:$O$111) -> -0.0042110452 | U111: =AVERAGE($L$111:$O$111) -> -0.0042110452
E112: Perdas pela Não Recuperabilidade de Ativos | J112: 0 | K112: 0 | L112: 0 | M112: 0 | N112: 0 | O112: 0
E113: Resultado Operacional Outros | J113: 25875 | K113: -3618 | L113: -3659 | M113: 21323 | N113: 9407 | O113: 509
E114: Resultado de Equivalência Patrimonial | J114: 0 | K114: 0 | L114: 0 | M114: 0 | N114: 0 | O114: 0
E115: EBIT | J115: =SUM(J107,J109) -> 21737 | K115: =SUM(K107,K109) -> -8508 | L115: =SUM(L107,L109) -> -51066 | M115: =SUM(M107,M109) -> -57183 | N115: =SUM(N107,N109) -> -63027 | O115: =SUM(O107,O109) -> -45086 | Q115: =Q110 -> -133313.08 | R115: =R110 -> -168143.6 | S115: =S110 -> -198242.14 | T115: =T110 -> -222614.54 | U115: =U110 -> -247631.95 | V115: O EBIT foi igulado aos custos administrativos da holding.
F119: 2014 | G119: 2015 | H119: 2016 | I119: 2017 | J119: 2018 | K119: 2019 | L119: 2020 | M119: 2021 | N119: 2022 | O119: YTD 2023 | P119: YTG2023 | Q119: 2023 | R119: 2024 | S119: 2025 | T119: 2026 | U119: 2027 | V119: Premissa | W119: Nível de Otimismo (0-5) | X119: CAGR (2018 a 2022) | Y119: CAGR (2023 a 2027)
E120: Receita Líquida | F120: -115197 | G120: -203939 | H120: -197163 | I120: -198350 | J120: -152176 | K120: -223981 | L120: -127199 | M120: -194529 | N120: -603318 | O120: -498004 | P120: =Q120-O120 -> -96503.463 | Q120: =-Q122*Q12 -> -594507.46 | R120: =-R122*R12 -> -749833.59 | S120: =-S122*S12 -> -884057.56 | T120: =-T122*T12 -> -992745.84 | U120: =-U122*U12 -> -1104310.6 | V120: Percentual fixo da Receita Líquida, com base na média histórica. | W120: 5 | X120: =(N120/F120)^(1/8)-1 -> 0.22995193 | Y120: =(U120/Q120)^(1/4)-1 -> 0.16743708
E121: Crescimento da Receita (YoY)¹ | F121: 0 | G121: =G120/F120-1 -> 0.77034992 | H121: =H120/G120-1 -> -0.033225621 | I121: =I120/H120-1 -> 0.0060203994 | J121: =J120/I120-1 -> -0.23279052 | K121: =K120/J120-1 -> 0.47185496 | L121: =L120/K120-1 -> -0.43209915 | M121: =M120/L120-1 -> 0.52932806 | N121: =N120/M120-1 -> 2.1014296 | Q121: =Q120/M120-1 -> 2.056138 | R121: =R120/Q120-1 -> 0.26126858 | S121: =S120/R120-1 -> 0.17900502 | T121: =T120/S120-1 -> 0.12294253 | U121: =U120/T120-1 -> 0.11237998
...

Sheet Projeções - CG + Capex
L3: =Dashboard!H3 -> SIMPAR (SIMH3)
A7: Páginas
A8: Dashboard
A9: WACC | E9: Data do Último Resultado: | K9: 2014 | L9: 2015 | M9: 2016 | N9: 2017 | O9: 2018 | P9: 2019 | Q9: 2020 | R9: 2021 | S9: 2022 | T9: 2023 | U9: 2024 | V9: 2025 | W9: 2026 | X9: 2027
A10: DRE Consolidado | E10: Capital de Giro | K10: ='Balanço Patrimonial'!F16 -> 1054514.9 | L10: ='Balanço Patrimonial'!G16 -> 903808.8 | M10: ='Balanço Patrimonial'!H16 -> 420797.9 | N10: ='Balanço Patrimonial'!I16 -> 837109.1 | O10: ='Balanço Patrimonial'!J16 -> 694547.73 | P10: ='Balanço Patrimonial'!K16 -> 923644.23 | Q10: ='Balanço Patrimonial'!L16 -> 228174.42 | R10: ='Balanço Patrimonial'!M16 -> 38166.475 | S10: ='Balanço Patrimonial'!N16 -> 610651.85 | T10: =T11*'DRE Consolidado'!V16 -> 2650721.7 | U10: =U11*'DRE Consolidado'!W16 -> 3343272 | V10: =V11*'DRE Consolidado'!X16 -> 3941734.5 | W10: =W11*'DRE Consolidado'!Y16 -> 4426341.3 | X10: =X11*'DRE Consolidado'!Z16 -> 4923773.5
A11: DRE + DCF | E11: (%) da Receita Líquida | K11: =K10/'DRE Consolidado'!K16 -> 0.19037334 | L11: =L10/'DRE Consolidado'!L16 -> 0.15088849 | M11: =M10/'DRE Consolidado'!M16 -> 0.064508726 | N11: =N10/'DRE Consolidado'!N16 -> 0.11537096 | O11: =O10/'DRE Consolidado'!O16 -> 0.086007959 | P11: =P10/'DRE Consolidado'!P16 -> 0.095356628 | Q11: =Q10/'DRE Consolidado'!Q16 -> 0.02326635 | R11: =R10/'DRE Consolidado'!R16 -> 0.0027524789 | S11: =S10/'DRE Consolidado'!S16 -> 0.025045406 | T11: =AVERAGE($K$11:$S$11) -> 0.083730038 | U11: =AVERAGE($K$11:$S$11) -> 0.083730038 | V11: =AVERAGE($K$11:$S$11) -> 0.083730038 | W11: =AVERAGE($K$11:$S$11) -> 0.083730038 | X11: =AVERAGE($K$11:$S$11) -> 0.083730038
A12: DRE - Contas Abertas
A13: Balanço Patrimonial
A14: Painel de Índices
A15: Projeções - Receita e EBIT | E15: Controladas | K15: 2014 | L15: 2015 | M15: 2016 | N15: 2017 | O15: 2018 | P15: 2019 | Q15: 2020 | R15: 2021 | S15: 2022 | T15: 2023 | U15: 2024 | V15: 2025 | W15: 2026 | X15: 2027
A16: Projeções - CG + CAPEX | E16: BBC
A17: Projeções 2023 | E17: Automob (Aquisições + Bruto de Renovação) | O17: 7811.0773 | P17: 11615.358 | Q17: 5230.2642 | R17: 13485.061 | S17: 1254968 | T17: =SUM(T19:T26) -> 306322.9 | U17: =SUM(U19:U26) -> 159545.27 | V17: =SUM(V19:V26) -> 188079.63 | W17: =SUM(W19:W26) -> 133175.44 | X17: =SUM(X19:X26) -> 142432.57
A18: Processos | E18: (%) da Receita Líquida | O18: =O17/'Projeções - Receita e EBIT'!J43 -> 0.011119193 | P18: =P17/'Projeções - Receita e EBIT'!K43 -> 0.014139688 | Q18: =Q17/'Projeções - Receita e EBIT'!L43 -> 0.0084662656 | R18: =R17/'Projeções - Receita e EBIT'!M43 -> 0.018428306 | S18: =S17/'Projeções - Receita e EBIT'!N43 -> 0.39352545 | T18: =AVERAGE($O$18:$R$18) -> 0.013038363 | U18: =AVERAGE($O$18:$R$18) -> 0.013038363 | V18: =AVERAGE($O$18:$R$18) -> 0.013038363 | W18: =AVERAGE($O$18:$R$18) -> 0.013038363 | X18: =AVERAGE($O$18:$R$18) -> 0.013038363
F19: Capex líquido de Renovação | S19: 28055 | T19: =T18*'Projeções - Receita e EBIT'!Q43 -> 83541.904 | U19: =U18*'Projeções - Receita e EBIT'!R43 -> 117345.27 | V19: =V18*'Projeções - Receita e EBIT'!S43 -> 124879.63 | W19: =W18*'Projeções - Receita e EBIT'!T43 -> 133175.44 | X19: =X18*'Projeções - Receita e EBIT'!U43 -> 142432.57
F20: Aquisição SAGAMAR | S20: 262588
F21: Aquisição Autostar | S21: 372189
F22: Aquisição Grupo Green | S22: 60686 | T22: 39481
F23: Aquisição UAB Motors | S23: 531450
F24: Aquisição Best Points | T24: 60200 | U24: 18900 | V24: 28300
F25: Aquisição Grupo Alta | T25: 59200 | U25: 23300 | V25: 34900
F26: Aquisição Nova Quality | T26: 63900
E27: CS Brasil | O27: 534255.88 | P27: 539504.35 | Q27: 602332.97 | R27: 811594.49 | S27: 0 | T27: =T28*'Projeções - Receita e EBIT'!Q62 -> 94544.364 | U27: =U28*'Projeções - Receita e EBIT'!R62 -> 100009.27 | V27: =V28*'Projeções - Receita e EBIT'!S62 -> 106430.54 | W27: =W28*'Projeções - Receita e EBIT'!T62 -> 113500.77 | X27: =X28*'Projeções - Receita e EBIT'!U62 -> 121390.3
E28: (%) da Receita Líquida | O28: =O27/'Projeções - Receita e EBIT'!J62 -> 0.64466743 | P28: =P27/'Projeções - Receita e EBIT'!K62 -> 0.63400167 | Q28: =Q27/'Projeções - Receita e EBIT'!L62 -> 0.71213744 | R28: =R27/'Projeções - Receita e EBIT'!M62 -> 0.97357031 | S28: =S27/'Projeções - Receita e EBIT'!N62 -> 0 | T28: 0.125 | U28: =T28 -> 0.125 | V28: =U28 -> 0.125 | W28: =V28 -> 0.125 | X28: =W28 -> 0.125
E29: CS Infra | O29: 0 | P29: 0 | Q29: 0 | R29: 0 | S29: 134000 | T29: =(171.7+103)*1000 -> 274700 | U29: =(171.7+103)*1000 -> 274700 | V29: 103000 | W29: =W30*'Projeções - Receita e EBIT'!T81 -> 107999.62 | X29: =X30*'Projeções - Receita e EBIT'!U81 -> 113493.56
E30: (%) da Receita Líquida | O30: =O29/'DRE Consolidado'!O16 -> 0 | P30: =P29/'DRE Consolidado'!P16 -> 0 | Q30: =Q29/'DRE Consolidado'!Q16 -> 0 | R30: =R29/'DRE Consolidado'!R16 -> 0 | S30: =S29/'DRE Consolidado'!S16 -> 0.0054959047 | T30: =T29/'Projeções - Receita e EBIT'!Q81 -> 0.42357844 | U30: =U29/'Projeções - Receita e EBIT'!R81 -> 0.35611727 | V30: =V29/'Projeções - Receita e EBIT'!S81 -> 0.11493351 | W30: =V30 -> 0.11493351 | X30: =W30 -> 0.11493351
E31: Custo de Venda de Ativos | O31: =SUM('Projeções - Receita e EBIT'!J28,'Projeções - Receita e EBIT'!J46,'Projeções - Receita e EBIT'!J65,'Projeções - Receita e EBIT'!J89) -> -137000 | P31: =SUM('Projeções - Receita e EBIT'!K28,'Projeções - Receita e EBIT'!K46,'Projeções - Receita e EBIT'!K65,'Projeções - Receita e EBIT'!K89) -> -145805 | Q31: =SUM('Projeções - Receita e EBIT'!L28,'Projeções - Receita e EBIT'!L46,'Projeções - Receita e EBIT'!L65,'Projeções - Receita e EBIT'!L89) -> -175759 | R31: =SUM('Projeções - Receita e EBIT'!M28,'Projeções - Receita e EBIT'!M46,'Projeções - Receita e EBIT'!M65,'Projeções - Receita e EBIT'!M89) -> -159998 | S31: =SUM('Projeções - Receita e EBIT'!N28,'Projeções - Receita e EBIT'!N46,'Projeções - Receita e EBIT'!N65,'Projeções - Receita e EBIT'!N89) -> -54540 | T31: =SUM('Projeções - Receita e EBIT'!Q46,'Projeções - Receita e EBIT'!Q65) -> -178533.96 | U31: =SUM('Projeções - Receita e EBIT'!R46,'Projeções - Receita e EBIT'!R65) -> -207121.32 | V31: =SUM('Projeções - Receita e EBIT'!S46,'Projeções - Receita e EBIT'!S65) -> -220419.92 | W31: =SUM('Projeções - Receita e EBIT'!T46,'Projeções - Receita e EBIT'!T65) -> -235062.5 | X31: =SUM('Projeções - Receita e EBIT'!U46,'Projeções - Receita e EBIT'!U65) -> -251401.88
E32: Total Capex Líquido | O32: =SUM(O16,O17,O27,O29,O31) -> 405066.96 | P32: =SUM(P16,P17,P27,P29,P31) -> 405314.71 | Q32: =SUM(Q16,Q17,Q27,Q29,Q31) -> 431804.23 | R32: =SUM(R16,R17,R27,R29,R31) -> 665081.55 | S32: =SUM(S16,S17,S27,S29,S31) -> 1334428 | T32: =SUM(T16,T17,T27,T29,T31) -> 497033.31 | U32: =SUM(U16,U17,U27,U29,U31) -> 327133.22 | V32: =SUM(V16,V17,V27,V29,V31) -> 177090.26 | ... X32: =SUM(X16,X17,X27,X29,X31) -> 125914.54
E36: Ano | K36: 2023 | L36: 2024 | M36: 2025 | N36: 2026 | O36: 2027 | P36: 2028 | Q36: 2029 | R36: 2030 | S36: 2031 | T36: 2032 | U36: 2033
E37: Inflação | K37: =WACC!F12 -> 0.0418 | L37: =WACC!G12 -> 0.04217 | M37: =WACC!H12 -> 0.04334 | N37: =WACC!I12 -> 0.04552 | O37: =WACC!J12 -> 0.04854 | P37: =WACC!K12 -> 0.05087 | Q37: =WACC!L12 -> 0.05238 | R37: =WACC!M12 -> 0.0543 | ... U37: =WACC!P12 -> 0.05584
E38: Crescimento PIB Real (FMI) | K38: 0.012 | L38: 0.015 | M38: 0.02 | N38: 0.02 | O38: 0.02 | P38: 0.02 | Q38: 0.02 | R38: 0.02 | S38: 0.02 | T38: 0.02 | U38: 0.02
E39: Crescimento PIB Nominal | K39: =(1+K37)*(1+K38)-1 -> 0.0543016 | L39: =(1+L37)*(1+L38)-1 -> 0.05780255 | M39: =(1+M37)*(1+M38)-1 -> 0.0642068 | N39: =(1+N37)*(1+N38)-1 -> 0.0664304 | O39: =(1+O37)*(1+O38)-1 -> 0.0695108 | P39: =(1+P37)*(1+P38)-1 -> 0.0718874 | Q39: =(1+Q37)*(1+Q38)-1 -> 0.0734276 | R39: =(1+R37)*(1+R38)-1 -> 0.075386 | ... U39: =(1+U37)*(1+U38)-1 -> 0.0769568
E44: Ano | K44: 2014 | L44: 2015 | M44: 2016 | N44: 2017 | O44: 2018 | P44: 2019 | Q44: 2020 | R44: 2021 | S44: 2022 | T44: YTD 2023
E45: D&A do Arrendamento JSL | P45: 44835 | Q45: 91139 | R45: 56466 | S45: 87450 | T45: 78322
E46: D&A do Arrendamento Movida | P46: 55977 | Q46: 58450 | R46: 101267 | S46: 183795 | T46: 109178
E47: D&A do Arrendamento Vamos | P47: 8974 | Q47: 9014 | R47: 10223 | S47: 16120 | T47: 18861
E48: D&A do Arrendamento Simpar | K48: 0 | L48: 0 | M48: 0 | N48: 0 | O48: 0 | P48: 127308 | Q48: 129146 | R48: 186383 | S48: 199519 | T48: =49753+254420 -> 304173
E53: Ano | K53: 2014 | L53: 2015 | M53: 2016 | N53: 2017 | O53: 2018 | P53: 2019 | Q53: 2020 | R53: 2021 | S53: 2022 | T53: YTD 2023
E54: Depreciação & Amortização JSL | F54: 0 | G54: 0 | H54: 0 | I54: 0 | J54: 0 | O54: 176783 | P54: 183884 | Q54: 144858 | R54: 177673 | S54: 71645 | T54: 239860
E55: Depreciação & Amortização Movida | F55: 0 | G55: 0 | H55: 0 | I55: 0 | J55: 0 | L55: 101445 | M55: 77845 | N55: 74739 | O55: 102011 | P55: 222394 | Q55: 354430 | R55: 314984 | S55: 951429 | T55: 1082576
E56: Depreciação & Amortização Vamos | F56: 0 | G56: 0 | H56: 0 | I56: 0 | J56: 0 | M56: 116439 | N56: 124043 | O56: 207475 | P56: 225997 | Q56: 260205 | R56: 285886 | S56: 305835 | T56: 387109
E57: Depreciação e Amortização Simpar | K57: =-'DRE - Contas Abertas'!F19 -> 408865 | L57: =-'DRE - Contas Abertas'!G19 -> 508626 | M57: =-'DRE - Contas Abertas'!H19 -> 547187 | N57: =-'DRE - Contas Abertas'!I19 -> 525731 | O57: =-'DRE - Contas Abertas'!J19 -> 636817 | P57: =-'DRE - Contas Abertas'!K19-P48 -> 789436 | Q57: =-'DRE - Contas Abertas'!L19-Q48 -> 982807 | R57: =-'DRE - Contas Abertas'!M19-R48 -> 872731 | S57: =-'DRE - Contas Abertas'!N19-S48 -> 1686758 | T57: =-'DRE - Contas Abertas'!O19-T48 -> 1739054
E62: Ano | K62: 2014 | L62: 2015 | M62: 2016 | N62: 2017 | O62: 2018 | P62: 2019 | Q62: 2020 | R62: 2021 | S62: 2022 | T62: YTD 2023
E63: ∆ Capital de Giro JSL | F63: 0 | G63: -122636.72 | H63: 147702.64 | I63: -36069.72 | J63: -41836.44 | O63: -106924.9 | P63: 165562.04 | Q63: -37475.532 | R63: 151983.54 | S63: -563688.64 | T63: 172467.59
E64: ∆ Capital de Giro Movida | F64: 0 | G64: -122636.72 | H64: 147702.64 | I64: -36069.72 | J64: -41836.44 | M64: -331764.22 | N64: 67357.25 | O64: -78593.6 | P64: -119673.88 | Q64: 7026 | R64: -595797 | S64: 1212017.5 | T64: 209538.86
E65: ∆ Capital de Giro Vamos | F65: 0 | G65: -122636.72 | H65: 147702.64 | I65: -36069.72 | J65: -41836.44 | M65: 85296.5 | N65: 109623.4 | O65: 49086.75 | P65: 122239.05 | Q65: -435335.02 | R65: 389113.7 | S65: -728826.54 | T65: 3507374.6
E66: ∆ Capital de Giro Simpar | L66: ='Projeções - CG + Capex'!L10-'Projeções - CG + Capex'!K10 -> -150706.05 | M66: ='Projeções - CG + Capex'!M10-'Projeções - CG + Capex'!L10 -> -483010.9 | N66: ='Projeções - CG + Capex'!N10-'Projeções - CG + Capex'!M10 -> 416311.2 | O66: ='Projeções - CG + Capex'!O10-'Projeções - CG + Capex'!N10 -> -142561.38 | P66: ='Projeções - CG + Capex'!P10-'Projeções - CG + Capex'!O10 -> 229096.5 | Q66: ='Projeções - CG + Capex'!Q10-'Projeções - CG + Capex'!P10 -> -695469.8 | R66: ='Projeções - CG + Capex'!R10-'Projeções - CG + Capex'!Q10 -> -190007.95 | S66: ='Projeções - CG + Capex'!S10-'Projeções - CG + Capex'!R10 -> 572485.38 | T66: ='Balanço Patrimonial'!O16-'Balanço Patrimonial'!N16 -> 5062236.7

Sheet Projeções 2023
F3: =Dashboard!H3 -> SIMPAR (SIMH3)
A7: Páginas
A8: Dashboard
A9: WACC | F9: 1T23E | G9: 2T23E | H9: 3T23E | I9: 4T23E | J9: 2023E | M9: 1T23E | N9: 2T23E | O9: 3T23E | P9: 4T23E | Q9: 2023E
A10: DRE Consolidado | E10: Receita Líquida | F10: =AVERAGE(M$21:M$22,M$24:M$25)*$J$10 -> 6690979.4 | G10: =AVERAGE(N$21:N$22,N$24:N$25)*$J$10 -> 7422415.8 | H10: =AVERAGE(O$21:O$22,O$24:O$25)*$J$10 -> 8532345.4 | I10: =AVERAGE(P$21:P$22,P$24:P$25)*$J$10 -> 9012213.4 | J10: ='DRE Consolidado'!V16 -> 31657954 | L10: Receita Líquida | M10: 7440044 | N10: 7563636 | O10: 8318109 | P10: 0 | Q10: 0
A11: DRE + DCF | E11: CPV + Despesas Operacionais | F11: =F12-F10 -> -5314726.2 | G11: =G12-G10 -> -5773192.8 | H11: =H12-H10 -> -6770628.5 | I11: =I12-I10 -> -7171863.2 | J11: =J12-J10 -> -25030411 | L11: CPV + Despesas Operacionais | M11: =-3874946-14313-1417269-303427-407793-63043-43430+1281 -> -6122940 | N11: =-4189000-10787-1213561-274419-449086-47563+207949+939 -> -5975528 | O11: =-6095554-302873-488047-31933-4825+856 -> -6922376 | P11: 0 | Q11: 0
A12: DRE - Contas Abertas | E12: EBIT | F12: =AVERAGE(M$29:M$30,M$32:M$33)*$J$12 -> 1376253.3 | G12: =AVERAGE(N$29:N$30,N$32:N$33)*$J$12 -> 1649223 | H12: =AVERAGE(O$29:O$30,O$32:O$33)*$J$12 -> 1761717 | I12: =AVERAGE(P$29:P$30,P$32:P$33)*$J$12 -> 1840350.2 | J12: ='DRE Consolidado'!S37*J10 -> 6627543.4 | L12: EBIT | M12: =SUM(M10:M11) -> 1317104 | N12: =SUM(N10:N11) -> 1588108 | O12: =SUM(O10:O11) -> 1395733 | P12: 0 | Q12: 0
A13: Balanço Patrimonial | E13: Margem EBIT | F13: =F12/F10 -> 0.20568786 | G13: =G12/G10 -> 0.22219491 | H13: =H12/H10 -> 0.20647511 | I13: =I12/I10 -> 0.20420624 | J13: =J12/J10 -> 0.20934844 | L13: Margem EBIT | M13: =M12/M10 -> 0.17702906 | N13: =N12/N10 -> 0.20996621 | O13: =O12/O10 -> 0.16779451 | P13: 0 | Q13: 0
A14: Painel de Índices | E14: Imposto de Renda e CSLL | F14: =-'DRE Consolidado'!$V$54*'Projeções 2023'!F12 -> -176155.56 | G14: =-'DRE Consolidado'!$V$54*'Projeções 2023'!G12 -> -211094.73 | H14: =-'DRE Consolidado'!$V$54*'Projeções 2023'!H12 -> -225493.56 | I14: =-'DRE Consolidado'!$V$54*'Projeções 2023'!I12 -> -235558.34 | J14: =SUM(F14:I14) -> -848302.18 | L14: Imposto de Renda e CSLL | M14: =-32898+103176 -> 70278 | N14: =-32042+25155 -> -6887 | O14: =-21094+103252 -> 82158 | P14: 0 | Q14: 0
A15: Projeções - Receita e EBIT | E15: D&A de Arrendamento | F15: ='DRE Consolidado'!$V$56*'Projeções 2023'!F10 -> 88663.102 | G15: ='DRE Consolidado'!$V$56*'Projeções 2023'!G10 -> 98355.468 | H15: ='DRE Consolidado'!$V$56*'Projeções 2023'!H10 -> 113063.3 | I15: ='DRE Consolidado'!$V$56*'Projeções 2023'!I10 -> 119422.1 | J15: ='DRE Consolidado'!$V$56*'Projeções 2023'!J10 -> 419503.97 | L15: D&A de Arrendamento | M15: 81612 | N15: 84705 | O15: 137856 | P15: 0 | Q15: 0
A16: Projeções - CG + Capex | E16: NOPAT | F16: =F12+F14+F15 -> 1288760.8 | G16: =G12+G14+G15 -> 1536483.7 | H16: =H12+H14+H15 -> 1649286.7 | I16: =I12+I14+I15 -> 1724214 | J16: =J12+J14+J15 -> 6198745.2 | L16: NOPAT | M16: =SUM(M12,M14:M15) -> 1468994 | N16: =SUM(N12,N14:N15) -> 1665926 | O16: =SUM(O12,O14:O15) -> 1615747 | P16: 0 | Q16: 0
A17: Projeções 2023
A18: Processos
F20: 1º Trimestre | G20: 2º Trimestre | H20: 3º Trimestre | I20: 4º Trimestre | M20: 1º Trimestre | N20: 2º Trimestre | O20: 3º Trimestre | P20: 4º Trimestre
E21: 2018 | F21: 1936817.3 | G21: 1938188.6 | H21: 2068909.9 | I21: 2131477.9 | L21: 2018 | M21: =F21/SUM($F21:$I21) -> 0.23984185 | N21: =G21/SUM($F21:$I21) -> 0.24001165 | O21: =H21/SUM($F21:$I21) -> 0.25619926 | P21: =I21/SUM($F21:$I21) -> 0.26394724
E22: 2019 | F22: 2211784.8 | G22: 2388942.9 | H22: 2453591.5 | I22: 2631890.1 | L22: 2019 | M22: =F22/SUM($F22:$I22) -> 0.22834369 | N22: =G22/SUM($F22:$I22) -> 0.24663342 | O22: =H22/SUM($F22:$I22) -> 0.25330771 | P22: =I22/SUM($F22:$I22) -> 0.27171518
E23: 2020 | F23: 2356892.3 | G23: 2197224.8 | H23: 2603044.9 | I23: 2649895 | L23: 2020 | M23: =F23/SUM($F23:$I23) -> 0.24032615 | N23: =G23/SUM($F23:$I23) -> 0.22404527 | O23: =H23/SUM($F23:$I23) -> 0.2654257 | P23: =I23/SUM($F23:$I23) -> 0.27020288
E24: 2021 | F24: 2620105.7 | G24: 3149066.3 | H24: 3958280 | I24: 4138767 | L24: 2021 | M24: =F24/SUM($F24:$I24) -> 0.18895603 | N24: =G24/SUM($F24:$I24) -> 0.22710346 | O24: =H24/SUM($F24:$I24) -> 0.2854621 | P24: =I24/SUM($F24:$I24) -> 0.29847841
E25: 2022 | F25: =4590.296*1000 -> 4590296 | G25: =5463.4182*1000 -> 5463418.2 | H25: =6902.4238*1000 -> 6902423.8 | I25: =7425.65273798362*1000 -> 7425652.7 | L25: 2022 | M25: =F25/SUM($F25:$I25) -> 0.18826739 | N25: =G25/SUM($F25:$I25) -> 0.22407781 | O25: =H25/SUM($F25:$I25) -> 0.28309749 | P25: =I25/SUM($F25:$I25) -> 0.30455732
F28: 1º Trimestre | G28: 2º Trimestre | H28: 3º Trimestre | I28: 4º Trimestre | M28: 1º Trimestre | N28: 2º Trimestre | O28: 3º Trimestre | P28: 4º Trimestre
E29: 2018 | F29: 211738.26 | G29: 245084.87 | H29: 251980.41 | I29: 251919.87 | L29: 2018 | M29: =F29/SUM($F29:$I29) -> 0.22039461 | N29: =G29/SUM($F29:$I29) -> 0.25510451 | O29: =H29/SUM($F29:$I29) -> 0.26228195 | P29: =I29/SUM($F29:$I29) -> 0.26221893
E30: 2019 | F30: 267737.72 | G30: 308979.8 | H30: 285057.99 | I30: 337389.34 | L30: 2019 | M30: =F30/SUM($F30:$I30) -> 0.22327015 | N30: =G30/SUM($F30:$I30) -> 0.25766249 | O30: =H30/SUM($F30:$I30) -> 0.23771376 | P30: =I30/SUM($F30:$I30) -> 0.2813536
E31: 2020 | F31: 286003.68 | G31: 187163 | H31: 297260.56 | I31: 425874.95 | L31: 2020 | M31: =F31/SUM($F31:$I31) -> 0.2390731 | N31: =G31/SUM($F31:$I31) -> 0.15645127 | O31: =H31/SUM($F31:$I31) -> 0.24848283 | P31: =I31/SUM($F31:$I31) -> 0.35599279
E32: 2021 | F32: 516655.02 | G32: 723575.59 | H32: 889681.74 | I32: 1000638.6 | L32: 2021 | M32: =F32/SUM($F32:$I32) -> 0.16503645 | N32: =G32/SUM($F32:$I32) -> 0.23113362 | O32: =H32/SUM($F32:$I32) -> 0.28419334 | P32: =I32/SUM($F32:$I32) -> 0.31963659
E33: 2022 | F33: =1135.551*1000 -> 1135551 | G33: =1286.7492*1000 -> 1286749.2 | H33: =1428.00600045888*1000 -> 1428006 | I33: =1266.51107638132*1000 -> 1266511.1 | L33: 2022 | M33: =F33/SUM($F33:$I33) -> 0.22192526 | N33: =G33/SUM($F33:$I33) -> 0.25147453 | O33: =H33/SUM($F33:$I33) -> 0.27908091 | P33: =I33/SUM($F33:$I33) -> 0.24751931

Sheet Processos
M1: Remota | N1: Tributário
M2: Possível | N2: Cível
F3: =Dashboard!H3 -> SIMPAR (SIMH3) | M3: Provável | N3: Trabalhista
N4: Administrativo
A7: Páginas
A8: Dashboard
A9: WACC
A10: DRE Consolidado | F10: Numero de Processos em Unidades | G10: Valor das Provisões | H10: Valor de Perdas Possiveis | I10: Valor de Perdas Remotas
A11: DRE + DCF | E11: Tributários | F11: 541 | G11: 0 | H11: 138400
A12: DRE - Contas Abertas | E12: Cíveis | F12: 4930 | G12: 18700 | H12: 116900
A13: Balanço Patrimonial | E13: Trabalhistas | F13: 3259 | G13: 156100 | H13: 141200
A14: Painel de Índices
A15: Projeções - Receita e EBIT
A16: Projeções - CG + Capex
A17: Projeções 2023
A18: Processos | E18: Número | F18: Descrição | G18: Valor do Processo | H18: Chance de Perda | I18: Comentário
E19: 0427983-81.2012.8.19.0001 | F19: O Ministério Público do Estado do Rio de Janeiro ajuizou três ações civis públicas discutindo a aquisição de veículos pela Polícia do Rio de Janeiro com gestão e manutenção de frota (processo 0152872-07.2014.8.19.0001, da 7ª Vara da Fazenda Pública do Rio de Janeiro; processo 0145782-45.2014.8.19.0001, da 13ª Vara da Fazenda Pública do Rio de Janeiro; e processo 0167693-16.2014.8.19.0001, da 9ª Vara da Fazenda Pública do Rio de Janeiro). Sobre o mesmo assunto, foram propostas quatro ações populares pelo Sr. Carlos Fernando dos Santos Azeredo (Processos: 0242335-28.2012.8.19.0001; 0043810-66.2013.8.19.0001; 0427983-81.2012.8.19.0001 e 0136630-70.2014.8.19.0001), as quais foram apensadas para julgamento em conjunto com as ações civis públicas acima referidas. Em todos os casos, a Companhia ratifica que cumpriu todas as suas obrigações contratuais. | G19: 85216 | H19: Remota
E20: 0152872-07.2014.8.19.0001 | F20: Ação Civil Pública proposta pelo MP, sendo um dos processos apensos ao processo explicado anteiormente. | G20: 134801 | H20: Remota
E21: 0167693-16.2014.8.19.0001 | F21: Ação Popular, sendo um dos processos apensos ao processo explicado anteiormente. | G21: 597401 | H21: Remota
E22: 0136630-70.2014.8.19.0001 | F22: Ação Civil Pública, sendo um dos processos apensos ao processo explicado anteiormente. | G22: 195085 | H22: Possível | I22: Consequências: Desembolso de caixa e suspensão/invalidação dos contratos discutidos.
E23: 0315594-41.2015.8.05.0001 | F23: Trata-se de ação civil pública proposta pelo Ministério Público do Estado da Bahia para discutir suposto ato de improbidade administrativa praticado pela Companhia e outras 27 pessoas, referente a um processo licitatório. O MP, em linhas gerais, alega a existência de uma organização de pessoas que agiram para fraudar diversas licitações relacionadas à Polícia Militar do Estado da Bahia, em benefício de empresas participantes. A Companhia foi mencionada em uma única licitação por ela vencida, referente a um contrato de venda de frota para a Polícia Militar do Estado da Bahia, com o fornecimento e manutenção, por 30 meses, de um total de 191 viaturas (“Contrato”). | G23: 4023 | H23: Possível | I23: Consequências: Desembolso de caixa, suspensão/invalidação do contrato discutido, restrições ao exercício de atividades e/ou recebimento de benefícios junto ao Poder Público.
E24: 0000225-70.2009.8.26.0045 | F24: Trata-se de ação civil pública, na qual se discute o preço do contrato de prestação de serviços de coleta e transporte de resíduos sólidos firmado pela Companhia com o Município de Arujá- SP, alegando que seria superior aos preços praticados por outros Municípios na mesma região | G24: 24193 | H24: Possível | I24: A JSL alega que o MP não considerou as diferenças de prestação de serviços em cada município. O processo encontra-se em primeira instância, sem sentença, ainda.
E25: 0009283-48.2007.8.26.0278 | F25: Trata-se de Ação Popular que tem por objeto o Contrato Emergencial n.º 160/0-A, mantido entre a JSL e a Prefeitura Municipal de Itaquaquecetuba, cujo objeto é a locação de veículos leves e caminhões sem motorista, com manutenção de frota e outras avenças. O Autor questiona a dispensa de licitação e critica a modalidade da contratação realizada pela Administração Pública, sustentando que a locação de veículos seria mais onerosa aos cofres públicos do que a sua aquisição. | G25: 1869 | H25: Provável | I25: O processo já teve decisão do STJ e determinou um ressarcimento parcial aos cofres públicos, cuja estimativa de perda é essa de R$ 1.869.
E26: 0039632-44.2010.8.26.0564 | F26: Trata-se de execução por quantia certa, com base em 40 (quarenta) contratos de mútuos no valor originário total de R$ 7.080.915,00, celebrados entre, de um lado e na condição de mutuante, a empresa Selpa, e do outro lado e na condição de mutuaria, a Transportadora Grande ABC Ltda., incorporada pela JSL em 29 de dezembro de 2011. Tais contratos teriam sido celebrados entre 2005 e 2006, antes da aquisição da Transportadora Grande ABC Ltda. pela Companhia. | G26: 46698 | H26: Remota
E27: 0015304-72.2013.8.26.0361 | F27: Trata-se de Ação Civil Pública que discute o contrato de concessão dos serviços de transporte público coletivo urbano de Mogi das Cruzes. O Ministério Público (“MP”) ajuizou Ação de Responsabilidade Civil por Ato de Improbidade Administrativa com base em gravação de conversa mantida unicamente entre representantes da empresa Eroles, que na ocasião explorava os serviços de transporte público coletivo de Mogi das Cruzes a título de permissão, com o então prefeito municipal. Nesta conversa, supostamente teria sido prometido pagamento de quantia ao então prefeito em troca de favorecimento das empresas Júlio Simões Transportes e Serviços Ltda. | G27: 3000 | H27: Possível | I27: Consequências: Desembolso de caixa, suspensão/invalidação dos contratos discutidos, restrições ao exercício de atividades e/ou recebimento de benefícios junto ao Poder Público.
E28: 0010938-33.2016.4.01.3200 | F28: O Ministério Público Federal (“MPF”) ajuizou seis ações civis públicas por improbidade administrativa decorrente de fatos ocorridos em período anterior à compra da Quick Logística Ltda. pela JSL S.A., movidas contra agentes públicos, despachantes e sociedades empresárias – entre as quais a Quick -, que supostamente estariam envolvidos em um esquema de pagamento indevido de valores para vistoriadores da SUFRAMA para facilitação de ingresso de mercadorias na Zona Franca de Manaus, (processo 10938-33.2016.4.01.3200, processo 10959-09.2016.4.01.3200, processo 11391- 28.2016.4.01.3200, processo 10960-91.2016.4.01.3200, processo 11345-39.2016.4.01.3200 e processo 10939-18.2016.4.01.3200, todos em trâmite na 3ª Vara Federal da Seção Judiciária do Estado do Amazonas). | G28: 1600 | H28: Possível | I28: MPF e a Quick celebraram acordo de não persecução cível para o encerramento das referidas ações, o qual será submetido à homologação judicial nos respectivos processos.
E29: 0011391-28.2016.4.01.3200 | F29: Um dos processos apensos ao anterior | G29: 3200 | H29: Possível
E30: 0010939-18.2016.4.01.3200 | F30: Um dos processos apensos ao anterior | G30: 1200 | H30: Possível
E31: 0010960-91.2016.4.01.3200 | F31: Um dos processos apensos ao anterior | G31: 2000 | H31: Possível
E32: 0011345-39.2016.4.01.3200 | F32: Um dos processos apensos ao anterior | G32: 400 | H32: Possível
E33: 0010959-09.2016.4.01.3200 | F33: Um dos processos apensos ao anterior | G33: 1800 | H33: Possível
E34: 0206683-08.2016.8.19.0001 | F34: O Ministério Público do Estado do Rio de Janeiro propôs Ação Civil Pública questionando supostas irregularidades relacionadas aos contratos administrativos nos 034/2007, 035/2007, 036/2007 e 037/2007, firmados após regular processo licitatório (Pregão Presencial nº 04/2007), entre o Município do Rio de Janeiro e as empresas Viação Saens Peña S.A, Consórcio Trespan Rio, Breda Transportes e Turismo Rio – EIRELI e Júlio Simões Transportes e Serviços Ltda. (atual JSL), cujo objeto é a prestação de serviços de transportes, com o fornecimento de veículos e mão-de-obra operacional, para o evento esportivo internacional dos Jogos Pan-americanos e Parapan-americanos, sediados na cidade do Rio de Janeiro em 2007, sendo pleiteado em face da JSL S.A. a condenação na devolução aos cofres públicos da quantia de R$ 6.582.655,87, em razão de alegado sobrepreço e inadimplemento parcial do contrato. | G34: 9966 | H34: Possível
E35: 1007206-52.2021.4.01.3814 | F35: Trata-se de Ação Civil Pública ajuizada pelo Ministério Público Federal (“MPF”) em face da Companhia, por suposto excesso de peso em seus veículos de transporte de carga (ou de seus contratados), quando trafegavam em rodovias federais. | G35: 100 | H35: Possível
E36: 0546979-57.2014.8.05.0001 | F36: Trata-se de ação civil pública ajuizada pelo Ministério Público do Estado da Bahia, na qual alega irregularidades no edital de licitação do Pregão Presencial nº 076/2014 – que resultou na celebração do Contrato SEMGE nº 056/2014, em virtude de exigências e restrições que alega serem excessivas e indevidas, bem como em razão do suposto caráter genérico do Termo de Referência, que indicava apenas o valor global de cada Secretaria, sem qualquer detalhamento de custos unitários, além de alegar discrepâncias de valores em relação a Contrato anterior, sugerindo sobrepreço. | G36: 154000 | H36: Remota | I36: Em defesa, a Pronto Express demonstrou a diferença de objeto e escopo entre os contratos comparados pelo Ministério Público, evidenciando a regularidade da contratação e o atendimento de requisitos legais pela Contratada. O processo se encontra na fase inicial, de modo que não houve prolação de sentença.
E37: 0005434-42.2009.8.26.0361 | F37: Trata-se de ação penal, movida contra o Diretor Presidente da controladora da Companhia, Sr. Fernando Antonio Simões e dos Srs. Antonio Alexandre Eroles, Antonio Adriano Eroles e José Carlos Pavanelli pelos mesmos fatos discutidos na ação civil pública processo nº 0015304-72.2013.8.26.0361, reportada abaixo. A denúncia foi recebida em 29 de novembro de 2013. O Sr. Fernando Antonio Simões apresentou resposta prévia à denúncia, rejeitando todas as alegações e acusações apresentadas contra si pelo Ministério Público e requerendo sua absolvição sumária uma vez que jamais participou de qualquer suposto acordo ilícito e pelos demais argumentos descritos no item 4.3 acima mencionado. Em audiência de instrução, o corréu Antonio Alexandre Eroles, em seu interrogatório perante o juízo, negou a participação do Sr. Fernando Antonio Simões em qualquer ato ilícito, desmentindo falsa afirmação anteriormente feita em relação ao mesmo e que deu origem à sua indevida inclusão em ambas as ações. A Ação Penal foi julgada improcedente em primeira instância e o Tribunal de Justiça do Estado de São Paulo, em julgamento realizado no dia 22/10/2020, manteve a improcedência. | G37: 0 | H37: Possível | I37: As principais consequência de uma condenação aqui são: Condenação criminal dos réus e restrição à administração de empresas.
E38: 0000080-25-2015-5-18-0191 | F38: Ação Civil Pública, requerendo a antecipação de tutela e a condenação da JSL às seguintes obrigações: (a) consignar em registro mecânico, manual ou sistema eletrônico os horários de entrada, saída e período de repouso efetivamente praticados pelo empregado; (b) respeitar a jornada legal de trabalho pactuada com os seus empregados, observado o limite legal; (c) respeitar o limite de prorrogação legal de 02 horas diárias; (d) remunerar as horas extras com 50%, quando não houver compensação; (e) conceder o descanso semanal remunerado conforme escala de revezamento; (f) compensar ou remunerar em dobro as horas trabalhadas em domingos e feriados; (g) arbitramento de multa de R$ 10.000,00, por dia, para a hipótese de descumprimento; (h) indenização por dano moral coletivo no valor de R$ 2.000.000,00. | G38: 123 | H38: Provável
E39: 10003410220175020044 | F39: Ação anulatória, para anular autos de infração lavrados em decorrência de suposta terceirização ilícita. | G39: 100 | H39: Possível | I39: O processo já teve sentença procedente. Está pendente de julgamento de recurso interposto pela União.
E40: 10005763020195020001 | F40: Idem ao anterior | G40: 500 | H40: Possível | I40: O processo já teve sentença procedente. Está pendente de julgamento de recurso interposto pela União.
E41: 0100759-80.2018.5.01.0262 | F41: Trata-se de ação civil pública ajuizada pelo Ministério Público do Trabalho visando: (i) declarar inconstitucional o artigo 235-C, caput da CLT, impedindo a prorrogação da jornada diária de trabalho dos motoristas da Companhia além do limite de 2 horas, sem justificativa legal; (ii) reconhecer a não concessão dos intervalos intrajornada e interjornada, e do descanso semanal remunerado; e (iii) ondenação ao pagamento de dano moral coletivo | G41: 500 | H41: Provável
E42: 0010963-36.2021.5.15.0116 | F42: A presente ação visa a condenação da Companhia ao cumprimento de obrigação de fazer consistente em manter o percentual de empregados previsto no artigo 93 da Lei n.º 8.213/1991, com beneficiários reabilitados ou pessoas portadoras de deficiência, considerando para o cálculo do percentual a somatória de todos os trabalhadores de todos os estabelecimentos da Ré. | G42: 1000 | H42: Possível
E43: 10932.000003/2008-41 | F43: Auto de infração que impõe multa isolada à Transportadora Grande ABC Ltda (empresa esta incorporada pela JSL S.A.) por alegada realização de compensações de débitos de COFINS (de Janeiro a Setembro de 2002 e de Janeiro de 2003 a Dezembro de 2005) e de PIS (de Abril de 2003 a Dezembro de 2005), nos meses de outubro e novembro de 2005 e junho de 2006 de forma indevida, utilizando-se de créditos de terceiros para tanto. | G43: 6454 | H43: Possível
E44: 10.803.720003/2013-02 | F44: Auto de infração lavrado (processo administrativo fiscal nº 10.803.720003/2013-02), com a constituição de créditos tributários no valor total de R$ 68.104.480,07 (sessenta e oito milhões, cento e quatro mil, quatrocentos e oitenta reais e sete centavos), incluindo Imposto de Renda Pessoa Jurídica – IRPJ, Contribuição Social sobre o Lucro Líquido – CSLL, contribuição ao PIS e COFINS. | G44: 109631 | H44: Remota
E45: 10.803.720334/2013-34 | F45: Autos de infração lavrados (processo administrativo fiscal nº 10.803.720334/2013-34), com a constituição de créditos tributários no valor total de R$ 71.197.415,46 (setenta e um milhões, cento e noventa e sete mil, quatrocentos e quinze reais e quarenta e seis centavos), incluindo Imposto de Renda Pessoa Jurídica – IRPJ, Contribuição Social sobre o Lucro Líquido – CSLL, contribuição ao PIS e COFINS | G45: 112760 | H45: Possível
E46: 19515.720.098/2018-81 | F46: Trata-se de autos de infração lavrados contra a Companhia , relativos ao exercício de 2013, com a constituição de créditos de contribuição ao PIS e de COFINS.Em apertada síntese, a fiscalização, a partir das declarações apresentadas pela JSL à Receita Federal do Brasil e da documentação contida no procedimento administrativo, refez a apuração da contribuição ao PIS e da COFINS da referida companhia no exercício de 2013, tendo sido apontadas supostas inconsistências. | G46: 12119 | H46: Possível
E47: 4.117.807-5 | F47: Trata-se de Auto de Infração por meio do qual foram constituídos em face da JSL supostos créditos tributários de ICMS, sob alegação de creditamento indevido do ICMS incidente na aquisição de bens destinados ao ativo imobilizado (caminhões e semirreboques) que teriam sido dados em locação a terceiros. | G47: 12016 | H47: Possível
E48: 4.121.117-0 | F48: Idem ao anterior | G48: 29652 | H48: Possível
E49: 4.060.192-4 | F49: Idem ao anterior | G49: 9259 | H49: Possível
E50: 2.081.717-0 | F50: Auto de Infração, com imposição de crédito de ICMS + multa em decorrência do suposto não pagamento do tributo em razão do diferencial de alíquotas, nas aquisições de máquinas, equipamentos e veículos leves; | G50: 14043 | H50: Remota
E51: 003603646.2013.4.03.6182 | F51: Cobrança de supostos débitos de COFINS devidos pela empresa (inscrição em dívida ativa nº 80613015708-20). | G51: 19986 | H51: Possível
E52: 4.011.801.72704-6 | F52: Trata-se de auto de infração lavrado por suposta omissão de recolhimento de ICMS, em decorrência da utilização irregular do benefício do LOGPRODUZIR, benefício fiscal concedido pelo Estado de Goiás que consiste na concessão de crédito outorgado do ICMS, incidente sobre as prestações interestaduais de transporte realizadas pela empresa operadora de logística. Processo aguarda julgamento em segunda instância. | G52: 11901 | H52: Possível
... E57: 000595.2017 | F57: Idem ao anterior | G57: 19763 | H57: Remota
E58: 5056523-69.2017.8.09.0051 | F58: Ação Civil Pública. Inobservância ao Estatuto da Pessoa com Deficiência pelo fato de não disponibilizar em sua frota a cota mínima de carros adaptados. | G58: 100 | H58: Possível | I58: A ação envolve norma que precisa de regulamentação, ainda. A defesa da empresa se sustenta nessa ausencia de regulamentação
E59: 0005434-42.2009.8.26.0361 | F59: Trata-se de ação penal, movida contra o Diretor Presidente da controladora da Companhia, Sr. Fernando Antonio Simões e dos Srs. Antonio Alexandre Eroles, Antonio Adriano Eroles e José Carlos Pavanelli pelos mesmos fatos discutidos na ação civil pública processo nº 0015304-72.2013.8.26.0361, reportada abaixo. A denúncia foi recebida em 29 de novembro de 2013. O Sr. Fernando Antonio Simões apresentou resposta prévia à denúncia, rejeitando todas as alegações e acusações apresentadas contra si pelo Ministério Público e requerendo sua absolvição sumária uma vez que jamais participou de qualquer suposto acordo ilícito e pelos demais argumentos descritos no item 4.3 acima mencionado. Em audiência de instrução, o corréu Antonio Alexandre Eroles, em seu interrogatório perante o juízo, negou a participação do Sr. Fernando Antonio Simões em qualquer ato ilícito, desmentindo falsa afirmação anteriormente feita em relação ao mesmo e que deu origem à sua indevida inclusão em ambas as ações. A Ação Penal foi julgada improcedente em primeira instância e o Tribunal de Justiça do Estado de São Paulo, em julgamento realizado no dia 22/10/2020, manteve a improcedência. | G59: 0 | H59: Possível | I59: As principais consequência de uma condenação aqui são: Condenação criminal dos réus e restrição à administração de empresas.
E60: 0136630-70.2014.8.19.0001 | F60: O Ministério Público do Estado do Rio de Janeiro ajuizou três ações civis públicas discutindo a aquisição de veículos pela Polícia do Rio de Janeiro com gestão e manutenção de frota (processo 0152872-07.2014.8.19.0001, da 7ª Vara da Fazenda Pública do Rio de Janeiro; processo 0145782-45.2014.8.19.0001, da 13ª Vara da Fazenda Pública do Rio de Janeiro; e processo 0167693-16.2014.8.19.0001, da 9ª Vara da Fazenda Pública do Rio de Janeiro). Sobre o mesmo assunto, foram propostas quatro ações populares pelo Sr. Carlos Fernando dos Santos Azeredo (Processos: 0242335-28.2012.8.19.0001; 0043810-66.2013.8.19.0001; 0427983-81.2012.8.19.0001 e 0136630-70.2014.8.19.0001), as quais foram apensadas para julgamento em conjunto com as ações civis públicas acima referidas. Em todos os casos, a Companhia ratifica que cumpriu todas as suas obrigações contratuais. | G60: 195085 | H60: Possível | I60: Consequências: Desembolso de caixa e suspensão/invalidação dos contratos discutidos.
E61: 0315594-41.2015.8.05.0001 | F61: Trata-se de ação civil pública proposta pelo Ministério Público do Estado da Bahia para discutir suposto ato de improbidade administrativa praticado pela Companhia e outras 27 pessoas, referente a um processo licitatório. O MP, em linhas gerais, alega a existência de uma organização de pessoas que agiram para fraudar diversas licitações relacionadas à Polícia Militar do Estado da Bahia, em benefício de empresas participantes. A Companhia foi mencionada em uma única licitação por ela vencida, referente a um contrato de venda de frota para a Polícia Militar do Estado da Bahia, com o fornecimento e manutenção, por 30 meses, de um total de 191 viaturas (“Contrato”). | G61: 4023 | H61: Possível | I61: Consequências: Desembolso de caixa, suspensão/invalidação do contrato discutido, restrições ao exercício de atividades e/ou recebimento de benefícios junto ao Poder Público.
E62: 0015304-72.2013.8.26.0361 | F62: Trata-se de Ação Civil Pública que discute o contrato de concessão dos serviços de transporte público coletivo urbano de Mogi das Cruzes. O Ministério Público (“MP”) ajuizou Ação de Responsabilidade Civil por Ato de Improbidade Administrativa com base em gravação de conversa mantida unicamente entre representantes da empresa Eroles, que na ocasião explorava os serviços de transporte público coletivo de Mogi das Cruzes a título de permissão, com o então prefeito municipal. Nesta conversa, supostamente teria sido prometido pagamento de quantia ao então prefeito em troca de favorecimento das empresas Júlio Simões Transportes e Serviços Ltda. | G62: 3000 | H62: Possível | I62: Consequências: Desembolso de caixa, suspensão/invalidação dos contratos discutidos, restrições ao exercício de atividades e/ou recebimento de benefícios junto ao Poder Público.
E63: 0242335-28.2012.8.19.0001 | F63: O Ministério Público do Estado do Rio de Janeiro ajuizou três ações civis públicas discutindo a aquisição conforme já relatado no processo da primeira linha. | G63: 134643 | H63: Remota | I63: Consequências: Desembolso de caixa, suspensão/invalidação dos contratos discutidos, restrições ao exercício de atividades e/ou recebimento de benefícios junto ao Poder Público.
E64: 0145782-45.2014.8.19.0001 | F64: O Ministério Público do Estado do Rio de Janeiro ajuizou três ações civis públicas discutindo a aquisição conforme já relatado no processo da primeira linha. | G64: 134643 | H64: Remota | I64: Consequências: Desembolso de caixa, suspensão/invalidação dos contratos discutidos, restrições ao exercício de atividades e/ou recebimento de benefícios junto ao Poder Público.
E65: 0043810-66.2013.8.19.0001 | F65: O Ministério Público do Estado do Rio de Janeiro ajuizou três ações civis públicas discutindo a aquisição conforme já relatado no processo da primeira linha. Essa é uma das ações popuplares | G65: 257749 | H65: Remota
E66: 0034695-44.2013.8.26.0577 | F66: Trata-se de Ação Popular tendo por objeto discussão a respeito do reajuste tarifário aplicado nos contratos de transporte coletivo urbano do Município de São Jose dos Campos | G66: 5 | H66: Possível
E67: 1001512-60.2016.8.26.0577 | F67: Trata-se de Ação Popular que tem por objeto discussão de reajuste tarifário no serviço de transporte coletivo no Município de São José dos Campos | G67: 25 | H67: Possível
E68: 1000098-27.2016.8.26.0577 | F68: Trata-se de Ação Popular objetivando a anulação do ato (Lei Complementar Municipal nº. 536, de 28 de abril de 2014), que concedeu isenção temporária de ISSQN às empresas que operam o serviço de transporte coletivo na cidade, bem como a condenação dos Réus a restituir aos cofres públicos os valores não arrecadados no período, estimados em R$ 15.000.000,00. | G68: 50 | H68: Remota
E69: 0179606-92.2014.8.19.0001 | F69: Trata-se de Ação Popular que questiona três processos licitatórios para locação de veículos e equipamentos para limpeza urbana realizados pela Comlurb sob os nºs. 698/2013, 073/2014 e 074/2014 | G69: 30 | H69: Possível
E70: 0804667-19.2018.4.05.8300 | F70: A Yolanda Logística sagrou-se vencedora em procedimento licitatório, tendo então celebrado, em 25.5.98, contrato de permissão para exploração de serviços públicos de movimentação e armazenagem de cargas em terminal alfandegado, regulado pela Lei nº 9.074/95 e pelo Decreto nº 1.910/96, que estabeleciam o prazo máximo de 10 (dez) anos para a delegação. Ocorre que, em 30.5.03, sobreveio a Lei Federal nº 10.684/03, que introduziu dois novos parágrafos no artigo 1º da Lei nº 9.074/95, os quais determinavam que “o prazo das concessões e permissões de que se trata o inciso VI deste artigo será de vinte e cinco anos, podendo ser prorrogados por dez anos” e que “ao término do prazo, as atuais concessões e permissões, mencionadas no § 2º, incluídas as anteriores à Lei n. 8.987, de 13 de fevereiro de 1995, seriam prorrogadas pelo prazo previsto no § 2º”. | G70: 10 | H70: Possível
E71: 1015595-42.2019.8.26.0071 | F71: Inobservância ao Estatuto da Pessoa com Deficiênc | G71: 1 | H71: Provável
E72: 0009137-51.2011.4.02.5101 | F72: Trata-se de ação civil pública movida por Universidade Federal Rural do Rio de Janeiro em face de Ciclus Ambiental do Brasil S.A, Município do Rio de Janeiro, Município de Seropédica e Instituto Estadual do Ambiente – INEA. Pleiteia a autora seja declarada a nulidade do licenciamento ambiental concedido pelo INEA à Central de Tratamento de Resíduos Sólidos Santa Rosa (“CTR Santa Rosa”), localizado no Município de Seropédica, condenando os réus à paralisação definitiva das atividades da CTR, com transferência para áreas adequadas, bem como retirada de todo e qualquer resíduo no local, às expensas das rés. O principal fundamento utilizado é no sentido de que o empreendimento causará danos ao ecossistema daquela região, e que no procedimento de expedição da licença teriam supostas irregularidades. | G72: 100 | H72: Remota | I72: Se a Simpar perder esse processo, a Ciclus poderá ter que parar de operar.
E73: 0190756-70.2014.8.19.0001 | F73: Trata-se de processo relativo à regularidade ambiental da Estação de Transferência de Resíduos (ETR) de Santa Cruz, oriundos da cidade do Rio de Janeiro e destinados ao Aterro Sanitário de Seropédica (CTR RIO), relativos a apuração de supostas irregularidades ambientais ocorridas no licenciamento, instalação e na operação da ETR Santa Cruz. | G73: 72 | H73: Possível | I73: Não há impacto direto a Companhia, em caso de perda, afetará somente a logística da disposição dos resíduos que deverá ser transferida para outro local.
E74: 0047867-20.2019.8.19.0001 | F74: Trata-se de potencial suspensão de todas as atividades que envolvam recebimento, armazenamento e transferência de resíduos na Estação de Transferência de Resíduos (ETR) de Jacarepaguá, instalada supostamente em caráter de ilegalidade, até que seja obtida licença ambiental de operação válida e atendidas todas as suas condicionantes, precedida de processo de licenciamento ambiental, no qual seja elaborado EIA/RIMA e realizada audiência pública pelo órgão ambiental competente | G74: 541 | H74: Possível | I74: Não há impacto
E75: 627262/2018 | F75: No ano de 2017 a CS Brasil foi surpreendida por uma decisão proferida em recurso administrativo interposto no Pregão Eletrônico n.º 019/2015, onde a empresa foi desclassificada por apresentar certidão negativa de débitos que não correspondia à certidão original emitida pelo Posto Fiscal da SEFAZ na cidade de Mogi das Cruzes. Após rápida apuração interna, a CS Brasil constatou que um de seus funcionários à época havia alterado o conteúdo da referida certidão através de montagem em máquina fotocopiadora (apesar da empresa dispor à época de outra certidão que lhe dava plenas condições de participar da referida licitação). O empregado autor do fato foi prontamente despedido por justa causa e a CS Brasil levou o caso ao conhecimento das autoridades competentes, pedindo, inclusive, a instauração de inquérito policial junto à 2º Delegacia de Polícia de Mogi das Cruzes. Após confessar sua conduta e afirmar que agiu por conta própria e por mero comodismo, o referido funcionário foi denunciado em ação penal e condenado pelo Tribunal de Justiça do Estado de São Paulo. | H75: Possível | I75: Entendemos que não se trata de hipótese de aplicação de qualquer penalidade à CS Brasil, que é vítima dos fatos acima mencionados, porém, na remota hipótese de ser aplicada qualquer penalidade à empresa, caberá recurso ainda no âmbito administrativo
E76: 396/2020 | F76: Após sagrar-se vencedora do Pregão Eletrônico nº 81/2020 por ter apresentado a proposta com o menor preço, a CS Frotas firmou o Contrato nº 396/2020 com a Alesp, cujo objeto é o fornecimento de 94 (noventa e quatro) veículos para locação pelo período de 12 (doze) meses. Na mesma data, a Alesp emitiu a ordem de serviço para entrega dos veículos no prazo de 30 (trinta) dias. Imediatamente, a CS Frotas cotou com diversas montadoras a aquisição dos veículos. Contudo, em razão do impacto da pandemia na indústria automobilística e que perdura até hoje, as montadoras informaram que não poderiam fornecer os veículos até a data aprazada pela Alesp. Por essa razão, a CS Frotas solicitou a prorrogação do prazo de entrega apresentando cronograma com as datas (05/02/2021 e 05/03/2021). Não obstante os argumentos da CS Frotas, a Alesp negou o requerimento de prorrogação do prazo de entrega e rescindiu o contrato. A CS Frotas apresentou defesa demonstrando que o atraso na entrega não caracterizaria inadimplemento contratual e, muito menos, que a rescisão contratual era a medida mais condizente ao interesse público. Contudo, a Mesa Diretora da Alesp aplicou as seguintes penalidades: i) rescisão contratual; ii) multa correspondente a 30% do valor do contrato e iii) proibição de contratar com a Administração Pública pelo prazo de 2 (dois) anos. | G76: 857 | H76: Possível
E77: 0100759-80.2018.5.01.0262 | F77: Trata-se de ação civil pública ajuizada pelo Ministério Público do Trabalho visando: (i) declarar inconstitucional o artigo 235-C, caput da CLT, impedindo a prorrogação da jornada diária de trabalho dos motoristas da Companhia além do limite de 2 horas, sem justificativa legal; (ii) reconhecer a não concessão dos intervalos intrajornada e interjornada, e do descanso semanal remunerado; e (iii) condenação ao pagamento de dano moral coletivo. | G77: 500 | H77: Provável
E78: 15.746-720.226/2020-36 | F78: O Agente Fiscal glosou os créditos a título de contribuição ao PIS e COFINS descontados pela JSL amparado em 2 (duas) premissas: (i) os serviços prestados à JSL teriam sido realizados por pessoas físicas e, ainda, (ii) os serviços prestados não se enquadrariam no conceito de “insumo”, com base na interpretação do Parecer Normativo COSIT/RFB nº 05/2018. | G78: 28098 | H78: Possível
E79: 03.620796-7 | F79: Auto de infração lavrado contra a CS BRASIL, por meio do qual foi constituído crédito tributário de ICMS referente ao período de janeiro de 2016, sob o entendimento equivocado de que a CS BRASIL não faria jus ao crédito de ICMS acumulado no período autuado, na medida em que não teriam sido localizadas operações de exportação ou quaisquer tipos de saídas isentas ou não tributadas, no período de 2010 a 2016, que a autorizasse a manter créditos referentes a aquisição de mercadorias para a venda através de saída não tributadas, infringido os artigos 2º, 3º, 33, 34, 35 e 39 da Lei nº 2657/1996. | G79: 72335 | H79: Remota
