Workbook

Sheet Dashboard
H3: SIMPAR (SIMH3)
A7: Páginas
A8: Dashboard
A9: WACC | E9: Ticker | F9: SIMH3 | G9: WACC | H9: =H10-0.5% -> 0.090330137 | I9: =(((NPV($H9,'DRE + DCF'!$V$36,'DRE + DCF'!$X$36:$AA$36)*((1+$H9)^((12-3)/12))+('DRE + DCF'!$AB$36*(1+I$18)/(($H9-I$18)*(1+$H9)^(COUNT('DRE + DCF'!$W$22:$AA$22)-((12-3)/12)))))+SUM($F$12:$F$17)))/$F$10-(((NPV($H9,'DRE + DCF'!$V$36,'DRE + DCF'!$X$36:$AA$36)*((1+$H9)^((12-3)/12))+('DRE + DCF'!$AB$36*(1+I$18)/(($H9-I$18)*(1+$H9)^(COUNT('DRE + DCF'!$W$22:$AA$22)-((12-3)/12)))))*$F$40+$F$42)*(1-$F$39))/$F$10 -> 14.189123 | J9: =(((NPV($H9,'DRE + DCF'!$V$36,'DRE + DCF'!$X$36:$AA$36)*((1+$H9)^((12-3)/12))+('DRE + DCF'!$AB$36*(1+J$18)/(($H9-J$18)*(1+$H9)^(COUNT('DRE + DCF'!$W$22:$AA$22)-((12-3)/12)))))+SUM($F$12:$F$17)))/$F$10-(((NPV($H9,'DRE + DCF'!$V$36,'DRE + DCF'!$X$36:$AA$36)*((1+$H9)^((12-3)/12))+('DRE + DCF'!$AB$36*(1+J$18)/(($H9-J$18)*(1+$H9)^(COUNT('DRE + DCF'!$W$22:$AA$22)-((12-3)/12)))))*$F$40+$F$42)*(1-$F$39))/$F$10 -> 15.347343 | K9: =(((NPV($H9,'DRE + DCF'!$V$36,'DRE + DCF'!$X$36:$AA$36)*((1+$H9)^((12-3)/12))+('DRE + DCF'!$AB$36*(1+K$18)/(($H9-K$18)*(1+$H9)^(COUNT('DRE + DCF'!$W$22:$AA$22)-((12-3)/12)))))+SUM($F$12:$F$17)))/$F$10-(((NPV($H9,'DRE + DCF'!$V$36,'DRE + DCF'!$X$36:$AA$36)*((1+$H9)^((12-3)/12))+('DRE + DCF'!$AB$36*(1+K$18)/(($H9-K$18)*(1+$H9)^(COUNT('DRE + DCF'!$W$22:$AA$22)-((12-3)/12)))))*$F$40+$F$42)*(1-$F$39))/$F$10 -> 16.743585 | L9: =(((NPV($H9,'DRE + DCF'!$V$36,'DRE + DCF'!$X$36:$AA$36)*((1+$H9)^((12-3)/12))+('DRE + DCF'!$AB$36*(1+L$18)/(($H9-L$18)*(1+$H9)^(COUNT('DRE + DCF'!$W$22:$AA$22)-((12-3)/12)))))+SUM($F$12:$F$17)))/$F$10-(((NPV($H9,'DRE + DCF'!$V$36,'DRE + DCF'!$X$36:$AA$36)*((1+$H9)^((12-3)/12))+('DRE + DCF'!$AB$36*(1+L$18)/(($H9-L$18)*(1+$H9)^(COUNT('DRE + DCF'!$W$22:$AA$22)-((12-3)/12)))))*$F$40+$F$42)*(1-$F$39))/$F$10 -> 18.459623 | M9: =(((NPV($H9,'DRE + DCF'!$V$36,'DRE + DCF'!$X$36:$AA$36)*((1+$H9)^((12-3)/12))+('DRE + DCF'!$AB$36*(1+M$18)/(($H9-M$18)*(1+$H9)^(COUNT('DRE + DCF'!$W$22:$AA$22)-((12-3)/12)))))+SUM($F$12:$F$17)))/$F$10-(((NPV($H9,'DRE + DCF'!$V$36,'DRE + DCF'!$X$36:$AA$36)*((1+$H9)^((12-3)/12))+('DRE + DCF'!$AB$36*(1+M$18)/(($H9-M$18)*(1+$H9)^(COUNT('DRE + DCF'!$W$22:$AA$22)-((12-3)/12)))))*$F$40+$F$42)*(1-$F$39))/$F$10 -> 20.619537 | N9: =(((NPV($H9,'DRE + DCF'!$V$36,'DRE + DCF'!$X$36:$AA$36)*((1+$H9)^((12-3)/12))+('DRE + DCF'!$AB$36*(1+N$18)/(($H9-N$18)*(1+$H9)^(COUNT('DRE + DCF'!$W$22:$AA$22)-((12-3)/12)))))+SUM($F$12:$F$17)))/$F$10-(((NPV($H9,'DRE + DCF'!$V$36,'DRE + DCF'!$X$36:$AA$36)*((1+$H9)^((12-3)/12))+('DRE + DCF'!$AB$36*(1+N$18)/(($H9-N$18)*(1+$H9)^(COUNT('DRE + DCF'!$W$22:$AA$22)-((12-3)/12)))))*$F$40+$F$42)*(1-$F$39))/$F$10 -> 23.421132 | O9: =(((NPV($H9,'DRE + DCF'!$V$36,'DRE + DCF'!$X$36:$AA$36)*((1+$H9)^((12-3)/12))+('DRE + DCF'!$AB$36*(1+O$18)/(($H9-O$18)*(1+$H9)^(COUNT('DRE + DCF'!$W$22:$AA$22)-((12-3)/12)))))+SUM($F$12:$F$17)))/$F$10-(((NPV($H9,'DRE + DCF'!$V$36,'DRE + DCF'!$X$36:$AA$36)*((1+$H9)^((12-3)/12))+('DRE + DCF'!$AB$36*(1+O$18)/(($H9-O$18)*(1+$H9)^(COUNT('DRE + DCF'!$W$22:$AA$22)-((12-3)/12)))))*$F$40+$F$42)*(1-$F$39))/$F$10 -> 27.200246 | P9: =(((NPV($H9,'DRE + DCF'!$V$36,'DRE + DCF'!$X$36:$AA$36)*((1+$H9)^((12-3)/12))+('DRE + DCF'!$AB$36*(1+P$18)/(($H9-P$18)*(1+$H9)^(COUNT('DRE + DCF'!$W$22:$AA$22)-((12-3)/12)))))+SUM($F$12:$F$17)))/$F$10-(((NPV($H9,'DRE + DCF'!$V$36,'DRE + DCF'!$X$36:$AA$36)*((1+$H9)^((12-3)/12))+('DRE + DCF'!$AB$36*(1+P$18)/(($H9-P$18)*(1+$H9)^(COUNT('DRE + DCF'!$W$22:$AA$22)-((12-3)/12)))))*$F$40+$F$42)*(1-$F$39))/$F$10 -> 32.576599 | ... R9: =(((NPV($H9,'DRE + DCF'!$V$36,'DRE + DCF'!$X$36:$AA$36)*((1+$H9)^((12-3)/12))+('DRE + DCF'!$AB$36*(1+R$18)/(($H9-R$18)*(1+$H9)^(COUNT('DRE + DCF'!$W$22:$AA$22)-((12-3)/12)))))+SUM($F$12:$F$17)))/$F$10-(((NPV($H9,'DRE + DCF'!$V$36,'DRE + DCF'!$X$36:$AA$36)*((1+$H9)^((12-3)/12))+('DRE + DCF'!$AB$36*(1+R$18)/(($H9-R$18)*(1+$H9)^(COUNT('DRE + DCF'!$W$22:$AA$22)-((12-3)/12)))))*$F$40+$F$42)*(1-$F$39))/$F$10 -> 55.136581
A10: DRE Consolidado | E10: Ações Emitidas (mil) | F10: 873040.53 | H10: =H11-0.5% -> 0.095330137 | I10: =(((NPV($H10,'DRE + DCF'!$V$36,'DRE + DCF'!$X$36:$AA$36)*((1+$H10)^((12-3)/12))+('DRE + DCF'!$AB$36*(1+I$18)/(($H10-I$18)*(1+$H10)^(COUNT('DRE + DCF'!$W$22:$AA$22)-((12-3)/12)))))+SUM($F$12:$F$17)))/$F$10-(((NPV($H10,'DRE + DCF'!$V$36,'DRE + DCF'!$X$36:$AA$36)*((1+$H10)^((12-3)/12))+('DRE + DCF'!$AB$36*(1+I$18)/(($H10-I$18)*(1+$H10)^(COUNT('DRE + DCF'!$W$22:$AA$22)-((12-3)/12)))))*$F$40+$F$42)*(1-$F$39))/$F$10 -> 12.188699 | J10: =(((NPV($H10,'DRE + DCF'!$V$36,'DRE + DCF'!$X$36:$AA$36)*((1+$H10)^((12-3)/12))+('DRE + DCF'!$AB$36*(1+J$18)/(($H10-J$18)*(1+$H10)^(COUNT('DRE + DCF'!$W$22:$AA$22)-((12-3)/12)))))+SUM($F$12:$F$17)))/$F$10-(((NPV($H10,'DRE + DCF'!$V$36,'DRE + DCF'!$X$36:$AA$36)*((1+$H10)^((12-3)/12))+('DRE + DCF'!$AB$36*(1+J$18)/(($H10-J$18)*(1+$H10)^(COUNT('DRE + DCF'!$W$22:$AA$22)-((12-3)/12)))))*$F$40+$F$42)*(1-$F$39))/$F$10 -> 13.01048 | K10: =(((NPV($H10,'DRE + DCF'!$V$36,'DRE + DCF'!$X$36:$AA$36)*((1+$H10)^((12-3)/12))+('DRE + DCF'!$AB$36*(1+K$18)/(($H10-K$18)*(1+$H10)^(COUNT('DRE + DCF'!$W$22:$AA$22)-((12-3)/12)))))+SUM($F$12:$F$17)))/$F$10-(((NPV($H10,'DRE + DCF'!$V$36,'DRE + DCF'!$X$36:$AA$36)*((1+$H10)^((12-3)/12))+('DRE + DCF'!$AB$36*(1+K$18)/(($H10-K$18)*(1+$H10)^(COUNT('DRE + DCF'!$W$22:$AA$22)-((12-3)/12)))))*$F$40+$F$42)*(1-$F$39))/$F$10 -> 13.972353 | L10: =(((NPV($H10,'DRE + DCF'!$V$36,'DRE + DCF'!$X$36:$AA$36)*((1+$H10)^((12-3)/12))+('DRE + DCF'!$AB$36*(1+L$18)/(($H10-L$18)*(1+$H10)^(COUNT('DRE + DCF'!$W$22:$AA$22)-((12-3)/12)))))+SUM($F$12:$F$17)))/$F$10-(((NPV($H10,'DRE + DCF'!$V$36,'DRE + DCF'!$X$36:$AA$36)*((1+$H10)^((12-3)/12))+('DRE + DCF'!$AB$36*(1+L$18)/(($H10-L$18)*(1+$H10)^(COUNT('DRE + DCF'!$W$22:$AA$22)-((12-3)/12)))))*$F$40+$F$42)*(1-$F$39))/$F$10 -> 15.113478 | M10: =(((NPV($H10,'DRE + DCF'!$V$36,'DRE + DCF'!$X$36:$AA$36)*((1+$H10)^((12-3)/12))+('DRE + DCF'!$AB$36*(1+M$18)/(($H10-M$18)*(1+$H10)^(COUNT('DRE + DCF'!$W$22:$AA$22)-((12-3)/12)))))+SUM($F$12:$F$17)))/$F$10-(((NPV($H10,'DRE + DCF'!$V$36,'DRE + DCF'!$X$36:$AA$36)*((1+$H10)^((12-3)/12))+('DRE + DCF'!$AB$36*(1+M$18)/(($H10-M$18)*(1+$H10)^(COUNT('DRE + DCF'!$W$22:$AA$22)-((12-3)/12)))))*$F$40+$F$42)*(1-$F$39))/$F$10 -> 16.489111 | N10: =(((NPV($H10,'DRE + DCF'!$V$36,'DRE + DCF'!$X$36:$AA$36)*((1+$H10)^((12-3)/12))+('DRE + DCF'!$AB$36*(1+N$18)/(($H10-N$18)*(1+$H10)^(COUNT('DRE + DCF'!$W$22:$AA$22)-((12-3)/12)))))+SUM($F$12:$F$17)))/$F$10-(((NPV($H10,'DRE + DCF'!$V$36,'DRE + DCF'!$X$36:$AA$36)*((1+$H10)^((12-3)/12))+('DRE + DCF'!$AB$36*(1+N$18)/(($H10-N$18)*(1+$H10)^(COUNT('DRE + DCF'!$W$22:$AA$22)-((12-3)/12)))))*$F$40+$F$42)*(1-$F$39))/$F$10 -> 18.179821 | O10: =(((NPV($H10,'DRE + DCF'!$V$36,'DRE + DCF'!$X$36:$AA$36)*((1+$H10)^((12-3)/12))+('DRE + DCF'!$AB$36*(1+O$18)/(($H10-O$18)*(1+$H10)^(COUNT('DRE + DCF'!$W$22:$AA$22)-((12-3)/12)))))+SUM($F$12:$F$17)))/$F$10-(((NPV($H10,'DRE + DCF'!$V$36,'DRE + DCF'!$X$36:$AA$36)*((1+$H10)^((12-3)/12))+('DRE + DCF'!$AB$36*(1+O$18)/(($H10-O$18)*(1+$H10)^(COUNT('DRE + DCF'!$W$22:$AA$22)-((12-3)/12)))))*$F$40+$F$42)*(1-$F$39))/$F$10 -> 20.307856 | P10: =(((NPV($H10,'DRE + DCF'!$V$36,'DRE + DCF'!$X$36:$AA$36)*((1+$H10)^((12-3)/12))+('DRE + DCF'!$AB$36*(1+P$18)/(($H10-P$18)*(1+$H10)^(COUNT('DRE + DCF'!$W$22:$AA$22)-((12-3)/12)))))+SUM($F$12:$F$17)))/$F$10-(((NPV($H10,'DRE + DCF'!$V$36,'DRE + DCF'!$X$36:$AA$36)*((1+$H10)^((12-3)/12))+('DRE + DCF'!$AB$36*(1+P$18)/(($H10-P$18)*(1+$H10)^(COUNT('DRE + DCF'!$W$22:$AA$22)-((12-3)/12)))))*$F$40+$F$42)*(1-$F$39))/$F$10 -> 23.0681 | ... R10: =(((NPV($H10,'DRE + DCF'!$V$36,'DRE + DCF'!$X$36:$AA$36)*((1+$H10)^((12-3)/12))+('DRE + DCF'!$AB$36*(1+R$18)/(($H10-R$18)*(1+$H10)^(COUNT('DRE + DCF'!$W$22:$AA$22)-((12-3)/12)))))+SUM($F$12:$F$17)))/$F$10-(((NPV($H10,'DRE + DCF'!$V$36,'DRE + DCF'!$X$36:$AA$36)*((1+$H10)^((12-3)/12))+('DRE + DCF'!$AB$36*(1+R$18)/(($H10-R$18)*(1+$H10)^(COUNT('DRE + DCF'!$W$22:$AA$22)-((12-3)/12)))))*$F$40+$F$42)*(1-$F$39))/$F$10 -> 32.088436
A11: DRE + DCF | E11: Valor da Empresa (mil) | F11: =SUM('DRE + DCF'!V38:AB38) -> 10729800 | H11: =H12-0.5% -> 0.10033014 | I11: =(((NPV($H11,'DRE + DCF'!$V$36,'DRE + DCF'!$X$36:$AA$36)*((1+$H11)^((12-3)/12))+('DRE + DCF'!$AB$36*(1+I$18)/(($H11-I$18)*(1+$H11)^(COUNT('DRE + DCF'!$W$22:$AA$22)-((12-3)/12)))))+SUM($F$12:$F$17)))/$F$10-(((NPV($H11,'DRE + DCF'!$V$36,'DRE + DCF'!$X$36:$AA$36)*((1+$H11)^((12-3)/12))+('DRE + DCF'!$AB$36*(1+I$18)/(($H11-I$18)*(1+$H11)^(COUNT('DRE + DCF'!$W$22:$AA$22)-((12-3)/12)))))*$F$40+$F$42)*(1-$F$39))/$F$10 -> 10.691676 | J11: =(((NPV($H11,'DRE + DCF'!$V$36,'DRE + DCF'!$X$36:$AA$36)*((1+$H11)^((12-3)/12))+('DRE + DCF'!$AB$36*(1+J$18)/(($H11-J$18)*(1+$H11)^(COUNT('DRE + DCF'!$W$22:$AA$22)-((12-3)/12)))))+SUM($F$12:$F$17)))/$F$10-(((NPV($H11,'DRE + DCF'!$V$36,'DRE + DCF'!$X$36:$AA$36)*((1+$H11)^((12-3)/12))+('DRE + DCF'!$AB$36*(1+J$18)/(($H11-J$18)*(1+$H11)^(COUNT('DRE + DCF'!$W$22:$AA$22)-((12-3)/12)))))*$F$40+$F$42)*(1-$F$39))/$F$10 -> 11.302495 | K11: =(((NPV($H11,'DRE + DCF'!$V$36,'DRE + DCF'!$X$36:$AA$36)*((1+$H11)^((12-3)/12))+('DRE + DCF'!$AB$36*(1+K$18)/(($H11-K$18)*(1+$H11)^(COUNT('DRE + DCF'!$W$22:$AA$22)-((12-3)/12)))))+SUM($F$12:$F$17)))/$F$10-(((NPV($H11,'DRE + DCF'!$V$36,'DRE + DCF'!$X$36:$AA$36)*((1+$H11)^((12-3)/12))+('DRE + DCF'!$AB$36*(1+K$18)/(($H11-K$18)*(1+$H11)^(COUNT('DRE + DCF'!$W$22:$AA$22)-((12-3)/12)))))*$F$40+$F$42)*(1-$F$39))/$F$10 -> 12.002278 | L11: =(((NPV($H11,'DRE + DCF'!$V$36,'DRE + DCF'!$X$36:$AA$36)*((1+$H11)^((12-3)/12))+('DRE + DCF'!$AB$36*(1+L$18)/(($H11-L$18)*(1+$H11)^(COUNT('DRE + DCF'!$W$22:$AA$22)-((12-3)/12)))))+SUM($F$12:$F$17)))/$F$10-(((NPV($H11,'DRE + DCF'!$V$36,'DRE + DCF'!$X$36:$AA$36)*((1+$H11)^((12-3)/12))+('DRE + DCF'!$AB$36*(1+L$18)/(($H11-L$18)*(1+$H11)^(COUNT('DRE + DCF'!$W$22:$AA$22)-((12-3)/12)))))*$F$40+$F$42)*(1-$F$39))/$F$10 -> 12.811984 | M11: =(((NPV($H11,'DRE + DCF'!$V$36,'DRE + DCF'!$X$36:$AA$36)*((1+$H11)^((12-3)/12))+('DRE + DCF'!$AB$36*(1+M$18)/(($H11-M$18)*(1+$H11)^(COUNT('DRE + DCF'!$W$22:$AA$22)-((12-3)/12)))))+SUM($F$12:$F$17)))/$F$10-(((NPV($H11,'DRE + DCF'!$V$36,'DRE + DCF'!$X$36:$AA$36)*((1+$H11)^((12-3)/12))+('DRE + DCF'!$AB$36*(1+M$18)/(($H11-M$18)*(1+$H11)^(COUNT('DRE + DCF'!$W$22:$AA$22)-((12-3)/12)))))*$F$40+$F$42)*(1-$F$39))/$F$10 -> 13.759724 | N11: =(((NPV($H11,'DRE + DCF'!$V$36,'DRE + DCF'!$X$36:$AA$36)*((1+$H11)^((12-3)/12))+('DRE + DCF'!$AB$36*(1+N$18)/(($H11-N$18)*(1+$H11)^(COUNT('DRE + DCF'!$W$22:$AA$22)-((12-3)/12)))))+SUM($F$12:$F$17)))/$F$10-(((NPV($H11,'DRE + DCF'!$V$36,'DRE + DCF'!$X$36:$AA$36)*((1+$H11)^((12-3)/12))+('DRE + DCF'!$AB$36*(1+N$18)/(($H11-N$18)*(1+$H11)^(COUNT('DRE + DCF'!$W$22:$AA$22)-((12-3)/12)))))*$F$40+$F$42)*(1-$F$39))/$F$10 -> 14.884082 | O11: =(((NPV($H11,'DRE + DCF'!$V$36,'DRE + DCF'!$X$36:$AA$36)*((1+$H11)^((12-3)/12))+('DRE + DCF'!$AB$36*(1+O$18)/(($H11-O$18)*(1+$H11)^(COUNT('DRE + DCF'!$W$22:$AA$22)-((12-3)/12)))))+SUM($F$12:$F$17)))/$F$10-(((NPV($H11,'DRE + DCF'!$V$36,'DRE + DCF'!$X$36:$AA$36)*((1+$H11)^((12-3)/12))+('DRE + DCF'!$AB$36*(1+O$18)/(($H11-O$18)*(1+$H11)^(COUNT('DRE + DCF'!$W$22:$AA$22)-((12-3)/12)))))*$F$40+$F$42)*(1-$F$39))/$F$10 -> 16.239504 | P11: =(((NPV($H11,'DRE + DCF'!$V$36,'DRE + DCF'!$X$36:$AA$36)*((1+$H11)^((12-3)/12))+('DRE + DCF'!$AB$36*(1+P$18)/(($H11-P$18)*(1+$H11)^(COUNT('DRE + DCF'!$W$22:$AA$22)-((12-3)/12)))))+SUM($F$12:$F$17)))/$F$10-(((NPV($H11,'DRE + DCF'!$V$36,'DRE + DCF'!$X$36:$AA$36)*((1+$H11)^((12-3)/12))+('DRE + DCF'!$AB$36*(1+P$18)/(($H11-P$18)*(1+$H11)^(COUNT('DRE + DCF'!$W$22:$AA$22)-((12-3)/12)))))*$F$40+$F$42)*(1-$F$39))/$F$10 -> 17.905372 | ... R11: =(((NPV($H11,'DRE + DCF'!$V$36,'DRE + DCF'!$X$36:$AA$36)*((1+$H11)^((12-3)/12))+('DRE + DCF'!$AB$36*(1+R$18)/(($H11-R$18)*(1+$H11)^(COUNT('DRE + DCF'!$W$22:$AA$22)-((12-3)/12)))))+SUM($F$12:$F$17)))/$F$10-(((NPV($H11,'DRE + DCF'!$V$36,'DRE + DCF'!$X$36:$AA$36)*((1+$H11)^((12-3)/12))+('DRE + DCF'!$AB$36*(1+R$18)/(($H11-R$18)*(1+$H11)^(COUNT('DRE + DCF'!$W$22:$AA$22)-((12-3)/12)))))*$F$40+$F$42)*(1-$F$39))/$F$10 -> 22.721828
A12: DRE - Contas Abertas | E12: Dívida (mil) | F12: =-F36 -> -13637481 | H12: =H13-0.5% -> 0.10533014 | I12: =(((NPV($H12,'DRE + DCF'!$V$36,'DRE + DCF'!$X$36:$AA$36)*((1+$H12)^((12-3)/12))+('DRE + DCF'!$AB$36*(1+I$18)/(($H12-I$18)*(1+$H12)^(COUNT('DRE + DCF'!$W$22:$AA$22)-((12-3)/12)))))+SUM($F$12:$F$17)))/$F$10-(((NPV($H12,'DRE + DCF'!$V$36,'DRE + DCF'!$X$36:$AA$36)*((1+$H12)^((12-3)/12))+('DRE + DCF'!$AB$36*(1+I$18)/(($H12-I$18)*(1+$H12)^(COUNT('DRE + DCF'!$W$22:$AA$22)-((12-3)/12)))))*$F$40+$F$42)*(1-$F$39))/$F$10 -> 9.5278566 | J12: =(((NPV($H12,'DRE + DCF'!$V$36,'DRE + DCF'!$X$36:$AA$36)*((1+$H12)^((12-3)/12))+('DRE + DCF'!$AB$36*(1+J$18)/(($H12-J$18)*(1+$H12)^(COUNT('DRE + DCF'!$W$22:$AA$22)-((12-3)/12)))))+SUM($F$12:$F$17)))/$F$10-(((NPV($H12,'DRE + DCF'!$V$36,'DRE + DCF'!$X$36:$AA$36)*((1+$H12)^((12-3)/12))+('DRE + DCF'!$AB$36*(1+J$18)/(($H12-J$18)*(1+$H12)^(COUNT('DRE + DCF'!$W$22:$AA$22)-((12-3)/12)))))*$F$40+$F$42)*(1-$F$39))/$F$10 -> 9.9980257 | K12: =(((NPV($H12,'DRE + DCF'!$V$36,'DRE + DCF'!$X$36:$AA$36)*((1+$H12)^((12-3)/12))+('DRE + DCF'!$AB$36*(1+K$18)/(($H12-K$18)*(1+$H12)^(COUNT('DRE + DCF'!$W$22:$AA$22)-((12-3)/12)))))+SUM($F$12:$F$17)))/$F$10-(((NPV($H12,'DRE + DCF'!$V$36,'DRE + DCF'!$X$36:$AA$36)*((1+$H12)^((12-3)/12))+('DRE + DCF'!$AB$36*(1+K$18)/(($H12-K$18)*(1+$H12)^(COUNT('DRE + DCF'!$W$22:$AA$22)-((12-3)/12)))))*$F$40+$F$42)*(1-$F$39))/$F$10 -> 10.527967 | L12: =(((NPV($H12,'DRE + DCF'!$V$36,'DRE + DCF'!$X$36:$AA$36)*((1+$H12)^((12-3)/12))+('DRE + DCF'!$AB$36*(1+L$18)/(($H12-L$18)*(1+$H12)^(COUNT('DRE + DCF'!$W$22:$AA$22)-((12-3)/12)))))+SUM($F$12:$F$17)))/$F$10-(((NPV($H12,'DRE + DCF'!$V$36,'DRE + DCF'!$X$36:$AA$36)*((1+$H12)^((12-3)/12))+('DRE + DCF'!$AB$36*(1+L$18)/(($H12-L$18)*(1+$H12)^(COUNT('DRE + DCF'!$W$22:$AA$22)-((12-3)/12)))))*$F$40+$F$42)*(1-$F$39))/$F$10 -> 11.129852 | M12: =(((NPV($H12,'DRE + DCF'!$V$36,'DRE + DCF'!$X$36:$AA$36)*((1+$H12)^((12-3)/12))+('DRE + DCF'!$AB$36*(1+M$18)/(($H12-M$18)*(1+$H12)^(COUNT('DRE + DCF'!$W$22:$AA$22)-((12-3)/12)))))+SUM($F$12:$F$17)))/$F$10-(((NPV($H12,'DRE + DCF'!$V$36,'DRE + DCF'!$X$36:$AA$36)*((1+$H12)^((12-3)/12))+('DRE + DCF'!$AB$36*(1+M$18)/(($H12-M$18)*(1+$H12)^(COUNT('DRE + DCF'!$W$22:$AA$22)-((12-3)/12)))))*$F$40+$F$42)*(1-$F$39))/$F$10 -> 11.819399 | N12: =(((NPV($H12,'DRE + DCF'!$V$36,'DRE + DCF'!$X$36:$AA$36)*((1+$H12)^((12-3)/12))+('DRE + DCF'!$AB$36*(1+N$18)/(($H12-N$18)*(1+$H12)^(COUNT('DRE + DCF'!$W$22:$AA$22)-((12-3)/12)))))+SUM($F$12:$F$17)))/$F$10-(((NPV($H12,'DRE + DCF'!$V$36,'DRE + DCF'!$X$36:$AA$36)*((1+$H12)^((12-3)/12))+('DRE + DCF'!$AB$36*(1+N$18)/(($H12-N$18)*(1+$H12)^(COUNT('DRE + DCF'!$W$22:$AA$22)-((12-3)/12)))))*$F$40+$F$42)*(1-$F$39))/$F$10 -> 12.617262 | O12: =(((NPV($H12,'DRE + DCF'!$V$36,'DRE + DCF'!$X$36:$AA$36)*((1+$H12)^((12-3)/12))+('DRE + DCF'!$AB$36*(1+O$18)/(($H12-O$18)*(1+$H12)^(COUNT('DRE + DCF'!$W$22:$AA$22)-((12-3)/12)))))+SUM($F$12:$F$17)))/$F$10-(((NPV($H12,'DRE + DCF'!$V$36,'DRE + DCF'!$X$36:$AA$36)*((1+$H12)^((12-3)/12))+('DRE + DCF'!$AB$36*(1+O$18)/(($H12-O$18)*(1+$H12)^(COUNT('DRE + DCF'!$W$22:$AA$22)-((12-3)/12)))))*$F$40+$F$42)*(1-$F$39))/$F$10 -> 13.551139 | P12: =(((NPV($H12,'DRE + DCF'!$V$36,'DRE + DCF'!$X$36:$AA$36)*((1+$H12)^((12-3)/12))+('DRE + DCF'!$AB$36*(1+P$18)/(($H12-P$18)*(1+$H12)^(COUNT('DRE + DCF'!$W$22:$AA$22)-((12-3)/12)))))+SUM($F$12:$F$17)))/$F$10-(((NPV($H12,'DRE + DCF'!$V$36,'DRE + DCF'!$X$36:$AA$36)*((1+$H12)^((12-3)/12))+('DRE + DCF'!$AB$36*(1+P$18)/(($H12-P$18)*(1+$H12)^(COUNT('DRE + DCF'!$W$22:$AA$22)-((12-3)/12)))))*$F$40+$F$42)*(1-$F$39))/$F$10 -> 14.659052 | ... R12: =(((NPV($H12,'DRE + DCF'!$V$36,'DRE + DCF'!$X$36:$AA$36)*((1+$H12)^((12-3)/12))+('DRE + DCF'!$AB$36*(1+R$18)/(($H12-R$18)*(1+$H12)^(COUNT('DRE + DCF'!$W$22:$AA$22)-((12-3)/12)))))+SUM($F$12:$F$17)))/$F$10-(((NPV($H12,'DRE + DCF'!$V$36,'DRE + DCF'!$X$36:$AA$36)*((1+$H12)^((12-3)/12))+('DRE + DCF'!$AB$36*(1+R$18)/(($H12-R$18)*(1+$H12)^(COUNT('DRE + DCF'!$W$22:$AA$22)-((12-3)/12)))))*$F$40+$F$42)*(1-$F$39))/$F$10 -> 17.63615
A13: Balanço Patrimonial | E13: Ativos/Passivos Não-Operacionais | F13: =F29 -> 3676632.3 | H13: =WACC!P20 -> 0.11033014 | I13: =(((NPV($H13,'DRE + DCF'!$V$36,'DRE + DCF'!$X$36:$AA$36)*((1+$H13)^((12-3)/12))+('DRE + DCF'!$AB$36*(1+I$18)/(($H13-I$18)*(1+$H13)^(COUNT('DRE + DCF'!$W$22:$AA$22)-((12-3)/12)))))+SUM($F$12:$F$17)))/$F$10-(((NPV($H13,'DRE + DCF'!$V$36,'DRE + DCF'!$X$36:$AA$36)*((1+$H13)^((12-3)/12))+('DRE + DCF'!$AB$36*(1+I$18)/(($H13-I$18)*(1+$H13)^(COUNT('DRE + DCF'!$W$22:$AA$22)-((12-3)/12)))))*$F$40+$F$42)*(1-$F$39))/$F$10 -> 8.5960433 | J13: =(((NPV($H13,'DRE + DCF'!$V$36,'DRE + DCF'!$X$36:$AA$36)*((1+$H13)^((12-3)/12))+('DRE + DCF'!$AB$36*(1+J$18)/(($H13-J$18)*(1+$H13)^(COUNT('DRE + DCF'!$W$22:$AA$22)-((12-3)/12)))))+SUM($F$12:$F$17)))/$F$10-(((NPV($H13,'DRE + DCF'!$V$36,'DRE + DCF'!$X$36:$AA$36)*((1+$H13)^((12-3)/12))+('DRE + DCF'!$AB$36*(1+J$18)/(($H13-J$18)*(1+$H13)^(COUNT('DRE + DCF'!$W$22:$AA$22)-((12-3)/12)))))*$F$40+$F$42)*(1-$F$39))/$F$10 -> 8.9679503 | K13: =(((NPV($H13,'DRE + DCF'!$V$36,'DRE + DCF'!$X$36:$AA$36)*((1+$H13)^((12-3)/12))+('DRE + DCF'!$AB$36*(1+K$18)/(($H13-K$18)*(1+$H13)^(COUNT('DRE + DCF'!$W$22:$AA$22)-((12-3)/12)))))+SUM($F$12:$F$17)))/$F$10-(((NPV($H13,'DRE + DCF'!$V$36,'DRE + DCF'!$X$36:$AA$36)*((1+$H13)^((12-3)/12))+('DRE + DCF'!$AB$36*(1+K$18)/(($H13-K$18)*(1+$H13)^(COUNT('DRE + DCF'!$W$22:$AA$22)-((12-3)/12)))))*$F$40+$F$42)*(1-$F$39))/$F$10 -> 9.3818047 | L13: =(((NPV($H13,'DRE + DCF'!$V$36,'DRE + DCF'!$X$36:$AA$36)*((1+$H13)^((12-3)/12))+('DRE + DCF'!$AB$36*(1+L$18)/(($H13-L$18)*(1+$H13)^(COUNT('DRE + DCF'!$W$22:$AA$22)-((12-3)/12)))))+SUM($F$12:$F$17)))/$F$10-(((NPV($H13,'DRE + DCF'!$V$36,'DRE + DCF'!$X$36:$AA$36)*((1+$H13)^((12-3)/12))+('DRE + DCF'!$AB$36*(1+L$18)/(($H13-L$18)*(1+$H13)^(COUNT('DRE + DCF'!$W$22:$AA$22)-((12-3)/12)))))*$F$40+$F$42)*(1-$F$39))/$F$10 -> 9.8451275 | M13: =(((NPV($H13,'DRE + DCF'!$V$36,'DRE + DCF'!$X$36:$AA$36)*((1+$H13)^((12-3)/12))+('DRE + DCF'!$AB$36*(1+M$18)/(($H13-M$18)*(1+$H13)^(COUNT('DRE + DCF'!$W$22:$AA$22)-((12-3)/12)))))+SUM($F$12:$F$17)))/$F$10-(((NPV($H13,'DRE + DCF'!$V$36,'DRE + DCF'!$X$36:$AA$36)*((1+$H13)^((12-3)/12))+('DRE + DCF'!$AB$36*(1+M$18)/(($H13-M$18)*(1+$H13)^(COUNT('DRE + DCF'!$W$22:$AA$22)-((12-3)/12)))))*$F$40+$F$42)*(1-$F$39))/$F$10 -> 10.367352 | N13: =(((NPV($H13,'DRE + DCF'!$V$36,'DRE + DCF'!$X$36:$AA$36)*((1+$H13)^((12-3)/12))+('DRE + DCF'!$AB$36*(1+N$18)/(($H13-N$18)*(1+$H13)^(COUNT('DRE + DCF'!$W$22:$AA$22)-((12-3)/12)))))+SUM($F$12:$F$17)))/$F$10-(((NPV($H13,'DRE + DCF'!$V$36,'DRE + DCF'!$X$36:$AA$36)*((1+$H13)^((12-3)/12))+('DRE + DCF'!$AB$36*(1+N$18)/(($H13-N$18)*(1+$H13)^(COUNT('DRE + DCF'!$W$22:$AA$22)-((12-3)/12)))))*$F$40+$F$42)*(1-$F$39))/$F$10 -> 10.960473 | O13: =(((NPV($H13,'DRE + DCF'!$V$36,'DRE + DCF'!$X$36:$AA$36)*((1+$H13)^((12-3)/12))+('DRE + DCF'!$AB$36*(1+O$18)/(($H13-O$18)*(1+$H13)^(COUNT('DRE + DCF'!$W$22:$AA$22)-((12-3)/12)))))+SUM($F$12:$F$17)))/$F$10-(((NPV($H13,'DRE + DCF'!$V$36,'DRE + DCF'!$X$36:$AA$36)*((1+$H13)^((12-3)/12))+('DRE + DCF'!$AB$36*(1+O$18)/(($H13-O$18)*(1+$H13)^(COUNT('DRE + DCF'!$W$22:$AA$22)-((12-3)/12)))))*$F$40+$F$42)*(1-$F$39))/$F$10 -> 11.639979 | P13: =(((NPV($H13,'DRE + DCF'!$V$36,'DRE + DCF'!$X$36:$AA$36)*((1+$H13)^((12-3)/12))+('DRE + DCF'!$AB$36*(1+P$18)/(($H13-P$18)*(1+$H13)^(COUNT('DRE + DCF'!$W$22:$AA$22)-((12-3)/12)))))+SUM($F$12:$F$17)))/$F$10-(((NPV($H13,'DRE + DCF'!$V$36,'DRE + DCF'!$X$36:$AA$36)*((1+$H13)^((12-3)/12))+('DRE + DCF'!$AB$36*(1+P$18)/(($H13-P$18)*(1+$H13)^(COUNT('DRE + DCF'!$W$22:$AA$22)-((12-3)/12)))))*$F$40+$F$42)*(1-$F$39))/$F$10 -> 12.426224 | ... R13: =(((NPV($H13,'DRE + DCF'!$V$36,'DRE + DCF'!$X$36:$AA$36)*((1+$H13)^((12-3)/12))+('DRE + DCF'!$AB$36*(1+R$18)/(($H13-R$18)*(1+$H13)^(COUNT('DRE + DCF'!$W$22:$AA$22)-((12-3)/12)))))+SUM($F$12:$F$17)))/$F$10-(((NPV($H13,'DRE + DCF'!$V$36,'DRE + DCF'!$X$36:$AA$36)*((1+$H13)^((12-3)/12))+('DRE + DCF'!$AB$36*(1+R$18)/(($H13-R$18)*(1+$H13)^(COUNT('DRE + DCF'!$W$22:$AA$22)-((12-3)/12)))))*$F$40+$F$42)*(1-$F$39))/$F$10 -> 14.438283
A14: Painel de Índices | E14: Empresas de Capital Aberto | F14: =K29 -> 12494156 | H14: =H13+0.5% -> 0.11533014 | I14: =(((NPV($H14,'DRE + DCF'!$V$36,'DRE + DCF'!$X$36:$AA$36)*((1+$H14)^((12-3)/12))+('DRE + DCF'!$AB$36*(1+I$18)/(($H14-I$18)*(1+$H14)^(COUNT('DRE + DCF'!$W$22:$AA$22)-((12-3)/12)))))+SUM($F$12:$F$17)))/$F$10-(((NPV($H14,'DRE + DCF'!$V$36,'DRE + DCF'!$X$36:$AA$36)*((1+$H14)^((12-3)/12))+('DRE + DCF'!$AB$36*(1+I$18)/(($H14-I$18)*(1+$H14)^(COUNT('DRE + DCF'!$W$22:$AA$22)-((12-3)/12)))))*$F$40+$F$42)*(1-$F$39))/$F$10 -> 7.8322874 | J14: =(((NPV($H14,'DRE + DCF'!$V$36,'DRE + DCF'!$X$36:$AA$36)*((1+$H14)^((12-3)/12))+('DRE + DCF'!$AB$36*(1+J$18)/(($H14-J$18)*(1+$H14)^(COUNT('DRE + DCF'!$W$22:$AA$22)-((12-3)/12)))))+SUM($F$12:$F$17)))/$F$10-(((NPV($H14,'DRE + DCF'!$V$36,'DRE + DCF'!$X$36:$AA$36)*((1+$H14)^((12-3)/12))+('DRE + DCF'!$AB$36*(1+J$18)/(($H14-J$18)*(1+$H14)^(COUNT('DRE + DCF'!$W$22:$AA$22)-((12-3)/12)))))*$F$40+$F$42)*(1-$F$39))/$F$10 -> 8.1329693 | K14: =(((NPV($H14,'DRE + DCF'!$V$36,'DRE + DCF'!$X$36:$AA$36)*((1+$H14)^((12-3)/12))+('DRE + DCF'!$AB$36*(1+K$18)/(($H14-K$18)*(1+$H14)^(COUNT('DRE + DCF'!$W$22:$AA$22)-((12-3)/12)))))+SUM($F$12:$F$17)))/$F$10-(((NPV($H14,'DRE + DCF'!$V$36,'DRE + DCF'!$X$36:$AA$36)*((1+$H14)^((12-3)/12))+('DRE + DCF'!$AB$36*(1+K$18)/(($H14-K$18)*(1+$H14)^(COUNT('DRE + DCF'!$W$22:$AA$22)-((12-3)/12)))))*$F$40+$F$42)*(1-$F$39))/$F$10 -> 8.4641276 | L14: =(((NPV($H14,'DRE + DCF'!$V$36,'DRE + DCF'!$X$36:$AA$36)*((1+$H14)^((12-3)/12))+('DRE + DCF'!$AB$36*(1+L$18)/(($H14-L$18)*(1+$H14)^(COUNT('DRE + DCF'!$W$22:$AA$22)-((12-3)/12)))))+SUM($F$12:$F$17)))/$F$10-(((NPV($H14,'DRE + DCF'!$V$36,'DRE + DCF'!$X$36:$AA$36)*((1+$H14)^((12-3)/12))+('DRE + DCF'!$AB$36*(1+L$18)/(($H14-L$18)*(1+$H14)^(COUNT('DRE + DCF'!$W$22:$AA$22)-((12-3)/12)))))*$F$40+$F$42)*(1-$F$39))/$F$10 -> 8.8306433 | M14: =(((NPV($H14,'DRE + DCF'!$V$36,'DRE + DCF'!$X$36:$AA$36)*((1+$H14)^((12-3)/12))+('DRE + DCF'!$AB$36*(1+M$18)/(($H14-M$18)*(1+$H14)^(COUNT('DRE + DCF'!$W$22:$AA$22)-((12-3)/12)))))+SUM($F$12:$F$17)))/$F$10-(((NPV($H14,'DRE + DCF'!$V$36,'DRE + DCF'!$X$36:$AA$36)*((1+$H14)^((12-3)/12))+('DRE + DCF'!$AB$36*(1+M$18)/(($H14-M$18)*(1+$H14)^(COUNT('DRE + DCF'!$W$22:$AA$22)-((12-3)/12)))))*$F$40+$F$42)*(1-$F$39))/$F$10 -> 9.2384983 | N14: =(((NPV($H14,'DRE + DCF'!$V$36,'DRE + DCF'!$X$36:$AA$36)*((1+$H14)^((12-3)/12))+('DRE + DCF'!$AB$36*(1+N$18)/(($H14-N$18)*(1+$H14)^(COUNT('DRE + DCF'!$W$22:$AA$22)-((12-3)/12)))))+SUM($F$12:$F$17)))/$F$10-(((NPV($H14,'DRE + DCF'!$V$36,'DRE + DCF'!$X$36:$AA$36)*((1+$H14)^((12-3)/12))+('DRE + DCF'!$AB$36*(1+N$18)/(($H14-N$18)*(1+$H14)^(COUNT('DRE + DCF'!$W$22:$AA$22)-((12-3)/12)))))*$F$40+$F$42)*(1-$F$39))/$F$10 -> 9.6951047 | O14: =(((NPV($H14,'DRE + DCF'!$V$36,'DRE + DCF'!$X$36:$AA$36)*((1+$H14)^((12-3)/12))+('DRE + DCF'!$AB$36*(1+O$18)/(($H14-O$18)*(1+$H14)^(COUNT('DRE + DCF'!$W$22:$AA$22)-((12-3)/12)))))+SUM($F$12:$F$17)))/$F$10-(((NPV($H14,'DRE + DCF'!$V$36,'DRE + DCF'!$X$36:$AA$36)*((1+$H14)^((12-3)/12))+('DRE + DCF'!$AB$36*(1+O$18)/(($H14-O$18)*(1+$H14)^(COUNT('DRE + DCF'!$W$22:$AA$22)-((12-3)/12)))))*$F$40+$F$42)*(1-$F$39))/$F$10 -> 10.209759 | P14: =(((NPV($H14,'DRE + DCF'!$V$36,'DRE + DCF'!$X$36:$AA$36)*((1+$H14)^((12-3)/12))+('DRE + DCF'!$AB$36*(1+P$18)/(($H14-P$18)*(1+$H14)^(COUNT('DRE + DCF'!$W$22:$AA$22)-((12-3)/12)))))+SUM($F$12:$F$17)))/$F$10-(((NPV($H14,'DRE + DCF'!$V$36,'DRE + DCF'!$X$36:$AA$36)*((1+$H14)^((12-3)/12))+('DRE + DCF'!$AB$36*(1+P$18)/(($H14-P$18)*(1+$H14)^(COUNT('DRE + DCF'!$W$22:$AA$22)-((12-3)/12)))))*$F$40+$F$42)*(1-$F$39))/$F$10 -> 10.794282 | ... R14: =(((NPV($H14,'DRE + DCF'!$V$36,'DRE + DCF'!$X$36:$AA$36)*((1+$H14)^((12-3)/12))+('DRE + DCF'!$AB$36*(1+R$18)/(($H14-R$18)*(1+$H14)^(COUNT('DRE + DCF'!$W$22:$AA$22)-((12-3)/12)))))+SUM($F$12:$F$17)))/$F$10-(((NPV($H14,'DRE + DCF'!$V$36,'DRE + DCF'!$X$36:$AA$36)*((1+$H14)^((12-3)/12))+('DRE + DCF'!$AB$36*(1+R$18)/(($H14-R$18)*(1+$H14)^(COUNT('DRE + DCF'!$W$22:$AA$22)-((12-3)/12)))))*$F$40+$F$42)*(1-$F$39))/$F$10 -> 12.238785
A15: Projeções - Receita e EBIT | E15: Valor do Equity da Automob que não pertence à Simpar | F15: =-F44 -> -1461068.2 | H15: =H14+0.5% -> 0.12033014 | I15: =(((NPV($H15,'DRE + DCF'!$V$36,'DRE + DCF'!$X$36:$AA$36)*((1+$H15)^((12-3)/12))+('DRE + DCF'!$AB$36*(1+I$18)/(($H15-I$18)*(1+$H15)^(COUNT('DRE + DCF'!$W$22:$AA$22)-((12-3)/12)))))+SUM($F$12:$F$17)))/$F$10-(((NPV($H15,'DRE + DCF'!$V$36,'DRE + DCF'!$X$36:$AA$36)*((1+$H15)^((12-3)/12))+('DRE + DCF'!$AB$36*(1+I$18)/(($H15-I$18)*(1+$H15)^(COUNT('DRE + DCF'!$W$22:$AA$22)-((12-3)/12)))))*$F$40+$F$42)*(1-$F$39))/$F$10 -> 7.1941941 | J15: =(((NPV($H15,'DRE + DCF'!$V$36,'DRE + DCF'!$X$36:$AA$36)*((1+$H15)^((12-3)/12))+('DRE + DCF'!$AB$36*(1+J$18)/(($H15-J$18)*(1+$H15)^(COUNT('DRE + DCF'!$W$22:$AA$22)-((12-3)/12)))))+SUM($F$12:$F$17)))/$F$10-(((NPV($H15,'DRE + DCF'!$V$36,'DRE + DCF'!$X$36:$AA$36)*((1+$H15)^((12-3)/12))+('DRE + DCF'!$AB$36*(1+J$18)/(($H15-J$18)*(1+$H15)^(COUNT('DRE + DCF'!$W$22:$AA$22)-((12-3)/12)))))*$F$40+$F$42)*(1-$F$39))/$F$10 -> 7.4416871 | K15: =(((NPV($H15,'DRE + DCF'!$V$36,'DRE + DCF'!$X$36:$AA$36)*((1+$H15)^((12-3)/12))+('DRE + DCF'!$AB$36*(1+K$18)/(($H15-K$18)*(1+$H15)^(COUNT('DRE + DCF'!$W$22:$AA$22)-((12-3)/12)))))+SUM($F$12:$F$17)))/$F$10-(((NPV($H15,'DRE + DCF'!$V$36,'DRE + DCF'!$X$36:$AA$36)*((1+$H15)^((12-3)/12))+('DRE + DCF'!$AB$36*(1+K$18)/(($H15-K$18)*(1+$H15)^(COUNT('DRE + DCF'!$W$22:$AA$22)-((12-3)/12)))))*$F$40+$F$42)*(1-$F$39))/$F$10 -> 7.7119569 | L15: =(((NPV($H15,'DRE + DCF'!$V$36,'DRE + DCF'!$X$36:$AA$36)*((1+$H15)^((12-3)/12))+('DRE + DCF'!$AB$36*(1+L$18)/(($H15-L$18)*(1+$H15)^(COUNT('DRE + DCF'!$W$22:$AA$22)-((12-3)/12)))))+SUM($F$12:$F$17)))/$F$10-(((NPV($H15,'DRE + DCF'!$V$36,'DRE + DCF'!$X$36:$AA$36)*((1+$H15)^((12-3)/12))+('DRE + DCF'!$AB$36*(1+L$18)/(($H15-L$18)*(1+$H15)^(COUNT('DRE + DCF'!$W$22:$AA$22)-((12-3)/12)))))*$F$40+$F$42)*(1-$F$39))/$F$10 -> 8.0082992 | M15: =(((NPV($H15,'DRE + DCF'!$V$36,'DRE + DCF'!$X$36:$AA$36)*((1+$H15)^((12-3)/12))+('DRE + DCF'!$AB$36*(1+M$18)/(($H15-M$18)*(1+$H15)^(COUNT('DRE + DCF'!$W$22:$AA$22)-((12-3)/12)))))+SUM($F$12:$F$17)))/$F$10-(((NPV($H15,'DRE + DCF'!$V$36,'DRE + DCF'!$X$36:$AA$36)*((1+$H15)^((12-3)/12))+('DRE + DCF'!$AB$36*(1+M$18)/(($H15-M$18)*(1+$H15)^(COUNT('DRE + DCF'!$W$22:$AA$22)-((12-3)/12)))))*$F$40+$F$42)*(1-$F$39))/$F$10 -> 8.3346783 | N15: =(((NPV($H15,'DRE + DCF'!$V$36,'DRE + DCF'!$X$36:$AA$36)*((1+$H15)^((12-3)/12))+('DRE + DCF'!$AB$36*(1+N$18)/(($H15-N$18)*(1+$H15)^(COUNT('DRE + DCF'!$W$22:$AA$22)-((12-3)/12)))))+SUM($F$12:$F$17)))/$F$10-(((NPV($H15,'DRE + DCF'!$V$36,'DRE + DCF'!$X$36:$AA$36)*((1+$H15)^((12-3)/12))+('DRE + DCF'!$AB$36*(1+N$18)/(($H15-N$18)*(1+$H15)^(COUNT('DRE + DCF'!$W$22:$AA$22)-((12-3)/12)))))*$F$40+$F$42)*(1-$F$39))/$F$10 -> 8.6959044 | O15: =(((NPV($H15,'DRE + DCF'!$V$36,'DRE + DCF'!$X$36:$AA$36)*((1+$H15)^((12-3)/12))+('DRE + DCF'!$AB$36*(1+O$18)/(($H15-O$18)*(1+$H15)^(COUNT('DRE + DCF'!$W$22:$AA$22)-((12-3)/12)))))+SUM($F$12:$F$17)))/$F$10-(((NPV($H15,'DRE + DCF'!$V$36,'DRE + DCF'!$X$36:$AA$36)*((1+$H15)^((12-3)/12))+('DRE + DCF'!$AB$36*(1+O$18)/(($H15-O$18)*(1+$H15)^(COUNT('DRE + DCF'!$W$22:$AA$22)-((12-3)/12)))))*$F$40+$F$42)*(1-$F$39))/$F$10 -> 9.0978733 | P15: =(((NPV($H15,'DRE + DCF'!$V$36,'DRE + DCF'!$X$36:$AA$36)*((1+$H15)^((12-3)/12))+('DRE + DCF'!$AB$36*(1+P$18)/(($H15-P$18)*(1+$H15)^(COUNT('DRE + DCF'!$W$22:$AA$22)-((12-3)/12)))))+SUM($F$12:$F$17)))/$F$10-(((NPV($H15,'DRE + DCF'!$V$36,'DRE + DCF'!$X$36:$AA$36)*((1+$H15)^((12-3)/12))+('DRE + DCF'!$AB$36*(1+P$18)/(($H15-P$18)*(1+$H15)^(COUNT('DRE + DCF'!$W$22:$AA$22)-((12-3)/12)))))*$F$40+$F$42)*(1-$F$39))/$F$10 -> 9.54789 | ... R15: =(((NPV($H15,'DRE + DCF'!$V$36,'DRE + DCF'!$X$36:$AA$36)*((1+$H15)^((12-3)/12))+('DRE + DCF'!$AB$36*(1+R$18)/(($H15-R$18)*(1+$H15)^(COUNT('DRE + DCF'!$W$22:$AA$22)-((12-3)/12)))))+SUM($F$12:$F$17)))/$F$10-(((NPV($H15,'DRE + DCF'!$V$36,'DRE + DCF'!$X$36:$AA$36)*((1+$H15)^((12-3)/12))+('DRE + DCF'!$AB$36*(1+R$18)/(($H15-R$18)*(1+$H15)^(COUNT('DRE + DCF'!$W$22:$AA$22)-((12-3)/12)))))*$F$40+$F$42)*(1-$F$39))/$F$10 -> 10.631204
A16: Projeções - CG + Capex | E16: Desconto de Holding | F16: =('Projeções - Receita e EBIT'!V133)/((WACC!P20)-3.5%)/'DRE + DCF'!AA37 -> -1549244.3 | H16: =H15+0.5% -> 0.12533014 | I16: =(((NPV($H16,'DRE + DCF'!$V$36,'DRE + DCF'!$X$36:$AA$36)*((1+$H16)^((12-3)/12))+('DRE + DCF'!$AB$36*(1+I$18)/(($H16-I$18)*(1+$H16)^(COUNT('DRE + DCF'!$W$22:$AA$22)-((12-3)/12)))))+SUM($F$12:$F$17)))/$F$10-(((NPV($H16,'DRE + DCF'!$V$36,'DRE + DCF'!$X$36:$AA$36)*((1+$H16)^((12-3)/12))+('DRE + DCF'!$AB$36*(1+I$18)/(($H16-I$18)*(1+$H16)^(COUNT('DRE + DCF'!$W$22:$AA$22)-((12-3)/12)))))*$F$40+$F$42)*(1-$F$39))/$F$10 -> 6.652546 | J16: =(((NPV($H16,'DRE + DCF'!$V$36,'DRE + DCF'!$X$36:$AA$36)*((1+$H16)^((12-3)/12))+('DRE + DCF'!$AB$36*(1+J$18)/(($H16-J$18)*(1+$H16)^(COUNT('DRE + DCF'!$W$22:$AA$22)-((12-3)/12)))))+SUM($F$12:$F$17)))/$F$10-(((NPV($H16,'DRE + DCF'!$V$36,'DRE + DCF'!$X$36:$AA$36)*((1+$H16)^((12-3)/12))+('DRE + DCF'!$AB$36*(1+J$18)/(($H16-J$18)*(1+$H16)^(COUNT('DRE + DCF'!$W$22:$AA$22)-((12-3)/12)))))*$F$40+$F$42)*(1-$F$39))/$F$10 -> 6.85933 | K16: =(((NPV($H16,'DRE + DCF'!$V$36,'DRE + DCF'!$X$36:$AA$36)*((1+$H16)^((12-3)/12))+('DRE + DCF'!$AB$36*(1+K$18)/(($H16-K$18)*(1+$H16)^(COUNT('DRE + DCF'!$W$22:$AA$22)-((12-3)/12)))))+SUM($F$12:$F$17)))/$F$10-(((NPV($H16,'DRE + DCF'!$V$36,'DRE + DCF'!$X$36:$AA$36)*((1+$H16)^((12-3)/12))+('DRE + DCF'!$AB$36*(1+K$18)/(($H16-K$18)*(1+$H16)^(COUNT('DRE + DCF'!$W$22:$AA$22)-((12-3)/12)))))*$F$40+$F$42)*(1-$F$39))/$F$10 -> 7.0835406 | L16: =(((NPV($H16,'DRE + DCF'!$V$36,'DRE + DCF'!$X$36:$AA$36)*((1+$H16)^((12-3)/12))+('DRE + DCF'!$AB$36*(1+L$18)/(($H16-L$18)*(1+$H16)^(COUNT('DRE + DCF'!$W$22:$AA$22)-((12-3)/12)))))+SUM($F$12:$F$17)))/$F$10-(((NPV($H16,'DRE + DCF'!$V$36,'DRE + DCF'!$X$36:$AA$36)*((1+$H16)^((12-3)/12))+('DRE + DCF'!$AB$36*(1+L$18)/(($H16-L$18)*(1+$H16)^(COUNT('DRE + DCF'!$W$22:$AA$22)-((12-3)/12)))))*$F$40+$F$42)*(1-$F$39))/$F$10 -> 7.3274775 | M16: =(((NPV($H16,'DRE + DCF'!$V$36,'DRE + DCF'!$X$36:$AA$36)*((1+$H16)^((12-3)/12))+('DRE + DCF'!$AB$36*(1+M$18)/(($H16-M$18)*(1+$H16)^(COUNT('DRE + DCF'!$W$22:$AA$22)-((12-3)/12)))))+SUM($F$12:$F$17)))/$F$10-(((NPV($H16,'DRE + DCF'!$V$36,'DRE + DCF'!$X$36:$AA$36)*((1+$H16)^((12-3)/12))+('DRE + DCF'!$AB$36*(1+M$18)/(($H16-M$18)*(1+$H16)^(COUNT('DRE + DCF'!$W$22:$AA$22)-((12-3)/12)))))*$F$40+$F$42)*(1-$F$39))/$F$10 -> 7.593864 | N16: =(((NPV($H16,'DRE + DCF'!$V$36,'DRE + DCF'!$X$36:$AA$36)*((1+$H16)^((12-3)/12))+('DRE + DCF'!$AB$36*(1+N$18)/(($H16-N$18)*(1+$H16)^(COUNT('DRE + DCF'!$W$22:$AA$22)-((12-3)/12)))))+SUM($F$12:$F$17)))/$F$10-(((NPV($H16,'DRE + DCF'!$V$36,'DRE + DCF'!$X$36:$AA$36)*((1+$H16)^((12-3)/12))+('DRE + DCF'!$AB$36*(1+N$18)/(($H16-N$18)*(1+$H16)^(COUNT('DRE + DCF'!$W$22:$AA$22)-((12-3)/12)))))*$F$40+$F$42)*(1-$F$39))/$F$10 -> 7.8859485 | O16: =(((NPV($H16,'DRE + DCF'!$V$36,'DRE + DCF'!$X$36:$AA$36)*((1+$H16)^((12-3)/12))+('DRE + DCF'!$AB$36*(1+O$18)/(($H16-O$18)*(1+$H16)^(COUNT('DRE + DCF'!$W$22:$AA$22)-((12-3)/12)))))+SUM($F$12:$F$17)))/$F$10-(((NPV($H16,'DRE + DCF'!$V$36,'DRE + DCF'!$X$36:$AA$36)*((1+$H16)^((12-3)/12))+('DRE + DCF'!$AB$36*(1+O$18)/(($H16-O$18)*(1+$H16)^(COUNT('DRE + DCF'!$W$22:$AA$22)-((12-3)/12)))))*$F$40+$F$42)*(1-$F$39))/$F$10 -> 8.2076381 | P16: =(((NPV($H16,'DRE + DCF'!$V$36,'DRE + DCF'!$X$36:$AA$36)*((1+$H16)^((12-3)/12))+('DRE + DCF'!$AB$36*(1+P$18)/(($H16-P$18)*(1+$H16)^(COUNT('DRE + DCF'!$W$22:$AA$22)-((12-3)/12)))))+SUM($F$12:$F$17)))/$F$10-(((NPV($H16,'DRE + DCF'!$V$36,'DRE + DCF'!$X$36:$AA$36)*((1+$H16)^((12-3)/12))+('DRE + DCF'!$AB$36*(1+P$18)/(($H16-P$18)*(1+$H16)^(COUNT('DRE + DCF'!$W$22:$AA$22)-((12-3)/12)))))*$F$40+$F$42)*(1-$F$39))/$F$10 -> 8.5636741 | ... R16: =(((NPV($H16,'DRE + DCF'!$V$36,'DRE + DCF'!$X$36:$AA$36)*((1+$H16)^((12-3)/12))+('DRE + DCF'!$AB$36*(1+R$18)/(($H16-R$18)*(1+$H16)^(COUNT('DRE + DCF'!$W$22:$AA$22)-((12-3)/12)))))+SUM($F$12:$F$17)))/$F$10-(((NPV($H16,'DRE + DCF'!$V$36,'DRE + DCF'!$X$36:$AA$36)*((1+$H16)^((12-3)/12))+('DRE + DCF'!$AB$36*(1+R$18)/(($H16-R$18)*(1+$H16)^(COUNT('DRE + DCF'!$W$22:$AA$22)-((12-3)/12)))))*$F$40+$F$42)*(1-$F$39))/$F$10 -> 9.4034181
A17: Projeções 2023 | E17: Passivo Judicial Capital Fechado | F17: =IF(F54>=0,0,F54) -> 0 | H17: =H16+0.5% -> 0.13033014 | I17: =(((NPV($H17,'DRE + DCF'!$V$36,'DRE + DCF'!$X$36:$AA$36)*((1+$H17)^((12-3)/12))+('DRE + DCF'!$AB$36*(1+I$18)/(($H17-I$18)*(1+$H17)^(COUNT('DRE + DCF'!$W$22:$AA$22)-((12-3)/12)))))+SUM($F$12:$F$17)))/$F$10-(((NPV($H17,'DRE + DCF'!$V$36,'DRE + DCF'!$X$36:$AA$36)*((1+$H17)^((12-3)/12))+('DRE + DCF'!$AB$36*(1+I$18)/(($H17-I$18)*(1+$H17)^(COUNT('DRE + DCF'!$W$22:$AA$22)-((12-3)/12)))))*$F$40+$F$42)*(1-$F$39))/$F$10 -> 6.1865515 | J17: =(((NPV($H17,'DRE + DCF'!$V$36,'DRE + DCF'!$X$36:$AA$36)*((1+$H17)^((12-3)/12))+('DRE + DCF'!$AB$36*(1+J$18)/(($H17-J$18)*(1+$H17)^(COUNT('DRE + DCF'!$W$22:$AA$22)-((12-3)/12)))))+SUM($F$12:$F$17)))/$F$10-(((NPV($H17,'DRE + DCF'!$V$36,'DRE + DCF'!$X$36:$AA$36)*((1+$H17)^((12-3)/12))+('DRE + DCF'!$AB$36*(1+J$18)/(($H17-J$18)*(1+$H17)^(COUNT('DRE + DCF'!$W$22:$AA$22)-((12-3)/12)))))*$F$40+$F$42)*(1-$F$39))/$F$10 -> 6.361528 | K17: =(((NPV($H17,'DRE + DCF'!$V$36,'DRE + DCF'!$X$36:$AA$36)*((1+$H17)^((12-3)/12))+('DRE + DCF'!$AB$36*(1+K$18)/(($H17-K$18)*(1+$H17)^(COUNT('DRE + DCF'!$W$22:$AA$22)-((12-3)/12)))))+SUM($F$12:$F$17)))/$F$10-(((NPV($H17,'DRE + DCF'!$V$36,'DRE + DCF'!$X$36:$AA$36)*((1+$H17)^((12-3)/12))+('DRE + DCF'!$AB$36*(1+K$18)/(($H17-K$18)*(1+$H17)^(COUNT('DRE + DCF'!$W$22:$AA$22)-((12-3)/12)))))*$F$40+$F$42)*(1-$F$39))/$F$10 -> 6.5501045 | L17: =(((NPV($H17,'DRE + DCF'!$V$36,'DRE + DCF'!$X$36:$AA$36)*((1+$H17)^((12-3)/12))+('DRE + DCF'!$AB$36*(1+L$18)/(($H17-L$18)*(1+$H17)^(COUNT('DRE + DCF'!$W$22:$AA$22)-((12-3)/12)))))+SUM($F$12:$F$17)))/$F$10-(((NPV($H17,'DRE + DCF'!$V$36,'DRE + DCF'!$X$36:$AA$36)*((1+$H17)^((12-3)/12))+('DRE + DCF'!$AB$36*(1+L$18)/(($H17-L$18)*(1+$H17)^(COUNT('DRE + DCF'!$W$22:$AA$22)-((12-3)/12)))))*$F$40+$F$42)*(1-$F$39))/$F$10 -> 6.7539305 | M17: =(((NPV($H17,'DRE + DCF'!$V$36,'DRE + DCF'!$X$36:$AA$36)*((1+$H17)^((12-3)/12))+('DRE + DCF'!$AB$36*(1+M$18)/(($H17-M$18)*(1+$H17)^(COUNT('DRE + DCF'!$W$22:$AA$22)-((12-3)/12)))))+SUM($F$12:$F$17)))/$F$10-(((NPV($H17,'DRE + DCF'!$V$36,'DRE + DCF'!$X$36:$AA$36)*((1+$H17)^((12-3)/12))+('DRE + DCF'!$AB$36*(1+M$18)/(($H17-M$18)*(1+$H17)^(COUNT('DRE + DCF'!$W$22:$AA$22)-((12-3)/12)))))*$F$40+$F$42)*(1-$F$39))/$F$10 -> 6.9749337 | N17: =(((NPV($H17,'DRE + DCF'!$V$36,'DRE + DCF'!$X$36:$AA$36)*((1+$H17)^((12-3)/12))+('DRE + DCF'!$AB$36*(1+N$18)/(($H17-N$18)*(1+$H17)^(COUNT('DRE + DCF'!$W$22:$AA$22)-((12-3)/12)))))+SUM($F$12:$F$17)))/$F$10-(((NPV($H17,'DRE + DCF'!$V$36,'DRE + DCF'!$X$36:$AA$36)*((1+$H17)^((12-3)/12))+('DRE + DCF'!$AB$36*(1+N$18)/(($H17-N$18)*(1+$H17)^(COUNT('DRE + DCF'!$W$22:$AA$22)-((12-3)/12)))))*$F$40+$F$42)*(1-$F$39))/$F$10 -> 7.2153812 | O17: =(((NPV($H17,'DRE + DCF'!$V$36,'DRE + DCF'!$X$36:$AA$36)*((1+$H17)^((12-3)/12))+('DRE + DCF'!$AB$36*(1+O$18)/(($H17-O$18)*(1+$H17)^(COUNT('DRE + DCF'!$W$22:$AA$22)-((12-3)/12)))))+SUM($F$12:$F$17)))/$F$10-(((NPV($H17,'DRE + DCF'!$V$36,'DRE + DCF'!$X$36:$AA$36)*((1+$H17)^((12-3)/12))+('DRE + DCF'!$AB$36*(1+O$18)/(($H17-O$18)*(1+$H17)^(COUNT('DRE + DCF'!$W$22:$AA$22)-((12-3)/12)))))*$F$40+$F$42)*(1-$F$39))/$F$10 -> 7.477957 | P17: =(((NPV($H17,'DRE + DCF'!$V$36,'DRE + DCF'!$X$36:$AA$36)*((1+$H17)^((12-3)/12))+('DRE + DCF'!$AB$36*(1+P$18)/(($H17-P$18)*(1+$H17)^(COUNT('DRE + DCF'!$W$22:$AA$22)-((12-3)/12)))))+SUM($F$12:$F$17)))/$F$10-(((NPV($H17,'DRE + DCF'!$V$36,'DRE + DCF'!$X$36:$AA$36)*((1+$H17)^((12-3)/12))+('DRE + DCF'!$AB$36*(1+P$18)/(($H17-P$18)*(1+$H17)^(COUNT('DRE + DCF'!$W$22:$AA$22)-((12-3)/12)))))*$F$40+$F$42)*(1-$F$39))/$F$10 -> 7.7658633 | ... R17: =(((NPV($H17,'DRE + DCF'!$V$36,'DRE + DCF'!$X$36:$AA$36)*((1+$H17)^((12-3)/12))+('DRE + DCF'!$AB$36*(1+R$18)/(($H17-R$18)*(1+$H17)^(COUNT('DRE + DCF'!$W$22:$AA$22)-((12-3)/12)))))+SUM($F$12:$F$17)))/$F$10-(((NPV($H17,'DRE + DCF'!$V$36,'DRE + DCF'!$X$36:$AA$36)*((1+$H17)^((12-3)/12))+('DRE + DCF'!$AB$36*(1+R$18)/(($H17-R$18)*(1+$H17)^(COUNT('DRE + DCF'!$W$22:$AA$22)-((12-3)/12)))))*$F$40+$F$42)*(1-$F$39))/$F$10 -> 8.433894
A18: Processos | E18: Valor da Ação | F18: =SUM($F$11:$F$17)/$F$10 -> 11.743778 | I18: =J18-0.25% -> 0.061 | J18: =K18-0.25% -> 0.0635 | K18: =L18-0.25% -> 0.066 | L18: =M18-0.25% -> 0.0685 | M18: ='DRE + DCF'!AD23 -> 0.071 | N18: =M18+0.25% -> 0.0735 | O18: =N18+0.25% -> 0.076 | P18: =O18+0.25% -> 0.0785 | Q18: =P18+0.25% -> 0.081 | R18: =Q18+0.25% -> 0.0835
E19: Cotação | F19: 6.16 | I19: Growth
E20: =IF(F20=0,"",IF(F20>0,"Upside","Downside")) -> Upside | F20: =IF(F18<0,"-",F18/F19-1) -> 0.90645746
E21: TIR | F21: 0.258
N24: Preço Teto | O24: 12.93 | P24: 11.31 | Q24: =O24/P24-1 -> 0.14323607
E25: Total Holding | F25: =SUM('Balanço Patrimonial'!P21,'Balanço Patrimonial'!P24+'Balanço Patrimonial'!P36+'Balanço Patrimonial'!P37) -> 12521834 | H25: Empresa | I25: Valor do Equity | J25: Participação Simpar | K25: Valor da Participação da Simpar | O25: =F18*(1-Q24) -> 10.061645
E26: JSL | F26: 3528272.2 | H26: JSL | I26: =SUM([1]Dashboard!$F$12:$F$16) -> 4067739.9 | J26: 0.7242 | K26: =I26*J26 -> 2945857.2
E27: Movida | F27: 2901197.7 | H27: Movida | I27: =SUM([2]Dashboard!$F$12:$F$15) -> 5221771.3 | J27: 0.6519 | K27: =I27*J27 -> 3404072.7
E28: Vamos | F28: 2415732.2 | H28: Vamos | I28: =SUM([3]Dashboard!$F$12:$F$15) -> 8896938.8 | J28: 0.6906 | K28: =I28*J28 -> 6144225.9
E29: Holding excluindo empresas de capital aberto | F29: =F25-SUM(F26:F28) -> 3676632.3 | H29: Total | K29: =SUM(K26:K28) -> 12494156
E32: Total Holding | F32: =WACC!F19 -> 55498129 | H32: Empresa | I32: Market Cap | J32: Participação Simpar | K32: Valor de mercado da Participação
E33: JSL | F33: -9650368 | H33: JSL | I33: =[1]Dashboard!$F$18*[1]Dashboard!$F$11 -> 3388479.7 | J33: =J26 -> 0.7242 | K33: =I33*J33 -> 2453937
E34: Movida | F34: -17964301 | H34: Movida | I34: =[2]Dashboard!$F$17*[2]Dashboard!$F$11 -> 2623067.1 | J34: =J27 -> 0.6519 | K34: =I34*J34 -> 1709977.4
E35: Vamos | F35: -14245979 | H35: Vamos | I35: =[3]Dashboard!$F$17*[3]Dashboard!$F$11 -> 9088591.2 | J35: =J28 -> 0.6906 | K35: =I35*J35 -> 6276581.1
E36: Holding excluindo empresas de capital aberto | F36: =SUM(F32:F35) -> 13637481 | H36: Simpar | I36: =F19*F10 -> 5377929.7 | J36: 1 | K36: =J36*I36 -> 5377929.7
H37: Empresas de Capital Fechado | K37: =K36-SUM(K33:K35) -> -5062565.8
E39: Participação da Simpar na Automob | F39: 0.794
E40: % médio do EBIT projetado que vem da Automob | F40: =AVERAGE('Projeções - Receita e EBIT'!$R$57:$V$57) -> 0.59655019
E41: Valor da Empresa da Automob baseado no EBIT | F41: =F11*F40 -> 6400863.9
E42: Dívida Líquida Automob | F42: 691700
E43: Valor do Equity Automob | F43: =F41+F42 -> 7092563.9
E44: Valor do Equity da Automob que não pertence à Simpar | F44: =F43*(1-$F$39) -> 1461068.2
E48: Total Holding | F48: =WACC!F35 -> 0
E49: JSL | F49: -528483
E50: Movida | F50: =[4]Dashboard!$F$15 -> 0
E51: Vamos | F51: -108010
E52: Holding excluindo empresas de capital aberto | F52: =SUM(F48:F51) -> -636493
E53: Holding | F53: =('Balanço Patrimonial'!P80-'Balanço Patrimonial'!P41)*-1 -> -631328
E54: Total Grupo | F54: =F53-F52 -> 5165

Sheet WACC
F3: =Dashboard!$H$3 -> SIMPAR (SIMH3)
A7: Páginas
A8: Dashboard
A9: WACC | E9: Atualizado em: 10/05/2024 | F9: 2024 | G9: =F9+1 -> 2025 | H9: =G9+1 -> 2026 | I9: =H9+1 -> 2027 | J9: =I9+1 -> 2028 | K9: =J9+1 -> 2029 | L9: =K9+1 -> 2030 | M9: =L9+1 -> 2031 | N9: =M9+1 -> 2032 | ... P9: =O9+1 -> 2034
A10: DRE Consolidado | E10: DI | F10: 0.1021 | G10: 0.1045 | H10: 0.10785 | I10: 0.1108 | J10: 0.11282 | K10: 0.1141 | L10: 0.11493 | M10: 0.1154 | N10: 0.11554 | O10: 0.1154 | P10: 0.1184
A11: DRE + DCF | E11: CDS | F11: 0.005192376 | G11: 0.007529595 | H11: 0.009825664 | I11: 0.012549005 | J11: 0.015362527 | K11: 0.017833094 | L11: 0.019839556 | M11: 0.021316616 | N11: 0.022198978 | O11: 0.022423308 | P11: 0.023871661
A12: DRE - Contas Abertas | E12: Inflação Implícita | F12: 0.04033 | G12: 0.03754 | H12: 0.04248 | I12: 0.04517 | J12: 0.0472 | K12: 0.04849 | L12: 0.05011 | M12: 0.05077 | N12: 0.05097 | O12: 0.05121 | P12: 0.05
A13: Balanço Patrimonial | E13: Taxa Livre de Risco | F13: =F10-F11 -> 0.096907624 | G13: =G10-G11 -> 0.096970405 | H13: =H10-H11 -> 0.098024336 | I13: =I10-I11 -> 0.098250995 | J13: =J10-J11 -> 0.097457473 | K13: =K10-K11 -> 0.096266906 | L13: =L10-L11 -> 0.095090444 | M13: =M10-M11 -> 0.094083384 | ... P13: =P10-P11 -> 0.094528339
A14: Painel de Índices | E14: Beta | F14: 2 | G14: =F14 -> 2 | H14: =G14 -> 2 | I14: =H14 -> 2 | J14: =I14 -> 2 | K14: =J14 -> 2 | L14: =K14 -> 2 | M14: =L14 -> 2 | N14: =M14 -> 2 | ... P14: =O14 -> 2
A15: Projeções - Receita e EBIT | E15: Prêmio de Risco | F15: 0.065 | G15: 0.065 | H15: 0.065 | I15: 0.065 | J15: 0.065 | K15: 0.065 | L15: 0.065 | M15: 0.065 | N15: 0.065 | O15: 0.065 | P15: 0.065
A16: Projeções - CG + Capex | E16: Custo de Capital Próprio (Ke) | F16: =F13+(F14*F15) -> 0.22690762 | G16: =G13+(G14*G15) -> 0.2269704 | H16: =H13+(H14*H15) -> 0.22802434 | I16: =I13+(I14*I15) -> 0.228251 | J16: =J13+(J14*J15) -> 0.22745747 | K16: =K13+(K14*K15) -> 0.22626691 | L16: =L13+(L14*L15) -> 0.22509044 | M16: =M13+(M14*M15) -> 0.22408338 | ... P16: =P13+(P14*P15) -> 0.22452834
A17: Projeções 2023 | E17: Valor Justo do Equity (R$ Mil) | F17: =Dashboard!F19*Dashboard!F10 -> 5377929.7 | G17: =F17 -> 5377929.7 | H17: =G17 -> 5377929.7 | I17: =H17 -> 5377929.7 | J17: =I17 -> 5377929.7 | K17: =J17 -> 5377929.7 | L17: =K17 -> 5377929.7 | M17: =L17 -> 5377929.7 | N17: =M17 -> 5377929.7 | ... P17: =O17 -> 5377929.7
A18: Processos | E18: Custo de Capital de Terceiros (Kd) | F18: =F10+3.2% -> 0.1341 | G18: =G10+3.2% -> 0.1365 | H18: =H10+3.2% -> 0.13985 | I18: =I10+3.2% -> 0.1428 | J18: =J10+3.2% -> 0.14482 | K18: =K10+3.2% -> 0.1461 | L18: =L10+3.2% -> 0.14693 | M18: =M10+3.2% -> 0.1474 | ... P18: =P10+3.2% -> 0.1504
E19: Dívida Bruta (R$ Mil) | F19: =SUM('Balanço Patrimonial'!P54:P60,'Balanço Patrimonial'!P63,'Balanço Patrimonial'!P72:P76,'Balanço Patrimonial'!P78,'Balanço Patrimonial'!P85) -> 55498129 | G19: =SUM('Balanço Patrimonial'!P54:P60,'Balanço Patrimonial'!P63,'Balanço Patrimonial'!P72:P76,'Balanço Patrimonial'!P78,'Balanço Patrimonial'!P85) -> 55498129 | H19: =G19 -> 55498129 | I19: =H19 -> 55498129 | J19: =I19 -> 55498129 | K19: =J19 -> 55498129 | L19: =K19 -> 55498129 | M19: =L19 -> 55498129 | N19: =M19 -> 55498129 | O19: =N19 -> 55498129 | P19: =O19 -> 55498129
E20: WACC | F20: =((F16*F17)+(F18*F19*(1-'DRE + DCF'!W23)))/(F17+F19) -> 0.10073271 | G20: =((G16*G17)+(G18*G19*(1-'DRE + DCF'!X23)))/(G17+G19) -> 0.10218233 | H20: =((H16*H17)+(H18*H19*(1-'DRE + DCF'!Y23)))/(H17+H19) -> 0.10429111 | I20: =((I16*I17)+(I18*I19*(1-'DRE + DCF'!Z23)))/(I17+I19) -> 0.10608613 | J20: =((J16*J17)+(J18*J19*(1-'DRE + DCF'!$AA$23)))/(J17+J19) -> 0.10723145 | K20: =((K16*K17)+(K18*K19*(1-'DRE + DCF'!$AA$23)))/(K17+K19) -> 0.10789644 | L20: =((L16*L17)+(L18*L19*(1-'DRE + DCF'!$AA$23)))/(L17+L19) -> 0.10829192 | M20: =((M16*M17)+(M18*M19*(1-'DRE + DCF'!$AA$23)))/(M17+M19) -> 0.10848575 | N20: =((N16*N17)+(N18*N19*(1-'DRE + DCF'!$AA$23)))/(N17+N19) -> 0.1085044 | O20: =((O16*O17)+(O18*O19*(1-'DRE + DCF'!$AA$23)))/(O17+O19) -> 0.10838798 | P20: =((P16*P17)+(P18*P19*(1-'DRE + DCF'!$AA$23)))/(P17+P19) -> 0.11033014
E21: Desconto | F21: =1*(1+F20)^((9)/12) -> 1.0746361 | G21: =F21*(1+G20) -> 1.1844449 | H21: =G21*(1+H20) -> 1.3079719 | I21: =H21*(1+I20) -> 1.4467296 | J21: =I21*(1+J20) -> 1.6018645 | K21: =J21*(1+K20) -> 1.7747 | L21: =K21*(1+L20) -> 1.9668857 | M21: =L21*(1+M20) -> 2.1802647 | N21: =M21*(1+N20) -> 2.4168331 | ... P21: =O21*(1+P20) -> 2.9743398

Sheet DRE Consolidado
K2: =Dashboard!H3 -> SIMPAR (SIMH3)
A7: Páginas
A8: Dashboard
A9: WACC
A10: DRE Consolidado
A11: DRE + DCF
A12: DRE - Contas Abertas | E12: Data do Último Resultado: | K12: 2014 | L12: 2015 | M12: 2016 | N12: 2017 | O12: 2018 | P12: 2019 | Q12: 2020 | R12: 2021 | S12: 2022 | T12: 2023 | U12: YTD 2024 | V12: YTG 2024E | W12: 2024 | X12: =W12+1 -> 2025 | Y12: =X12+1 -> 2026 | Z12: =Y12+1 -> 2027 | AA12: =Z12+1 -> 2028
A13: Balanço Patrimonial | E13: Receita Bruta | K13: 6079086.1 | L13: 6561486.7 | M13: 7403983 | N13: 8199829 | O13: 9203466 | P13: 10734355 | Q13: 10874860 | R13: 15453380 | S13: 26844012 | T13: 35513417
A14: Painel de Índices | E14: Deduções | K14: =-(K13-K16) -> -539892.08 | L14: =-(L13-L16) -> -571574.68 | M14: =-(M13-M16) -> -880867 | N14: =-(N13-N16) -> -944025 | O14: =-(O13-O16) -> -1128077 | P14: =-(P13-P16) -> -1048146.5 | Q14: =-(Q13-Q16) -> -1067803 | R14: =-(R13-R16) -> -1587161 | S14: -2462220.7 | T14: -2462220.7
A15: Projeções - Receita e EBIT | E15: % da Receita Bruta | K15: =-K14/K13 -> 0.088811389 | L15: =-L14/L13 -> 0.087110545 | M15: =-M14/M13 -> 0.11897205 | N15: =-N14/N13 -> 0.1151274 | O15: =-O14/O13 -> 0.12257089 | P15: =-P14/P13 -> 0.097644102 | Q15: =-Q14/Q13 -> 0.098190046 | R15: =-R14/R13 -> 0.1027064 | ... T15: =-T14/T13 -> 0.069332126
A16: Projeções - CG + Capex | E16: Receita Líquida | K16: 5539194 | L16: 5989912 | M16: 6523116 | N16: 7255804 | O16: 8075389 | P16: 9686209 | Q16: 9807057 | R16: 13866219 | S16: 24381791 | T16: 31843613 | U16: 9146986 | V16: =W16-SUM(U16:U16) -> 28759355 | W16: ='Projeções - Receita e EBIT'!R10 -> 37906341 | X16: ='Projeções - Receita e EBIT'!S10 -> 43423210 | Y16: ='Projeções - Receita e EBIT'!T10 -> 50252034 | Z16: ='Projeções - Receita e EBIT'!U10 -> 55355892 | AA16: ='Projeções - Receita e EBIT'!V10 -> 60832681
A17: Projeções 2023 | E17: Crescimento da Receita (YoY)¹ | K17: 0 | L17: =L16/K16-1 -> 0.081368878 | M17: =M16/L16-1 -> 0.089017001 | N17: =N16/M16-1 -> 0.11232178 | O17: =O16/N16-1 -> 0.11295578 | P17: =P16/O16-1 -> 0.19947274 | Q17: =Q16/P16-1 -> 0.012476295 | R17: =R16/Q16-1 -> 0.41390215 | S17: =S16/R16-1 -> 0.758359 | T17: =T16/S16-1 -> 0.30604077 | W17: =W16/T16-1 -> 0.19039071 | X17: =X16/W16-1 -> 0.14553946 | Y17: =Y16/X16-1 -> 0.15726208 | Z17: =Z16/Y16-1 -> 0.10156521 | AA17: =AA16/Z16-1 -> 0.098937782
A18: Processos | E18: Custos das Vendas e Serviços | K18: -3865141 | L18: -3974936 | M18: -3936687 | N18: -4032052 | O18: -4699220 | P18: -5102646 | Q18: -5168883 | R18: -7304534 | S18: -12624428 | T18: -23669760 | U18: -6677400
E19: Custo de Construção | F19: Custo de Construção | U19: 0
A20: Gráficos | E20: Custo de Venda de Ativos Desmobilizados | K20: -681231 | L20: -877618 | M20: -1289069 | N20: -1737637 | O20: -1609867 | P20: -2524180 | Q20: -2618101 | R20: -2077780 | S20: -4166192 | U20: 0
E21: Lucro Bruto | K21: =K16+K18+K20 -> 992822 | L21: =L16+L18+L20 -> 1137358 | M21: =M16+M18+M20 -> 1297360 | N21: =N16+N18+N20 -> 1486115 | O21: =O16+O18+O20 -> 1766302 | P21: =P16+P18+P20 -> 2059383 | Q21: =Q16+Q18+Q20 -> 2020073 | R21: =R16+R18+R20 -> 4483905 | ... T21: =T16+T18+T20 -> 8173853 | U21: =U16+U18+U19+U20 -> 2469586
E22: Margem Bruta | K22: =K21/K16 -> 0.17923582 | L22: =L21/L16 -> 0.18987892 | M22: =M21/M16 -> 0.19888654 | N22: =N21/N16 -> 0.20481741 | O22: =O21/O16 -> 0.21872655 | P22: =P21/P16 -> 0.2126098 | Q22: =Q21/Q16 -> 0.20598157 | R22: =R21/R16 -> 0.32336897 | ... U22: =U21/U16 -> 0.26998904
E23: Despesas/ Receitas Operacionais | K23: =SUM(K24,K26,K28,K29,K32) -> -532720 | L23: =SUM(L24,L26,L28,L29,L32) -> -553903 | M23: =SUM(M24,M26,M28,M29,M32) -> -798577 | N23: =SUM(N24,N26,N28,N29,N32) -> -781645 | O23: =SUM(O24,O26,O28,O29,O32) -> -805585 | P23: =SUM(P24,P26,P28,P29,P32) -> -860218 | Q23: =SUM(Q24,Q26,Q28,Q29,Q32) -> -990091 | R23: =SUM(R24,R26,R28,R29,R32) -> -1353354 | ... U23: =SUM(U24,U26,U28,U29,U32) -> -891623
E24: Despesas Tributárias | K24: -8093 | L24: -9584 | M24: 0 | N24: 0 | O24: 0 | P24: 0 | Q24: 0 | R24: 0 | S24: 0 | U24: 0
E25: (%) da Receita Líquida | K25: =-K24/K16 -> 0.0014610429 | L25: =-L24/L16 -> 0.0016000235 | M25: =-M24/M16 -> 0 | N25: =-N24/N16 -> 0 | O25: =-O24/O16 -> 0 | P25: =-P24/P16 -> 0 | Q25: =-Q24/Q16 -> 0 | R25: =-R24/R16 -> 0 | ... U25: =-U24/U16 -> 0
E26: Despesas Comerciais Gerais e Administrativas | K26: -491535 | L26: -510134 | M26: -684175 | N26: -746102 | O26: -794421 | P26: =-571098-293107 -> -864205 | Q26: -896692 | R26: -1398455 | S26: =-884377-1397532 -> -2281909 | T26: =-1217597-2064530 -> -3282127 | U26: =-349090-452112 -> -801202
E27: (%) da Receita Líquida | K27: =-K26/K16 -> 0.088737639 | L27: =-L26/L16 -> 0.085165525 | M27: =-M26/M16 -> 0.10488469 | N27: =-N26/N16 -> 0.1028283 | O27: =-O26/O16 -> 0.098375571 | P27: =-P26/P16 -> 0.089220148 | Q27: =-Q26/Q16 -> 0.091433342 | R27: =-R26/R16 -> 0.10085338 | ... U27: =-U26/U16 -> 0.087591913
E28: Perdas pela Não Recuperabilidade de Ativos | K28: 0 | L28: 0 | M28: 0 | N28: 0 | O28: -9146 | P28: -32527 | Q28: -78667 | R28: -56164 | S28: -127315 | T28: -184393 | U28: -53232
E29: Resultado Operacional Outros | K29: =SUM(K30:K31) -> -33186 | L29: =SUM(L30:L31) -> -34256 | M29: =SUM(M30:M31) -> -114402 | N29: =SUM(N30:N31) -> -35543 | O29: =SUM(O30:O31) -> -1058 | P29: =SUM(P30:P31) -> 37715 | Q29: =SUM(Q30:Q31) -> -14217 | R29: =SUM(R30:R31) -> 102799 | ... U29: =SUM(U30:U31) -> -36142
E30: Outras Receitas Operacionais | K30: -33186 | L30: -34256 | M30: -114402 | N30: -35543 | O30: -1058 | P30: 37715 | Q30: -14217 | R30: 102799 | S30: 0 | T30: 182011 | U30: 0
E31: Outras Despesas Operacionais | K31: 0 | L31: 0 | M31: 0 | N31: 0 | O31: 0 | P31: 0 | Q31: 0 | R31: 0 | S31: -67941 | U31: -36142
E32: Resultado de Equivalência Patrimonial | K32: 94 | L32: 71 | M32: 0 | N32: 0 | O32: -960 | P32: -1201 | Q32: -515 | R32: -1534 | S32: 2810 | T32: 5327 | U32: -1047
E33: EBITDA | K33: =K35+K56+'Projeções - CG + Capex'!K57 -> 868967 | L33: =L35+L56+'Projeções - CG + Capex'!L57 -> 1092081 | M33: =M35+M56+'Projeções - CG + Capex'!M57 -> 1045970 | N33: =N35+N56+'Projeções - CG + Capex'!N57 -> 1230201 | O33: =O35+O56+'Projeções - CG + Capex'!O57 -> 1597534 | P33: =P35+P56+'Projeções - CG + Capex'!P57 -> 2115909 | Q33: =Q35+Q56+'Projeções - CG + Capex'!Q57 -> 2141935 | R33: =R35+R56+'Projeções - CG + Capex'!R57 -> 4189665 | ... U33: =U35+U56+'Projeções - CG + Capex'!U57 -> 2391544 | W33: ='DRE Consolidado'!W76 -> 10673112 | X33: ='DRE Consolidado'!X76 -> 12207507 | Y33: ='DRE Consolidado'!Y76 -> 13530227 | Z33: ='DRE Consolidado'!Z76 -> 14681135 | AA33: ='DRE Consolidado'!AA76 -> 15843161
E34: Margem EBITDA | K34: =K33/K16 -> 0.15687607 | L34: =L33/L16 -> 0.18232004 | M34: =M33/M16 -> 0.16034821 | N34: =N33/N16 -> 0.16954717 | O34: =O33/O16 -> 0.1978275 | P34: =P33/P16 -> 0.21844552 | Q34: =Q33/Q16 -> 0.21840752 | R34: =R33/R16 -> 0.30214906 | ... U34: =U33/U16 -> 0.26145705 | V34: =U34 -> 0.26145705
E35: EBIT | K35: =K21+K23 -> 460102 | L35: =L21+L23 -> 583455 | M35: =M21+M23 -> 498783 | N35: =N21+N23 -> 704470 | O35: =O21+O23 -> 960717 | P35: =P21+P23 -> 1199165 | Q35: =Q21+Q23 -> 1029982 | R35: =R21+R23 -> 3130551 | ... U35: =U21+U23 -> 1577963 | V35: =V16*V38 -> 4983198.7
E36: Eventos não Recorrentes | K36: ='DRE - Contas Abertas'!F56 -> -24516 | L36: ='DRE - Contas Abertas'!I56 -> 34204 | M36: ='DRE - Contas Abertas'!J56 -> 30444 | N36: ='DRE - Contas Abertas'!I56 -> 34204 | O36: ='DRE - Contas Abertas'!J56 -> 30444 | P36: ='DRE - Contas Abertas'!K56 -> -929 | Q36: ='DRE - Contas Abertas'!L56 -> -141683 | R36: ='DRE - Contas Abertas'!M56 -> 107566 | S36: ='DRE - Contas Abertas'!N56 -> 12526 | T36: ='DRE - Contas Abertas'!O56 -> -16503 | U36: ='DRE - Contas Abertas'!P56 -> -6956
E37: EBIT Recorrente | K37: =SUM(K35-K36) -> 484618 | L37: =SUM(L35-L36) -> 549251 | M37: =SUM(M35-M36) -> 468339 | N37: =SUM(N35-N36) -> 670266 | O37: =SUM(O35-O36) -> 930273 | P37: =SUM(P35-P36) -> 1200094 | Q37: =SUM(Q35-Q36) -> 1171665 | R37: =SUM(R35-R36) -> 3022985 | ... U37: =SUM(U35-U36) -> 1584919 | V37: =V35 -> 4983198.7
E38: Margem EBIT | K38: =K37/K16 -> 0.087488902 | L38: =L37/L16 -> 0.091696005 | M38: =M37/M16 -> 0.071796822 | N38: =N37/N16 -> 0.092376531 | O38: =O37/O16 -> 0.11519854 | P38: =P37/P16 -> 0.12389718 | Q38: =Q37/Q16 -> 0.11947162 | R38: =R37/R16 -> 0.21801076 | ... U38: =U37/U16 -> 0.17327227 | V38: =U38 -> 0.17327227
E39: Resultado Financeiro | K39: =SUM(K40:K41) -> -348965 | L39: =SUM(L40:L41) -> -516233 | M39: =SUM(M40:M41) -> -748253 | N39: =SUM(N40:N41) -> -670541 | O39: =SUM(O40:O41) -> -681219 | P39: =SUM(P40:P41) -> -768039 | Q39: =SUM(Q40:Q41) -> -374776 | R39: =SUM(R40:R41) -> -1217593 | ... U39: =SUM(U40:U41) -> -1476938
E40: Receitas Financeiras | K40: 109484 | L40: 198480 | M40: 201723 | N40: 209555 | O40: 317809 | P40: 365336 | Q40: 679426 | R40: 736362 | S40: 1229042 | T40: 1137502 | U40: 356775
E41: Despesas Financeiras | K41: -458449 | L41: -714713 | M41: -949976 | N41: -880096 | O41: -999028 | P41: -1133375 | Q41: -1054202 | R41: -1953955 | S41: -5358473 | T41: -7031228 | U41: -1833713
E42: Resultado Antes dos Tributos Sobre o Lucro | K42: =K35+K39 -> 111137 | L42: =L35+L39 -> 67222 | M42: =M35+M39 -> -249470 | N42: =N35+N39 -> 33929 | O42: =O35+O39 -> 279498 | P42: =P35+P39 -> 431126 | Q42: =Q35+Q39 -> 655206 | R42: =R35+R39 -> 1912958 | ... U42: =U35+U39 -> 101025
E43: Imposto de Renda e CSLL | K43: =K44+K45 -> -38697 | L43: =L44+L45 -> -20461 | M43: =M44+M45 -> 66296 | N43: =N44+N45 -> -17211 | O43: =O44+O45 -> -90328 | P43: =P44+P45 -> -112501 | Q43: =Q44+Q45 -> -229167 | R43: =R44+R45 -> -584008 | ... U43: =U44+U45 -> -10923
E44: Corrente | K44: -19885 | L44: -13925 | M44: -21844 | N44: -30178 | O44: -72495 | P44: -68869 | Q44: -177605 | R44: -126774 | S44: -117262 | T44: -85675 | U44: -70729
E45: Diferido | K45: -18812 | L45: -6536 | M45: 88140 | N45: 12967 | O45: -17833 | P45: -43632 | Q45: -51562 | R45: -457234 | S45: 70584 | T45: 462880 | U45: 59806
E46: Resultado Líquido de Operações Continuadas | K46: =K42+K43 -> 72440 | L46: =L42+L43 -> 46761 | M46: =M42+M43 -> -183174 | N46: =N42+N43 -> 16718 | O46: =O42+O43 -> 189170 | P46: =P42+P43 -> 318625 | Q46: =Q42+Q43 -> 426039 | R46: =R42+R43 -> 1328950 | ... U46: =U42+U43 -> 90102
E47: Lucro das operações descontinuadas, líquido de impostos | F47: Atribuído a Sócios da Empresa Controladora | K47: 0 | L47: 0 | M47: 0 | N47: 0 | O47: 0 | P47: 0 | Q47: -28539 | R47: 0
E48: Participação de não controladores | K48: 1 | L48: 1 | M48: 0 | N48: 0 | O48: 0 | P48: 0 | Q48: 0 | R48: 0
E49: Lucro Líquido do exercício | K49: =SUM(K46:K48) -> 72441 | L49: =SUM(L46:L48) -> 46762 | M49: =SUM(M46:M48) -> -183174 | N49: =SUM(N46:N48) -> 16718 | O49: =SUM(O46:O48) -> 189170 | P49: =SUM(P46:P48) -> 318625 | Q49: =SUM(Q46:Q48) -> 397500 | R49: =SUM(R46:R48) -> 1328950 | ... U49: =SUM(U46:U48) -> 90102
E50: Margem Líquida | K50: =K46/K16 -> 0.013077715 | L50: =L46/L16 -> 0.0078066255 | M50: =M46/M16 -> -0.028080752 | N50: =N46/N16 -> 0.0023040865 | O50: =O46/O16 -> 0.023425497 | P50: =P46/P16 -> 0.032894706 | Q50: =Q46/Q16 -> 0.043442085 | R50: =R46/R16 -> 0.095840834 | ... U50: =U46/U16 -> 0.0098504578
K54: 2014 | L54: 2015 | M54: 2016 | N54: 2017 | O54: 2018 | P54: 2019 | Q54: 2020 | R54: 2021 | S54: 2022 | T54: 2023 | U54: YTD 2024 | V54: YTG 2024E | W54: 2024 | X54: =W54+1 -> 2025 | Y54: =X54+1 -> 2026 | Z54: =Y54+1 -> 2027 | AA54: =Z54+1 -> 2028
E55: Alíquota Efetiva | F55: 0.030034188 | G55: -0.02092541 | H55: -0.043315116 | I55: 0.13811998 | J55: -0.59211219 | K55: =IFERROR(IF(K35>0,-K43/K35,"-"),"-") -> 0.084105264 | L55: =IFERROR(IF(L35>0,-L43/L35,"-"),"-") -> 0.035068686 | M55: =IFERROR(IF(M35>0,-M43/M35,"-"),"-") -> -0.13291552 | N55: =IFERROR(IF(N35>0,-N43/N35,"-"),"-") -> 0.024431133 | O55: =IFERROR(IF(O35>0,-O43/O35,"-"),"-") -> 0.094021444 | P55: =IFERROR(IF(P35>0,-P43/P35,"-"),"-") -> 0.093816114 | Q55: =IFERROR(IF(Q35>0,-Q43/Q35,"-"),"-") -> 0.22249612 | R55: =IFERROR(IF(R35>0,-R43/R35,"-"),"-") -> 0.18655119 | ... V55: =IFERROR(IF(V35>0,-V43/V35,"-"),"-") -> 0 | W55: =AVERAGE($P$55:$S$55) -> 0.12799647
E56: D&A do Arrendamento | P56: ='Projeções - CG + Capex'!P48 -> 127308 | Q56: ='Projeções - CG + Capex'!Q48 -> 129146 | R56: ='Projeções - CG + Capex'!R48 -> 186383 | S56: ='Projeções - CG + Capex'!S48 -> 199519 | T56: ='Projeções - CG + Capex'!T48 -> 357907 | U56: ='Projeções - CG + Capex'!U48 -> 98340 | V56: ='Projeções - CG + Capex'!U48 -> 98340 | W56: =W57*W16 -> 502302.22
E57: D&A do Arrendamento como (%) da Receita | K57: =K56/K16 -> 0 | L57: =L56/L16 -> 0 | M57: =M56/M16 -> 0 | N57: =N56/N16 -> 0 | O57: =O56/O16 -> 0 | P57: =P56/P16 -> 0.013143222 | Q57: =Q56/Q16 -> 0.01316868 | R57: =R56/R16 -> 0.013441516 | ... V57: =V56/V16 -> 0.0034194091 | W57: =AVERAGE(P57:R57) -> 0.01325114
E58: NOPAT | F58: 215718 | G58: 230388 | H58: 181530 | I58: -272310 | J58: -42610 | K58: =K37+K43+K56 -> 445921 | L58: =L37+L43+L56 -> 528790 | M58: =M37+M43+M56 -> 534635 | N58: =N37+N43+N56 -> 653055 | O58: =O37+O43+O56 -> 839945 | P58: =P37+P43+P56 -> 1214901 | Q58: =Q37+Q43+Q56 -> 1071644 | R58: =R37+R43+R56 -> 2625360 | ... V58: =V37+V43+V56 -> 5081538.7
K62: 2014 | L62: 2015 | M62: 2016 | N62: 2017 | O62: 2018 | P62: 2019 | Q62: 2020 | R62: 2021 | S62: 2022 | T62: 2023 | U62: YTD 2024 | V62: YTG 2024E | W62: 2024 | X62: =W62+1 -> 2025 | Y62: =X62+1 -> 2026 | Z62: =Y62+1 -> 2027 | AA62: =Z62+1 -> 2028
E63: JSL | F63: 0.030034188 | G63: -0.02092541 | H63: -0.043315116 | I63: 0.13811998 | J63: -0.59211219 | N63: 569446 | O63: 479168.73 | P63: 171363.26 | Q63: 43916.532 | R63: -883487.04 | S63: 78146 | T63: -839578 | U63: -199025.66 | V63: -816025.97 | W63: -874796.62 | X63: -424255.69 | Y63: -212381.38 | Z63: 366115 | AA63: 771281.76
E64: Movida | N64: -478120.25 | O64: -575059.4 | P64: -682431.13 | Q64: -773022 | R64: -3740226 | S64: -3112013.1 | T64: 1864502 | U64: 1059446 | V64: 1477124.6 | W64: -441486.62 | X64: 405703.94 | Y64: 223302.82 | Z64: -40989.664 | AA64: -2780.2915
E65: Vamos | N65: 18384.976 | O65: -78986.538 | P65: -280288.13 | Q65: -10630.655 | R65: -2176840.3 | S65: -2191416.2 | T65: -4231740 | U65: -905322.49 | V65: -1367519.3 | W65: -1295653.8 | X65: -223959.72 | Y65: 196890.09 | Z65: 734271.85 | AA65: 1060195.5
E66: Capital Fechado | O66: ='DRE + DCF'!O36 -> -136695.34 | P66: ='DRE + DCF'!P36 -> -170206 | Q66: ='DRE + DCF'!Q36 -> 19586.008 | R66: ='DRE + DCF'!R36 -> -742156.37 | S66: ='DRE + DCF'!S36 -> -1997146 | T66: ='DRE + DCF'!T36 -> -5014840.1 | U66: ='DRE + DCF'!U36 -> -334459.39 | V66: ='DRE + DCF'!V36 -> -347388.36 | ... AA66: ='DRE + DCF'!AA36 -> 1197536.3
E67: Total | F67: 215718 | G67: 230388 | H67: 181530 | I67: -272310 | J67: -42610 | N67: =SUM(N63:N66) -> 109710.73 | O67: =SUM(O63:O66) -> -311572.54 | P67: =SUM(P63:P66) -> -961561.99 | Q67: =SUM(Q63:Q66) -> -720150.11 | R67: =SUM(R63:R66) -> -7542709.7 | S67: =SUM(S63:S66) -> -7222429.3 | T67: =SUM(T63:T66) -> -8221656.1 | U67: =SUM(U63:U66) -> -379361.55 | ... AA67: =SUM(AA63:AA66) -> 3026233.3
K71: 2014 | L71: 2015 | M71: 2016 | N71: 2017 | O71: 2018 | P71: 2019 | Q71: 2020 | R71: 2021 | S71: 2022 | T71: 2023 | U71: YTD 2024 | V71: YTG 2024E | W71: 2024 | X71: =W71+1 -> 2025 | Y71: =X71+1 -> 2026 | Z71: =Y71+1 -> 2027 | AA71: =Z71+1 -> 2028
E72: JSL | F72: 0.030034188 | G72: -0.02092541 | H72: -0.043315116 | I72: 0.13811998 | J72: -0.59211219 | N72: 378729 | O72: 406833.83 | P72: 512702.29 | Q72: 431386 | R72: 758072.49 | S72: 1079820 | T72: 1727990 | U72: 396041 | V72: 1499530 | W72: 1499529.7 | X72: 1769388.4 | Y72: 2042282.7 | Z72: 2298436.8 | AA72: 2515195.8
E73: Movida | N73: 326351 | O73: 481738 | P73: 743193 | Q73: 717181 | R73: 2082987 | S73: 3551973 | T73: 3499246 | U73: 1059446 | V73: 3271231.9 | W73: 4154597.4 | X73: 4193881.4 | Y73: 4147799.6 | Z73: 4389413.5 | AA73: 4650008.1
E74: Vamos | N74: 304993 | O74: 426119 | P74: 527624 | Q74: 638774 | R74: 1049744 | S74: 1933140 | T74: 2668133 | U74: 819772 | V74: 3455787.7 | W74: 3455787.7 | X74: 4436069.1 | Y74: 5420961.8 | Z74: 5946192.3 | AA74: 6490058.6
E75: Capital Fechado | O75: ='DRE + DCF'!O14 -> 278146 | P75: ='DRE + DCF'!P14 -> 339526 | Q75: ='DRE + DCF'!Q14 -> 354594 | R75: ='DRE + DCF'!R14 -> 298861 | S75: ='DRE + DCF'!S14 -> 590052 | T75: ='DRE + DCF'!T14 -> 477484.88 | U75: ='DRE + DCF'!U14 -> 99646 | V75: ='DRE + DCF'!V14 -> 1463550.7 | ... AA75: ='DRE + DCF'!AA14 -> 2187898.9
E76: Total | F76: 215718 | G76: 230388 | H76: 181530 | I76: -272310 | J76: -42610 | N76: =SUM(N72:N75) -> 1010073 | O76: =SUM(O72:O75) -> 1592836.8 | P76: =SUM(P72:P75) -> 2123045.3 | Q76: =SUM(Q72:Q75) -> 2141935 | R76: =SUM(R72:R75) -> 4189664.5 | S76: =SUM(S72:S75) -> 7154985 | T76: =SUM(T72:T75) -> 8372853.9 | U76: =SUM(U72:U75) -> 2374905 | ... AA76: =SUM(AA72:AA75) -> 15843161
E78: ¹- "YoY", ou "year over year", significa "de um ano pro outro".

Sheet DRE + DCF
K2: =Dashboard!H3 -> SIMPAR (SIMH3)
A7: Páginas
A8: Dashboard
A9: WACC
A10: DRE Consolidado
A11: DRE + DCF
A12: DRE - Contas Abertas | K12: 2014 | L12: 2015 | M12: 2016 | N12: 2017 | O12: 2018 | P12: 2019 | Q12: 2020 | R12: 2021 | S12: 2022 | T12: 2023 | U12: YTD 2024 | V12: YTG 2024E | W12: 2024 | X12: =W12+1 -> 2025 | Y12: =X12+1 -> 2026 | Z12: =Y12+1 -> 2027 | AA12: =Z12+1 -> 2028
A13: Balanço Patrimonial | E13: Receita Líquida Ex empresas de capital aberto | O13: =SUM('Projeções - Receita e EBIT'!J16:J22) -> 1415123 | P13: =SUM('Projeções - Receita e EBIT'!K16:K22) -> 1536679 | Q13: =SUM('Projeções - Receita e EBIT'!L16:L22) -> 1381814 | R13: =SUM('Projeções - Receita e EBIT'!M16:M22) -> 1414123 | S13: =SUM('Projeções - Receita e EBIT'!N16:N22) -> 3845902 | T13: =SUM('Projeções - Receita e EBIT'!O16:O22) -> 7841471 | U13: =SUM('Projeções - Receita e EBIT'!P16:P22) -> 2328887 | V13: =W13-U13 -> 7248647.8 | W13: =SUM('Projeções - Receita e EBIT'!R16:R22) -> 9577534.8 | X13: =SUM('Projeções - Receita e EBIT'!S16:S22) -> 10339893 | Y13: =SUM('Projeções - Receita e EBIT'!T16:T22) -> 10898010 | Z13: =SUM('Projeções - Receita e EBIT'!U16:U22) -> 11565348 | AA13: =SUM('Projeções - Receita e EBIT'!V16:V22) -> 12301821
E14: EBITDA Excluindo Empresas de Capital Aberto | O14: =O15+O24+O32 -> 278146 | P14: =P15+P24+P32 -> 339526 | Q14: =Q15+Q24+Q32 -> 354594 | R14: =R15+R24+R32 -> 298861 | S14: =S15+S24+S32 -> 590052 | T14: =T15+T24+T32 -> 477484.88 | U14: =U15+U24+U32 -> 99646 | V14: =V15+V24+V32 -> 1463550.7 | ... AA14: =AA15+AA24+AA32 -> 2187898.9
A15: Painel de Índices | E15: EBIT Recorrente Excluindo Empresas de Capital Aberto | O15: =SUM('Projeções - Receita e EBIT'!J37+'Projeções - Receita e EBIT'!J56+'Projeções - Receita e EBIT'!J75+'Projeções - Receita e EBIT'!J98+'Projeções - Receita e EBIT'!J133+'Projeções - Receita e EBIT'!J151) -> 127598 | P15: =SUM('Projeções - Receita e EBIT'!K37+'Projeções - Receita e EBIT'!K56+'Projeções - Receita e EBIT'!K75+'Projeções - Receita e EBIT'!K98+'Projeções - Receita e EBIT'!K133+'Projeções - Receita e EBIT'!K151) -> 164843 | Q15: =SUM('Projeções - Receita e EBIT'!L37+'Projeções - Receita e EBIT'!L56+'Projeções - Receita e EBIT'!L75+'Projeções - Receita e EBIT'!L98+'Projeções - Receita e EBIT'!L133+'Projeções - Receita e EBIT'!L151) -> 160737 | R15: =SUM('Projeções - Receita e EBIT'!M37+'Projeções - Receita e EBIT'!M56+'Projeções - Receita e EBIT'!M75+'Projeções - Receita e EBIT'!M98+'Projeções - Receita e EBIT'!M133+'Projeções - Receita e EBIT'!M151) -> 186246 | S15: =SUM('Projeções - Receita e EBIT'!N37+'Projeções - Receita e EBIT'!N56+'Projeções - Receita e EBIT'!N75+'Projeções - Receita e EBIT'!N98+'Projeções - Receita e EBIT'!N133+'Projeções - Receita e EBIT'!N151) -> 320049 | T15: =SUM('Projeções - Receita e EBIT'!O37+'Projeções - Receita e EBIT'!O56+'Projeções - Receita e EBIT'!O75+'Projeções - Receita e EBIT'!O98+'Projeções - Receita e EBIT'!O133+'Projeções - Receita e EBIT'!O151) -> 237755.88 | U15: =SUM('Projeções - Receita e EBIT'!P37+'Projeções - Receita e EBIT'!P56+'Projeções - Receita e EBIT'!P75+'Projeções - Receita e EBIT'!P98+'Projeções - Receita e EBIT'!P133+'Projeções - Receita e EBIT'!P151) -> 64614 | V15: =W15-U15 -> 515623.67 | W15: =SUM('Projeções - Receita e EBIT'!R37,'Projeções - Receita e EBIT'!R56,'Projeções - Receita e EBIT'!R75,'Projeções - Receita e EBIT'!R98) -> 580237.67 | X15: =SUM('Projeções - Receita e EBIT'!S37,'Projeções - Receita e EBIT'!S56,'Projeções - Receita e EBIT'!S75,'Projeções - Receita e EBIT'!S98) -> 746967.05 | Y15: =SUM('Projeções - Receita e EBIT'!T37,'Projeções - Receita e EBIT'!T56,'Projeções - Receita e EBIT'!T75,'Projeções - Receita e EBIT'!T98) -> 800701 | Z15: =SUM('Projeções - Receita e EBIT'!U37,'Projeções - Receita e EBIT'!U56,'Projeções - Receita e EBIT'!U75,'Projeções - Receita e EBIT'!U98) -> 860120.97 | AA15: =SUM('Projeções - Receita e EBIT'!V37,'Projeções - Receita e EBIT'!V56,'Projeções - Receita e EBIT'!V75,'Projeções - Receita e EBIT'!V98) -> 925341.58
A16: Projeções - Receita e EBIT | E16: Margem EBIT Excluindo Empresas de Capital Aberto | O16: =O15/O13 -> 0.090167427 | P16: =P15/P13 -> 0.10727224 | Q16: =Q15/Q13 -> 0.11632318 | R16: =R15/R13 -> 0.13170424 | S16: =S15/S13 -> 0.083218189 | T16: =T15/T13 -> 0.030320317 | U16: =U15/U13 -> 0.027744584 | W16: =W15/W13 -> 0.060583197 | X16: =X15/X13 -> 0.072241273 | Y16: =Y15/Y13 -> 0.073472221 | Z16: =Z15/Z13 -> 0.074370522 | AA16: =AA15/AA13 -> 0.075219888
A17: Projeções - CG + Capex | E17: Imposto de Renda e CSLL Ex empresas de capital aberto | M17: ='DRE Consolidado'!M43-SUM('DRE - Contas Abertas'!H145:H147) -> 125739 | N17: ='DRE Consolidado'!N43-SUM('DRE - Contas Abertas'!I145:I147) -> -9835 | O17: ='DRE Consolidado'!O43-SUM('DRE - Contas Abertas'!J145:J147) -> -8702 | P17: ='DRE Consolidado'!P43-SUM('DRE - Contas Abertas'!K145:K147) -> -14799 | Q17: ='DRE Consolidado'!Q43-SUM('DRE - Contas Abertas'!L145:L147) -> -151261 | R17: ='DRE Consolidado'!R43-SUM('DRE - Contas Abertas'!M145:M147) -> 5761 | S17: ='DRE Consolidado'!S43-SUM('DRE - Contas Abertas'!N145:N147) -> 196898 | T17: ='DRE Consolidado'!T43-SUM('DRE - Contas Abertas'!O145:O147) -> 139608 | U17: 0 | V17: =W17-U17 -> -197280.81 | W17: =-W23*W15 -> -197280.81 | X17: =-X23*X15 -> -253968.8 | Y17: =-Y23*Y15 -> -272238.34 | Z17: =-Z23*Z15 -> -292441.13 | AA17: =-AA23*AA15 -> -314616.14
A18: Projeções 2023
A19: Processos
A20: Gráficos
K22: 2014 | L22: 2015 | M22: 2016 | N22: 2017 | O22: 2018 | P22: 2019 | Q22: 2020 | R22: 2021 | S22: 2022 | T22: 2023 | U22: YTD 2024 | V22: YTG 2024E | W22: 2024 | X22: =W22+1 -> 2025 | Y22: =X22+1 -> 2026 | Z22: =Y22+1 -> 2027 | AA22: =Z22+1 -> 2028 | AB22: Perpetuidade | AC22: ROIC Perp. | AD22: Growth
E23: Alíquota Efetiva Ex Empresas de Capital Aberto | F23: 0.030034188 | G23: -0.02092541 | H23: -0.043315116 | I23: 0.13811998 | J23: -0.59211219 | K23: =IFERROR(IF(K15>0,-K17/K15,"-"),"-") -> - | L23: =IFERROR(IF(L15>0,-L17/L15,"-"),"-") -> - | M23: =IFERROR(IF(M15>0,-M17/M15,"-"),"-") -> - | N23: =IFERROR(IF(N15>0,-N17/N15,"-"),"-") -> - | O23: =IFERROR(IF('DRE Consolidado'!O37>0,-O17/O15,"-"),"-") -> 0.068198561 | P23: =IFERROR(IF('DRE Consolidado'!P37>0,-P17/P15,"-"),"-") -> 0.089776333 | Q23: =IFERROR(IF('DRE Consolidado'!Q37>0,-Q17/Q15,"-"),"-") -> 0.94104655 | R23: =IFERROR(IF('DRE Consolidado'!R37>0,-R17/R15,"-"),"-") -> -0.030932208 | S23: =IFERROR(IF('DRE Consolidado'!S37>0,-S17/S15,"-"),"-") -> -0.61521205 | T23: =IFERROR(IF('DRE Consolidado'!T37>0,-T17/T15,"-"),"-") -> -0.58719052 | U23: =IFERROR(IF('DRE Consolidado'!U37>0,-U17/U15,"-"),"-") -> 0 | V23: =IFERROR(IF(#REF!>0,-#REF!/#REF!,"-"),"-") -> - | W23: 0.34 | X23: 0.34 | Y23: 0.34 | Z23: 0.34 | AA23: 0.34 | AC23: =WACC!P20 -> 0.11033014 | AD23: =(1+'Projeções - CG + Capex'!U37)*(1+'Projeções - CG + Capex'!U38)-1 -> 0.071
E24: D&A do Arrendamento Ex empresas de capital aberto | P24: ='Projeções - CG + Capex'!P48-SUM('Projeções - CG + Capex'!P45:P47) -> 17522 | Q24: ='Projeções - CG + Capex'!Q48-SUM('Projeções - CG + Capex'!Q45:Q47) -> -29457 | R24: ='Projeções - CG + Capex'!R48-SUM('Projeções - CG + Capex'!R45:R47) -> 18427 | S24: ='Projeções - CG + Capex'!S48-SUM('Projeções - CG + Capex'!S45:S47) -> -87846 | T24: ='Projeções - CG + Capex'!T48-SUM('Projeções - CG + Capex'!T45:T47) -> 50440 | U24: 0 | V24: =W24-SUM(U24:U24) -> 98539.007 | W24: =W25*W13 -> 98539.007 | X24: =X25*X13 -> 106382.58 | Y24: =Y25*Y13 -> 112124.79 | Z24: =Z25*Z13 -> 118990.74 | AA24: =AA25*AA13 -> 126567.98
E25: D&A do Arrendamento como (%) da Receita das empresas de Capital Fechado | P25: =P24/P13 -> 0.011402512 | Q25: =Q24/Q13 -> -0.02131763 | R25: =R24/R13 -> 0.013030691 | S25: =S24/S13 -> -0.022841456 | T25: =T24/T13 -> 0.0064324666 | U25: =U24/U13 -> 0 | V25: =V24/V13 -> 0.013594123 | W25: =AVERAGE($P$25,$R$25,$T$25) -> 0.010288556 | X25: =AVERAGE($P$25,$R$25,$T$25) -> 0.010288556 | Y25: =AVERAGE($P$25,$R$25,$T$25) -> 0.010288556 | Z25: =AVERAGE($P$25,$R$25,$T$25) -> 0.010288556 | AA25: =AVERAGE($P$25,$R$25,$T$25) -> 0.010288556
E26: NOPAT Ex Empresas de Capital Aberto | F26: 215718 | G26: 230388 | H26: 181530 | I26: -272310 | J26: -42610 | O26: =O15+O17+O24 -> 118896 | P26: =P15+P17+P24 -> 167566 | Q26: =Q15+Q17+Q24 -> -19981 | R26: =R15+R17+R24 -> 210434 | S26: =S15+S17+S24 -> 429101 | T26: =T15+T17+T24 -> 427803.88 | U26: =U15+U17+U24 -> 64614 | V26: =W26-SUM(U26:U26) -> 416881.87 | W26: =W15*(1-W23)+W24 -> 481495.87 | X26: =X15*(1-X23)+X24 -> 599380.83 | Y26: =Y15*(1-Y23)+Y24 -> 640587.45 | Z26: =Z15*(1-Z23)+Z24 -> 686670.58 | AA26: =AA15*(1-AA23)+AA24 -> 737293.42 | AB26: =AA26 -> 737293.42
E27: Taxa de Reinvestimento | O27: =IFERROR(SUM(O28,O34)/O26,0) -> 2.1497051 | P27: =IFERROR(SUM(P28,P34)/P26,0) -> 2.015755 | Q27: =IFERROR(SUM(Q28,Q34)/Q26,0) -> 1.9802316 | R27: =IFERROR(SUM(R28,R34)/R26,0) -> 4.5267892 | S27: =IFERROR(SUM(S28,S34)/S26,0) -> 5.6542562 | T27: =IFERROR(SUM(T28,T34)/T26,0) -> 12.722287 | U27: =IFERROR(SUM(U28,U34)/U26,0) -> 6.1762682 | V27: =IFERROR(SUM(V28,V34)/V26,0) -> 1.8333017 | ... AA27: =IFERROR(SUM(AA28,AA34)/AA26,0) -> -0.62423301 | AB27: =(AD23-'Projeções - CG + Capex'!U37)/('DRE + DCF'!AC23-'Projeções - CG + Capex'!U37) -> 0.34808474
E28: CAPEX Líquido Ex Empresas de Capital Aberto | F28: 0 | G28: 0 | H28: 0 | I28: 0 | J28: 0 | O28: =O29-O32 -> 254518.96 | P28: =P29-P32 -> 248153.71 | Q28: =Q29-Q32 -> 208490.23 | R28: =R29-R32 -> 570893.55 | S28: =S29-S32 -> 976579 | T28: =T29-T32 -> 453802 | U28: =U29-U32 -> -35032 | V28: =W28-SUM(U28:U28) -> -538045.94 | W28: =W29-W32 -> -573077.94 | X28: =X29-X32 -> -772695.37 | Y28: =Y29-Y32 -> -875423.75 | Z28: =Z29-Z32 -> -930641.19 | AA28: =AA29-AA32 -> -991640.99
E29: CAPEX Bruto (Ex empresas de Capital Aberto) | F29: 0 | G29: 0 | H29: 0 | I29: 0 | J29: 0 | O29: ='Projeções - CG + Capex'!O32 -> 405066.96 | P29: ='Projeções - CG + Capex'!P32 -> 405314.71 | Q29: ='Projeções - CG + Capex'!Q32 -> 431804.23 | R29: ='Projeções - CG + Capex'!R32 -> 665081.55 | S29: ='Projeções - CG + Capex'!S32 -> 1334428 | T29: ='Projeções - CG + Capex'!T32 -> 643091 | U29: 0 | V29: =W29-SUM(U29:U29) -> 311342.1 | W29: ='Projeções - CG + Capex'!U32 -> 311342.1 | X29: ='Projeções - CG + Capex'!V32 -> 182123.3 | Y29: ='Projeções - CG + Capex'!W32 -> 130933.18 | Z29: ='Projeções - CG + Capex'!X32 -> 137339.87 | AA29: ='Projeções - CG + Capex'!Y32 -> 144348.31
E30: Crescimento do Capex Bruto (YoY)¹ | O30: 0 | P30: =(P29-O29)/O29 -> 0.00061163483 | Q30: =(Q29-P29)/P29 -> 0.065355445 | R30: =(R29-Q29)/Q29 -> 0.54023861 | S30: =(S29-R29)/R29 -> 1.0064126 | T30: =(T29-S29)/S29 -> -0.51807741 | W30: =W29/S29-1 -> -0.76668497 | X30: =X29/W29-1 -> -0.41503801 | Y30: =Y29/X29-1 -> -0.28107395 | Z30: =Z29/Y29-1 -> 0.048930979 | AA30: =AA29/Z29-1 -> 0.051029868
E31: (%) da Receita Líquida | O31: =O29/O13 -> 0.28624152 | P31: =P29/P13 -> 0.26376017 | Q31: =Q29/Q13 -> 0.31249085 | R31: =R29/R13 -> 0.4703138 | S31: =S29/S13 -> 0.346974 | T31: =T29/T13 -> 0.082011526 | V31: =V29/V13 -> 0.04295175 | W31: =W29/W13 -> 0.032507541 | X31: =X29/X13 -> 0.017613653 | Y31: =Y29/Y13 -> 0.012014412 | Z31: =Z29/Z13 -> 0.011875118 | AA31: =AA29/AA13 -> 0.011733898
E32: Depreciação & Amortização Ex empresas de capital aberto | F32: 0 | G32: 0 | H32: 0 | I32: 0 | J32: 0 | O32: ='Projeções - CG + Capex'!O57-SUM('Projeções - CG + Capex'!O54:O56) -> 150548 | P32: ='Projeções - CG + Capex'!P57-SUM('Projeções - CG + Capex'!P54:P56) -> 157161 | Q32: ='Projeções - CG + Capex'!Q57-SUM('Projeções - CG + Capex'!Q54:Q56) -> 223314 | R32: ='Projeções - CG + Capex'!R57-SUM('Projeções - CG + Capex'!R54:R56) -> 94188 | S32: ='Projeções - CG + Capex'!S57-SUM('Projeções - CG + Capex'!S54:S56) -> 357849 | T32: ='Projeções - CG + Capex'!T57-SUM('Projeções - CG + Capex'!T54:T56) -> 189289 | U32: ='Projeções - CG + Capex'!U57-SUM('Projeções - CG + Capex'!U54:U56) -> 35032 | V32: =W32-U32 -> 849388.05 | W32: =W33*W13 -> 884420.05 | X32: =X33*X13 -> 954818.66 | Y32: =Y33*Y13 -> 1006356.9 | Z32: =Z33*Z13 -> 1067981.1 | AA32: =AA33*AA13 -> 1135989.3
E33: (%) da Receita Líquida | O33: =O32/O13 -> 0.1063851 | P33: =P32/P13 -> 0.10227315 | Q33: =Q32/Q13 -> 0.1616093 | R33: =R32/R13 -> 0.066605239 | S33: =S32/S13 -> 0.093046833 | T33: =T32/T13 -> 0.024139476 | U33: =U32/U13 -> 0.015042379 | V33: =V32/V13 -> 0.11717883 | W33: =AVERAGE(O33:T33) -> 0.092343183 | X33: =W33 -> 0.092343183 | Y33: =X33 -> 0.092343183 | Z33: =Y33 -> 0.092343183 | AA33: =Z33 -> 0.092343183
E34: ∆ Capital de Giro Ex empresas de capital aberto | F34: 0 | G34: -122636.72 | H34: 147702.64 | I34: -36069.72 | J34: -41836.44 | O34: ='Projeções - CG + Capex'!O66-SUM('Projeções - CG + Capex'!O63:O65) -> 1072.3793 | P34: ='Projeções - CG + Capex'!P66-SUM('Projeções - CG + Capex'!P63:P65) -> 89618.288 | Q34: ='Projeções - CG + Capex'!Q66-SUM('Projeções - CG + Capex'!Q63:Q65) -> -248057.24 | R34: ='Projeções - CG + Capex'!R66-SUM('Projeções - CG + Capex'!R63:R65) -> 381696.81 | S34: ='Projeções - CG + Capex'!S66-SUM('Projeções - CG + Capex'!S63:S65) -> 1449668 | T34: ='Projeções - CG + Capex'!T66-SUM('Projeções - CG + Capex'!T63:T65) -> 4988842 | U34: =W34/4 -> 434105.39 | V34: =W34-SUM(U34:U34) -> 1302316.2 | W34: =('Projeções - CG + Capex'!U10-'Projeções - CG + Capex'!S10)*W35 -> 1736421.6 | X34: =('Projeções - CG + Capex'!V10-'Projeções - CG + Capex'!U10)*X35 -> 535286.88 | Y34: =('Projeções - CG + Capex'!W10-'Projeções - CG + Capex'!V10)*Y35 -> 662582.4 | Z34: =('Projeções - CG + Capex'!X10-'Projeções - CG + Capex'!W10)*Z35 -> 495213.6 | AA34: =('Projeções - CG + Capex'!Y10-'Projeções - CG + Capex'!X10)*AA35 -> 531398.09
E35: ∆ Capital de Giro Ex empresas de capital aberto % da ∆ Capital de Giro do Grupo todo | F35: 0 | G35: -122636.72 | H35: 147702.64 | I35: -36069.72 | J35: -41836.44 | O35: =O34/'Projeções - CG + Capex'!O66 -> -0.0079224606 | P35: =P34/'Projeções - CG + Capex'!P66 -> 0.34770069 | Q35: =Q34/'Projeções - CG + Capex'!Q66 -> 0.3474961 | R35: =R34/'Projeções - CG + Capex'!R66 -> 1.1672791 | S35: =S34/'Projeções - CG + Capex'!S66 -> 1.0587931 | T35: =T34/'Projeções - CG + Capex'!T66 -> 3.0688375 | W35: =AVERAGE($O$35:$T$35) -> 0.99703065 | X35: =AVERAGE($O$35:$T$35) -> 0.99703065 | Y35: =AVERAGE($O$35:$T$35) -> 0.99703065 | Z35: =AVERAGE($O$35:$T$35) -> 0.99703065 | AA35: =AVERAGE($O$35:$T$35) -> 0.99703065
E36: FCFF Ex Empresas de Capital Aberto | O36: =O26*(1-O27) -> -136695.34 | P36: =P26*(1-P27) -> -170206 | Q36: =Q26*(1-Q27) -> 19586.008 | R36: =R26*(1-R27) -> -742156.37 | S36: =S26*(1-S27) -> -1997146 | T36: =T26*(1-T27) -> -5014840.1 | U36: =U26*(1-U27) -> -334459.39 | V36: =W36-SUM(U36:U36) -> -347388.36 | W36: =W26*(1-W27) -> -681847.76 | X36: =X26*(1-X27) -> 836789.32 | Y36: =Y26*(1-Y27) -> 853428.8 | Z36: =Z26*(1-Z27) -> 1122098.2 | AA36: =AA26*(1-AA27) -> 1197536.3 | AB36: =AB26*(1-AB27) -> 480652.83
E37: Desconto | V37: =WACC!F21 -> 1.0746361 | X37: =WACC!G21 -> 1.1844449 | Y37: =WACC!H21 -> 1.3079719 | Z37: =WACC!I21 -> 1.4467296 | AA37: =WACC!J21 -> 1.6018645
E38: FCFF Descontado Ex Empresas de Capital Aberto | V38: =V36/V37 -> -323261.41 | X38: =X36/X37 -> 706482.29 | Y38: =Y36/Y37 -> 652482.5 | Z38: =Z36/Z37 -> 775610.15 | AA38: =AA36/AA37 -> 747589.01 | AB38: =(AB36*(1+AD23))/(WACC!P20-AD23)/'DRE + DCF'!AA37 -> 8170897
E39: ROIC - Simpar Consolidado | F39: 0.19812982 | G39: 0.1966132 | H39: 0.14196039 | I39: -0.20916931 | J39: -0.040922008 | K39: ='DRE Consolidado'!K58/(SUM('Balanço Patrimonial'!F54:F59,'Balanço Patrimonial'!F72:F75,'Balanço Patrimonial'!F87,-'Balanço Patrimonial'!F19,-'Balanço Patrimonial'!F36)) -> 0.087496051 | L39: ='DRE Consolidado'!L58/(SUM('Balanço Patrimonial'!G54:G59,'Balanço Patrimonial'!G72:G75,'Balanço Patrimonial'!G87,-'Balanço Patrimonial'!G19,-'Balanço Patrimonial'!G36)) -> 0.0927418 | M39: ='DRE Consolidado'!M58/(SUM('Balanço Patrimonial'!H54:H59,'Balanço Patrimonial'!H72:H75,'Balanço Patrimonial'!H87,-'Balanço Patrimonial'!H19,-'Balanço Patrimonial'!H36)) -> 0.090692945 | N39: ='DRE Consolidado'!N58/(SUM('Balanço Patrimonial'!I54:I59,'Balanço Patrimonial'!I72:I75,'Balanço Patrimonial'!I87,-'Balanço Patrimonial'!I19,-'Balanço Patrimonial'!I36)) -> 0.092089722 | O39: ='DRE Consolidado'!O58/(SUM('Balanço Patrimonial'!J54:J59,'Balanço Patrimonial'!J72:J75,'Balanço Patrimonial'!J87,-'Balanço Patrimonial'!J19,-'Balanço Patrimonial'!J36)) -> 0.098681459 | P39: ='DRE Consolidado'!P58/(SUM('Balanço Patrimonial'!K54:K59,'Balanço Patrimonial'!K72:K75,'Balanço Patrimonial'!K87,-'Balanço Patrimonial'!K19,-'Balanço Patrimonial'!K36)) -> 0.10811252 | Q39: ='DRE Consolidado'!Q58/(SUM('Balanço Patrimonial'!L54:L59,'Balanço Patrimonial'!L72:L75,'Balanço Patrimonial'!L87,-'Balanço Patrimonial'!L19,-'Balanço Patrimonial'!L36)) -> 0.084555268 | R39: ='DRE Consolidado'!R58/(SUM('Balanço Patrimonial'!M54:M59,'Balanço Patrimonial'!M72:M75,'Balanço Patrimonial'!M87,-'Balanço Patrimonial'!M19,-'Balanço Patrimonial'!M36)) -> 0.12089622 | ... T39: ='DRE Consolidado'!T58/(SUM('Balanço Patrimonial'!O54:O59,'Balanço Patrimonial'!O72:O75,'Balanço Patrimonial'!O87,-'Balanço Patrimonial'!O19,-'Balanço Patrimonial'!O36)) -> 0.13630931
E41: ¹- "YoY", ou "year over year", significa "de um ano pro outro".

Sheet DRE - Contas Abertas
F3: =Dashboard!$H$3 -> SIMPAR (SIMH3)
A7: Páginas
A8: Dashboard
A9: WACC | F9: 2014 | G9: 2015 | H9: 2016 | I9: 2017 | J9: 2018 | K9: 2019 | L9: 2020 | M9: 2021 | N9: 2022 | O9: 2023 | P9: YTD
A10: DRE Consolidado | E10: Custo de venda de veículos novos e usados | L10: -1019754 | M10: -1899550 | N10: -4817452 | O10: -7842006 | P10: -2259530
A11: DRE + DCF | E11: Custo de venda de veículos novos | F11: -592675 | G11: -427897 | H11: -281566 | I11: -319150 | J11: -535727 | K11: -586574
A12: DRE - Contas Abertas | E12: Custo de venda de veículos usados | F12: -280455 | G12: -285571 | H12: -275399 | I12: -251561 | J12: -254716 | K12: -282749
A13: Balanço Patrimonial | E13: Custo de venda de peças | F13: -110505 | H13: -90706 | I13: -77717 | J13: -111711 | K13: -122657
A14: Painel de Índices | E14: Custo de Construção | O14: -175507 | P14: -118308
A15: Projeções - Receita e EBIT | E15: Custo / despesas com frota | F15: -148406 | H15: -247034 | I15: -224258 | J15: -177630 | K15: -271440 | L15: -279687 | M15: -405447 | N15: -522589 | O15: -555379 | P15: -175867
A16: Projeções - CG + Capex | E16: Custo de venda de ativos desmobilizados | F16: -681231 | G16: -877618 | H16: -1289069 | I16: -1584813 | J16: -1609867 | K16: -2524180 | L16: -2618101 | M16: -2077780 | N16: -4166192 | O16: -5366708 | P16: -1616181
A17: Projeções 2023 | E17: Pessoal | F17: =-1045800-228365 -> -1274165 | G17: -1299564 | H17: -1365077 | I17: -1399487 | J17: -1510200 | K17: -1603040 | L17: -1477812 | M17: -2278160 | N17: -3291385 | O17: -4194475 | P17: -1078384
A18: Processos | E18: Agregados e terceiros | F18: -656182 | G18: -656004 | H18: -721429 | I18: -900896 | J18: -996936 | K18: -952975 | L18: -854451 | M18: -1149724 | N18: -1382969 | O18: -1676299 | P18: -404182
E19: Depreciação e amortização (i) | F19: =-391194-17671 -> -408865 | G19: -508626 | H19: -547187 | I19: -525731 | J19: -636817 | K19: -916744 | L19: -1111953 | M19: -1059114 | N19: -1886277 | O19: -3508285 | P19: -813581
E20: Peças, pneus e manutenções | F20: -260230 | G20: -394413 | H20: -348746 | I20: -424460 | J20: -438912 | K20: -498789 | L20: -489633 | M20: -701562 | N20: -1015445 | O20: -1345151 | P20: -354143
E21: Combustíveis e lubrificantes | F21: -233123 | G21: -256416 | H21: -271274 | I21: -244744 | J21: -256323 | K21: -236111 | L21: -214393 | M21: -494957 | N21: -899084 | O21: -1005787 | P21: -304152
E22: Propaganda e publicidade | F22: -14836 | H22: -4418 | I22: -5213 | J22: -17297 | K22: -11895 | L22: -43158 | M22: -65288 | N22: -115364 | O22: -150302 | P22: -42554
E23: Prestação de serviços | F23: =-18944-62100 -> -81044 | G23: -93764 | H23: -175477 | I23: -184196 | J23: -241971 | K23: -271413 | L23: -285556 | M23: -444935 | N23: -657511 | O23: -911677 | P23: -265140
E24: Reversão (provisão) de perdas esperadas ("impairment") de contas a receber | F24: -3352 | H24: -27025 | I24: 2249 | J24: -9146 | K24: -32527 | L24: -78667 | M24: -56164 | N24: -127315 | O24: -184393 | P24: -53232
E25: Provisão para perdas de valor recuperável ("Impairment") | L25: -145249 | M25: - | N25: -9498 | O25: 0
E26: Indenizações judiciais | F26: -24516 | G26: -6205 | H26: -34755 | I26: -48724 | J26: -32345 | K26: -48635 | L26: -56253 | M26: -41436 | N26: -49176 | O26: -65748 | P26: -28056
E27: Energia elétrica | H27: -25250 | I27: -23879 | J27: -26243 | K27: -33047 | L27: -29820 | M27: -39861 | N27: -52864 | O27: -58912 | P27: -16973
E28: Resultado na venda de veículos avariados (ii) | H28: -45447 | I28: -77445 | J28: -80763 | K28: -42601 | L28: -37135 | M28: -58698 | N28: -169869 | O28: -224494 | P28: -47736
E29: Alugueis de imóveis (nota 4.1.(d)) (i) | F29: =-65505-46743 -> -112248 | G29: -38650 | H29: -161059 | I29: -161048 | J29: -152328 | K29: -45151 | L29: -21769 | M29: -2215 | N29: -30761 | O29: -23455 | P29: -8415
E30: Aluguéis de veículos, máquinas e equipamentos | G30: -95354 | H30: -86129 | I30: -24727 | J30: -36851 | K30: -27051 | L30: -25913 | M30: -43100 | N30: -88637 | O30: -75486 | P30: -10563
E31: Recuperação de PIS e COFINS | H31: 216301 | I31: 260766 | J31: 285022 | K31: 366861 | L31: 398061 | M31: 562762 | N31: 1101761 | O31: 1221607 | P31: 337020
E32: Crédito de impostos extemporâneos | H32: - | I32: 82928 | J32: 62789 | K32: 47706 | L32: 59819 | M32: 149002 | N32: 71200 | O32: 49245 | P32: 21100
E33: Provisão para perdas tributárias ICMS RJ | G33: - | H33: -27466 | I33: -
E34: Perdas estimadas com créditos de liquidação duvidosa | F34: -18540 | G34: -32258 | H34: -68409 | I34: -60680
E35: Material de embalagem | H35: -9437 | I35: -9255 | J35: -10804 | K35: -5710
E36: Comunicação | F36: -623 | G36: -5277 | H36: -35206 | I36: -35876 | J36: -35528 | K36: -27144
E37: Telefones | F37: -11744
E38: Viagens, refeições e estadias | F38: -5267 | G38: -4816 | H38: -8732 | I38: -10206 | J38: -13677 | K38: -17160
E39: Baixa da mais valia de ativo vendido | H39: -25653 | I39: -55061
E40: Despesas tributárias | H40: -13822 | I40: -13208 | J40: -17120 | K40: -8573
E41: Manutenção Predial | F41: -5514
E42: Impostos, manutenção e conservação de automóveis | F42: -20532
E43: Provisão para demandas judiciais e administrativas | F43: -12038 | O43: 0
E44: Gasto com infraestrutura das filiais | G44: -90307
E45: Outros custos | F45: =-62122-52880 -> -115002 | G45: -324204 | H45: -54862 | I45: -234942 | J45: -258611 | K45: -334244 | L45: -445136 | M45: -627907 | N45: -1158358 | O45: -891057 | P45: -329099
E46: Equivalência Patrimonial | F46: ='DRE Consolidado'!K32 -> 94 | G46: ='DRE Consolidado'!L32 -> 71 | H46: ='DRE Consolidado'!M32 -> 0 | I46: ='DRE Consolidado'!N32 -> 0 | J46: ='DRE Consolidado'!O32 -> -960 | K46: ='DRE Consolidado'!P32 -> -1201 | L46: ='DRE Consolidado'!Q32 -> -515 | M46: ='DRE Consolidado'!R32 -> -1534 | N46: 0 | O46: 0 | P46: 0
E47: Total: | F47: =SUM(F10:F46) -> -5070999 | G47: =SUM(G10:G46) -> -5396873 | H47: =SUM(H10:H46) -> -6024333 | I47: =SUM(I10:I46) -> -6551334 | J47: =SUM(J10:J46) -> -7114672 | K47: =SUM(K10:K46) -> -8487044 | L47: =SUM(L10:L46) -> -8777075 | M47: =SUM(M10:M46) -> -10735668 | ... P47: =SUM(P10:P46) -> -7567976
F51: 2014 | G51: 2015 | H51: 2016 | I51: 2017 | J51: 2018 | K51: 2019 | L51: 2020 | M51: 2021 | N51: 2022 | O51: 2023 | P51: =P9 -> YTD
E52: Receita Líquida | F52: ='DRE Consolidado'!K16 -> 5539194 | G52: ='DRE Consolidado'!L16 -> 5989912 | H52: ='DRE Consolidado'!M16 -> 6523116 | I52: ='DRE Consolidado'!N16 -> 7255804 | J52: ='DRE Consolidado'!O16 -> 8075389 | K52: ='DRE Consolidado'!P16 -> 9686209 | L52: ='DRE Consolidado'!Q16 -> 9807057 | M52: ='DRE Consolidado'!R16 -> 13866219 | ... P52: ='DRE Consolidado'!U16 -> 9146986
E53: Custos das Vendas e Serviços + Despesas | F53: ='DRE Consolidado'!K18+'DRE Consolidado'!K20+'DRE Consolidado'!K23 -> -5079092 | G53: ='DRE Consolidado'!L18+'DRE Consolidado'!L20+'DRE Consolidado'!L23 -> -5406457 | H53: ='DRE Consolidado'!M18+'DRE Consolidado'!M20+'DRE Consolidado'!M23 -> -6024333 | I53: ='DRE Consolidado'!N18+'DRE Consolidado'!N20+'DRE Consolidado'!N23 -> -6551334 | J53: ='DRE Consolidado'!O18+'DRE Consolidado'!O20+'DRE Consolidado'!O23 -> -7114672 | K53: ='DRE Consolidado'!P18+'DRE Consolidado'!P20+'DRE Consolidado'!P23 -> -8487044 | L53: ='DRE Consolidado'!Q18+'DRE Consolidado'!Q20+'DRE Consolidado'!Q23 -> -8777075 | M53: ='DRE Consolidado'!R18+'DRE Consolidado'!R20+'DRE Consolidado'!R23 -> -10735668 | ... P53: ='DRE Consolidado'!U18+'DRE Consolidado'!U20+'DRE Consolidado'!U23 -> -7569023
E54: EBIT | F54: =SUM(F52:F53) -> 460102 | G54: =SUM(G52:G53) -> 583455 | H54: =SUM(H52:H53) -> 498783 | I54: =SUM(I52:I53) -> 704470 | J54: =SUM(J52:J53) -> 960717 | K54: =SUM(K52:K53) -> 1199165 | L54: =SUM(L52:L53) -> 1029982 | M54: =SUM(M52:M53) -> 3130551 | ... P54: =SUM(P52:P53) -> 1577963
E55: Margem EBIT | F55: =F54/F52 -> 0.083062987 | G55: =G54/G52 -> 0.097406272 | H55: =H54/H52 -> 0.076463917 | I55: =I54/I52 -> 0.09709055 | J55: =J54/J52 -> 0.11896851 | K55: =K54/K52 -> 0.12380127 | L55: =L54/L52 -> 0.10502458 | M55: =M54/M52 -> 0.22576818 | ... P55: =P54/P52 -> 0.1725118
E56: Eventos não recorrentes | F56: =SUM(F25,F26,F32,F33) -> -24516 | G56: =SUM(G25,G26,G32,G33) -> -6205 | H56: =SUM(H25,H26,H32,H33) -> -62221 | I56: =SUM(I25,I26,I32,I33) -> 34204 | J56: =SUM(J25,J26,J32,J33) -> 30444 | K56: =SUM(K25,K26,K32,K33) -> -929 | L56: =SUM(L25,L26,L32,L33) -> -141683 | M56: =SUM(M25,M26,M32,M33) -> 107566 | ... P56: =SUM(P25,P26,P32,P33) -> -6956
E57: EBIT recorrente | F57: =F54-F56 -> 484618 | G57: =G54-G56 -> 589660 | H57: =H54-H56 -> 561004 | I57: =I54-I56 -> 670266 | J57: =J54-J56 -> 930273 | K57: =K54-K56 -> 1200094 | L57: =L54-L56 -> 1171665 | M57: =M54-M56 -> 3022985 | ... P57: =P54-P56 -> 1584919
E58: Margem EBIT recorrente | F58: =F57/F52 -> 0.087488902 | G58: =G57/G52 -> 0.098442181 | H58: =H57/H52 -> 0.086002456 | I58: =I57/I52 -> 0.092376531 | J58: =J57/J52 -> 0.11519854 | K58: =K57/K52 -> 0.12389718 | L58: =L57/L52 -> 0.11947162 | M58: =M57/M52 -> 0.21801076 | ... P58: =P57/P52 -> 0.17327227
E59: Incentivos Fiscais | F59: =F126/34% -> 0 | G59: =G126/34% -> 0 | H59: =H126/34% -> 0 | I59: =I126/34% -> 0 | J59: =J126/34% -> 0 | K59: =K126/34% -> 31564.706 | L59: =L126/34% -> 29579.412 | M59: =M126/34% -> 34847.059 | ... P59: =P126/34% -> 0
E60: Ebit Recorrente sem incentivos | F60: =F57-F59 -> 484618 | G60: =G57-G59 -> 589660 | H60: =H57-H59 -> 561004 | I60: =I57-I59 -> 670266 | J60: =J57-J59 -> 930273 | K60: =K57-K59 -> 1168529.3 | L60: =L57-L59 -> 1142085.6 | M60: =M57-M59 -> 2988137.9 | ... P60: =P57-P59 -> 1584919
E61: Margem EBIT recorrente sem Incentivos | F61: =F60/F52 -> 0.087488902 | G61: =G60/G52 -> 0.098442181 | H61: =H60/H52 -> 0.086002456 | I61: =I60/I52 -> 0.092376531 | J61: =J60/J52 -> 0.11519854 | K61: =K60/K52 -> 0.12063846 | L61: =L60/L52 -> 0.11645549 | M61: =M60/M52 -> 0.21549767 | ... P61: =P60/P52 -> 0.17327227
F65: 2014 | G65: 2015 | H65: 2016 | I65: 2017 | J65: 2018 | K65: 2019 | L65: 2020 | M65: 2021 | N65: 2022 | O65: 2023 | P65: =P51 -> YTD
E66: Juros sobre empréstimos, financiamentos e debêntures | F66: -380589 | G66: -555934 | H66: -669521 | I66: -699233 | J66: -869284 | K66: -969381 | L66: -1005078 | M66: -2001424 | N66: -3631554 | O66: -4132227 | P66: -1320277
E67: Juros e encargos bancários sobre arrendamento mercantil | G67: -35548 | H67: -48855 | I67: -33007 | J67: -20929 | K67: -23157 | L67: -15836 | M67: -17783 | N67: -29761 | O67: -30745 | P67: -7176
E68: Juros de risco sacado - montadoras | H68: -75695 | I68: -84455 | J68: -304207 | K68: -186 | L68: -24253 | M68: -1030 | N68: -3926 | O68: -6417 | P68: -248
E69: Variação monetária | F69: -9996
E70: Variação cambial | F70: -7602 | H70: 48741 | I70: 1171 | J70: 293586 | K70: -175092 | L70: -637087 | M70: -95625 | N70: 394836 | O70: 474138 | P70: -162741
E71: Resultado na apuração dos swaps, líquido | H71: -106105 | I71: 13379 | K71: 172610 | L71: 723440 | M71: 326352 | N71: -1547875 | O71: -1951027 | P71: -25523
E72: Juros passivos | F72: -32661
E73: Juros de alongamento | G73: -66177 | J73: -17661
E74: Despesas com captação | N74: -108446 | O74: -142773 | P74: -31407
E75: Despesas bancárias | F75: -2587
E76: Descontos | F76: -4161
E77: IOF | F77: -1245
E78: Outras despesas financeiras | G78: -67062
E79: Despesa total do serviço da dívida | F79: =SUM(F66:F78) -> -438841 | G79: =SUM(G66:G78) -> -724721 | H79: =SUM(H66:H78) -> -851435 | I79: =SUM(I66:I78) -> -802145 | J79: =SUM(J66:J78) -> -918495 | K79: =SUM(K66:K78) -> -995206 | L79: =SUM(L66:L78) -> -958814 | M79: =SUM(M66:M78) -> -1789510 | ... P79: =SUM(P66:P78) -> -1547372
E80: Juros sobre arrendamento por direito de uso | F80: 0 | H80: 0 | J80: - | K80: -49557 | L80: -52448 | M80: -69956 | N80: -122010 | O80: -163284 | P80: -45764
E81: Juros passivos | F81: 0 | H81: 0 | J81: -34062 | K81: -23203 | L81: -21276 | M81: -46006 | N81: -116992 | O81: -713028 | P81: -105054
E82: Juros sobre cessão de direitos creditórios | O82: 0
E83: Outras despesas financeiras | F83: -4706 | H83: -98541 | I83: -77951 | J83: -46471 | K83: -65409 | L83: -21664 | M83: -48483 | N83: -192745 | O83: -365865 | P83: -135523
E84: Total: | F84: =SUM(F79:F83) -> -443547 | G84: =SUM(G79:G83) -> -724721 | H84: =SUM(H79:H83) -> -949976 | I84: =SUM(I79:I83) -> -880096 | J84: =SUM(J79:J83) -> -999028 | K84: =SUM(K79:K83) -> -1133375 | L84: =SUM(L79:L83) -> -1054202 | M84: =SUM(M79:M83) -> -1953955 | ... P84: =SUM(P79:P83) -> -1833713
F88: 2014 | G88: 2015 | H88: 2016 | I88: 2017 | J88: 2018 | K88: 2019 | L88: 2020 | M88: 2021 | N88: 2022 | O88: 2023 | P88: =P65 -> YTD
E89: Aplicações financeiras | F89: 55763 | G89: 155709 | H89: 161024 | I89: 148535 | J89: 262955 | K89: 295995 | L89: 345166 | M89: 660349 | N89: 1189610 | O89: 823655 | P89: 261611
E90: Receita de variação monetária | F90: 124 | G90: 16613 | H90: 9797 | I90: 31542 | J90: 22565 | K90: 24623 | L90: 12880 | M90: 13557 | N90: 4812 | O90: 69314 | P90: 23451
E91: AVP | F91: 23075
E92: Juros recebidos | F92: 6126 | H92: 8373 | I92: 13920 | J92: 11798 | K92: 17934 | L92: 28408 | M92: 33229 | N92: 33971 | O92: 55839 | P92: 16178
E93: Descontos | F93: 2367
E94: Ganho na liquidação antecipada de swaps | L94: 281440 | M94: -
E95: Receita de financiamentos e produtos de créditos concedidos | O95: 131985 | P95: 43050
E96: Outras receitas financeiras | F96: 2170 | G96: 13733 | H96: 22529 | I96: 15558 | J96: 20491 | K96: 26784 | L96: 11532 | M96: 29227 | N96: 649 | O96: 56709 | P96: 12485
E97: Total: | F97: =SUM(F89:F96) -> 89625 | G97: =SUM(G89:G96) -> 186055 | H97: =SUM(H89:H96) -> 201723 | I97: =SUM(I89:I96) -> 209555 | J97: =SUM(J89:J96) -> 317809 | K97: =SUM(K89:K96) -> 365336 | L97: =SUM(L89:L96) -> 679426 | M97: =SUM(M89:M96) -> 736362 | ... P97: =SUM(P89:P96) -> 356775
F101: 2014 | G101: 2015 | H101: 2016 | I101: 2017 | J101: 2018 | K101: 2019 | L101: 2020 | M101: 2021 | N101: 2022 | O101: 2023 | P101: =P88 -> YTD
E102: EBIT Recorrente | F102: =F57 -> 484618 | G102: =G57 -> 589660 | H102: =H57 -> 561004 | I102: =I57 -> 670266 | J102: =J57 -> 930273 | K102: =K57 -> 1200094 | L102: =L57 -> 1171665 | M102: =M57 -> 3022985 | ... P102: =P57 -> 1584919
E103: EBIT Recorrente sem Incentivos | F103: =F60 -> 484618 | G103: =G60 -> 589660 | H103: =H60 -> 561004 | I103: =I60 -> 670266 | J103: =J60 -> 930273 | K103: =K60 -> 1168529.3 | L103: =L60 -> 1142085.6 | M103: =M60 -> 2988137.9 | ... P103: =P60 -> 1584919
E104: Lucro antes do IR Não Recorrente | F104: ='DRE Consolidado'!K42 -> 111137 | G104: ='DRE Consolidado'!L42 -> 67222 | H104: ='DRE Consolidado'!M42 -> -249470 | I104: ='DRE Consolidado'!N42 -> 33929 | J104: ='DRE Consolidado'!O42 -> 279498 | K104: ='DRE Consolidado'!P42 -> 431126 | L104: ='DRE Consolidado'!Q42 -> 655206 | M104: ='DRE Consolidado'!R42 -> 1912958 | ... P104: ='DRE Consolidado'!U42 -> 101025
E105: Eventos não recorrentes | F105: =SUM(F72,F73,F76,F77,F78,F91,F93) -> -12625 | G105: =SUM(G72,G73,G76,G77,G78,G91,G93) -> -133239 | H105: =SUM(H72,H73,H76,H77,H78,H91,H93) -> 0 | I105: =SUM(I72,I73,I76,I77,I78,I91,I93) -> 0 | J105: =SUM(J72,J73,J76,J77,J78,J91,J93) -> -17661 | K105: =SUM(K72,K73,K76,K77,K78,K91,K93) -> 0 | L105: =SUM(L72,L73,L76,L77,L78,L91,L93) -> 0 | M105: =SUM(M72,M73,M76,M77,M78,M91,M93) -> 0 | ... P105: =SUM(P72,P73,P76,P77,P78,P91,P93) -> 0
E106: Lucro Antes do IR Recorrente | F106: =F104-F105 -> 123762 | G106: =G104-G105 -> 200461 | H106: =H104-H105 -> -249470 | I106: =I104-I105 -> 33929 | J106: =J104-J105 -> 297159 | K106: =K104-K105 -> 431126 | L106: =L104-L105 -> 655206 | M106: =M104-M105 -> 1912958 | ... P106: =P104-P105 -> 101025
E107: Lucro Antes do IR Recorrente sem Incentivos | F107: =F103+F97+F84 -> 130696 | G107: =G103+G97+G84 -> 50994 | H107: =H103+H97+H84 -> -187249 | I107: =I103+I97+I84 -> -275 | J107: =J103+J97+J84 -> 249054 | K107: =K103+K97+K84 -> 400490.29 | L107: =L103+L97+L84 -> 767309.59 | M107: =M103+M97+M84 -> 1770544.9 | ... P107: =P103+P97+P84 -> 107981
F111: 2014 | G111: 2015 | H111: 2016 | I111: 2017 | J111: 2018 | K111: 2019 | L111: 2020 | M111: 2021 | N111: 2022 | O111: 2023 | P111: =P101 -> YTD
E112: Lucro (prejuízo) líquido antes de imposto Recorrente e da CSLL | F112: =F106 -> 123762 | G112: =G106 -> 200461 | H112: =H106 -> -249470 | I112: =I106 -> 33929 | J112: =J106 -> 297159 | K112: =K106 -> 431126 | L112: =L106 -> 655206 | M112: =M106 -> 1912958 | ... P112: =P106 -> 101025
E113: Alíquota Vigente | F113: 0.34 | G113: 0.34 | H113: 0.34 | I113: 0.34 | J113: 0.34 | K113: 0.34 | L113: 0.34 | M113: 0.34 | N113: 0.34 | O113: 0.34 | P113: 0.34
E114: IRPJ e CSLL calculados às aliquotas nominais | F114: =-F113*F112 -> -42079.08 | G114: =-G113*G112 -> -68156.74 | H114: =-H113*H112 -> 84819.8 | I114: =-I113*I112 -> -11535.86 | J114: =-J113*J112 -> -101034.06 | K114: =-K113*K112 -> -146582.84 | L114: =-L113*L112 -> -222770.04 | M114: =-M113*M112 -> -650405.72 | ... P114: =-P113*P112 -> -34348.5
E115: Efeito Fiscal das adiçoes e exclusões permanentes:
E116: Equivalência Patrimonial | F116: 32 | G116: 24 | H116: 0 | I116: 0 | J116: -610 | K116: -2759 | L116: -175 | M116: -522 | N116: 955 | O116: 1811 | P116: -356
E117: Incentivos fiscais – PAT | F117: 725 | G117: 261 | H117: 421 | I117: 380 | J117: 825 | K117: 2074 | L117: 2347 | M117: 3536 | N117: 269 | P117: 273
E118: Juros sobre capital próprio | F118: 5361 | G118: 3400 | H118: 0 | I118: 2144 | J118: 18764 | K118: 27044 | L118: 16045 | M118: 51852 | N118: 102594 | O118: 4266 | P118: 12727
E119: Provisão para créditos de impostos diferidos sobre prejuízos fiscais | N119: 205
E120: Despesas indedutíveis | F120: -7863 | G120: -1812 | H120: -1963 | I120: -2130 | J120: -6269 | K120: 5979 | L120: -192 | M120: 28379 | N120: -9198 | O120: -195089 | P120: 8240
...

Sheet Balanço Patrimonial
F9: =Dashboard!H3 -> SIMPAR (SIMH3)
A13: Páginas
A14: Dashboard
A15: WACC | E15: Data do Último Resultado: | F15: 2014 | G15: 2015 | H15: 2016 | I15: 2017 | J15: 2018 | K15: 2019 | L15: 2020 | M15: 2021 | N15: 2022 | O15: 2023 | P15: YTD
A16: DRE Consolidado | E16: Capital de Giro | F16: =SUM(F20,F25:F30,F32:F34)-SUM(F53,F61:F62,F64,F66,F68,F69) -> 1071719.9 | G16: =SUM(G20,G25:G30,G32:G34)-SUM(G53,G61:G62,G64,G66,G68,G69) -> 914914.8 | H16: =SUM(H20,H25:H30,H32:H34)-SUM(H53,H61:H62,H64,H66,H68,H69) -> 419015.9 | I16: =SUM(I20,I25:I30,I32:I34)-SUM(I53,I61:I62,I64,I66,I68,I69) -> 842599.1 | J16: =SUM(J20,J25:J30,J32:J34)-SUM(J53,J61:J62,J64,J66,J68,J69) -> 707239.73 | K16: =SUM(K20,K25:K30,K32:K34)-SUM(K53,K61:K62,K64,K66,K68,K69) -> 964985.23 | L16: =SUM(L20,L25:L30,L32:L34)-SUM(L53,L61:L62,L64,L66,L68,L69) -> 251143.42 | M16: =SUM(M20,M25:M30,M32:M34)-SUM(M53,M61:M62,M64,M66,M68,M69) -> 578140.47 | ... P16: =SUM(P20,P25:P30,P32:P34)-SUM(P53,P61:P62,P64,P66,P68,P69) -> 4847984.5
A17: DRE + DCF | E17: Ativo Total | F17: =SUM(F18,F35) -> 7465231 | G17: =SUM(G18,G35) -> 8742595 | H17: =SUM(H18,H35) -> 8868383 | I17: =SUM(I18,I35) -> 11500924 | J17: =SUM(J18,J35) -> 15873954 | K17: =SUM(K18,K35) -> 20248234 | L17: =SUM(L18,L35) -> 25562248 | M17: =SUM(M18,M35) -> 47968194 | ... P17: =SUM(P18,P35) -> 75030622
A18: DRE - Contas Abertas | E18: Ativo Circulante | F18: =SUM(F19,F24:F34) -> 2854393 | G18: =SUM(G19,G24:G34) -> 3371043 | H18: =SUM(H19,H24:H34) -> 2716700 | I18: =SUM(I19,I24:I34) -> 4488461 | J18: =SUM(J19,J24:J34) -> 7191320 | K18: =SUM(K19,K24:K34) -> 8890832 | L18: =SUM(L19,L24:L34) -> 11495872 | M18: =SUM(M19,M24:M34) -> 23561250 | ... P18: =SUM(P19,P24:P34) -> 24859822
A19: Balanço Patrimonial | E19: Caixa e equivalentes de caixa | F19: =SUM(F22:F23) -> 1205846 | G19: =SUM(G22:G23) -> 1676261 | H19: =SUM(H22:H23) -> 1043220 | I19: =SUM(I22:I23) -> 2433254 | J19: =SUM(J22:J23) -> 4827233 | K19: =SUM(K22:K23) -> 5773825 | L19: =SUM(L22:L23) -> 8328381 | M19: =SUM(M22:M23) -> 18652225 | ... P19: =SUM(P22:P23) -> 12470555
A20: Painel de Índices | E20: Caixa Operacional | F20: =IF(F19>2.5%*'DRE Consolidado'!K16,2.5%*'DRE Consolidado'!K16,'Balanço Patrimonial'!F19) -> 138479.85 | G20: =IF(G19>2.5%*'DRE Consolidado'!L16,2.5%*'DRE Consolidado'!L16,'Balanço Patrimonial'!G19) -> 149747.8 | H20: =IF(H19>2.5%*'DRE Consolidado'!M16,2.5%*'DRE Consolidado'!M16,'Balanço Patrimonial'!H19) -> 163077.9 | I20: =IF(I19>2.5%*'DRE Consolidado'!N16,2.5%*'DRE Consolidado'!N16,'Balanço Patrimonial'!I19) -> 181395.1 | J20: =IF(J19>2.5%*'DRE Consolidado'!O16,2.5%*'DRE Consolidado'!O16,'Balanço Patrimonial'!J19) -> 201884.73 | K20: =IF(K19>2.5%*'DRE Consolidado'!P16,2.5%*'DRE Consolidado'!P16,'Balanço Patrimonial'!K19) -> 242155.23 | L20: =IF(L19>2.5%*'DRE Consolidado'!Q16,2.5%*'DRE Consolidado'!Q16,'Balanço Patrimonial'!L19) -> 245176.43 | M20: =IF(M19>2.5%*'DRE Consolidado'!R16,2.5%*'DRE Consolidado'!R16,'Balanço Patrimonial'!M19) -> 346655.48 | ... O20: =IF(O19>2.5%*'DRE Consolidado'!T16,2.5%*'DRE Consolidado'!T16,'Balanço Patrimonial'!O19) -> 796090.33 | P20: =IF(P19>2.5%*'DRE Consolidado'!W16,2.5%*'DRE Consolidado'!W16,'Balanço Patrimonial'!P19) -> 947658.53
A21: Projeções - Receita e EBIT | E21: Excesso de Caixa | F21: =F19-F20 -> 1067366.1 | G21: =G19-G20 -> 1526513.2 | H21: =H19-H20 -> 880142.1 | I21: =I19-I20 -> 2251858.9 | J21: =J19-J20 -> 4625348.3 | K21: =K19-K20 -> 5531669.8 | L21: =L19-L20 -> 8083204.6 | M21: =M19-M20 -> 18305570 | ... P21: =P19-P20 -> 11522896
A22: Projeções - CG + Capex | E22: Caixa | F22: 372047 | G22: 951166 | H22: 585920 | I22: 714734 | J22: 690324 | K22: 591815 | L22: 409601 | M22: 1029383 | N22: 1718025 | O22: 1345475 | P22: 1644981
A23: Projeções 2023 | E23: Títulos, valores mobiliários e aplicações financeiras | F23: 833799 | G23: 725095 | H23: 457300 | I23: 1718520 | J23: 4136909 | K23: 5182010 | L23: 7918780 | M23: 17622842 | N23: 11024128 | O23: 9600835 | P23: 10825574
A24: Processos | E24: Instrumentos financeiros derivativos | F24: 0 | G24: 0 | H24: 0 | I24: 0 | J24: 22013 | K24: 32233 | L24: 80380 | M24: 147 | N24: 86 | O24: 29181 | P24: 31840
E25: Contas a receber | F25: 930511 | G25: 1007831 | H25: 1021422 | I25: 1211836 | J25: 1334813 | K25: 1755137 | L25: 1934446 | M25: 3260329 | N25: 4433345 | O25: 5106680 | P25: 5565636
E26: Estoques | F26: 293987 | G26: 199270 | H26: 164626 | I26: 246147 | J26: 261987 | K26: 306037 | L26: 213017 | M26: 525950 | N26: 1694320 | O26: 2890509 | P26: 2893514
E27: Ativo imobilizado disponibilizado para venda | F27: 172786 | G27: 226336 | H27: 331249 | I27: 313390 | J27: 397784 | K27: 541188 | L27: 320879 | M27: 431962 | N27: 1527738 | O27: 1262241 | P27: 1642618
E28: Tributos a recuperar | F28: 156041 | G28: 178817 | H28: 45573 | I28: 125015 | J28: 117507 | K28: 155284 | L28: 160490 | M28: 325496 | N28: 361125 | O28: 499765 | P28: 526697
E29: Imposto de renda e contribuição social a recuperar | F29: 0 | G29: 0 | H29: 50027 | I29: 97196 | J29: 110149 | K29: 147266 | L29: 298451 | M29: 227643 | N29: 577912 | O29: 855076 | P29: 842978
E30: Despesas antecipadas | F30: 36070 | G30: 28290 | H30: 12891 | I30: 18673 | J30: 25583 | K30: 42874 | L30: 58314 | M30: 67977 | N30: 98457 | O30: 127725 | P30: 393757
E31: Dividendos a receber | F31: 0 | G31: 0 | H31: 0 | I31: 0 | J31: 0 | K31: 0 | L31: 0 | M31: 0 | N31: 0 | O31: 0 | P31: 0
E32: Partes relacionadas | F32: 0 | G32: 0 | H32: 0 | I32: 0 | J32: 0 | K32: 0 | L32: 0 | M32: 0 | N32: 253 | O32: 180 | P32: 5943
E33: Adiantamentos a terceiros | F33: 0 | G33: 0 | H33: 29420 | I33: 27687 | J33: 58763 | K33: 82420 | L33: 43689 | M33: 69140 | N33: 111317 | O33: 380240 | P33: 388419
E34: Outros créditos | F34: 59152 | G34: 54238 | H34: 18272 | I34: 15263 | J34: 35488 | K34: 54568 | L34: 57825 | M34: 381 | N34: 86140 | O34: 62668 | P34: 97865
E35: Ativo Não Circulante | F35: =SUM(F36:F50) -> 4610838 | G35: =SUM(G36:G50) -> 5371552 | H35: =SUM(H36:H50) -> 6151683 | I35: =SUM(I36:I50) -> 7012463 | J35: =SUM(J36:J50) -> 8682634 | K35: =SUM(K36:K50) -> 11357402 | L35: =SUM(L36:L50) -> 14066376 | M35: =SUM(M36:M50) -> 24406944 | ... P35: =SUM(P36:P50) -> 50170800
E36: Títulos. valores mobiliários e aplicações financeiras | F36: 19746 | G36: 10376 | H36: 0 | I36: 5584 | J36: 4532 | K36: 655 | L36: 149483 | M36: 9264 | N36: 160116 | O36: 178226 | P36: 174202
E37: Instrumentos financeiros derivativos | F37: 9906 | G37: 71462 | H37: 36037 | I37: 108252 | J37: 438160 | K37: 638400 | L37: 334642 | M37: 58733 | N37: 184154 | O37: 873062 | P37: 792896
E38: Contas a receber | F38: 74085 | G38: 15792 | H38: 108356 | I38: 120603 | J38: 111868 | K38: 88321 | L38: 104684 | M38: 134627 | N38: 190197 | O38: 494197 | P38: 525982
E39: Tributos a recuperar | F39: 32440 | G39: 23518 | H39: 42604 | I39: 61930 | J39: 114222 | K39: 138466 | L39: 151909 | M39: 231145 | N39: 448366 | O39: 384773 | P39: 410331
E40: Imposto de renda e contribuição social a recuperar | F40: 0 | G40: 0 | H40: 19864 | I40: 20307 | J40: 24312 | K40: 34929 | L40: 66664 | M40: 127733 | N40: 155806 | O40: 114026 | P40: 111898
E41: Depósitos judiciais | F41: 44175 | G41: 42309 | H41: 120704 | I41: 62335 | J41: 73400 | K41: 76353 | L41: 75532 | M41: 103303 | N41: 105475 | O41: 118518 | P41: 139599
E42: Fundos para capitalizações de concessionárias | F42: 0 | G42: 0 | H42: 52642 | I42: 39692 | J42: 0 | K42: 0 | L42: 0 | M42: 0 | N42: 0 | O42: 0 | P42: 0
E43: Imposto de renda e contribuição social diferidos | F43: 13727 | G43: 15635 | H43: 31438 | I43: 60626 | J43: 83620 | K43: 138431 | L43: 161215 | M43: 407120 | N43: 1177823 | O43: 1591413 | P43: 1807660
E44: Despesas antecipadas | F44: 7400 | G44: 0 | H44: 0 | I44: 0 | J44: 0 | K44: 0 | L44: 0 | M44: 0 | N44: 0 | O44: 0 | P44: 0
E45: Partes relacionadas | F45: 67 | G45: 410 | H45: 76 | I45: 188 | J45: 346 | K45: 0 | L45: 0 | M45: 0 | N45: 791 | O45: 942 | P45: 942
E46: Ativo de indenização por combinação de negócios | F46: 0 | G46: 0 | H46: 0 | I46: 0 | J46: 0 | K46: 0 | L46: 103783 | M46: 281432 | N46: 299342 | O46: 604600 | P46: 597902
E47: Outros créditos | F47: 72381 | G47: 64463 | H47: 6035 | I47: 3634 | J47: 64437 | K47: 82391 | L47: 82984 | M47: 108782 | N47: 112804 | O47: 239468 | P47: 200190
... E50: Intangível | F50: 330469 | G50: 361790 | H50: 346029 | I50: 471719 | J50: 484576 | K50: 537735 | L50: 1071420 | M50: 1346837 | N50: 3026787 | O50: 3516655 | P50: 3680310
E51: Passivo Total | F51: =SUM(F52,F71) -> 6420352 | G51: =SUM(G52,G71) -> 7722722 | H51: =SUM(H52,H71) -> 8259394 | I51: =SUM(I52,I71) -> 10311604 | J51: =SUM(J52,J71) -> 14625455 | K51: =SUM(K52,K71) -> 17888271 | L51: =SUM(L52,L71) -> 22338398 | M51: =SUM(M52,M71) -> 42143934 | ... P51: =SUM(P52,P71) -> 68308179
E52: Passivo Circulante | F52: =SUM(F53:F70) -> 1871356 | G52: =SUM(G53:G70) -> 2414240 | H52: =SUM(H53:H70) -> 3194162 | I52: =SUM(I53:I70) -> 3129688 | J52: =SUM(J53:J70) -> 4035478 | K52: =SUM(K53:K70) -> 4678968 | L52: =SUM(L53:L70) -> 5524858 | M52: =SUM(M53:M70) -> 7137334 | ... P52: =SUM(P53:P70) -> 16866873
E53: Fornecedores | F53: 316952 | G53: 505199 | H53: 992368 | I53: 878274 | J53: 1195407 | K53: 1691713 | L53: 2135298 | M53: 3374264 | N53: 5724420 | O53: 6391443 | P53: 6211036
E54: Floor plan | F54: 56313 | G54: 33982 | H54: 28387 | I54: 72051 | J54: 93588 | K54: 106735 | L54: 71844 | M54: 175536 | N54: 378753 | O54: 377000 | P54: 468912
E55: Risco sacado a pagar - montadoras | F55: 378610 | G55: 625195 | H55: 551359 | I55: 248148 | J55: 0 | K55: 12051 | L55: 157923 | M55: 0 | N55: 72920 | O55: 115582 | P55: 55196
E56: Empréstimos e financiamentos | F56: 405601 | G56: 526829 | H56: 888916 | I56: 982697 | J56: 1495151 | K56: 1171988 | L56: 1284761 | M56: 765352 | N56: 1427853 | O56: 2372351 | P56: 3004563
E57: Debêntures | F57: 164041 | G57: 126794 | H57: 142242 | I57: 284417 | J57: 483667 | K57: 694901 | L57: 592595 | M57: 661877 | N57: 2361078 | O57: 1320557 | P57: 1356772
E58: Arrendamentos a pagar | F58: 134279 | G58: 160719 | H58: 165716 | I58: 142329 | J58: 91402 | K58: 140850 | L58: 131092 | M58: 118833 | N58: 71637 | O58: 124609 | P58: 132263
E59: Arrendamentos por direito de uso | F59: 0 | G59: 0 | H59: 0 | I59: 0 | J59: 0 | K59: 113869 | L59: 101600 | M59: 197769 | N59: 291430 | O59: 364875 | P59: 355156
E60: Cessão de direitos creditórios | F60: 0 | G60: 0 | H60: 0 | I60: 6043 | J60: 7410 | K60: 6043 | L60: 6043 | M60: 6043 | N60: 698404 | O60: 1129946 | P60: 1707822
E61: Obrigações sociais e trabalhistas | F61: 163623 | G61: 163687 | H61: 179418 | I61: 211652 | J61: 238034 | K61: 231374 | L61: 270006 | M61: 408154 | N61: 625156 | O61: 727767 | P61: 762333
E62: Imposto de renda e contribuição social a recolher | F62: 3851 | G62: 3625 | H62: 11528 | I62: 8907 | J62: 12356 | K62: 3094 | L62: 18679 | M62: 45865 | N62: 99818 | O62: 45215 | P62: 53614
E63: Instrumentos financeiros derivativos | F63: 0 | G63: 0 | H63: 0 | I63: 0 | J63: 0 | K63: 0 | L63: 0 | M63: 271251 | N63: 561290 | O63: 723681 | P63: 750587
E64: Tributos a recolher | F64: =44840-F62 -> 40989 | G64: =56608-3625 -> 52983 | H64: 51968 | I64: 76093 | J64: 75856 | K64: 83162 | L64: 103291 | M64: 220213 | N64: 385329 | O64: 455584 | P64: 473734
E65: Dividendos e juros sobre capital próprio a pagar | F65: 17205 | G65: 11106 | H65: 0 | I65: 0 | J65: 27541 | K65: 70587 | L65: 97856 | M65: 263280 | N65: 259201 | O65: 123657 | P65: 133710
E66: Adiantamentos de clientes | F66: 105144 | G66: 83747 | H66: 29101 | I66: 50844 | J66: 139345 | K66: 175700 | L66: 177170 | M66: 207720 | N66: 428469 | O66: 657601 | P66: 776501
E67: Compra de Ações Controlada a Termo | F67: 0 | G67: 0 | H67: 0 | I67: 0 | J67: 0 | K67: 0 | L67: 0 | M67: 0 | N67: 130606 | O67: 0 | P67: 132660
E68: Partes relacionadas | F68: 0 | G68: 0 | H68: 1782 | I68: 553 | J68: 246 | K68: 3056 | L68: 550 | M68: 453 | N68: 499 | O68: 511 | P68: 125
E69: Outras contas a pagar | F69: 84748 | G69: 120374 | H69: 151377 | I69: 167680 | J69: 175475 | K69: 173845 | L69: 376150 | M69: 420724 | N69: 289150 | O69: 130097 | P69: 179758
E70: Obrigações a pagar por aquisição de emrpesas | N70: 153852 | O70: 268291 | P70: 312131
E71: Passivo Não Circulante | F71: =SUM(F72:F86) -> 4548996 | G71: =SUM(G72:G86) -> 5308482 | H71: =SUM(H72:H86) -> 5065232 | I71: =SUM(I72:I86) -> 7181916 | J71: =SUM(J72:J86) -> 10589977 | K71: =SUM(K72:K86) -> 13209303 | L71: =SUM(L72:L86) -> 16813540 | M71: =SUM(M72:M86) -> 35006600 | ... P71: =SUM(P72:P86) -> 51441306
E72: Empréstimos e financiamentos | F72: 2734029 | G72: 3213632 | H72: 2957220 | I72: 4809871 | J72: 7092551 | K72: 7050051 | L72: 9046647 | M72: 17962499 | N72: 15397022 | O72: 18686784 | P72: 20436000
E73: Debêntures | F73: 1264377 | G73: 1487751 | H73: 1406375 | I73: 1731065 | J73: 2687075 | K73: 4676855 | L73: 5968161 | M73: 13874041 | N73: 18714687 | O73: 20786421 | P73: 22291780
E74: Arrendamentos a pagar | F74: 139933 | G74: 193606 | H74: 189017 | I74: 70448 | J74: 151512 | K74: 260762 | L74: 182314 | M74: 137126 | N74: 161623 | O74: 147481 | P74: 127488
E75: Arrendamentos por direito de uso | F75: 0 | G75: 0 | H75: 0 | I75: 0 | J75: 0 | K75: 403831 | L75: 390965 | M75: 660011 | N75: 1399556 | O75: 1499744 | P75: 1558808
E76: Instrumentos financeiros derivativos | F76: 3188 | G76: 0 | H76: 12223 | I76: 0 | J76: 0 | K76: 0 | L76: 0 | M76: 409000 | N76: 2670500 | O76: 1163486 | P76: 998229
E77: Partes relacionadas | F77: 525 | G77: 1017 | H77: 0 | I77: 0 | J77: 0 | K77: 0 | L77: 528 | M77: 528 | N77: 28047 | O77: 528 | P77: 528
E78: Cessão de direitos creditórios | F78: 0 | G78: 0 | H78: 0 | I78: 24171 | J78: 16761 | K78: 12085 | L78: 6043 | M78: 0 | N78: 1318613 | O78: 1191701 | P78: 1196067
E79: Tributos a recolher | F79: 2021 | G79: 1805 | H79: 2701 | I79: 1705 | J79: 1103 | K79: 1095 | L79: 15992 | M79: 26995 | N79: 32945 | O79: 31356 | P79: 31257
E80: Provisão para demandas judiciais e administrativas | F80: 45131 | G80: 43354 | H80: 73712 | I80: 71463 | J80: 75563 | K80: 67829 | L80: 181865 | M80: 356544 | N80: 415333 | O80: 766066 | P80: 770927
E81: Imposto de renda e contribuição social diferidos | F81: 254860 | G81: 269451 | H81: 197088 | I81: 288893 | J81: 361234 | K81: 574120 | L81: 621467 | M81: 1038582 | N81: 1205986 | O81: 1494779 | P81: 1614904
E82: Obrigações por aquisições de empresas | F82: 0 | G82: 0 | H82: 0 | I82: 0 | J82: 0 | K82: 93077 | L82: 0 | M82: 0 | N82: 641975 | O82: 971666 | P82: 1084022
E83: Aterro sanitário – custo de encerramento | F83: 0 | G83: 0 | H83: 0 | I83: 0 | J83: 0 | K83: 0 | L83: - | M83: 105024 | N83: 9693 | O83: 12321 | P83: 11592
E84: Obrigações sociais e trabalhistas | O84: 183941 | P84: 184584
E85: Compra de ações de controladas a termo sintético | F85: 0 | G85: 0 | H85: 0 | I85: 0 | J85: 0 | K85: 0 | L85: 0 | M85: 0 | N85: 0 | O85: 1058486 | P85: 1058486
E86: Outras contas a pagar | F86: 104932 | G86: 97866 | H86: 226896 | I86: 184300 | J86: 204178 | K86: 69598 | L86: 399558 | M86: 436250 | N86: 121916 | O86: 65581 | P86: 76634
E87: Patrimônio Líquido | F87: =SUM(F88:F96) -> 1044879 | G87: =SUM(G88:G96) -> 1019873 | H87: =SUM(H88:H96) -> 608989 | I87: =SUM(I88:I96) -> 1189320 | J87: =SUM(J88:J96) -> 1248499 | K87: =SUM(K88:K96) -> 2379963 | L87: =SUM(L88:L96) -> 3223850 | M87: =SUM(M88:M96) -> 5824260 | ... P87: =SUM(P88:P96) -> 6722743
E88: Capital social | F88: 660495 | G88: 660395 | H88: 660395 | I88: 660395 | J88: 681202 | K88: 695069 | L88: 713975 | M88: 1164330 | N88: 1174362 | O88: 1174362 | P88: 1174362
E89: Reservas de capital | F89: 6196 | G89: 8789 | H89: 14060 | I89: 21961 | J89: 33731 | K89: 50951 | L89: 575114 | M89: 1633343 | N89: 1903189 | O89: 2252268 | P89: 2252268
E90: Ações em tesouraria | F90: -53509 | G90: -54133 | H90: -3741 | I90: -460 | J90: -103925 | K90: -460 | L90: -10503 | M90: -151633 | N90: -148114 | O90: -151047 | P90: -151047
E91: Reservas de lucros | F91: 424344 | G91: 400167 | H91: 0 | I91: 0 | J91: 17841 | K91: 159121 | L91: 262336 | M91: 877940 | N91: 925757 | O91: 430539 | P91: 417483
E92: Prejuízos Acumulados | F92: 0 | G92: 0 | H92: -66359 | I92: -72329 | J92: 0 | K92: 0 | L92: 0 | M92: 0 | N92: 0 | O92: 0
E93: Outros resultados abrangentes | F93: 0 | G93: 0 | H93: 0 | I93: -5400 | J93: -8273 | K93: 158635 | L93: 2103 | M93: -255956 | N93: -769101 | O93: -537800 | P93: -578046
E94: Ajustes de avaliação patrimonial | F94: 7327 | G94: 4634 | H94: 4634 | I94: 82621 | J94: 132569 | K94: 286760 | L94: 470044 | M94: 517257 | N94: 517257 | O94: 132296 | P94: 132296
E95: Outros ajustes patrimoniais reflexos de controladas | F95: 0 | G95: 0 | H95: 0 | I95: 0 | J95: 0 | K95: -3031 | L95: -120471 | M95: -269203 | N95: -721574 | O95: 25628 | P95: -30431
E96: Participações de não controladores | F96: 26 | G96: 21 | H96: 0 | I96: 502532 | J96: 495354 | K96: 1032918 | L96: 1331252 | M96: 2308182 | N96: 2699977 | O96: 3425486 | P96: 3505858

Sheet Painel de Índices
E3: =Dashboard!H3 -> SIMPAR (SIMH3)
A7: Páginas
A8: Dashboard
A9: WACC | F9: 2014 | G9: 2015 | H9: 2016 | I9: 2017 | J9: 2018 | K9: 2019 | L9: 2020 | M9: 2021 | N9: 2022 | O9: 2023
A10: DRE Consolidado | E10: Liquidez Geral | F10: ='Balanço Patrimonial'!F17/'Balanço Patrimonial'!F51 -> 1.1627448 | G10: ='Balanço Patrimonial'!G17/'Balanço Patrimonial'!G51 -> 1.1320613 | H10: ='Balanço Patrimonial'!H17/'Balanço Patrimonial'!H51 -> 1.0737329 | I10: ='Balanço Patrimonial'!I17/'Balanço Patrimonial'!I51 -> 1.115338 | J10: ='Balanço Patrimonial'!J17/'Balanço Patrimonial'!J51 -> 1.0853648 | K10: ='Balanço Patrimonial'!K17/'Balanço Patrimonial'!K51 -> 1.131928 | L10: ='Balanço Patrimonial'!L17/'Balanço Patrimonial'!L51 -> 1.1443188 | M10: ='Balanço Patrimonial'!M17/'Balanço Patrimonial'!M51 -> 1.1381992 | ... O10: ='Balanço Patrimonial'!O17/'Balanço Patrimonial'!O51 -> 1.1065125
A11: DRE + DCF | E11: Liquidez Corrente | F11: ='Balanço Patrimonial'!F18/'Balanço Patrimonial'!F52 -> 1.5253073 | G11: ='Balanço Patrimonial'!G18/'Balanço Patrimonial'!G52 -> 1.3963164 | H11: ='Balanço Patrimonial'!H18/'Balanço Patrimonial'!H52 -> 0.85052042 | I11: ='Balanço Patrimonial'!I18/'Balanço Patrimonial'!I52 -> 1.4341561 | J11: ='Balanço Patrimonial'!J18/'Balanço Patrimonial'!J52 -> 1.7820243 | K11: ='Balanço Patrimonial'!K18/'Balanço Patrimonial'!K52 -> 1.9001694 | L11: ='Balanço Patrimonial'!L18/'Balanço Patrimonial'!L52 -> 2.0807543 | M11: ='Balanço Patrimonial'!M18/'Balanço Patrimonial'!M52 -> 3.3011276 | ... O11: ='Balanço Patrimonial'!O18/'Balanço Patrimonial'!O52 -> 1.4456854
A12: DRE - Contas Abertas | E12: Liquidez Seca | F12: =('Balanço Patrimonial'!F18-'Balanço Patrimonial'!F26)/'Balanço Patrimonial'!F52 -> 1.3682089 | G12: =('Balanço Patrimonial'!G18-'Balanço Patrimonial'!G26)/'Balanço Patrimonial'!G52 -> 1.313777 | H12: =('Balanço Patrimonial'!H18-'Balanço Patrimonial'!H26)/'Balanço Patrimonial'!H52 -> 0.79898077 | I12: =('Balanço Patrimonial'!I18-'Balanço Patrimonial'!I26)/'Balanço Patrimonial'!I52 -> 1.355507 | J12: =('Balanço Patrimonial'!J18-'Balanço Patrimonial'!J26)/'Balanço Patrimonial'!J52 -> 1.7171034 | K12: =('Balanço Patrimonial'!K18-'Balanço Patrimonial'!K26)/'Balanço Patrimonial'!K52 -> 1.8347625 | L12: =('Balanço Patrimonial'!L18-'Balanço Patrimonial'!L26)/'Balanço Patrimonial'!L52 -> 2.0421982 | M12: =('Balanço Patrimonial'!M18-'Balanço Patrimonial'!M26)/'Balanço Patrimonial'!M52 -> 3.2274376 | N12: =('Balanço Patrimonial'!L18-'Balanço Patrimonial'!N26)/'Balanço Patrimonial'!N52 -> 0.7021237 | O12: =('Balanço Patrimonial'!M18-'Balanço Patrimonial'!O26)/'Balanço Patrimonial'!O52 -> 1.3484934
A13: Balanço Patrimonial | E13: Liquidez Imediata | F13: =('Balanço Patrimonial'!F19+'Balanço Patrimonial'!F23)/'Balanço Patrimonial'!F52 -> 1.0899289 | G13: =('Balanço Patrimonial'!G19+'Balanço Patrimonial'!G23)/'Balanço Patrimonial'!G52 -> 0.99466333 | H13: =('Balanço Patrimonial'!H19+'Balanço Patrimonial'!H23)/'Balanço Patrimonial'!H52 -> 0.46976954 | I13: =('Balanço Patrimonial'!I19+'Balanço Patrimonial'!I23)/'Balanço Patrimonial'!I52 -> 1.3265776 | J13: =('Balanço Patrimonial'!J19+'Balanço Patrimonial'!J23)/'Balanço Patrimonial'!J52 -> 2.2213334 | K13: =('Balanço Patrimonial'!K19+'Balanço Patrimonial'!K23)/'Balanço Patrimonial'!K52 -> 2.3415067 | L13: =('Balanço Patrimonial'!L19+'Balanço Patrimonial'!L23)/'Balanço Patrimonial'!L52 -> 2.9407382 | M13: =('Balanço Patrimonial'!M19+'Balanço Patrimonial'!M23)/'Balanço Patrimonial'!M52 -> 5.0824393 | ... O13: =('Balanço Patrimonial'!O19+'Balanço Patrimonial'!O23)/'Balanço Patrimonial'!O52 -> 1.3404304
A14: Painel de Índices
A15: Projeções - Receita e EBIT
A16: Projeções - CG + Capex
A17: Projeções 2023 | F17: 2014 | G17: 2015 | H17: 2016 | I17: 2017 | J17: 2018 | K17: 2019 | L17: 2020 | M17: 2021 | N17: 2022 | O17: 2023
A18: Processos | E18: Retorno sobre o Equity (ROE) | F18: ='DRE Consolidado'!K46/'Balanço Patrimonial'!F87 -> 0.069328602 | G18: ='DRE Consolidado'!L46/'Balanço Patrimonial'!G87 -> 0.045849826 | H18: ='DRE Consolidado'!M46/'Balanço Patrimonial'!H87 -> -0.30078376 | I18: ='DRE Consolidado'!N46/'Balanço Patrimonial'!I87 -> 0.014056772 | J18: ='DRE Consolidado'!O46/'Balanço Patrimonial'!J87 -> 0.15151794 | K18: ='DRE Consolidado'!P46/'Balanço Patrimonial'!K87 -> 0.13387813 | L18: ='DRE Consolidado'!Q46/'Balanço Patrimonial'!L87 -> 0.13215224 | M18: ='DRE Consolidado'!R46/'Balanço Patrimonial'!M87 -> 0.22817491 | ... O18: ='DRE Consolidado'!T46/'Balanço Patrimonial'!O87 -> -0.092102293
E19: Retorno sobre o Ativo (ROA) | F19: ='DRE Consolidado'!K46/'Balanço Patrimonial'!F17 -> 0.0097036515 | G19: ='DRE Consolidado'!L46/'Balanço Patrimonial'!G17 -> 0.0053486408 | H19: ='DRE Consolidado'!M46/'Balanço Patrimonial'!H17 -> -0.020654724 | I19: ='DRE Consolidado'!N46/'Balanço Patrimonial'!I17 -> 0.0014536223 | J19: ='DRE Consolidado'!O46/'Balanço Patrimonial'!J17 -> 0.011917006 | K19: ='DRE Consolidado'!P46/'Balanço Patrimonial'!K17 -> 0.01573594 | L19: ='DRE Consolidado'!Q46/'Balanço Patrimonial'!L17 -> 0.016666727 | M19: ='DRE Consolidado'!R46/'Balanço Patrimonial'!M17 -> 0.027704816 | ... O19: ='DRE Consolidado'!T46/'Balanço Patrimonial'!O17 -> -0.0088657336
E20: ROIC | F20: ='DRE + DCF'!K39 -> 0.087496051 | G20: ='DRE + DCF'!L39 -> 0.0927418 | H20: ='DRE + DCF'!M39 -> 0.090692945 | I20: ='DRE + DCF'!N39 -> 0.092089722 | J20: ='DRE + DCF'!O39 -> 0.098681459 | K20: ='DRE + DCF'!P39 -> 0.10811252 | L20: ='DRE + DCF'!Q39 -> 0.084555268 | M20: ='DRE + DCF'!R39 -> 0.12089622 | ... O20: ='DRE + DCF'!T39 -> 0.13630931
J23: -624650
F24: 2014 | G24: 2015 | H24: 2016 | I24: 2017 | J24: 2018 | K24: 2019 | L24: 2020 | M24: 2021 | N24: 2022 | O24: 2023
E25: Divida Líquida/EBITDA | F25: =SUM('Balanço Patrimonial'!F54:F59,'Balanço Patrimonial'!F72:F75,-'Balanço Patrimonial'!F19,-'Balanço Patrimonial'!F23,-'Balanço Patrimonial'!F36)/('DRE Consolidado'!K35+'Projeções - CG + Capex'!K57+'DRE Consolidado'!K56) -> 3.7030083 | G25: =SUM('Balanço Patrimonial'!G54:G59,'Balanço Patrimonial'!G72:G75,-'Balanço Patrimonial'!G19,-'Balanço Patrimonial'!G23,-'Balanço Patrimonial'!G36)/('DRE Consolidado'!L35+'Projeções - CG + Capex'!L57+'DRE Consolidado'!L56) -> 3.6231525 | H25: =SUM('Balanço Patrimonial'!H54:H59,'Balanço Patrimonial'!H72:H75,-'Balanço Patrimonial'!H19,-'Balanço Patrimonial'!H23,-'Balanço Patrimonial'!H36)/('DRE Consolidado'!M35+'Projeções - CG + Capex'!M57+'DRE Consolidado'!M56) -> 4.6164919 | I25: =SUM('Balanço Patrimonial'!I54:I59,'Balanço Patrimonial'!I72:I75,-'Balanço Patrimonial'!I19,-'Balanço Patrimonial'!I23,-'Balanço Patrimonial'!I36)/('DRE Consolidado'!N35+'Projeções - CG + Capex'!N57+'DRE Consolidado'!N56) -> 3.4008004 | J25: =SUM('Balanço Patrimonial'!J54:J59,'Balanço Patrimonial'!J72:J75,-'Balanço Patrimonial'!J19,-'Balanço Patrimonial'!J23,-'Balanço Patrimonial'!J36)/('DRE Consolidado'!O35+'Projeções - CG + Capex'!O57+'DRE Consolidado'!O56) -> 1.9569361 | K25: =SUM('Balanço Patrimonial'!K54:K59,'Balanço Patrimonial'!K72:K75,-'Balanço Patrimonial'!K19,-'Balanço Patrimonial'!K23,-'Balanço Patrimonial'!K36)/('DRE Consolidado'!P35+'Projeções - CG + Capex'!P57+'DRE Consolidado'!P56) -> 1.7370326 | L25: =SUM('Balanço Patrimonial'!L54:L59,'Balanço Patrimonial'!L72:L75,-'Balanço Patrimonial'!L19,-'Balanço Patrimonial'!L23,-'Balanço Patrimonial'!L36)/('DRE Consolidado'!Q35+'Projeções - CG + Capex'!Q57+'DRE Consolidado'!Q56) -> 0.71489471 | M25: =SUM('Balanço Patrimonial'!M54:M59,'Balanço Patrimonial'!M72:M75,-'Balanço Patrimonial'!M19,-'Balanço Patrimonial'!M23,-'Balanço Patrimonial'!M36)/('DRE Consolidado'!R35+'Projeções - CG + Capex'!R57+'DRE Consolidado'!R56) -> -0.41322803 | ... O25: =SUM('Balanço Patrimonial'!O54:O59,'Balanço Patrimonial'!O72:O75,-'Balanço Patrimonial'!O19,-'Balanço Patrimonial'!O23,-'Balanço Patrimonial'!O36)/('DRE Consolidado'!T35+'Projeções - CG + Capex'!T57+'DRE Consolidado'!T56) -> 2.9834778
E26: Cobertura de Juros | F26: =-'DRE Consolidado'!K35/'DRE Consolidado'!K41 -> 1.0036056 | G26: =-'DRE Consolidado'!L35/'DRE Consolidado'!L41 -> 0.81634866 | H26: =-'DRE Consolidado'!M35/'DRE Consolidado'!M41 -> 0.525048 | I26: =-'DRE Consolidado'!N35/'DRE Consolidado'!N41 -> 0.80044677 | J26: =-'DRE Consolidado'!O35/'DRE Consolidado'!O41 -> 0.96165173 | K26: =-'DRE Consolidado'!P35/'DRE Consolidado'!P41 -> 1.0580479 | L26: =-'DRE Consolidado'!Q35/'DRE Consolidado'!Q41 -> 0.97702528 | M26: =-'DRE Consolidado'!R35/'DRE Consolidado'!R41 -> 1.6021613 | ... O26: =-'DRE Consolidado'!T35/'DRE Consolidado'!T41 -> 0.69613316
E27: Dívida/Ativo | F27: =SUM('Balanço Patrimonial'!F54:F59,'Balanço Patrimonial'!F72:F75)/'Balanço Patrimonial'!F17 -> 0.7069015 | G27: =SUM('Balanço Patrimonial'!G54:G59,'Balanço Patrimonial'!G72:G75)/'Balanço Patrimonial'!G17 -> 0.72844596 | H27: =SUM('Balanço Patrimonial'!H54:H59,'Balanço Patrimonial'!H72:H75)/'Balanço Patrimonial'!H17 -> 0.71368501 | I27: =SUM('Balanço Patrimonial'!I54:I59,'Balanço Patrimonial'!I72:I75)/'Balanço Patrimonial'!I17 -> 0.72524834 | J27: =SUM('Balanço Patrimonial'!J54:J59,'Balanço Patrimonial'!J72:J75)/'Balanço Patrimonial'!J17 -> 0.76193657 | K27: =SUM('Balanço Patrimonial'!K54:K59,'Balanço Patrimonial'!K72:K75)/'Balanço Patrimonial'!K17 -> 0.72262564 | L27: =SUM('Balanço Patrimonial'!L54:L59,'Balanço Patrimonial'!L72:L75)/'Balanço Patrimonial'!L17 -> 0.70134293 | M27: =SUM('Balanço Patrimonial'!M54:M59,'Balanço Patrimonial'!M72:M75)/'Balanço Patrimonial'!M17 -> 0.72033239 | ... O27: =SUM('Balanço Patrimonial'!O54:O59,'Balanço Patrimonial'!O72:O75)/'Balanço Patrimonial'!O17 -> 0.65290641
E28: Dívida/Patrimônio Líquido | F28: =SUM('Balanço Patrimonial'!F54:F59,'Balanço Patrimonial'!F72:F75)/'Balanço Patrimonial'!F87 -> 5.0505207 | G28: =SUM('Balanço Patrimonial'!G54:G59,'Balanço Patrimonial'!G72:G75)/'Balanço Patrimonial'!G87 -> 6.2444128 | H28: =SUM('Balanço Patrimonial'!H54:H59,'Balanço Patrimonial'!H72:H75)/'Balanço Patrimonial'!H87 -> 10.393015 | I28: =SUM('Balanço Patrimonial'!I54:I59,'Balanço Patrimonial'!I72:I75)/'Balanço Patrimonial'!I87 -> 7.0132731 | J28: =SUM('Balanço Patrimonial'!J54:J59,'Balanço Patrimonial'!J72:J75)/'Balanço Patrimonial'!J87 -> 9.6875897 | K28: =SUM('Balanço Patrimonial'!K54:K59,'Balanço Patrimonial'!K72:K75)/'Balanço Patrimonial'!K87 -> 6.1479498 | L28: =SUM('Balanço Patrimonial'!L54:L59,'Balanço Patrimonial'!L72:L75)/'Balanço Patrimonial'!L87 -> 5.5610224 | M28: =SUM('Balanço Patrimonial'!M54:M59,'Balanço Patrimonial'!M72:M75)/'Balanço Patrimonial'!M87 -> 5.9326067 | ... O28: =SUM('Balanço Patrimonial'!O54:O59,'Balanço Patrimonial'!O72:O75)/'Balanço Patrimonial'!O87 -> 6.7827639
E29: Dívida/(Dívida + Patrimônio Líquido) | F29: =SUM('Balanço Patrimonial'!F54:F59,'Balanço Patrimonial'!F72:F75)/(SUM('Balanço Patrimonial'!F54:F59,'Balanço Patrimonial'!F72:F75)+'Balanço Patrimonial'!F87) -> 0.83472497 | G29: =SUM('Balanço Patrimonial'!G54:G59,'Balanço Patrimonial'!G72:G75)/(SUM('Balanço Patrimonial'!G54:G59,'Balanço Patrimonial'!G72:G75)+'Balanço Patrimonial'!G87) -> 0.86196259 | H29: =SUM('Balanço Patrimonial'!H54:H59,'Balanço Patrimonial'!H72:H75)/(SUM('Balanço Patrimonial'!H54:H59,'Balanço Patrimonial'!H72:H75)+'Balanço Patrimonial'!H87) -> 0.91222692 | I29: =SUM('Balanço Patrimonial'!I54:I59,'Balanço Patrimonial'!I72:I75)/(SUM('Balanço Patrimonial'!I54:I59,'Balanço Patrimonial'!I72:I75)+'Balanço Patrimonial'!I87) -> 0.87520705 | J29: =SUM('Balanço Patrimonial'!J54:J59,'Balanço Patrimonial'!J72:J75)/(SUM('Balanço Patrimonial'!J54:J59,'Balanço Patrimonial'!J72:J75)+'Balanço Patrimonial'!J87) -> 0.90643353 | K29: =SUM('Balanço Patrimonial'!K54:K59,'Balanço Patrimonial'!K72:K75)/(SUM('Balanço Patrimonial'!K54:K59,'Balanço Patrimonial'!K72:K75)+'Balanço Patrimonial'!K87) -> 0.86009974 | L29: =SUM('Balanço Patrimonial'!L54:L59,'Balanço Patrimonial'!L72:L75)/(SUM('Balanço Patrimonial'!L54:L59,'Balanço Patrimonial'!L72:L75)+'Balanço Patrimonial'!L87) -> 0.84758473 | M29: =SUM('Balanço Patrimonial'!M54:M59,'Balanço Patrimonial'!M72:M75)/(SUM('Balanço Patrimonial'!M54:M59,'Balanço Patrimonial'!M72:M75)+'Balanço Patrimonial'!M87) -> 0.85575411 | ... O29: =SUM('Balanço Patrimonial'!O54:O59,'Balanço Patrimonial'!O72:O75)/(SUM('Balanço Patrimonial'!O54:O59,'Balanço Patrimonial'!O72:O75)+'Balanço Patrimonial'!O87) -> 0.87151094
K32: -67020
F33: 2014 | G33: 2015 | H33: 2016 | I33: 2017 | J33: 2018 | K33: 2019 | L33: 2020 | M33: 2021 | N33: 2022 | O33: 2023
E34: Prazo Médio de Recebimento | F34: ='Balanço Patrimonial'!F25*365/'DRE Consolidado'!K13 -> 55.869667 | G34: ='Balanço Patrimonial'!G25*365/'DRE Consolidado'!L13 -> 56.063257 | H34: ='Balanço Patrimonial'!H25*365/'DRE Consolidado'!M13 -> 50.353847 | I34: ='Balanço Patrimonial'!I25*365/'DRE Consolidado'!N13 -> 53.942605 | J34: ='Balanço Patrimonial'!J25*365/'DRE Consolidado'!O13 -> 52.937311 | K34: ='Balanço Patrimonial'!K25*365/'DRE Consolidado'!P13 -> 59.679876 | L34: ='Balanço Patrimonial'!L25*365/'DRE Consolidado'!Q13 -> 64.927069 | M34: ='Balanço Patrimonial'!M25*365/'DRE Consolidado'!R13 -> 77.007107 | ... O34: ='Balanço Patrimonial'!O25*365/'DRE Consolidado'!T13 -> 52.485465
E35: Prazo Médio de Estoques | F35: ='Balanço Patrimonial'!F26*365/-'DRE Consolidado'!K18 -> 27.762313 | G35: ='Balanço Patrimonial'!G26*365/-'DRE Consolidado'!L18 -> 18.298043 | H35: ='Balanço Patrimonial'!H26*365/-'DRE Consolidado'!M18 -> 15.26372 | I35: ='Balanço Patrimonial'!I26*365/-'DRE Consolidado'!N18 -> 22.282365 | J35: ='Balanço Patrimonial'!J26*365/-'DRE Consolidado'!O18 -> 20.349176 | K35: ='Balanço Patrimonial'!K26*365/-'DRE Consolidado'!P18 -> 21.89129 | L35: ='Balanço Patrimonial'!L26*365/-'DRE Consolidado'!Q18 -> 15.042168 | M35: ='Balanço Patrimonial'!M26*365/-'DRE Consolidado'!R18 -> 26.281177 | ... O35: ='Balanço Patrimonial'!O26*365/-'DRE Consolidado'!T18 -> 44.573151
E36: Prazo Médio de Compras | F36: =-('Balanço Patrimonial'!F53+'Balanço Patrimonial'!F61)*365/('DRE Consolidado'!K18+'DRE Consolidado'!K23+'DRE Consolidado'!K56+'Projeções - CG + Capex'!K57) -> 43.97344 | G36: =-('Balanço Patrimonial'!G53+'Balanço Patrimonial'!G61)*365/('DRE Consolidado'!L18+'DRE Consolidado'!L23+'DRE Consolidado'!L56+'Projeções - CG + Capex'!L57) -> 60.728969 | H36: =-('Balanço Patrimonial'!H53+'Balanço Patrimonial'!H61)*365/('DRE Consolidado'!M18+'DRE Consolidado'!M23+'DRE Consolidado'!M56+'Projeções - CG + Capex'!M57) -> 102.12369 | I36: =-('Balanço Patrimonial'!I53+'Balanço Patrimonial'!I61)*365/('DRE Consolidado'!N18+'DRE Consolidado'!N23+'DRE Consolidado'!N56+'Projeções - CG + Capex'!N57) -> 92.776619 | J36: =-('Balanço Patrimonial'!J53+'Balanço Patrimonial'!J61)*365/('DRE Consolidado'!O18+'DRE Consolidado'!O23+'DRE Consolidado'!O56+'Projeções - CG + Capex'!O57) -> 107.47889 | K36: =-('Balanço Patrimonial'!K53+'Balanço Patrimonial'!K61)*365/('DRE Consolidado'!P18+'DRE Consolidado'!P23+'DRE Consolidado'!P56+'Projeções - CG + Capex'!P57) -> 139.10227 | L36: =-('Balanço Patrimonial'!L53+'Balanço Patrimonial'!L61)*365/('DRE Consolidado'!Q18+'DRE Consolidado'!Q23+'DRE Consolidado'!Q56+'Projeções - CG + Capex'!Q57) -> 173.95132 | M36: =-('Balanço Patrimonial'!M53+'Balanço Patrimonial'!M61)*365/('DRE Consolidado'!R18+'DRE Consolidado'!R23+'DRE Consolidado'!R56+'Projeções - CG + Capex'!R57) -> 181.68491 | ... O36: =-('Balanço Patrimonial'!O53+'Balanço Patrimonial'!O61)*365/('DRE Consolidado'!T18+'DRE Consolidado'!T23+'DRE Consolidado'!T56+'Projeções - CG + Capex'!T57) -> 110.8549
E37: Ciclo de Caixa | F37: =F34+F35-F36 -> 39.658541 | G37: =G34+G35-G36 -> 13.632331 | H37: =H34+H35-H36 -> -36.506125 | I37: =I34+I35-I36 -> -16.551649 | J37: =J34+J35-J36 -> -34.192406 | K37: =K34+K35-K36 -> -57.531105 | L37: =L34+L35-L36 -> -93.982082 | M37: =M34+M35-M36 -> -78.396626 | ... O37: =O34+O35-O36 -> -13.796283
F41: 2014 | G41: 2015 | H41: 2016 | I41: 2017 | J41: 2018 | K41: 2019 | L41: 2020 | M41: 2021 | N41: 2022 | O41: 2023
E42: Proventos por ação | F42: 0 | I42: 0 | J42: 0 | K42: 0 | L42: 0 | M42: 0.52083224 | N42: 0 | O42: 0
E43: Dividend Yield (12 meses) | F43: 0 | I43: 0 | J43: 0 | K43: 0 | L43: 0 | M43: 0.034152934 | N43: 0 | O43: 0
E44: Payout | F44: 0 | I44: 0 | J44: 0 | K44: 0 | L44: 0 | M44: 0.22965084 | N44: 0 | O44: 0
H48: -624650
F49: 2024 | G49: =F49+1 -> 2025 | H49: =G49+1 -> 2026 | I49: =H49+1 -> 2027 | J49: =I49+1 -> 2028
E50: EBITDA | F50: ='DRE Consolidado'!W76 -> 10673112 | G50: ='DRE Consolidado'!X76 -> 12207507 | H50: ='DRE Consolidado'!Y76 -> 13530227 | I50: ='DRE Consolidado'!Z76 -> 14681135 | J50: ='DRE Consolidado'!AA76 -> 15843161
E51: EBITDA - A | F51: 13683300
E52: Dívida Líquida para Covenant dos Bonds | F52: =30916700-F56-F57 -> 32111825
E53: Dívida Líquida Para Covenant Local | F53: 31605200 | G53: =F53-SUM(G54,G56) -> 35243913 | H53: =G53-SUM(H54,H56) -> 38963119 | I53: =H53-SUM(I54,I56) -> 42034040 | J53: =I53-SUM(J54,J56) -> 44656917
E54: Resultado Financeiro Líquido Total | F54: =F55+F57 -> -4379573.1 | G54: =SUM(G55,G57) -> -4232990.9 | H54: =SUM(H55,H57) -> -4780446.8 | I54: =SUM(I55,I57) -> -5252415.9 | J54: =SUM(J55,J57) -> -5649110.6
E55: Resultado Financeiro Sobre Dívida Líquida | F55: =-F53*WACC!F18 -> -4238257.3 | G55: =-F53*WACC!G18 -> -4314109.8 | H55: =-G53*WACC!H18 -> -4928861.2 | I55: =-H53*WACC!I18 -> -5563933.5 | J55: =-I53*WACC!J18 -> -6087369.7
E56: FCFF | F56: ='DRE Consolidado'!V67 -> -1053809 | G56: ='DRE Consolidado'!X67 -> 594277.85 | H56: ='DRE Consolidado'!Y67 -> 1061240.3 | I56: ='DRE Consolidado'!Z67 -> 2181495.4 | J56: ='DRE Consolidado'!AA67 -> 3026233.3
E57: Resultado Financeiro Sobre Variação de Caixa | F57: =F56*WACC!F18 -> -141315.79 | G57: =G56*WACC!G18 -> 81118.926 | H57: =H56*WACC!H18 -> 148414.46 | I57: =I56*WACC!I18 -> 311517.54 | J57: =J56*WACC!J18 -> 438259.11
E58: Dívida Líquida Máxima Bonds | F58: =F50*4 -> 42692446 | G58: =G50*4 -> 48830029 | H58: =H50*4 -> 54120907 | I58: =I50*4 -> 58724542 | J58: =J50*4 -> 63372645
E59: Dívida Líquida Máxima Local | F59: =F51*3.5 -> 47891550 | G59: =G51*3.5 -> 0 | H59: =H51*3.5 -> 0 | I59: =I51*3.5 -> 0 | J59: =J51*3.5 -> 0
E60: Resultado Financeiro Máximo | F60: =-F51/2 -> -6841650 | G60: =-G51*2 -> 0 | H60: =-H51*2 -> 0 | I60: =-I51*2 -> 0 | J60: =-J51*2 -> 0
E61: Divida Líquida/EBITDA Bonds | F61: =F52/F50 -> 3.0086657 | G61: =G53/G50 -> 2.8870688 | H61: =H53/H50 -> 2.8797093 | I61: =I53/I50 -> 2.8631328 | J61: =J53/J50 -> 2.8186873
E62: Divida Líquida/EBITDA Local | F62: =F53/F51 -> 2.3097645
E63: Cobertura de Juros | F63: =-F51/F54 -> 3.1243456 | G63: =-G50/G54 -> 2.8838964 | H63: =-H50/H54 -> 2.8303268 | I63: =-I50/I54 -> 2.7951205 | J63: =-J50/J54 -> 2.8045409

Sheet Projeções - Receita e EBIT
R3: =Dashboard!H3 -> SIMPAR (SIMH3)
A7: Páginas
A8: Dashboard
A9: WACC | F9: 2014 | G9: 2015 | H9: 2016 | I9: 2017 | J9: 2018 | K9: 2019 | L9: 2020 | M9: 2021 | N9: 2022 | O9: 2023 | P9: YTD 2024 | Q9: YTG2024 | R9: 2024 | S9: =R9+1 -> 2025 | T9: =S9+1 -> 2026 | U9: =T9+1 -> 2027 | V9: =U9+1 -> 2028 | W9: Premissa | X9: Nível de Otimismo (0-5) | Y9: CAGR (2018 a 2022) | Z9: CAGR (2023 a 2027)
A10: DRE Consolidado | E10: Receita Líquida | J10: =SUM(J13:J22) -> 8031044.8 | K10: =SUM(K13:K22) -> 9686209.3 | L10: =SUM(L13:L22) -> 9807057 | M10: =SUM(M13:M22) -> 13866219 | N10: =SUM(N13:N22) -> 24381790 | O10: =SUM(O13:O22) -> 31843612 | P10: =SUM(P13:P22) -> 9146985 | Q10: =R10-P10 -> 28759356 | R10: =SUM(R13:R22) -> 37906341 | S10: =SUM(S13:S22) -> 43423210 | T10: =SUM(T13:T22) -> 50252034 | U10: =SUM(U13:U22) -> 55355892 | V10: =SUM(V13:V22) -> 60832681 | Y10: =(N10/J10)^(1/4)-1 -> 0.31999834 | Z10: =(V10/R10)^(1/4)-1 -> 0.12552792
A11: DRE + DCF | E11: Crescimento da Receita (YoY)¹ | K11: =K10/J10-1 -> 0.20609578 | L11: =L10/K10-1 -> 0.012476264 | M11: =M10/L10-1 -> 0.4139022 | N11: =N10/M10-1 -> 0.75835887 | O11: =O10/N10-1 -> 0.30604078 | R11: =R10/O10-1 -> 0.19039075 | S11: =S10/R10-1 -> 0.14553946 | T11: =T10/S10-1 -> 0.15726208 | U11: =U10/T10-1 -> 0.10156521 | V11: =V10/U10-1 -> 0.098937782
E12: Receita Líquida Ex Eliminações | J12: =SUM(J13:J19) -> 8178993.8 | K12: =SUM(K13:K19) -> 9861984.3 | L12: =SUM(L13:L19) -> 9934256 | M12: =SUM(M13:M19) -> 14060748 | N12: =SUM(N13:N19) -> 24921822 | O12: =SUM(O13:O19) -> 32426159 | P12: =SUM(P13:P19) -> 9150154 | Q12: =SUM(Q13:Q19) -> 14504533 | ... V12: =SUM(V13:V19) -> 62010344
A13: DRE - Contas Abertas | E13: JSL | J13: 3138376.8 | K13: 3101978.3 | L13: 2826797 | M13: 4295978.5 | N13: 6022405 | O13: 7574644 | P13: 2070341 | Q13: ='[5]DRE + DCF'!R12 -> 2168879 | R13: 8958232.2 | S13: 10570375 | T13: 12200653 | U13: 13730925 | V13: 15025849
A14: Balanço Patrimonial | E14: Movida | J14: 2538599 | K14: 3836044 | L14: 4085259 | M14: 5332623 | N14: 9600029 | O14: 10342015 | P14: 3021646 | Q14: ='[4]DRE + DCF'!T12 -> 2569024.9 | R14: 11774455 | S14: 13141611 | T14: 16238958 | U14: 18004159 | V14: 19919172
A15: Painel de Índices | E15: Vamos | J15: 938946 | K15: 1211508 | L15: 1513187 | M15: 2823495 | N15: 4913454 | O15: 6085482 | P15: 1726111 | Q15: ='[6]DRE + DCF'!S12 -> 1787320.1 | R15: 7596119 | S15: 9371330.2 | T15: 10914413 | U15: 12055460 | V15: 13585839
A16: Projeções - Receita e EBIT | E16: BBC | J16: =J26 -> 31855 | K16: =K26 -> 40031 | L16: =L26 -> 45426 | M16: =M26 -> 43267 | N16: =N26 -> 78351 | O16: =O26 -> 14041 | P16: =P26 -> 1904 | Q16: =R16-P16 -> 5712 | R16: =R26 -> 7616 | S16: =S26 -> 9537.7002 | T16: =T26 -> 11944.292 | U16: =U26 -> 14958.124 | V16: =V26 -> 18732.419
A17: Projeções - CG + Capex | E17: Automob | J17: =J43 -> 702486 | K17: =K43 -> 821472 | L17: =L43 -> 617777 | M17: =M43 -> 731758 | N17: =N43 -> 3189039 | O17: =O43 -> 6970812 | P17: =P43 -> 2039783 | Q17: =R17-P17 -> 6960217 | R17: =R43 -> 9000000 | S17: =S43 -> 9477927.9 | T17: =T43 -> 10078161 | U17: =U43 -> 10744060 | V17: =V43 -> 11476203
A18: Projeções 2023 | E18: CS Brasil | J18: =J62 -> 828731 | K18: =K62 -> 850951 | L18: =L62 -> 845810 | M18: =M62 -> 833627 | N18: =N62 -> 717399 | O18: =O62 -> 681550 | P18: =P62 -> 143818 | Q18: =R18-P18 -> 573727.35 | R18: =R62 -> 717545.35 | S18: =S62 -> 755649.24 | T18: =T62 -> 803504.2 | U18: =U62 -> 856594.46 | V18: =V62 -> 914966.23
A19: Processos | E19: CS Infra | J19: =J81 -> 0 | K19: =K81 -> 0 | L19: =L81 -> 0 | M19: =M81 -> 0 | N19: =N81 -> 401145 | O19: =O81 -> 757615 | P19: =P81 -> 146551 | Q19: =R19-P19 -> 439653 | R19: =R81 -> 586204 | S19: =S81 -> 937410.39 | T19: =T81 -> 977231.59 | U19: =U81 -> 1021373.1 | V19: =V81 -> 1069581.9
E20: Ciclus Ambiental | J20: =J82 -> 0 | K20: =K82 -> 0 | L20: =L82 -> 0 | M20: =M82 -> 0 | N20: =N82 -> 0 | O20: 0 | P20: =P104 -> 111157
E21: Holding | J21: =J83 -> 0 | K21: =K83 -> 0 | L21: =L83 -> 0 | M21: =M83 -> 0 | N21: =N122 -> 63286 | O21: =O122 -> 123814 | P21: =P122 -> 10596 | Q21: =R21-P21 -> -10596 | R21: =R122 -> 0 | S21: =S122 -> 0 | T21: =T122 -> 0 | U21: =U122 -> 0 | V21: =V122 -> 0
E22: Eliminações | J22: -147949 | K22: -175775 | L22: =L138 -> -127199 | M22: =M138 -> -194529 | N22: =N138 -> -603318 | O22: =O138 -> -706361 | P22: =P138 -> -124922 | Q22: =R22-P22 -> -608908.59 | R22: =R138 -> -733830.59 | S22: =S138 -> -840631.9 | T22: =T138 -> -972831.42 | U22: =U138 -> -1071637.2 | V22: =V138 -> -1177662.7
F25: 2014 | G25: 2015 | H25: 2016 | I25: 2017 | J25: 2018 | K25: 2019 | L25: 2020 | M25: 2021 | N25: 2022 | O25: 2023 | P25: YTD 2024 | Q25: YTG2024 | R25: 2024 | S25: =R25+1 -> 2025 | T25: =S25+1 -> 2026 | U25: =T25+1 -> 2027 | V25: =U25+1 -> 2028 | W25: Premissa | X25: Nível de Otimismo (0-5) | Y25: CAGR (2015 a 2022) | Z25: CAGR (2018 a 2022)
E26: Receita Líquida | F26: 184.59 | G26: 5389 | H26: 28166 | I26: 23983 | J26: 31855 | K26: 40031 | L26: 45426 | M26: 43267 | N26: 78351 | O26: 14041 | P26: 1904 | Q26: =R26-P26 -> 5712 | R26: =P26*4 -> 7616 | S26: =R26*(1+$Z$26) -> 9537.7002 | T26: =S26*(1+$Z$26) -> 11944.292 | U26: =T26*(1+$Z$26) -> 14958.124 | V26: =U26*(1+$Z$26) -> 18732.419 | W26: Crescimento com base no CAGR histórico de 2018 a 2022, cuja operação é mais parecida com a atual. | X26: 3 | Y26: =(N26/G26)^(1/7)-1 -> 0.46580643 | Z26: =(N26/J26)^(1/4)-1 -> 0.25232409
E27: Crescimento da Receita (YoY)¹ | F27: 0 | G27: =G26/F26-1 -> 28.194431 | H27: =H26/G26-1 -> 4.2265726 | I27: =I26/H26-1 -> -0.14851239 | J27: =J26/I26-1 -> 0.3282325 | K27: =K26/J26-1 -> 0.256663 | L27: =L26/K26-1 -> 0.13477055 | M27: =M26/L26-1 -> -0.047527847 | N27: =N26/M26-1 -> 0.81087203 | O27: =O26/N26-1 -> -0.82079361 | R27: =$Z$26 -> 0.25232409 | S27: =$Z$26 -> 0.25232409 | T27: =$Z$26 -> 0.25232409 | U27: =$Z$26 -> 0.25232409 | V27: =$Z$26 -> 0.25232409
E28: Custos das Vendas e Serviços | F28: -417.345 | G28: -4656 | H28: -21161 | I28: -9488 | J28: -10409 | K28: -11295 | L28: -10872 | M28: -8190 | N28: -17107 | O28: -6356 | P28: -1830
E29: Lucro Bruto | F29: =SUM(F26,F28:F28) -> -232.755 | G29: =SUM(G26,G28:G28) -> 733 | H29: =SUM(H26,H28:H28) -> 7005 | I29: =SUM(I26,I28:I28) -> 14495 | J29: =SUM(J26,J28:J28) -> 21446 | K29: =SUM(K26,K28:K28) -> 28736 | L29: =SUM(L26,L28:L28) -> 34554 | M29: =SUM(M26,M28:M28) -> 35077 | ... P29: =SUM(P26,P28:P28) -> 74
E30: Margem Bruta | F30: =F29/F26 -> -1.2609296 | G30: =G29/G26 -> 0.13601781 | H30: =H29/H26 -> 0.24870411 | I30: =I29/I26 -> 0.60438644 | J30: =J29/J26 -> 0.67323811 | K30: =K29/K26 -> 0.71784367 | L30: =L29/L26 -> 0.7606657 | M30: =M29/M26 -> 0.81071024 | ... O30: =O29/O26 -> 0.54732569
E31: Despesas/ Receitas Operacionais | F31: =SUM(F33:F36) -> -5951 | G31: =SUM(G33:G36) -> -7780 | H31: =SUM(H33:H36) -> -8684 | I31: =SUM(I33:I36) -> -10297 | J31: =SUM(J33:J36) -> -12390 | K31: =SUM(K33:K36) -> -15687 | L31: =SUM(L33:L36) -> -18706 | M31: =SUM(M33:M36) -> -18295 | ... P31: =SUM(P33:P36) -> -16094
E32: (%) da Receita Líquida | F32: =-F31/F26 -> 32.239016 | G32: =-G31/G26 -> 1.4436816 | H32: =-H31/H26 -> 0.30831499 | I32: =-I31/I26 -> 0.42934579 | J32: =-J31/J26 -> 0.38894993 | K32: =-K31/K26 -> 0.3918713 | L32: =-L31/L26 -> 0.4117906 | M32: =-M31/M26 -> 0.42283958 | ... O32: =-O31/O26 -> 4.5766683 | P32: =P31/P26 -> -8.4527311
E33: Despesas Comerciais Gerais e Administrativas | F33: =-5919-9 -> -5928 | G33: =-7707-26 -> -7733 | H33: =-8588-75 -> -8663 | I33: -10232 | J33: -10585 | K33: =-340-11697 -> -12037 | L33: =-231-11019 -> -11250 | M33: =-8-12736 -> -12744 | N33: =-5352-38878 -> -44230 | O33: =-4344-45731 -> -50075 | P33: =-163-10142 -> -10305
E34: Perdas pela Não Recuperabilidade de Ativos | J34: -1833 | K34: -3921 | L34: -9140 | M34: -6664 | N34: -13080 | O34: -2507 | P34: -7125
E35: Resultado Operacional Outros | F35: -23 | G35: -47 | H35: -21 | I35: -65 | J35: 28 | K35: 271 | L35: 1684 | M35: 1109 | N35: 3907 | O35: -11679 | P35: 1336
E36: Resultado de Equivalência Patrimonial | M36: 4 | N36: 0 | P36: 0
E37: EBIT | F37: =SUM(F29,F31) -> -6183.755 | G37: =SUM(G29,G31) -> -7047 | H37: =SUM(H29,H31) -> -1679 | I37: =SUM(I29,I31) -> 4198 | J37: =SUM(J29,J31) -> 9056 | K37: =SUM(K29,K31) -> 13049 | L37: =SUM(L29,L31) -> 15848 | M37: =SUM(M29,M31) -> 16782 | ... P37: =SUM(P29,P31) -> -16020 | Q37: =R37-P37 -> 16020 | R37: =R26*R38 -> 0 | S37: =S38*S26 -> 0 | T37: =T38*T26 -> 0 | U37: =U38*U26 -> 0 | V37: =V38*V26 -> 0
E38: Margem EBIT | F38: =F37/F26 -> -33.499946 | G38: =G37/G26 -> -1.3076638 | H38: =H37/H26 -> -0.059610878 | I38: =I37/I26 -> 0.17504065 | J38: =J37/J26 -> 0.28428818 | K38: =K37/K26 -> 0.32597237 | L38: =L37/L26 -> 0.34887509 | M38: =M37/M26 -> 0.38787066 | ... P38: =P37/P26 -> -8.4138655 | R38: 0 | S38: 0 | T38: 0 | U38: 0 | V38: 0
F42: 2014 | G42: 2015 | H42: 2016 | I42: 2017 | J42: 2018 | K42: 2019 | L42: 2020 | M42: 2021 | N42: 2022 | O42: 2023 | P42: YTD 2024 | Q42: YTG2024 | R42: 2024 | S42: =R42+1 -> 2025 | T42: =S42+1 -> 2026 | U42: =T42+1 -> 2027 | V42: =U42+1 -> 2028 | W42: Premissa | X42: Nível de Otimismo (0-5) | Y42: CAGR (2017 a 2022) | Z42: CAGR (2023 a 2027)
E43: Receita Líquida | I43: 597682.38 | J43: 702486 | K43: 821472 | L43: 617777 | M43: 731758 | N43: 3189039 | O43: 6970812 | P43: 2039783 | Q43: =R43-P43 -> 6960217 | R43: 9000000 | S43: =R43*(1+S44) -> 9477927.9 | T43: =S43*(1+T44) -> 10078161 | U43: =T43*(1+U44) -> 10744060 | V43: =U43*(1+V44) -> 11476203 | W43: Crescimento com o PIB. Difícil projetar Automob agora, depois das últimas aquisições. Por isso, usamos um modelo de crescimento bem conservador. | X43: 2 | Y43: =(N43/I43)^(1/5)-1 -> 0.39777695 | Z43: =(V43/#REF!)^(1/4)-1 -> #REF!
E44: Crescimento da Receita (YoY)¹ | I44: 0 | J44: =J43/I43-1 -> 0.17535002 | K44: =K43/J43-1 -> 0.16937846 | L44: =L43/K43-1 -> -0.24796341 | M44: =M43/L43-1 -> 0.18450185 | N44: =N43/M43-1 -> 3.3580514 | O44: =O43/N43-1 -> 1.185866 | R44: =R43/O43-1 -> 0.29109779 | S44: ='Projeções - CG + Capex'!L39 -> 0.0531031 | T44: ='Projeções - CG + Capex'!M39 -> 0.0633296 | U44: ='Projeções - CG + Capex'!N39 -> 0.0660734 | V44: ='Projeções - CG + Capex'!O39 -> 0.068144
E45: Custos das Vendas e Serviços | I45: -485163 | J45: -589249 | K45: -688206 | L45: -505964 | M45: -589455 | N45: -2647230 | O45: -5928845 | P45: -1723307
E46: Custo de Venda de Ativos Desmobilizados | I46: -13455 | J46: -5157 | K46: -6611 | L46: -4517 | M46: -1155 | N46: -11457 | O46: 0 | R46: =-R47*R43 -> -64778.767 | S46: =-S47*S43 -> -68218.721 | T46: =-T47*T43 -> -72538.985 | U46: =-U47*U43 -> -77331.882 | V46: =-V47*V43 -> -82601.586
E47: % da Receita | I47: =-I46/I43 -> 0.022511957 | J47: =-J46/J43 -> 0.0073410716 | K47: =-K46/K43 -> 0.0080477484 | L47: =-L46/L43 -> 0.0073116999 | M47: =-M46/M43 -> 0.0015783907 | N47: =-N46/N43 -> 0.0035926183 | O47: =-O46/O43 -> 0 | P47: =-P46/P43 -> 0 | R47: =AVERAGE($I$47:$O$47) -> 0.0071976408 | S47: =AVERAGE($I$47:$O$47) -> 0.0071976408 | T47: =AVERAGE($I$47:$O$47) -> 0.0071976408 | U47: =AVERAGE($I$47:$O$47) -> 0.0071976408 | V47: =AVERAGE($I$47:$O$47) -> 0.0071976408
E48: Lucro Bruto | I48: =SUM(I43,I45:I46) -> 99064.383 | J48: =SUM(J43,J45:J46) -> 108080 | K48: =SUM(K43,K45:K46) -> 126655 | L48: =SUM(L43,L45:L46) -> 107296 | M48: =SUM(M43,M45:M46) -> 141148 | N48: =SUM(N43,N45:N46) -> 530352 | O48: =SUM(O43,O45:O46) -> 1041967 | P48: =SUM(P43,P45:P46) -> 316476
E49: Margem Bruta | I49: =I48/I43 -> 0.16574754 | J49: =J48/J43 -> 0.1538536 | K49: =K48/K43 -> 0.15418054 | L49: =L48/L43 -> 0.17368079 | M49: =M48/M43 -> 0.19288891 | N49: =N48/N43 -> 0.16630465 | O49: =O48/O43 -> 0.1494757 | P49: =P48/P43 -> 0.1551518
E50: Despesas/ Receitas Operacionais | I50: =SUM(I52:I55) -> -81992 | J50: =SUM(J52:J55) -> -94262 | K50: =SUM(K52:K55) -> -104013 | L50: =SUM(L52:L55) -> -87199 | M50: =SUM(M52:M55) -> -90691 | N50: =SUM(N52:N55) -> -387044 | O50: =SUM(O52:O55) -> -796366 | P50: =SUM(P52:P55) -> -247602
E51: (%) da Receita Líquida | I51: =-I50/I43 -> 0.13718323 | J51: =-J50/J43 -> 0.13418346 | K51: =-K50/K43 -> 0.12661783 | L51: =-L50/L43 -> 0.14114964 | M51: =-M50/M43 -> 0.12393578 | N51: =-N50/N43 -> 0.12136697 | O51: =-O50/O43 -> 0.11424293 | P51: =-P50/P43 -> 0.12138644
E52: Despesas Comerciais Gerais e Administrativas | I52: =-87439-7926 -> -95365 | J52: =-7776-89544 -> -97320 | K52: =-16460-89599 -> -106059 | L52: =-32038-57039 -> -89077 | M52: =-43502-66412 -> -109914 | N52: =-184076-195167 -> -379243 | O52: =-387777-403091 -> -790868 | P52: =-135558-108707 -> -244265
E53: Perdas pela Não Recuperabilidade de Ativos | I53: -97 | J53: -98 | K53: -944 | L53: 581 | M53: 97 | N53: -3076 | O53: -7324 | P53: -2046
E54: Resultado Operacional Outros | I54: 13470 | J54: 3156 | K54: 2990 | L54: 1297 | M54: 19126 | N54: -4747 | O54: 1762 | P54: -1291
E55: Resultado de Equivalência Patrimonial | N55: 22 | O55: 64
E56: EBIT | I56: =SUM(I48,I50) -> 17072.383 | J56: =SUM(J48,J50) -> 13818 | K56: =SUM(K48,K50) -> 22642 | L56: =SUM(L48,L50) -> 20097 | M56: =SUM(M48,M50) -> 50457 | N56: =SUM(N48,N50) -> 143308 | O56: =SUM(O48,O50) -> 245601 | P56: =SUM(P48,P50) -> 68874 | Q56: =R56-P56 -> 339849.13 | R56: =R58*R43 -> 408723.13 | S56: =S58*S43 -> 430427.59 | T56: =T58*T43 -> 457686.4 | U56: =U58*U43 -> 487927.3 | V56: =V58*V43 -> 521176.61
E57: % EBIT Simpar Capital Fechado | J57: =J56/'DRE + DCF'!O15 -> 0.10829323 | K57: =K56/'DRE + DCF'!P15 -> 0.13735494 | L57: =L56/'DRE + DCF'!Q15 -> 0.12503033 | M57: =M56/'DRE + DCF'!R15 -> 0.27091589 | N57: =N56/'DRE + DCF'!S15 -> 0.44776894 | O57: =O56/'DRE + DCF'!T15 -> 1.0329965 | P57: =P56/'DRE + DCF'!U15 -> 1.06593 | Q57: =Q56/'DRE + DCF'!V15 -> 0.65910303 | ... V57: =V56/'DRE + DCF'!AA15 -> 0.56322619
E58: Margem EBIT | I58: =I56/I43 -> 0.028564307 | J58: =J56/J43 -> 0.019670143 | K58: =K56/K43 -> 0.027562717 | L58: =L56/L43 -> 0.032531156 | M58: =M56/M43 -> 0.068953124 | N58: =N56/N43 -> 0.044937676 | O58: =O56/O43 -> 0.035232768 | P58: =P56/P43 -> 0.033765356 | Q58: =Q56/Q43 -> 0.048827375 | R58: =AVERAGE($L$58:$O$58) -> 0.045413681 | S58: =AVERAGE($L$58:$O$58) -> 0.045413681 | T58: =AVERAGE($L$58:$O$58) -> 0.045413681 | U58: =AVERAGE($L$58:$O$58) -> 0.045413681 | V58: =AVERAGE($L$58:$O$58) -> 0.045413681
F61: 2014 | G61: 2015 | H61: 2016 | I61: 2017 | J61: 2018 | K61: 2019 | L61: 2020 | M61: 2021 | N61: 2022 | O61: 2023 | P61: YTD 2024 | Q61: YTG2024 | R61: 2024 | S61: =R61+1 -> 2025 | T61: =S61+1 -> 2026 | U61: =T61+1 -> 2027 | V61: =U61+1 -> 2028 | W61: Premissa | X61: Nível de Otimismo (0-5) | Y61: CAGR (2018 a 2022) | Z61: CAGR (2023 a 2027)
E62: Receita Líquida | J62: 828731 | K62: 850951 | L62: 845810 | M62: 833627 | N62: 717399 | O62: 681550 | P62: 143818 | Q62: =R62-P62 -> 573727.35 | R62: =O62*(1+R63) -> 717545.35 | S62: =R62*(1+S63) -> 755649.24 | T62: =S62*(1+T63) -> 803504.2 | U62: =T62*(1+U63) -> 856594.46 | V62: =U62*(1+V63) -> 914966.23 | W62: Crescimento com o PIB. Difícil projetar CS Brasil agora, depois das últimas transformações. Por isso, usamos um modelo de crescimento bem conservador. | X62: 4 | Y62: =(N62/J62)^(1/4)-1 -> -0.035423237 | Z62: =(V62/R62)^(1/4)-1 -> 0.062646771
E63: Crescimento da Receita (YoY)¹ | J63: 0 | K63: =K62/J62-1 -> 0.026812078 | L63: =L62/K62-1 -> -0.0060414759 | M63: =M62/L62-1 -> -0.014403944 | N63: =N62/M62-1 -> -0.13942447 | O63: =O62/N62-1 -> -0.049970797 | R63: ='Projeções - CG + Capex'!K39 -> 0.05281396 | S63: ='Projeções - CG + Capex'!L39 -> 0.0531031 | T63: ='Projeções - CG + Capex'!M39 -> 0.0633296 | U63: ='Projeções - CG + Capex'!N39 -> 0.0660734 | V63: ='Projeções - CG + Capex'!O39 -> 0.068144
E64: Custos das Vendas e Serviços | J64: -580962 | K64: -558867 | L64: -469196 | M64: -444164 | N64: -530566 | O64: -401412.3 | P64: -120857
E65: Custo de Venda de Ativos Desmobilizados | J65: -131843 | K65: -139194 | L65: -171242 | M65: -158843 | N65: -43083 | O65: -134590 | P65: 0 | R65: =-R66*R62 -> -116385.77 | S65: =-S66*S62 -> -122566.22 | T65: =-T66*T62 -> -130328.29 | U65: =-U66*U62 -> -138939.52 | V65: =-V66*V62 -> -148407.41
E66: % da Receita | J66: =-J65/J62 -> 0.15909022 | K66: =-K65/K62 -> 0.16357464 | L66: =-L65/L62 -> 0.20245918 | M66: =-M65/M62 -> 0.19054445 | N66: =-N65/N62 -> 0.060054447 | O66: =-O65/O62 -> 0.19747634 | P66: =-P65/P62 -> 0 | R66: =AVERAGE($J$66:$O$66) -> 0.16219988 | S66: =AVERAGE($J$66:$O$66) -> 0.16219988 | T66: =AVERAGE($J$66:$O$66) -> 0.16219988 | U66: =AVERAGE($J$66:$O$66) -> 0.16219988 | V66: =AVERAGE($J$66:$O$66) -> 0.16219988
E67: Lucro Bruto | J67: =SUM(J62,J64:J65) -> 115926 | K67: =SUM(K62,K64:K65) -> 152890 | L67: =SUM(L62,L64:L65) -> 205372 | M67: =SUM(M62,M64:M65) -> 230620 | N67: =SUM(N62,N64:N65) -> 143750 | O67: =SUM(O62,O64:O65) -> 145547.7 | P67: =SUM(P62,P64:P65) -> 22961
E68: Margem Bruta | J68: =J67/J62 -> 0.13988375 | K68: =K67/K62 -> 0.17966957 | L68: =L67/L62 -> 0.24281103 | M68: =M67/M62 -> 0.27664651 | N68: =N67/N62 -> 0.20037664 | O68: =O67/O62 -> 0.21355396 | P68: =P67/P62 -> 0.15965317
E69: Despesas/ Receitas Operacionais | J69: =SUM(J71:J74) -> -32939 | K69: =SUM(K71:K74) -> -15212 | L69: =SUM(L71:L74) -> -39199 | M69: =SUM(M71:M74) -> -48879 | N69: =SUM(N71:N74) -> -10417 | O69: =SUM(O71:O74) -> 8743 | P69: =SUM(P71:P74) -> 4491
E70: (%) da Receita Líquida | J70: =J69/J62 -> -0.039746311 | K70: =K69/K62 -> -0.01787647 | L70: =L69/L62 -> -0.046344924 | M70: =M69/M62 -> -0.058634137 | N70: =N69/N62 -> -0.014520511 | O70: =O69/O62 -> 0.012828112 | P70: =P69/P62 -> 0.031226967
E71: Despesas Comerciais Gerais e Administrativas | J71: =-2517-40311 -> -42828 | K71: =-3658-31369 -> -35027 | L71: =-2557-36106 -> -38663 | M71: =-4290-41322 -> -45612 | N71: =-2391-45440 -> -47831 | O71: =-1690-34587 -> -36277 | P71: =-181-9072 -> -9253
E72: Perdas pela Não Recuperabilidade de Ativos | J72: 2636 | K72: -1246 | L72: -2122 | M72: 160 | N72: -2965 | O72: -4394 | P72: 55
E73: Resultado Operacional Outros | J73: 8225 | K73: 22262 | L73: 2101 | M73: -1936 | N73: 37598 | O73: 44151 | P73: -1627
E74: Resultado de Equivalência Patrimonial | J74: -972 | K74: -1201 | L74: -515 | M74: -1491 | N74: 2781 | O74: 5263 | P74: 15316
E75: EBIT | J75: =SUM(J67,J69) -> 82987 | K75: =SUM(K67,K69) -> 137678 | L75: =SUM(L67,L69) -> 166173 | M75: =SUM(M67,M69) -> 181741 | N75: =SUM(N67,N69) -> 133333 | O75: =SUM(O67,O69) -> 154290.7 | P75: =SUM(P67,P69) -> 27452 | Q75: =R75-P75 -> 120849.68 | R75: =R62*R76 -> 148301.68 | S75: =S62*S76 -> 156176.96 | T75: =T62*T76 -> 166067.58 | U75: =U62*U76 -> 177040.23 | V75: =V62*V76 -> 189104.46
E76: Margem EBIT | J76: =J75/J62 -> 0.10013744 | K76: =K75/K62 -> 0.1617931 | L76: =L75/L62 -> 0.19646611 | M76: =M75/M62 -> 0.21801237 | N76: =N75/N62 -> 0.18585613 | O76: =O75/O62 -> 0.22638207 | P76: =P75/P62 -> 0.19088014 | Q76: =Q75/Q62 -> 0.21063956 | R76: =AVERAGE($L$76:$O$76) -> 0.20667917 | S76: =AVERAGE($L$76:$O$76) -> 0.20667917 | T76: =AVERAGE($L$76:$O$76) -> 0.20667917 | U76: =AVERAGE($L$76:$O$76) -> 0.20667917 | V76: =AVERAGE($L$76:$O$76) -> 0.20667917
F80: 2014 | G80: 2015 | H80: 2016 | I80: 2017 | J80: 2018 | K80: 2019 | L80: 2020 | M80: 2021 | N80: 2022 | O80: 2023 | P80: YTD 2024 | Q80: YTG2024 | R80: 2024 | S80: =R80+1 -> 2025 | T80: =S80+1 -> 2026 | U80: =T80+1 -> 2027 | V80: =U80+1 -> 2028 | W80: Premissa | X80: Nível de Otimismo (0-5) | Z80: CAGR (2023 a 2027)
E81: Receita Líquida | N81: 401145 | O81: 757615 | P81: 146551 | Q81: =R81-P81 -> 439653 | R81: =P81*4 -> 586204 | S81: =SUM(S82:S85) -> 937410.39 | T81: =S81*(1+'Projeções - CG + Capex'!M37) -> 977231.59 | U81: =T81*(1+'Projeções - CG + Capex'!N37) -> 1021373.1 | V81: =U81*(1+'Projeções - CG + Capex'!O37) -> 1069581.9 | W81: Crescemos a Receita conforme calendário de maturidade das concessões fornecidos pela Simpar. Daí em diante, crescemos a Receita com a inflação, por se tratarem de concessões com preços regulados. | X81: 3 | Z81: =(V81/R81)^(1/4)-1 -> 0.16222797
E82: Portos | O82: 151300 | R82: =S82*3/4 -> 234750 | S82: 313000
E83: Transcerrados | O83: 13700 | R83: =S83*2/3 -> 48666.667 | S83: 73000
E84: BRT + CS Mobi Cuiabá | O84: 0 | R84: 88688.82 | S84: =R84*(1+'Projeções - CG + Capex'!M37) -> 92456.321
E85: Ciclus | O85: 425200 | R85: =O85*(1+'Projeções - CG + Capex'!K37) -> 442348.32 | S85: =R85*(1+'Projeções - CG + Capex'!L37) -> 458954.07
E86: Crescimento da Receita (YoY)¹ | R86: =R81/O81-1 -> -0.2262508 | S86: =S81/R81-1 -> 0.59911975 | T86: =T81/S81-1 -> 0.04248 | U86: =U81/T81-1 -> 0.04517 | V86: =V81/U81-1 -> 0.0472
E87: Custos das Vendas e Serviços | N87: -279667 | O87: -432535.93 | P87: -143688
E88: Custo de Construção | N88: 0 | O88: -175506.89 | P88: 0
E89: Custo de Venda de Ativos Desmobilizados | N89: 0 | P89: 0
E90: Lucro Bruto | N90: =SUM(N81,N87:N89) -> 121478 | O90: =SUM(O81,O87:O88) -> 149572.18 | P90: =SUM(P81,P87:P89) -> 2863
E91: Margem Bruta | N91: =N90/N81 -> 0.30282815 | O91: =O90/O81 -> 0.19742505 | P91: =P90/P81 -> 0.019535861
E92: Despesas/ Receitas Operacionais | N92: =SUM(N94:N97) -> -20828 | O92: =SUM(O94:O97) -> -80453 | P92: =SUM(P94:P97) -> -16327
E93: (%) da Receita Líquida | N93: =N92/N81 -> -0.051921375 | O93: =O92/O81 -> -0.10619246 | P93: =P92/P81 -> -0.11140832
E94: Despesas Comerciais Gerais e Administrativas | N94: =-44-24016 -> -24060 | O94: =-826-80433 -> -81259 | P94: =-1-14365 -> -14366
E95: Perdas pela Não Recuperabilidade de Ativos | N95: 0 | O95: 49 | P95: 0
E96: Resultado Operacional Outros | N96: 3232 | O96: 757 | P96: 7
E97: Resultado de Equivalência Patrimonial | N97: 0 | P97: -1968
E98: EBIT | N98: =SUM(N90,N92) -> 100650 | O98: =SUM(O90,O92) -> 69119.181 | P98: =SUM(P90,P92) -> -13464 | Q98: =R98-P98 -> 36676.867 | R98: =R99*R81 -> 23212.867 | S98: =S99*S81 -> 160362.5 | T98: =T99*T81 -> 176947.02 | U98: =U99*U81 -> 195153.44 | V98: =V99*V81 -> 215060.51
E99: Margem EBIT | N99: =N98/N81 -> 0.25090678 | O99: =O98/O81 -> 0.091232593 | P99: =P98/P81 -> -0.091872454 | Q99: =Q98/Q81 -> 0.083422306 | R99: =AVERAGE(S99,P99) -> 0.039598616 | S99: =AVERAGE(N99:O99) -> 0.17106969 | T99: =S99+1% -> 0.18106969 | U99: =T99+1% -> 0.19106969 | V99: =U99+1% -> 0.20106969 | W99: No periodo de investimentos, fizemos a média de margem entre 2022 e 2023. Depois disso, conforme as concessões maturam, adicionamos 1 p.p. a cada ano. Para 2024 fizemos uma transição entre 2023 e 2025. Tendo em vista que os terminais portuários ficarão fechados até 2026.
F103: 2014 | G103: 2015 | H103: 2016 | I103: 2017 | J103: 2018 | K103: 2019 | L103: 2020 | M103: 2021 | N103: 2022 | O103: 2023 | P103: YTD 2024 | Q103: YTG2024 | R103: 2024 | S103: =R103+1 -> 2025 | T103: =S103+1 -> 2026 | U103: =T103+1 -> 2027 | V103: =U103+1 -> 2028 | W103: Premissa | X103: Nível de Otimismo (0-5) | Y103: CAGR (2017 a 2022) | Z103: CAGR (2023 a 2027)
E104: Receita Líquida | P104: 111157 | Q104: =R104-P104 -> 333471 | R104: =P104*4 -> 444628 | S104: =R104*(1+S105) -> 444628 | T104: =S104*(1+T105) -> 444628 | U104: =T104*(1+U105) -> 444628 | V104: =U104*(1+V105) -> 444628 | W104: Voltar aqui para ver crescimento | X104: 2 | Y104: =(N104/I104)^(1/5)-1 -> #DIV/0! | Z104: =(V104/#REF!)^(1/4)-1 -> #REF!
E105: Crescimento da Receita (YoY)¹ | S105: ='Projeções - CG + Capex'!L100 -> 0 | T105: ='Projeções - CG + Capex'!M100 -> 0 | U105: ='Projeções - CG + Capex'!N100 -> 0 | V105: ='Projeções - CG + Capex'!O100 -> 0
E106: Custos das Vendas e Serviços | P106: -84699
E107: % da Receita | P107: =-P106/P104 -> 0.7619763 | R107: =AVERAGE($I$47:$O$47) -> 0.0071976408 | S107: =AVERAGE($I$47:$O$47) -> 0.0071976408 | T107: =AVERAGE($I$47:$O$47) -> 0.0071976408 | U107: =AVERAGE($I$47:$O$47) -> 0.0071976408 | V107: =AVERAGE($I$47:$O$47) -> 0.0071976408
E108: Lucro Bruto | P108: =SUM(P104,P106:P106) -> 26458
E109: Margem Bruta | P109: =P108/P104 -> 0.2380237
E110: Despesas/ Receitas Operacionais | P110: =SUM(P112:P115) -> -5842
E111: (%) da Receita Líquida | P111: =-P110/P104 -> 0.052556294
E112: Despesas Comerciais Gerais e Administrativas | P112: =-560-5247 -> -5807
E113: Perdas pela Não Recuperabilidade de Ativos
E114: Resultado Operacional Outros | P114: -35
E115: Resultado de Equivalência Patrimonial
E116: EBIT | P116: =SUM(P108,P110) -> 20616 | Q116: =R116-P116 -> 61848 | R116: =R117*R104 -> 82464 | S116: =S117*S104 -> 82464 | T116: =T117*T104 -> 82464 | U116: =U117*U104 -> 82464 | V116: =V117*V104 -> 82464
E117: Margem EBIT | P117: =P116/P104 -> 0.1854674 | Q117: =Q116/Q104 -> 0.1854674 | R117: =P117 -> 0.1854674 | S117: =R117 -> 0.1854674 | T117: =S117 -> 0.1854674 | U117: =T117 -> 0.1854674 | V117: =U117 -> 0.1854674
F121: 2014 | G121: 2015 | H121: 2016 | I121: 2017 | J121: 2018 | K121: 2019 | L121: 2020 | M121: 2021 | N121: 2022 | O121: 2023 | P121: YTD 2024 | Q121: YTG2024 | R121: 2024 | S121: =R121+1 -> 2025 | T121: =S121+1 -> 2026 | U121: =T121+1 -> 2027 | V121: =U121+1 -> 2028 | W121: Premissa | X121: Nível de Otimismo (0-5) | Y121: CAGR (2018 a 2022) | Z121: CAGR (2023 a 2027)
...

Sheet Projeções - CG + Capex
L3: =Dashboard!H3 -> SIMPAR (SIMH3)
A7: Páginas
A8: Dashboard
A9: WACC | E9: Data do Último Resultado: | K9: 2014 | L9: 2015 | M9: 2016 | N9: 2017 | O9: 2018 | P9: 2019 | Q9: 2020 | R9: 2021 | S9: 2022 | T9: 2023 | U9: 2024 | V9: =U9+1 -> 2025 | W9: =V9+1 -> 2026 | X9: =W9+1 -> 2027 | Y9: =X9+1 -> 2028
A10: DRE Consolidado | E10: Capital de Giro | K10: ='Balanço Patrimonial'!F16 -> 1071719.9 | L10: ='Balanço Patrimonial'!G16 -> 914914.8 | M10: ='Balanço Patrimonial'!H16 -> 419015.9 | N10: ='Balanço Patrimonial'!I16 -> 842599.1 | O10: ='Balanço Patrimonial'!J16 -> 707239.73 | P10: ='Balanço Patrimonial'!K16 -> 964985.23 | Q10: ='Balanço Patrimonial'!L16 -> 251143.42 | R10: ='Balanço Patrimonial'!M16 -> 578140.47 | ... T10: ='Balanço Patrimonial'!O16 -> 3572956.3 | U10: =U11*'DRE Consolidado'!W16 -> 3688903.7 | V10: =V11*'DRE Consolidado'!X16 -> 4225784.8 | W10: =W11*'DRE Consolidado'!Y16 -> 4890340.5 | X10: =X11*'DRE Consolidado'!Z16 -> 5387028.9 | Y10: =Y11*'DRE Consolidado'!AA16 -> 5920009.6
A11: DRE + DCF | E11: (%) da Receita Líquida | K11: =K10/'DRE Consolidado'!K16 -> 0.19347939 | L11: =L10/'DRE Consolidado'!L16 -> 0.15274261 | M11: =M10/'DRE Consolidado'!M16 -> 0.064235543 | N11: =N10/'DRE Consolidado'!N16 -> 0.1161276 | O11: =O10/'DRE Consolidado'!O16 -> 0.087579648 | P11: =P10/'DRE Consolidado'!P16 -> 0.099624654 | Q11: =Q10/'DRE Consolidado'!Q16 -> 0.025608439 | R11: =R10/'DRE Consolidado'!R16 -> 0.041694169 | ... T11: =T10/'DRE Consolidado'!T16 -> 0.11220323 | U11: =AVERAGE($K$11:$T$11) -> 0.09731627 | V11: =AVERAGE($K$11:$T$11) -> 0.09731627 | W11: =AVERAGE($K$11:$T$11) -> 0.09731627 | X11: =AVERAGE($K$11:$T$11) -> 0.09731627 | Y11: =AVERAGE($K$11:$T$11) -> 0.09731627
A12: DRE - Contas Abertas
A13: Balanço Patrimonial
A14: Painel de Índices
A15: Projeções - Receita e EBIT | E15: Controladas | K15: 2014 | L15: 2015 | M15: 2016 | N15: 2017 | O15: 2018 | P15: 2019 | Q15: 2020 | R15: 2021 | S15: 2022 | T15: 2023 | U15: 2024 | V15: =U15+1 -> 2025 | W15: =V15+1 -> 2026 | X15: =W15+1 -> 2027 | Y15: =X15+1 -> 2028
A16: Projeções - CG + CAPEX | E16: BBC
A17: Projeções 2023 | E17: Automob (Aquisições + Bruto de Renovação) | O17: 7811.0773 | P17: 11615.358 | Q17: 5230.2642 | R17: 13485.061 | S17: 1254968 | T17: =SUM(T19:T26) -> 354681 | U17: =SUM(U19:U26) -> 132949.84 | V17: =SUM(V19:V26) -> 180545.27 | W17: =SUM(W19:W26) -> 131402.73 | X17: =SUM(X19:X26) -> 140084.95 | Y17: =SUM(Y19:Y26) -> 149630.9
A18: Processos | E18: (%) da Receita Líquida | O18: =O17/'Projeções - Receita e EBIT'!J43 -> 0.011119193 | P18: =P17/'Projeções - Receita e EBIT'!K43 -> 0.014139688 | Q18: =Q17/'Projeções - Receita e EBIT'!L43 -> 0.0084662656 | R18: =R17/'Projeções - Receita e EBIT'!M43 -> 0.018428306 | S18: =S17/'Projeções - Receita e EBIT'!N43 -> 0.39352545 | T18: =T17/'Projeções - Receita e EBIT'!O43 -> 0.050880873 | U18: =AVERAGE($O$18:$R$18) -> 0.013038363 | V18: =AVERAGE($O$18:$R$18) -> 0.013038363 | W18: =AVERAGE($O$18:$R$18) -> 0.013038363 | X18: =AVERAGE($O$18:$R$18) -> 0.013038363 | Y18: =AVERAGE($O$18:$R$18) -> 0.013038363
F19: Capex líquido de Renovação | S19: 28055 | T19: 131900 | U19: =U18*'Projeções - Receita e EBIT'!Q43 -> 90749.837 | V19: =V18*'Projeções - Receita e EBIT'!R43 -> 117345.27 | W19: =W18*'Projeções - Receita e EBIT'!T43 -> 131402.73 | X19: =X18*'Projeções - Receita e EBIT'!U43 -> 140084.95 | Y19: =Y18*'Projeções - Receita e EBIT'!V43 -> 149630.9
F20: Aquisição SAGAMAR | S20: 262588
F21: Aquisição Autostar | S21: 372189
F22: Aquisição Grupo Green | S22: 60686 | T22: 39481
F23: Aquisição UAB Motors | S23: 531450
F24: Aquisição Best Points | T24: 60200 | U24: 18900 | V24: 28300
F25: Aquisição Grupo Alta | T25: 59200 | U25: 23300 | V25: 34900
F26: Aquisição Nova Quality | T26: 63900
E27: CS Brasil | O27: 534255.88 | P27: 539504.35 | Q27: 602332.97 | R27: 811594.49 | S27: 0 | T27: 80600 | U27: =U28*'Projeções - Receita e EBIT'!R62 -> 84856.805 | V27: =V28*'Projeções - Receita e EBIT'!S62 -> 89362.965 | W27: =W28*'Projeções - Receita e EBIT'!T62 -> 95022.285 | X27: =X28*'Projeções - Receita e EBIT'!U62 -> 101300.73 | Y27: =Y28*'Projeções - Receita e EBIT'!V62 -> 108203.77
E28: (%) da Receita Líquida | O28: =O27/'Projeções - Receita e EBIT'!J62 -> 0.64466743 | P28: =P27/'Projeções - Receita e EBIT'!K62 -> 0.63400167 | Q28: =Q27/'Projeções - Receita e EBIT'!L62 -> 0.71213744 | R28: =R27/'Projeções - Receita e EBIT'!M62 -> 0.97357031 | S28: =S27/'Projeções - Receita e EBIT'!N62 -> 0 | T28: =T27/'Projeções - Receita e EBIT'!O62 -> 0.11825985 | U28: =T28 -> 0.11825985 | V28: =U28 -> 0.11825985 | W28: =V28 -> 0.11825985 | X28: =W28 -> 0.11825985 | Y28: =X28 -> 0.11825985
E29: CS Infra | O29: 0 | P29: 0 | Q29: 0 | R29: 0 | S29: 134000 | T29: 342400 | U29: 274700 | V29: 103000 | W29: =W30*'Projeções - Receita e EBIT'!T81 -> 107375.44 | X29: =X30*'Projeções - Receita e EBIT'!U81 -> 112225.59 | Y29: =Y30*'Projeções - Receita e EBIT'!V81 -> 117522.64
E30: (%) da Receita Líquida | O30: =O29/'DRE Consolidado'!O16 -> 0 | P30: =P29/'DRE Consolidado'!P16 -> 0 | Q30: =Q29/'DRE Consolidado'!Q16 -> 0 | R30: =R29/'DRE Consolidado'!R16 -> 0 | S30: =S29/'DRE Consolidado'!S16 -> 0.0054959047 | T30: =T29/'DRE Consolidado'!T16 -> 0.010752549 | U30: =U29/'Projeções - Receita e EBIT'!R81 -> 0.4686082 | V30: =V29/'Projeções - Receita e EBIT'!S81 -> 0.10987717 | W30: =V30 -> 0.10987717 | X30: =W30 -> 0.10987717 | Y30: =X30 -> 0.10987717
E31: Custo de Venda de Ativos | O31: =SUM('Projeções - Receita e EBIT'!J46,'Projeções - Receita e EBIT'!J65,'Projeções - Receita e EBIT'!J89) -> -137000 | P31: =SUM('Projeções - Receita e EBIT'!K46,'Projeções - Receita e EBIT'!K65,'Projeções - Receita e EBIT'!K89) -> -145805 | Q31: =SUM('Projeções - Receita e EBIT'!L46,'Projeções - Receita e EBIT'!L65,'Projeções - Receita e EBIT'!L89) -> -175759 | R31: =SUM('Projeções - Receita e EBIT'!M46,'Projeções - Receita e EBIT'!M65,'Projeções - Receita e EBIT'!M89) -> -159998 | S31: =SUM('Projeções - Receita e EBIT'!N46,'Projeções - Receita e EBIT'!N65,'Projeções - Receita e EBIT'!N89) -> -54540 | T31: =SUM('Projeções - Receita e EBIT'!O46,'Projeções - Receita e EBIT'!O65,'Projeções - Receita e EBIT'!O89) -> -134590 | U31: =SUM('Projeções - Receita e EBIT'!R46,'Projeções - Receita e EBIT'!R65) -> -181164.54 | V31: =SUM('Projeções - Receita e EBIT'!S46,'Projeções - Receita e EBIT'!S65) -> -190784.94 | W31: =SUM('Projeções - Receita e EBIT'!T46,'Projeções - Receita e EBIT'!T65) -> -202867.27 | X31: =SUM('Projeções - Receita e EBIT'!U46,'Projeções - Receita e EBIT'!U65) -> -216271.4 | Y31: =SUM('Projeções - Receita e EBIT'!V46,'Projeções - Receita e EBIT'!V65) -> -231009
E32: Total Capex Líquido | O32: =SUM(O16,O17,O27,O29,O31) -> 405066.96 | P32: =SUM(P16,P17,P27,P29,P31) -> 405314.71 | Q32: =SUM(Q16,Q17,Q27,Q29,Q31) -> 431804.23 | R32: =SUM(R16,R17,R27,R29,R31) -> 665081.55 | S32: =SUM(S16,S17,S27,S29,S31) -> 1334428 | T32: =SUM(T16,T17,T27,T29,T31) -> 643091 | U32: =SUM(U16,U17,U27,U29,U31) -> 311342.1 | V32: =SUM(V16,V17,V27,V29,V31) -> 182123.3 | ... Y32: =SUM(Y16,Y17,Y27,Y29,Y31) -> 144348.31
E36: Ano | K36: 2024 | L36: =K36+1 -> 2025 | M36: =L36+1 -> 2026 | N36: =M36+1 -> 2027 | O36: =N36+1 -> 2028 | P36: =O36+1 -> 2029 | Q36: =P36+1 -> 2030 | R36: =Q36+1 -> 2031 | S36: =R36+1 -> 2032 | ... U36: =T36+1 -> 2034
E37: Inflação | K37: =WACC!F12 -> 0.04033 | L37: =WACC!G12 -> 0.03754 | M37: =WACC!H12 -> 0.04248 | N37: =WACC!I12 -> 0.04517 | O37: =WACC!J12 -> 0.0472 | P37: =WACC!K12 -> 0.04849 | Q37: =WACC!L12 -> 0.05011 | R37: =WACC!M12 -> 0.05077 | ... U37: =WACC!P12 -> 0.05
E38: Crescimento PIB Real (FMI) | K38: 0.012 | L38: 0.015 | M38: 0.02 | N38: 0.02 | O38: 0.02 | P38: 0.02 | Q38: 0.02 | R38: 0.02 | S38: 0.02 | T38: 0.02 | U38: 0.02
E39: Crescimento PIB Nominal | K39: =(1+K37)*(1+K38)-1 -> 0.05281396 | L39: =(1+L37)*(1+L38)-1 -> 0.0531031 | M39: =(1+M37)*(1+M38)-1 -> 0.0633296 | N39: =(1+N37)*(1+N38)-1 -> 0.0660734 | O39: =(1+O37)*(1+O38)-1 -> 0.068144 | P39: =(1+P37)*(1+P38)-1 -> 0.0694598 | Q39: =(1+Q37)*(1+Q38)-1 -> 0.0711122 | R39: =(1+R37)*(1+R38)-1 -> 0.0717854 | ... U39: =(1+U37)*(1+U38)-1 -> 0.071
E44: Ano | K44: 2014 | L44: 2015 | M44: 2016 | N44: 2017 | O44: 2018 | P44: 2019 | Q44: 2020 | R44: 2021 | S44: 2022 | T44: 2023 | U44: YTD
E45: D&A do Arrendamento JSL | P45: 44835 | Q45: 91139 | R45: 56466 | S45: 87450 | T45: 112687 | U45: 37497
E46: D&A do Arrendamento Movida | P46: 55977 | Q46: 58450 | R46: 101267 | S46: 183795 | T46: 167130 | U46: 38023
E47: D&A do Arrendamento Vamos | P47: 8974 | Q47: 9014 | R47: 10223 | S47: 16120 | T47: 27650 | U47: 9637
E48: D&A do Arrendamento Simpar | K48: 0 | L48: 0 | M48: 0 | N48: 0 | O48: 0 | P48: 127308 | Q48: 129146 | R48: 186383 | S48: 199519 | T48: 357907 | U48: 98340
E53: Ano | K53: 2014 | L53: 2015 | M53: 2016 | N53: 2017 | O53: 2018 | P53: 2019 | Q53: 2020 | R53: 2021 | S53: 2022 | T53: 2023 | U53: =U44 -> YTD
E54: Depreciação & Amortização JSL | F54: 0 | G54: 0 | H54: 0 | I54: 0 | J54: 0 | O54: 176783 | P54: 183884 | Q54: 144858 | R54: 177673 | S54: 71645 | T54: 333899 | U54: 101164
E55: Depreciação & Amortização Movida | F55: 0 | G55: 0 | H55: 0 | I55: 0 | J55: 0 | L55: 101445 | M55: 77845 | N55: 74739 | O55: 102011 | P55: 222394 | Q55: 354430 | R55: 314984 | S55: 951429 | T55: 2070649 | U55: 409776
E56: Depreciação & Amortização Vamos | F56: 0 | G56: 0 | H56: 0 | I56: 0 | J56: 0 | M56: 116439 | N56: 124043 | O56: 207475 | P56: 225997 | Q56: 260205 | R56: 285886 | S56: 305835 | T56: 556541 | U56: 169269
E57: Depreciação e Amortização Simpar | K57: =-'DRE - Contas Abertas'!F19 -> 408865 | L57: =-'DRE - Contas Abertas'!G19 -> 508626 | M57: =-'DRE - Contas Abertas'!H19 -> 547187 | N57: =-'DRE - Contas Abertas'!I19 -> 525731 | O57: =-'DRE - Contas Abertas'!J19 -> 636817 | P57: =-'DRE - Contas Abertas'!K19-P48 -> 789436 | Q57: =-'DRE - Contas Abertas'!L19-Q48 -> 982807 | R57: =-'DRE - Contas Abertas'!M19-R48 -> 872731 | S57: =-'DRE - Contas Abertas'!N19-S48 -> 1686758 | T57: =-'DRE - Contas Abertas'!O19-T48 -> 3150378 | U57: =-'DRE - Contas Abertas'!P19-U48 -> 715241
E62: Ano | K62: 2014 | L62: 2015 | M62: 2016 | N62: 2017 | O62: 2018 | P62: 2019 | Q62: 2020 | R62: 2021 | S62: 2022 | T62: 2023 | U62: =U53 -> YTD
E63: ∆ Capital de Giro JSL | F63: 0 | G63: -122636.72 | H63: 147702.64 | I63: -36069.72 | J63: -41836.44 | O63: -106924.9 | P63: 165562.04 | Q63: -37475.532 | R63: 151983.54 | S63: -563688.64 | T63: 172467.59
E64: ∆ Capital de Giro Movida | F64: 0 | G64: -122636.72 | H64: 147702.64 | I64: -36069.72 | J64: -41836.44 | M64: -331764.22 | N64: 67357.25 | O64: -78593.6 | P64: -119673.88 | Q64: 7026 | R64: -595797 | S64: 1212017.5 | T64: -2619758
E65: ∆ Capital de Giro Vamos | F65: 0 | G65: -122636.72 | H65: 147702.64 | I65: -36069.72 | J65: -41836.44 | M65: 85296.5 | N65: 109623.4 | O65: 49086.75 | P65: 122239.05 | Q65: -435335.02 | R65: 389113.7 | S65: -728826.54 | T65: -915906
E66: ∆ Capital de Giro Simpar | L66: ='Projeções - CG + Capex'!L10-'Projeções - CG + Capex'!K10 -> -156805.05 | M66: ='Projeções - CG + Capex'!M10-'Projeções - CG + Capex'!L10 -> -495898.9 | N66: ='Projeções - CG + Capex'!N10-'Projeções - CG + Capex'!M10 -> 423583.2 | O66: ='Projeções - CG + Capex'!O10-'Projeções - CG + Capex'!N10 -> -135359.38 | P66: ='Projeções - CG + Capex'!P10-'Projeções - CG + Capex'!O10 -> 257745.5 | Q66: ='Projeções - CG + Capex'!Q10-'Projeções - CG + Capex'!P10 -> -713841.8 | R66: ='Projeções - CG + Capex'!R10-'Projeções - CG + Capex'!Q10 -> 326997.05 | S66: ='Projeções - CG + Capex'!S10-'Projeções - CG + Capex'!R10 -> 1369170.3 | T66: ='Balanço Patrimonial'!O16-'Balanço Patrimonial'!N16 -> 1625645.5

Sheet Projeções 2023
F3: =Dashboard!H3 -> SIMPAR (SIMH3)
A7: Páginas
A8: Dashboard
A9: WACC | F9: 1T24E | G9: 2T24E | H9: 3T24E | I9: 4T24E | J9: 2024E | M9: 1T24 | N9: 2T24 | O9: 3T24 | P9: 4T24 | Q9: 2024
A10: DRE Consolidado | E10: Receita Líquida | F10: =AVERAGE(M$21:M$22,M$24:M$26)*$J$10 -> 8180583.9 | G10: =AVERAGE(N$21:N$22,N$24:N$26)*$J$10 -> 8910649.4 | H10: =AVERAGE(O$21:O$22,O$24:O$26)*$J$10 -> 10153472 | I10: =AVERAGE(P$21:P$22,P$24:P$26)*$J$10 -> 10661636 | J10: ='DRE Consolidado'!W16 -> 37906341 | L10: Receita Líquida | M10: 9146986
A11: DRE + DCF | E11: CPV + Despesas Operacionais | F11: =F12-F10 -> -6532697 | G11: =G12-G10 -> -6935916.3 | H11: =H12-H10 -> -8044041.5 | I11: =I12-I10 -> -8458052.7 | J11: =J12-J10 -> -29970708 | L11: CPV + Despesas Operacionais | M11: -7569023
A12: DRE - Contas Abertas | E12: EBIT | F12: =AVERAGE(M$31:M$32,M$34:M$35)*$J$12 -> 1647886.8 | G12: =AVERAGE(N$31:N$32,N$34:N$35)*$J$12 -> 1974733.1 | H12: =AVERAGE(O$31:O$32,O$34:O$35)*$J$12 -> 2109430.2 | I12: =AVERAGE(P$31:P$32,P$34:P$35)*$J$12 -> 2203583.4 | J12: ='DRE Consolidado'!S38*J10 -> 7935633.5 | L12: EBIT | M12: =SUM(M10:M11) -> 1577963 | N12: =SUM(N10:N11) -> 0 | O12: =SUM(O10:O11) -> 0 | P12: =SUM(P10:P11) -> 0 | Q12: =SUM(M12:P12) -> 1577963
A13: Balanço Patrimonial | E13: Margem EBIT | F13: =F12/F10 -> 0.20143878 | G13: =G12/G10 -> 0.22161495 | H13: =H12/H10 -> 0.20775457 | I13: =I12/I10 -> 0.20668342 | J13: =J12/J10 -> 0.20934844 | L13: Margem EBIT | M13: =M12/M10 -> 0.1725118 | N13: =N12/N10 -> #DIV/0! | O13: =O12/O10 -> #DIV/0! | P13: =P12/P10 -> #DIV/0! | Q13: =Q12/Q10 -> #DIV/0!
A14: Painel de Índices | E14: Imposto de Renda e CSLL | F14: =-'DRE Consolidado'!$W$55*'Projeções 2023'!F12 -> -210923.7 | G14: =-'DRE Consolidado'!$W$55*'Projeções 2023'!G12 -> -252758.87 | H14: =-'DRE Consolidado'!$W$55*'Projeções 2023'!H12 -> -269999.62 | I14: =-'DRE Consolidado'!$W$55*'Projeções 2023'!I12 -> -282050.91 | J14: =SUM(F14:I14) -> -1015733.1 | L14: Imposto de Renda e CSLL | M14: 10923 | P14: 0 | Q14: 0
A15: Projeções - Receita e EBIT | E15: D&A de Arrendamento | F15: ='DRE Consolidado'!$W$57*'Projeções 2023'!F10 -> 108402.06 | G15: ='DRE Consolidado'!$W$57*'Projeções 2023'!G10 -> 118076.26 | H15: ='DRE Consolidado'!$W$57*'Projeções 2023'!H10 -> 134545.07 | I15: ='DRE Consolidado'!$W$57*'Projeções 2023'!I10 -> 141278.83 | J15: ='DRE Consolidado'!$W$57*'Projeções 2023'!J10 -> 502302.22 | L15: D&A de Arrendamento | M15: 98340 | P15: 0 | Q15: 0
A16: Projeções - CG + Capex | E16: NOPAT | F16: =F12+F14+F15 -> 1545365.2 | G16: =G12+G14+G15 -> 1840050.5 | H16: =H12+H14+H15 -> 1973975.6 | I16: =I12+I14+I15 -> 2062811.4 | J16: =J12+J14+J15 -> 7422202.6 | L16: NOPAT | M16: =SUM(M12,M14:M15) -> 1687226 | N16: =SUM(N12,N14:N15) -> 0 | O16: =SUM(O12,O14:O15) -> 0 | P16: 0 | Q16: 0
A17: Projeções 2023
A18: Processos
F20: 1º Trimestre | G20: 2º Trimestre | H20: 3º Trimestre | I20: 4º Trimestre | M20: 1º Trimestre | N20: 2º Trimestre | O20: 3º Trimestre | P20: 4º Trimestre
E21: 2018 | F21: 1936817.3 | G21: 1938188.6 | H21: 2068909.9 | I21: 2131477.9 | L21: 2018 | M21: =F21/SUM($F21:$I21) -> 0.23984185 | N21: =G21/SUM($F21:$I21) -> 0.24001165 | O21: =H21/SUM($F21:$I21) -> 0.25619926 | P21: =I21/SUM($F21:$I21) -> 0.26394724
E22: 2019 | F22: 2211784.8 | G22: 2388942.9 | H22: 2453591.5 | I22: 2631890.1 | L22: 2019 | M22: =F22/SUM($F22:$I22) -> 0.22834369 | N22: =G22/SUM($F22:$I22) -> 0.24663342 | O22: =H22/SUM($F22:$I22) -> 0.25330771 | P22: =I22/SUM($F22:$I22) -> 0.27171518
E23: 2020 | F23: 2356892.3 | G23: 2197224.8 | H23: 2603044.9 | I23: 2649895 | L23: 2020 | M23: =F23/SUM($F23:$I23) -> 0.24032615 | N23: =G23/SUM($F23:$I23) -> 0.22404527 | O23: =H23/SUM($F23:$I23) -> 0.2654257 | P23: =I23/SUM($F23:$I23) -> 0.27020288
E24: 2021 | F24: 2620105.7 | G24: 3149066.3 | H24: 3958280 | I24: 4138767 | L24: 2021 | M24: =F24/SUM($F24:$I24) -> 0.18895603 | N24: =G24/SUM($F24:$I24) -> 0.22710346 | O24: =H24/SUM($F24:$I24) -> 0.2854621 | P24: =I24/SUM($F24:$I24) -> 0.29847841
E25: 2022 | F25: =4590.296*1000 -> 4590296 | G25: =5463.4182*1000 -> 5463418.2 | H25: =6902.4238*1000 -> 6902423.8 | I25: =7425.65273798362*1000 -> 7425652.7 | L25: 2022 | M25: =F25/SUM($F25:$I25) -> 0.18826739 | N25: =G25/SUM($F25:$I25) -> 0.22407781 | O25: =H25/SUM($F25:$I25) -> 0.28309749 | P25: =I25/SUM($F25:$I25) -> 0.30455732
E26: 2023 | F26: 7440044 | G26: 7563636 | H26: 8318109 | I26: 8521824 | L26: 2023 | M26: =F26/SUM($F26:$I26) -> 0.23364321 | N26: =G26/SUM($F26:$I26) -> 0.23752443 | O26: =H26/SUM($F26:$I26) -> 0.2612175 | P26: =I26/SUM($F26:$I26) -> 0.26761486
F30: 1º Trimestre | G30: 2º Trimestre | H30: 3º Trimestre | I30: 4º Trimestre | M30: 1º Trimestre | N30: 2º Trimestre | O30: 3º Trimestre | P30: 4º Trimestre
E31: 2018 | F31: 211738.26 | G31: 245084.87 | H31: 251980.41 | I31: 251919.87 | L31: 2018 | M31: =F31/SUM($F31:$I31) -> 0.22039461 | N31: =G31/SUM($F31:$I31) -> 0.25510451 | O31: =H31/SUM($F31:$I31) -> 0.26228195 | P31: =I31/SUM($F31:$I31) -> 0.26221893
E32: 2019 | F32: 267737.72 | G32: 308979.8 | H32: 285057.99 | I32: 337389.34 | L32: 2019 | M32: =F32/SUM($F32:$I32) -> 0.22327015 | N32: =G32/SUM($F32:$I32) -> 0.25766249 | O32: =H32/SUM($F32:$I32) -> 0.23771376 | P32: =I32/SUM($F32:$I32) -> 0.2813536
E33: 2020 | F33: 286003.68 | G33: 187163 | H33: 297260.56 | I33: 425874.95 | L33: 2020 | M33: =F33/SUM($F33:$I33) -> 0.2390731 | N33: =G33/SUM($F33:$I33) -> 0.15645127 | O33: =H33/SUM($F33:$I33) -> 0.24848283 | P33: =I33/SUM($F33:$I33) -> 0.35599279
E34: 2021 | F34: 516655.02 | G34: 723575.59 | H34: 889681.74 | I34: 1000638.6 | L34: 2021 | M34: =F34/SUM($F34:$I34) -> 0.16503645 | N34: =G34/SUM($F34:$I34) -> 0.23113362 | O34: =H34/SUM($F34:$I34) -> 0.28419334 | P34: =I34/SUM($F34:$I34) -> 0.31963659
E35: 2022 | F35: =1135.551*1000 -> 1135551 | G35: =1286.7492*1000 -> 1286749.2 | H35: =1428.00600045888*1000 -> 1428006 | I35: =1266.51107638132*1000 -> 1266511.1 | L35: 2022 | M35: =F35/SUM($F35:$I35) -> 0.22192526 | N35: =G35/SUM($F35:$I35) -> 0.25147453 | O35: =H35/SUM($F35:$I35) -> 0.27908091 | P35: =I35/SUM($F35:$I35) -> 0.24751931
E36: 2023 | F36: 1317104 | G36: 1588108 | H36: 1395733 | I36: 591595.54 | L36: 2023 | M36: =F36/SUM($F36:$I36) -> 0.26920656 | N36: =G36/SUM($F36:$I36) -> 0.32459782 | O36: =H36/SUM($F36:$I36) -> 0.28527776 | P36: =I36/SUM($F36:$I36) -> 0.12091786

Sheet Processos
M1: Remota | N1: Tributário
M2: Possível | N2: Cível
F3: =Dashboard!H3 -> SIMPAR (SIMH3) | M3: Provável | N3: Trabalhista
N4: Administrativo
A7: Páginas
A8: Dashboard
A9: WACC
A10: DRE Consolidado | F10: Numero de Processos em Unidades | G10: Valor das Provisões | H10: Valor de Perdas Possiveis | I10: Valor de Perdas Remotas
A11: DRE + DCF | E11: Tributários | F11: 541 | G11: 0 | H11: 138400
A12: DRE - Contas Abertas | E12: Cíveis | F12: 4930 | G12: 18700 | H12: 116900
A13: Balanço Patrimonial | E13: Trabalhistas | F13: 3259 | G13: 156100 | H13: 141200
A14: Painel de Índices
A15: Projeções - Receita e EBIT
A16: Projeções - CG + Capex
A17: Projeções 2023
A18: Processos | E18: Número | F18: Descrição | G18: Valor do Processo | H18: Chance de Perda | I18: Comentário
E19: 0427983-81.2012.8.19.0001 | F19: O Ministério Público do Estado do Rio de Janeiro ajuizou três ações civis públicas discutindo a aquisição de veículos pela Polícia do Rio de Janeiro com gestão e manutenção de frota (processo 0152872-07.2014.8.19.0001, da 7ª Vara da Fazenda Pública do Rio de Janeiro; processo 0145782-45.2014.8.19.0001, da 13ª Vara da Fazenda Pública do Rio de Janeiro; e processo 0167693-16.2014.8.19.0001, da 9ª Vara da Fazenda Pública do Rio de Janeiro). Sobre o mesmo assunto, foram propostas quatro ações populares pelo Sr. Carlos Fernando dos Santos Azeredo (Processos: 0242335-28.2012.8.19.0001; 0043810-66.2013.8.19.0001; 0427983-81.2012.8.19.0001 e 0136630-70.2014.8.19.0001), as quais foram apensadas para julgamento em conjunto com as ações civis públicas acima referidas. Em todos os casos, a Companhia ratifica que cumpriu todas as suas obrigações contratuais. | G19: 85216 | H19: Remota
E20: 0152872-07.2014.8.19.0001 | F20: Ação Civil Pública proposta pelo MP, sendo um dos processos apensos ao processo explicado anteiormente. | G20: 134801 | H20: Remota
E21: 0167693-16.2014.8.19.0001 | F21: Ação Popular, sendo um dos processos apensos ao processo explicado anteiormente. | G21: 597401 | H21: Remota
E22: 0136630-70.2014.8.19.0001 | F22: Ação Civil Pública, sendo um dos processos apensos ao processo explicado anteiormente. | G22: 195085 | H22: Possível | I22: Consequências: Desembolso de caixa e suspensão/invalidação dos contratos discutidos.
E23: 0315594-41.2015.8.05.0001 | F23: Trata-se de ação civil pública proposta pelo Ministério Público do Estado da Bahia para discutir suposto ato de improbidade administrativa praticado pela Companhia e outras 27 pessoas, referente a um processo licitatório. O MP, em linhas gerais, alega a existência de uma organização de pessoas que agiram para fraudar diversas licitações relacionadas à Polícia Militar do Estado da Bahia, em benefício de empresas participantes. A Companhia foi mencionada em uma única licitação por ela vencida, referente a um contrato de venda de frota para a Polícia Militar do Estado da Bahia, com o fornecimento e manutenção, por 30 meses, de um total de 191 viaturas (“Contrato”). | G23: 4023 | H23: Possível | I23: Consequências: Desembolso de caixa, suspensão/invalidação do contrato discutido, restrições ao exercício de atividades e/ou recebimento de benefícios junto ao Poder Público.
E24: 0000225-70.2009.8.26.0045 | F24: Trata-se de ação civil pública, na qual se discute o preço do contrato de prestação de serviços de coleta e transporte de resíduos sólidos firmado pela Companhia com o Município de Arujá- SP, alegando que seria superior aos preços praticados por outros Municípios na mesma região | G24: 24193 | H24: Possível | I24: A JSL alega que o MP não considerou as diferenças de prestação de serviços em cada município. O processo encontra-se em primeira instância, sem sentença, ainda.
E25: 0009283-48.2007.8.26.0278 | F25: Trata-se de Ação Popular que tem por objeto o Contrato Emergencial n.º 160/0-A, mantido entre a JSL e a Prefeitura Municipal de Itaquaquecetuba, cujo objeto é a locação de veículos leves e caminhões sem motorista, com manutenção de frota e outras avenças. O Autor questiona a dispensa de licitação e critica a modalidade da contratação realizada pela Administração Pública, sustentando que a locação de veículos seria mais onerosa aos cofres públicos do que a sua aquisição. | G25: 1869 | H25: Provável | I25: O processo já teve decisão do STJ e determinou um ressarcimento parcial aos cofres públicos, cuja estimativa de perda é essa de R$ 1.869.
E26: 0039632-44.2010.8.26.0564 | F26: Trata-se de execução por quantia certa, com base em 40 (quarenta) contratos de mútuos no valor originário total de R$ 7.080.915,00, celebrados entre, de um lado e na condição de mutuante, a empresa Selpa, e do outro lado e na condição de mutuaria, a Transportadora Grande ABC Ltda., incorporada pela JSL em 29 de dezembro de 2011. Tais contratos teriam sido celebrados entre 2005 e 2006, antes da aquisição da Transportadora Grande ABC Ltda. pela Companhia. | G26: 46698 | H26: Remota
E27: 0015304-72.2013.8.26.0361 | F27: Trata-se de Ação Civil Pública que discute o contrato de concessão dos serviços de transporte público coletivo urbano de Mogi das Cruzes. O Ministério Público (“MP”) ajuizou Ação de Responsabilidade Civil por Ato de Improbidade Administrativa com base em gravação de conversa mantida unicamente entre representantes da empresa Eroles, que na ocasião explorava os serviços de transporte público coletivo de Mogi das Cruzes a título de permissão, com o então prefeito municipal. Nesta conversa, supostamente teria sido prometido pagamento de quantia ao então prefeito em troca de favorecimento das empresas Júlio Simões Transportes e Serviços Ltda. | G27: 3000 | H27: Possível | I27: Consequências: Desembolso de caixa, suspensão/invalidação dos contratos discutidos, restrições ao exercício de atividades e/ou recebimento de benefícios junto ao Poder Público.
E28: 0010938-33.2016.4.01.3200 | F28: O Ministério Público Federal (“MPF”) ajuizou seis ações civis públicas por improbidade administrativa decorrente de fatos ocorridos em período anterior à compra da Quick Logística Ltda. pela JSL S.A., movidas contra agentes públicos, despachantes e sociedades empresárias – entre as quais a Quick -, que supostamente estariam envolvidos em um esquema de pagamento indevido de valores para vistoriadores da SUFRAMA para facilitação de ingresso de mercadorias na Zona Franca de Manaus, (processo 10938-33.2016.4.01.3200, processo 10959-09.2016.4.01.3200, processo 11391- 28.2016.4.01.3200, processo 10960-91.2016.4.01.3200, processo 11345-39.2016.4.01.3200 e processo 10939-18.2016.4.01.3200, todos em trâmite na 3ª Vara Federal da Seção Judiciária do Estado do Amazonas). | G28: 1600 | H28: Possível | I28: MPF e a Quick celebraram acordo de não persecução cível para o encerramento das referidas ações, o qual será submetido à homologação judicial nos respectivos processos.
E29: 0011391-28.2016.4.01.3200 | F29: Um dos processos apensos ao anterior | G29: 3200 | H29: Possível
E30: 0010939-18.2016.4.01.3200 | F30: Um dos processos apensos ao anterior | G30: 1200 | H30: Possível
E31: 0010960-91.2016.4.01.3200 | F31: Um dos processos apensos ao anterior | G31: 2000 | H31: Possível
E32: 0011345-39.2016.4.01.3200 | F32: Um dos processos apensos ao anterior | G32: 400 | H32: Possível
E33: 0010959-09.2016.4.01.3200 | F33: Um dos processos apensos ao anterior | G33: 1800 | H33: Possível
E34: 0206683-08.2016.8.19.0001 | F34: O Ministério Público do Estado do Rio de Janeiro propôs Ação Civil Pública questionando supostas irregularidades relacionadas aos contratos administrativos nos 034/2007, 035/2007, 036/2007 e 037/2007, firmados após regular processo licitatório (Pregão Presencial nº 04/2007), entre o Município do Rio de Janeiro e as empresas Viação Saens Peña S.A, Consórcio Trespan Rio, Breda Transportes e Turismo Rio – EIRELI e Júlio Simões Transportes e Serviços Ltda. (atual JSL), cujo objeto é a prestação de serviços de transportes, com o fornecimento de veículos e mão-de-obra operacional, para o evento esportivo internacional dos Jogos Pan-americanos e Parapan-americanos, sediados na cidade do Rio de Janeiro em 2007, sendo pleiteado em face da JSL S.A. a condenação na devolução aos cofres públicos da quantia de R$ 6.582.655,87, em razão de alegado sobrepreço e inadimplemento parcial do contrato. | G34: 9966 | H34: Possível
E35: 1007206-52.2021.4.01.3814 | F35: Trata-se de Ação Civil Pública ajuizada pelo Ministério Público Federal (“MPF”) em face da Companhia, por suposto excesso de peso em seus veículos de transporte de carga (ou de seus contratados), quando trafegavam em rodovias federais. | G35: 100 | H35: Possível
E36: 0546979-57.2014.8.05.0001 | F36: Trata-se de ação civil pública ajuizada pelo Ministério Público do Estado da Bahia, na qual alega irregularidades no edital de licitação do Pregão Presencial nº 076/2014 – que resultou na celebração do Contrato SEMGE nº 056/2014, em virtude de exigências e restrições que alega serem excessivas e indevidas, bem como em razão do suposto caráter genérico do Termo de Referência, que indicava apenas o valor global de cada Secretaria, sem qualquer detalhamento de custos unitários, além de alegar discrepâncias de valores em relação a Contrato anterior, sugerindo sobrepreço. | G36: 154000 | H36: Remota | I36: Em defesa, a Pronto Express demonstrou a diferença de objeto e escopo entre os contratos comparados pelo Ministério Público, evidenciando a regularidade da contratação e o atendimento de requisitos legais pela Contratada. O processo se encontra na fase inicial, de modo que não houve prolação de sentença.
E37: 0005434-42.2009.8.26.0361 | F37: Trata-se de ação penal, movida contra o Diretor Presidente da controladora da Companhia, Sr. Fernando Antonio Simões e dos Srs. Antonio Alexandre Eroles, Antonio Adriano Eroles e José Carlos Pavanelli pelos mesmos fatos discutidos na ação civil pública processo nº 0015304-72.2013.8.26.0361, reportada abaixo. A denúncia foi recebida em 29 de novembro de 2013. O Sr. Fernando Antonio Simões apresentou resposta prévia à denúncia, rejeitando todas as alegações e acusações apresentadas contra si pelo Ministério Público e requerendo sua absolvição sumária uma vez que jamais participou de qualquer suposto acordo ilícito e pelos demais argumentos descritos no item 4.3 acima mencionado. Em audiência de instrução, o corréu Antonio Alexandre Eroles, em seu interrogatório perante o juízo, negou a participação do Sr. Fernando Antonio Simões em qualquer ato ilícito, desmentindo falsa afirmação anteriormente feita em relação ao mesmo e que deu origem à sua indevida inclusão em ambas as ações. A Ação Penal foi julgada improcedente em primeira instância e o Tribunal de Justiça do Estado de São Paulo, em julgamento realizado no dia 22/10/2020, manteve a improcedência. | G37: 0 | H37: Possível | I37: As principais consequência de uma condenação aqui são: Condenação criminal dos réus e restrição à administração de empresas.
E38: 0000080-25-2015-5-18-0191 | F38: Ação Civil Pública, requerendo a antecipação de tutela e a condenação da JSL às seguintes obrigações: (a) consignar em registro mecânico, manual ou sistema eletrônico os horários de entrada, saída e período de repouso efetivamente praticados pelo empregado; (b) respeitar a jornada legal de trabalho pactuada com os seus empregados, observado o limite legal; (c) respeitar o limite de prorrogação legal de 02 horas diárias; (d) remunerar as horas extras com 50%, quando não houver compensação; (e) conceder o descanso semanal remunerado conforme escala de revezamento; (f) compensar ou remunerar em dobro as horas trabalhadas em domingos e feriados; (g) arbitramento de multa de R$ 10.000,00, por dia, para a hipótese de descumprimento; (h) indenização por dano moral coletivo no valor de R$ 2.000.000,00. | G38: 123 | H38: Provável
E39: 10003410220175020044 | F39: Ação anulatória, para anular autos de infração lavrados em decorrência de suposta terceirização ilícita. | G39: 100 | H39: Possível | I39: O processo já teve sentença procedente. Está pendente de julgamento de recurso interposto pela União.
E40: 10005763020195020001 | F40: Idem ao anterior | G40: 500 | H40: Possível | I40: O processo já teve sentença procedente. Está pendente de julgamento de recurso interposto pela União.
E41: 0100759-80.2018.5.01.0262 | F41: Trata-se de ação civil pública ajuizada pelo Ministério Público do Trabalho visando: (i) declarar inconstitucional o artigo 235-C, caput da CLT, impedindo a prorrogação da jornada diária de trabalho dos motoristas da Companhia além do limite de 2 horas, sem justificativa legal; (ii) reconhecer a não concessão dos intervalos intrajornada e interjornada, e do descanso semanal remunerado; e (iii) ondenação ao pagamento de dano moral coletivo | G41: 500 | H41: Provável
E42: 0010963-36.2021.5.15.0116 | F42: A presente ação visa a condenação da Companhia ao cumprimento de obrigação de fazer consistente em manter o percentual de empregados previsto no artigo 93 da Lei n.º 8.213/1991, com beneficiários reabilitados ou pessoas portadoras de deficiência, considerando para o cálculo do percentual a somatória de todos os trabalhadores de todos os estabelecimentos da Ré. | G42: 1000 | H42: Possível
E43: 10932.000003/2008-41 | F43: Auto de infração que impõe multa isolada à Transportadora Grande ABC Ltda (empresa esta incorporada pela JSL S.A.) por alegada realização de compensações de débitos de COFINS (de Janeiro a Setembro de 2002 e de Janeiro de 2003 a Dezembro de 2005) e de PIS (de Abril de 2003 a Dezembro de 2005), nos meses de outubro e novembro de 2005 e junho de 2006 de forma indevida, utilizando-se de créditos de terceiros para tanto. | G43: 6454 | H43: Possível
E44: 10.803.720003/2013-02 | F44: Auto de infração lavrado (processo administrativo fiscal nº 10.803.720003/2013-02), com a constituição de créditos tributários no valor total de R$ 68.104.480,07 (sessenta e oito milhões, cento e quatro mil, quatrocentos e oitenta reais e sete centavos), incluindo Imposto de Renda Pessoa Jurídica – IRPJ, Contribuição Social sobre o Lucro Líquido – CSLL, contribuição ao PIS e COFINS. | G44: 109631 | H44: Remota
E45: 10.803.720334/2013-34 | F45: Autos de infração lavrados (processo administrativo fiscal nº 10.803.720334/2013-34), com a constituição de créditos tributários no valor total de R$ 71.197.415,46 (setenta e um milhões, cento e noventa e sete mil, quatrocentos e quinze reais e quarenta e seis centavos), incluindo Imposto de Renda Pessoa Jurídica – IRPJ, Contribuição Social sobre o Lucro Líquido – CSLL, contribuição ao PIS e COFINS | G45: 112760 | H45: Possível
E46: 19515.720.098/2018-81 | F46: Trata-se de autos de infração lavrados contra a Companhia , relativos ao exercício de 2013, com a constituição de créditos de contribuição ao PIS e de COFINS.Em apertada síntese, a fiscalização, a partir das declarações apresentadas pela JSL à Receita Federal do Brasil e da documentação contida no procedimento administrativo, refez a apuração da contribuição ao PIS e da COFINS da referida companhia no exercício de 2013, tendo sido apontadas supostas inconsistências. | G46: 12119 | H46: Possível
E47: 4.117.807-5 | F47: Trata-se de Auto de Infração por meio do qual foram constituídos em face da JSL supostos créditos tributários de ICMS, sob alegação de creditamento indevido do ICMS incidente na aquisição de bens destinados ao ativo imobilizado (caminhões e semirreboques) que teriam sido dados em locação a terceiros. | G47: 12016 | H47: Possível
E48: 4.121.117-0 | F48: Idem ao anterior | G48: 29652 | H48: Possível
E49: 4.060.192-4 | F49: Idem ao anterior | G49: 9259 | H49: Possível
E50: 2.081.717-0 | F50: Auto de Infração, com imposição de crédito de ICMS + multa em decorrência do suposto não pagamento do tributo em razão do diferencial de alíquotas, nas aquisições de máquinas, equipamentos e veículos leves; | G50: 14043 | H50: Remota
E51: 003603646.2013.4.03.6182 | F51: Cobrança de supostos débitos de COFINS devidos pela empresa (inscrição em dívida ativa nº 80613015708-20). | G51: 19986 | H51: Possível
E52: 4.011.801.72704-6 | F52: Trata-se de auto de infração lavrado por suposta omissão de recolhimento de ICMS, em decorrência da utilização irregular do benefício do LOGPRODUZIR, benefício fiscal concedido pelo Estado de Goiás que consiste na concessão de crédito outorgado do ICMS, incidente sobre as prestações interestaduais de transporte realizadas pela empresa operadora de logística. Processo aguarda julgamento em segunda instância. | G52: 11901 | H52: Possível
... E57: 000595.2017 | F57: Idem ao anterior | G57: 19763 | H57: Remota
E58: 5056523-69.2017.8.09.0051 | F58: Ação Civil Pública. Inobservância ao Estatuto da Pessoa com Deficiência pelo fato de não disponibilizar em sua frota a cota mínima de carros adaptados. | G58: 100 | H58: Possível | I58: A ação envolve norma que precisa de regulamentação, ainda. A defesa da empresa se sustenta nessa ausencia de regulamentação
E59: 0005434-42.2009.8.26.0361 | F59: Trata-se de ação penal, movida contra o Diretor Presidente da controladora da Companhia, Sr. Fernando Antonio Simões e dos Srs. Antonio Alexandre Eroles, Antonio Adriano Eroles e José Carlos Pavanelli pelos mesmos fatos discutidos na ação civil pública processo nº 0015304-72.2013.8.26.0361, reportada abaixo. A denúncia foi recebida em 29 de novembro de 2013. O Sr. Fernando Antonio Simões apresentou resposta prévia à denúncia, rejeitando todas as alegações e acusações apresentadas contra si pelo Ministério Público e requerendo sua absolvição sumária uma vez que jamais participou de qualquer suposto acordo ilícito e pelos demais argumentos descritos no item 4.3 acima mencionado. Em audiência de instrução, o corréu Antonio Alexandre Eroles, em seu interrogatório perante o juízo, negou a participação do Sr. Fernando Antonio Simões em qualquer ato ilícito, desmentindo falsa afirmação anteriormente feita em relação ao mesmo e que deu origem à sua indevida inclusão em ambas as ações. A Ação Penal foi julgada improcedente em primeira instância e o Tribunal de Justiça do Estado de São Paulo, em julgamento realizado no dia 22/10/2020, manteve a improcedência. | G59: 0 | H59: Possível | I59: As principais consequência de uma condenação aqui são: Condenação criminal dos réus e restrição à administração de empresas.
E60: 0136630-70.2014.8.19.0001 | F60: O Ministério Público do Estado do Rio de Janeiro ajuizou três ações civis públicas discutindo a aquisição de veículos pela Polícia do Rio de Janeiro com gestão e manutenção de frota (processo 0152872-07.2014.8.19.0001, da 7ª Vara da Fazenda Pública do Rio de Janeiro; processo 0145782-45.2014.8.19.0001, da 13ª Vara da Fazenda Pública do Rio de Janeiro; e processo 0167693-16.2014.8.19.0001, da 9ª Vara da Fazenda Pública do Rio de Janeiro). Sobre o mesmo assunto, foram propostas quatro ações populares pelo Sr. Carlos Fernando dos Santos Azeredo (Processos: 0242335-28.2012.8.19.0001; 0043810-66.2013.8.19.0001; 0427983-81.2012.8.19.0001 e 0136630-70.2014.8.19.0001), as quais foram apensadas para julgamento em conjunto com as ações civis públicas acima referidas. Em todos os casos, a Companhia ratifica que cumpriu todas as suas obrigações contratuais. | G60: 195085 | H60: Possível | I60: Consequências: Desembolso de caixa e suspensão/invalidação dos contratos discutidos.
E61: 0315594-41.2015.8.05.0001 | F61: Trata-se de ação civil pública proposta pelo Ministério Público do Estado da Bahia para discutir suposto ato de improbidade administrativa praticado pela Companhia e outras 27 pessoas, referente a um processo licitatório. O MP, em linhas gerais, alega a existência de uma organização de pessoas que agiram para fraudar diversas licitações relacionadas à Polícia Militar do Estado da Bahia, em benefício de empresas participantes. A Companhia foi mencionada em uma única licitação por ela vencida, referente a um contrato de venda de frota para a Polícia Militar do Estado da Bahia, com o fornecimento e manutenção, por 30 meses, de um total de 191 viaturas (“Contrato”). | G61: 4023 | H61: Possível | I61: Consequências: Desembolso de caixa, suspensão/invalidação do contrato discutido, restrições ao exercício de atividades e/ou recebimento de benefícios junto ao Poder Público.
E62: 0015304-72.2013.8.26.0361 | F62: Trata-se de Ação Civil Pública que discute o contrato de concessão dos serviços de transporte público coletivo urbano de Mogi das Cruzes. O Ministério Público (“MP”) ajuizou Ação de Responsabilidade Civil por Ato de Improbidade Administrativa com base em gravação de conversa mantida unicamente entre representantes da empresa Eroles, que na ocasião explorava os serviços de transporte público coletivo de Mogi das Cruzes a título de permissão, com o então prefeito municipal. Nesta conversa, supostamente teria sido prometido pagamento de quantia ao então prefeito em troca de favorecimento das empresas Júlio Simões Transportes e Serviços Ltda. | G62: 3000 | H62: Possível | I62: Consequências: Desembolso de caixa, suspensão/invalidação dos contratos discutidos, restrições ao exercício de atividades e/ou recebimento de benefícios junto ao Poder Público.
E63: 0242335-28.2012.8.19.0001 | F63: O Ministério Público do Estado do Rio de Janeiro ajuizou três ações civis públicas discutindo a aquisição conforme já relatado no processo da primeira linha. | G63: 134643 | H63: Remota | I63: Consequências: Desembolso de caixa, suspensão/invalidação dos contratos discutidos, restrições ao exercício de atividades e/ou recebimento de benefícios junto ao Poder Público.
E64: 0145782-45.2014.8.19.0001 | F64: O Ministério Público do Estado do Rio de Janeiro ajuizou três ações civis públicas discutindo a aquisição conforme já relatado no processo da primeira linha. | G64: 134643 | H64: Remota | I64: Consequências: Desembolso de caixa, suspensão/invalidação dos contratos discutidos, restrições ao exercício de atividades e/ou recebimento de benefícios junto ao Poder Público.
E65: 0043810-66.2013.8.19.0001 | F65: O Ministério Público do Estado do Rio de Janeiro ajuizou três ações civis públicas discutindo a aquisição conforme já relatado no processo da primeira linha. Essa é uma das ações popuplares | G65: 257749 | H65: Remota
E66: 0034695-44.2013.8.26.0577 | F66: Trata-se de Ação Popular tendo por objeto discussão a respeito do reajuste tarifário aplicado nos contratos de transporte coletivo urbano do Município de São Jose dos Campos | G66: 5 | H66: Possível
E67: 1001512-60.2016.8.26.0577 | F67: Trata-se de Ação Popular que tem por objeto discussão de reajuste tarifário no serviço de transporte coletivo no Município de São José dos Campos | G67: 25 | H67: Possível
E68: 1000098-27.2016.8.26.0577 | F68: Trata-se de Ação Popular objetivando a anulação do ato (Lei Complementar Municipal nº. 536, de 28 de abril de 2014), que concedeu isenção temporária de ISSQN às empresas que operam o serviço de transporte coletivo na cidade, bem como a condenação dos Réus a restituir aos cofres públicos os valores não arrecadados no período, estimados em R$ 15.000.000,00. | G68: 50 | H68: Remota
E69: 0179606-92.2014.8.19.0001 | F69: Trata-se de Ação Popular que questiona três processos licitatórios para locação de veículos e equipamentos para limpeza urbana realizados pela Comlurb sob os nºs. 698/2013, 073/2014 e 074/2014 | G69: 30 | H69: Possível
E70: 0804667-19.2018.4.05.8300 | F70: A Yolanda Logística sagrou-se vencedora em procedimento licitatório, tendo então celebrado, em 25.5.98, contrato de permissão para exploração de serviços públicos de movimentação e armazenagem de cargas em terminal alfandegado, regulado pela Lei nº 9.074/95 e pelo Decreto nº 1.910/96, que estabeleciam o prazo máximo de 10 (dez) anos para a delegação. Ocorre que, em 30.5.03, sobreveio a Lei Federal nº 10.684/03, que introduziu dois novos parágrafos no artigo 1º da Lei nº 9.074/95, os quais determinavam que “o prazo das concessões e permissões de que se trata o inciso VI deste artigo será de vinte e cinco anos, podendo ser prorrogados por dez anos” e que “ao término do prazo, as atuais concessões e permissões, mencionadas no § 2º, incluídas as anteriores à Lei n. 8.987, de 13 de fevereiro de 1995, seriam prorrogadas pelo prazo previsto no § 2º”. | G70: 10 | H70: Possível
E71: 1015595-42.2019.8.26.0071 | F71: Inobservância ao Estatuto da Pessoa com Deficiênc | G71: 1 | H71: Provável
E72: 0009137-51.2011.4.02.5101 | F72: Trata-se de ação civil pública movida por Universidade Federal Rural do Rio de Janeiro em face de Ciclus Ambiental do Brasil S.A, Município do Rio de Janeiro, Município de Seropédica e Instituto Estadual do Ambiente – INEA. Pleiteia a autora seja declarada a nulidade do licenciamento ambiental concedido pelo INEA à Central de Tratamento de Resíduos Sólidos Santa Rosa (“CTR Santa Rosa”), localizado no Município de Seropédica, condenando os réus à paralisação definitiva das atividades da CTR, com transferência para áreas adequadas, bem como retirada de todo e qualquer resíduo no local, às expensas das rés. O principal fundamento utilizado é no sentido de que o empreendimento causará danos ao ecossistema daquela região, e que no procedimento de expedição da licença teriam supostas irregularidades. | G72: 100 | H72: Remota | I72: Se a Simpar perder esse processo, a Ciclus poderá ter que parar de operar.
E73: 0190756-70.2014.8.19.0001 | F73: Trata-se de processo relativo à regularidade ambiental da Estação de Transferência de Resíduos (ETR) de Santa Cruz, oriundos da cidade do Rio de Janeiro e destinados ao Aterro Sanitário de Seropédica (CTR RIO), relativos a apuração de supostas irregularidades ambientais ocorridas no licenciamento, instalação e na operação da ETR Santa Cruz. | G73: 72 | H73: Possível | I73: Não há impacto direto a Companhia, em caso de perda, afetará somente a logística da disposição dos resíduos que deverá ser transferida para outro local.
