Workbook
Name InfImp22: '[1]Dados Complementares'!$F$11
Name InfImp23: '[1]Dados Complementares'!$G$11
Name InfImp24: '[1]Dados Complementares'!$H$11
Name InfImp25: '[1]Dados Complementares'!$I$11
Name InfImp26: '[1]Dados Complementares'!$J$11
Name InfImp27: '[1]Dados Complementares'!$K$11
Name InfImp28: '[1]Dados Complementares'!$L$11
Name InfImp29: '[1]Dados Complementares'!$M$11
Name InfImp30: '[1]Dados Complementares'!$N$11
Name InfImp32: '[1]Dados Complementares'!$P$11
Name PIB26_BRASIL: '[1]Dados Complementares'!$J$14
Name PIB26_CHINA: '[1]Dados Complementares'!$J$15
Name PIB26_INDIA: '[1]Dados Complementares'!$J$16
Name PIB26_MUNDO: '[1]Dados Complementares'!$J$20
Name PIB27_BRASIL: '[1]Dados Complementares'!$K$14
Name PIB27_INDIA: '[1]Dados Complementares'!$K$16

Sheet Dashboard
I3: Raia Drogasil ($RADL3)
A7: Páginas
A8: Dashboard
A9: WACC | E9: Trimestre | F9: 1 | H9: WACC | I9: =I10-0.5% -> 0.11847175 | J9: =((SUM('DRE + DCF'!$P$54,NPV($I9,'DRE + DCF'!$Q$54:$AZ$54,SUM('DRE + DCF'!$BA$54,('DRE + DCF'!$BB$46*(1-((J$18-'Projeções - Receita'!$BA$58)/('DRE + DCF'!$BC$43-'Projeções - Receita'!$BA$58)))*(1+J$18))/($I9-J$18))))/((1+$I9)^((5-$F$9)*3/12)))+SUM($F$13:$F$14))/$F$11 -> 41.506622 | K9: =((SUM('DRE + DCF'!$P$54,NPV($I9,'DRE + DCF'!$Q$54:$AZ$54,SUM('DRE + DCF'!$BA$54,('DRE + DCF'!$BB$46*(1-((K$18-'Projeções - Receita'!$BA$58)/('DRE + DCF'!$BC$43-'Projeções - Receita'!$BA$58)))*(1+K$18))/($I9-K$18))))/((1+$I9)^((5-$F$9)*3/12)))+SUM($F$13:$F$14))/$F$11 -> 42.026797 | L9: =((SUM('DRE + DCF'!$P$54,NPV($I9,'DRE + DCF'!$Q$54:$AZ$54,SUM('DRE + DCF'!$BA$54,('DRE + DCF'!$BB$46*(1-((L$18-'Projeções - Receita'!$BA$58)/('DRE + DCF'!$BC$43-'Projeções - Receita'!$BA$58)))*(1+L$18))/($I9-L$18))))/((1+$I9)^((5-$F$9)*3/12)))+SUM($F$13:$F$14))/$F$11 -> 42.609525 | M9: =((SUM('DRE + DCF'!$P$54,NPV($I9,'DRE + DCF'!$Q$54:$AZ$54,SUM('DRE + DCF'!$BA$54,('DRE + DCF'!$BB$46*(1-((M$18-'Projeções - Receita'!$BA$58)/('DRE + DCF'!$BC$43-'Projeções - Receita'!$BA$58)))*(1+M$18))/($I9-M$18))))/((1+$I9)^((5-$F$9)*3/12)))+SUM($F$13:$F$14))/$F$11 -> 43.267183 | N9: =((SUM('DRE + DCF'!$P$54,NPV($I9,'DRE + DCF'!$Q$54:$AZ$54,SUM('DRE + DCF'!$BA$54,('DRE + DCF'!$BB$46*(1-((N$18-'Projeções - Receita'!$BA$58)/('DRE + DCF'!$BC$43-'Projeções - Receita'!$BA$58)))*(1+N$18))/($I9-N$18))))/((1+$I9)^((5-$F$9)*3/12)))+SUM($F$13:$F$14))/$F$11 -> 44.015641 | O9: =((SUM('DRE + DCF'!$P$54,NPV($I9,'DRE + DCF'!$Q$54:$AZ$54,SUM('DRE + DCF'!$BA$54,('DRE + DCF'!$BB$46*(1-((O$18-'Projeções - Receita'!$BA$58)/('DRE + DCF'!$BC$43-'Projeções - Receita'!$BA$58)))*(1+O$18))/($I9-O$18))))/((1+$I9)^((5-$F$9)*3/12)))+SUM($F$13:$F$14))/$F$11 -> 44.875596 | P9: =((SUM('DRE + DCF'!$P$54,NPV($I9,'DRE + DCF'!$Q$54:$AZ$54,SUM('DRE + DCF'!$BA$54,('DRE + DCF'!$BB$46*(1-((P$18-'Projeções - Receita'!$BA$58)/('DRE + DCF'!$BC$43-'Projeções - Receita'!$BA$58)))*(1+P$18))/($I9-P$18))))/((1+$I9)^((5-$F$9)*3/12)))+SUM($F$13:$F$14))/$F$11 -> 45.87455 | Q9: =((SUM('DRE + DCF'!$P$54,NPV($I9,'DRE + DCF'!$Q$54:$AZ$54,SUM('DRE + DCF'!$BA$54,('DRE + DCF'!$BB$46*(1-((Q$18-'Projeções - Receita'!$BA$58)/('DRE + DCF'!$BC$43-'Projeções - Receita'!$BA$58)))*(1+Q$18))/($I9-Q$18))))/((1+$I9)^((5-$F$9)*3/12)))+SUM($F$13:$F$14))/$F$11 -> 47.049859 | ... S9: =((SUM('DRE + DCF'!$P$54,NPV($I9,'DRE + DCF'!$Q$54:$AZ$54,SUM('DRE + DCF'!$BA$54,('DRE + DCF'!$BB$46*(1-((S$18-'Projeções - Receita'!$BA$58)/('DRE + DCF'!$BC$43-'Projeções - Receita'!$BA$58)))*(1+S$18))/($I9-S$18))))/((1+$I9)^((5-$F$9)*3/12)))+SUM($F$13:$F$14))/$F$11 -> 50.160515
A10: DRE + DCF | E10: Ticker | F10: RADL3 | I10: =I11-0.5% -> 0.12347175 | J10: =((SUM('DRE + DCF'!$P$54,NPV($I10,'DRE + DCF'!$Q$54:$AZ$54,SUM('DRE + DCF'!$BA$54,('DRE + DCF'!$BB$46*(1-((J$18-'Projeções - Receita'!$BA$58)/('DRE + DCF'!$BC$43-'Projeções - Receita'!$BA$58)))*(1+J$18))/($I10-J$18))))/((1+$I10)^((5-$F$9)*3/12)))+SUM($F$13:$F$14))/$F$11 -> 35.777812 | K10: =((SUM('DRE + DCF'!$P$54,NPV($I10,'DRE + DCF'!$Q$54:$AZ$54,SUM('DRE + DCF'!$BA$54,('DRE + DCF'!$BB$46*(1-((K$18-'Projeções - Receita'!$BA$58)/('DRE + DCF'!$BC$43-'Projeções - Receita'!$BA$58)))*(1+K$18))/($I10-K$18))))/((1+$I10)^((5-$F$9)*3/12)))+SUM($F$13:$F$14))/$F$11 -> 36.107173 | L10: =((SUM('DRE + DCF'!$P$54,NPV($I10,'DRE + DCF'!$Q$54:$AZ$54,SUM('DRE + DCF'!$BA$54,('DRE + DCF'!$BB$46*(1-((L$18-'Projeções - Receita'!$BA$58)/('DRE + DCF'!$BC$43-'Projeções - Receita'!$BA$58)))*(1+L$18))/($I10-L$18))))/((1+$I10)^((5-$F$9)*3/12)))+SUM($F$13:$F$14))/$F$11 -> 36.471437 | M10: =((SUM('DRE + DCF'!$P$54,NPV($I10,'DRE + DCF'!$Q$54:$AZ$54,SUM('DRE + DCF'!$BA$54,('DRE + DCF'!$BB$46*(1-((M$18-'Projeções - Receita'!$BA$58)/('DRE + DCF'!$BC$43-'Projeções - Receita'!$BA$58)))*(1+M$18))/($I10-M$18))))/((1+$I10)^((5-$F$9)*3/12)))+SUM($F$13:$F$14))/$F$11 -> 36.876708 | N10: =((SUM('DRE + DCF'!$P$54,NPV($I10,'DRE + DCF'!$Q$54:$AZ$54,SUM('DRE + DCF'!$BA$54,('DRE + DCF'!$BB$46*(1-((N$18-'Projeções - Receita'!$BA$58)/('DRE + DCF'!$BC$43-'Projeções - Receita'!$BA$58)))*(1+N$18))/($I10-N$18))))/((1+$I10)^((5-$F$9)*3/12)))+SUM($F$13:$F$14))/$F$11 -> 37.330595 | O10: =((SUM('DRE + DCF'!$P$54,NPV($I10,'DRE + DCF'!$Q$54:$AZ$54,SUM('DRE + DCF'!$BA$54,('DRE + DCF'!$BB$46*(1-((O$18-'Projeções - Receita'!$BA$58)/('DRE + DCF'!$BC$43-'Projeções - Receita'!$BA$58)))*(1+O$18))/($I10-O$18))))/((1+$I10)^((5-$F$9)*3/12)))+SUM($F$13:$F$14))/$F$11 -> 37.842719 | P10: =((SUM('DRE + DCF'!$P$54,NPV($I10,'DRE + DCF'!$Q$54:$AZ$54,SUM('DRE + DCF'!$BA$54,('DRE + DCF'!$BB$46*(1-((P$18-'Projeções - Receita'!$BA$58)/('DRE + DCF'!$BC$43-'Projeções - Receita'!$BA$58)))*(1+P$18))/($I10-P$18))))/((1+$I10)^((5-$F$9)*3/12)))+SUM($F$13:$F$14))/$F$11 -> 38.425415 | Q10: =((SUM('DRE + DCF'!$P$54,NPV($I10,'DRE + DCF'!$Q$54:$AZ$54,SUM('DRE + DCF'!$BA$54,('DRE + DCF'!$BB$46*(1-((Q$18-'Projeções - Receita'!$BA$58)/('DRE + DCF'!$BC$43-'Projeções - Receita'!$BA$58)))*(1+Q$18))/($I10-Q$18))))/((1+$I10)^((5-$F$9)*3/12)))+SUM($F$13:$F$14))/$F$11 -> 39.094767 | ... S10: =((SUM('DRE + DCF'!$P$54,NPV($I10,'DRE + DCF'!$Q$54:$AZ$54,SUM('DRE + DCF'!$BA$54,('DRE + DCF'!$BB$46*(1-((S$18-'Projeções - Receita'!$BA$58)/('DRE + DCF'!$BC$43-'Projeções - Receita'!$BA$58)))*(1+S$18))/($I10-S$18))))/((1+$I10)^((5-$F$9)*3/12)))+SUM($F$13:$F$14))/$F$11 -> 40.786603
A11: DRE - Contas Abertas | E11: Ações Emitidas (mil) | F11: 1647747.4 | I11: =I12-0.5% -> 0.12847175 | J11: =((SUM('DRE + DCF'!$P$54,NPV($I11,'DRE + DCF'!$Q$54:$AZ$54,SUM('DRE + DCF'!$BA$54,('DRE + DCF'!$BB$46*(1-((J$18-'Projeções - Receita'!$BA$58)/('DRE + DCF'!$BC$43-'Projeções - Receita'!$BA$58)))*(1+J$18))/($I11-J$18))))/((1+$I11)^((5-$F$9)*3/12)))+SUM($F$13:$F$14))/$F$11 -> 31.208886 | K11: =((SUM('DRE + DCF'!$P$54,NPV($I11,'DRE + DCF'!$Q$54:$AZ$54,SUM('DRE + DCF'!$BA$54,('DRE + DCF'!$BB$46*(1-((K$18-'Projeções - Receita'!$BA$58)/('DRE + DCF'!$BC$43-'Projeções - Receita'!$BA$58)))*(1+K$18))/($I11-K$18))))/((1+$I11)^((5-$F$9)*3/12)))+SUM($F$13:$F$14))/$F$11 -> 31.420764 | L11: =((SUM('DRE + DCF'!$P$54,NPV($I11,'DRE + DCF'!$Q$54:$AZ$54,SUM('DRE + DCF'!$BA$54,('DRE + DCF'!$BB$46*(1-((L$18-'Projeções - Receita'!$BA$58)/('DRE + DCF'!$BC$43-'Projeções - Receita'!$BA$58)))*(1+L$18))/($I11-L$18))))/((1+$I11)^((5-$F$9)*3/12)))+SUM($F$13:$F$14))/$F$11 -> 31.652621 | M11: =((SUM('DRE + DCF'!$P$54,NPV($I11,'DRE + DCF'!$Q$54:$AZ$54,SUM('DRE + DCF'!$BA$54,('DRE + DCF'!$BB$46*(1-((M$18-'Projeções - Receita'!$BA$58)/('DRE + DCF'!$BC$43-'Projeções - Receita'!$BA$58)))*(1+M$18))/($I11-M$18))))/((1+$I11)^((5-$F$9)*3/12)))+SUM($F$13:$F$14))/$F$11 -> 31.907585 | N11: =((SUM('DRE + DCF'!$P$54,NPV($I11,'DRE + DCF'!$Q$54:$AZ$54,SUM('DRE + DCF'!$BA$54,('DRE + DCF'!$BB$46*(1-((N$18-'Projeções - Receita'!$BA$58)/('DRE + DCF'!$BC$43-'Projeções - Receita'!$BA$58)))*(1+N$18))/($I11-N$18))))/((1+$I11)^((5-$F$9)*3/12)))+SUM($F$13:$F$14))/$F$11 -> 32.189473 | O11: =((SUM('DRE + DCF'!$P$54,NPV($I11,'DRE + DCF'!$Q$54:$AZ$54,SUM('DRE + DCF'!$BA$54,('DRE + DCF'!$BB$46*(1-((O$18-'Projeções - Receita'!$BA$58)/('DRE + DCF'!$BC$43-'Projeções - Receita'!$BA$58)))*(1+O$18))/($I11-O$18))))/((1+$I11)^((5-$F$9)*3/12)))+SUM($F$13:$F$14))/$F$11 -> 32.502992 | P11: =((SUM('DRE + DCF'!$P$54,NPV($I11,'DRE + DCF'!$Q$54:$AZ$54,SUM('DRE + DCF'!$BA$54,('DRE + DCF'!$BB$46*(1-((P$18-'Projeções - Receita'!$BA$58)/('DRE + DCF'!$BC$43-'Projeções - Receita'!$BA$58)))*(1+P$18))/($I11-P$18))))/((1+$I11)^((5-$F$9)*3/12)))+SUM($F$13:$F$14))/$F$11 -> 32.854011 | Q11: =((SUM('DRE + DCF'!$P$54,NPV($I11,'DRE + DCF'!$Q$54:$AZ$54,SUM('DRE + DCF'!$BA$54,('DRE + DCF'!$BB$46*(1-((Q$18-'Projeções - Receita'!$BA$58)/('DRE + DCF'!$BC$43-'Projeções - Receita'!$BA$58)))*(1+Q$18))/($I11-Q$18))))/((1+$I11)^((5-$F$9)*3/12)))+SUM($F$13:$F$14))/$F$11 -> 33.249951 | ... S11: =((SUM('DRE + DCF'!$P$54,NPV($I11,'DRE + DCF'!$Q$54:$AZ$54,SUM('DRE + DCF'!$BA$54,('DRE + DCF'!$BB$46*(1-((S$18-'Projeções - Receita'!$BA$58)/('DRE + DCF'!$BC$43-'Projeções - Receita'!$BA$58)))*(1+S$18))/($I11-S$18))))/((1+$I11)^((5-$F$9)*3/12)))+SUM($F$13:$F$14))/$F$11 -> 34.217549
A12: Balanço Patrimonial | E12: Valor da Empresa (mil) | F12: =SUM('DRE + DCF'!P56:BB56) -> 42241218 | I12: =I13-0.5% -> 0.13347175 | J12: =((SUM('DRE + DCF'!$P$54,NPV($I12,'DRE + DCF'!$Q$54:$AZ$54,SUM('DRE + DCF'!$BA$54,('DRE + DCF'!$BB$46*(1-((J$18-'Projeções - Receita'!$BA$58)/('DRE + DCF'!$BC$43-'Projeções - Receita'!$BA$58)))*(1+J$18))/($I12-J$18))))/((1+$I12)^((5-$F$9)*3/12)))+SUM($F$13:$F$14))/$F$11 -> 27.496603 | K12: =((SUM('DRE + DCF'!$P$54,NPV($I12,'DRE + DCF'!$Q$54:$AZ$54,SUM('DRE + DCF'!$BA$54,('DRE + DCF'!$BB$46*(1-((K$18-'Projeções - Receita'!$BA$58)/('DRE + DCF'!$BC$43-'Projeções - Receita'!$BA$58)))*(1+K$18))/($I12-K$18))))/((1+$I12)^((5-$F$9)*3/12)))+SUM($F$13:$F$14))/$F$11 -> 27.634439 | L12: =((SUM('DRE + DCF'!$P$54,NPV($I12,'DRE + DCF'!$Q$54:$AZ$54,SUM('DRE + DCF'!$BA$54,('DRE + DCF'!$BB$46*(1-((L$18-'Projeções - Receita'!$BA$58)/('DRE + DCF'!$BC$43-'Projeções - Receita'!$BA$58)))*(1+L$18))/($I12-L$18))))/((1+$I12)^((5-$F$9)*3/12)))+SUM($F$13:$F$14))/$F$11 -> 27.783915 | M12: =((SUM('DRE + DCF'!$P$54,NPV($I12,'DRE + DCF'!$Q$54:$AZ$54,SUM('DRE + DCF'!$BA$54,('DRE + DCF'!$BB$46*(1-((M$18-'Projeções - Receita'!$BA$58)/('DRE + DCF'!$BC$43-'Projeções - Receita'!$BA$58)))*(1+M$18))/($I12-M$18))))/((1+$I12)^((5-$F$9)*3/12)))+SUM($F$13:$F$14))/$F$11 -> 27.946682 | N12: =((SUM('DRE + DCF'!$P$54,NPV($I12,'DRE + DCF'!$Q$54:$AZ$54,SUM('DRE + DCF'!$BA$54,('DRE + DCF'!$BB$46*(1-((N$18-'Projeções - Receita'!$BA$58)/('DRE + DCF'!$BC$43-'Projeções - Receita'!$BA$58)))*(1+N$18))/($I12-N$18))))/((1+$I12)^((5-$F$9)*3/12)))+SUM($F$13:$F$14))/$F$11 -> 28.124717 | O12: =((SUM('DRE + DCF'!$P$54,NPV($I12,'DRE + DCF'!$Q$54:$AZ$54,SUM('DRE + DCF'!$BA$54,('DRE + DCF'!$BB$46*(1-((O$18-'Projeções - Receita'!$BA$58)/('DRE + DCF'!$BC$43-'Projeções - Receita'!$BA$58)))*(1+O$18))/($I12-O$18))))/((1+$I12)^((5-$F$9)*3/12)))+SUM($F$13:$F$14))/$F$11 -> 28.320411 | P12: =((SUM('DRE + DCF'!$P$54,NPV($I12,'DRE + DCF'!$Q$54:$AZ$54,SUM('DRE + DCF'!$BA$54,('DRE + DCF'!$BB$46*(1-((P$18-'Projeções - Receita'!$BA$58)/('DRE + DCF'!$BC$43-'Projeções - Receita'!$BA$58)))*(1+P$18))/($I12-P$18))))/((1+$I12)^((5-$F$9)*3/12)))+SUM($F$13:$F$14))/$F$11 -> 28.53668 | Q12: =((SUM('DRE + DCF'!$P$54,NPV($I12,'DRE + DCF'!$Q$54:$AZ$54,SUM('DRE + DCF'!$BA$54,('DRE + DCF'!$BB$46*(1-((Q$18-'Projeções - Receita'!$BA$58)/('DRE + DCF'!$BC$43-'Projeções - Receita'!$BA$58)))*(1+Q$18))/($I12-Q$18))))/((1+$I12)^((5-$F$9)*3/12)))+SUM($F$13:$F$14))/$F$11 -> 28.77712 | ... S12: =((SUM('DRE + DCF'!$P$54,NPV($I12,'DRE + DCF'!$Q$54:$AZ$54,SUM('DRE + DCF'!$BA$54,('DRE + DCF'!$BB$46*(1-((S$18-'Projeções - Receita'!$BA$58)/('DRE + DCF'!$BC$43-'Projeções - Receita'!$BA$58)))*(1+S$18))/($I12-S$18))))/((1+$I12)^((5-$F$9)*3/12)))+SUM($F$13:$F$14))/$F$11 -> 29.349648
A13: Painel de Índices | E13: Dívida (mil) | F13: =-WACC!F19 -> -6057912 | I13: =WACC!P20 -> 0.13847175 | J13: =((SUM('DRE + DCF'!$P$54,NPV($I13,'DRE + DCF'!$Q$54:$AZ$54,SUM('DRE + DCF'!$BA$54,('DRE + DCF'!$BB$46*(1-((J$18-'Projeções - Receita'!$BA$58)/('DRE + DCF'!$BC$43-'Projeções - Receita'!$BA$58)))*(1+J$18))/($I13-J$18))))/((1+$I13)^((5-$F$9)*3/12)))+SUM($F$13:$F$14))/$F$11 -> 24.432465 | K13: =((SUM('DRE + DCF'!$P$54,NPV($I13,'DRE + DCF'!$Q$54:$AZ$54,SUM('DRE + DCF'!$BA$54,('DRE + DCF'!$BB$46*(1-((K$18-'Projeções - Receita'!$BA$58)/('DRE + DCF'!$BC$43-'Projeções - Receita'!$BA$58)))*(1+K$18))/($I13-K$18))))/((1+$I13)^((5-$F$9)*3/12)))+SUM($F$13:$F$14))/$F$11 -> 24.522777 | L13: =((SUM('DRE + DCF'!$P$54,NPV($I13,'DRE + DCF'!$Q$54:$AZ$54,SUM('DRE + DCF'!$BA$54,('DRE + DCF'!$BB$46*(1-((L$18-'Projeções - Receita'!$BA$58)/('DRE + DCF'!$BC$43-'Projeções - Receita'!$BA$58)))*(1+L$18))/($I13-L$18))))/((1+$I13)^((5-$F$9)*3/12)))+SUM($F$13:$F$14))/$F$11 -> 24.619944 | M13: =((SUM('DRE + DCF'!$P$54,NPV($I13,'DRE + DCF'!$Q$54:$AZ$54,SUM('DRE + DCF'!$BA$54,('DRE + DCF'!$BB$46*(1-((M$18-'Projeções - Receita'!$BA$58)/('DRE + DCF'!$BC$43-'Projeções - Receita'!$BA$58)))*(1+M$18))/($I13-M$18))))/((1+$I13)^((5-$F$9)*3/12)))+SUM($F$13:$F$14))/$F$11 -> 24.724855 | N13: =((SUM('DRE + DCF'!$P$54,NPV($I13,'DRE + DCF'!$Q$54:$AZ$54,SUM('DRE + DCF'!$BA$54,('DRE + DCF'!$BB$46*(1-((N$18-'Projeções - Receita'!$BA$58)/('DRE + DCF'!$BC$43-'Projeções - Receita'!$BA$58)))*(1+N$18))/($I13-N$18))))/((1+$I13)^((5-$F$9)*3/12)))+SUM($F$13:$F$14))/$F$11 -> 24.838559 | O13: =((SUM('DRE + DCF'!$P$54,NPV($I13,'DRE + DCF'!$Q$54:$AZ$54,SUM('DRE + DCF'!$BA$54,('DRE + DCF'!$BB$46*(1-((O$18-'Projeções - Receita'!$BA$58)/('DRE + DCF'!$BC$43-'Projeções - Receita'!$BA$58)))*(1+O$18))/($I13-O$18))))/((1+$I13)^((5-$F$9)*3/12)))+SUM($F$13:$F$14))/$F$11 -> 24.962301 | P13: =((SUM('DRE + DCF'!$P$54,NPV($I13,'DRE + DCF'!$Q$54:$AZ$54,SUM('DRE + DCF'!$BA$54,('DRE + DCF'!$BB$46*(1-((P$18-'Projeções - Receita'!$BA$58)/('DRE + DCF'!$BC$43-'Projeções - Receita'!$BA$58)))*(1+P$18))/($I13-P$18))))/((1+$I13)^((5-$F$9)*3/12)))+SUM($F$13:$F$14))/$F$11 -> 25.097576 | Q13: =((SUM('DRE + DCF'!$P$54,NPV($I13,'DRE + DCF'!$Q$54:$AZ$54,SUM('DRE + DCF'!$BA$54,('DRE + DCF'!$BB$46*(1-((Q$18-'Projeções - Receita'!$BA$58)/('DRE + DCF'!$BC$43-'Projeções - Receita'!$BA$58)))*(1+Q$18))/($I13-Q$18))))/((1+$I13)^((5-$F$9)*3/12)))+SUM($F$13:$F$14))/$F$11 -> 25.246188 | ... S13: =((SUM('DRE + DCF'!$P$54,NPV($I13,'DRE + DCF'!$Q$54:$AZ$54,SUM('DRE + DCF'!$BA$54,('DRE + DCF'!$BB$46*(1-((S$18-'Projeções - Receita'!$BA$58)/('DRE + DCF'!$BC$43-'Projeções - Receita'!$BA$58)))*(1+S$18))/($I13-S$18))))/((1+$I13)^((5-$F$9)*3/12)))+SUM($F$13:$F$14))/$F$11 -> 25.592752
A14: Provisões e Processos | E14: Ativos Não-Operacionais | F14: ='Balanço Patrimonial'!O17+'Balanço Patrimonial'!O18 -> 100884.59 | I14: =I13+0.5% -> 0.14347175 | J14: =((SUM('DRE + DCF'!$P$54,NPV($I14,'DRE + DCF'!$Q$54:$AZ$54,SUM('DRE + DCF'!$BA$54,('DRE + DCF'!$BB$46*(1-((J$18-'Projeções - Receita'!$BA$58)/('DRE + DCF'!$BC$43-'Projeções - Receita'!$BA$58)))*(1+J$18))/($I14-J$18))))/((1+$I14)^((5-$F$9)*3/12)))+SUM($F$13:$F$14))/$F$11 -> 21.868792 | K14: =((SUM('DRE + DCF'!$P$54,NPV($I14,'DRE + DCF'!$Q$54:$AZ$54,SUM('DRE + DCF'!$BA$54,('DRE + DCF'!$BB$46*(1-((K$18-'Projeções - Receita'!$BA$58)/('DRE + DCF'!$BC$43-'Projeções - Receita'!$BA$58)))*(1+K$18))/($I14-K$18))))/((1+$I14)^((5-$F$9)*3/12)))+SUM($F$13:$F$14))/$F$11 -> 21.928163 | L14: =((SUM('DRE + DCF'!$P$54,NPV($I14,'DRE + DCF'!$Q$54:$AZ$54,SUM('DRE + DCF'!$BA$54,('DRE + DCF'!$BB$46*(1-((L$18-'Projeções - Receita'!$BA$58)/('DRE + DCF'!$BC$43-'Projeções - Receita'!$BA$58)))*(1+L$18))/($I14-L$18))))/((1+$I14)^((5-$F$9)*3/12)))+SUM($F$13:$F$14))/$F$11 -> 21.991588 | M14: =((SUM('DRE + DCF'!$P$54,NPV($I14,'DRE + DCF'!$Q$54:$AZ$54,SUM('DRE + DCF'!$BA$54,('DRE + DCF'!$BB$46*(1-((M$18-'Projeções - Receita'!$BA$58)/('DRE + DCF'!$BC$43-'Projeções - Receita'!$BA$58)))*(1+M$18))/($I14-M$18))))/((1+$I14)^((5-$F$9)*3/12)))+SUM($F$13:$F$14))/$F$11 -> 22.059552 | N14: =((SUM('DRE + DCF'!$P$54,NPV($I14,'DRE + DCF'!$Q$54:$AZ$54,SUM('DRE + DCF'!$BA$54,('DRE + DCF'!$BB$46*(1-((N$18-'Projeções - Receita'!$BA$58)/('DRE + DCF'!$BC$43-'Projeções - Receita'!$BA$58)))*(1+N$18))/($I14-N$18))))/((1+$I14)^((5-$F$9)*3/12)))+SUM($F$13:$F$14))/$F$11 -> 22.132616 | O14: =((SUM('DRE + DCF'!$P$54,NPV($I14,'DRE + DCF'!$Q$54:$AZ$54,SUM('DRE + DCF'!$BA$54,('DRE + DCF'!$BB$46*(1-((O$18-'Projeções - Receita'!$BA$58)/('DRE + DCF'!$BC$43-'Projeções - Receita'!$BA$58)))*(1+O$18))/($I14-O$18))))/((1+$I14)^((5-$F$9)*3/12)))+SUM($F$13:$F$14))/$F$11 -> 22.211443 | P14: =((SUM('DRE + DCF'!$P$54,NPV($I14,'DRE + DCF'!$Q$54:$AZ$54,SUM('DRE + DCF'!$BA$54,('DRE + DCF'!$BB$46*(1-((P$18-'Projeções - Receita'!$BA$58)/('DRE + DCF'!$BC$43-'Projeções - Receita'!$BA$58)))*(1+P$18))/($I14-P$18))))/((1+$I14)^((5-$F$9)*3/12)))+SUM($F$13:$F$14))/$F$11 -> 22.296811 | Q14: =((SUM('DRE + DCF'!$P$54,NPV($I14,'DRE + DCF'!$Q$54:$AZ$54,SUM('DRE + DCF'!$BA$54,('DRE + DCF'!$BB$46*(1-((Q$18-'Projeções - Receita'!$BA$58)/('DRE + DCF'!$BC$43-'Projeções - Receita'!$BA$58)))*(1+Q$18))/($I14-Q$18))))/((1+$I14)^((5-$F$9)*3/12)))+SUM($F$13:$F$14))/$F$11 -> 22.389649 | ... S14: =((SUM('DRE + DCF'!$P$54,NPV($I14,'DRE + DCF'!$Q$54:$AZ$54,SUM('DRE + DCF'!$BA$54,('DRE + DCF'!$BB$46*(1-((S$18-'Projeções - Receita'!$BA$58)/('DRE + DCF'!$BC$43-'Projeções - Receita'!$BA$58)))*(1+S$18))/($I14-S$18))))/((1+$I14)^((5-$F$9)*3/12)))+SUM($F$13:$F$14))/$F$11 -> 22.602409
A15: Projeções - Receita | E15: Valor da Ação | F15: =SUM(F12:F14)/F11 -> 22.020481 | I15: =I14+0.5% -> 0.14847175 | J15: =((SUM('DRE + DCF'!$P$54,NPV($I15,'DRE + DCF'!$Q$54:$AZ$54,SUM('DRE + DCF'!$BA$54,('DRE + DCF'!$BB$46*(1-((J$18-'Projeções - Receita'!$BA$58)/('DRE + DCF'!$BC$43-'Projeções - Receita'!$BA$58)))*(1+J$18))/($I15-J$18))))/((1+$I15)^((5-$F$9)*3/12)))+SUM($F$13:$F$14))/$F$11 -> 19.698331 | K15: =((SUM('DRE + DCF'!$P$54,NPV($I15,'DRE + DCF'!$Q$54:$AZ$54,SUM('DRE + DCF'!$BA$54,('DRE + DCF'!$BB$46*(1-((K$18-'Projeções - Receita'!$BA$58)/('DRE + DCF'!$BC$43-'Projeções - Receita'!$BA$58)))*(1+K$18))/($I15-K$18))))/((1+$I15)^((5-$F$9)*3/12)))+SUM($F$13:$F$14))/$F$11 -> 19.73734 | L15: =((SUM('DRE + DCF'!$P$54,NPV($I15,'DRE + DCF'!$Q$54:$AZ$54,SUM('DRE + DCF'!$BA$54,('DRE + DCF'!$BB$46*(1-((L$18-'Projeções - Receita'!$BA$58)/('DRE + DCF'!$BC$43-'Projeções - Receita'!$BA$58)))*(1+L$18))/($I15-L$18))))/((1+$I15)^((5-$F$9)*3/12)))+SUM($F$13:$F$14))/$F$11 -> 19.778738 | M15: =((SUM('DRE + DCF'!$P$54,NPV($I15,'DRE + DCF'!$Q$54:$AZ$54,SUM('DRE + DCF'!$BA$54,('DRE + DCF'!$BB$46*(1-((M$18-'Projeções - Receita'!$BA$58)/('DRE + DCF'!$BC$43-'Projeções - Receita'!$BA$58)))*(1+M$18))/($I15-M$18))))/((1+$I15)^((5-$F$9)*3/12)))+SUM($F$13:$F$14))/$F$11 -> 19.822789 | N15: =((SUM('DRE + DCF'!$P$54,NPV($I15,'DRE + DCF'!$Q$54:$AZ$54,SUM('DRE + DCF'!$BA$54,('DRE + DCF'!$BB$46*(1-((N$18-'Projeções - Receita'!$BA$58)/('DRE + DCF'!$BC$43-'Projeções - Receita'!$BA$58)))*(1+N$18))/($I15-N$18))))/((1+$I15)^((5-$F$9)*3/12)))+SUM($F$13:$F$14))/$F$11 -> 19.869797 | O15: =((SUM('DRE + DCF'!$P$54,NPV($I15,'DRE + DCF'!$Q$54:$AZ$54,SUM('DRE + DCF'!$BA$54,('DRE + DCF'!$BB$46*(1-((O$18-'Projeções - Receita'!$BA$58)/('DRE + DCF'!$BC$43-'Projeções - Receita'!$BA$58)))*(1+O$18))/($I15-O$18))))/((1+$I15)^((5-$F$9)*3/12)))+SUM($F$13:$F$14))/$F$11 -> 19.920115 | P15: =((SUM('DRE + DCF'!$P$54,NPV($I15,'DRE + DCF'!$Q$54:$AZ$54,SUM('DRE + DCF'!$BA$54,('DRE + DCF'!$BB$46*(1-((P$18-'Projeções - Receita'!$BA$58)/('DRE + DCF'!$BC$43-'Projeções - Receita'!$BA$58)))*(1+P$18))/($I15-P$18))))/((1+$I15)^((5-$F$9)*3/12)))+SUM($F$13:$F$14))/$F$11 -> 19.974153 | Q15: =((SUM('DRE + DCF'!$P$54,NPV($I15,'DRE + DCF'!$Q$54:$AZ$54,SUM('DRE + DCF'!$BA$54,('DRE + DCF'!$BB$46*(1-((Q$18-'Projeções - Receita'!$BA$58)/('DRE + DCF'!$BC$43-'Projeções - Receita'!$BA$58)))*(1+Q$18))/($I15-Q$18))))/((1+$I15)^((5-$F$9)*3/12)))+SUM($F$13:$F$14))/$F$11 -> 20.032395 | ... S15: =((SUM('DRE + DCF'!$P$54,NPV($I15,'DRE + DCF'!$Q$54:$AZ$54,SUM('DRE + DCF'!$BA$54,('DRE + DCF'!$BB$46*(1-((S$18-'Projeções - Receita'!$BA$58)/('DRE + DCF'!$BC$43-'Projeções - Receita'!$BA$58)))*(1+S$18))/($I15-S$18))))/((1+$I15)^((5-$F$9)*3/12)))+SUM($F$13:$F$14))/$F$11 -> 20.163869
A16: Projeções - Capex | E16: Cotação | F16: 25.35 | I16: =I15+0.5% -> 0.15347175 | J16: =((SUM('DRE + DCF'!$P$54,NPV($I16,'DRE + DCF'!$Q$54:$AZ$54,SUM('DRE + DCF'!$BA$54,('DRE + DCF'!$BB$46*(1-((J$18-'Projeções - Receita'!$BA$58)/('DRE + DCF'!$BC$43-'Projeções - Receita'!$BA$58)))*(1+J$18))/($I16-J$18))))/((1+$I16)^((5-$F$9)*3/12)))+SUM($F$13:$F$14))/$F$11 -> 17.841514 | K16: =((SUM('DRE + DCF'!$P$54,NPV($I16,'DRE + DCF'!$Q$54:$AZ$54,SUM('DRE + DCF'!$BA$54,('DRE + DCF'!$BB$46*(1-((K$18-'Projeções - Receita'!$BA$58)/('DRE + DCF'!$BC$43-'Projeções - Receita'!$BA$58)))*(1+K$18))/($I16-K$18))))/((1+$I16)^((5-$F$9)*3/12)))+SUM($F$13:$F$14))/$F$11 -> 17.867017 | L16: =((SUM('DRE + DCF'!$P$54,NPV($I16,'DRE + DCF'!$Q$54:$AZ$54,SUM('DRE + DCF'!$BA$54,('DRE + DCF'!$BB$46*(1-((L$18-'Projeções - Receita'!$BA$58)/('DRE + DCF'!$BC$43-'Projeções - Receita'!$BA$58)))*(1+L$18))/($I16-L$18))))/((1+$I16)^((5-$F$9)*3/12)))+SUM($F$13:$F$14))/$F$11 -> 17.893908 | M16: =((SUM('DRE + DCF'!$P$54,NPV($I16,'DRE + DCF'!$Q$54:$AZ$54,SUM('DRE + DCF'!$BA$54,('DRE + DCF'!$BB$46*(1-((M$18-'Projeções - Receita'!$BA$58)/('DRE + DCF'!$BC$43-'Projeções - Receita'!$BA$58)))*(1+M$18))/($I16-M$18))))/((1+$I16)^((5-$F$9)*3/12)))+SUM($F$13:$F$14))/$F$11 -> 17.922331 | N16: =((SUM('DRE + DCF'!$P$54,NPV($I16,'DRE + DCF'!$Q$54:$AZ$54,SUM('DRE + DCF'!$BA$54,('DRE + DCF'!$BB$46*(1-((N$18-'Projeções - Receita'!$BA$58)/('DRE + DCF'!$BC$43-'Projeções - Receita'!$BA$58)))*(1+N$18))/($I16-N$18))))/((1+$I16)^((5-$F$9)*3/12)))+SUM($F$13:$F$14))/$F$11 -> 17.95245 | O16: =((SUM('DRE + DCF'!$P$54,NPV($I16,'DRE + DCF'!$Q$54:$AZ$54,SUM('DRE + DCF'!$BA$54,('DRE + DCF'!$BB$46*(1-((O$18-'Projeções - Receita'!$BA$58)/('DRE + DCF'!$BC$43-'Projeções - Receita'!$BA$58)))*(1+O$18))/($I16-O$18))))/((1+$I16)^((5-$F$9)*3/12)))+SUM($F$13:$F$14))/$F$11 -> 17.984452 | P16: =((SUM('DRE + DCF'!$P$54,NPV($I16,'DRE + DCF'!$Q$54:$AZ$54,SUM('DRE + DCF'!$BA$54,('DRE + DCF'!$BB$46*(1-((P$18-'Projeções - Receita'!$BA$58)/('DRE + DCF'!$BC$43-'Projeções - Receita'!$BA$58)))*(1+P$18))/($I16-P$18))))/((1+$I16)^((5-$F$9)*3/12)))+SUM($F$13:$F$14))/$F$11 -> 18.018552 | Q16: =((SUM('DRE + DCF'!$P$54,NPV($I16,'DRE + DCF'!$Q$54:$AZ$54,SUM('DRE + DCF'!$BA$54,('DRE + DCF'!$BB$46*(1-((Q$18-'Projeções - Receita'!$BA$58)/('DRE + DCF'!$BC$43-'Projeções - Receita'!$BA$58)))*(1+Q$18))/($I16-Q$18))))/((1+$I16)^((5-$F$9)*3/12)))+SUM($F$13:$F$14))/$F$11 -> 18.055001 | ... S16: =((SUM('DRE + DCF'!$P$54,NPV($I16,'DRE + DCF'!$Q$54:$AZ$54,SUM('DRE + DCF'!$BA$54,('DRE + DCF'!$BB$46*(1-((S$18-'Projeções - Receita'!$BA$58)/('DRE + DCF'!$BC$43-'Projeções - Receita'!$BA$58)))*(1+S$18))/($I16-S$18))))/((1+$I16)^((5-$F$9)*3/12)))+SUM($F$13:$F$14))/$F$11 -> 18.136162
A17: Projeções 2022 | E17: =IF(F17=0,"",IF(F17>0,"Upside","Downside")) -> Downside | F17: =F15/F16-1 -> -0.13134198 | I17: =I16+0.5% -> 0.15847175 | J17: =((SUM('DRE + DCF'!$P$54,NPV($I17,'DRE + DCF'!$Q$54:$AZ$54,SUM('DRE + DCF'!$BA$54,('DRE + DCF'!$BB$46*(1-((J$18-'Projeções - Receita'!$BA$58)/('DRE + DCF'!$BC$43-'Projeções - Receita'!$BA$58)))*(1+J$18))/($I17-J$18))))/((1+$I17)^((5-$F$9)*3/12)))+SUM($F$13:$F$14))/$F$11 -> 16.238212 | K17: =((SUM('DRE + DCF'!$P$54,NPV($I17,'DRE + DCF'!$Q$54:$AZ$54,SUM('DRE + DCF'!$BA$54,('DRE + DCF'!$BB$46*(1-((K$18-'Projeções - Receita'!$BA$58)/('DRE + DCF'!$BC$43-'Projeções - Receita'!$BA$58)))*(1+K$18))/($I17-K$18))))/((1+$I17)^((5-$F$9)*3/12)))+SUM($F$13:$F$14))/$F$11 -> 16.254709 | L17: =((SUM('DRE + DCF'!$P$54,NPV($I17,'DRE + DCF'!$Q$54:$AZ$54,SUM('DRE + DCF'!$BA$54,('DRE + DCF'!$BB$46*(1-((L$18-'Projeções - Receita'!$BA$58)/('DRE + DCF'!$BC$43-'Projeções - Receita'!$BA$58)))*(1+L$18))/($I17-L$18))))/((1+$I17)^((5-$F$9)*3/12)))+SUM($F$13:$F$14))/$F$11 -> 16.271992 | M17: =((SUM('DRE + DCF'!$P$54,NPV($I17,'DRE + DCF'!$Q$54:$AZ$54,SUM('DRE + DCF'!$BA$54,('DRE + DCF'!$BB$46*(1-((M$18-'Projeções - Receita'!$BA$58)/('DRE + DCF'!$BC$43-'Projeções - Receita'!$BA$58)))*(1+M$18))/($I17-M$18))))/((1+$I17)^((5-$F$9)*3/12)))+SUM($F$13:$F$14))/$F$11 -> 16.290136 | N17: =((SUM('DRE + DCF'!$P$54,NPV($I17,'DRE + DCF'!$Q$54:$AZ$54,SUM('DRE + DCF'!$BA$54,('DRE + DCF'!$BB$46*(1-((N$18-'Projeções - Receita'!$BA$58)/('DRE + DCF'!$BC$43-'Projeções - Receita'!$BA$58)))*(1+N$18))/($I17-N$18))))/((1+$I17)^((5-$F$9)*3/12)))+SUM($F$13:$F$14))/$F$11 -> 16.309228 | O17: =((SUM('DRE + DCF'!$P$54,NPV($I17,'DRE + DCF'!$Q$54:$AZ$54,SUM('DRE + DCF'!$BA$54,('DRE + DCF'!$BB$46*(1-((O$18-'Projeções - Receita'!$BA$58)/('DRE + DCF'!$BC$43-'Projeções - Receita'!$BA$58)))*(1+O$18))/($I17-O$18))))/((1+$I17)^((5-$F$9)*3/12)))+SUM($F$13:$F$14))/$F$11 -> 16.329364 | P17: =((SUM('DRE + DCF'!$P$54,NPV($I17,'DRE + DCF'!$Q$54:$AZ$54,SUM('DRE + DCF'!$BA$54,('DRE + DCF'!$BB$46*(1-((P$18-'Projeções - Receita'!$BA$58)/('DRE + DCF'!$BC$43-'Projeções - Receita'!$BA$58)))*(1+P$18))/($I17-P$18))))/((1+$I17)^((5-$F$9)*3/12)))+SUM($F$13:$F$14))/$F$11 -> 16.350655 | Q17: =((SUM('DRE + DCF'!$P$54,NPV($I17,'DRE + DCF'!$Q$54:$AZ$54,SUM('DRE + DCF'!$BA$54,('DRE + DCF'!$BB$46*(1-((Q$18-'Projeções - Receita'!$BA$58)/('DRE + DCF'!$BC$43-'Projeções - Receita'!$BA$58)))*(1+Q$18))/($I17-Q$18))))/((1+$I17)^((5-$F$9)*3/12)))+SUM($F$13:$F$14))/$F$11 -> 16.37323 | ... S17: =((SUM('DRE + DCF'!$P$54,NPV($I17,'DRE + DCF'!$Q$54:$AZ$54,SUM('DRE + DCF'!$BA$54,('DRE + DCF'!$BB$46*(1-((S$18-'Projeções - Receita'!$BA$58)/('DRE + DCF'!$BC$43-'Projeções - Receita'!$BA$58)))*(1+S$18))/($I17-S$18))))/((1+$I17)^((5-$F$9)*3/12)))+SUM($F$13:$F$14))/$F$11 -> 16.422843
E18: TIR | F18: 0.1383656 | J18: =K18-0.25% -> 0.0730656 | K18: =L18-0.25% -> 0.0755656 | L18: =M18-0.25% -> 0.0780656 | M18: =N18-0.25% -> 0.0805656 | N18: =O18-0.25% -> 0.0830656 | O18: ='DRE + DCF'!BD43 -> 0.0855656 | P18: =O18+0.25% -> 0.0880656 | Q18: =P18+0.25% -> 0.0905656 | R18: =Q18+0.25% -> 0.0930656 | S18: =R18+0.25% -> 0.0955656
J19: Growth
F22: =VLOOKUP(MIN(#REF!),#REF!,2,FALSE) -> #REF!

Sheet WACC
S3: =Dashboard!$I$3 -> Raia Drogasil ($RADL3)
A7: Páginas
A8: Dashboard
A9: WACC | E9: Atualizado em: 10/04/2023 | F9: 2023 | G9: =F9+1 -> 2024 | H9: =G9+1 -> 2025 | I9: =H9+1 -> 2026 | J9: =I9+1 -> 2027 | K9: =J9+1 -> 2028 | L9: =K9+1 -> 2029 | M9: =L9+1 -> 2030 | N9: =M9+1 -> 2031 | ... AQ9: =AP9+1 -> 2060 | AR9: Descrição
A10: DRE + DCF | E10: DI | F10: 0.1367155 | G10: 0.1296456 | H10: 0.1183783 | I10: 0.1169052 | J10: 0.1166546 | K10: 0.1170971 | L10: 0.117698 | M10: 0.1183976 | N10: 0.1184996 | O10: 0.1185 | P10: 0.1185 | Q10: =P10 -> 0.1185 | R10: =Q10 -> 0.1185 | S10: =R10 -> 0.1185 | T10: =S10 -> 0.1185 | U10: =T10 -> 0.1185 | V10: =U10 -> 0.1185 | W10: =V10 -> 0.1185 | X10: =W10 -> 0.1185 | ... AQ10: =AP10 -> 0.1185 | AR10: A taxa livre de risco no Brasil pode partir do DI, que é equivalente ao prêmio de um titulo IPCA+ do governo de mesmo prazo somado à inflação implicita.
A11: DRE - Contas Abertas | E11: CDS | F11: 0.008755413 | G11: 0.009904279 | H11: 0.01464963 | I11: 0.01941573 | J11: 0.024180477 | K11: 0.028611426 | L11: 0.031305624 | M11: 0.032702755 | N11: 0.033554629 | O11: 0.034613059 | P11: 0.036629856 | Q11: =P11 -> 0.036629856 | R11: =Q11 -> 0.036629856 | S11: =R11 -> 0.036629856 | T11: =S11 -> 0.036629856 | U11: =T11 -> 0.036629856 | V11: =U11 -> 0.036629856 | W11: =V11 -> 0.036629856 | X11: =W11 -> 0.036629856 | ... AQ11: =AP11 -> 0.036629856 | AR11: Credit Default Swap (CDS) - Fonte: investing.com
A12: Balanço Patrimonial | E12: Inflação Implícita | F12: 0.06688 | G12: 0.05303 | H12: 0.06963 | I12: 0.06656 | J12: 0.07113 | K12: 0.06915 | L12: 0.07392 | M12: 0.07356 | N12: 0.06627 | O12: 0.06154 | P12: 0.06428 | Q12: =P12 -> 0.06428 | R12: =Q12 -> 0.06428 | S12: =R12 -> 0.06428 | T12: =S12 -> 0.06428 | U12: =T12 -> 0.06428 | V12: =U12 -> 0.06428 | W12: =V12 -> 0.06428 | X12: =W12 -> 0.06428 | ... AQ12: =AP12 -> 0.06428
A13: Painel de Índices | E13: Taxa Livre de Risco | F13: =F10-F11 -> 0.12796009 | G13: =G10-G11 -> 0.11974132 | H13: =H10-H11 -> 0.10372867 | I13: =I10-I11 -> 0.09748947 | J13: =J10-J11 -> 0.092474123 | K13: =K10-K11 -> 0.088485674 | L13: =L10-L11 -> 0.086392376 | M13: =M10-M11 -> 0.085694845 | ... AQ13: =AQ10-AQ11 -> 0.081870144
A14: Provisões e Processos | E14: Bottom-up Beta | F14: 0.88382 | G14: =F14 -> 0.88382 | H14: =G14 -> 0.88382 | I14: =H14 -> 0.88382 | J14: =I14 -> 0.88382 | K14: =J14 -> 0.88382 | L14: =K14 -> 0.88382 | M14: =L14 -> 0.88382 | N14: =M14 -> 0.88382 | ... AQ14: =AP14 -> 0.88382 | AR14: Bottom-Up Beta levando em consideração o beta de empresas do mesmo setor e a alavancagem da empresa.
A15: Projeções - Receita | E15: Prêmio de Risco | F15: 0.065 | G15: 0.065 | H15: 0.065 | I15: 0.065 | J15: 0.065 | K15: 0.065 | L15: 0.065 | M15: 0.065 | N15: 0.065 | O15: 0.065 | P15: 0.065 | Q15: 0.065 | R15: 0.065 | S15: 0.065 | T15: 0.065 | U15: 0.065 | V15: 0.065 | W15: 0.065 | X15: 0.065 | Y15: 0.065 | Z15: 0.065 | AA15: 0.065 | AB15: 0.065 | AC15: 0.065 | AD15: 0.065 | AE15: 0.065 | AF15: 0.065 | AG15: 0.065 | AH15: 0.065 | AI15: 0.065 | AJ15: 0.065 | AK15: 0.065 | AL15: 0.065 | AM15: 0.065 | AN15: 0.065 | AO15: 0.065 | AP15: 0.065 | AQ15: 0.065 | AR15: Dados Alternativos FGV: https://goo.gl/bBfwGq
A16: Projeções - Capex | E16: Custo de Capital Próprio (Ke) | F16: =F13+(F14*F15) -> 0.18540839 | G16: =G13+(G14*G15) -> 0.17718962 | H16: =H13+(H14*H15) -> 0.16117697 | I16: =I13+(I14*I15) -> 0.15493777 | J16: =J13+(J14*J15) -> 0.14992242 | K16: =K13+(K14*K15) -> 0.14593397 | L16: =L13+(L14*L15) -> 0.14384068 | M16: =M13+(M14*M15) -> 0.14314315 | ... AQ16: =AQ13+(AQ14*AQ15) -> 0.13931844
A17: Projeções 2022 | E17: Valor do Equity (R$ Mil) | F17: 36287500 | G17: 36287500 | H17: 36287500 | I17: 36287500 | J17: 36287500 | K17: 36287500 | L17: 36287500 | M17: 36287500 | N17: 36287500 | O17: 36287500 | P17: 36287500 | Q17: 36287500 | R17: 36287500 | S17: 36287500 | T17: 36287500 | U17: 36287500 | V17: 36287500 | W17: 36287500 | X17: 36287500 | Y17: 36287500 | Z17: 36287500 | AA17: 36287500 | AB17: 36287500 | AC17: 36287500 | AD17: 36287500 | AE17: 36287500 | AF17: 36287500 | AG17: 36287500 | AH17: 36287500 | AI17: 36287500 | AJ17: 36287500 | AK17: 36287500 | AL17: 36287500 | AM17: 36287500 | AN17: 36287500 | AO17: 36287500 | AP17: 36287500 | AQ17: 36287500 | AR17: Valor Justo do Equity
E18: Custo de Capital de Terceiros (Kd) | F18: =F10+1.49% -> 0.1516155 | G18: =G10+1.49% -> 0.1445456 | H18: =H10+1.49% -> 0.1332783 | I18: =I10+1.49% -> 0.1318052 | J18: =J10+1.49% -> 0.1315546 | K18: =K10+1.49% -> 0.1319971 | L18: =L10+1.49% -> 0.132598 | M18: =M10+1.49% -> 0.1332976 | ... AQ18: =AQ10+1.49% -> 0.1334 | AR18: Custo da Dívida baseado na debênture de prazo mais longo emitida nos últimos doze meses (DI + 1,49%)
E19: Dívida Bruta (R$ Mil) | F19: =('Balanço Patrimonial'!$O$43+'Balanço Patrimonial'!$O$47+'Balanço Patrimonial'!$O$49+'Balanço Patrimonial'!$O$55) -> 6057912 | G19: =F19 -> 6057912 | H19: =G19 -> 6057912 | I19: =H19 -> 6057912 | J19: =I19 -> 6057912 | K19: =J19 -> 6057912 | L19: =K19 -> 6057912 | M19: =L19 -> 6057912 | N19: =M19 -> 6057912 | ... AQ19: =AP19 -> 6057912 | AR19: Valor contábil dos empréstimos, financiamentos e passivo de arrendamento no último balanço patrimonial divulgado.
E20: WACC | F20: =((F16*F17)+(F18*F19))/(F17+F19) -> 0.18057399 | G20: =((G16*G17)+(G18*G19))/(G17+G19) -> 0.17251958 | H20: =((H16*H17)+(H18*H19))/(H17+H19) -> 0.1571858 | I20: =((I16*I17)+(I18*I19))/(I17+I19) -> 0.15162844 | J20: =((J16*J17)+(J18*J19))/(J17+J19) -> 0.14729473 | K20: =((K16*K17)+(K18*K19))/(K17+K19) -> 0.14394017 | L20: =((L16*L17)+(L18*L19))/(L17+L19) -> 0.1422323 | M20: =((M16*M17)+(M18*M19))/(M17+M19) -> 0.14173465 | ... AQ20: =((AQ16*AQ17)+(AQ18*AQ19))/(AQ17+AQ19) -> 0.13847175
E21: Desconto | F21: =(1+F20)^((5-Dashboard!$F$9)*3/12) -> 1.180574 | G21: =F21*(1+G20) -> 1.3842461 | H21: =G21*(1+H20) -> 1.60183 | I21: =H21*(1+I20) -> 1.8447129 | J21: =I21*(1+J20) -> 2.1164294 | K21: =J21*(1+K20) -> 2.4210687 | L21: =K21*(1+L20) -> 2.7654228 | M21: =L21*(1+M20) -> 3.1573791 | N21: =M21*(1+N20) -> 3.6029062 | ... AQ21: =AP21*(1+AQ20) -> 155.11625

Sheet DRE + DCF
J2: Raia Drogasil ($RADL3)
A7: Páginas
A8: Dashboard
A9: WACC | E9: Data do Último Resultado: | F9: 2013 | G9: =F9+1 -> 2014 | H9: =G9+1 -> 2015 | I9: =H9+1 -> 2016 | J9: =I9+1 -> 2017 | K9: =J9+1 -> 2018 | L9: =K9+1 -> 2019 | M9: =L9+1 -> 2020 | N9: 2021 | O9: 2022 | P9: 2023 | Q9: 2024 | R9: 2025 | S9: 2026 | T9: 2027 | U9: 2028 | V9: 2029 | W9: 2030 | X9: 2031 | Y9: =X9+1 -> 2032 | Z9: =Y9+1 -> 2033 | AA9: =Z9+1 -> 2034 | AB9: =AA9+1 -> 2035 | AC9: =AB9+1 -> 2036 | AD9: =AC9+1 -> 2037 | AE9: =AD9+1 -> 2038 | AF9: =AE9+1 -> 2039 | ... BA9: =AZ9+1 -> 2060
A10: DRE + DCF | E10: Receita Bruta | F10: 6464103 | G10: 7658890 | H10: 9295978 | I10: 11827566 | J10: 13852469 | K10: 15519133 | L10: 18468183 | M10: 21180476 | N10: 25605684 | O10: 30950564
A11: DRE - Contas Abertas | E11: Impostos Incidentes sobre vendas | F11: -197812 | G11: -221733 | H11: -278605 | I11: -425384 | J11: -500288 | K11: -585676 | L11: -747690 | M11: -940608 | N11: -1218499 | O11: -1373403
A12: Balanço Patrimonial | E12: (%) da Receita Bruta | F12: =F11/F10 -> -0.030601616 | G12: =G11/G10 -> -0.028951062 | H12: =H11/H10 -> -0.029970488 | I12: =I11/I10 -> -0.035965473 | J12: =J11/J10 -> -0.036115439 | K12: =K11/K10 -> -0.037738964 | L12: =L11/L10 -> -0.040485304 | M12: =M11/M10 -> -0.0444092 | ... O12: =O11/O10 -> -0.044374086
A13: Painel de Índices | E13: Devoluções, Abatimentos e Outros | F13: -33372 | G13: -45588 | H13: -119524 | I13: -145617 | J13: -139676 | K13: -132012 | L13: -154893 | M13: -173028 | N13: -260183 | O13: -509781
A14: Provisões e Processos | E14: (%) da Receita Bruta | F14: =F13/F10 -> -0.0051626653 | G14: =G13/G10 -> -0.0059522986 | H14: =H13/H10 -> -0.012857604 | I14: =I13/I10 -> -0.012311662 | J14: =J13/J10 -> -0.010083112 | K14: =K13/K10 -> -0.008506403 | L14: =L13/L10 -> -0.0083870189 | M14: =M13/M10 -> -0.0081692215 | ... O14: =O13/O10 -> -0.016470815
A15: Projeções - Receita | E15: Receita Líquida | F15: 6232919 | G15: 7391569 | H15: 8897849 | I15: 11256565 | J15: 13212505 | K15: 14801445 | L15: 17565600 | M15: 20066840 | N15: 24127002 | O15: 29067380 | P15: ='Projeções - Receita'!P22 -> 33449541 | Q15: ='Projeções - Receita'!Q22 -> 37882634 | R15: ='Projeções - Receita'!R22 -> 43302702 | S15: ='Projeções - Receita'!S22 -> 49095679 | T15: ='Projeções - Receita'!T22 -> 55616250 | U15: ='Projeções - Receita'!U22 -> 62622077 | V15: ='Projeções - Receita'!V22 -> 70543239 | W15: ='Projeções - Receita'!W22 -> 79175286 | ... BA15: ='Projeções - Receita'!BA22 -> 1.1232524e+09
A16: Projeções - Capex | E16: Crescimento da Receita (YoY)¹ | G16: =G15/F15-1 -> 0.18589204 | H16: =H15/G15-1 -> 0.20378353 | I16: =I15/H15-1 -> 0.26508834 | J16: =J15/I15-1 -> 0.17375993 | K16: =K15/J15-1 -> 0.12026031 | L16: =L15/K15-1 -> 0.186749 | M16: =M15/L15-1 -> 0.14239423 | N16: =N15/M15-1 -> 0.20233191 | ... BA16: =BA15/AZ15-1 -> 0.085499962
A17: Projeções 2022 | E17: Custos das Vendas e Serviços | F17: -4512743 | G17: -5281377 | H17: -6183289 | I17: -7752422 | J17: -9224505 | K17: -10355923 | L17: -12367239 | M17: -14175708 | N17: -16920834 | O17: -20257912
E18: Lucro Bruto | F18: =F15+F17 -> 1720176 | G18: =G15+G17 -> 2110192 | H18: =H15+H17 -> 2714560 | I18: =I15+I17 -> 3504143 | J18: =J15+J17 -> 3988000 | K18: =K15+K17 -> 4445522 | L18: =L15+L17 -> 5198361 | M18: =M15+M17 -> 5891132 | N18: =N15+N17 -> 7206168 | O18: 8809468
E19: Margem Bruta | F19: =F18/F15 -> 0.27598241 | G19: =G18/G15 -> 0.28548634 | H19: =H18/H15 -> 0.30508048 | I19: =I18/I15 -> 0.31129772 | J19: =J18/J15 -> 0.30183527 | K19: =K18/K15 -> 0.30034378 | L19: =L18/L15 -> 0.29593985 | M19: =M18/M15 -> 0.29357547 | ... O19: =O18/O15 -> 0.30307059
E20: Despesas/ Receitas Operacionais | F20: =F21+F23+F25 -> -1570342 | G20: =G21+G23+G25 -> -1801066 | H20: =H21+H23+H25 -> -2213697 | I20: =I21+I23+I25 -> -2798605 | J20: =J21+J23+J25 -> -3195416 | K20: =K21+K23+K25 -> -3724012 | L20: =L21+L23+L25 -> -4079892 | M20: =M21+M23+M25 -> -4967281 | ... O20: =O21+O23+O25 -> -6969323
E21: Despesas com Vendas | F21: -1188077 | G21: -1409067 | H21: -1742093 | I21: -2218765 | J21: -2825959 | K21: -3261896 | L21: -3754770 | M21: -4256422 | N21: -4966819 | O21: -5805992
E22: (%) da Receita Líquida | F22: =F21/F15 -> -0.19061326 | G22: =G21/G15 -> -0.19063165 | H22: =H21/H15 -> -0.19578811 | I22: =I21/I15 -> -0.19710853 | J22: =J21/J15 -> -0.21388518 | K22: =K21/K15 -> -0.22037686 | L22: =L21/L15 -> -0.213757 | M22: =M21/M15 -> -0.21211222 | ... O22: =O21/O15 -> -0.19974253
E23: Despesas Gerais e Administrativas | F23: -335199 | G23: -382526 | H23: -462786 | I23: -572163 | J23: -369669 | K23: -402568 | L23: -533393 | M23: -679320 | N23: -912404 | O23: -1249847
E24: (%) da Receita Líquida | F24: =F23/F15 -> -0.053778815 | G24: =G23/G15 -> -0.051751665 | H24: =H23/H15 -> -0.052010997 | I24: =I23/I15 -> -0.050829272 | J24: =J23/J15 -> -0.027978722 | K24: =K23/K15 -> -0.027197885 | L24: =L23/L15 -> -0.030365772 | M24: =M23/M15 -> -0.033852864 | ... O24: =O23/O15 -> -0.042998268
E25: Resultado Operacional Outros | F25: -47066 | G25: -9473 | H25: -8818 | I25: -7677 | J25: 212 | K25: -59548 | L25: =355263-146992 -> 208271 | M25: =37911-69450 -> -31539 | N25: =78083-37429 -> 40654 | O25: =50097+36419 -> 86516
E26: (%) da Receita Líquida | F26: =F25/F15 -> -0.0075511971 | G26: =G25/G15 -> -0.0012815953 | H26: =H25/H15 -> -0.00099102603 | I26: =I25/I15 -> -0.00068200201 | J26: =J25/J15 -> 1.6045405e-05 | K26: =K25/K15 -> -0.0040231207 | L26: =L25/L15 -> 0.011856754 | M26: =M25/M15 -> -0.0015716974 | ... O26: =O25/O15 -> 0.0029763948
E27: Equivalência Patrimonial | F27: 0 | G27: 0 | H27: 0 | I27: 0 | J27: 0 | K27: 0 | L27: 0 | M27: =-7867 -> -7867 | N27: -1127 | O27: -821
E28: EBIT | F28: =F18+F20+F27 -> 149834 | G28: =G18+G20+G27 -> 309126 | H28: =H18+H20+H27 -> 500863 | I28: =I18+I20+I27 -> 705538 | J28: =J18+J20+J27 -> 792584 | K28: =K18+K20+K27 -> 721510 | L28: =L18+L20+L27 -> 1118469 | M28: =M18+M20+M27 -> 915984 | ... O28: =O18+O20+O27 -> 1839324
E29: Margem EBIT | F29: =F28/F$15 -> 0.024039138 | G29: =G28/G$15 -> 0.041821432 | H29: =H28/H$15 -> 0.056290346 | I29: =I28/I$15 -> 0.062677913 | J29: =J28/J$15 -> 0.059987413 | K29: =K28/K$15 -> 0.048745916 | L29: =L28/L$15 -> 0.063673828 | M29: =M28/M$15 -> 0.045646649 | ... O29: =O28/O$15 -> 0.063277942
E30: Não-Recorrente | F30: ='DRE - Contas Abertas'!F50 -> 0 | G30: ='DRE - Contas Abertas'!G50 -> 0 | H30: ='DRE - Contas Abertas'!H50 -> 0 | I30: ='DRE - Contas Abertas'!I50 -> 0 | J30: ='DRE - Contas Abertas'!J50 -> 0 | K30: ='DRE - Contas Abertas'!K50 -> -54803 | L30: ='DRE - Contas Abertas'!L50 -> 232320 | M30: ='DRE - Contas Abertas'!M50 -> 28317 | ... O30: ='DRE - Contas Abertas'!O50 -> 91387
E31: EBIT Recorrente | F31: =F28-F30 -> 149834 | G31: =G28-G30 -> 309126 | H31: =H28-H30 -> 500863 | I31: =I28-I30 -> 705538 | J31: =J28-J30 -> 792584 | K31: =K28-K30 -> 776313 | L31: =L28-L30 -> 886149 | M31: =M28-M30 -> 887667 | ... O31: =O28-O30 -> 1747937 | P31: =P32*P15 -> 1778702.2 | Q31: =Q32*Q15 -> 2014434.9 | R31: =R32*R15 -> 2302650.7 | S31: =S32*S15 -> 2610696.2 | T31: =T32*T15 -> 2957432.1 | U31: =U32*U15 -> 3329971.7 | V31: =V32*V15 -> 3751184.9 | W31: =W32*W15 -> 4210199.9 | ... BA31: =BA32*BA15 -> 54962151
E32: Margem EBIT Recorrente | F32: =F31/F$15 -> 0.024039138 | G32: =G31/G$15 -> 0.041821432 | H32: =H31/H$15 -> 0.056290346 | I32: =I31/I$15 -> 0.062677913 | J32: =J31/J$15 -> 0.059987413 | K32: =K31/K$15 -> 0.05244846 | L32: =L31/L$15 -> 0.050447978 | M32: =M31/M$15 -> 0.044235515 | ... O32: =O31/O$15 -> 0.060133971 | P32: =AVERAGE($O$32,$N$32)+('Projeções - Receita'!P66-'Projeções - Receita'!$O$66) -> 0.053175683 | Q32: =AVERAGE($O$32,$N$32)+('Projeções - Receita'!Q66-'Projeções - Receita'!$O$66) -> 0.053175683 | R32: =AVERAGE($O$32,$N$32)+('Projeções - Receita'!R66-'Projeções - Receita'!$O$66) -> 0.053175683 | S32: =AVERAGE($O$32,$N$32)+('Projeções - Receita'!S66-'Projeções - Receita'!$O$66) -> 0.053175683 | T32: =AVERAGE($O$32,$N$32)+('Projeções - Receita'!T66-'Projeções - Receita'!$O$66) -> 0.053175683 | U32: =AVERAGE($O$32,$N$32)+('Projeções - Receita'!U66-'Projeções - Receita'!$O$66) -> 0.053175683 | V32: =AVERAGE($O$32,$N$32)+('Projeções - Receita'!V66-'Projeções - Receita'!$O$66) -> 0.053175683 | W32: =AVERAGE($O$32,$N$32)+('Projeções - Receita'!W66-'Projeções - Receita'!$O$66) -> 0.053175683 | ... BA32: =AVERAGE($O$32,$N$32)+('Projeções - Receita'!BA66-'Projeções - Receita'!$O$66) -> 0.048931258
E33: Resultado Financeiro | F33: =SUM(F34:F35) -> -10447 | G33: =SUM(G34:G35) -> -6902 | H33: =SUM(H34:H35) -> -64961 | I33: =SUM(I34:I35) -> -110322 | J33: =SUM(J34:J35) -> -106040 | K33: =SUM(K34:K35) -> -82654 | L33: =SUM(L34:L35) -> -334301 | M33: =SUM(M34:M35) -> -299616 | ... O33: =SUM(O34:O35) -> -646115
E34: Receitas Financeiras | F34: 9863 | G34: 18347 | H34: 88786 | I34: 109433 | J34: 106883 | K34: 71783 | L34: 76945 | M34: 54182 | N34: 80016 | O34: 293586
E35: Despesas Financeiras | F35: -20310 | G35: -25249 | H35: -153747 | I35: -219755 | J35: -212923 | K35: -154437 | L35: -411246 | M35: -353798 | N35: -459226 | O35: -939701
E36: Resultado Antes dos Tributos Sobre o Lucro | F36: =F28+F33 -> 139387 | G36: =G28+G33 -> 302224 | H36: =H28+H33 -> 435902 | I36: =I28+I33 -> 595216 | J36: =J28+J33 -> 686544 | K36: =K28+K33 -> 638856 | L36: =L28+L33 -> 784168 | M36: =M28+M33 -> 616368 | ... O36: =O28+O33 -> 1193209
E37: Imposto de Renda e CSLL | F37: -38402 | G37: -80838 | H37: -96117 | I37: -143964 | J37: -173891 | K37: -129543 | L37: -106205 | M37: -120835 | N37: -223129 | O37: -178241 | P37: =-P43*P31 -> -284475.13 | Q37: =-Q43*Q31 -> -322176.84 | R37: =-R43*R31 -> -368272.38 | S37: =-S43*S31 -> -417539.36 | T37: =-T43*T31 -> -472994.24 | U37: =-U43*U31 -> -532576.03 | V37: =-V43*V31 -> -599942.39 | W37: =-W43*W31 -> -673354.54 | ... BA37: =-BA43*BA31 -> -10323617
E38: Lucro Líquido | F38: =F36+F37 -> 100985 | G38: =G36+G37 -> 221386 | H38: =H36+H37 -> 339785 | I38: =I36+I37 -> 451252 | J38: =J36+J37 -> 512653 | K38: =K36+K37 -> 509313 | L38: =L36+L37 -> 677963 | M38: =M36+M37 -> 495533 | ... O38: =O36+O37 -> 1014968
E39: Margem Líquida | F39: =F38/F15 -> 0.016201879 | G39: =G38/G15 -> 0.029951151 | H39: =H38/H15 -> 0.038187319 | I39: =I38/I15 -> 0.040087895 | J39: =J38/J15 -> 0.038800591 | K39: =K38/K15 -> 0.034409681 | L39: =L38/L15 -> 0.038596063 | M39: =M38/M15 -> 0.024694122 | ... O39: =O38/O15 -> 0.034917767
F42: =F9 -> 2013 | G42: =G9 -> 2014 | H42: =H9 -> 2015 | I42: =I9 -> 2016 | J42: =J9 -> 2017 | K42: =K9 -> 2018 | L42: =L9 -> 2019 | M42: =M9 -> 2020 | ... BA42: =BA9 -> 2060 | BB42: Perpetuidade | BC42: ROIC Perp. | BD42: Growth
E43: Alíquota Efetiva | F43: =IFERROR(IF(F28>0,-F37/F28,"-"),"-") -> 0.25629697 | G43: =IFERROR(IF(G28>0,-G37/G28,"-"),"-") -> 0.26150502 | H43: =IFERROR(IF(H28>0,-H37/H28,"-"),"-") -> 0.19190278 | I43: =IFERROR(IF(I28>0,-I37/I28,"-"),"-") -> 0.20404854 | J43: =IFERROR(IF(J28>0,-J37/J28,"-"),"-") -> 0.21939757 | K43: =IFERROR(IF(K28>0,-K37/K28,"-"),"-") -> 0.17954429 | L43: =IFERROR(IF(L28>0,-L37/L28,"-"),"-") -> 0.094955694 | M43: =IFERROR(IF(M28>0,-M37/M28,"-"),"-") -> 0.13191824 | ... O43: =IFERROR(IF(O28>0,-O37/O28,"-"),"-") -> 0.096905711 | P43: =(-AVERAGE('DRE - Contas Abertas'!$K$114:$N$114)*2-AVERAGE('DRE - Contas Abertas'!$H$116:$N$116))/3 -> 0.1599341 | Q43: =(-AVERAGE('DRE - Contas Abertas'!$K$114:$N$114)*2-AVERAGE('DRE - Contas Abertas'!$H$116:$N$116))/3 -> 0.1599341 | R43: =(-AVERAGE('DRE - Contas Abertas'!$K$114:$N$114)*2-AVERAGE('DRE - Contas Abertas'!$H$116:$N$116))/3 -> 0.1599341 | S43: =(-AVERAGE('DRE - Contas Abertas'!$K$114:$N$114)*2-AVERAGE('DRE - Contas Abertas'!$H$116:$N$116))/3 -> 0.1599341 | T43: =(-AVERAGE('DRE - Contas Abertas'!$K$114:$N$114)*2-AVERAGE('DRE - Contas Abertas'!$H$116:$N$116))/3 -> 0.1599341 | U43: =(-AVERAGE('DRE - Contas Abertas'!$K$114:$N$114)*2-AVERAGE('DRE - Contas Abertas'!$H$116:$N$116))/3 -> 0.1599341 | V43: =(-AVERAGE('DRE - Contas Abertas'!$K$114:$N$114)*2-AVERAGE('DRE - Contas Abertas'!$H$116:$N$116))/3 -> 0.1599341 | W43: =(-AVERAGE('DRE - Contas Abertas'!$K$114:$N$114)*2-AVERAGE('DRE - Contas Abertas'!$H$116:$N$116))/3 -> 0.1599341 | ... Y43: =(-AVERAGE('DRE - Contas Abertas'!$K$114:$N$114)*2-AVERAGE('DRE - Contas Abertas'!$H$116:$N$116))/3 -> 0.1599341 | Z43: =-AVERAGE('DRE - Contas Abertas'!$H$116:$N$116) -> 0.18783138 | AA43: =-AVERAGE('DRE - Contas Abertas'!$H$116:$N$116) -> 0.18783138 | AB43: =-AVERAGE('DRE - Contas Abertas'!$H$116:$N$116) -> 0.18783138 | AC43: =-AVERAGE('DRE - Contas Abertas'!$H$116:$N$116) -> 0.18783138 | AD43: =-AVERAGE('DRE - Contas Abertas'!$H$116:$N$116) -> 0.18783138 | AE43: =-AVERAGE('DRE - Contas Abertas'!$H$116:$N$116) -> 0.18783138 | AF43: =-AVERAGE('DRE - Contas Abertas'!$H$116:$N$116) -> 0.18783138 | AG43: =-AVERAGE('DRE - Contas Abertas'!$H$116:$N$116) -> 0.18783138 | ... BA43: =-AVERAGE('DRE - Contas Abertas'!$H$116:$N$116) -> 0.18783138 | BC43: =AVERAGE(H57:N58) -> 0.17847899 | BD43: =(1+'Projeções - Capex'!$Z$26)*(1+'Projeções - Receita'!$BA$60)-1 -> 0.0855656
E44: Depreciação de Arrendamento | F44: 0 | G44: 0 | H44: 0 | I44: 0 | J44: 0 | K44: 0 | L44: 533806 | M44: 613434 | N44: 700296 | O44: 815372 | P44: =P45*P15 -> 987056.86 | Q44: =Q45*Q15 -> 1117872.3 | R44: =R45*R15 -> 1277812.1 | S44: =S45*S15 -> 1448756.1 | T44: =T45*T15 -> 1641170.5 | U44: =U45*U15 -> 1847904.3 | V44: =V45*V15 -> 2081648.6 | W44: =W45*W15 -> 2336370.2 | ... BA44: =BA45*BA15 -> 33145865
E45: (%) da Receita Líquida | F45: =F44/F15 -> 0 | G45: =G44/G15 -> 0 | H45: =H44/H15 -> 0 | I45: =I44/I15 -> 0 | J45: =J44/J15 -> 0 | K45: =K44/K15 -> 0 | L45: =L44/L15 -> 0.030389284 | M45: =M44/M15 -> 0.030569537 | ... O45: =O44/O15 -> 0.028051101 | P45: =AVERAGE($L$45:$N$45,$O$45) -> 0.029508831 | Q45: =AVERAGE($L$45:$N$45,$O$45) -> 0.029508831 | R45: =AVERAGE($L$45:$N$45,$O$45) -> 0.029508831 | S45: =AVERAGE($L$45:$N$45,$O$45) -> 0.029508831 | T45: =AVERAGE($L$45:$N$45,$O$45) -> 0.029508831 | U45: =AVERAGE($L$45:$N$45,$O$45) -> 0.029508831 | V45: =AVERAGE($L$45:$N$45,$O$45) -> 0.029508831 | W45: =AVERAGE($L$45:$N$45,$O$45) -> 0.029508831 | ... BA45: =AVERAGE($L$45:$N$45,$O$45) -> 0.029508831
E46: NOPAT Recorrente | F46: =F31+F37+F44 -> 111432 | G46: =G31+G37+G44 -> 228288 | H46: =H31+H37+H44 -> 404746 | I46: =I31+I37+I44 -> 561574 | J46: =J31+J37+J44 -> 618693 | K46: =K31+K37+K44 -> 646770 | L46: =L31+L37+L44 -> 1313750 | M46: =M31+M37+M44 -> 1380266 | ... BA46: =BA31+BA37+BA44 -> 77784399 | BB46: =BA46 -> 77784399
E47: Margem NOPAT | F47: =F46/F15 -> 0.01787798 | G47: =G46/G15 -> 0.030884918 | H47: =H46/H15 -> 0.045488072 | I47: =I46/I15 -> 0.049888576 | J47: =J46/J15 -> 0.046826321 | K47: =K46/K15 -> 0.043696409 | L47: =L46/L15 -> 0.074791069 | M47: =M46/M15 -> 0.068783426 | ... BA47: =BA46/BA15 -> 0.069249263
E48: Taxa de Reinvestimento | F48: =IFERROR(SUM(F49,F53)/(F46),0) -> 0.7005528 | G48: =IFERROR(SUM(G49,G53)/(G46),0) -> 0.88329763 | H48: =IFERROR(SUM(H49,H53)/(H46),0) -> 0.68766584 | I48: =IFERROR(SUM(I49,I53)/(I46),0) -> 0.87292463 | J48: =IFERROR(SUM(J49,J53)/(J46),0) -> 0.91777182 | K48: =IFERROR(SUM(K49,K53)/(K46),0) -> 0.82700342 | L48: =IFERROR(SUM(L49,L53)/(L46),0) -> 0.5884666 | M48: =IFERROR(SUM(M49,M53)/(M46),0) -> 0.33293945 | ... X48: =IFERROR(SUM(X49,X53)/(X46),0) -> 0.21170691 | Y48: =(Y16-'Projeções - Capex'!$Y$26)/('DRE + DCF'!$BC$43-'Projeções - Capex'!$Y$26) -> 0.29866155 | Z48: =(Z16-'Projeções - Capex'!$Y$26)/('DRE + DCF'!$BC$43-'Projeções - Capex'!$Y$26) -> 0.2457738 | AA48: =(AA16-'Projeções - Capex'!$Y$26)/('DRE + DCF'!$BC$43-'Projeções - Capex'!$Y$26) -> 0.30708235 | AB48: =(AB16-'Projeções - Capex'!$Y$26)/('DRE + DCF'!$BC$43-'Projeções - Capex'!$Y$26) -> 0.3049139 | AC48: =(AC16-'Projeções - Capex'!$Y$26)/('DRE + DCF'!$BC$43-'Projeções - Capex'!$Y$26) -> 0.30179561 | AD48: =(AD16-'Projeções - Capex'!$Y$26)/('DRE + DCF'!$BC$43-'Projeções - Capex'!$Y$26) -> 0.29868076 | AE48: =(AE16-'Projeções - Capex'!$Y$26)/('DRE + DCF'!$BC$43-'Projeções - Capex'!$Y$26) -> 0.29575575 | AF48: =(AF16-'Projeções - Capex'!$Y$26)/('DRE + DCF'!$BC$43-'Projeções - Capex'!$Y$26) -> 0.29177908 | ... AZ48: =(AZ16-'Projeções - Capex'!$Y$26)/('DRE + DCF'!$BC$43-'Projeções - Capex'!$Y$26) -> 0.21007099 | BA48: =(BA16-'Projeções - Capex'!$Z$26)/('DRE + DCF'!$BC$43-'Projeções - Capex'!$Z$26) -> 0.18581567 | BB48: =(BD43-'Projeções - Capex'!$Z$26)/('DRE + DCF'!BC43-'Projeções - Capex'!Z26) -> 0.18639045
E49: CAPEX Líquido | F49: =F50-F51 -> 78064 | G49: =G50-G51 -> 83187 | H49: =H50-H51 -> 161641 | I49: =I50-I51 -> 214666 | J49: =J50-J51 -> 301285 | K49: =K50-K51 -> 288866 | L49: =L50-L51 -> 146137 | M49: =M50-M51 -> 109153 | ... X49: =X50-X51 -> 194547.46
E50: CAPEX | F50: ='Projeções - Capex'!F15 -> 236800 | G50: ='Projeções - Capex'!G15 -> 271000 | H50: ='Projeções - Capex'!H15 -> 388700 | I50: ='Projeções - Capex'!I15 -> 489100 | J50: ='Projeções - Capex'!J15 -> 639200 | K50: ='Projeções - Capex'!K15 -> 703000 | L50: ='Projeções - Capex'!L15 -> 649100 | M50: ='Projeções - Capex'!M15 -> 673000 | ... X50: ='Projeções - Capex'!X15 -> 2493122.9
E51: Depreciação & Amortização | F51: 158736 | G51: 187813 | H51: 227059 | I51: 274434 | J51: 337915 | K51: 414134 | L51: 502963 | M51: 563847 | N51: =1327110-N44 -> 626814 | O51: =1515538-O44 -> 700166 | P51: =P52*P15 -> 873463.73 | Q51: =Q52*Q15 -> 989224.56 | R51: =R52*R15 -> 1130758.1 | S51: =S52*S15 -> 1282029.4 | T51: =T52*T15 -> 1452300.3 | U51: =U52*U15 -> 1635242.6 | V51: =V52*V15 -> 1842086.9 | W51: =W52*W15 -> 2067494.5 | X51: =X52*X15 -> 2298575.4
E52: (%) da Receita Líquida | F52: =F51/F15 -> 0.025467361 | G52: =G51/G15 -> 0.025409084 | H52: =H51/H15 -> 0.025518415 | I52: =I51/I15 -> 0.024379906 | J52: =J51/J15 -> 0.025575392 | K52: =K51/K15 -> 0.027979295 | L52: =L51/L15 -> 0.028633408 | M52: =M51/M15 -> 0.028098445 | ... O52: =O51/O15 -> 0.024087689 | P52: =AVERAGE($F$52:$N$52,$O$52) -> 0.026112877 | Q52: =AVERAGE($F$52:$N$52,$O$52) -> 0.026112877 | R52: =AVERAGE($F$52:$N$52,$O$52) -> 0.026112877 | S52: =AVERAGE($F$52:$N$52,$O$52) -> 0.026112877 | T52: =AVERAGE($F$52:$N$52,$O$52) -> 0.026112877 | U52: =AVERAGE($F$52:$N$52,$O$52) -> 0.026112877 | V52: =AVERAGE($F$52:$N$52,$O$52) -> 0.026112877 | W52: =AVERAGE($F$52:$N$52,$O$52) -> 0.026112877 | X52: =AVERAGE($F$52:$N$52,$O$52) -> 0.026112877
E53: ∆ Capital de Giro | F53: 0 | G53: ='Balanço Patrimonial'!G10-'Balanço Patrimonial'!F10 -> 118459.25 | H53: ='Balanço Patrimonial'!H10-'Balanço Patrimonial'!G10 -> 116689 | I53: ='Balanço Patrimonial'!I10-'Balanço Patrimonial'!H10 -> 275545.77 | J53: ='Balanço Patrimonial'!J10-'Balanço Patrimonial'!I10 -> 266534 | K53: ='Balanço Patrimonial'!K10-'Balanço Patrimonial'!J10 -> 246015 | L53: ='Balanço Patrimonial'!L10-'Balanço Patrimonial'!K10 -> 626961 | M53: ='Balanço Patrimonial'!M10-'Balanço Patrimonial'!L10 -> 350392 | N53: ='Balanço Patrimonial'!N10-'Balanço Patrimonial'!M10 -> 321004 | O53: ='Balanço Patrimonial'!O10-'Balanço Patrimonial'!N10 -> 912917.41 | P53: =AVERAGE('Balanço Patrimonial'!$F$11:$N$11)*(P15-O15) -> 588209.14 | Q53: =AVERAGE('Balanço Patrimonial'!$F$11:$N$11)*(Q15-P15) -> 595045.77 | R53: =AVERAGE('Balanço Patrimonial'!$F$11:$N$11)*(R15-Q15) -> 727525.47 | S53: =AVERAGE('Balanço Patrimonial'!$F$11:$N$11)*(S15-R15) -> 777580.28 | T53: =AVERAGE('Balanço Patrimonial'!$F$11:$N$11)*(T15-S15) -> 875243.93 | U53: =AVERAGE('Balanço Patrimonial'!$F$11:$N$11)*(U15-T15) -> 940378.9 | V53: =AVERAGE('Balanço Patrimonial'!$F$11:$N$11)*(V15-U15) -> 1063242.6 | W53: =AVERAGE('Balanço Patrimonial'!$F$11:$N$11)*(W15-V15) -> 1158663.4 | X53: =AVERAGE('Balanço Patrimonial'!$F$11:$N$11)*(X15-W15) -> 1187825.9
E54: FCFF | F54: =(F46)*(1-F48) -> 33368 | G54: =(G46)*(1-G48) -> 26641.75 | H54: =(H46)*(1-H48) -> 126416 | I54: =(I46)*(1-I48) -> 71362.225 | J54: =(J46)*(1-J48) -> 50874 | K54: =(K46)*(1-K48) -> 111889 | L54: =(L46)*(1-L48) -> 540652 | M54: =(M46)*(1-M48) -> 920721 | ... BB54: =(BB46)*(1-BB48) -> 63286130
E55: Desconto | P55: =WACC!F21 -> 1.180574 | Q55: =WACC!G21 -> 1.3842461 | R55: =WACC!H21 -> 1.60183 | S55: =WACC!I21 -> 1.8447129 | T55: =WACC!J21 -> 2.1164294 | U55: =WACC!K21 -> 2.4210687 | V55: =WACC!L21 -> 2.7654228 | W55: =WACC!M21 -> 3.1573791 | ... BA55: =WACC!AQ21 -> 155.11625
E56: FCFF Descontado | P56: =P54/P55 -> 1429274.3 | Q56: =Q54/Q55 -> 1448651.6 | R56: =R54/R55 -> 1426417.9 | S56: =S54/S55 -> 1444752.1 | T56: =T54/T55 -> 1441667.7 | U56: =U54/U55 -> 1448361.5 | V56: =V54/V55 -> 1436130.2 | W56: =W54/W55 -> 1430655.1 | ... BA56: =BA54/BA55 -> 408279.85 | BB56: =BB54*(1+BD43)/(WACC!AQ20-BD43)/BA55 -> 8371458.4
E57: ROIC | F57: =(F46)/('Balanço Patrimonial'!F47+'Balanço Patrimonial'!F55+'Balanço Patrimonial'!F43+'Balanço Patrimonial'!F49+'Balanço Patrimonial'!F56-'Balanço Patrimonial'!F17) -> 0.044828412 | G57: =(G46)/('Balanço Patrimonial'!G47+'Balanço Patrimonial'!G55+'Balanço Patrimonial'!G43+'Balanço Patrimonial'!G49+'Balanço Patrimonial'!G56-'Balanço Patrimonial'!G17) -> 0.086014983 | H57: =(H46)/('Balanço Patrimonial'!H47+'Balanço Patrimonial'!H55+'Balanço Patrimonial'!H43+'Balanço Patrimonial'!H49+'Balanço Patrimonial'!H56-'Balanço Patrimonial'!H17) -> 0.13910799 | I57: =(I46)/('Balanço Patrimonial'!I47+'Balanço Patrimonial'!I55+'Balanço Patrimonial'!I43+'Balanço Patrimonial'!I49+'Balanço Patrimonial'!I56-'Balanço Patrimonial'!I17) -> 0.16763788 | J57: =(J46)/('Balanço Patrimonial'!J47+'Balanço Patrimonial'!J55+'Balanço Patrimonial'!J43+'Balanço Patrimonial'!J49+'Balanço Patrimonial'!J56-'Balanço Patrimonial'!J17) -> 0.16022787 | K57: =(K46)/('Balanço Patrimonial'!K47+'Balanço Patrimonial'!K55+'Balanço Patrimonial'!K43+'Balanço Patrimonial'!K49+'Balanço Patrimonial'!K56-'Balanço Patrimonial'!K17) -> 0.14773464 | L57: =(L46)/('Balanço Patrimonial'!L47+'Balanço Patrimonial'!L55+'Balanço Patrimonial'!L43+'Balanço Patrimonial'!L49+'Balanço Patrimonial'!L56-'Balanço Patrimonial'!L17) -> 0.15663137 | M57: =(M46)/('Balanço Patrimonial'!M47+'Balanço Patrimonial'!M55+'Balanço Patrimonial'!M43+'Balanço Patrimonial'!M49+'Balanço Patrimonial'!M56-'Balanço Patrimonial'!M17) -> 0.15115743 | ... O57: =(O46)/('Balanço Patrimonial'!O47+'Balanço Patrimonial'!O55+'Balanço Patrimonial'!O43+'Balanço Patrimonial'!O49+'Balanço Patrimonial'!O56-'Balanço Patrimonial'!O17) -> 0.20995378
E58: ROIC sem ágio e marcas | F58: =(F46)/('Balanço Patrimonial'!F47+'Balanço Patrimonial'!F55+'Balanço Patrimonial'!F43+'Balanço Patrimonial'!F49+'Balanço Patrimonial'!F56-'Balanço Patrimonial'!F37-'Balanço Patrimonial'!F17) -> 0.072638005 | G58: =(G46)/('Balanço Patrimonial'!G47+'Balanço Patrimonial'!G55+'Balanço Patrimonial'!G43+'Balanço Patrimonial'!G49+'Balanço Patrimonial'!G56-'Balanço Patrimonial'!G37-'Balanço Patrimonial'!G17) -> 0.13409954 | H58: =(H46)/('Balanço Patrimonial'!H47+'Balanço Patrimonial'!H55+'Balanço Patrimonial'!H43+'Balanço Patrimonial'!H49+'Balanço Patrimonial'!H56-'Balanço Patrimonial'!H37-'Balanço Patrimonial'!H17) -> 0.20998166 | I58: =(I46)/('Balanço Patrimonial'!I47+'Balanço Patrimonial'!I55+'Balanço Patrimonial'!I43+'Balanço Patrimonial'!I49+'Balanço Patrimonial'!I56-'Balanço Patrimonial'!I37-'Balanço Patrimonial'!I17) -> 0.23706248 | J58: =(J46)/('Balanço Patrimonial'!J47+'Balanço Patrimonial'!J55+'Balanço Patrimonial'!J43+'Balanço Patrimonial'!J49+'Balanço Patrimonial'!J56-'Balanço Patrimonial'!J37-'Balanço Patrimonial'!J17) -> 0.21472636 | K58: =(K46)/('Balanço Patrimonial'!K47+'Balanço Patrimonial'!K55+'Balanço Patrimonial'!K43+'Balanço Patrimonial'!K49+'Balanço Patrimonial'!K56-'Balanço Patrimonial'!K37-'Balanço Patrimonial'!K17) -> 0.18962719 | L58: =(L46)/('Balanço Patrimonial'!L47+'Balanço Patrimonial'!L55+'Balanço Patrimonial'!L43+'Balanço Patrimonial'!L49+'Balanço Patrimonial'!L56-'Balanço Patrimonial'!L37-'Balanço Patrimonial'!L17) -> 0.17741724 | M58: =(M46)/('Balanço Patrimonial'!M47+'Balanço Patrimonial'!M55+'Balanço Patrimonial'!M43+'Balanço Patrimonial'!M49+'Balanço Patrimonial'!M56-'Balanço Patrimonial'!M37-'Balanço Patrimonial'!M17) -> 0.1693804 | ... O58: =(O46)/('Balanço Patrimonial'!O47+'Balanço Patrimonial'!O55+'Balanço Patrimonial'!O43+'Balanço Patrimonial'!O49+'Balanço Patrimonial'!O56-'Balanço Patrimonial'!O37-'Balanço Patrimonial'!O17) -> 0.20995378
E59: ¹- "YoY", ou "year over year", significa "de um ano pro outro".

Sheet DRE - Contas Abertas
F3: =Dashboard!$I$3 -> Raia Drogasil ($RADL3)
A7: Páginas
A8: Dashboard
A9: WACC | F9: 2013 | G9: =H9-1 -> 2014 | H9: =I9-1 -> 2015 | I9: =J9-1 -> 2016 | J9: 2017 | K9: 2018 | L9: 2019 | M9: 2020 | N9: 2021 | O9: 2022
A10: DRE + DCF | E10: Custo das Mercadorias Vendidas | F10: -4512743 | G10: -5281377 | H10: -6183289 | I10: -7752422 | J10: -9224505 | K10: ='DRE + DCF'!K17 -> -10355923 | L10: ='DRE + DCF'!L17 -> -12367239 | M10: ='DRE + DCF'!M17 -> -14175708 | N10: -16901753 | O10: -20223406
A11: DRE - Contas Abertas | E11: Despesas com Pessoal | F11: -803348 | G11: -942024 | H11: -1144608 | I11: -1455915 | J11: -1626658 | K11: -1839906 | L11: -2167200 | M11: -2396582 | N11: -2890025 | O11: -3565669
A12: Balanço Patrimonial | E12: Despesas com Ocupação | F12: 0 | G12: 0 | H12: 0 | I12: 0 | J12: -602508 | K12: -699902 | L12: -272414 | M12: -279382 | N12: -324608 | O12: -348735
A13: Painel de Índices | E13: Descontos sobre locação de imóveis | F13: 0 | G13: 0 | H13: 0 | I13: 0 | J13: 0 | K13: 0 | L13: 0 | M13: 13804 | N13: 6390 | O13: 1105
A14: Provisões e Processos | E14: Despesas com Prestadores de Serviços | F14: -73741 | G14: -77910 | H14: -101919 | I14: -124857 | J14: -150449 | K14: -162044 | L14: -205892 | M14: -292285 | N14: -368999 | O14: -414916
A15: Projeções - Receita | E15: Depreciação e Amortização | F15: -158736 | G15: -187568 | H15: -227698 | I15: -274434 | J15: -337914 | K15: -414133 | L15: -1012403 | M15: -1148827 | N15: -1292310 | O15: -1473350
A16: Projeções - Capex | E16: Despesas com taxas de operadoras de cartões | F16: 0 | G16: 0 | H16: 0 | I16: 0 | J16: 0 | K16: 0 | L16: -212629 | M16: -249136 | N16: -307876 | O16: -412483
A17: Projeções 2022 | E17: Outras | F17: -487451 | G17: -584091 | H17: -730654 | I17: -935722 | J17: -478099 | K17: -548479 | L17: -417625 | M17: -583334 | N17: -720876 | O17: -876297
E18: Outros Resultados Operacionais | F18: -47066 | G18: -9473 | H18: -8818 | I18: -7677 | J18: 212 | K18: 0 | L18: 0 | M18: 0 | N18: 0 | O18: 0
E19: Gastos com Consultorias e Assessorias | F19: 0 | G19: 0 | H19: 0 | I19: 0 | J19: 0 | K19: -13913 | L19: -15320 | M19: -20437 | N19: 70 | O19: 0
E20: Créditos de anos anteriores, sobretudo de PIS e COFINS | F20: 0 | G20: 0 | H20: 0 | I20: 0 | J20: 0 | K20: 10698 | L20: 8193 | M20: 5417 | N20: 2238 | O20: 0
E21: Despesas adicionais devido ao encerramento do CD Barra Mansa | F21: 0 | G21: 0 | H21: 0 | I21: 0 | J21: 0 | K21: 0 | L21: -12767 | M21: 0 | N21: 0 | O21: 0
E22: Baixa de imobilizado e intangível devido ao encerramento de lojas | F22: 0 | G22: 0 | H22: 0 | I22: 0 | J22: 0 | K22: -1530 | L22: -16922 | M22: -3750 | N22: -23391 | O22: -28345
E23: Restruturação hierárquica | F23: 0 | G23: 0 | H23: 0 | I23: 0 | J23: 0 | K23: -7596 | L23: -16145 | M23: 732 | N23: 0 | O23: 0
E24: Integração da Onofre | F24: 0 | G24: 0 | H24: 0 | I24: 0 | J24: 0 | K24: 0 | L24: -95001 | M24: 0 | N24: 0 | O24: 0
E25: Apropriação de crédito de INSS de 2012 a 2015 | F25: 0 | G25: 0 | H25: 0 | I25: 0 | J25: 0 | K25: 0 | L25: 4625 | M25: 31059 | N25: 1142 | O25: 0
E26: Ganho por compra vantajosa Onofre | F26: 0 | G26: 0 | H26: 0 | I26: 0 | J26: 0 | K26: 0 | L26: 355263 | M26: 0 | N26: 0 | O26: 0
E27: Atualização Provisão Trabalhista - Taxa Selic | F27: 0 | G27: 0 | H27: 0 | I27: 0 | J27: 0 | K27: 0 | L27: 0 | M27: 0 | N27: 3410 | O27: 0
E28: Ressarcimento de ICMS-ST sobre vendas de 2020 | F28: 0 | G28: 0 | H28: 0 | I28: 0 | J28: 0 | K28: 0 | L28: 0 | M28: 0 | N28: 13706 | O28: 10210
E29: Exclusão do ICMS da base de cálculo de PIS/COFINS | F29: 0 | G29: 0 | H29: 0 | I29: 0 | J29: 0 | K29: 0 | L29: 0 | M29: 0 | N29: 58044 | O29: 15943
... E42: Doações | F42: 0 | G42: 0 | H42: 0 | I42: 0 | J42: 0 | K42: 0 | L42: 0 | M42: -29282 | N42: -15903 | O42: -884
E43: Total: | F43: =SUM(F10:F42) -> -6083085 | G43: =SUM(G10:G42) -> -7082443 | H43: =SUM(H10:H42) -> -8396986 | I43: =SUM(I10:I42) -> -10551027 | J43: =SUM(J10:J42) -> -12419921 | K43: =SUM(K10:K42) -> -14079935 | L43: =SUM(L10:L42) -> -16447131 | M43: =SUM(M10:M42) -> -19142989 | ... O43: =SUM(O10:O42) -> -27236345
F46: =G46-1 -> 2013 | G46: =H46-1 -> 2014 | H46: =I46-1 -> 2015 | I46: =J46-1 -> 2016 | J46: 2017 | K46: 2018 | L46: 2019 | M46: 2020 | N46: 2021 | O46: 2022
E47: Lucro Bruto | F47: ='DRE + DCF'!F18 -> 1720176 | G47: ='DRE + DCF'!G18 -> 2110192 | H47: ='DRE + DCF'!H18 -> 2714560 | I47: ='DRE + DCF'!I18 -> 3504143 | J47: ='DRE + DCF'!J18 -> 3988000 | K47: ='DRE + DCF'!K18 -> 4445522 | L47: ='DRE + DCF'!L18 -> 5198361 | M47: ='DRE + DCF'!M18 -> 5891132 | N47: ='DRE + DCF'!N18 -> 7206168 | O47: 8809468
E48: EBIT | F48: ='DRE + DCF'!F28 -> 149834 | G48: ='DRE + DCF'!G28 -> 309126 | H48: ='DRE + DCF'!H28 -> 500863 | I48: ='DRE + DCF'!I28 -> 705538 | J48: ='DRE + DCF'!J28 -> 792584 | K48: ='DRE + DCF'!K28 -> 721510 | L48: ='DRE + DCF'!L28 -> 1118469 | M48: ='DRE + DCF'!M28 -> 915984 | N48: ='DRE + DCF'!N28 -> 1366472 | O48: 1873830
E49: Margem EBIT | F49: =F48/'DRE + DCF'!F15 -> 0.024039138 | G49: =G48/'DRE + DCF'!G15 -> 0.041821432 | H49: =H48/'DRE + DCF'!H15 -> 0.056290346 | I49: =I48/'DRE + DCF'!I15 -> 0.062677913 | J49: =J48/'DRE + DCF'!J15 -> 0.059987413 | K49: =K48/'DRE + DCF'!K15 -> 0.048745916 | L49: =L48/'DRE + DCF'!L15 -> 0.063673828 | M49: =M48/'DRE + DCF'!M15 -> 0.045646649 | ... O49: =O48/'DRE + DCF'!O15 -> 0.064465046
E50: Eventos não recorrentes | F50: =F13+F21+F24+F25+F31+F32+F33+F34+F35+F30+F26+F35+F36+F37+F38+F27+F28+F29+F23+F40 -> 0 | G50: =G13+G21+G24+G25+G31+G32+G33+G34+G35+G30+G26+G35+G36+G37+G38+G27+G28+G29+G23+G40 -> 0 | H50: =H13+H21+H24+H25+H31+H32+H33+H34+H35+H30+H26+H35+H36+H37+H38+H27+H28+H29+H23+H40 -> 0 | I50: =I13+I21+I24+I25+I31+I32+I33+I34+I35+I30+I26+I35+I36+I37+I38+I27+I28+I29+I23+I40 -> 0 | J50: =J13+J21+J24+J25+J31+J32+J33+J34+J35+J30+J26+J35+J36+J37+J38+J27+J28+J29+J23+J40 -> 0 | K50: =K13+K21+K24+K25+K31+K32+K33+K34+K35+K30+K26+K35+K36+K37+K38+K27+K28+K29+K23+K40 -> -54803 | L50: =L13+L21+L24+L25+L31+L32+L33+L34+L35+L30+L26+L35+L36+L37+L38+L27+L28+L29+L23+L40 -> 232320 | M50: =M13+M21+M24+M25+M31+M32+M33+M34+M35+M30+M26+M35+M36+M37+M38+M27+M28+M29+M23+M40 -> 28317 | N50: =N13+N21+N24+N25+N31+N32+N33+N34+N35+N30+N26+N35+N36+N37+N38+N27+N28+N29+N23+N40 -> 84578 | O50: 91387
E51: EBIT recorrente | F51: =F48-F50 -> 149834 | G51: =G48-G50 -> 309126 | H51: =H48-H50 -> 500863 | I51: =I48-I50 -> 705538 | J51: =J48-J50 -> 792584 | K51: =K48-K50 -> 776313 | L51: =L48-L50 -> 886149 | M51: =M48-M50 -> 887667 | N51: =N48-N50 -> 1281894 | O51: 1782443
E52: Margem EBIT recorrente | F52: =F51/'DRE + DCF'!F15 -> 0.024039138 | G52: =G51/'DRE + DCF'!G15 -> 0.041821432 | H52: =H51/'DRE + DCF'!H15 -> 0.056290346 | I52: =I51/'DRE + DCF'!I15 -> 0.062677913 | J52: =J51/'DRE + DCF'!J15 -> 0.059987413 | K52: =K51/'DRE + DCF'!K15 -> 0.05244846 | L52: =L51/'DRE + DCF'!L15 -> 0.050447978 | M52: =M51/'DRE + DCF'!M15 -> 0.044235515 | ... O52: =O51/'DRE + DCF'!O15 -> 0.061321075
E53: Subvenção de Investimentos na Receita Líquida | F53: ='Projeções - Receita'!F65 -> 0 | G53: ='Projeções - Receita'!G65 -> 0 | H53: ='Projeções - Receita'!H65 -> 0 | I53: ='Projeções - Receita'!I65 -> 0 | J53: ='Projeções - Receita'!J65 -> 0 | K53: ='Projeções - Receita'!K65 -> 64344.118 | L53: ='Projeções - Receita'!L65 -> 81529.412 | M53: ='Projeções - Receita'!M65 -> 125511.76 | N53: ='Projeções - Receita'!N65 -> 165732.35 | O53: 147596.17
E54: EBIT recorrente excluindo a subvenção de investimentos | F54: =F51-F53 -> 149834 | G54: =G51-G53 -> 309126 | H54: =H51-H53 -> 500863 | I54: =I51-I53 -> 705538 | J54: =J51-J53 -> 792584 | K54: =K51-K53 -> 711968.88 | L54: =L51-L53 -> 804619.59 | M54: =M51-M53 -> 762155.24 | ... O54: =O51-O53 -> 1634846.8
E55: Margem EBIT recorrente excluindo a subvenção de investimentos | F55: =F54/'DRE + DCF'!F15 -> 0.024039138 | G55: =G54/'DRE + DCF'!G15 -> 0.041821432 | H55: =H54/'DRE + DCF'!H15 -> 0.056290346 | I55: =I54/'DRE + DCF'!I15 -> 0.062677913 | J55: =J54/'DRE + DCF'!J15 -> 0.059987413 | K55: =K54/'DRE + DCF'!K15 -> 0.048101309 | L55: =L54/'DRE + DCF'!L15 -> 0.045806553 | M55: =M54/'DRE + DCF'!M15 -> 0.03798083 | ... O55: =O54/'DRE + DCF'!O15 -> 0.05624335
F58: =G58-1 -> 2013 | G58: =H58-1 -> 2014 | H58: =I58-1 -> 2015 | I58: =J58-1 -> 2016 | J58: 2017 | K58: 2018 | L58: 2019 | M58: 2020 | N58: 2021 | O58: 2022
E59: Descontos obtidos | F59: 555 | G59: 243 | H59: 1667 | I59: 1611 | J59: 1107 | K59: 1997 | L59: 3426 | M59: 8563 | N59: 503 | O59: 8162
E60: Rendimentos de Aplicações Financeiras | F60: 8204 | G60: 16548 | H60: 27256 | I60: 19863 | J60: 24174 | K60: 10104 | L60: 7070 | M60: 6136 | N60: 9513 | O60: 27799
E61: Juros recebidos | F61: 154 | G61: 8 | H61: 0 | I61: 0 | J61: 0 | K61: 0 | L61: 0 | M61: 0 | N61: 64 | O61: 487
E62: Juros sobre Mútuo | F62: 0 | G62: 0 | H62: 0 | I62: 0 | J62: 0 | K62: 0 | L62: 0 | M62: 0 | N62: 0 | O62: 0
E63: Variações Monetárias Ativas | F63: 945 | G63: 1542 | H63: 2294 | I63: 2642 | J63: 3308 | K63: 1061 | L63: 6222 | M63: 1356 | N63: 5218 | O63: 3986
E64: Outras receitas financeiras | F64: 5 | G64: 6 | H64: 41 | I64: 142 | J64: 306 | K64: 192 | L64: 335 | M64: 190 | N64: 379 | O64: 5065
E65: Impostos Incidentes (PIS/COFINS) | F65: 0 | G65: 0 | H65: -810 | I65: -1188 | J65: -1449 | K65: -716 | L65: -798 | M65: -813 | N65: 0 | O65: 0
E66: Ajuste a Valor Presente (AVP) - Receitas Financeiras | F66: 0 | G66: 0 | H66: 58338 | I66: 86363 | J66: 79437 | K66: 59145 | L66: 60690 | M66: 38750 | N66: 64339 | O66: 248087
E67: Total: | F67: =SUM(F59:F66) -> 9863 | G67: =SUM(G59:G66) -> 18347 | H67: =SUM(H59:H66) -> 88786 | I67: =SUM(I59:I66) -> 109433 | J67: =SUM(J59:J66) -> 106883 | K67: =SUM(K59:K66) -> 71783 | L67: =SUM(L59:L66) -> 76945 | M67: =SUM(M59:M66) -> 54182 | ... O67: =SUM(O59:O66) -> 293586
F70: =G70-1 -> 2013 | G70: =H70-1 -> 2014 | H70: =I70-1 -> 2015 | I70: =J70-1 -> 2016 | J70: 2017 | K70: 2018 | L70: 2019 | M70: 2020 | N70: 2021 | O70: 2022
E71: Descontos Concedidos a Clientes | F71: -3 | G71: -62 | H71: -440 | I71: -2129 | J71: -187 | K71: -281 | L71: -42 | M71: -444 | N71: -565 | O71: -94
E72: Juros, encargos e taxas bancárias | F72: -2182 | G72: -935 | H72: -1321 | I72: -1798 | J72: -1185 | K72: -1246 | L72: -2665 | M72: -1729 | N72: -1624 | O72: -19699
E73: Encargos sobre Debêntures e Notas Promissórias | F73: 0 | G73: 0 | H73: 0 | I73: 0 | J73: -19128 | K73: -36495 | L73: -54191 | M73: -38494 | N73: -58262 | O73: -219274
E74: Amortização de custos de transação | F74: 0 | G74: 0 | H74: 0 | I74: 0 | J74: -247 | K74: -582 | L74: -1722 | M74: -3937 | N74: -4315 | O74: -5194
E75: Encargos sobre Empréstimos e Financiamentos | F75: -17338 | G75: -23638 | H75: -31624 | I75: -42304 | J75: -45106 | K75: -20731 | L75: -11434 | M75: -20496 | N75: -29511 | O75: -47259
E76: Juros Sobre Arrendamento | F76: 0 | G76: 0 | H76: 0 | I76: 0 | J76: 0 | K76: 0 | L76: -216100 | M76: -228020 | N76: -223757 | O76: -244623
E77: Variações Monetárias Passivas | F77: -787 | G77: -614 | H77: -5266 | I77: -5335 | J77: -6152 | K77: 2635 | L77: -1967 | M77: 6977 | N77: -6233 | O77: -9721
E78: Juros sobre opção de compra de ações adicionais | F78: 0 | G78: 0 | H78: -1402 | I78: -13596 | J78: -2286 | K78: 11135 | L78: -5733 | M78: -4336 | N78: -2849 | O78: -28368
E79: Ajuste a Valor Presente (AVP) - Despesas Financeiras | F79: 0 | G79: 0 | H79: -113694 | I79: -154593 | J79: -138632 | K79: -108872 | L79: -117392 | M79: -63319 | N79: -132110 | O79: -365469
E80: Total: | F80: =SUM(F71:F79) -> -20310 | G80: =SUM(G71:G79) -> -25249 | H80: =SUM(H71:H79) -> -153747 | I80: =SUM(I71:I79) -> -219755 | J80: =SUM(J71:J79) -> -212923 | K80: =SUM(K71:K79) -> -154437 | L80: =SUM(L71:L79) -> -411246 | M80: =SUM(M71:M79) -> -353798 | ... O80: =SUM(O71:O79) -> -939701
F83: =G83-1 -> 2013 | G83: =H83-1 -> 2014 | H83: =I83-1 -> 2015 | I83: =J83-1 -> 2016 | J83: 2017 | K83: 2018 | L83: 2019 | M83: 2020 | N83: 2021 | O83: 1T2022
E84: EBIT Recorrente | F84: =F51 -> 149834 | G84: =G51 -> 309126 | H84: =H51 -> 500863 | I84: =I51 -> 705538 | J84: =J51 -> 792584 | K84: =K51 -> 776313 | L84: =L51 -> 886149 | M84: =M51 -> 887667 | ... O84: =O51 -> 1782443
E85: Lucro Líquido antes do IR (A partir do EBIT recorrente) | F85: =F84+F67+F80 -> 139387 | G85: =G84+G67+G80 -> 302224 | H85: =H84+H67+H80 -> 435902 | I85: =I84+I67+I80 -> 595216 | J85: =J84+J67+J80 -> 686544 | K85: =K84+K67+K80 -> 693659 | L85: =L84+L67+L80 -> 551848 | M85: =M84+M67+M80 -> 588051 | ... O85: =O84+O67+O80 -> 1136328
E86: Eventos não recorrentes | F86: 0 | G86: 0 | H86: 0 | I86: 0 | J86: 0 | K86: 0 | L86: 0 | M86: 0 | N86: 0 | O86: 0
E87: Lucro Antes do IR Recorrente | F87: =F85-F86 -> 139387 | G87: =G85-G86 -> 302224 | H87: =H85-H86 -> 435902 | I87: =I85-I86 -> 595216 | J87: =J85-J86 -> 686544 | K87: =K85-K86 -> 693659 | L87: =L85-L86 -> 551848 | M87: =M85-M86 -> 588051 | ... O87: =O85-O86 -> 1136328
E88: Subvenção de Investimentos na Receita Líquida | F88: =F53 -> 0 | G88: =G53 -> 0 | H88: =H53 -> 0 | I88: =I53 -> 0 | J88: =J53 -> 0 | K88: =K53 -> 64344.118 | L88: =L53 -> 81529.412 | M88: =M53 -> 125511.76 | ... O88: =O53 -> 147596.17
E89: Lucro Antes do IR Recorrente excluindo a subvenção de investimentos | F89: =F87-F88 -> 139387 | G89: =G87-G88 -> 302224 | H89: =H87-H88 -> 435902 | I89: =I87-I88 -> 595216 | J89: =J87-J88 -> 686544 | K89: =K87-K88 -> 629314.88 | L89: =L87-L88 -> 470318.59 | M89: =M87-M88 -> 462539.24 | ... O89: =O87-O88 -> 988731.83
F92: =G92-1 -> 2013 | G92: =H92-1 -> 2014 | H92: =I92-1 -> 2015 | I92: =J92-1 -> 2016 | J92: 2017 | K92: 2018 | L92: 2019 | M92: 2020 | N92: 2021 | O92: 2020
E93: Lucro (prejuízo) líquido antes de imposto Recorrente | F93: =F87 -> 139387 | G93: =G87 -> 302224 | H93: =H87 -> 435902 | I93: =I87 -> 595216 | J93: =J87 -> 686544 | K93: =K87 -> 693659 | L93: =L87 -> 551848 | M93: =M87 -> 588051 | ... O93: =O87 -> 1136328
E94: Alíquota Vigente | F94: 0.34 | G94: 0.34 | H94: 0.34 | I94: 0.34 | J94: 0.34 | K94: 0.34 | L94: 0.34 | M94: 0.34 | N94: 0.34 | O94: 0.34
E95: Expectativa de despesa de acordo com alíquota vigente | F95: =F94*-F93 -> -47391.58 | G95: =G94*-G93 -> -102756.16 | H95: =H94*-H93 -> -148206.68 | I95: =I94*-I93 -> -202373.44 | J95: =J94*-J93 -> -233424.96 | K95: =K94*-K93 -> -235844.06 | L95: =L94*-L93 -> -187628.32 | M95: =M94*-M93 -> -199937.34 | ... O95: =O94*-O93 -> -386351.52
E96: Efeito Fiscal das adiçoes e exclusões permanentes: | F96: 0 | G96: 0 | H96: 0 | I96: 0 | J96: 0 | K96: 0 | L96: 0 | M96: 0 | N96: 0 | O96: 0
E97: Juros sobre o Capital Próprio | F97: =38900*34% -> 13226 | G97: =74559*34% -> 25350.06 | H97: =179210*34% -> 60931.4 | I97: =194701*34% -> 66198.34 | J97: =202500*34% -> 68850 | K97: =209500*34% -> 71230 | L97: =211501*34% -> 71910.34 | M97: =193000*34% -> 65620 | N97: =205000*34% -> 69700 | O97: =312000*34% -> 106080
E98: Adições Permanentes | F98: -2107 | G98: -2220 | H98: -7054 | I98: -9940 | J98: -11805 | K98: -7479 | L98: -13379 | M98: -29630 | N98: -25781 | O98: -5895
E99: Equivalência Patrimonial | F99: 0 | G99: 0 | H99: 0 | I99: 0 | J99: 0 | K99: 0 | L99: 0 | M99: -2674 | N99: -383 | O99: -56
E100: Redução do Imposto por Incentivos | F100: 203 | G100: 2810 | H100: 3545 | I100: 5525 | J100: 6669 | K100: 5487 | L100: 2144 | M100: 3714 | N100: 4098 | O100: 4090
E101: Subvenção para Investimentos | F101: 0 | G101: 0 | H101: 0 | I101: 0 | J101: 0 | K101: 21877 | L101: 27720 | M101: 42674 | N101: 56349 | O101: 76111
E102: Prejuízo Fiscal e Base Negativa CSLL | F102: 0 | G102: 0 | H102: 0 | I102: 0 | J102: 0 | K102: 0 | L102: 0 | M102: 0 | N102: -6100 | O102: -13752
E103: Provisões sem constítuição de diferido | F103: 0 | G103: 0 | H103: 0 | I103: 0 | J103: 0 | K103: 0 | L103: 0 | M103: 0 | N103: 5 | O103: 192
E104: Ganho por compra vantajosa | F104: 0 | G104: 0 | H104: 0 | I104: 0 | J104: 0 | K104: 0 | L104: 113083 | M104: 0 | N104: 0 | O104: 0
E105: Provisões não dedutíveis temporariamente | F105: 0 | G105: 0 | H105: 0 | I105: 0 | J105: 0 | K105: 12975 | L105: 60143 | M105: 0 | N105: 0 | O105: 0
E106: Inovação Tecnológica | F106: 0 | G106: 0 | H106: 0 | I106: 0 | J106: 0 | K106: 0 | L106: 0 | M106: 2561 | N106: 9288 | O106: 15504
E107: Ajuste de compensação de prejuízos fiscais | F107: 0 | G107: 0 | H107: -2933 | I107: 0 | J107: 0 | K107: 0 | L107: 0 | M107: 0 | N107: 0 | O107: 0
E108: Incentivos Fiscais - Doações | F108: 0 | G108: -1920 | H108: -2455 | I108: -3515 | J108: -4195 | K108: -3320 | L108: 1190 | M108: 6300 | N108: 6269 | O108: 5055
E109: Processo de Destruição de Mercadorias | F109: -2172 | G109: -2102 | H109: 0 | I109: 0 | J109: 0 | K109: 0 | L109: 0 | M109: 0 | N109: 0 | O109: 0
E110: Outros (reserva de reavaliação + limite de isenção adicional de IR) | F110: -160 | G110: 0 | H110: 55 | I110: 141 | J110: 15 | K110: -127 | L110: -9106 | M110: 165 | N110: -905 | O110: 40522
E111: IRPJ + CSLL | F111: =SUM(F95:F110) -> -38401.58 | G111: =SUM(G95:G110) -> -80838.1 | H111: =SUM(H95:H110) -> -96117.28 | I111: =SUM(I95:I110) -> -143964.1 | J111: =SUM(J95:J110) -> -173890.96 | K111: =SUM(K95:K110) -> -135201.06 | L111: =SUM(L95:L110) -> 66077.02 | M111: =SUM(M95:M110) -> -111207.34 | ... O111: =SUM(O95:O110) -> -158500.52
E112: Como % do EBIT Recorrente | F112: =F111/F84 -> -0.25629417 | G112: =G111/G84 -> -0.26150534 | H112: =H111/H84 -> -0.19190333 | I112: =I111/I84 -> -0.20404868 | J112: =J111/J84 -> -0.21939751 | K112: =K111/K84 -> -0.17415792 | L112: =L111/L84 -> 0.074566489 | M112: =M111/M84 -> -0.12528047 | ... O112: =O111/O84 -> -0.088923191
E113: IRPJ + CSLL - Não-Recorrentes | F113: =F95+F97+F98+F99+F100+F101+F106+F108+F110 -> -36229.58 | G113: =G95+G97+G98+G99+G100+G101+G106+G108+G110 -> -78736.1 | H113: =H95+H97+H98+H99+H100+H101+H106+H108+H110 -> -93184.28 | I113: =I95+I97+I98+I99+I100+I101+I106+I108+I110 -> -143964.1 | J113: =J95+J97+J98+J99+J100+J101+J106+J108+J110 -> -173890.96 | K113: =K95+K97+K98+K99+K100+K101+K106+K108+K110 -> -148176.06 | L113: =L95+L97+L98+L99+L100+L101+L106+L108+L110 -> -107148.98 | M113: =M95+M97+M98+M99+M100+M101+M106+M108+M110 -> -111207.34 | ... O113: =O95+O97+O98+O99+O100+O101+O106+O108+O110 -> -144940.52
E114: Como % do EBIT Recorrente | F114: =F113/F84 -> -0.24179812 | G114: =G113/G84 -> -0.25470552 | H114: =H113/H84 -> -0.18604744 | I114: =I113/I84 -> -0.20404868 | J114: =J113/J84 -> -0.21939751 | K114: =K113/K84 -> -0.19087154 | L114: =L113/L84 -> -0.12091531 | M114: =M113/M84 -> -0.12528047 | ... O114: =O113/O84 -> -0.081315655
E115: IRPJ + CSLL - Não-Recorrentes - Incentivos | F115: =-F89*F94+F97+F98+F110+F99 -> -36432.58 | G115: =-G89*G94+G97+G98+G110+G99 -> -79626.1 | H115: =-H89*H94+H97+H98+H110+H99 -> -94274.28 | I115: =-I89*I94+I97+I98+I110+I99 -> -145974.1 | J115: =-J89*J94+J97+J98+J110+J99 -> -176364.96 | K115: =-K89*K94+K97+K98+K110+K99 -> -150343.06 | L115: =-L89*L94+L97+L98+L110+L99 -> -110482.98 | M115: =-M89*M94+M97+M98+M110+M99 -> -123782.34 | ... O115: =-O89*O94+O97+O98+O110+O99 -> -195517.82
E116: Como % do EBIT Recorrente sem Incentivos | F116: =F115/F54 -> -0.24315296 | G116: =G115/G54 -> -0.25758461 | H116: =H115/H54 -> -0.18822369 | I116: =I115/I54 -> -0.20689757 | J116: =J115/J54 -> -0.22251895 | K116: =K115/K54 -> -0.21116521 | L116: =L115/L54 -> -0.13731083 | M116: =M115/M54 -> -0.16241093 | ... O116: =O115/O54 -> -0.11959397

Sheet Balanço Patrimonial
F3: Raia Drogasil ($RADL3)
A7: Páginas
A8: Dashboard
A9: WACC | E9: Data do Último Resultado: | F9: 2013 | G9: 2014 | H9: 2015 | I9: 2016 | J9: 2017 | K9: 2018 | L9: 2019 | M9: 2020 | N9: 2021 | O9: 2022
A10: DRE + DCF | E10: Capital de Giro | F10: =SUM(F16,F19:F23)-SUM(F40:F41,F42,F45,F46) -> 890918.98 | G10: =SUM(G16,G19:G23)-SUM(G40:G41,G42,G45,G46) -> 1009378.2 | H10: =SUM(H16,H19:H23)-SUM(H40:H41,H42,H45,H46) -> 1126067.2 | I10: =SUM(I16,I19:I23)-SUM(I40:I41,I42,I45,I46) -> 1401613 | J10: =SUM(J16,J19:J23)-SUM(J40:J41,J42,J45,J46) -> 1668147 | K10: =SUM(K16,K19:K23)-SUM(K40:K41,K42,K45,K46) -> 1914162 | L10: =SUM(L16,L19:L23)-SUM(L40:L41,L42,L45,L46) -> 2541123 | M10: =SUM(M16,M19:M23)-SUM(M40:M41,M42,M45,M46) -> 2891515 | ... O10: =SUM(O16,O19:O23)-SUM(O40:O41,O42,O45,O46) -> 4125436.4
A11: DRE - Contas Abertas | E11: % da Receita Líquida | F11: =F10/'DRE + DCF'!F15 -> 0.14293768 | G11: =G10/'DRE + DCF'!G15 -> 0.13655805 | H11: =H10/'DRE + DCF'!H15 -> 0.12655499 | I11: =I10/'DRE + DCF'!I15 -> 0.12451516 | J11: =J10/'DRE + DCF'!J15 -> 0.12625517 | K11: =K10/'DRE + DCF'!K15 -> 0.12932264 | L11: =L10/'DRE + DCF'!L15 -> 0.14466474 | M11: =M10/'DRE + DCF'!M15 -> 0.14409419 | ... O11: =O10/'DRE + DCF'!O15 -> 0.14192667
A12: Balanço Patrimonial | E12: Ativo Total | F12: 3614094 | G12: 4079503 | H12: 4699201 | I12: 5659301 | J12: 6464250 | K12: 7352005 | L12: 12248255 | M12: 13828088 | N12: =N13+N24 -> 14775506 | O12: =O13+O24 -> 17243771
A13: Painel de Índices | E13: Ativo Circulante | F13: 1903576 | G13: 2272317 | H13: 2685844 | I13: 3427782 | J13: 3928204 | K13: 4529825 | L13: 5756046 | M13: 7020490 | N13: =N14+N19+N20+N21+N22+N23 -> 7718924 | O13: =O14+O19+O20+O21+O22+O23 -> 9577068
A14: Provisões e Processos | E14: Caixa e Equivalente de Caixa | F14: 241885 | G14: 281467 | H14: 266051 | I14: 276632 | J14: 264873 | K14: 241568 | L14: 299226 | M14: 880357 | N14: 356118 | O14: 433541
A15: Projeções - Receita | E15: % da Receita Líquida | F15: =F14/'DRE + DCF'!F15 -> 0.03880766 | G15: =G14/'DRE + DCF'!G15 -> 0.038079466 | H15: =H14/'DRE + DCF'!H15 -> 0.029900597 | I15: =I14/'DRE + DCF'!I15 -> 0.02457517 | J15: =J14/'DRE + DCF'!J15 -> 0.020047145 | K15: =K14/'DRE + DCF'!K15 -> 0.016320569 | L15: =L14/'DRE + DCF'!L15 -> 0.017034773 | M15: =M14/'DRE + DCF'!M15 -> 0.043871232 | N15: =N14/'DRE + DCF'!N15 -> 0.014760143 | O15: =O14/'DRE + DCF'!Q15 -> 0.01144432
A16: Projeções - Capex | E16: Caixa Operacional | F16: =IF(F15>2.5%,2.5%*'DRE + DCF'!F15,'DRE + DCF'!F15*'Balanço Patrimonial'!F15) -> 155822.98 | G16: =IF(G15>2.5%,2.5%*'DRE + DCF'!G15,'DRE + DCF'!G15*'Balanço Patrimonial'!G15) -> 184789.23 | H16: =IF(H15>2.5%,2.5%*'DRE + DCF'!H15,'DRE + DCF'!H15*'Balanço Patrimonial'!H15) -> 222446.23 | I16: =IF(I15>2.5%,2.5%*'DRE + DCF'!I15,'DRE + DCF'!I15*'Balanço Patrimonial'!I15) -> 276632 | J16: =IF(J15>2.5%,2.5%*'DRE + DCF'!J15,'DRE + DCF'!J15*'Balanço Patrimonial'!J15) -> 264873 | K16: =IF(K15>2.5%,2.5%*'DRE + DCF'!K15,'DRE + DCF'!K15*'Balanço Patrimonial'!K15) -> 241568 | L16: =IF(L15>2.5%,2.5%*'DRE + DCF'!L15,'DRE + DCF'!L15*'Balanço Patrimonial'!L15) -> 299226 | M16: =IF(M15>2.5%,2.5%*'DRE + DCF'!M15,'DRE + DCF'!M15*'Balanço Patrimonial'!M15) -> 501671 | ... O16: =IF(O15>2.5%,2.5%*'DRE + DCF'!O15,'DRE + DCF'!O15*'Balanço Patrimonial'!O15) -> 332656.41
A17: Projeções 2022 | E17: Excesso de Caixa | F17: =F14-F16 -> 86062.025 | G17: =G14-G16 -> 96677.775 | H17: =H14-H16 -> 43604.775 | I17: =I14-I16 -> 0 | J17: =J14-J16 -> 0 | K17: =K14-K16 -> 0 | L17: =L14-L16 -> 0 | M17: =M14-M16 -> 378686 | ... O17: =O14-O16 -> 100884.59
E18: Aplicações Financeiras | F18: 0 | G18: 0 | H18: 0 | I18: 0 | J18: 0 | K18: 0 | L18: 0 | M18: 0 | N18: 0 | O18: 0
E19: Contas a Receber | F19: 373260 | G19: 482840 | H19: 601831 | I19: 772241 | J19: 930071 | K19: 1094236 | L19: 1433446 | M19: 1816456 | N19: 2000871 | O19: 2562521
E20: Estoques | F20: 1132620 | G20: 1350971 | H20: 1650453 | I20: 2149468 | J20: 2517594 | K20: 3087275 | L20: 3851388 | M20: 4225408 | N20: 5117799 | O20: 6126056
E21: Tributos a Recuperar | F21: 38658 | G21: 39429 | H21: 59530 | I21: 111772 | J21: 78777 | K21: 84852 | L21: 145617 | M21: 61531 | N21: 195777 | O21: 393336
E22: Despesas Antecipadas | F22: 8200 | G22: 9972 | H22: 9718 | I22: 12558 | J22: 17885 | K22: 21894 | L22: 26369 | M22: 36738 | N22: 48359 | O22: 61614
E23: Outros | F23: 108953 | G23: 107638 | H23: 98261 | I23: 105111 | J23: 119004 | K23: 0 | L23: 0 | M23: 0 | N23: 0 | O23: 0
E24: Ativo Não Circulante | F24: =SUM(F31,F25,F32,F35) -> 1710518 | G24: =SUM(G31,G25,G32,G35) -> 1807186 | H24: =SUM(H31,H25,H32,H35) -> 2013357 | I24: =SUM(I31,I25,I32,I35) -> 2231519 | J24: =SUM(J31,J25,J32,J35) -> 2536046 | K24: =SUM(K31,K25,K32,K35) -> 2822180 | L24: =SUM(L31,L25,L32,L35) -> 6492209 | M24: =SUM(M31,M25,M32,M35) -> 6807598 | N24: =N25+N31+N32+N35 -> 7056582 | O24: =O25+O31+O32+O35 -> 7666703.2
E25: Ativo Realizável a Longo Prazo | F25: =SUM(F26:F30) -> 23350 | G25: =SUM(G26:G30) -> 33549 | H25: =SUM(H26:H30) -> 44499 | I25: =SUM(I26:I30) -> 50857 | J25: =SUM(J26:J30) -> 68754 | K25: =SUM(K26:K30) -> 72832 | L25: =SUM(L26:L30) -> 432508 | M25: =SUM(M26:M30) -> 525424 | ... O25: =SUM(O26:O30) -> 349255.45
E26: Depósitos Judiciais | F26: 10763 | G26: 14116 | H26: 18730 | I26: 23007 | J26: 29215 | K26: 25770 | L26: 30001 | M26: 25753 | N26: 29951 | O26: 137623.45
E27: Impostos a recuperar | F27: 11859 | G27: 17330 | H27: 23156 | I27: 22963 | J27: 34293 | K27: 44345 | L27: 68099 | M27: 111548 | N27: 132929 | O27: 121434
E28: IR e CSLL Diferidos | F28: 0 | G28: 0 | H28: 0 | I28: 0 | J28: 0 | K28: 0 | L28: 0 | M28: 36261 | N28: 49047 | O28: 10357
E29: Outros Ativos Não Circulantes | F29: 728 | G29: 2103 | H29: 2613 | I29: 4887 | J29: 5246 | K29: =1589+1128 -> 2717 | L29: =894+587 -> 1481 | M29: =3502+6454 -> 9956 | N29: =571+5189 -> 5760 | O29: =61614+4426 -> 66040
E30: Créditos de Empresas Controladas | F30: 0 | G30: 0 | H30: 0 | I30: 0 | J30: 0 | K30: 0 | L30: 332927 | M30: 341906 | N30: 22227 | O30: 13801
E31: Investimentos | F31: 0 | G31: 0 | H31: 0 | I31: 0 | J31: 0 | K31: 0 | L31: 0 | M31: 0 | N31: 830 | O31: 4477.8736
E32: Imobilizado | F32: =SUM(F33:F34) -> 536629 | G32: =SUM(G33:G34) -> 648360 | H32: =SUM(H33:H34) -> 801985 | I32: =SUM(I33:I34) -> 1006606 | J32: =SUM(J33:J34) -> 1276276 | K32: =SUM(K33:K34) -> 1546960 | L32: =SUM(L33:L34) -> 4814260 | M32: =SUM(M33:M34) -> 5020465 | N32: =SUM(N33:N34) -> 5329587 | O32: 5574857.2
E33: Imobilizado em Operação | F33: 536629 | G33: 648360 | H33: 801985 | I33: 1006606 | J33: 1276276 | K33: 1546960 | L33: 1777735 | M33: 1859220 | N33: 1999020 | O33: 2196405
E34: Imobilizado Arrendado | F34: 0 | G34: 0 | H34: 0 | I34: 0 | J34: 0 | K34: 0 | L34: 3036525 | M34: 3161245 | N34: 3330567 | O34: 3378452
E35: Intangível | F35: 1150539 | G35: 1125277 | H35: 1166873 | I35: 1174056 | J35: 1191016 | K35: 1202388 | L35: 1245441 | M35: 1261709 | N35: 1486251 | O35: 1738112.7
E36: Intangíveis | F36: =F35-F37 -> 198867 | G36: =G35-G37 -> 173605 | H36: =H35-H37 -> 184822 | I36: =I35-I37 -> 193019 | J36: =J35-J37 -> 210993 | K36: =K35-K37 -> 235216 | L36: =L35-L37 -> 262774 | M36: =M35-M37 -> 279307 | N36: =N35-N37 -> 372553 | O36: 0
E37: Ágio e Marcas | F37: 951672 | G37: 951672 | H37: 982051 | I37: 981037 | J37: 980023 | K37: 967172 | L37: 982667 | M37: 982402 | N37: =19888+780084+25563+20886+153930+10524+5617+7120+90086 -> 1113698 | O37: 0
E38: Passivo Total | F38: 1287109 | G38: 1620662 | H38: 2042403 | I38: 2723348 | J38: 3213877 | K38: =K39+K48 -> 3817238 | L38: =L39+L48 -> 8171836 | M38: =M39+M48 -> 9402467 | N38: =N39+N48 -> 10056704 | O38: =O39+O48 -> 11774019
E39: Passivo Circulante | F39: 1020003 | G39: 1298611 | H39: 1648766 | I39: 2184684 | J39: 2493779 | K39: 2913445 | L39: 4078485 | M39: 4801303 | N39: =SUM(N40:N47) -> 5896193 | O39: =SUM(O40:O47) -> 6358821
E40: Obrigações Sociais e Trabalhistas | F40: 116352 | G40: 142635 | H40: 165409 | I40: 199378 | J40: 202799 | K40: 237541 | L40: 296674 | M40: 309160 | N40: 420356 | O40: 561623
E41: Fornecedores | F41: 671455 | G41: 886533 | H41: 1203382 | I41: 1615587 | J41: 1815687 | K41: 2141274 | L41: 2653236 | M41: 3106938 | N41: 3656607 | O41: 4252361
E42: Obrigações Fiscais | F42: 65920 | G42: 43516 | H42: 55878 | I42: 96731 | J42: 130432 | K42: 92964 | L42: 102671 | M42: 138671 | N42: 154773 | O42: 211508
E43: Empréstimos e Financiamentos | F43: 83944 | G43: 103686 | H43: 108192 | I43: 132581 | J43: 196248 | K43: 272939 | L43: 228661 | M43: 531204 | N43: 613831 | O43: 186356
E44: Dividendos e JCP a Pagar | F44: 9464 | G44: 28664 | H44: 24402 | I44: 25934 | J44: 37474 | K44: 24843 | L44: 68255 | M44: 16492 | N44: 76787 | O44: 62417
E45: Outras contas a pagar | F45: 67956 | G45: 88368 | H45: 88157 | I45: 92970 | J45: 108415 | K45: 119350 | L45: =60814+44213 -> 105027 | M45: =69322+56775 -> 126097 | N45: =84060+82056 -> 166116 | O45: =93940+81917 -> 175857
E46: Provisões | F46: 4912 | G46: 5209 | H46: 3346 | I46: 21503 | J46: 2724 | K46: 24534 | L46: 57315 | M46: 69423 | N46: 108553 | O46: 149398
E47: Passivos de Arrendamento | F47: 0 | G47: 0 | H47: 0 | I47: 0 | J47: 0 | K47: 0 | L47: 566646 | M47: 503318 | N47: 699170 | O47: 759301
E48: Passivo Não Circulante | F48: 267106 | G48: 322051 | H48: 393637 | I48: 538664 | J48: 720098 | K48: 903793 | L48: 4093351 | M48: 4601164 | N48: =SUM(N49:N51,N53:N55) -> 4160511 | O48: =SUM(O49:O51,O53:O55) -> 5415197.6
E49: Empréstimos e Financiamentos | F49: 160881 | G49: 188200 | H49: 188196 | I49: 281387 | J49: 414711 | K49: 570211 | L49: 897815 | M49: 1122250 | N49: 891391 | O49: 2131548
E50: Outras Obrigações | F50: 4224 | G50: 3792 | H50: 36108 | I50: 61499 | J50: 68503 | K50: 46948 | L50: =11436+42113 -> 53549 | M50: =13188+46448 -> 59636 | N50: =114898+37943 -> 152841 | O50: 230271.77
E51: Tributos Diferidos | F51: =F52 -> 93980 | G51: =G52 -> 125946 | H51: =H52 -> 165981 | I51: =I52 -> 193187 | J51: =J52 -> 228714 | K51: =K52 -> 237757 | L51: =L52 -> 123986 | M51: =M52 -> 74428 | N51: 89011 | O51: 17659.12
E52: Imposto de renda e contribuição social diferidos | F52: 93980 | G52: 125946 | H52: 165981 | I52: 193187 | J52: 228714 | K52: 237757 | L52: 123986 | M52: 74428 | N52: 89011 | O52: 17659.12
E53: Provisões | F53: 8021 | G53: 4113 | H53: 3352 | I53: 2591 | J53: 8170 | K53: 48877 | L53: 67114 | M53: 75400 | N53: 53540 | O53: 55011.676
E54: Débitos de Empresas Controladas | F54: 0 | G54: 0 | H54: 0 | I54: 0 | J54: 0 | K54: 0 | L54: 332900 | M54: 341843 | N54: 0 | O54: 0
E55: Passivos de Arrendamento | F55: 0 | G55: 0 | H55: 0 | I55: 0 | J55: 0 | K55: 0 | L55: 2617987 | M55: 2927607 | N55: 2973728 | O55: 2980707
E56: Patrimônio Líquido | F56: =SUM(F57:F64) -> 2326982 | G56: =SUM(G57:G64) -> 2458841 | H56: =SUM(H57:H64) -> 2656798 | I56: =SUM(I57:I64) -> 2935955 | J56: =SUM(J57:J64) -> 3250373 | K56: =SUM(K57:K64) -> 3534767 | L56: =SUM(L57:L64) -> 4076419 | M56: =SUM(M57:M64) -> 4425621 | ... O56: =SUM(O57:O64) -> 5402939.8
E57: Capital Social Realizado | F57: 908639 | G57: 909407 | H57: 1808639 | I57: 1808639 | J57: 1808639 | K57: 1808639 | L57: 2500000 | M57: 2500000 | N57: 2500000 | O57: 2500000
E58: Reserva de Capital | F58: 1039935 | G58: 1019791 | H58: 128767 | I58: 138553 | J58: 151156 | K58: 116363 | L58: 129768 | M58: 148029 | N58: 89914 | O58: 112761.56
E59: Reservas de Reavaliação | F59: 12941 | G59: 12755 | H59: 12569 | I59: 12383 | J59: 12197 | K59: 0 | L59: 0 | M59: 0 | N59: 0 | O59: 0
E60: Reservas de Lucro | F60: 357169 | G60: 475420 | H60: 665821 | I60: 919118 | J60: 1228149 | K60: 1522073 | L60: 1371984 | M60: 1664172 | N60: 2072984 | O60: 2716768.2
E61: Lucros/Prejuízos Acumulados | F61: 0 | G61: 1137 | H61: 0 | I61: 0 | J61: 0 | K61: 0 | L61: 0 | M61: 0 | N61: 0 | O61: 0
E62: Ajustes de Avaliação Patrimonial | F62: 0 | G62: 0 | H62: -30230 | I62: -30230 | J62: -30230 | K62: -18208 | L62: -18382 | M62: -18553 | N62: 14775 | O62: 11331
E63: Dividendo Adicional Proposto | F63: 8298 | G63: 40331 | H63: 48243 | I63: 61324 | J63: 52602 | K63: 70990 | L63: 41643 | M63: 69478 | N63: 0 | O63: 0
E64: Participação dos Acionistas Não Controladores | F64: 0 | G64: 0 | H64: 22989 | I64: 26168 | J64: 27860 | K64: 34910 | L64: 51406 | M64: 62495 | N64: 41129 | O64: 62078.99

Sheet Painel de Índices
G3: Raia Drogasil ($RADL3)
A7: Páginas
A8: Dashboard
A9: WACC | F9: =G9-1 -> 2013 | G9: =H9-1 -> 2014 | H9: =I9-1 -> 2015 | I9: 2016 | J9: 2017 | K9: 2018 | L9: 2019 | M9: 2020 | N9: 2021 | O9: 2022
A10: DRE + DCF | E10: Liquidez Geral | F10: ='Balanço Patrimonial'!F12/'Balanço Patrimonial'!F38 -> 2.807916 | G10: ='Balanço Patrimonial'!G12/'Balanço Patrimonial'!G38 -> 2.5171831 | H10: ='Balanço Patrimonial'!H12/'Balanço Patrimonial'!H38 -> 2.3008197 | I10: ='Balanço Patrimonial'!I12/'Balanço Patrimonial'!I38 -> 2.0780675 | J10: ='Balanço Patrimonial'!J12/'Balanço Patrimonial'!J38 -> 2.0113558 | K10: ='Balanço Patrimonial'!K12/'Balanço Patrimonial'!K38 -> 1.9260012 | L10: ='Balanço Patrimonial'!L12/'Balanço Patrimonial'!L38 -> 1.4988376 | M10: ='Balanço Patrimonial'!M12/'Balanço Patrimonial'!M38 -> 1.4706872 | ... O10: ='Balanço Patrimonial'!O12/'Balanço Patrimonial'!O38 -> 1.4645612
A11: DRE - Contas Abertas | E11: Liquidez Corrente | F11: ='Balanço Patrimonial'!F13/'Balanço Patrimonial'!F39 -> 1.8662455 | G11: ='Balanço Patrimonial'!G13/'Balanço Patrimonial'!G39 -> 1.7498058 | H11: ='Balanço Patrimonial'!H13/'Balanço Patrimonial'!H39 -> 1.6290025 | I11: ='Balanço Patrimonial'!I13/'Balanço Patrimonial'!I39 -> 1.5690059 | J11: ='Balanço Patrimonial'!J13/'Balanço Patrimonial'!J39 -> 1.5752013 | K11: ='Balanço Patrimonial'!K13/'Balanço Patrimonial'!K39 -> 1.5548002 | L11: ='Balanço Patrimonial'!L13/'Balanço Patrimonial'!L39 -> 1.4113196 | M11: ='Balanço Patrimonial'!M13/'Balanço Patrimonial'!M39 -> 1.4622052 | ... O11: ='Balanço Patrimonial'!O13/'Balanço Patrimonial'!O39 -> 1.5061075
A12: Balanço Patrimonial | E12: Liquidez Seca | F12: =('Balanço Patrimonial'!F13-'Balanço Patrimonial'!F20)/'Balanço Patrimonial'!F39 -> 0.75583699 | G12: =('Balanço Patrimonial'!G13-'Balanço Patrimonial'!G20)/'Balanço Patrimonial'!G39 -> 0.70948575 | H12: =('Balanço Patrimonial'!H13-'Balanço Patrimonial'!H20)/'Balanço Patrimonial'!H39 -> 0.62797935 | I12: =('Balanço Patrimonial'!I13-'Balanço Patrimonial'!I20)/'Balanço Patrimonial'!I39 -> 0.58512535 | J12: =('Balanço Patrimonial'!J13-'Balanço Patrimonial'!J20)/'Balanço Patrimonial'!J39 -> 0.56565157 | K12: =('Balanço Patrimonial'!K13-'Balanço Patrimonial'!K20)/'Balanço Patrimonial'!K39 -> 0.49513548 | L12: =('Balanço Patrimonial'!L13-'Balanço Patrimonial'!L20)/'Balanço Patrimonial'!L39 -> 0.46700135 | M12: =('Balanço Patrimonial'!M13-'Balanço Patrimonial'!M20)/'Balanço Patrimonial'!M39 -> 0.58215072 | ... O12: =('Balanço Patrimonial'!O13-'Balanço Patrimonial'!O20)/'Balanço Patrimonial'!O39 -> 0.54271256
A13: Painel de Índices | E13: Liquidez Imediata | F13: =('Balanço Patrimonial'!F16+'Balanço Patrimonial'!F18)/'Balanço Patrimonial'!F39 -> 0.15276717 | G13: =('Balanço Patrimonial'!G16+'Balanço Patrimonial'!G18)/'Balanço Patrimonial'!G39 -> 0.1422976 | H13: =('Balanço Patrimonial'!H16+'Balanço Patrimonial'!H18)/'Balanço Patrimonial'!H39 -> 0.1349168 | I13: =('Balanço Patrimonial'!I16+'Balanço Patrimonial'!I18)/'Balanço Patrimonial'!I39 -> 0.12662335 | J13: =('Balanço Patrimonial'!J16+'Balanço Patrimonial'!J18)/'Balanço Patrimonial'!J39 -> 0.1062135 | K13: =('Balanço Patrimonial'!K16+'Balanço Patrimonial'!K18)/'Balanço Patrimonial'!K39 -> 0.0829149 | L13: =('Balanço Patrimonial'!L16+'Balanço Patrimonial'!L18)/'Balanço Patrimonial'!L39 -> 0.073366949 | M13: =('Balanço Patrimonial'!M16+'Balanço Patrimonial'!M18)/'Balanço Patrimonial'!M39 -> 0.10448643 | ... O13: =('Balanço Patrimonial'!O16+'Balanço Patrimonial'!O18)/'Balanço Patrimonial'!O39 -> 0.052314164
A14: Provisões e Processos
A15: Projeções - Receita
A16: Projeções - Capex
A17: Projeções 2022 | F17: =G17-1 -> 2013 | G17: =H17-1 -> 2014 | H17: =I17-1 -> 2015 | I17: 2016 | J17: 2017 | K17: 2018 | L17: 2019 | M17: 2020 | N17: 2021 | O17: 2022
E18: Retorno sobre o Equity (ROE) | F18: ='DRE + DCF'!F38/'Balanço Patrimonial'!F56 -> 0.043397413 | G18: ='DRE + DCF'!G38/'Balanço Patrimonial'!G56 -> 0.090036729 | H18: ='DRE + DCF'!H38/'Balanço Patrimonial'!H56 -> 0.12789267 | I18: ='DRE + DCF'!I38/'Balanço Patrimonial'!I56 -> 0.15369854 | J18: ='DRE + DCF'!J38/'Balanço Patrimonial'!J56 -> 0.15772128 | K18: ='DRE + DCF'!K38/'Balanço Patrimonial'!K56 -> 0.14408672 | L18: ='DRE + DCF'!L38/'Balanço Patrimonial'!L56 -> 0.16631337 | M18: ='DRE + DCF'!M38/'Balanço Patrimonial'!M56 -> 0.11196915 | ... O18: ='DRE + DCF'!O38/'Balanço Patrimonial'!O56 -> 0.18785477
E19: Retorno sobre o Ativo (ROA) | F19: ='DRE + DCF'!F38/'Balanço Patrimonial'!F12 -> 0.027941996 | G19: ='DRE + DCF'!G38/'Balanço Patrimonial'!G12 -> 0.054267885 | H19: ='DRE + DCF'!H38/'Balanço Patrimonial'!H12 -> 0.072306973 | I19: ='DRE + DCF'!I38/'Balanço Patrimonial'!I12 -> 0.079736349 | J19: ='DRE + DCF'!J38/'Balanço Patrimonial'!J12 -> 0.079305875 | K19: ='DRE + DCF'!K38/'Balanço Patrimonial'!K12 -> 0.069275388 | L19: ='DRE + DCF'!L38/'Balanço Patrimonial'!L12 -> 0.055351803 | M19: ='DRE + DCF'!M38/'Balanço Patrimonial'!M12 -> 0.035835251 | ... O19: ='DRE + DCF'!O38/'Balanço Patrimonial'!O12 -> 0.058859978
E20: ROIC | F20: ='DRE + DCF'!F57 -> 0.044828412 | G20: ='DRE + DCF'!G57 -> 0.086014983 | H20: ='DRE + DCF'!H57 -> 0.13910799 | I20: ='DRE + DCF'!I57 -> 0.16763788 | J20: ='DRE + DCF'!J57 -> 0.16022787 | K20: ='DRE + DCF'!K57 -> 0.14773464 | L20: ='DRE + DCF'!L57 -> 0.15663137 | M20: ='DRE + DCF'!M57 -> 0.15115743 | ... O20: ='DRE + DCF'!O57 -> 0.20995378
F24: =G24-1 -> 2013 | G24: =H24-1 -> 2014 | H24: =I24-1 -> 2015 | I24: 2016 | J24: 2017 | K24: 2018 | L24: 2019 | M24: 2020 | N24: 2021 | O24: 2022
E25: Divida Líquida/EBITDA | F25: =('Balanço Patrimonial'!F43+'Balanço Patrimonial'!F47+'Balanço Patrimonial'!F49+'Balanço Patrimonial'!F55-'Balanço Patrimonial'!F14-'Balanço Patrimonial'!F18)/('DRE + DCF'!F28+'DRE + DCF'!F44+'DRE + DCF'!F51) -> 0.0095278219 | G25: =('Balanço Patrimonial'!G43+'Balanço Patrimonial'!G47+'Balanço Patrimonial'!G49+'Balanço Patrimonial'!G55-'Balanço Patrimonial'!G14-'Balanço Patrimonial'!G18)/('DRE + DCF'!G28+'DRE + DCF'!G44+'DRE + DCF'!G51) -> 0.020966356 | H25: =('Balanço Patrimonial'!H43+'Balanço Patrimonial'!H47+'Balanço Patrimonial'!H49+'Balanço Patrimonial'!H55-'Balanço Patrimonial'!H14-'Balanço Patrimonial'!H18)/('DRE + DCF'!H28+'DRE + DCF'!H44+'DRE + DCF'!H51) -> 0.041676169 | I25: =('Balanço Patrimonial'!I43+'Balanço Patrimonial'!I47+'Balanço Patrimonial'!I49+'Balanço Patrimonial'!I55-'Balanço Patrimonial'!I14-'Balanço Patrimonial'!I18)/('DRE + DCF'!I28+'DRE + DCF'!I44+'DRE + DCF'!I51) -> 0.14014278 | J25: =('Balanço Patrimonial'!J43+'Balanço Patrimonial'!J47+'Balanço Patrimonial'!J49+'Balanço Patrimonial'!J55-'Balanço Patrimonial'!J14-'Balanço Patrimonial'!J18)/('DRE + DCF'!J28+'DRE + DCF'!J44+'DRE + DCF'!J51) -> 0.30613561 | K25: =('Balanço Patrimonial'!K43+'Balanço Patrimonial'!K47+'Balanço Patrimonial'!K49+'Balanço Patrimonial'!K55-'Balanço Patrimonial'!K14-'Balanço Patrimonial'!K18)/('DRE + DCF'!K28+'DRE + DCF'!K44+'DRE + DCF'!K51) -> 0.52972763 | L25: =('Balanço Patrimonial'!L43+'Balanço Patrimonial'!L47+'Balanço Patrimonial'!L49+'Balanço Patrimonial'!L55-'Balanço Patrimonial'!L14-'Balanço Patrimonial'!L18)/('DRE + DCF'!L28+'DRE + DCF'!L44+'DRE + DCF'!L51) -> 1.8614571 | M25: =('Balanço Patrimonial'!M43+'Balanço Patrimonial'!M47+'Balanço Patrimonial'!M49+'Balanço Patrimonial'!M55-'Balanço Patrimonial'!M14-'Balanço Patrimonial'!M18)/('DRE + DCF'!M28+'DRE + DCF'!M44+'DRE + DCF'!M51) -> 2.0083563 | ... O25: =('Balanço Patrimonial'!O43+'Balanço Patrimonial'!O47+'Balanço Patrimonial'!O49+'Balanço Patrimonial'!O55-'Balanço Patrimonial'!O14-'Balanço Patrimonial'!O18)/('DRE + DCF'!O28+'DRE + DCF'!O44+'DRE + DCF'!O51) -> 1.6764836
E26: Cobertura de Juros | F26: =-'DRE + DCF'!F28/'DRE + DCF'!F35 -> 7.3773511 | G26: =-'DRE + DCF'!G28/'DRE + DCF'!G35 -> 12.243099 | H26: =-'DRE + DCF'!H28/'DRE + DCF'!H35 -> 3.2577091 | I26: =-'DRE + DCF'!I28/'DRE + DCF'!I35 -> 3.2105663 | J26: =-'DRE + DCF'!J28/'DRE + DCF'!J35 -> 3.7223973 | K26: =-'DRE + DCF'!K28/'DRE + DCF'!K35 -> 4.6718727 | L26: =-'DRE + DCF'!L28/'DRE + DCF'!L35 -> 2.7197079 | M26: =-'DRE + DCF'!M28/'DRE + DCF'!M35 -> 2.5890028 | ... O26: =-'DRE + DCF'!O28/'DRE + DCF'!O35 -> 1.9573503
E27: Dívida/Ativo | F27: =('Balanço Patrimonial'!F43+'Balanço Patrimonial'!F47+'Balanço Patrimonial'!F49+'Balanço Patrimonial'!F55)/'Balanço Patrimonial'!F12 -> 0.067741736 | G27: =('Balanço Patrimonial'!G43+'Balanço Patrimonial'!G47+'Balanço Patrimonial'!G49+'Balanço Patrimonial'!G55)/'Balanço Patrimonial'!G12 -> 0.071549402 | H27: =('Balanço Patrimonial'!H43+'Balanço Patrimonial'!H47+'Balanço Patrimonial'!H49+'Balanço Patrimonial'!H55)/'Balanço Patrimonial'!H12 -> 0.063071999 | I27: =('Balanço Patrimonial'!I43+'Balanço Patrimonial'!I47+'Balanço Patrimonial'!I49+'Balanço Patrimonial'!I55)/'Balanço Patrimonial'!I12 -> 0.073148256 | J27: =('Balanço Patrimonial'!J43+'Balanço Patrimonial'!J47+'Balanço Patrimonial'!J49+'Balanço Patrimonial'!J55)/'Balanço Patrimonial'!J12 -> 0.094513517 | K27: =('Balanço Patrimonial'!K43+'Balanço Patrimonial'!K47+'Balanço Patrimonial'!K49+'Balanço Patrimonial'!K55)/'Balanço Patrimonial'!K12 -> 0.114683 | L27: =('Balanço Patrimonial'!L43+'Balanço Patrimonial'!L47+'Balanço Patrimonial'!L49+'Balanço Patrimonial'!L55)/'Balanço Patrimonial'!L12 -> 0.3519774 | M27: =('Balanço Patrimonial'!M43+'Balanço Patrimonial'!M47+'Balanço Patrimonial'!M49+'Balanço Patrimonial'!M55)/'Balanço Patrimonial'!M12 -> 0.36768489 | ... O27: =('Balanço Patrimonial'!O43+'Balanço Patrimonial'!O47+'Balanço Patrimonial'!O49+'Balanço Patrimonial'!O55)/'Balanço Patrimonial'!O12 -> 0.35131016
E28: Dívida/Patrimônio Líquido | F28: =('Balanço Patrimonial'!F43+'Balanço Patrimonial'!F47+'Balanço Patrimonial'!F49+'Balanço Patrimonial'!F55)/'Balanço Patrimonial'!F56 -> 0.10521139 | G28: =('Balanço Patrimonial'!G43+'Balanço Patrimonial'!G47+'Balanço Patrimonial'!G49+'Balanço Patrimonial'!G55)/'Balanço Patrimonial'!G56 -> 0.11870877 | H28: =('Balanço Patrimonial'!H43+'Balanço Patrimonial'!H47+'Balanço Patrimonial'!H49+'Balanço Patrimonial'!H55)/'Balanço Patrimonial'!H56 -> 0.11155835 | I28: =('Balanço Patrimonial'!I43+'Balanço Patrimonial'!I47+'Balanço Patrimonial'!I49+'Balanço Patrimonial'!I55)/'Balanço Patrimonial'!I56 -> 0.14099944 | J28: =('Balanço Patrimonial'!J43+'Balanço Patrimonial'!J47+'Balanço Patrimonial'!J49+'Balanço Patrimonial'!J55)/'Balanço Patrimonial'!J56 -> 0.18796581 | K28: =('Balanço Patrimonial'!K43+'Balanço Patrimonial'!K47+'Balanço Patrimonial'!K49+'Balanço Patrimonial'!K55)/'Balanço Patrimonial'!K56 -> 0.23853057 | L28: =('Balanço Patrimonial'!L43+'Balanço Patrimonial'!L47+'Balanço Patrimonial'!L49+'Balanço Patrimonial'!L55)/'Balanço Patrimonial'!L56 -> 1.0575726 | M28: =('Balanço Patrimonial'!M43+'Balanço Patrimonial'!M47+'Balanço Patrimonial'!M49+'Balanço Patrimonial'!M55)/'Balanço Patrimonial'!M56 -> 1.148851 | ... O28: =('Balanço Patrimonial'!O43+'Balanço Patrimonial'!O47+'Balanço Patrimonial'!O49+'Balanço Patrimonial'!O55)/'Balanço Patrimonial'!O56 -> 1.1212252
E29: Dívida/(Dívida + Patrimônio Líquido) | F29: =('Balanço Patrimonial'!F43+'Balanço Patrimonial'!F47+'Balanço Patrimonial'!F49+'Balanço Patrimonial'!F55)/('Balanço Patrimonial'!F43+'Balanço Patrimonial'!F47+'Balanço Patrimonial'!F49+'Balanço Patrimonial'!F55+'Balanço Patrimonial'!F56) -> 0.095195713 | G29: =('Balanço Patrimonial'!G43+'Balanço Patrimonial'!G47+'Balanço Patrimonial'!G49+'Balanço Patrimonial'!G55)/('Balanço Patrimonial'!G43+'Balanço Patrimonial'!G47+'Balanço Patrimonial'!G49+'Balanço Patrimonial'!G55+'Balanço Patrimonial'!G56) -> 0.10611231 | H29: =('Balanço Patrimonial'!H43+'Balanço Patrimonial'!H47+'Balanço Patrimonial'!H49+'Balanço Patrimonial'!H55)/('Balanço Patrimonial'!H43+'Balanço Patrimonial'!H47+'Balanço Patrimonial'!H49+'Balanço Patrimonial'!H55+'Balanço Patrimonial'!H56) -> 0.10036212 | I29: =('Balanço Patrimonial'!I43+'Balanço Patrimonial'!I47+'Balanço Patrimonial'!I49+'Balanço Patrimonial'!I55)/('Balanço Patrimonial'!I43+'Balanço Patrimonial'!I47+'Balanço Patrimonial'!I49+'Balanço Patrimonial'!I55+'Balanço Patrimonial'!I56) -> 0.12357538 | J29: =('Balanço Patrimonial'!J43+'Balanço Patrimonial'!J47+'Balanço Patrimonial'!J49+'Balanço Patrimonial'!J55)/('Balanço Patrimonial'!J43+'Balanço Patrimonial'!J47+'Balanço Patrimonial'!J49+'Balanço Patrimonial'!J55+'Balanço Patrimonial'!J56) -> 0.15822493 | K29: =('Balanço Patrimonial'!K43+'Balanço Patrimonial'!K47+'Balanço Patrimonial'!K49+'Balanço Patrimonial'!K55)/('Balanço Patrimonial'!K43+'Balanço Patrimonial'!K47+'Balanço Patrimonial'!K49+'Balanço Patrimonial'!K55+'Balanço Patrimonial'!K56) -> 0.19259159 | L29: =('Balanço Patrimonial'!L43+'Balanço Patrimonial'!L47+'Balanço Patrimonial'!L49+'Balanço Patrimonial'!L55)/('Balanço Patrimonial'!L43+'Balanço Patrimonial'!L47+'Balanço Patrimonial'!L49+'Balanço Patrimonial'!L55+'Balanço Patrimonial'!L56) -> 0.51399042 | M29: =('Balanço Patrimonial'!M43+'Balanço Patrimonial'!M47+'Balanço Patrimonial'!M49+'Balanço Patrimonial'!M55)/('Balanço Patrimonial'!M43+'Balanço Patrimonial'!M47+'Balanço Patrimonial'!M49+'Balanço Patrimonial'!M55+'Balanço Patrimonial'!M56) -> 0.53463502 | ... O29: =('Balanço Patrimonial'!O43+'Balanço Patrimonial'!O47+'Balanço Patrimonial'!O49+'Balanço Patrimonial'!O55)/('Balanço Patrimonial'!O43+'Balanço Patrimonial'!O47+'Balanço Patrimonial'!O49+'Balanço Patrimonial'!O55+'Balanço Patrimonial'!O56) -> 0.52857433
F33: =G33-1 -> 2013 | G33: =H33-1 -> 2014 | H33: =I33-1 -> 2015 | I33: 2016 | J33: 2017 | K33: 2018 | L33: 2019 | M33: 2020 | N33: 2021 | O33: 2022
E34: Prazo Médio de Recebimento | F34: ='Balanço Patrimonial'!F19*365/'DRE + DCF'!F10 -> 21.076381 | G34: =AVERAGE('Balanço Patrimonial'!F19:G19)*365/'DRE + DCF'!G10 -> 20.399594 | H34: =AVERAGE('Balanço Patrimonial'!G19:H19)*365/'DRE + DCF'!H10 -> 21.29442 | I34: =AVERAGE('Balanço Patrimonial'!H19:I19)*365/'DRE + DCF'!I10 -> 21.202007 | J34: =AVERAGE('Balanço Patrimonial'!I19:J19)*365/'DRE + DCF'!J10 -> 22.427189 | K34: =AVERAGE('Balanço Patrimonial'!J19:K19)*365/'DRE + DCF'!K10 -> 23.805198 | L34: =AVERAGE('Balanço Patrimonial'!K19:L19)*365/'DRE + DCF'!L10 -> 24.9782 | M34: =AVERAGE('Balanço Patrimonial'!L19:M19)*365/'DRE + DCF'!M10 -> 28.002539 | N34: =AVERAGE('Balanço Patrimonial'!M19:N19)*365/'DRE + DCF'!N10 -> 27.207325 | O34: =AVERAGE('Balanço Patrimonial'!N19:O19)*365/'DRE + DCF'!O10 -> 26.908041
E35: Prazo Médio de Estoques | F35: ='Balanço Patrimonial'!F20*365/-'DRE + DCF'!F17 -> 91.608651 | G35: =AVERAGE('Balanço Patrimonial'!F20:G20)*365/-'DRE + DCF'!G17 -> 85.821436 | H35: =AVERAGE('Balanço Patrimonial'!G20:H20)*365/-'DRE + DCF'!H17 -> 88.587139 | I35: =AVERAGE('Balanço Patrimonial'!H20:I20)*365/-'DRE + DCF'!I17 -> 89.454055 | J35: =AVERAGE('Balanço Patrimonial'!I20:J20)*365/-'DRE + DCF'!J17 -> 92.334365 | K35: =AVERAGE('Balanço Patrimonial'!J20:K20)*365/-'DRE + DCF'!K17 -> 98.773291 | L35: =AVERAGE('Balanço Patrimonial'!K20:L20)*365/-'DRE + DCF'!L17 -> 102.39197 | M35: =AVERAGE('Balanço Patrimonial'!L20:M20)*365/-'DRE + DCF'!M17 -> 103.98177 | N35: =AVERAGE('Balanço Patrimonial'!M20:N20)*365/-'DRE + DCF'!N17 -> 100.77135 | O35: =AVERAGE('Balanço Patrimonial'!N20:O20)*365/-'DRE + DCF'!O17 -> 101.29393
E36: Prazo Médio de Pagamento | F36: =('Balanço Patrimonial'!F41+'Balanço Patrimonial'!F40)*365/-('DRE + DCF'!F17+'DRE + DCF'!F20+'DRE + DCF'!F44+'DRE + DCF'!F51) -> 48.536903 | G36: =(AVERAGE('Balanço Patrimonial'!F41:G41)+AVERAGE('Balanço Patrimonial'!F40:G40))*365/-('DRE + DCF'!G17+'DRE + DCF'!G20+'DRE + DCF'!G44+'DRE + DCF'!G51) -> 48.095103 | H36: =(AVERAGE('Balanço Patrimonial'!G41:H41)+AVERAGE('Balanço Patrimonial'!G40:H40))*365/-('DRE + DCF'!H17+'DRE + DCF'!H20+'DRE + DCF'!H44+'DRE + DCF'!H51) -> 53.565658 | I36: =(AVERAGE('Balanço Patrimonial'!H41:I41)+AVERAGE('Balanço Patrimonial'!H40:I40))*365/-('DRE + DCF'!I17+'DRE + DCF'!I20+'DRE + DCF'!I44+'DRE + DCF'!I51) -> 56.539699 | J36: =(AVERAGE('Balanço Patrimonial'!I41:J41)+AVERAGE('Balanço Patrimonial'!I40:J40))*365/-('DRE + DCF'!J17+'DRE + DCF'!J20+'DRE + DCF'!J44+'DRE + DCF'!J51) -> 57.90469 | K36: =(AVERAGE('Balanço Patrimonial'!J41:K41)+AVERAGE('Balanço Patrimonial'!J40:K40))*365/-('DRE + DCF'!K17+'DRE + DCF'!K20+'DRE + DCF'!K44+'DRE + DCF'!K51) -> 58.723776 | L36: =(AVERAGE('Balanço Patrimonial'!K41:L41)+AVERAGE('Balanço Patrimonial'!K40:L40))*365/-('DRE + DCF'!L17+'DRE + DCF'!L20+'DRE + DCF'!L44+'DRE + DCF'!L51) -> 63.10639 | M36: =(AVERAGE('Balanço Patrimonial'!L41:M41)+AVERAGE('Balanço Patrimonial'!L40:M40))*365/-('DRE + DCF'!M17+'DRE + DCF'!M20+'DRE + DCF'!M44+'DRE + DCF'!M51) -> 64.667446 | N36: =(AVERAGE('Balanço Patrimonial'!M41:N41)+AVERAGE('Balanço Patrimonial'!M40:N40))*365/-('DRE + DCF'!N17+'DRE + DCF'!N20+'DRE + DCF'!N44+'DRE + DCF'!N51) -> 63.804822 | O36: =(AVERAGE('Balanço Patrimonial'!N41:O41)+AVERAGE('Balanço Patrimonial'!N40:O40))*365/-('DRE + DCF'!O17+'DRE + DCF'!O20+'DRE + DCF'!O44+'DRE + DCF'!O51) -> 63.10738
E37: Ciclo de Caixa | F37: =F34+F35-F36 -> 64.148129 | G37: =G34+G35-G36 -> 58.125928 | H37: =H34+H35-H36 -> 56.3159 | I37: =I34+I35-I36 -> 54.116364 | J37: =J34+J35-J36 -> 56.856865 | K37: =K34+K35-K36 -> 63.854713 | L37: =L34+L35-L36 -> 64.263783 | M37: =M34+M35-M36 -> 67.316867 | ... O37: =O34+O35-O36 -> 65.094592
F41: =G41-1 -> 2013 | G41: =H41-1 -> 2014 | H41: =I41-1 -> 2015 | I41: 2016 | J41: 2017 | K41: 2018 | L41: 2019 | M41: 2020 | N41: 2021 | O41: 2022
E42: Proventos por ação | F42: 0.11774107 | G42: 0.22634735 | H42: 0.54423761 | I42: 0.5911879 | J42: 0.61417266 | K42: 0.63612183 | L42: 0.64160693 | M42: 0.12924154 | N42: 0.2221084 | O42: 1.2221084
E43: Dividend Yield (12 meses) | F43: 0.0077716875 | G43: 0.009053894 | H43: 0.015478885 | I43: 0.0097507489 | J43: 0.0067901897 | K43: 0.01121908 | L43: 0.0055874504 | M43: 0.0051634654 | N43: 0.0095530494 | O43: 0.0103
E44: Payout | F44: 0.38520572 | G44: 0 | H44: 0.52742124 | I44: 0.43171738 | J44: 0.39500403 | K44: 0.41133841 | L44: 0.2681635 | M44: 0.43019844 | N44: 0.47877527 | O44: 0.40759883

Sheet Provisões e Processos
M1: Remota | N1: Tributário
M2: Possível | N2: Cível
F3: Raia Drogasil ($RADL3) | M3: Provável | N3: Trabalhista
N4: Administrativo
A7: Páginas
A8: Dashboard
A9: WACC
A10: DRE + DCF | F10: Valor dos Processos | G10: Valor das Provisões | H10: Valor de Perdas Possiveis | I10: Valor de Perdas Remotas
A11: DRE - Contas Abertas | E11: Tributários | F11: 465400 | G11: 14342 | H11: 184619 | I11: =F11-G11-H11 -> 266439
A12: Balanço Patrimonial | E12: Cíveis | F12: 11500 | G12: 7673 | H12: 4266 | I12: =F12-G12-H12 -> -439
A13: Painel de Índices | E13: Trabalhistas | F13: 86000 | G13: 94267 | H13: 4868 | I13: =F13-G13-H13 -> -13135
A14: Provisões e Processos | E14: Administrativos | F14: 0 | G14: 0 | I14: =F14-G14-H14 -> 0
A15: Projeções - Receita | E15: Total | F15: =SUM(F11:F14) -> 562900 | G15: =SUM(G11:G14) -> 116282 | H15: =SUM(H11:H14) -> 193753 | I15: =SUM(I11:I14) -> 252865
A16: Projeções - Capex
A17: Projeções 2022
E19: Classificação | F19: Descrição | G19: Valor do Processo | H19: Chance de Perda | I19: Comentário
E20: Trabalhista | F20: Ação Cívil Pública: a. horas extras; b. registro de ponto; c. intervalos intra e interjornadas, d. DSR e folga aos domingos | G20: 1000 | H20: Possível | I20: Valor é estimado, o valor da causa é R$ 1 milhão, mas há diversas outras multas nesse processo
E21: Trabalhista | F21: Ação Cívil Pública: Revista de pertences de empregados e vigilância das áreas da loja | G21: 2000 | H21: Remota | I21: Valor é estimado, o valor da causa é R$ 2 milhão, mas há diversas outras multas nesse processo
E22: Tributário | F22: Autos de infração lavrados para a exigência de crédito tributário de Imposto sobre a Renda da Pessoa Jurídica (“IRPJ”) e da Contribuição Social sobre o Lucro Líquido (“CSLL”), relativo ao ano-calendário de 2013 cumulado com multa de ofício e juros de mora. | G22: 5004.6418 | H22: Possível | I22: -
E23: Tributário | F23: Autos de infração lavrados para exigência do Imposto sobre a Renda da Pessoa Jurídica (“IRPJ”) e da Contribuição Social sobre Lucros Líquidos (“CSLL”), relativos aos anos base de 2009 a 2012, cumulados com multa de ofício agravada e juros de mora. | G23: 10466.184 | H23: Possível | I23: A chance de perda do Principal é Possível e da Multa é Remota
E24: Tributário | F24: Autos de Infração lavrados para a exigência complementar de crédito tributário de Imposto Sobre a Renda da Pessoa Jurídica (“IRPJ”) e da Contribuição Social Sobre Lucro Líquido (“CSLL”) referente a 2011 e aos três primeiros trimestres de 2012 | G24: 10466.144 | H24: Possível | I24: A chance de perda do Principal é Possível e da Multa é Remota
E25: Tributário | F25: Autos de infração lavrados para cobrança de imposto de renda da pessoa jurídica (IRPJ) e da contribuição social sobre o lucro líquido (CSLL), relativos aos anos-base de 2014 a 2017 | G25: 12583.959 | H25: Possível | I25: Processo referente à Onofre
E26: Tributário | F26: A empresa foi autuada sob a alegação de não ter efetuado os recolhimentos do FINSOCIAL no período de janeiro a março de 1992 e da COFINS, no período de abril a dezembro de 1992, pela alíquota de 2% | G26: 3495.2395 | H26: Possível | I26: -
E27: Tributário | F27: Auto de Infração e Imposição de Multa por meio do qual se exige o recolhimento de ICMS no importe de R$ 3.978.563,09, acrescido de multa de ofício de 50% e juros de mora, em razão da não comprovação do direito de ressarcimento do ICMS retido a maior por substituição tributária, relativo aos períodos de apuração de abril, maio e junho de 2008 | G27: 18116.141 | H27: Remota | I27: -
E28: Tributário | F28: Anulação do auto de infração nº 4.046.508-1 que exige o recolhimento de ICMS no importe de R$ 802.825,58, acrescido de multa de mora, por suposta falta de recolhimento do tributo devido sob o regime de substituição tributária no período de apuração de 11/2013 a 01/2014. | G28: =2288.68498 -> 2288.685 | H28: Remota | I28: A RD está movendo esta ação contra o Estado de São Paulo
E29: Tributário | F29: Tutela antecipada antecedente objetivando a garantia do débito objeto do auto de infração n. 4.039.062-7. e no mérito a comprovação de sua invalidade. | G29: =4458.31356 -> 4458.3136 | H29: Remota | I29: A RD está movendo esta ação contra o Estado de São Paulo
E30: Tributário | F30: Auto de infração lavrado com a exigência de ICMS, juros e multa, por suposto creditamento indevido nos períodos de 02/2013, 03/2013, 08/2013, 09/2013 e 11/2013, assim como por supostas incorreções na escrituração para o período de 01/2013 a 12/2013 e suposto crédito em duplicidade em 11/2013 | G30: =30521.38235 -> 30521.382 | H30: Remota | I30: -
E31: Tributário | F31: Suposta irregularidade consubstanciada na falta de recolhimento do ICMS relativo a substituição tributária quanto às mercadorias (entradas) constantes no relatório denominado "Levantamento Físico - resumo" cujo valor teria sido obtido após levantamento físico quantitativo realizado no exercício de 2013. | G31: 2568.2589 | H31: Remota | I31: -
E32: Tributário | F32: Notificação apontando suposto débito de ICMS relativo a substituição tributária quanto às mercadorias (entradas) constantes no relatório denominado “Levantamento Físico – Resumo.pdf”, cujo valor teria sido obtido após levantamento físico quantitativo realizado nos exercícios de 2011 e 2012. | G32: =2735.8431 -> 2735.8431 | H32: Remota | I32: -
E33: Tributário | F33: Trata-se de notificação apontando suposto débito de ICMS relativo a substituição tributária quanto às mercadorias (entradas) constantes no relatório denominado “Levantamento Físico – Resumo.pdf”, cujo valor teria sido obtido após levantamento físico quantitativo realizado nos exercícios de 2011 e 2012 | G33: =1792.95272 -> 1792.9527 | H33: Remota | I33: -
E34: Tributário | F34: Execução Fiscal do crédito tributário objeto Auto de Infração PTA 01.000198561- 20, lavrado por ter a empresa, supostamente, deixado de reter ou retido a menor o ICMS devido por substituição tributária, em operações de transferência de mercadorias para filiais mineiras, ocorridas nos anos de 2009, 2010 e 2011. | G34: 7598.0705 | H34: Possível | I34: -
E35: Trabalhista | F35: a) Reajuste salarial e diferenças salarias; b) Aplicação dos benefícios sociais (inclusive o vale refeição); c) Multa convencional e d) Pagamento de indenização aos funcionários ofendidos. | G35: 1000 | H35: Provável | I35: -
E36: Trabalhista | F36: a. Adicional de 40% para Gerentes; b. Multa convencional; c. Honorários de sucumbência | G36: 963.06703 | H36: Provável | I36: -
E37: Trabalhista | F37: a) Adicional de insalubridade por aplicação de injetáveis, b) multa convencional e c) honorários advocatícios | G37: 906.55998 | H37: Provável
E38: Trabalhista | F38: a) Ajuda de custo do plano de saúde; b) Vale alimentação c) Pagamento em dobro pelos feriados trabalhados sem folga compensatória e d) Multa normativa | G38: 575.05396 | H38: Provável
E39: Trabalhista | F39: a) Horas extras (acima da 8ª hora diária e 4ª hora aos sábados; b) Feriados trabalhados e não autorizados pelo sindicato, com ausência do pagamento do adicional de 100% | G39: 391.89098 | H39: Provável
E40: Trabalhista | F40: Descumprimento de cláusulas convencionais relacionadas a: a) Auxilio alimentação e b) Multa normativa | G40: 387.48566 | H40: Provável
E41: Trabalhista | F41: a) HE (sobrejornada, intrajornada, domingos e feriados); b) danos morais e materiais decorrentes do acidente de trabalho fatal (dia 21/01/2015, durante o expediente de trabalho e enquanto o funcionário dirigia o caminhão da empresa); c) auxilio refeição; d) PLR; e) auxilio funeral; f) multa da CCT e g) verbas rescisórias. | G41: 873.87111 | H41: Provável | I41: -
E42: Trabalhista | F42: a) horas extras; b) acumulo de função; c) equiparação de função e por grupo econômico; d) salário substituição;; e) gratificação de função; f) adicional de insalubridade; g) restituição de descontos salariais (contribuição assistencial e confederativa, entre outros); g) indenização de diferença do benefício previdenciário; h) doença ocupacional - caracterização, danos morais e demais verbas; i) diferenças de verbas rescisórias - data base; j) Diferenças de PPR; k) aplicação das multas dos artigos 467 e 477 da CLT; l) Auxilio Alimentação; m) Danos Morais - salario a menor; n) multas convencionais; | G42: 765.21689 | H42: Provável
E43: Trabalhista | F43: a) horas extras (sobrejornada, intrajornada e feriados); b) Comissões; c) Prêmios; d) Doença ocupacional decorrente da atividade de esteticista (estabilidade/reintegração, danos materiais e morais); d) Devolução de descontos indevidos; e) Auxilio alimentação; f) Multa normativa; g) Acumulo de função; h) danos morais (suposta revista íntima) | G43: 904.56525 | H43: Provável
E44: Trabalhista | F44: a) Reconhecimento da função de gerente e pagamento das diferenças salariais correspondentes ou, subsidiariamente, diferenças por equiparação salarial devido ao efetivo cargo de gerente; b) Integração do salário supostamente “pago por fora” nas demais verbas; c) Diferenças de comissões; d) Retificação CTPS para o cargo de Gerente de Perfumaria; e) Horas extras (sobrejornada e intervalares); f) Indenização por danos morais; g) Devolução de descontos indevidos; h) Vale alimentação e i) multa normativa. | G44: 2302.6751 | H44: Provável

Sheet Projeções - Receita
M3: Raia Drogasil ($RADL3)
A7: Páginas
A8: Dashboard
A9: WACC | F9: =G9-1 -> 2013 | G9: =H9-1 -> 2014 | H9: =I9-1 -> 2015 | I9: 2016 | J9: 2017 | K9: 2018 | L9: 2019 | M9: 2020 | N9: 2021 | O9: =N9+1 -> 2022 | P9: =O9+1 -> 2023 | Q9: =P9+1 -> 2024 | R9: =Q9+1 -> 2025 | S9: =R9+1 -> 2026 | T9: =S9+1 -> 2027 | U9: =T9+1 -> 2028 | V9: =U9+1 -> 2029 | ... BA9: =AZ9+1 -> 2060 | BB9: CAGR 2013-2022 | BC9: Racional | BD9: Premissa | BE9: Nível de Otimismo (0-5)
A10: DRE + DCF | E10: Total de Lojas ao Fim do Ano | F10: =SUM(F11:F15) -> 970 | G10: =SUM(G11:G15) -> 1094 | H10: =SUM(H11:H15) -> 1235 | I10: =SUM(I11:I15) -> 1420 | J10: =SUM(J11:J15) -> 1610 | K10: =SUM(K11:K15) -> 1825 | L10: =SUM(L11:L15) -> 2073 | M10: =SUM(M11:M15) -> 2303 | ... X10: =SUM(X11:X15) -> 4444.8693 | BB10: =(O10/F10)^(1/COUNT($G$9:$O$9))-1 -> 0.11899691
A11: DRE - Contas Abertas | E11: Maduras | F11: 546 | G11: 646 | H11: 728 | I11: 801 | J11: 912 | K11: 1024 | L11: 1151 | M11: 1347 | N11: =M11+M12-N16 -> 1478 | O11: =N11+N12-O16 -> 1662 | P11: =O11+O12-P16 -> 1880.8825 | Q11: =P11+P12-Q16 -> 2068.5189 | R11: =Q11+Q12-R16 -> 2252.9876 | S11: =R11+R12-S16 -> 2453.78 | T11: =S11+S12-T16 -> 2650.9621 | U11: =T11+T12-U16 -> 2844.5989 | ... X11: =W11+W12-X16 -> 3404.8693 | BB11: =(O11/F11)^(1/COUNT($G$9:$O$9))-1 -> 0.13165846 | BC11: Maturação de acordo com curva de maturação fornecida pela RD
A12: Balanço Patrimonial | E12: Estágio 4 | F12: 106 | G12: =F13 -> 93 | H12: =G13 -> 94 | I12: =H13 -> 128 | J12: =I13 -> 126 | K12: =J13 -> 153 | L12: =K13 -> 204 | M12: =L13 -> 199 | N12: 237 | O12: =N13 -> 266.858 | P12: =O13 -> 239.424 | Q12: =P13 -> 240 | R12: =Q13 -> 260 | S12: =R13 -> 260 | T12: =S13 -> 260 | U12: =T13 -> 260 | V12: =U13 -> 260 | ... X12: =W13 -> 260 | BB12: =(O12/F12)^(1/COUNT($G$9:$O$9))-1 -> 0.10803303 | BC12: Maturação de acordo com curva de maturação fornecida pela RD
A13: Painel de Índices | E13: Estágio 3 | F13: 93 | G13: 94 | H13: 128 | I13: 126 | J13: 153 | K13: 204 | L13: 199 | M13: 237 | N13: 266.858 | O13: =N14 -> 239.424 | P13: =O14 -> 240 | Q13: =P14 -> 260 | R13: =Q14 -> 260 | S13: =R14 -> 260 | T13: =S14 -> 260 | U13: =T14 -> 260 | V13: =U14 -> 260 | ... X13: =W14 -> 260 | BB13: =(O13/F13)^(1/COUNT($G$9:$O$9))-1 -> 0.11078917 | BC13: Maturação de acordo com curva de maturação fornecida pela RD
A14: Provisões e Processos | E14: Estágio 2 | F14: 95 | G14: 130 | H14: 129 | I14: 152 | J14: 210 | K14: 204 | L14: 237 | M14: 280 | N14: 239.424 | O14: =N15 -> 240 | P14: =O15 -> 260 | Q14: =P15 -> 260 | R14: =Q15 -> 260 | S14: =R15 -> 260 | T14: =S15 -> 260 | U14: =T15 -> 260 | V14: =U15 -> 260 | ... X14: =W15 -> 260 | BB14: =(O14/F14)^(1/COUNT($G$9:$O$9))-1 -> 0.1084621 | BC14: Maturação de acordo com curva de maturação fornecida pela RD
A15: Projeções - Receita | E15: Novas Lojas | F15: 130 | G15: 131 | H15: 156 | I15: 213 | J15: 209 | K15: 240 | L15: 282 | M15: 240 | N15: 240 | O15: 260 | P15: 260 | Q15: 260 | R15: 260 | S15: 260 | T15: 260 | U15: 260 | V15: 260 | W15: 260 | X15: 260 | BB15: =(O15/F15)^(1/COUNT($G$9:$O$9))-1 -> 0.080059739 | BC15: 260 lojas até 2031 | BE15: 4
A16: Projeções - Capex | E16: Fechamento de Lojas | F16: 28 | G16: 7 | H16: 15 | I16: 27 | J16: 20 | K16: 25 | L16: 34 | M16: 11 | N16: 68 | O16: 53 | P16: =P17*O10 -> 47.975472 | Q16: =Q17*P10 -> 51.787654 | R16: =R17*Q10 -> 55.531293 | S16: =S17*R10 -> 59.207622 | T16: =T17*S10 -> 62.817851 | U16: =U17*T10 -> 66.363169 | V16: =V17*U10 -> 69.844742 | W16: =W17*V10 -> 73.263716 | X16: =X17*W10 -> 76.621218 | BB16: =(O16/F16)^(1/COUNT($G$9:$O$9))-1 -> 0.073472371 | BD16: As lojas fechadas são lojas maduras
A17: Projeções 2022 | E17: % de Fechamento | F17: 0.0324 | G17: =G16/F10 -> 0.0072164948 | H17: =H16/G10 -> 0.013711152 | I17: =I16/H10 -> 0.021862348 | J17: =J16/I10 -> 0.014084507 | K17: =K16/J10 -> 0.01552795 | L17: =L16/K10 -> 0.018630137 | M17: =M16/L10 -> 0.0053063193 | N17: =N16/M10 -> 0.029526704 | O17: =O16/N10 -> 0.021533494 | P17: =AVERAGE($F$17:$O$17) -> 0.017979911 | Q17: =AVERAGE($F$17:$O$17) -> 0.017979911 | R17: =AVERAGE($F$17:$O$17) -> 0.017979911 | S17: =AVERAGE($F$17:$O$17) -> 0.017979911 | T17: =AVERAGE($F$17:$O$17) -> 0.017979911 | U17: =AVERAGE($F$17:$O$17) -> 0.017979911 | V17: =AVERAGE($F$17:$O$17) -> 0.017979911 | W17: =AVERAGE($F$17:$O$17) -> 0.017979911 | X17: =AVERAGE($F$17:$O$17) -> 0.017979911 | BC17: A RD vai fechar o mesmo % de suas lojas todo ano | BD17: A RD vai manter a média histórica de % de fechamento de lojas entre 2013 e 2021 | BE17: 2
F21: =G21-1 -> 2013 | G21: =H21-1 -> 2014 | H21: =I21-1 -> 2015 | I21: 2016 | J21: 2017 | K21: 2018 | L21: 2019 | M21: 2020 | N21: 2021 | O21: =N21+1 -> 2022 | P21: =O21+1 -> 2023 | Q21: =P21+1 -> 2024 | R21: =Q21+1 -> 2025 | S21: =R21+1 -> 2026 | T21: =S21+1 -> 2027 | U21: =T21+1 -> 2028 | V21: =U21+1 -> 2029 | ... BA21: =AZ21+1 -> 2060 | BB21: CAGR 2013-2022 | BC21: Racional | BD21: Premissa | BE21: Nível de Otimismo (0-5)
E22: Receita Líquida Total | F22: ='DRE + DCF'!F15 -> 6232919 | G22: ='DRE + DCF'!G15 -> 7391569 | H22: ='DRE + DCF'!H15 -> 8897849 | I22: ='DRE + DCF'!I15 -> 11256565 | J22: ='DRE + DCF'!J15 -> 13212505 | K22: ='DRE + DCF'!K15 -> 14801445 | L22: ='DRE + DCF'!L15 -> 17565600 | M22: ='DRE + DCF'!M15 -> 20066840 | ... O22: ='DRE + DCF'!O15 -> 29067380 | P22: =SUMPRODUCT(P11:P15,'Projeções - Receita'!$I$70:$I$74)*'Projeções - Receita'!P23*(1+(P66-$O$66)) -> 33449541 | Q22: =SUMPRODUCT(Q11:Q15,'Projeções - Receita'!$I$70:$I$74)*'Projeções - Receita'!Q23*(1+(Q66-$O$66)) -> 37882634 | R22: =SUMPRODUCT(R11:R15,'Projeções - Receita'!$I$70:$I$74)*'Projeções - Receita'!R23*(1+(R66-$O$66)) -> 43302702 | S22: =SUMPRODUCT(S11:S15,'Projeções - Receita'!$I$70:$I$74)*'Projeções - Receita'!S23*(1+(S66-$O$66)) -> 49095679 | T22: =SUMPRODUCT(T11:T15,'Projeções - Receita'!$I$70:$I$74)*'Projeções - Receita'!T23*(1+(T66-$O$66)) -> 55616250 | U22: =SUMPRODUCT(U11:U15,'Projeções - Receita'!$I$70:$I$74)*'Projeções - Receita'!U23*(1+(U66-$O$66)) -> 62622077 | V22: =SUMPRODUCT(V11:V15,'Projeções - Receita'!$I$70:$I$74)*'Projeções - Receita'!V23*(1+(V66-$O$66)) -> 70543239 | W22: =SUMPRODUCT(W11:W15,'Projeções - Receita'!$I$70:$I$74)*'Projeções - Receita'!W23*(1+(W66-$O$66)) -> 79175286 | X22: =SUMPRODUCT(X11:X15,'Projeções - Receita'!$I$70:$I$74)*'Projeções - Receita'!X23*(1+(X66-$O$66)) -> 88024595 | Y22: =Y26*Y25*(1+(Y66-$O$66)) -> 96515903 | Z22: =Z26*Z25*(1+(Z66-$O$66)) -> 1.0522941e+08 | AA22: =AA26*AA25*(1+(AA66-$O$66)) -> 1.1548401e+08 | AB22: =AB26*AB25*(1+(AB66-$O$66)) -> 1.2670863e+08 | AC22: =AC26*AC25*(1+(AC66-$O$66)) -> 1.3897804e+08 | AD22: =AD26*AD25*(1+(AD66-$O$66)) -> 1.5238489e+08 | AE22: =AE26*AE25*(1+(AE66-$O$66)) -> 1.6703294e+08 | AF22: =AF26*AF25*(1+(AF66-$O$66)) -> 1.8301137e+08 | ... BA22: =BA26*BA25*(1+(BA66-$O$66)) -> 1.1232524e+09 | BB22: =(O22/F22)^(1/COUNT($G$9:$O$9))-1 -> 0.1865925
E23: Receita Líquida de uma loja madura | F23: =F22/SUMPRODUCT(F11:F15,'Projeções - Receita'!I$70:I$74) -> 7285.7031 | G23: =G22/SUMPRODUCT(G11:G15,'Projeções - Receita'!$I$70:$I$74) -> 7631.9763 | H23: =H22/SUMPRODUCT(H11:H15,'Projeções - Receita'!$I$70:$I$74) -> 8152.0206 | I23: =I22/SUMPRODUCT(I11:I15,'Projeções - Receita'!$I$70:$I$74) -> 9079.0465 | J23: =J22/SUMPRODUCT(J11:J15,'Projeções - Receita'!$I$70:$I$74) -> 9374.8927 | K23: =K22/SUMPRODUCT(K11:K15,'Projeções - Receita'!$I$70:$I$74) -> 9245.3559 | L23: =L22/SUMPRODUCT(L11:L15,'Projeções - Receita'!$I$70:$I$74) -> 9669.8118 | M23: =M22/SUMPRODUCT(M11:M15,'Projeções - Receita'!$I$70:$I$74) -> 9798.5009 | N23: =N22/SUMPRODUCT(N11:N15,'Projeções - Receita'!$I$70:$I$74) -> 10906.266 | O23: =O22/SUMPRODUCT(O11:O15,'Projeções - Receita'!$I$70:$I$74) -> 12048.627 | P23: =O23*(1+$BB$23*P$58/$BB$59) -> 12814.566 | Q23: =P23*(1+$BB$23*Q$58/$BB$59) -> 13460.497 | R23: =Q23*(1+$BB$23*R$58/$BB$59) -> 14351.374 | S23: =R23*(1+$BB$23*S$58/$BB$59) -> 15259.335 | T23: =S23*(1+$BB$23*T$58/$BB$59) -> 16291.024 | U23: =T23*(1+$BB$23*U$58/$BB$59) -> 17361.806 | V23: =U23*(1+$BB$23*V$58/$BB$59) -> 18581.687 | W23: =V23*(1+$BB$23*W$58/$BB$59) -> 19880.92 | X23: =W23*(1+$BB$23*X$58/$BB$59) -> 21133.236 | BB23: =(O23/F23)^(1/COUNT($G$9:$O$9))-1 -> 0.057484499 | BC23: O crescimento vai ser fruto uma regra de 3 entre o CAGR de 2013 a 2022 da Receita por Loja Madura, o CAGR de inflação desse mesmo período e a inflação projetada pro ano que estamos calculando | BD23: O crescimento da Receita Líquida de uma loja madura vai continuar de acordo com o histórico. Não haverá ganhos com omnicanalidade, Nova Farmácia e aplicativos | BE23: 3
E24: Crescimento das Lojas Maduras | F24: n/a | G24: =G23/F23-1 -> 0.047527761 | H24: =H23/G23-1 -> 0.068140199 | I24: =I23/H23-1 -> 0.11371731 | J24: =J23/I23-1 -> 0.032585602 | K24: =K23/J23-1 -> -0.013817414 | L24: =L23/K23-1 -> 0.045910177 | M24: =M23/L23-1 -> 0.013308335 | N24: =N23/M23-1 -> 0.11305455 | ... X24: =X23/W23-1 -> 0.06299084
E25: Market Share | F25: 0.094 | G25: 0.097 | H25: 0.103 | I25: 0.115 | J25: 0.12 | K25: 0.124 | L25: 0.137 | M25: 0.139 | N25: 0.142 | O25: =15.1% -> 0.151 | P25: =P22/P26 -> 0.16019752 | Q25: =Q22/Q26 -> 0.16444128 | R25: =R22/R26 -> 0.17249116 | S25: =S22/S26 -> 0.17673485 | T25: =T22/T26 -> 0.18151157 | U25: =U22/U26 -> 0.18456729 | V25: =V22/V26 -> 0.18819119 | W25: =W22/W26 -> 0.19042687 | X25: =X22/X26 -> 0.19101779 | Y25: =X25 -> 0.19101779 | Z25: =Y25 -> 0.19101779 | AA25: =Z25 -> 0.19101779 | AB25: =AA25 -> 0.19101779 | AC25: =AB25 -> 0.19101779 | AD25: =AC25 -> 0.19101779 | AE25: =AD25 -> 0.19101779 | AF25: =AE25 -> 0.19101779 | ... BA25: =AZ25 -> 0.19101779 | BC25: Market Share fixo a partir de 2031 | BD25: A empresa baterá no teto de market share daqui a dez anos | BE25: 3
E26: Tamanho do Mercado | F26: =F22/F25 -> 66307649 | G26: =G22/G25 -> 76201742 | H26: =H22/H25 -> 86386883 | I26: =I22/I25 -> 97883174 | J26: =J22/J25 -> 1.1010421e+08 | K26: =K22/K25 -> 1.1936649e+08 | L26: =L22/L25 -> 1.2821606e+08 | M26: =M22/M25 -> 1.4436576e+08 | ... O26: =O22/O25 -> 1.9249921e+08 | P26: =P51*P56/1000 -> 2.0880186e+08 | Q26: =Q51*Q56/1000 -> 2.3037181e+08 | R26: =R51*R56/1000 -> 2.5104302e+08 | S26: =S51*S56/1000 -> 2.7779285e+08 | T26: =T51*T56/1000 -> 3.0640609e+08 | U26: =U51*U56/1000 -> 3.392913e+08 | V26: =V51*V56/1000 -> 3.7484878e+08 | W26: =W51*W56/1000 -> 4.157779e+08 | ... BA26: =BA51*BA56/1000 -> 5.9259924e+09 | BB26: =(O26/F26)^(1/COUNT($G$9:$O$9))-1 -> 0.12571766 | BC26: Tamanho do Mercado calculado a partir da quantidade de pessoas em cada faixa etária e do gasto relativo entre faixas etárias. Até 2021 é calculado dividindo a Receita Líquida da RD pelo seu Market Share | BD26: O catalisador do crescimento do setor vai ser o envelhecimento populacional | BE26: 3
E27: Crescimento do Mercado | F27: na | G27: =G26/F26-1 -> 0.14921496 | H27: =H26/G26-1 -> 0.13366021 | I27: =I26/H26-1 -> 0.13307912 | J27: =J26/I26-1 -> 0.12485327 | K27: =K26/J26-1 -> 0.084122885 | L27: =L26/K26-1 -> 0.074137778 | M27: =M26/L26-1 -> 0.1259569 | N27: =N26/M26-1 -> 0.17693053 | ... BA27: =BA26/AZ26-1 -> 0.085499962
F31: =G31-1 -> 2013 | G31: =H31-1 -> 2014 | H31: =I31-1 -> 2015 | I31: 2016 | J31: 2017 | K31: 2018 | L31: 2019 | M31: 2020 | N31: 2021 | O31: =N31+1 -> 2022 | P31: =O31+1 -> 2023 | Q31: =P31+1 -> 2024 | R31: =Q31+1 -> 2025 | S31: =R31+1 -> 2026 | T31: =S31+1 -> 2027 | U31: =T31+1 -> 2028 | V31: =U31+1 -> 2029 | ... BA31: =AZ31+1 -> 2060 | BB31: CAGR 2013-2022 | BC31: Racional | BD31: Fonte
E32: < 20 | F32: 63668449 | G32: 63155784 | H32: 62676386 | I32: 62112859 | J32: 61500942 | K32: 60947256 | L32: 60429604 | M32: 59976963 | N32: 59569226 | O32: 59266403 | P32: 58989621 | Q32: 58717054 | R32: 58428570 | S32: 58150169 | T32: 57920778 | U32: 57686808 | V32: 57445508 | W32: 57221126 | X32: 56962970 | Y32: 56668546 | Z32: 56356837 | AA32: 55982588 | AB32: 55525986 | AC32: 55108663 | AD32: 54692729 | AE32: 54204578 | AF32: 53714348 | AG32: 53224403 | AH32: 52737405 | AI32: 52257663 | AJ32: 51789288 | AK32: 51333515 | AL32: 50891236 | AM32: 50462987 | AN32: 50049337 | AO32: 49650769 | AP32: 49265966 | AQ32: 48892595 | AR32: 48529931 | AS32: 48178255 | AT32: 47835734 | AU32: 47499658 | AV32: 47167612 | AW32: 46838636 | AX32: 46512574 | AY32: 46187580 | AZ32: 45862027 | BA32: 45534890 | BB32: =(O32/F32)^(1/COUNT($G$9:$O$9))-1 -> -0.0079291249 | BC32: Número de Pessoas com menos de 20 anos | BD32: IBGE
E33: 20-29 | F33: 34632096 | G33: 34516131 | H33: 34432620 | I33: 34379203 | J33: 34365199 | K33: 34363373 | L33: 34324757 | M33: 34219132 | N33: 34069012 | O33: 33819144 | P33: 33529754 | Q33: 33195956 | R33: 32823772 | S33: 32391171 | T33: 31855371 | U33: 31300728 | V33: 30778269 | W33: 30295466 | X33: 29885083 | Y33: 29611803 | Z33: 29382523 | AA33: 29222922 | AB33: 29134898 | AC33: 29023585 | AD33: 28965811 | AE33: 28983683 | AF33: 29004640 | AG33: 29049807 | AH33: 29066935 | AI33: 29050739 | AJ33: 29016159 | AK33: 28916143 | AL33: 28728907 | AM33: 28573969 | AN33: 28413370 | AO33: 28172729 | AP33: 27921097 | AQ33: 27661367 | AR33: 27395712 | AS33: 27126918 | AT33: 26858786 | AU33: 26593791 | AV33: 26334064 | AW33: 26080578 | AX33: 25833790 | AY33: 25595279 | AZ33: 25365447 | BA33: 25143734 | BB33: =(O33/F33)^(1/COUNT($G$9:$O$9))-1 -> -0.0026358367 | BC33: Número de Pessoas entre 20 e 29 anos | BD33: IBGE
E34: 30-39 | F34: 31889434 | G34: 32470602 | H34: 32966477 | I34: 33379591 | J34: 33709762 | K34: 33958624 | L34: 34130660 | M34: 34231961 | N34: 34259369 | O34: 34206034 | P34: 34103867 | Q34: 34002064 | R34: 33931127 | S34: 33888592 | T34: 33881086 | U34: 33881881 | V34: 33846336 | W34: 33745687 | X34: 33602329 | Y34: 33361487 | Z34: 33082558 | AA34: 32760222 | AB34: 32399687 | AC34: 31979112 | AD34: 31456354 | AE34: 30914742 | AF34: 30404718 | AG34: 29933581 | AH34: 29533714 | AI34: 29269203 | AJ34: 29048194 | AK34: 28895868 | AL34: 28814233 | AM34: 28709421 | AN34: 28657232 | AO34: 28679614 | AP34: 28704731 | AQ34: 28753330 | AR34: 28773938 | AS34: 28761197 | AT34: 28730003 | AU34: 28633830 | AV34: 28451267 | AW34: 28300388 | AX34: 28143755 | AY34: 27907856 | AZ34: 27660951 | BA34: 27405885 | BB34: =(O34/F34)^(1/COUNT($G$9:$O$9))-1 -> 0.0078223615 | BC34: Número de Pessoas entre 30 e 39 anos | BD34: IBGE
E35: 40-49 | F35: 26135110 | G35: 26452554 | H35: 26817881 | I35: 27225236 | J35: 27671879 | K35: 28160322 | L35: 28689589 | M35: 29255478 | N35: 29854837 | O35: 30488714 | P35: 31122631 | Q35: 31706146 | R35: 32206017 | S35: 32624401 | T35: 32959248 | U35: 33211598 | V35: 33388260 | W35: 33496182 | X35: 33532266 | Y35: 33489793 | Z35: 33400099 | AA35: 33311028 | AB35: 33251938 | AC35: 33220328 | AD35: 33222747 | AE35: 33232808 | AF35: 33206427 | AG35: 33115349 | AH35: 32981719 | AI35: 32751280 | AJ35: 32482719 | AK35: 32171354 | AL35: 31822586 | AM35: 31414749 | AN35: 30906579 | AO35: 30380075 | AP35: 29884643 | AQ35: 29427199 | AR35: 29039549 | AS35: 28784685 | AT35: 28572603 | AU35: 28428159 | AV35: 28353434 | AW35: 28255573 | AX35: 28208896 | AY35: 28235539 | AZ35: 28264372 | BA35: 28315644 | BB35: =(O35/F35)^(1/COUNT($G$9:$O$9))-1 -> 0.017267044 | BC35: Número de Pessoas entre 40 e 49 anos | BD35: IBGE
E36: 50-59 | F36: 20431139 | G36: 20999638 | H36: 21543967 | I36: 22065249 | J36: 22566087 | K36: 23040023 | L36: 23477440 | M36: 23875081 | N36: 24234960 | O36: 24554480 | P36: 24858410 | Q36: 25184028 | R36: 25555533 | S36: 25967200 | T36: 26415495 | U36: 26902321 | V36: 27427457 | W36: 27987154 | X36: 28578374 | Y36: 29202067 | Z36: 29825362 | AA36: 30399863 | AB36: 30893619 | AC36: 31308739 | AD36: 31643337 | AE36: 31898364 | AF36: 32080322 | AG36: 32195833 | AH36: 32241985 | AI36: 32212227 | AJ36: 32136945 | AK36: 32062295 | AL36: 32016505 | AM36: 31997056 | AN36: 32010164 | AO36: 32030082 | AP36: 32013579 | AQ36: 31933140 | AR36: 31810624 | AS36: 31592658 | AT36: 31337074 | AU36: 31040310 | AV36: 30708167 | AW36: 30319445 | AX36: 29834288 | AY36: 29332299 | AZ36: 28860643 | BA36: 28425248 | BB36: =(O36/F36)^(1/COUNT($G$9:$O$9))-1 -> 0.020636057 | BC36: Número de Pessoas entre 50 e 59 anos | BD36: IBGE
E37: 60-69 | F37: 12945225 | G37: 13467240 | H37: 13997470 | I37: 14534648 | J37: 15075632 | K37: 15621201 | L37: 16173590 | M37: 16732972 | N37: 17295908 | O37: 17860444 | P37: 18419294 | Q37: 18962399 | R37: 19483118 | S37: 19982459 | T37: 20462533 | U37: 20917236 | V37: 21338214 | W37: 21722494 | X37: 22072181 | Y37: 22384973 | Z37: 22683935 | AA37: 23003541 | AB37: 23366030 | AC37: 23766050 | AD37: 24200406 | AE37: 24670327 | AF37: 25174730 | AG37: 25709553 | AH37: 26271781 | AI37: 26862098 | AJ37: 27450279 | AK37: 27992225 | AL37: 28459010 | AM37: 28852689 | AN37: 29171691 | AO37: 29417024 | AP37: 29594679 | AQ37: 29710802 | AR37: 29762867 | AS37: 29744806 | AT37: 29685073 | AU37: 29626640 | AV37: 29595494 | AW37: 29589014 | AX37: 29612798 | AY37: 29642107 | AZ37: 29635759 | BA37: 29567496 | BB37: =(O37/F37)^(1/COUNT($G$9:$O$9))-1 -> 0.036409548 | BC37: Número de Pessoas entre 60 e 69 anos | BD37: IBGE
E38: 70+ | F38: 10302735 | G38: 10655592 | H38: 11040882 | I38: 11459801 | J38: 11915240 | K38: 12404101 | L38: 12921485 | M38: 13464105 | N38: 14034327 | O38: 14633321 | P38: 15260692 | Q38: 15916815 | R38: 16600956 | S38: 17312538 | T38: 18050723 | U38: 18813097 | V38: 19597261 | W38: 20400353 | X38: 21221212 | Y38: 22059133 | Z38: 22907267 | AA38: 23756958 | AB38: 24601527 | AC38: 25441355 | AD38: 26277678 | AE38: 27103369 | AF38: 27909465 | AG38: 28691396 | AH38: 29450694 | AI38: 30185370 | AJ38: 30910481 | AK38: 31649596 | AL38: 32417148 | AM38: 33209386 | AN38: 34025297 | AO38: 34860189 | AP38: 35705769 | AQ38: 36554843 | AR38: 37406548 | AS38: 38260348 | AT38: 39103175 | AU38: 39917244 | AV38: 40690285 | AW38: 41421589 | AX38: 42109584 | AY38: 42751626 | AZ38: 43346342 | BA38: 43893450 | BB38: =(O38/F38)^(1/COUNT($G$9:$O$9))-1 -> 0.039757983 | BC38: Número de Pessoas com mais de 70 anos | BD38: IBGE
E39: Total Brasil | F39: =SUM(F32:F38) -> 200004188 | G39: =SUM(G32:G38) -> 201717541 | H39: =SUM(H32:H38) -> 203475683 | I39: =SUM(I32:I38) -> 205156587 | J39: =SUM(J32:J38) -> 206804741 | K39: =SUM(K32:K38) -> 208494900 | L39: =SUM(L32:L38) -> 210147125 | M39: =SUM(M32:M38) -> 211755692 | ... BA39: =SUM(BA32:BA38) -> 228286347 | BB39: =(O39/F39)^(1/COUNT($G$9:$O$9))-1 -> 0.0079762998 | BC39: População Brasileira | BD39: IBGE
AQ40: =SUM(AQ37:AQ38) -> 66265645 | AR40: =AQ40/AQ39 -> 0.28448338
F43: =G43-1 -> 2013 | G43: =H43-1 -> 2014 | H43: =I43-1 -> 2015 | I43: 2016 | J43: 2017 | K43: 2018 | L43: 2019 | M43: 2020 | N43: 2021 | O43: =N43+1 -> 2022 | P43: =O43+1 -> 2023 | Q43: =P43+1 -> 2024 | R43: =Q43+1 -> 2025 | S43: =R43+1 -> 2026 | T43: =S43+1 -> 2027 | U43: =T43+1 -> 2028 | V43: =U43+1 -> 2029 | ... BA43: =AZ43+1 -> 2060 | BB43: CAGR 2013-2022 | BC43: Racional | BD43: Premissa
E44: < 20 | F44: =F32*'Projeções - Receita'!$F70 -> 14406125 | G44: =G32*'Projeções - Receita'!$F70 -> 14290125 | H44: =H32*'Projeções - Receita'!$F70 -> 14181653 | I44: =I32*'Projeções - Receita'!$F70 -> 14054145 | J44: =J32*'Projeções - Receita'!$F70 -> 13915688 | K44: =K32*'Projeções - Receita'!$F70 -> 13790406 | L44: =L32*'Projeções - Receita'!$F70 -> 13673278 | M44: =M32*'Projeções - Receita'!$F70 -> 13570860 | ... BA44: =BA32*'Projeções - Receita'!$F70 -> 10303083 | BB44: =(O44/F44)^(1/COUNT($G$9:$O$9))-1 -> -0.0079291249 | BC44: Multiplicação do Número de Pessoas desta Faixa Etária pela maturação do consumidor nessa faixa etária
E45: 20-29 | F45: =F33*'Projeções - Receita'!$F71 -> 10117916 | G45: =G33*'Projeções - Receita'!$F71 -> 10084037 | H45: =H33*'Projeções - Receita'!$F71 -> 10059638 | I45: =I33*'Projeções - Receita'!$F71 -> 10044032 | J45: =J33*'Projeções - Receita'!$F71 -> 10039941 | K45: =K33*'Projeções - Receita'!$F71 -> 10039408 | L45: =L33*'Projeções - Receita'!$F71 -> 10028126 | M45: =M33*'Projeções - Receita'!$F71 -> 9997267 | ... BA45: =BA33*'Projeções - Receita'!$F71 -> 7345850.3 | BB45: =(O45/F45)^(1/COUNT($G$9:$O$9))-1 -> -0.0026358367 | BC45: Multiplicação do Número de Pessoas desta Faixa Etária pela maturação do consumidor nessa faixa etária
E46: 30-39 | F46: =F34*'Projeções - Receita'!$F72 -> 11362425 | G46: =G34*'Projeções - Receita'!$F72 -> 11569499 | H46: =H34*'Projeções - Receita'!$F72 -> 11746183 | I46: =I34*'Projeções - Receita'!$F72 -> 11893378 | J46: =J34*'Projeções - Receita'!$F72 -> 12011021 | K46: =K34*'Projeções - Receita'!$F72 -> 12099692 | L46: =L34*'Projeções - Receita'!$F72 -> 12160989 | M46: =M34*'Projeções - Receita'!$F72 -> 12197084 | ... BA46: =BA34*'Projeções - Receita'!$F72 -> 9764905.7 | BB46: =(O46/F46)^(1/COUNT($G$9:$O$9))-1 -> 0.0078223615 | BC46: Multiplicação do Número de Pessoas desta Faixa Etária pela maturação do consumidor nessa faixa etária
E47: 40-49 | F47: =F35*'Projeções - Receita'!$F73 -> 12699375 | G47: =G35*'Projeções - Receita'!$F73 -> 12853625 | H47: =H35*'Projeções - Receita'!$F73 -> 13031142 | I47: =I35*'Projeções - Receita'!$F73 -> 13229081 | J47: =J35*'Projeções - Receita'!$F73 -> 13446110 | K47: =K35*'Projeções - Receita'!$F73 -> 13683451 | L47: =L35*'Projeções - Receita'!$F73 -> 13940628 | M47: =M35*'Projeções - Receita'!$F73 -> 14215601 | ... BA47: =BA35*'Projeções - Receita'!$F73 -> 13758924 | BB47: =(O47/F47)^(1/COUNT($G$9:$O$9))-1 -> 0.017267044 | BC47: Multiplicação do Número de Pessoas desta Faixa Etária pela maturação do consumidor nessa faixa etária
E48: 50-59 | F48: =F36*'Projeções - Receita'!$F74 -> 13346219 | G48: =G36*'Projeções - Receita'!$F74 -> 13717579 | H48: =H36*'Projeções - Receita'!$F74 -> 14073151 | I48: =I36*'Projeções - Receita'!$F74 -> 14413667 | J48: =J36*'Projeções - Receita'!$F74 -> 14740829 | K48: =K36*'Projeções - Receita'!$F74 -> 15050418 | L48: =L36*'Projeções - Receita'!$F74 -> 15336152 | M48: =M36*'Projeções - Receita'!$F74 -> 15595902 | ... BA48: =BA36*'Projeções - Receita'!$F74 -> 18568205 | BB48: =(O48/F48)^(1/COUNT($G$9:$O$9))-1 -> 0.020636057 | BC48: Multiplicação do Número de Pessoas desta Faixa Etária pela maturação do consumidor nessa faixa etária
E49: 60-69 | F49: =F37*'Projeções - Receita'!$F75 -> 12501934 | G49: =G37*'Projeções - Receita'!$F75 -> 13006073 | H49: =H37*'Projeções - Receita'!$F75 -> 13518146 | I49: =I37*'Projeções - Receita'!$F75 -> 14036929 | J49: =J37*'Projeções - Receita'!$F75 -> 14559388 | K49: =K37*'Projeções - Receita'!$F75 -> 15086275 | L49: =L37*'Projeções - Receita'!$F75 -> 15619748 | M49: =M37*'Projeções - Receita'!$F75 -> 16159975 | ... BA49: =BA37*'Projeções - Receita'!$F75 -> 28554998 | BB49: =(O49/F49)^(1/COUNT($G$9:$O$9))-1 -> 0.036409548 | BC49: Multiplicação do Número de Pessoas desta Faixa Etária pela maturação do consumidor nessa faixa etária
E50: 70+ | F50: =F38*'Projeções - Receita'!$F76 -> 10302735 | G50: =G38*'Projeções - Receita'!$F76 -> 10655592 | H50: =H38*'Projeções - Receita'!$F76 -> 11040882 | I50: =I38*'Projeções - Receita'!$F76 -> 11459801 | J50: =J38*'Projeções - Receita'!$F76 -> 11915240 | K50: =K38*'Projeções - Receita'!$F76 -> 12404101 | L50: =L38*'Projeções - Receita'!$F76 -> 12921485 | M50: =M38*'Projeções - Receita'!$F76 -> 13464105 | ... BA50: =BA38*'Projeções - Receita'!$F76 -> 43893450 | BB50: =(O50/F50)^(1/COUNT($G$9:$O$9))-1 -> 0.039757983 | BC50: Multiplicação do Número de Pessoas desta Faixa Etária pela maturação do consumidor nessa faixa etária
E51: Total Brasil | F51: =SUM(F44:F50) -> 84736729 | G51: =SUM(G44:G50) -> 86176530 | H51: =SUM(H44:H50) -> 87650795 | I51: =SUM(I44:I50) -> 89131034 | J51: =SUM(J44:J50) -> 90628217 | K51: =SUM(K44:K50) -> 92153751 | L51: =SUM(L44:L50) -> 93680406 | M51: =SUM(M44:M50) -> 95200794 | ... BA51: =SUM(BA44:BA50) -> 1.3218942e+08 | BB51: =(O51/F51)^(1/COUNT($G$9:$O$9))-1 -> 0.016536382
F55: =G55-1 -> 2013 | G55: =H55-1 -> 2014 | H55: =I55-1 -> 2015 | I55: 2016 | J55: 2017 | K55: 2018 | L55: 2019 | M55: 2020 | N55: 2021 | O55: =N55+1 -> 2022 | P55: =O55+1 -> 2023 | Q55: =P55+1 -> 2024 | R55: =Q55+1 -> 2025 | S55: =R55+1 -> 2026 | T55: =S55+1 -> 2027 | U55: =T55+1 -> 2028 | V55: =U55+1 -> 2029 | ... BA55: =AZ55+1 -> 2060 | BB55: CAGR 2013-2022 | BC55: Racional | BD55: Premissa | BE55: Nível de Otimismo (0-5)
E56: Receita do Varejo Farmacêutico para cada pessoa com mais de 70 anos | F56: =F26*1000/F51 -> 782.51367 | G56: =G26*1000/G51 -> 884.25169 | H56: =H26*1000/H51 -> 985.58015 | I56: =I26*1000/I51 -> 1098.1941 | J56: =J26*1000/J51 -> 1214.8999 | K56: =K26*1000/K51 -> 1295.2972 | L56: =L26*1000/L51 -> 1368.654 | M56: =M26*1000/M51 -> 1516.4344 | ... O56: =O26*1000/O51 -> 1959.9767 | P56: =O56*(1+P57) -> 2094.1939 | Q56: =P56*(1+Q57) -> 2276.7044 | R56: =Q56*(1+R57) -> 2445.3868 | S56: =R56*(1+S57) -> 2667.9723 | T56: =S56*(1+T57) -> 2902.4636 | U56: =T56*(1+U57) -> 3171.0942 | V56: =U56*(1+V57) -> 3458.1828 | W56: =V56*(1+W57) -> 3788.0879 | ... BA56: =AZ56*(1+BA57) -> 44829.553 | BC56: A Receita Líquida do Varejo Farmacêutico brasileiro com cada pessoa com mais de 70 anos | BD56: Cresce com a inflação do ano anterior + PIB
E57: Crescimento | F57: na | G57: =G56/F56-1 -> 0.13001436 | H57: =H56/G56-1 -> 0.11459233 | I57: =I56/H56-1 -> 0.11426157 | J57: =J56/I56-1 -> 0.10627064 | K57: =K56/J56-1 -> 0.066176074 | L57: =L56/K56-1 -> 0.056633169 | M57: =M56/L56-1 -> 0.107975 | N57: =N56/M56-1 -> 0.15850833 | O57: =O56/N56-1 -> 0.11565041 | P57: =(1+O58)*(1+P60)-1 -> 0.068479 | Q57: =(1+P58)*(1+Q60)-1 -> 0.08715072 | R57: =(1+Q58)*(1+R60)-1 -> 0.0740906 | S57: =(1+R58)*(1+S60)-1 -> 0.0910226 | T57: =(1+S58)*(1+T60)-1 -> 0.0878912 | U57: =(1+T58)*(1+U60)-1 -> 0.0925526 | V57: =(1+U58)*(1+V60)-1 -> 0.090533 | W57: =(1+V58)*(1+W60)-1 -> 0.0953984 | ... BA57: =(1+AZ58)*(1+BA60)-1 -> 0.0855656 | BC57: Inflação do ano anterior + PIB | BE57: 3
E58: Inflação | F58: 0.0591 | G58: 0.064 | H58: 0.1067 | I58: 0.0628 | J58: 0.0294 | K58: 0.0374 | L58: 0.043 | M58: 0.0452 | N58: 0.1006 | O58: 0.0579 | P58: =WACC!F12 -> 0.06688 | Q58: =WACC!G12 -> 0.05303 | R58: =WACC!H12 -> 0.06963 | S58: =WACC!I12 -> 0.06656 | T58: =WACC!J12 -> 0.07113 | U58: =WACC!K12 -> 0.06915 | V58: =WACC!L12 -> 0.07392 | W58: =WACC!M12 -> 0.07356 | ... BA58: =WACC!AQ12 -> 0.06428 | BC58: De acordo com a inflação implícita
E59: Inflação Acumulada | F59: =(1+F58) -> 1.0591 | G59: =F59*(1+G58) -> 1.1268824 | H59: =G59*(1+H58) -> 1.2471208 | I59: =H59*(1+I58) -> 1.3254399 | J59: =I59*(1+J58) -> 1.3644079 | K59: =J59*(1+K58) -> 1.4154367 | L59: =K59*(1+L58) -> 1.4763005 | M59: =L59*(1+M58) -> 1.5430293 | N59: =M59*(1+N58) -> 1.698258 | ... BA59: =AZ59*(1+BA58) -> 19.691162 | BB59: =(O59/F59)^(1/COUNT($G$9:$O$9))-1 -> 0.060477011
E60: Crescimento PIB | F60: 0.03 | G60: 0.005 | H60: -0.0355 | I60: -0.0328 | J60: 0.0132 | K60: 0.0132 | L60: 0.0114 | M60: -0.033 | N60: 0.05 | O60: 0.029 | P60: 0.01 | Q60: 0.019 | R60: 0.02 | S60: 0.02 | T60: 0.02 | U60: 0.02 | V60: 0.02 | W60: 0.02 | X60: 0.02 | Y60: 0.02 | Z60: =Y60 -> 0.02 | AA60: =Z60 -> 0.02 | AB60: =AA60 -> 0.02 | AC60: =AB60 -> 0.02 | AD60: =AC60 -> 0.02 | AE60: =AD60 -> 0.02 | AF60: =AE60 -> 0.02 | AG60: =AF60 -> 0.02 | ... BA60: =AZ60 -> 0.02 | BC60: De acordo com as projeções do FMI | BE60: 3
F64: =G64-1 -> 2013 | G64: =H64-1 -> 2014 | H64: =I64-1 -> 2015 | I64: 2016 | J64: 2017 | K64: 2018 | L64: 2019 | M64: 2020 | N64: 2021 | O64: =N64+1 -> 2022 | P64: =O64+1 -> 2023 | Q64: =P64+1 -> 2024 | R64: =Q64+1 -> 2025 | S64: =R64+1 -> 2026 | T64: =S64+1 -> 2027 | U64: =T64+1 -> 2028 | V64: =U64+1 -> 2029 | ... BA64: =AZ64+1 -> 2060 | BC64: Racional | BD64: Premissa
E65: Subvenção de Investimentos | F65: 0 | G65: 0 | H65: 0 | I65: 0 | J65: 0 | K65: ='DRE - Contas Abertas'!K101/34% -> 64344.118 | L65: ='DRE - Contas Abertas'!L101/34% -> 81529.412 | M65: ='DRE - Contas Abertas'!M101/34% -> 125511.76 | N65: ='DRE - Contas Abertas'!N101/34% -> 165732.35 | O65: ='DRE - Contas Abertas'!O101/34% -> 223855.88 | P65: =SUMPRODUCT(P11:P15,'Projeções - Receita'!$I$70:$I$74)*'Projeções - Receita'!P23*P66 -> 142466.55 | Q65: =SUMPRODUCT(Q11:Q15,'Projeções - Receita'!$I$70:$I$74)*'Projeções - Receita'!Q23*Q66 -> 161347.75 | R65: =SUMPRODUCT(R11:R15,'Projeções - Receita'!$I$70:$I$74)*'Projeções - Receita'!R23*R66 -> 184432.62 | S65: =SUMPRODUCT(S11:S15,'Projeções - Receita'!$I$70:$I$74)*'Projeções - Receita'!S23*S66 -> 209105.77 | T65: =SUMPRODUCT(T11:T15,'Projeções - Receita'!$I$70:$I$74)*'Projeções - Receita'!T23*T66 -> 236877.85 | U65: =SUMPRODUCT(U11:U15,'Projeções - Receita'!$I$70:$I$74)*'Projeções - Receita'!U23*U66 -> 266716.7 | V65: =SUMPRODUCT(V11:V15,'Projeções - Receita'!$I$70:$I$74)*'Projeções - Receita'!V23*V66 -> 300454.11 | W65: =SUMPRODUCT(W11:W15,'Projeções - Receita'!$I$70:$I$74)*'Projeções - Receita'!W23*W66 -> 337219.28 | X65: =SUMPRODUCT(X11:X15,'Projeções - Receita'!$I$70:$I$74)*'Projeções - Receita'!X23*X66 -> 374909.79 | Y65: =Y26*Y25*Y66 -> 411075.53
E66: % da Receita Líquida | F66: =F65/F22 -> 0 | G66: =G65/G22 -> 0 | H66: =H65/H22 -> 0 | I66: =I65/I22 -> 0 | J66: =J65/J22 -> 0 | K66: =K65/K22 -> 0.0043471511 | L66: =L65/L22 -> 0.0046414248 | M66: =M65/M22 -> 0.0062546851 | ... O66: =O65/O22 -> 0.0077012748 | P66: =AVERAGE($L$66:$O$66)*2/3 -> 0.0042444249 | Q66: =AVERAGE($L$66:$O$66)*2/3 -> 0.0042444249 | R66: =AVERAGE($L$66:$O$66)*2/3 -> 0.0042444249 | S66: =AVERAGE($L$66:$O$66)*2/3 -> 0.0042444249 | T66: =AVERAGE($L$66:$O$66)*2/3 -> 0.0042444249 | U66: =AVERAGE($L$66:$O$66)*2/3 -> 0.0042444249 | V66: =AVERAGE($L$66:$O$66)*2/3 -> 0.0042444249 | W66: =AVERAGE($L$66:$O$66)*2/3 -> 0.0042444249 | ... Y66: =AVERAGE($L$66:$O$66)*2/3 -> 0.0042444249
P67: =SUM('DRE - Contas Abertas'!O53:O53)/SUM('DRE + DCF'!#REF!) -> #REF!
E70: < 20 | F70: 0.22626788 | H70: 5 anos | I70: 1
E71: 20-29 | F71: 0.29215431 | H71: 4 anos | I71: 0.96
E72: 30-39 | F72: 0.35630689 | H72: 3 anos | I72: 0.83
E73: 40-49 | F73: 0.48591244 | H73: 2 anos | I73: 0.69
E74: 50-59 | F74: 0.6532293 | H74: 1 ano | I74: 0.5
E75: 60-69 | F75: 0.96575639
E76: 70+ | F76: 1

Sheet Projeções - Capex
M3: Raia Drogasil ($RADL3)
A7: Páginas
A8: Dashboard
A9: WACC | F9: =G9-1 -> 2013 | G9: =H9-1 -> 2014 | H9: =I9-1 -> 2015 | I9: 2016 | J9: 2017 | K9: 2018 | L9: 2019 | M9: 2020 | N9: 2021 | O9: =N9+1 -> 2022 | P9: =O9+1 -> 2023 | Q9: =P9+1 -> 2024 | R9: =Q9+1 -> 2025 | S9: =R9+1 -> 2026 | T9: =S9+1 -> 2027 | U9: =T9+1 -> 2028 | V9: =U9+1 -> 2029 | ... X9: =W9+1 -> 2031 | Y9: Racional | Z9: Premissa | AA9: Nível de Otimismo (0-5)
A10: DRE + DCF | E10: Abertura de Novas Lojas | F10: 151900 | G10: 172900 | H10: 229800 | I10: 315100 | J10: 360700 | K10: 441300 | L10: 361400 | M10: 337900 | N10: 377500 | O10: 431800 | P10: =P20*'Projeções - Receita'!P15 -> 460678.78 | Q10: =Q20*'Projeções - Receita'!Q15 -> 485108.58 | R10: =R20*'Projeções - Receita'!R15 -> 518886.69 | S10: =S20*'Projeções - Receita'!S15 -> 553423.79 | T10: =T20*'Projeções - Receita'!T15 -> 592788.82 | U10: =U20*'Projeções - Receita'!U15 -> 633780.17 | V10: =V20*'Projeções - Receita'!V15 -> 680629.2 | W10: =W20*'Projeções - Receita'!W15 -> 730696.28 | X10: =X20*'Projeções - Receita'!X15 -> 779119.53 | Y10: Multiplica-se o valor de abertura de uma loja pelo número de lojas abertas a cada ano
A11: DRE - Contas Abertas | E11: Reforma de Lojas Existentes | F11: 43800 | G11: 39800 | H11: 56100 | I11: 73300 | J11: 111300 | K11: 128900 | L11: 72900 | M11: 125300 | N11: 155300 | O11: 166400 | P11: =P21*'Projeções - Receita'!P11 -> 200909.07 | Q11: =Q21*'Projeções - Receita'!Q11 -> 232668.78 | R11: =R21*'Projeções - Receita'!R11 -> 271063.47 | S11: =S21*'Projeções - Receita'!S11 -> 314871.32 | T11: =T21*'Projeções - Receita'!T11 -> 364370.48 | U11: =U21*'Projeções - Receita'!U11 -> 418022.21 | V11: =V21*'Projeções - Receita'!V11 -> 478931.9 | W11: =W21*'Projeções - Receita'!W11 -> 545799.85 | X11: =X21*'Projeções - Receita'!X11 -> 615097.83 | Y11: Multiplica-se o valor anual de reforma de uma loja madura pelo número de lojas maduras de cada ano | Z11: Só lojas maduras sofrem reformas | AA11: 3
A12: Balanço Patrimonial | E12: Investimento em Infraestrutura | F12: 41100 | G12: 58300 | H12: 102800 | I12: 100700 | J12: 167200 | K12: 132800 | L12: 214800 | M12: 209800 | N12: =218600+77100+19300 -> 315000 | O12: 412666 | P12: =P13*'DRE + DCF'!P15 -> 417586.52 | Q12: =Q13*'DRE + DCF'!Q15 -> 472929.59 | R12: =R13*'DRE + DCF'!R15 -> 540594.11 | S12: =S13*'DRE + DCF'!S15 -> 612914.06 | T12: =T13*'DRE + DCF'!T15 -> 694317.34 | U12: =U13*'DRE + DCF'!U15 -> 781778.6 | V12: =V13*'DRE + DCF'!V15 -> 880666.97 | W12: =W13*'DRE + DCF'!W15 -> 988430.08 | X12: =X13*'DRE + DCF'!X15 -> 1098905.5
A13: Painel de Índices | E13: % da Receita Líquida | F13: =F12/'DRE + DCF'!F15 -> 0.0065940212 | G13: =G12/'DRE + DCF'!G15 -> 0.0078873646 | H13: =H12/'DRE + DCF'!H15 -> 0.011553354 | I13: =I12/'DRE + DCF'!I15 -> 0.0089458907 | J13: =J12/'DRE + DCF'!J15 -> 0.012654678 | K13: =K12/'DRE + DCF'!K15 -> 0.008972097 | L13: =L12/'DRE + DCF'!L15 -> 0.012228447 | M13: =M12/'DRE + DCF'!M15 -> 0.010455059 | ... O13: =O12/'DRE + DCF'!O15 -> 0.014196876 | P13: =AVERAGE($L$13:$N$13,$O$13) -> 0.012484073 | Q13: =AVERAGE($L$13:$N$13,$O$13) -> 0.012484073 | R13: =AVERAGE($L$13:$N$13,$O$13) -> 0.012484073 | S13: =AVERAGE($L$13:$N$13,$O$13) -> 0.012484073 | T13: =AVERAGE($L$13:$N$13,$O$13) -> 0.012484073 | U13: =AVERAGE($L$13:$N$13,$O$13) -> 0.012484073 | V13: =AVERAGE($L$13:$N$13,$O$13) -> 0.012484073 | W13: =AVERAGE($L$13:$N$13,$O$13) -> 0.012484073 | X13: =AVERAGE($L$13:$N$13,$O$13) -> 0.012484073 | Y13: Média do valor de Investimento em Infraestrutura/Receita Líquida entre 2019 e 2021 | Z13: Os investimentos em infraestrutura aumentaram bastante nos últimos anos. Esperamos que isso vá continuar daqui pra frente | AA13: 2
A14: Provisões e Processos | E14: Aquisições | F14: 0 | G14: 0 | H14: 0 | I14: 0 | J14: 0 | K14: 0 | L14: 0 | M14: 0 | N14: =137400+11884 -> 149284 | O14: 77600 | P14: 0 | Q14: =(11884/2)*(1+WACC!H10)^3 -> 8311.8719 | R14: 0 | S14: 0 | T14: 0 | U14: 0 | V14: 0 | W14: 0 | X14: 0
A15: Projeções - Receita | E15: Capex Total | F15: =SUM(F10:F12,F14) -> 236800 | G15: =SUM(G10:G12,G14) -> 271000 | H15: =SUM(H10:H12,H14) -> 388700 | I15: =SUM(I10:I12,I14) -> 489100 | J15: =SUM(J10:J12,J14) -> 639200 | K15: =SUM(K10:K12,K14) -> 703000 | L15: =SUM(L10:L12,L14) -> 649100 | M15: =SUM(M10:M12,M14) -> 673000 | ... X15: =SUM(X10:X12,X14) -> 2493122.9
A16: Projeções - Capex
A17: Projeções 2022
F19: =G19-1 -> 2013 | G19: =H19-1 -> 2014 | H19: =I19-1 -> 2015 | I19: 2016 | J19: 2017 | K19: 2018 | L19: 2019 | M19: 2020 | N19: 2021 | O19: =N19+1 -> 2022 | P19: =O19+1 -> 2023 | Q19: =P19+1 -> 2024 | R19: =Q19+1 -> 2025 | S19: =R19+1 -> 2026 | T19: =S19+1 -> 2027 | U19: =T19+1 -> 2028 | V19: =U19+1 -> 2029 | ... X19: =W19+1 -> 2031 | Y19: Racional | Z19: Premissa | AA19: Nível de Otimismo (0-5)
E20: Capex de Abertura por Loja | F20: =F10/'Projeções - Receita'!F15 -> 1168.4615 | G20: =G10/'Projeções - Receita'!G15 -> 1319.8473 | H20: =H10/'Projeções - Receita'!H15 -> 1473.0769 | I20: =I10/'Projeções - Receita'!I15 -> 1479.3427 | J20: =J10/'Projeções - Receita'!J15 -> 1725.8373 | K20: =K10/'Projeções - Receita'!K15 -> 1838.75 | L20: =L10/'Projeções - Receita'!L15 -> 1281.5603 | M20: =M10/'Projeções - Receita'!M15 -> 1407.9167 | ... O20: =O10/'Projeções - Receita'!O15 -> 1660.7692 | P20: =O20*(1+P26) -> 1771.8415 | Q20: =P20*(1+Q26) -> 1865.8022 | R20: =Q20*(1+R26) -> 1995.718 | S20: =R20*(1+S26) -> 2128.553 | T20: =S20*(1+T26) -> 2279.957 | U20: =T20*(1+U26) -> 2437.616 | V20: =U20*(1+V26) -> 2617.8046 | W20: =V20*(1+W26) -> 2810.3703 | X20: =W20*(1+X26) -> 2996.6136 | Y20: Capex de aberturas de lojas de 2021 dividido pelo número de lojas abertas em 2021 e posteriormente inflacionado durante o período de projeção. | Z20: Cresce somente com a inflação | AA20: 3
E21: Capex de Reforma por Loja Madura | F21: =F11/'Projeções - Receita'!F11 -> 80.21978 | G21: =G11/'Projeções - Receita'!G11 -> 61.609907 | H21: =H11/'Projeções - Receita'!H11 -> 77.06044 | I21: =I11/'Projeções - Receita'!I11 -> 91.510612 | J21: =J11/'Projeções - Receita'!J11 -> 122.03947 | K21: =K11/'Projeções - Receita'!K11 -> 125.87891 | L21: =L11/'Projeções - Receita'!L11 -> 63.336229 | M21: =M11/'Projeções - Receita'!M11 -> 93.021529 | ... O21: =O11/'Projeções - Receita'!O11 -> 100.12034 | P21: =O21*(1+'Projeções - Receita'!P58) -> 106.81639 | Q21: =P21*(1+'Projeções - Receita'!Q58) -> 112.48086 | R21: =Q21*(1+'Projeções - Receita'!R58) -> 120.3129 | S21: =R21*(1+'Projeções - Receita'!S58) -> 128.32093 | T21: =S21*(1+'Projeções - Receita'!T58) -> 137.44839 | U21: =T21*(1+'Projeções - Receita'!U58) -> 146.95295 | V21: =U21*(1+'Projeções - Receita'!V58) -> 157.81571 | W21: =V21*(1+'Projeções - Receita'!W58) -> 169.42464 | X21: =W21*(1+'Projeções - Receita'!X58) -> 180.65241 | Y21: Capex de reformas de lojas de 2021 dividido pelo número de lojas maduras em 2021 e posteriormente inflacionado durante o período de projeção. | Z21: Cresce somente com a inflação | AA21: 3
F25: 2013 | G25: 2014 | H25: 2015 | I25: 2016 | J25: =I25+1 -> 2017 | K25: =J25+1 -> 2018 | L25: =K25+1 -> 2019 | M25: =L25+1 -> 2020 | N25: 2021 | O25: 2022 | P25: 2023 | Q25: 2024 | R25: =Q25+1 -> 2025 | S25: =R25+1 -> 2026 | T25: =S25+1 -> 2027 | U25: =T25+1 -> 2028 | V25: =U25+1 -> 2029 | W25: =V25+1 -> 2030 | X25: =W25+1 -> 2031 | Y25: =X25+1 -> 2032 | Z25: =Y25+1 -> 2033
E26: Inflação | F26: ='Projeções - Receita'!F58 -> 0.0591 | G26: ='Projeções - Receita'!G58 -> 0.064 | H26: ='Projeções - Receita'!H58 -> 0.1067 | I26: ='Projeções - Receita'!I58 -> 0.0628 | J26: ='Projeções - Receita'!J58 -> 0.0294 | K26: ='Projeções - Receita'!K58 -> 0.0374 | L26: ='Projeções - Receita'!L58 -> 0.043 | M26: ='Projeções - Receita'!M58 -> 0.0452 | N26: ='Projeções - Receita'!N58 -> 0.1006 | O26: 0.0579 | P26: =WACC!F12 -> 0.06688 | Q26: =WACC!G12 -> 0.05303 | R26: =WACC!H12 -> 0.06963 | S26: =WACC!I12 -> 0.06656 | T26: =WACC!J12 -> 0.07113 | U26: =WACC!K12 -> 0.06915 | V26: =WACC!L12 -> 0.07392 | W26: =WACC!M12 -> 0.07356 | ... Z26: =WACC!P12 -> 0.06428

Sheet Projeções 2023
F3: Raia Drogasil ($RADL3)
A7: Páginas
A8: Dashboard
A9: WACC | F9: 1T22R | G9: 2T22R | H9: 3T22R | I9: 4T22E | J9: 2022E
A10: DRE + DCF | E10: Receita Líquida | F10: ='DRE + DCF'!#REF! -> #REF! | G10: ='DRE + DCF'!#REF! -> #REF! | H10: ='DRE + DCF'!#REF! -> #REF! | I10: =AVERAGE(O$23:O$27,O$31)*($F$10+$G$10+H10)/AVERAGE(SUM($L$23:$N$23),SUM($L$24:$N$24),SUM($L$25:$N$25),SUM($L$26:$N$26),SUM($L$27:$N$27),SUM($L$31:$N$31)) -> #REF! | J10: =SUM(F10:I10) -> #REF!
A11: DRE - Contas Abertas | E11: CPV + Despesas Operacionais | F11: =F12-F10 -> #REF! | G11: =G12-G10 -> #REF! | H11: =H12-H10 -> #REF! | I11: =I12-I10 -> #REF! | J11: =J12-J10 -> #REF!
A12: Balanço Patrimonial | E12: EBIT Recorrente | F12: ='DRE + DCF'!#REF! -> #REF! | G12: ='DRE + DCF'!#REF! -> #REF! | H12: ='DRE + DCF'!#REF! -> #REF! | I12: =AVERAGE(O$36:O$40,O$44)*($F$12+$G$12+$H$12)/AVERAGE(SUM($L$36:$N$36),SUM($L$37:$N$37),SUM($L$38:$N$38),SUM($L$39:$N$39),SUM($L$40:$N$40),SUM($L$44:$N$44)) -> #REF! | J12: =SUM(F12:I12) -> #REF!
A13: Painel de Índices | E13: Margem EBIT | F13: =F12/F10 -> #REF! | G13: =G12/G10 -> #REF! | H13: =H12/H10 -> #REF! | I13: =I12/I10 -> #REF! | J13: =J12/J10 -> #REF!
A14: Provisões e Processos | E14: Imposto de Renda e CSLL | F14: ='DRE + DCF'!#REF! -> #REF! | G14: ='DRE + DCF'!#REF! -> #REF! | H14: ='DRE + DCF'!#REF! -> #REF! | I14: =($J14-$F14-$G14-$H$14) -> #REF! | J14: ='DRE + DCF'!O37 -> -178241
A15: Projeções - Receita | E15: D&A de Arrendamento | F15: ='DRE + DCF'!#REF! -> #REF! | G15: ='DRE + DCF'!#REF! -> #REF! | H15: ='DRE + DCF'!#REF! -> #REF! | I15: =($J15-$F15-$G15-$H$15) -> #REF! | J15: ='DRE + DCF'!O44 -> 815372
A16: Projeções - Capex | E16: NOPAT | F16: =F12+F14+F15 -> #REF! | G16: =G12+G14+G15 -> #REF! | H16: =H12+H14+H15 -> #REF! | I16: =I12+I14+I15 -> #REF! | J16: ='DRE + DCF'!O46 -> 2385068
A17: Projeções 2022
F22: 1º Trimestre | G22: 2º Trimestre | H22: 3º Trimestre | I22: 4º Trimestre | L22: 1º Trimestre | M22: 2º Trimestre | N22: 3º Trimestre | O22: 4º Trimestre
E23: 2013 | F23: 1383771 | G23: 1543860 | H23: 1618271 | I23: 1671989 | K23: 2013 | L23: =F23/SUM($F23:$I23) -> 0.22254668 | M23: =G23/SUM($F23:$I23) -> 0.24829319 | N23: =H23/SUM($F23:$I23) -> 0.26026043 | O23: =I23/SUM($F23:$I23) -> 0.2688997
E24: 2014 | F24: 1676685.1 | G24: 1808818.2 | H24: 1943551.2 | I24: 2041595.3 | K24: 2014 | L24: =F24/SUM($F24:$I24) -> 0.22443632 | M24: =G24/SUM($F24:$I24) -> 0.24212327 | N24: =H24/SUM($F24:$I24) -> 0.26015825 | O24: =I24/SUM($F24:$I24) -> 0.27328216
E25: 2015 | F25: 2003991 | G25: 2226202 | H25: 2331823.9 | I25: 2459938 | K25: 2015 | L25: =F25/SUM($F25:$I25) -> 0.22212381 | M25: =G25/SUM($F25:$I25) -> 0.24675384 | N25: =H25/SUM($F25:$I25) -> 0.25846105 | O25: =I25/SUM($F25:$I25) -> 0.2726613
E26: 2016 | F26: 2515427.3 | G26: 2783211.5 | H26: 2900929.9 | I26: 3056996.8 | K26: 2016 | L26: =F26/SUM($F26:$I26) -> 0.22346312 | M26: =G26/SUM($F26:$I26) -> 0.24725228 | N26: =H26/SUM($F26:$I26) -> 0.25771004 | O26: =I26/SUM($F26:$I26) -> 0.27157456
E27: 2017 | F27: 3057110.4 | G27: 3237258.1 | H27: 3416840.1 | I27: 3501296.3 | K27: 2017 | L27: =F27/SUM($F27:$I27) -> 0.23138008 | M27: =G27/SUM($F27:$I27) -> 0.24501471 | N27: =H27/SUM($F27:$I27) -> 0.25860653 | O27: =I27/SUM($F27:$I27) -> 0.26499867
E28: 2018 | F28: 3433577.7 | G28: 3613988.9 | H28: 3756813.9 | I28: 3997064.3 | K28: 2018 | L28: =F28/SUM($F28:$I28) -> 0.23197585 | M28: =G28/SUM($F28:$I28) -> 0.2441646 | N28: =H28/SUM($F28:$I28) -> 0.253814 | O28: =I28/SUM($F28:$I28) -> 0.27004555
E29: 2019 | F29: 3953351.5 | G29: 4225494 | H29: 4538936 | I29: 4785114.6 | K29: 2019 | L29: =F29/SUM($F29:$I29) -> 0.22586842 | M29: =G29/SUM($F29:$I29) -> 0.24141685 | N29: =H29/SUM($F29:$I29) -> 0.25932486 | O29: =I29/SUM($F29:$I29) -> 0.27338988
E30: 2020 | F30: 4949871.3 | G30: 4469774.4 | H30: 5093451.6 | I30: 5553741.2 | K30: 2020 | L30: =F30/SUM($F30:$I30) -> 0.24666922 | M30: =G30/SUM($F30:$I30) -> 0.22274433 | N30: =H30/SUM($F30:$I30) -> 0.25382432 | O30: =I30/SUM($F30:$I30) -> 0.27676214
E31: 2021 | F31: 5620051.4 | G31: 5868265 | H31: 6164862.8 | I31: 6473825 | K31: 2021 | L31: =F31/SUM($F31:$I31) -> 0.23293615 | M31: =G31/SUM($F31:$I31) -> 0.24322394 | N31: =H31/SUM($F31:$I31) -> 0.25551713 | O31: =I31/SUM($F31:$I31) -> 0.26832279
F35: 1º Trimestre | G35: 2º Trimestre | H35: 3º Trimestre | I35: 4º Trimestre | L35: 1º Trimestre | M35: 2º Trimestre | N35: 3º Trimestre | O35: 4º Trimestre
E36: 2013 | F36: 24401 | G36: 56334 | H36: 29409 | I36: 39690 | K36: 2013 | L36: =F36/SUM($F36:$I36) -> 0.16285356 | M36: =G36/SUM($F36:$I36) -> 0.37597608 | N36: =H36/SUM($F36:$I36) -> 0.19627721 | O36: =I36/SUM($F36:$I36) -> 0.26489315
E37: 2014 | F37: 42329 | G37: 85756 | H37: 88893 | I37: 92148 | K37: 2014 | L37: =F37/SUM($F37:$I37) -> 0.13693122 | M37: =G37/SUM($F37:$I37) -> 0.27741439 | N37: =H37/SUM($F37:$I37) -> 0.28756235 | O37: =I37/SUM($F37:$I37) -> 0.29809204
E38: 2015 | F38: 98843 | G38: 161588 | H38: 123545 | I38: 117233 | K38: 2015 | L38: =F38/SUM($F38:$I38) -> 0.19720915 | M38: =G38/SUM($F38:$I38) -> 0.32239645 | N38: =H38/SUM($F38:$I38) -> 0.24649398 | O38: =I38/SUM($F38:$I38) -> 0.23390043
E39: 2016 | F39: 129909.2 | G39: 238201.43 | H39: 183505.25 | I39: 153922.81 | K39: 2016 | L39: =F39/SUM($F39:$I39) -> 0.18412768 | M39: =G39/SUM($F39:$I39) -> 0.3376164 | N39: =H39/SUM($F39:$I39) -> 0.2600924 | O39: =I39/SUM($F39:$I39) -> 0.21816353
E40: 2017 | F40: 164336.15 | G40: 219575.65 | H40: 209702.94 | I40: 198968.08 | K40: 2017 | L40: =F40/SUM($F40:$I40) -> 0.20734256 | M40: =G40/SUM($F40:$I40) -> 0.27703811 | N40: =H40/SUM($F40:$I40) -> 0.26458174 | O40: =I40/SUM($F40:$I40) -> 0.25103759
E41: 2018 | F41: 176147 | G41: 210140 | H41: 186230 | I41: 148993 | K41: 2018 | L41: =F41/SUM($F41:$I41) -> 0.2441366 | M41: =G41/SUM($F41:$I41) -> 0.29125029 | N41: =H41/SUM($F41:$I41) -> 0.25811146 | O41: =I41/SUM($F41:$I41) -> 0.20650164
E42: 2019 | F42: 156371 | G42: 236052 | H42: 491930 | I42: 234116 | K42: 2019 | L42: =F42/SUM($F42:$I42) -> 0.13980808 | M42: =G42/SUM($F42:$I42) -> 0.21104921 | N42: =H42/SUM($F42:$I42) -> 0.43982444 | O42: =I42/SUM($F42:$I42) -> 0.20931827
E43: 2020 | F43: 241825.84 | G43: 122127.56 | H43: 278968.93 | I43: 273061.44 | K43: 2020 | L43: =F43/SUM($F43:$I43) -> 0.26400668 | M43: =G43/SUM($F43:$I43) -> 0.13332939 | N43: =H43/SUM($F43:$I43) -> 0.30455663 | O43: =I43/SUM($F43:$I43) -> 0.29810729
E44: 2021 | F44: 318094.1 | G44: 433420.22 | H44: 322274.8 | I44: 292667.2 | K44: 2021 | L44: =F44/SUM($F44:$I44) -> 0.23278761 | M44: =G44/SUM($F44:$I44) -> 0.31718556 | N44: =H44/SUM($F44:$I44) -> 0.23584713 | O44: =I44/SUM($F44:$I44) -> 0.2141797
