Workbook

Sheet 1.Capa
B2: ITUB4 — Modelo de Valuation
B3: Itaú Unibanco Holding S.A.
B4: Tipo: Banco privado — large cap | CVM: 019348 | Data-base: 2025-12-31
B6: Sumário Executivo
B7: Preço atual (R$) | C7: 35.5
B8: Preço-alvo DDM (R$/ação) | C8: ='7.DDM_Valuation'!C35 -> 30.451577
B9: Upside / (Downside) | C9: =IFERROR(C8/C7-1,0) -> -0.1422091
B10: Recomendação | C10: =IF(C9>0.15,"COMPRA",IF(C9>0.05,"NEUTRO +",IF(C9>-0.05,"NEUTRO",IF(C9>-0.15,"NEUTRO -","VENDA")))) -> NEUTRO -
B12: Navegação
B13: 2.Premissas | C13: Inputs macro, CAPM, cenários
B14: 3.Historico | C14: DRE e BP 2019-2025
B15: 4.Drivers | C15: NIM, crescimento carteira, custo crédito, eficiência
B16: 5.DRE_Proj | C16: Projeção 2026-2030 + Terminal
B17: 6.BP_Proj | C17: Balanço Patrimonial projetado
B18: 7.DDM_Valuation | C18: Modelo Gordon 2 estágios
B19: 8.Multiplos | C19: P/L, P/VP, EV/Receita histórico
B20: 9.Sensibilidade | C20: Tabela Ke × g terminal
B21: 10.Dashboard | C21: KPIs e visualização
B22: 11.Cenarios | C22: Stress / Base / Blue-Sky
B24: Premissas-chave (resumo)
B25: Rf — Taxa livre de risco (nominal) | C25: ='2.Premissas'!C7 -> 0.115
B26: ERP — Prêmio de risco Brasil | C26: ='2.Premissas'!C8 -> 0.065
B27: Beta alavancado | C27: ='2.Premissas'!C9 -> 0.95
B28: Ke — Custo de equity (CAPM) | C28: ='2.Premissas'!C11 -> 0.17675
B29: g — Crescimento terminal | C29: ='2.Premissas'!C13 -> 0.05
B30: Payout projetado | C30: ='2.Premissas'!C19 -> 0.55
B31: ROE sustentável (steady state) | C31: ='2.Premissas'!C20 -> 0.17
B34: Legenda de cores
B35: Input (hardcode)
B36: Fórmula / cálculo
B37: Link cross-sheet
B38: Premissa-chave

Sheet 2.Premissas
B2: Premissas — ITUB4
B5: 1. Macroeconomia e Custo de Capital
B6: Item | C6: Valor | D6: Unidade | E6: Fonte / Comentário
B7: Rf — Selic longa proxy (NTN-B) | C7: 0.115 | D7: % a.a. | E7: Tesouro Direto — IPCA+2035
B8: ERP — Equity Risk Premium Brasil | C8: 0.065 | D8: % a.a. | E8: Damodaran 2025 — BR
B9: Beta alavancado (5y) | C9: 0.95 | D9: × | E9: Regressão IBOV 60m
B10: Risco-país (informativo — já embutido no ERP_BR) | C10: 0.02 | D10: % a.a. | E10: EMBI+ Brasil — referência
B11: Ke — Custo de Equity (CAPM) | C11: =C7+C9*C8 -> 0.17675 | D11: % a.a. | E11: Rf_BR + β·ERP_BR (CRP já embutido)
B12: Inflação média projetada | C12: 0.035 | D12: % a.a. | E12: BCB Focus 2026-2030
B13: g — Crescimento terminal (nominal) | C13: 0.05 | D13: % a.a. | E13: Inflação + real 1,5%
B14: Alíquota IR/CSLL efetiva | C14: 0.35 | D14: % a.a. | E14: CSLL 20% + IR 25% — bancos
B16: 2. Política de Capital e Distribuição
B17: Item | C17: Valor | D17: Unidade | E17: Comentário
B18: Índice de Basileia alvo | C18: 0.145 | E18: Req. mínimo 10,5% + buffer
B19: Payout ratio projetado | C19: 0.55 | E19: Histórico recente
B20: ROE sustentável (steady state) | C20: 0.17 | E20: Convergência gradual
B21: Ações em circulação (milhões) | C21: 9807 | E21: Totais ON+PN / Units
B23: 3. Cenário de Projeção (2026E–2030E)
B24: Driver | C24: 2026 | D24: 2027 | E24: 2028 | F24: 2029 | G24: 2030
B25: Crescimento da carteira de crédito (YoY) | C25: 0.075 | D25: 0.08 | E25: 0.08 | F25: 0.075 | G25: 0.07
B26: NIM — Margem financeira / ativos rentáveis | C26: 0.052 | D26: 0.052 | E26: 0.053 | F26: 0.053 | G26: 0.053
B27: Custo do crédito (PDD / carteira) | C27: 0.032 | D27: 0.03 | E27: 0.028 | F27: 0.028 | G27: 0.028
B28: Crescimento receitas de serviços (YoY) | C28: 0.07 | D28: 0.07 | E28: 0.065 | F28: 0.06 | G28: 0.06
B29: Crescimento OPEX (YoY) | C29: 0.055 | D29: 0.055 | E29: 0.055 | F29: 0.05 | G29: 0.05
B30: Índice de Eficiência (OPEX / Receitas) | C30: 0.42 | D30: 0.41 | E30: 0.4 | F30: 0.4 | G30: 0.4
B32: Notas: valores em R$ bi quando não indicado. Cenário base.

Sheet 3.Historico
B2: Histórico — ITUB4 (R$ bilhões)
B4: Linha | C4: 2019 | D4: 2020 | E4: 2021 | F4: 2022 | G4: 2023 | H4: 2024 | I4: 2025
B6: DRE
B7: Receitas de Intermediação Financeira | C7: 193 | D7: 173.8 | E7: 195.7 | F7: 283.4 | G7: 313.2 | H7: 335.3 | I7: 387.1
B8: (-) Despesas de Intermediação Financeira | C8: -76 | D8: -73.6 | E8: -69.3 | F8: -167.8 | G8: -188.7 | H8: -199.6 | I8: -248.2
B9: Margem Financeira Bruta (NII) | C9: 117.1 | D9: 100.2 | E9: 126.4 | F9: 115.6 | G9: 124.5 | H9: 135.7 | I9: 138.9
B10: Receitas de Serviços / Tarifas | C10: 39 | D10: 38.6 | E10: 42 | F10: 46.4 | G10: 45.7 | H10: 47.1 | I10: 47
B11: (-) PDD / Provisão para créditos | C11: -18.3 | D11: -24.5 | E11: -14 | F11: -28.1 | G11: -31.6 | H11: -29.5 | I11: -32.6
B12: (-) Despesas Administrativas (OPEX) | C12: -55 | D12: -58 | E12: -62 | F12: -69.2 | G12: -75.8 | H12: -79.4 | I12: -79.2
B13: Lucro Antes de IR (EBT) | C13: 31.2 | D13: 5.2 | E13: 42.2 | F13: 37.5 | G13: 39.7 | H13: 47.6 | I13: 50.2
B14: Lucro Líquido | C14: 27.1 | D14: 18.9 | E14: 26.8 | F14: 29.7 | G14: 33.1 | H14: 41.1 | I14: 44.9
B16: Balanço Patrimonial
B17: Ativo Total | C17: 1637.5 | D17: 2019.3 | E17: 2069.2 | F17: 2323.4 | G17: 2543.1 | H17: 2854.5 | I17: 3066.2
B18: Carteira de Crédito | C18: 585.8 | D18: 714.1 | E18: 822.6 | F18: 909.4 | G18: 910.6 | H18: 955 | I18: 1020
B19: Depósitos | C19: 507.1 | D19: 809 | E19: 850.4 | F19: 871.4 | G19: 951.4 | H19: 1054.7 | I19: 1114.5
B20: Patrimônio Líquido | C20: 136.9 | D20: 143 | E20: 152.9 | F20: 168 | G20: 190.2 | H20: 211.1 | I20: 204.5
B22: Indicadores Calculados
B23: Margem Líquida (LL / Receitas) | C23: =IFERROR(C14/C7,0) -> 0.14041451 | D23: =IFERROR(D14/D7,0) -> 0.10874568 | E23: =IFERROR(E14/E7,0) -> 0.1369443 | F23: =IFERROR(F14/F7,0) -> 0.10479887 | G23: =IFERROR(G14/G7,0) -> 0.10568327 | H23: =IFERROR(H14/H7,0) -> 0.1225768 | I23: =IFERROR(I14/I7,0) -> 0.1159907
B24: NIM (NII / Ativos médios) | C24: =IFERROR(C9/C17,0) -> 0.07151145 | D24: =IFERROR(D9/((D17+C17)/2),0) -> 0.054802013 | E24: =IFERROR(E9/((E17+D17)/2),0) -> 0.061831968 | F24: =IFERROR(F9/((F17+E17)/2),0) -> 0.052633975 | G24: =IFERROR(G9/((G17+F17)/2),0) -> 0.051166136 | H24: =IFERROR(H9/((H17+G17)/2),0) -> 0.050281607 | I24: =IFERROR(I9/((I17+H17)/2),0) -> 0.046920128
B25: ROE (LL / PL médio) | C25: =IFERROR(C14/C20,0) -> 0.19795471 | D25: =IFERROR(D14/((D20+C20)/2),0) -> 0.13504823 | E25: =IFERROR(E14/((E20+D20)/2),0) -> 0.18114228 | F25: =IFERROR(F14/((F20+E20)/2),0) -> 0.18510439 | G25: =IFERROR(G14/((G20+F20)/2),0) -> 0.18481295 | H25: =IFERROR(H14/((H20+G20)/2),0) -> 0.20483429 | I25: =IFERROR(I14/((I20+H20)/2),0) -> 0.21607315
B26: ROA (LL / Ativos médios) | C26: =IFERROR(C14/C17,0) -> 0.016549618 | D26: =IFERROR(D14/((D17+C17)/2),0) -> 0.010336907 | E26: =IFERROR(E14/((E17+D17)/2),0) -> 0.013109943 | F26: =IFERROR(F14/((F17+E17)/2),0) -> 0.013522743 | G26: =IFERROR(G14/((G17+F17)/2),0) -> 0.013603206 | H26: =IFERROR(H14/((H17+G17)/2),0) -> 0.015228991 | I26: =IFERROR(I14/((I17+H17)/2),0) -> 0.015167126
B27: Custo do Crédito (-PDD/Carteira) | C27: =IFERROR(-C11/C18,0) -> 0.031239331 | D27: =IFERROR(-D11/D18,0) -> 0.03430892 | E27: =IFERROR(-E11/E18,0) -> 0.017019207 | F27: =IFERROR(-F11/F18,0) -> 0.030899494 | G27: =IFERROR(-G11/G18,0) -> 0.034702394 | H27: =IFERROR(-H11/H18,0) -> 0.030890052 | I27: =IFERROR(-I11/I18,0) -> 0.031960784
B28: Índice de Eficiência (-OPEX/(NII+Tarifas)) | C28: =IFERROR(-C12/(C9+C10),0) -> 0.35233824 | D28: =IFERROR(-D12/(D9+D10),0) -> 0.41786744 | E28: =IFERROR(-E12/(E9+E10),0) -> 0.36817102 | F28: =IFERROR(-F12/(F9+F10),0) -> 0.42716049 | G28: =IFERROR(-G12/(G9+G10),0) -> 0.4453584 | H28: =IFERROR(-H12/(H9+H10),0) -> 0.43435449 | I28: =IFERROR(-I12/(I9+I10),0) -> 0.4260355
B29: Alavancagem (Ativos/PL) | C29: =IFERROR(C17/C20,0) -> 11.961286 | D29: =IFERROR(D17/D20,0) -> 14.120979 | E29: =IFERROR(E17/E20,0) -> 13.533028 | F29: =IFERROR(F17/F20,0) -> 13.829762 | G29: =IFERROR(G17/G20,0) -> 13.370662 | H29: =IFERROR(H17/H20,0) -> 13.522027 | I29: =IFERROR(I17/I20,0) -> 14.993643
B30: Crescimento Carteira (YoY) | C30: ="-" -> - | D30: =IFERROR(D18/C18-1,0) -> 0.21901673 | E30: =IFERROR(E18/D18-1,0) -> 0.1519395 | F30: =IFERROR(F18/E18-1,0) -> 0.10551909 | G30: =IFERROR(G18/F18-1,0) -> 0.0013195514 | H30: =IFERROR(H18/G18-1,0) -> 0.04875906 | I30: =IFERROR(I18/H18-1,0) -> 0.068062827
B31: Crescimento LL (YoY) | C31: ="-" -> - | D31: =IFERROR(D14/C14-1,0) -> -0.30258303 | E31: =IFERROR(E14/D14-1,0) -> 0.41798942 | F31: =IFERROR(F14/E14-1,0) -> 0.10820896 | G31: =IFERROR(G14/F14-1,0) -> 0.11447811 | H31: =IFERROR(H14/G14-1,0) -> 0.24169184 | I31: =IFERROR(I14/H14-1,0) -> 0.092457421

Sheet 4.Drivers
B2: Drivers — Histórico + Projeção
B4: Driver | C4: 2019 | D4: 2020 | E4: 2021 | F4: 2022 | G4: 2023 | H4: 2024 | I4: 2025 | J4: 2026 | K4: 2027 | L4: 2028 | M4: 2029 | N4: 2030
B6: Carteira de Crédito (R$ bi) | C6: ='3.Historico'!C18 -> 585.8 | D6: ='3.Historico'!D18 -> 714.1 | E6: ='3.Historico'!E18 -> 822.6 | F6: ='3.Historico'!F18 -> 909.4 | G6: ='3.Historico'!G18 -> 910.6 | H6: ='3.Historico'!H18 -> 955 | I6: ='3.Historico'!I18 -> 1020 | J6: =I6*(1+'2.Premissas'!C25) -> 1096.5 | K6: =J6*(1+'2.Premissas'!D25) -> 1184.22 | L6: =K6*(1+'2.Premissas'!E25) -> 1278.9576 | M6: =L6*(1+'2.Premissas'!F25) -> 1374.8794 | N6: =M6*(1+'2.Premissas'!G25) -> 1471.121
B7: NIM (%) | C7: ='3.Historico'!C9/'3.Historico'!C17 -> 0.07151145 | D7: ='3.Historico'!D9/(('3.Historico'!D17+'3.Historico'!C17)/2) -> 0.054802013 | E7: ='3.Historico'!E9/(('3.Historico'!E17+'3.Historico'!D17)/2) -> 0.061831968 | F7: ='3.Historico'!F9/(('3.Historico'!F17+'3.Historico'!E17)/2) -> 0.052633975 | G7: ='3.Historico'!G9/(('3.Historico'!G17+'3.Historico'!F17)/2) -> 0.051166136 | H7: ='3.Historico'!H9/(('3.Historico'!H17+'3.Historico'!G17)/2) -> 0.050281607 | I7: ='3.Historico'!I9/(('3.Historico'!I17+'3.Historico'!H17)/2) -> 0.046920128 | J7: ='2.Premissas'!C26 -> 0.052 | K7: ='2.Premissas'!D26 -> 0.052 | L7: ='2.Premissas'!E26 -> 0.053 | M7: ='2.Premissas'!F26 -> 0.053 | N7: ='2.Premissas'!G26 -> 0.053
B8: Custo do Crédito (PDD/Carteira) | C8: =-'3.Historico'!C11/'3.Historico'!C18 -> 0.031239331 | D8: =-'3.Historico'!D11/'3.Historico'!D18 -> 0.03430892 | E8: =-'3.Historico'!E11/'3.Historico'!E18 -> 0.017019207 | F8: =-'3.Historico'!F11/'3.Historico'!F18 -> 0.030899494 | G8: =-'3.Historico'!G11/'3.Historico'!G18 -> 0.034702394 | H8: =-'3.Historico'!H11/'3.Historico'!H18 -> 0.030890052 | I8: =-'3.Historico'!I11/'3.Historico'!I18 -> 0.031960784 | J8: ='2.Premissas'!C27 -> 0.032 | K8: ='2.Premissas'!D27 -> 0.03 | L8: ='2.Premissas'!E27 -> 0.028 | M8: ='2.Premissas'!F27 -> 0.028 | N8: ='2.Premissas'!G27 -> 0.028
B9: Crescimento OPEX YoY | D9: ='3.Historico'!D12/'3.Historico'!C12-1 -> 0.054545455 | E9: ='3.Historico'!E12/'3.Historico'!D12-1 -> 0.068965517 | F9: ='3.Historico'!F12/'3.Historico'!E12-1 -> 0.11612903 | G9: ='3.Historico'!G12/'3.Historico'!F12-1 -> 0.095375723 | H9: ='3.Historico'!H12/'3.Historico'!G12-1 -> 0.047493404 | I9: ='3.Historico'!I12/'3.Historico'!H12-1 -> -0.0025188917 | J9: ='2.Premissas'!C29 -> 0.055 | K9: ='2.Premissas'!D29 -> 0.055 | L9: ='2.Premissas'!E29 -> 0.055 | M9: ='2.Premissas'!F29 -> 0.05 | N9: ='2.Premissas'!G29 -> 0.05
B10: ROE | C10: ='3.Historico'!C14/'3.Historico'!C20 -> 0.19795471 | D10: ='3.Historico'!D14/(('3.Historico'!D20+'3.Historico'!C20)/2) -> 0.13504823 | E10: ='3.Historico'!E14/(('3.Historico'!E20+'3.Historico'!D20)/2) -> 0.18114228 | F10: ='3.Historico'!F14/(('3.Historico'!F20+'3.Historico'!E20)/2) -> 0.18510439 | G10: ='3.Historico'!G14/(('3.Historico'!G20+'3.Historico'!F20)/2) -> 0.18481295 | H10: ='3.Historico'!H14/(('3.Historico'!H20+'3.Historico'!G20)/2) -> 0.20483429 | I10: ='3.Historico'!I14/(('3.Historico'!I20+'3.Historico'!H20)/2) -> 0.21607315 | J10: =IFERROR('5.DRE_Proj'!C18/(('6.BP_Proj'!C17+'3.Historico'!I20)/2),0) -> 0.26883391 | K10: =IFERROR('5.DRE_Proj'!D18/(('6.BP_Proj'!D17+'6.BP_Proj'!C17)/2),0) -> 0.26827778 | L10: =IFERROR('5.DRE_Proj'!E18/(('6.BP_Proj'!E17+'6.BP_Proj'!D17)/2),0) -> 0.27242819 | M10: =IFERROR('5.DRE_Proj'!F18/(('6.BP_Proj'!F17+'6.BP_Proj'!E17)/2),0) -> 0.25935906 | N10: =IFERROR('5.DRE_Proj'!G18/(('6.BP_Proj'!G17+'6.BP_Proj'!F17)/2),0) -> 0.24750143
B11: Índice de Eficiência | C11: =-'3.Historico'!C12/('3.Historico'!C9+'3.Historico'!C10) -> 0.35233824 | D11: =-'3.Historico'!D12/('3.Historico'!D9+'3.Historico'!D10) -> 0.41786744 | E11: =-'3.Historico'!E12/('3.Historico'!E9+'3.Historico'!E10) -> 0.36817102 | F11: =-'3.Historico'!F12/('3.Historico'!F9+'3.Historico'!F10) -> 0.42716049 | G11: =-'3.Historico'!G12/('3.Historico'!G9+'3.Historico'!G10) -> 0.4453584 | H11: =-'3.Historico'!H12/('3.Historico'!H9+'3.Historico'!H10) -> 0.43435449 | I11: =-'3.Historico'!I12/('3.Historico'!I9+'3.Historico'!I10) -> 0.4260355 | J11: ='2.Premissas'!C30 -> 0.42 | K11: ='2.Premissas'!D30 -> 0.41 | L11: ='2.Premissas'!E30 -> 0.4 | M11: ='2.Premissas'!F30 -> 0.4 | N11: ='2.Premissas'!G30 -> 0.4

Sheet 5.DRE_Proj
B2: DRE Projetada — ITUB4 (R$ bi)
B4: Linha | C4: 2026 | D4: 2027 | E4: 2028 | F4: 2029 | G4: 2030 | H4: Terminal
B6: Ativos Totais médios (R$ bi) | C6: =('6.BP_Proj'!C5+'3.Historico'!I17)/2 -> 3181.1825 | D6: =('6.BP_Proj'!D5+'6.BP_Proj'!C5)/2 -> 3428.0116 | E6: =('6.BP_Proj'!E5+'6.BP_Proj'!D5)/2 -> 3702.2525 | F6: =('6.BP_Proj'!F5+'6.BP_Proj'!E5)/2 -> 3988.8211 | G6: =('6.BP_Proj'!G5+'6.BP_Proj'!F5)/2 -> 4277.6502 | H6: =G6*(1+'2.Premissas'!C13)/(1+'2.Premissas'!G25) -> 4197.6941
B7: Margem Financeira Bruta (NII) | C7: =C6*'2.Premissas'!C26 -> 165.42149 | D7: =D6*'2.Premissas'!D26 -> 178.2566 | E7: =E6*'2.Premissas'!E26 -> 196.21938 | F7: =F6*'2.Premissas'!F26 -> 211.40752 | G7: =G6*'2.Premissas'!G26 -> 226.71546 | H7: =H6*'2.Premissas'!G26 -> 222.47779
B8: (+) Receitas de Serviços / Tarifas | C8: ='3.Historico'!I10*(1+'2.Premissas'!C28) -> 50.29 | D8: =C8*(1+'2.Premissas'!D28) -> 53.8103 | E8: =D8*(1+'2.Premissas'!E28) -> 57.307969 | F8: =E8*(1+'2.Premissas'!F28) -> 60.746448 | G8: =F8*(1+'2.Premissas'!G28) -> 64.391235 | H8: =G8*(1+'2.Premissas'!C13) -> 67.610796
B9: (-) PDD / Custo do Crédito | C9: =-'4.Drivers'!J6*'2.Premissas'!C27 -> -35.088 | D9: =-'4.Drivers'!K6*'2.Premissas'!D27 -> -35.5266 | E9: =-'4.Drivers'!L6*'2.Premissas'!E27 -> -35.810813 | F9: =-'4.Drivers'!M6*'2.Premissas'!F27 -> -38.496624 | G9: =-'4.Drivers'!N6*'2.Premissas'!G27 -> -41.191387 | H9: =G9*(1+'2.Premissas'!C13) -> -43.250957
B10: Receita Operacional (NII + Serviços) | C10: =C7+C8 -> 215.71149 | D10: =D7+D8 -> 232.0669 | E10: =E7+E8 -> 253.52735 | F10: =F7+F8 -> 272.15397 | G10: =G7+G8 -> 291.1067 | H10: =H7+H8 -> 290.08859
B11: (-) Despesas Administrativas (OPEX) | C11: =-C10*'2.Premissas'!C30 -> -90.598826 | D11: =-D10*'2.Premissas'!D30 -> -95.14743 | E11: =-E10*'2.Premissas'!E30 -> -101.41094 | F11: =-F10*'2.Premissas'!F30 -> -108.86159 | G11: =-G10*'2.Premissas'!G30 -> -116.44268 | H11: =-H10*'2.Premissas'!G30 -> -116.03543
B13: Resultado Operacional antes de IR | C13: =C7+C8+C9+C11 -> 90.024664 | D13: =D7+D8+D9+D11 -> 101.39287 | E13: =E7+E8+E9+E11 -> 116.3056 | F13: =F7+F8+F9+F11 -> 124.79576 | G13: =G7+G8+G9+G11 -> 133.47263 | H13: =H7+H8+H9+H11 -> 130.80219
B14: (+/-) Outras receitas/despesas (não recorrentes) | C14: 0 | D14: 0 | E14: 0 | F14: 0 | G14: 0 | H14: 0
B15: Lucro Antes de IR (EBT) | C15: =C13+C14 -> 90.024664 | D15: =D13+D14 -> 101.39287 | E15: =E13+E14 -> 116.3056 | F15: =F13+F14 -> 124.79576 | G15: =G13+G14 -> 133.47263 | H15: =H13+H14 -> 130.80219
B16: (-) IR/CSLL | C16: =-C15*'2.Premissas'!$C$14 -> -31.508632 | D16: =-D15*'2.Premissas'!$C$14 -> -35.487506 | E16: =-E15*'2.Premissas'!$C$14 -> -40.70696 | F16: =-F15*'2.Premissas'!$C$14 -> -43.678515 | G16: =-G15*'2.Premissas'!$C$14 -> -46.71542 | H16: =-H15*'2.Premissas'!$C$14 -> -45.780768
B18: LUCRO LÍQUIDO | C18: =C15+C16 -> 58.516032 | D18: =D15+D16 -> 65.905367 | E18: =E15+E16 -> 75.59864 | F18: =F15+F16 -> 81.117242 | G18: =G15+G16 -> 86.757209 | H18: =H15+H16 -> 85.021426
B20: Dividendos Distribuídos | C20: =C18*'2.Premissas'!$C$19 -> 32.183817 | D20: =D18*'2.Premissas'!$C$19 -> 36.247952 | E20: =E18*'2.Premissas'!$C$19 -> 41.579252 | F20: =F18*'2.Premissas'!$C$19 -> 44.614483 | G20: =G18*'2.Premissas'!$C$19 -> 47.716465 | H20: =H18*'2.Premissas'!$C$19 -> 46.761784
B21: Lucro Retido | C21: =C18-C20 -> 26.332214 | D21: =D18-D20 -> 29.657415 | E21: =E18-E20 -> 34.019388 | F21: =F18-F20 -> 36.502759 | G21: =G18-G20 -> 39.040744 | H21: =H18-H20 -> 38.259642
B23: Métricas efetivas (calculadas)
B24: ROE do ano (LL / PL médio) | C24: =C18/(('6.BP_Proj'!C17+'3.Historico'!I20)/2) -> 0.26883391 | D24: =D18/(('6.BP_Proj'!D17+'6.BP_Proj'!C17)/2) -> 0.26827778 | E24: =E18/(('6.BP_Proj'!E17+'6.BP_Proj'!D17)/2) -> 0.27242819 | F24: =F18/(('6.BP_Proj'!F17+'6.BP_Proj'!E17)/2) -> 0.25935906 | G24: =G18/(('6.BP_Proj'!G17+'6.BP_Proj'!F17)/2) -> 0.24750143 | H24: =H18/(('6.BP_Proj'!H17+'6.BP_Proj'!G17)/2) -> 0.22415124
B25: NIM efetivo (NII / Ativos médios) | C25: =C7/C6 -> 0.052 | D25: =D7/D6 -> 0.052 | E25: =E7/E6 -> 0.053 | F25: =F7/F6 -> 0.053 | G25: =G7/G6 -> 0.053 | H25: =H7/H6 -> 0.053
B26: Eficiência efetiva (OPEX / Receita) | C26: =-C11/C10 -> 0.42 | D26: =-D11/D10 -> 0.41 | E26: =-E11/E10 -> 0.4 | F26: =-F11/F10 -> 0.4 | G26: =-G11/G10 -> 0.4 | H26: =-H11/H10 -> 0.4
B27: Margem Líquida (LL / Receita) | C27: =C18/C10 -> 0.27126989 | D27: =D18/D10 -> 0.28399296 | E27: =E18/E10 -> 0.29818731 | F27: =F18/F10 -> 0.29805644 | G27: =G18/G10 -> 0.29802547 | H27: =H18/H10 -> 0.2930878
B28: Custo do Crédito efetivo (PDD / Carteira) | C28: =-C9/'4.Drivers'!J6 -> 0.032 | D28: =-D9/'4.Drivers'!K6 -> 0.03 | E28: =-E9/'4.Drivers'!L6 -> 0.028 | F28: =-F9/'4.Drivers'!M6 -> 0.028 | G28: =-G9/'4.Drivers'!N6 -> 0.028

Sheet 6.BP_Proj
B2: Balanço Patrimonial Projetado — ITUB4 (R$ bi)
B4: Linha | C4: 2026 | D4: 2027 | E4: 2028 | F4: 2029 | G4: 2030 | H4: Terminal
B5: Ativo Total | C5: ='3.Historico'!I17*(1+'2.Premissas'!C25) -> 3296.165 | D5: =C5*(1+'2.Premissas'!D25) -> 3559.8582 | E5: =D5*(1+'2.Premissas'!E25) -> 3844.6469 | F5: =E5*(1+'2.Premissas'!F25) -> 4132.9954 | G5: =F5*(1+'2.Premissas'!G25) -> 4422.305 | H5: =G5*(1+'2.Premissas'!C13) -> 4643.4203
B6: (+) Carteira de Crédito Líquida | C6: ='4.Drivers'!J6 -> 1096.5 | D6: ='4.Drivers'!K6 -> 1184.22 | E6: ='4.Drivers'!L6 -> 1278.9576 | F6: ='4.Drivers'!M6 -> 1374.8794 | G6: ='4.Drivers'!N6 -> 1471.121 | H6: =G6*(1+'2.Premissas'!C13) -> 1544.677
B7: (+) Aplicações Interfinanceiras + TVM | C7: =C5*0.28 -> 922.9262 | D7: =D5*0.28 -> 996.7603 | E7: =E5*0.28 -> 1076.5011 | F7: =F5*0.28 -> 1157.2387 | G7: =G5*0.28 -> 1238.2454 | H7: =H5*0.28 -> 1300.1577
B8: (+) Outros Ativos (imobilizado, caixa, etc.) | C8: =C5-C6-C7 -> 1276.7388 | D8: =D5-D6-D7 -> 1378.8779 | E8: =E5-E6-E7 -> 1489.1881 | F8: =F5-F6-F7 -> 1600.8772 | G8: =G5-G6-G7 -> 1712.9387 | H8: =H5-H6-H7 -> 1798.5856
B10: Memorando: PDD Acumulada (proxy Carteira × 5%) | C10: =C6*0.05 -> 54.825 | D10: =D6*0.05 -> 59.211 | E10: =E6*0.05 -> 63.94788 | F10: =F6*0.05 -> 68.743971 | G10: =G6*0.05 -> 73.556049 | H10: =H6*0.05 -> 77.233851
B12: Passivo + Patrimônio Líquido
B13: (+) Depósitos | C13: ='3.Historico'!I19*(1+'2.Premissas'!C25) -> 1198.0875 | D13: =C13*(1+'2.Premissas'!D25) -> 1293.9345 | E13: =D13*(1+'2.Premissas'!E25) -> 1397.4493 | F13: =E13*(1+'2.Premissas'!F25) -> 1502.258 | G13: =F13*(1+'2.Premissas'!G25) -> 1607.416 | H13: =G13*(1+'2.Premissas'!C13) -> 1687.7868
B14: (+) Captações / Dívida Subordinada | C14: =C5*0.22 -> 725.1563 | D14: =D5*0.22 -> 783.1688 | E14: =E5*0.22 -> 845.82231 | F14: =F5*0.22 -> 909.25898 | G14: =G5*0.22 -> 972.90711 | H14: =H5*0.22 -> 1021.5525
B15: (+) Outros Passivos (provisões, tributos, etc.) | C15: =C5-C13-C14-C17 -> 1142.089 | D15: =D5-D13-D14-D17 -> 1222.2653 | E15: =E5-E13-E14-E17 -> 1306.8663 | F15: =F5-F13-F14-F17 -> 1390.4667 | G15: =G5-G13-G14-G17 -> 1471.9294 | H15: =H5-H13-H14-H17 -> 1545.5259
B16: (=) Total Passivo | C16: =C13+C14+C15 -> 3065.3328 | D16: =D13+D14+D15 -> 3299.3686 | E16: =E13+E14+E15 -> 3550.1378 | F16: =F13+F14+F15 -> 3801.9836 | G16: =G13+G14+G15 -> 4052.2525 | H16: =H13+H14+H15 -> 4254.8652
B17: Patrimônio Líquido | C17: ='3.Historico'!I20+'5.DRE_Proj'!C21 -> 230.83221 | D17: =C17+'5.DRE_Proj'!D21 -> 260.48963 | E17: =D17+'5.DRE_Proj'!E21 -> 294.50902 | F17: =E17+'5.DRE_Proj'!F21 -> 331.01178 | G17: =F17+'5.DRE_Proj'!G21 -> 370.05252 | H17: =G17*(1+'2.Premissas'!C13) -> 388.55515
B19: Alavancagem (Ativos / PL) | C19: =C5/C17 -> 14.279484 | D19: =D5/D17 -> 13.666027 | E19: =E5/E17 -> 13.054428 | F19: =F5/F17 -> 12.485947 | G19: =G5/G17 -> 11.950479 | H19: =H5/H17 -> 11.950479
B21: Reconciliação do Patrimônio Líquido
B22: PL inicial (t-1) | C22: ='3.Historico'!I20 -> 204.5 | D22: =C17 -> 230.83221 | E22: =D17 -> 260.48963 | F22: =E17 -> 294.50902 | G22: =F17 -> 331.01178 | H22: =G17 -> 370.05252
B23: (+) Lucro Líquido do período | C23: ='5.DRE_Proj'!C18 -> 58.516032 | D23: ='5.DRE_Proj'!D18 -> 65.905367 | E23: ='5.DRE_Proj'!E18 -> 75.59864 | F23: ='5.DRE_Proj'!F18 -> 81.117242 | G23: ='5.DRE_Proj'!G18 -> 86.757209 | H23: ='5.DRE_Proj'!H18 -> 85.021426
B24: (-) Dividendos Distribuídos | C24: =-'5.DRE_Proj'!C20 -> -32.183817 | D24: =-'5.DRE_Proj'!D20 -> -36.247952 | E24: =-'5.DRE_Proj'!E20 -> -41.579252 | F24: =-'5.DRE_Proj'!F20 -> -44.614483 | G24: =-'5.DRE_Proj'!G20 -> -47.716465 | H24: =-'5.DRE_Proj'!H20 -> -46.761784
B25: (=) PL final (check) | C25: =C22+C23+C24 -> 230.83221 | D25: =D22+D23+D24 -> 260.48963 | E25: =E22+E23+E24 -> 294.50902 | F25: =F22+F23+F24 -> 331.01178 | G25: =G22+G23+G24 -> 370.05252 | H25: =H22+H23+H24 -> 408.31216
B26: Δ check (PL final - linha 17) | C26: =C25-C17 -> 0 | D26: =D25-D17 -> 0 | E26: =E25-E17 -> 0 | F26: =F25-F17 -> 0 | G26: =G25-G17 -> 0 | H26: =H25-H17 -> 19.757016
B28: Indicadores Regulatórios (proxy)
B29: RWA proxy (Ativos × 75%) | C29: =C5*0.75 -> 2472.1238 | D29: =D5*0.75 -> 2669.8936 | E29: =E5*0.75 -> 2883.4851 | F29: =F5*0.75 -> 3099.7465 | G29: =G5*0.75 -> 3316.7288 | H29: =H5*0.75 -> 3482.5652
B30: Índice Basileia proxy (PL / RWA) | C30: =C17/C29 -> 0.093374053 | D30: =D17/D29 -> 0.097565545 | E30: =E17/E29 -> 0.10213648 | F30: =F17/F29 -> 0.10678672 | G30: =G17/G29 -> 0.11157153 | H30: =H17/H29 -> 0.11157153
B31: Check: Δ (Ativo - Passivo - PL) | C31: =C5-C16-C17 -> 0 | D31: =D5-D16-D17 -> 0 | E31: =E5-E16-E17 -> 0 | F31: =F5-F16-F17 -> 0 | G31: =G5-G16-G17 -> 0 | H31: =H5-H16-H17 -> 0

Sheet 7.DDM_Valuation
B2: DDM — Modelo de Gordon 2 Estágios (ITUB4)
B5: Estágio 1 — Dividendos explícitos 2026-2030
B7: Ano | C7: Dividendos (R$ bi) | D7: Período | E7: Fator de Desconto | F7: VP Dividendos (R$ bi)
B8: 2026 | C8: ='5.DRE_Proj'!C20 -> 32.183817 | D8: 1 | E8: =1/(1+'2.Premissas'!$C$11)^D8 -> 0.84979817 | F8: =C8*E8 -> 27.349749
B9: 2027 | C9: ='5.DRE_Proj'!D20 -> 36.247952 | D9: 2 | E9: =1/(1+'2.Premissas'!$C$11)^D9 -> 0.72215693 | F9: =C9*E9 -> 26.17671
B10: 2028 | C10: ='5.DRE_Proj'!E20 -> 41.579252 | D10: 3 | E10: =1/(1+'2.Premissas'!$C$11)^D10 -> 0.61368764 | F10: =C10*E10 -> 25.516673
B11: 2029 | C11: ='5.DRE_Proj'!F20 -> 44.614483 | D11: 4 | E11: =1/(1+'2.Premissas'!$C$11)^D11 -> 0.52151064 | F11: =C11*E11 -> 23.266927
B12: 2030 | C12: ='5.DRE_Proj'!G20 -> 47.716465 | D12: 5 | E12: =1/(1+'2.Premissas'!$C$11)^D12 -> 0.44317879 | F12: =C12*E12 -> 21.146925
B14: Soma VP Estágio 1 | F14: =SUM(F8:F12) -> 123.45698
B17: Estágio 2 — Valor Terminal (Perpetuidade Gordon)
B19: Dividendo 2031E (D_t+1) | C19: =C12*(1+'2.Premissas'!$C$13) -> 50.102288
B20: Ke — Custo de Equity | C20: ='2.Premissas'!$C$11 -> 0.17675
B21: g — Crescimento terminal | C21: ='2.Premissas'!$C$13 -> 0.05
B22: TV em 2030 (R$ bi) | C22: =C19/(C20-C21) -> 395.28433
B23: VP do TV (R$ bi) | C23: =C22/(1+C20)^5 -> 175.18163
B26: Valor do Equity
B28: Equity Value (R$ bi) | C28: =F14+C23 -> 298.63861
B29: (/) Ações em circulação (mi) | C29: ='2.Premissas'!$C$21 -> 9807
B30: Valor por ação (R$) | C30: =C28*1000/C29 -> 30.451577
B32: Checagem cruzada — Preço-alvo
B34: Preço atual (R$) | C34: =35.5 -> 35.5
B35: Preço-alvo DDM (R$) | C35: =C30 -> 30.451577
B36: Upside/(Downside) | C36: =C35/C34-1 -> -0.1422091
B37: Dividend Yield (prospectivo 2026) | C37: =C8/C34/1000*'2.Premissas'!$C$21 -> 8.8908929
B39: Decomposição do Valor
B40: % Estágio 1 (dividendos explícitos) | C40: =F14/C28 -> 0.41339927
B41: % Valor Terminal | C41: =C23/C28 -> 0.58660073

Sheet 8.Multiplos
B2: Múltiplos Históricos e Implícitos — ITUB4
B4: Múltiplo | C4: 2019 | D4: 2020 | E4: 2021 | F4: 2022 | G4: 2023 | H4: 2024 | I4: 2025
B6: Preço médio anual (R$) | C6: 25 | D6: 22.5 | E6: 23 | F6: 28 | G6: 31.5 | H6: 33.8 | I6: 35.5
B7: Market Cap (R$ bi) | C7: =C6*'2.Premissas'!$C$21/1000 -> 245.175 | D7: =D6*'2.Premissas'!$C$21/1000 -> 220.6575 | E7: =E6*'2.Premissas'!$C$21/1000 -> 225.561 | F7: =F6*'2.Premissas'!$C$21/1000 -> 274.596 | G7: =G6*'2.Premissas'!$C$21/1000 -> 308.9205 | H7: =H6*'2.Premissas'!$C$21/1000 -> 331.4766 | I7: =I6*'2.Premissas'!$C$21/1000 -> 348.1485
B9: LPA (R$) | C9: ='3.Historico'!C14*1000/'2.Premissas'!$C$21 -> 2.7633323 | D9: ='3.Historico'!D14*1000/'2.Premissas'!$C$21 -> 1.9271949 | E9: ='3.Historico'!E14*1000/'2.Premissas'!$C$21 -> 2.7327419 | F9: ='3.Historico'!F14*1000/'2.Premissas'!$C$21 -> 3.0284491 | G9: ='3.Historico'!G14*1000/'2.Premissas'!$C$21 -> 3.3751402 | H9: ='3.Historico'!H14*1000/'2.Premissas'!$C$21 -> 4.1908841 | I9: ='3.Historico'!I14*1000/'2.Premissas'!$C$21 -> 4.5783624
B10: VPA (R$) | C10: ='3.Historico'!C20*1000/'2.Premissas'!$C$21 -> 13.959417 | D10: ='3.Historico'!D20*1000/'2.Premissas'!$C$21 -> 14.581421 | E10: ='3.Historico'!E20*1000/'2.Premissas'!$C$21 -> 15.590904 | F10: ='3.Historico'!F20*1000/'2.Premissas'!$C$21 -> 17.130621 | G10: ='3.Historico'!G20*1000/'2.Premissas'!$C$21 -> 19.39431 | H10: ='3.Historico'!H20*1000/'2.Premissas'!$C$21 -> 21.525441 | I10: ='3.Historico'!I20*1000/'2.Premissas'!$C$21 -> 20.852452
B12: P/L | C12: =IFERROR(C6/C9,0) -> 9.047048 | D12: =IFERROR(D6/D9,0) -> 11.675 | E12: =IFERROR(E6/E9,0) -> 8.4164552 | F12: =IFERROR(F6/F9,0) -> 9.2456566 | G12: =IFERROR(G6/G9,0) -> 9.3329456 | H12: =IFERROR(H6/H9,0) -> 8.0651241 | I12: =IFERROR(I6/I9,0) -> 7.7538641
B13: P/VP | C13: =IFERROR(C6/C10,0) -> 1.7909058 | D13: =IFERROR(D6/D10,0) -> 1.5430594 | E13: =IFERROR(E6/E10,0) -> 1.4752191 | F13: =IFERROR(F6/F10,0) -> 1.6345 | G13: =IFERROR(G6/G10,0) -> 1.6241877 | H13: =IFERROR(H6/H10,0) -> 1.570235 | I13: =IFERROR(I6/I10,0) -> 1.7024377
B14: Dividend Yield (est.) | C14: =C9*'2.Premissas'!$C$19/C6 -> 0.060793311 | D14: =D9*'2.Premissas'!$C$19/D6 -> 0.047109208 | E14: =E9*'2.Premissas'!$C$19/E6 -> 0.065348176 | F14: =F9*'2.Premissas'!$C$19/F6 -> 0.059487392 | G14: =G9*'2.Premissas'!$C$19/G6 -> 0.058931019 | H14: =H9*'2.Premissas'!$C$19/H6 -> 0.068194859 | I14: =I9*'2.Premissas'!$C$19/I6 -> 0.070932375
B16: Média P/L 7 anos | C16: =AVERAGE(C12:I12) -> 9.0765848
B17: Média P/VP 7 anos | C17: =AVERAGE(C13:I13) -> 1.6200778
B19: Múltiplos implícitos no preço-alvo (2025)
B20: Preço-alvo DDM | C20: ='7.DDM_Valuation'!C35 -> 30.451577
B21: P/L implícito (2025) | C21: =C20/I9 -> 6.6511941
B22: P/VP implícito (2025) | C22: =C20/I10 -> 1.4603355
B23: vs. Média histórica P/L | C23: =C21/C16-1 -> -0.26721402
B24: vs. Média histórica P/VP | C24: =C22/C17-1 -> -0.098601612
B26: Múltiplos Forward (preço atual vs projeções)
B27: Ano | C27: 2026 | D27: 2027 | E27: 2028 | F27: 2029 | G27: 2030
B28: LPA projetado (R$) | C28: ='5.DRE_Proj'!C18*1000/'2.Premissas'!$C$21 -> 5.9667617 | D28: ='5.DRE_Proj'!D18*1000/'2.Premissas'!$C$21 -> 6.7202373 | E28: ='5.DRE_Proj'!E18*1000/'2.Premissas'!$C$21 -> 7.7086407 | F28: ='5.DRE_Proj'!F18*1000/'2.Premissas'!$C$21 -> 8.2713614 | G28: ='5.DRE_Proj'!G18*1000/'2.Premissas'!$C$21 -> 8.8464576
B29: VPA projetado (R$) | C29: ='6.BP_Proj'!C17*1000/'2.Premissas'!$C$21 -> 23.537495 | D29: ='6.BP_Proj'!D17*1000/'2.Premissas'!$C$21 -> 26.561602 | E29: ='6.BP_Proj'!E17*1000/'2.Premissas'!$C$21 -> 30.03049 | F29: ='6.BP_Proj'!F17*1000/'2.Premissas'!$C$21 -> 33.752603 | G29: ='6.BP_Proj'!G17*1000/'2.Premissas'!$C$21 -> 37.733509
B30: P/L forward (preço atual) | C30: ='1.Capa'!$C$7/C28 -> 5.9496259 | D30: ='1.Capa'!$C$7/D28 -> 5.2825515 | E30: ='1.Capa'!$C$7/E28 -> 4.6052218 | F30: ='1.Capa'!$C$7/F28 -> 4.2919174 | G30: ='1.Capa'!$C$7/G28 -> 4.0129057
B31: P/VP forward (preço atual) | C31: ='1.Capa'!$C$7/C29 -> 1.5082319 | D31: ='1.Capa'!$C$7/D29 -> 1.3365158 | E31: ='1.Capa'!$C$7/E29 -> 1.1821319 | F31: ='1.Capa'!$C$7/F29 -> 1.0517707 | G31: ='1.Capa'!$C$7/G29 -> 0.94080835
B32: Dividend Yield projetado | C32: ='5.DRE_Proj'!C20*1000/('1.Capa'!$C$7*'2.Premissas'!$C$21) -> 0.092442786 | D32: ='5.DRE_Proj'!D20*1000/('1.Capa'!$C$7*'2.Premissas'!$C$21) -> 0.10411635 | E32: ='5.DRE_Proj'!E20*1000/('1.Capa'!$C$7*'2.Premissas'!$C$21) -> 0.11942964 | F32: ='5.DRE_Proj'!F20*1000/('1.Capa'!$C$7*'2.Premissas'!$C$21) -> 0.12814785 | G32: ='5.DRE_Proj'!G20*1000/('1.Capa'!$C$7*'2.Premissas'!$C$21) -> 0.13705779
B33: Market Cap / Ativos (proxy EV/A) | C33: =('1.Capa'!$C$7*'2.Premissas'!$C$21/1000)/'6.BP_Proj'!C5 -> 0.10562229 | D33: =('1.Capa'!$C$7*'2.Premissas'!$C$21/1000)/'6.BP_Proj'!D5 -> 0.097798418 | E33: =('1.Capa'!$C$7*'2.Premissas'!$C$21/1000)/'6.BP_Proj'!E5 -> 0.090554091 | F33: =('1.Capa'!$C$7*'2.Premissas'!$C$21/1000)/'6.BP_Proj'!F5 -> 0.084236363 | G33: =('1.Capa'!$C$7*'2.Premissas'!$C$21/1000)/'6.BP_Proj'!G5 -> 0.078725573
B35: ROE implícito no preço atual (Gordon) | C35: =('1.Capa'!$C$7/I10)*('2.Premissas'!$C$11-'2.Premissas'!$C$13)+'2.Premissas'!$C$13 -> 0.26578397
B36: ROE sustentável premissa | C36: ='2.Premissas'!$C$20 -> 0.17
B37: Δ (ROE implícito - ROE premissa) | C37: =C35-C36 -> 0.095783972

Sheet 9.Sensibilidade
B2: Sensibilidade: Preço-alvo (R$) — Ke × g
B5: Tabela bidirecional: cada célula é o preço-alvo recalculado
B6: Parâmetros atuais: | C6: Ke | D6: ='2.Premissas'!C11 -> 0.17675 | E6: g | F6: ='2.Premissas'!C13 -> 0.05 | G6: Preço: | H6: ='7.DDM_Valuation'!C35 -> 30.451577
B9: Ke ↓ / g → | C9: 0.035 | D9: 0.04 | E9: 0.045 | F9: 0.05 | G9: 0.055 | H9: 0.06
B10: 0.12 | C10: =('7.DDM_Valuation'!$C$8/(1+$B10)^1+'7.DDM_Valuation'!$C$9/(1+$B10)^2+'7.DDM_Valuation'!$C$10/(1+$B10)^3+'7.DDM_Valuation'!$C$11/(1+$B10)^4+'7.DDM_Valuation'!$C$12/(1+$B10)^5+('7.DDM_Valuation'!$C$12*(1+C$9)/($B10-C$9))/(1+$B10)^5)*1000/'2.Premissas'!$C$21 -> 48.163729 | D10: =('7.DDM_Valuation'!$C$8/(1+$B10)^1+'7.DDM_Valuation'!$C$9/(1+$B10)^2+'7.DDM_Valuation'!$C$10/(1+$B10)^3+'7.DDM_Valuation'!$C$11/(1+$B10)^4+'7.DDM_Valuation'!$C$12/(1+$B10)^5+('7.DDM_Valuation'!$C$12*(1+D$9)/($B10-D$9))/(1+$B10)^5)*1000/'2.Premissas'!$C$21 -> 50.437366 | E10: =('7.DDM_Valuation'!$C$8/(1+$B10)^1+'7.DDM_Valuation'!$C$9/(1+$B10)^2+'7.DDM_Valuation'!$C$10/(1+$B10)^3+'7.DDM_Valuation'!$C$11/(1+$B10)^4+'7.DDM_Valuation'!$C$12/(1+$B10)^5+('7.DDM_Valuation'!$C$12*(1+E$9)/($B10-E$9))/(1+$B10)^5)*1000/'2.Premissas'!$C$21 -> 53.014155 | F10: =('7.DDM_Valuation'!$C$8/(1+$B10)^1+'7.DDM_Valuation'!$C$9/(1+$B10)^2+'7.DDM_Valuation'!$C$10/(1+$B10)^3+'7.DDM_Valuation'!$C$11/(1+$B10)^4+'7.DDM_Valuation'!$C$12/(1+$B10)^5+('7.DDM_Valuation'!$C$12*(1+F$9)/($B10-F$9))/(1+$B10)^5)*1000/'2.Premissas'!$C$21 -> 55.959056 | G10: =('7.DDM_Valuation'!$C$8/(1+$B10)^1+'7.DDM_Valuation'!$C$9/(1+$B10)^2+'7.DDM_Valuation'!$C$10/(1+$B10)^3+'7.DDM_Valuation'!$C$11/(1+$B10)^4+'7.DDM_Valuation'!$C$12/(1+$B10)^5+('7.DDM_Valuation'!$C$12*(1+G$9)/($B10-G$9))/(1+$B10)^5)*1000/'2.Premissas'!$C$21 -> 59.357018 | H10: =('7.DDM_Valuation'!$C$8/(1+$B10)^1+'7.DDM_Valuation'!$C$9/(1+$B10)^2+'7.DDM_Valuation'!$C$10/(1+$B10)^3+'7.DDM_Valuation'!$C$11/(1+$B10)^4+'7.DDM_Valuation'!$C$12/(1+$B10)^5+('7.DDM_Valuation'!$C$12*(1+H$9)/($B10-H$9))/(1+$B10)^5)*1000/'2.Premissas'!$C$21 -> 63.321308
B11: 0.13 | C11: =('7.DDM_Valuation'!$C$8/(1+$B11)^1+'7.DDM_Valuation'!$C$9/(1+$B11)^2+'7.DDM_Valuation'!$C$10/(1+$B11)^3+'7.DDM_Valuation'!$C$11/(1+$B11)^4+'7.DDM_Valuation'!$C$12/(1+$B11)^5+('7.DDM_Valuation'!$C$12*(1+C$9)/($B11-C$9))/(1+$B11)^5)*1000/'2.Premissas'!$C$21 -> 42.939225 | D11: =('7.DDM_Valuation'!$C$8/(1+$B11)^1+'7.DDM_Valuation'!$C$9/(1+$B11)^2+'7.DDM_Valuation'!$C$10/(1+$B11)^3+'7.DDM_Valuation'!$C$11/(1+$B11)^4+'7.DDM_Valuation'!$C$12/(1+$B11)^5+('7.DDM_Valuation'!$C$12*(1+D$9)/($B11-D$9))/(1+$B11)^5)*1000/'2.Premissas'!$C$21 -> 44.684333 | E11: =('7.DDM_Valuation'!$C$8/(1+$B11)^1+'7.DDM_Valuation'!$C$9/(1+$B11)^2+'7.DDM_Valuation'!$C$10/(1+$B11)^3+'7.DDM_Valuation'!$C$11/(1+$B11)^4+'7.DDM_Valuation'!$C$12/(1+$B11)^5+('7.DDM_Valuation'!$C$12*(1+E$9)/($B11-E$9))/(1+$B11)^5)*1000/'2.Premissas'!$C$21 -> 46.634747 | F11: =('7.DDM_Valuation'!$C$8/(1+$B11)^1+'7.DDM_Valuation'!$C$9/(1+$B11)^2+'7.DDM_Valuation'!$C$10/(1+$B11)^3+'7.DDM_Valuation'!$C$11/(1+$B11)^4+'7.DDM_Valuation'!$C$12/(1+$B11)^5+('7.DDM_Valuation'!$C$12*(1+F$9)/($B11-F$9))/(1+$B11)^5)*1000/'2.Premissas'!$C$21 -> 48.828963 | G11: =('7.DDM_Valuation'!$C$8/(1+$B11)^1+'7.DDM_Valuation'!$C$9/(1+$B11)^2+'7.DDM_Valuation'!$C$10/(1+$B11)^3+'7.DDM_Valuation'!$C$11/(1+$B11)^4+'7.DDM_Valuation'!$C$12/(1+$B11)^5+('7.DDM_Valuation'!$C$12*(1+G$9)/($B11-G$9))/(1+$B11)^5)*1000/'2.Premissas'!$C$21 -> 51.315742 | H11: =('7.DDM_Valuation'!$C$8/(1+$B11)^1+'7.DDM_Valuation'!$C$9/(1+$B11)^2+'7.DDM_Valuation'!$C$10/(1+$B11)^3+'7.DDM_Valuation'!$C$11/(1+$B11)^4+'7.DDM_Valuation'!$C$12/(1+$B11)^5+('7.DDM_Valuation'!$C$12*(1+H$9)/($B11-H$9))/(1+$B11)^5)*1000/'2.Premissas'!$C$21 -> 54.157774
B12: 0.14 | C12: =('7.DDM_Valuation'!$C$8/(1+$B12)^1+'7.DDM_Valuation'!$C$9/(1+$B12)^2+'7.DDM_Valuation'!$C$10/(1+$B12)^3+'7.DDM_Valuation'!$C$11/(1+$B12)^4+'7.DDM_Valuation'!$C$12/(1+$B12)^5+('7.DDM_Valuation'!$C$12*(1+C$9)/($B12-C$9))/(1+$B12)^5)*1000/'2.Premissas'!$C$21 -> 38.714149 | D12: =('7.DDM_Valuation'!$C$8/(1+$B12)^1+'7.DDM_Valuation'!$C$9/(1+$B12)^2+'7.DDM_Valuation'!$C$10/(1+$B12)^3+'7.DDM_Valuation'!$C$11/(1+$B12)^4+'7.DDM_Valuation'!$C$12/(1+$B12)^5+('7.DDM_Valuation'!$C$12*(1+D$9)/($B12-D$9))/(1+$B12)^5)*1000/'2.Premissas'!$C$21 -> 40.085958 | E12: =('7.DDM_Valuation'!$C$8/(1+$B12)^1+'7.DDM_Valuation'!$C$9/(1+$B12)^2+'7.DDM_Valuation'!$C$10/(1+$B12)^3+'7.DDM_Valuation'!$C$11/(1+$B12)^4+'7.DDM_Valuation'!$C$12/(1+$B12)^5+('7.DDM_Valuation'!$C$12*(1+E$9)/($B12-E$9))/(1+$B12)^5)*1000/'2.Premissas'!$C$21 -> 41.602167 | F12: =('7.DDM_Valuation'!$C$8/(1+$B12)^1+'7.DDM_Valuation'!$C$9/(1+$B12)^2+'7.DDM_Valuation'!$C$10/(1+$B12)^3+'7.DDM_Valuation'!$C$11/(1+$B12)^4+'7.DDM_Valuation'!$C$12/(1+$B12)^5+('7.DDM_Valuation'!$C$12*(1+F$9)/($B12-F$9))/(1+$B12)^5)*1000/'2.Premissas'!$C$21 -> 43.286843 | G12: =('7.DDM_Valuation'!$C$8/(1+$B12)^1+'7.DDM_Valuation'!$C$9/(1+$B12)^2+'7.DDM_Valuation'!$C$10/(1+$B12)^3+'7.DDM_Valuation'!$C$11/(1+$B12)^4+'7.DDM_Valuation'!$C$12/(1+$B12)^5+('7.DDM_Valuation'!$C$12*(1+G$9)/($B12-G$9))/(1+$B12)^5)*1000/'2.Premissas'!$C$21 -> 45.169717 | H12: =('7.DDM_Valuation'!$C$8/(1+$B12)^1+'7.DDM_Valuation'!$C$9/(1+$B12)^2+'7.DDM_Valuation'!$C$10/(1+$B12)^3+'7.DDM_Valuation'!$C$11/(1+$B12)^4+'7.DDM_Valuation'!$C$12/(1+$B12)^5+('7.DDM_Valuation'!$C$12*(1+H$9)/($B12-H$9))/(1+$B12)^5)*1000/'2.Premissas'!$C$21 -> 47.287951
B13: 0.15 | C13: =('7.DDM_Valuation'!$C$8/(1+$B13)^1+'7.DDM_Valuation'!$C$9/(1+$B13)^2+'7.DDM_Valuation'!$C$10/(1+$B13)^3+'7.DDM_Valuation'!$C$11/(1+$B13)^4+'7.DDM_Valuation'!$C$12/(1+$B13)^5+('7.DDM_Valuation'!$C$12*(1+C$9)/($B13-C$9))/(1+$B13)^5)*1000/'2.Premissas'!$C$21 -> 35.227619 | D13: =('7.DDM_Valuation'!$C$8/(1+$B13)^1+'7.DDM_Valuation'!$C$9/(1+$B13)^2+'7.DDM_Valuation'!$C$10/(1+$B13)^3+'7.DDM_Valuation'!$C$11/(1+$B13)^4+'7.DDM_Valuation'!$C$12/(1+$B13)^5+('7.DDM_Valuation'!$C$12*(1+D$9)/($B13-D$9))/(1+$B13)^5)*1000/'2.Premissas'!$C$21 -> 36.327182 | E13: =('7.DDM_Valuation'!$C$8/(1+$B13)^1+'7.DDM_Valuation'!$C$9/(1+$B13)^2+'7.DDM_Valuation'!$C$10/(1+$B13)^3+'7.DDM_Valuation'!$C$11/(1+$B13)^4+'7.DDM_Valuation'!$C$12/(1+$B13)^5+('7.DDM_Valuation'!$C$12*(1+E$9)/($B13-E$9))/(1+$B13)^5)*1000/'2.Premissas'!$C$21 -> 37.531466 | F13: =('7.DDM_Valuation'!$C$8/(1+$B13)^1+'7.DDM_Valuation'!$C$9/(1+$B13)^2+'7.DDM_Valuation'!$C$10/(1+$B13)^3+'7.DDM_Valuation'!$C$11/(1+$B13)^4+'7.DDM_Valuation'!$C$12/(1+$B13)^5+('7.DDM_Valuation'!$C$12*(1+F$9)/($B13-F$9))/(1+$B13)^5)*1000/'2.Premissas'!$C$21 -> 38.856178 | G13: =('7.DDM_Valuation'!$C$8/(1+$B13)^1+'7.DDM_Valuation'!$C$9/(1+$B13)^2+'7.DDM_Valuation'!$C$10/(1+$B13)^3+'7.DDM_Valuation'!$C$11/(1+$B13)^4+'7.DDM_Valuation'!$C$12/(1+$B13)^5+('7.DDM_Valuation'!$C$12*(1+G$9)/($B13-G$9))/(1+$B13)^5)*1000/'2.Premissas'!$C$21 -> 40.320333 | H13: =('7.DDM_Valuation'!$C$8/(1+$B13)^1+'7.DDM_Valuation'!$C$9/(1+$B13)^2+'7.DDM_Valuation'!$C$10/(1+$B13)^3+'7.DDM_Valuation'!$C$11/(1+$B13)^4+'7.DDM_Valuation'!$C$12/(1+$B13)^5+('7.DDM_Valuation'!$C$12*(1+H$9)/($B13-H$9))/(1+$B13)^5)*1000/'2.Premissas'!$C$21 -> 41.947172
B14: 0.16 | C14: =('7.DDM_Valuation'!$C$8/(1+$B14)^1+'7.DDM_Valuation'!$C$9/(1+$B14)^2+'7.DDM_Valuation'!$C$10/(1+$B14)^3+'7.DDM_Valuation'!$C$11/(1+$B14)^4+'7.DDM_Valuation'!$C$12/(1+$B14)^5+('7.DDM_Valuation'!$C$12*(1+C$9)/($B14-C$9))/(1+$B14)^5)*1000/'2.Premissas'!$C$21 -> 32.302242 | D14: =('7.DDM_Valuation'!$C$8/(1+$B14)^1+'7.DDM_Valuation'!$C$9/(1+$B14)^2+'7.DDM_Valuation'!$C$10/(1+$B14)^3+'7.DDM_Valuation'!$C$11/(1+$B14)^4+'7.DDM_Valuation'!$C$12/(1+$B14)^5+('7.DDM_Valuation'!$C$12*(1+D$9)/($B14-D$9))/(1+$B14)^5)*1000/'2.Premissas'!$C$21 -> 33.197975 | E14: =('7.DDM_Valuation'!$C$8/(1+$B14)^1+'7.DDM_Valuation'!$C$9/(1+$B14)^2+'7.DDM_Valuation'!$C$10/(1+$B14)^3+'7.DDM_Valuation'!$C$11/(1+$B14)^4+'7.DDM_Valuation'!$C$12/(1+$B14)^5+('7.DDM_Valuation'!$C$12*(1+E$9)/($B14-E$9))/(1+$B14)^5)*1000/'2.Premissas'!$C$21 -> 34.171599 | F14: =('7.DDM_Valuation'!$C$8/(1+$B14)^1+'7.DDM_Valuation'!$C$9/(1+$B14)^2+'7.DDM_Valuation'!$C$10/(1+$B14)^3+'7.DDM_Valuation'!$C$11/(1+$B14)^4+'7.DDM_Valuation'!$C$12/(1+$B14)^5+('7.DDM_Valuation'!$C$12*(1+F$9)/($B14-F$9))/(1+$B14)^5)*1000/'2.Premissas'!$C$21 -> 35.233733 | G14: =('7.DDM_Valuation'!$C$8/(1+$B14)^1+'7.DDM_Valuation'!$C$9/(1+$B14)^2+'7.DDM_Valuation'!$C$10/(1+$B14)^3+'7.DDM_Valuation'!$C$11/(1+$B14)^4+'7.DDM_Valuation'!$C$12/(1+$B14)^5+('7.DDM_Valuation'!$C$12*(1+G$9)/($B14-G$9))/(1+$B14)^5)*1000/'2.Premissas'!$C$21 -> 36.397024 | H14: =('7.DDM_Valuation'!$C$8/(1+$B14)^1+'7.DDM_Valuation'!$C$9/(1+$B14)^2+'7.DDM_Valuation'!$C$10/(1+$B14)^3+'7.DDM_Valuation'!$C$11/(1+$B14)^4+'7.DDM_Valuation'!$C$12/(1+$B14)^5+('7.DDM_Valuation'!$C$12*(1+H$9)/($B14-H$9))/(1+$B14)^5)*1000/'2.Premissas'!$C$21 -> 37.676643
B15: 0.17 | C15: =('7.DDM_Valuation'!$C$8/(1+$B15)^1+'7.DDM_Valuation'!$C$9/(1+$B15)^2+'7.DDM_Valuation'!$C$10/(1+$B15)^3+'7.DDM_Valuation'!$C$11/(1+$B15)^4+'7.DDM_Valuation'!$C$12/(1+$B15)^5+('7.DDM_Valuation'!$C$12*(1+C$9)/($B15-C$9))/(1+$B15)^5)*1000/'2.Premissas'!$C$21 -> 29.813192 | D15: =('7.DDM_Valuation'!$C$8/(1+$B15)^1+'7.DDM_Valuation'!$C$9/(1+$B15)^2+'7.DDM_Valuation'!$C$10/(1+$B15)^3+'7.DDM_Valuation'!$C$11/(1+$B15)^4+'7.DDM_Valuation'!$C$12/(1+$B15)^5+('7.DDM_Valuation'!$C$12*(1+D$9)/($B15-D$9))/(1+$B15)^5)*1000/'2.Premissas'!$C$21 -> 30.552936 | E15: =('7.DDM_Valuation'!$C$8/(1+$B15)^1+'7.DDM_Valuation'!$C$9/(1+$B15)^2+'7.DDM_Valuation'!$C$10/(1+$B15)^3+'7.DDM_Valuation'!$C$11/(1+$B15)^4+'7.DDM_Valuation'!$C$12/(1+$B15)^5+('7.DDM_Valuation'!$C$12*(1+E$9)/($B15-E$9))/(1+$B15)^5)*1000/'2.Premissas'!$C$21 -> 31.35186 | F15: =('7.DDM_Valuation'!$C$8/(1+$B15)^1+'7.DDM_Valuation'!$C$9/(1+$B15)^2+'7.DDM_Valuation'!$C$10/(1+$B15)^3+'7.DDM_Valuation'!$C$11/(1+$B15)^4+'7.DDM_Valuation'!$C$12/(1+$B15)^5+('7.DDM_Valuation'!$C$12*(1+F$9)/($B15-F$9))/(1+$B15)^5)*1000/'2.Premissas'!$C$21 -> 32.21736 | G15: =('7.DDM_Valuation'!$C$8/(1+$B15)^1+'7.DDM_Valuation'!$C$9/(1+$B15)^2+'7.DDM_Valuation'!$C$10/(1+$B15)^3+'7.DDM_Valuation'!$C$11/(1+$B15)^4+'7.DDM_Valuation'!$C$12/(1+$B15)^5+('7.DDM_Valuation'!$C$12*(1+G$9)/($B15-G$9))/(1+$B15)^5)*1000/'2.Premissas'!$C$21 -> 33.158122 | H15: =('7.DDM_Valuation'!$C$8/(1+$B15)^1+'7.DDM_Valuation'!$C$9/(1+$B15)^2+'7.DDM_Valuation'!$C$10/(1+$B15)^3+'7.DDM_Valuation'!$C$11/(1+$B15)^4+'7.DDM_Valuation'!$C$12/(1+$B15)^5+('7.DDM_Valuation'!$C$12*(1+H$9)/($B15-H$9))/(1+$B15)^5)*1000/'2.Premissas'!$C$21 -> 34.184407

Sheet 10.Dashboard
B2: ITUB4 — Dashboard de KPIs
B5: Recomendação | C5: ='1.Capa'!C10 -> NEUTRO - | E5: Ke | F5: ='2.Premissas'!C11 -> 0.17675
B6: Preço atual (R$) | C6: ='1.Capa'!C7 -> 35.5 | E6: g terminal | F6: ='2.Premissas'!C13 -> 0.05
B7: Preço-alvo (R$) | C7: ='7.DDM_Valuation'!C35 -> 30.451577 | E7: Payout | F7: ='2.Premissas'!C19 -> 0.55
B8: Upside | C8: =C7/C6-1 -> -0.1422091 | E8: ROE sustentável | F8: ='2.Premissas'!C20 -> 0.17
B11: KPI | C11: 2019 | D11: 2020 | E11: 2021 | F11: 2022 | G11: 2023 | H11: 2024 | I11: 2025 | J11: 2026 | K11: 2027 | L11: 2028 | M11: 2029 | N11: 2030
B12: Lucro Líquido (R$ bi) | C12: ='3.Historico'!C14 -> 27.1 | D12: ='3.Historico'!D14 -> 18.9 | E12: ='3.Historico'!E14 -> 26.8 | F12: ='3.Historico'!F14 -> 29.7 | G12: ='3.Historico'!G14 -> 33.1 | H12: ='3.Historico'!H14 -> 41.1 | I12: ='3.Historico'!I14 -> 44.9 | J12: ='5.DRE_Proj'!C18 -> 58.516032 | K12: ='5.DRE_Proj'!D18 -> 65.905367 | L12: ='5.DRE_Proj'!E18 -> 75.59864 | M12: ='5.DRE_Proj'!F18 -> 81.117242 | N12: ='5.DRE_Proj'!G18 -> 86.757209
B13: ROE | C13: ='4.Drivers'!C10 -> 0.19795471 | D13: ='4.Drivers'!D10 -> 0.13504823 | E13: ='4.Drivers'!E10 -> 0.18114228 | F13: ='4.Drivers'!F10 -> 0.18510439 | G13: ='4.Drivers'!G10 -> 0.18481295 | H13: ='4.Drivers'!H10 -> 0.20483429 | I13: ='4.Drivers'!I10 -> 0.21607315 | J13: ='4.Drivers'!J10 -> 0.26883391 | ... N13: ='4.Drivers'!N10 -> 0.24750143
B14: NIM | C14: ='4.Drivers'!C7 -> 0.07151145 | D14: ='4.Drivers'!D7 -> 0.054802013 | E14: ='4.Drivers'!E7 -> 0.061831968 | F14: ='4.Drivers'!F7 -> 0.052633975 | G14: ='4.Drivers'!G7 -> 0.051166136 | H14: ='4.Drivers'!H7 -> 0.050281607 | I14: ='4.Drivers'!I7 -> 0.046920128 | J14: ='4.Drivers'!J7 -> 0.052 | ... N14: ='4.Drivers'!N7 -> 0.053
B15: Índice de Eficiência | C15: ='4.Drivers'!C11 -> 0.35233824 | D15: ='4.Drivers'!D11 -> 0.41786744 | E15: ='4.Drivers'!E11 -> 0.36817102 | F15: ='4.Drivers'!F11 -> 0.42716049 | G15: ='4.Drivers'!G11 -> 0.4453584 | H15: ='4.Drivers'!H11 -> 0.43435449 | I15: ='4.Drivers'!I11 -> 0.4260355 | J15: ='4.Drivers'!J11 -> 0.42 | ... N15: ='4.Drivers'!N11 -> 0.4
B16: Carteira de Crédito (R$ bi) | C16: ='4.Drivers'!C6 -> 585.8 | D16: ='4.Drivers'!D6 -> 714.1 | E16: ='4.Drivers'!E6 -> 822.6 | F16: ='4.Drivers'!F6 -> 909.4 | G16: ='4.Drivers'!G6 -> 910.6 | H16: ='4.Drivers'!H6 -> 955 | I16: ='4.Drivers'!I6 -> 1020 | J16: ='4.Drivers'!J6 -> 1096.5 | ... N16: ='4.Drivers'!N6 -> 1471.121
B17: Custo do Crédito | C17: ='4.Drivers'!C8 -> 0.031239331 | D17: ='4.Drivers'!D8 -> 0.03430892 | E17: ='4.Drivers'!E8 -> 0.017019207 | F17: ='4.Drivers'!F8 -> 0.030899494 | G17: ='4.Drivers'!G8 -> 0.034702394 | H17: ='4.Drivers'!H8 -> 0.030890052 | I17: ='4.Drivers'!I8 -> 0.031960784 | J17: ='4.Drivers'!J8 -> 0.032 | ... N17: ='4.Drivers'!N8 -> 0.028

Sheet 11.Cenarios
B2: Cenários Macro — ITUB4
B4: Três cenários macro para stress-test do valuation:
B6: Premissa | C6: 🔴 Stress | D6: ⚪ Base (atual) | E6: 🟢 Blue-Sky
B7: Rf — NTN-B longo | C7: 0.135 | D7: 0.115 | E7: 0.09
B8: ERP Brasil | C8: 0.085 | D8: 0.065 | E8: 0.055
B9: Beta | C9: 1.14 | D9: 0.95 | E9: 0.855
B10: Ke calculado | C10: =C7+C9*C8 -> 0.2319 | D10: =D7+D9*D8 -> 0.17675 | E10: =E7+E9*E8 -> 0.137025
B11: g terminal | C11: 0.035 | D11: 0.05 | E11: 0.055
B12: Crescimento carteira (médio) | C12: 0.03 | D12: 0.07 | E12: 0.12
B13: Custo do crédito (médio) | C13: 0.055 | D13: 0.035 | E13: 0.025
B14: ROE sustentável | C14: 0.1512 | D14: 0.2052 | E14: 0.2376
B17: RESULTADOS POR CENÁRIO
B19: Preço-alvo (Gordon 1-stage) | C19: =IF(AND(C10>C11,C14>C11),('3.Historico'!I20*1000/'2.Premissas'!$C$21)*(C14-C11)/(C10-C11),('3.Historico'!I20*1000/'2.Premissas'!$C$21)*0.5) -> 12.306018 | D19: =IF(AND(D10>D11,D14>D11),('3.Historico'!I20*1000/'2.Premissas'!$C$21)*(D14-D11)/(D10-D11),('3.Historico'!I20*1000/'2.Premissas'!$C$21)*0.5) -> 25.532944 | E19: =IF(AND(E10>E11,E14>E11),('3.Historico'!I20*1000/'2.Premissas'!$C$21)*(E14-E11)/(E10-E11),('3.Historico'!I20*1000/'2.Premissas'!$C$21)*0.5) -> 46.420699
B20: Preço atual (R$) | C20: ='1.Capa'!C7 -> 35.5 | D20: ='1.Capa'!C7 -> 35.5 | E20: ='1.Capa'!C7 -> 35.5
B21: Upside / (Downside) | C21: =C19/C20-1 -> -0.6533516 | D21: =D19/D20-1 -> -0.28076215 | E21: =E19/E20-1 -> 0.30762531
B22: Recomendação implícita | C22: =IF(C21>0.15,"COMPRA",IF(C21>0.05,"NEUTRO+",IF(C21>-0.05,"NEUTRO",IF(C21>-0.15,"NEUTRO-","VENDA")))) -> VENDA | D22: =IF(D21>0.15,"COMPRA",IF(D21>0.05,"NEUTRO+",IF(D21>-0.05,"NEUTRO",IF(D21>-0.15,"NEUTRO-","VENDA")))) -> VENDA | E22: =IF(E21>0.15,"COMPRA",IF(E21>0.05,"NEUTRO+",IF(E21>-0.05,"NEUTRO",IF(E21>-0.15,"NEUTRO-","VENDA")))) -> COMPRA
B24: Notas metodológicas
B25: • Preço-alvo Gordon 1-stage: VPA_2025 × (ROE - g) / (Ke - g)
B26: • Cenário base replica Ke e g da aba Premissas (2.Premissas)
B27: • Stress: Selic no topo + default crédito + spread soberano mais amplo
B28: • Blue-Sky: ciclo de corte de Selic + melhoria operacional + crescimento
B29: • Use os cenários para definir range de preço-alvo (não apenas ponto único)
