Workbook
Name InfImp22: #REF!
Name InfImp22: '[1]Dados Complementares'!$F$11
Name InfImp22: #REF!
Name InfImp23: #REF!
Name InfImp23: '[1]Dados Complementares'!$G$11
Name InfImp23: #REF!
Name InfImp24: #REF!
Name InfImp24: '[1]Dados Complementares'!$H$11
Name InfImp24: #REF!
Name InfImp25: #REF!
Name InfImp25: '[1]Dados Complementares'!$I$11
Name InfImp25: #REF!
Name InfImp26: #REF!
Name InfImp26: '[1]Dados Complementares'!$J$11
Name InfImp26: #REF!
Name InfImp27: #REF!
Name InfImp27: '[1]Dados Complementares'!$K$11
Name InfImp27: #REF!
Name InfImp28: #REF!
Name InfImp28: '[1]Dados Complementares'!$L$11
Name InfImp28: #REF!
Name InfImp29: #REF!
Name InfImp29: '[1]Dados Complementares'!$M$11
Name InfImp29: #REF!
Name InfImp30: #REF!
Name InfImp30: '[1]Dados Complementares'!$N$11
Name InfImp30: #REF!
Name InfImp31: #REF!
Name InfImp31: #REF!
Name InfImp32: #REF!
Name InfImp32: '[1]Dados Complementares'!$P$11
Name InfImp32: #REF!
Name PIB22_China: #REF!
Name PIB22_China: #REF!
Name PIB22_Mundo: #REF!
Name PIB22_Mundo: #REF!
Name PIB23_China: #REF!
Name PIB23_China: #REF!
Name PIB23_Mundo: #REF!
Name PIB23_Mundo: #REF!
Name PIB24_China: #REF!
Name PIB24_China: #REF!
Name PIB24_Mundo: #REF!
Name PIB24_Mundo: #REF!
Name PIB25_China: #REF!
Name PIB25_China: #REF!
Name PIB25_Mundo: #REF!
Name PIB25_Mundo: #REF!
Name PIB26_ARGENTINA: #REF!
Name PIB26_ARGENTINA: #REF!
Name PIB26_BRASIL: #REF!
Name PIB26_BRASIL: '[1]Dados Complementares'!$J$14
Name PIB26_BRASIL: #REF!
Name PIB26_CHINA: #REF!
Name PIB26_CHINA: '[1]Dados Complementares'!$J$15
Name PIB26_CHINA: #REF!
Name PIB26_EUA: #REF!
Name PIB26_EUA: #REF!
Name PIB26_EUROPA: #REF!
Name PIB26_EUROPA: #REF!

Sheet Dashboard
I4: Banco do Brasil ($BBAS3)
A7: Páginas
A8: Dashboard
A9: Ke | E9: Trimestre Atual | F9: 4 | H9: Custo de Capital Próprio (Ke) | I9: =I10-0.5% -> 0.14010913 | J9: =(NPV($I9,'DRE + DCF'!$U$41:$AC$41,SUM('DRE + DCF'!$AD$41,('DRE + DCF'!$AE$38*(1-(J$18/$I9))*(1+J$18))/($I9-J$18)))+'DRE + DCF'!$S$41)/((1+$I9)^((5-$F$9)*3/12)) -> 84.68172 | K9: =(NPV($I9,'DRE + DCF'!$U$41:$AC$41,SUM('DRE + DCF'!$AD$41,('DRE + DCF'!$AE$38*(1-(K$18/$I9))*(1+K$18))/($I9-K$18)))+'DRE + DCF'!$S$41)/((1+$I9)^((5-$F$9)*3/12)) -> 84.806684 | L9: =(NPV($I9,'DRE + DCF'!$U$41:$AC$41,SUM('DRE + DCF'!$AD$41,('DRE + DCF'!$AE$38*(1-(L$18/$I9))*(1+L$18))/($I9-L$18)))+'DRE + DCF'!$S$41)/((1+$I9)^((5-$F$9)*3/12)) -> 84.931648 | M9: =(NPV($I9,'DRE + DCF'!$U$41:$AC$41,SUM('DRE + DCF'!$AD$41,('DRE + DCF'!$AE$38*(1-(M$18/$I9))*(1+M$18))/($I9-M$18)))+'DRE + DCF'!$S$41)/((1+$I9)^((5-$F$9)*3/12)) -> 85.056611 | N9: =(NPV($I9,'DRE + DCF'!$U$41:$AC$41,SUM('DRE + DCF'!$AD$41,('DRE + DCF'!$AE$38*(1-(N$18/$I9))*(1+N$18))/($I9-N$18)))+'DRE + DCF'!$S$41)/((1+$I9)^((5-$F$9)*3/12)) -> 85.181575 | O9: =(NPV($I9,'DRE + DCF'!$U$41:$AC$41,SUM('DRE + DCF'!$AD$41,('DRE + DCF'!$AE$38*(1-(O$18/$I9))*(1+O$18))/($I9-O$18)))+'DRE + DCF'!$S$41)/((1+$I9)^((5-$F$9)*3/12)) -> 85.306539 | P9: =(NPV($I9,'DRE + DCF'!$U$41:$AC$41,SUM('DRE + DCF'!$AD$41,('DRE + DCF'!$AE$38*(1-(P$18/$I9))*(1+P$18))/($I9-P$18)))+'DRE + DCF'!$S$41)/((1+$I9)^((5-$F$9)*3/12)) -> 85.431502 | Q9: =(NPV($I9,'DRE + DCF'!$U$41:$AC$41,SUM('DRE + DCF'!$AD$41,('DRE + DCF'!$AE$38*(1-(Q$18/$I9))*(1+Q$18))/($I9-Q$18)))+'DRE + DCF'!$S$41)/((1+$I9)^((5-$F$9)*3/12)) -> 85.556466 | ... S9: =(NPV($I9,'DRE + DCF'!$U$41:$AC$41,SUM('DRE + DCF'!$AD$41,('DRE + DCF'!$AE$38*(1-(S$18/$I9))*(1+S$18))/($I9-S$18)))+'DRE + DCF'!$S$41)/((1+$I9)^((5-$F$9)*3/12)) -> 85.806393
A10: DRE + DCF | E10: Ticker | F10: BBAS3 | I10: =I11-0.5% -> 0.14510913 | J10: =(NPV($I10,'DRE + DCF'!$U$41:$AC$41,SUM('DRE + DCF'!$AD$41,('DRE + DCF'!$AE$38*(1-(J$18/$I10))*(1+J$18))/($I10-J$18)))+'DRE + DCF'!$S$41)/((1+$I10)^((5-$F$9)*3/12)) -> 79.827908 | K10: =(NPV($I10,'DRE + DCF'!$U$41:$AC$41,SUM('DRE + DCF'!$AD$41,('DRE + DCF'!$AE$38*(1-(K$18/$I10))*(1+K$18))/($I10-K$18)))+'DRE + DCF'!$S$41)/((1+$I10)^((5-$F$9)*3/12)) -> 79.943273 | L10: =(NPV($I10,'DRE + DCF'!$U$41:$AC$41,SUM('DRE + DCF'!$AD$41,('DRE + DCF'!$AE$38*(1-(L$18/$I10))*(1+L$18))/($I10-L$18)))+'DRE + DCF'!$S$41)/((1+$I10)^((5-$F$9)*3/12)) -> 80.058639 | M10: =(NPV($I10,'DRE + DCF'!$U$41:$AC$41,SUM('DRE + DCF'!$AD$41,('DRE + DCF'!$AE$38*(1-(M$18/$I10))*(1+M$18))/($I10-M$18)))+'DRE + DCF'!$S$41)/((1+$I10)^((5-$F$9)*3/12)) -> 80.174004 | N10: =(NPV($I10,'DRE + DCF'!$U$41:$AC$41,SUM('DRE + DCF'!$AD$41,('DRE + DCF'!$AE$38*(1-(N$18/$I10))*(1+N$18))/($I10-N$18)))+'DRE + DCF'!$S$41)/((1+$I10)^((5-$F$9)*3/12)) -> 80.28937 | O10: =(NPV($I10,'DRE + DCF'!$U$41:$AC$41,SUM('DRE + DCF'!$AD$41,('DRE + DCF'!$AE$38*(1-(O$18/$I10))*(1+O$18))/($I10-O$18)))+'DRE + DCF'!$S$41)/((1+$I10)^((5-$F$9)*3/12)) -> 80.404735 | P10: =(NPV($I10,'DRE + DCF'!$U$41:$AC$41,SUM('DRE + DCF'!$AD$41,('DRE + DCF'!$AE$38*(1-(P$18/$I10))*(1+P$18))/($I10-P$18)))+'DRE + DCF'!$S$41)/((1+$I10)^((5-$F$9)*3/12)) -> 80.520101 | Q10: =(NPV($I10,'DRE + DCF'!$U$41:$AC$41,SUM('DRE + DCF'!$AD$41,('DRE + DCF'!$AE$38*(1-(Q$18/$I10))*(1+Q$18))/($I10-Q$18)))+'DRE + DCF'!$S$41)/((1+$I10)^((5-$F$9)*3/12)) -> 80.635466 | ... S10: =(NPV($I10,'DRE + DCF'!$U$41:$AC$41,SUM('DRE + DCF'!$AD$41,('DRE + DCF'!$AE$38*(1-(S$18/$I10))*(1+S$18))/($I10-S$18)))+'DRE + DCF'!$S$41)/((1+$I10)^((5-$F$9)*3/12)) -> 80.866197
A11: Contas Abertas | E11: Ações Emitidas (Ex-Treasury) | F11: 2853776040 | I11: =I12-0.5% -> 0.15010913 | J11: =(NPV($I11,'DRE + DCF'!$U$41:$AC$41,SUM('DRE + DCF'!$AD$41,('DRE + DCF'!$AE$38*(1-(J$18/$I11))*(1+J$18))/($I11-J$18)))+'DRE + DCF'!$S$41)/((1+$I11)^((5-$F$9)*3/12)) -> 75.380749 | K11: =(NPV($I11,'DRE + DCF'!$U$41:$AC$41,SUM('DRE + DCF'!$AD$41,('DRE + DCF'!$AE$38*(1-(K$18/$I11))*(1+K$18))/($I11-K$18)))+'DRE + DCF'!$S$41)/((1+$I11)^((5-$F$9)*3/12)) -> 75.487401 | L11: =(NPV($I11,'DRE + DCF'!$U$41:$AC$41,SUM('DRE + DCF'!$AD$41,('DRE + DCF'!$AE$38*(1-(L$18/$I11))*(1+L$18))/($I11-L$18)))+'DRE + DCF'!$S$41)/((1+$I11)^((5-$F$9)*3/12)) -> 75.594053 | M11: =(NPV($I11,'DRE + DCF'!$U$41:$AC$41,SUM('DRE + DCF'!$AD$41,('DRE + DCF'!$AE$38*(1-(M$18/$I11))*(1+M$18))/($I11-M$18)))+'DRE + DCF'!$S$41)/((1+$I11)^((5-$F$9)*3/12)) -> 75.700705 | N11: =(NPV($I11,'DRE + DCF'!$U$41:$AC$41,SUM('DRE + DCF'!$AD$41,('DRE + DCF'!$AE$38*(1-(N$18/$I11))*(1+N$18))/($I11-N$18)))+'DRE + DCF'!$S$41)/((1+$I11)^((5-$F$9)*3/12)) -> 75.807357 | O11: =(NPV($I11,'DRE + DCF'!$U$41:$AC$41,SUM('DRE + DCF'!$AD$41,('DRE + DCF'!$AE$38*(1-(O$18/$I11))*(1+O$18))/($I11-O$18)))+'DRE + DCF'!$S$41)/((1+$I11)^((5-$F$9)*3/12)) -> 75.914009 | P11: =(NPV($I11,'DRE + DCF'!$U$41:$AC$41,SUM('DRE + DCF'!$AD$41,('DRE + DCF'!$AE$38*(1-(P$18/$I11))*(1+P$18))/($I11-P$18)))+'DRE + DCF'!$S$41)/((1+$I11)^((5-$F$9)*3/12)) -> 76.020661 | Q11: =(NPV($I11,'DRE + DCF'!$U$41:$AC$41,SUM('DRE + DCF'!$AD$41,('DRE + DCF'!$AE$38*(1-(Q$18/$I11))*(1+Q$18))/($I11-Q$18)))+'DRE + DCF'!$S$41)/((1+$I11)^((5-$F$9)*3/12)) -> 76.127313 | ... S11: =(NPV($I11,'DRE + DCF'!$U$41:$AC$41,SUM('DRE + DCF'!$AD$41,('DRE + DCF'!$AE$38*(1-(S$18/$I11))*(1+S$18))/($I11-S$18)))+'DRE + DCF'!$S$41)/((1+$I11)^((5-$F$9)*3/12)) -> 76.340617
A12: Balanço Patrimonial | E12: Valor da Ação | F12: =SUM('DRE + DCF'!S43,'DRE + DCF'!U43:AE43) -> 70.46412 | I12: =I13-0.5% -> 0.15510913 | J12: =(NPV($I12,'DRE + DCF'!$U$41:$AC$41,SUM('DRE + DCF'!$AD$41,('DRE + DCF'!$AE$38*(1-(J$18/$I12))*(1+J$18))/($I12-J$18)))+'DRE + DCF'!$S$41)/((1+$I12)^((5-$F$9)*3/12)) -> 71.296907 | K12: =(NPV($I12,'DRE + DCF'!$U$41:$AC$41,SUM('DRE + DCF'!$AD$41,('DRE + DCF'!$AE$38*(1-(K$18/$I12))*(1+K$18))/($I12-K$18)))+'DRE + DCF'!$S$41)/((1+$I12)^((5-$F$9)*3/12)) -> 71.395632 | L12: =(NPV($I12,'DRE + DCF'!$U$41:$AC$41,SUM('DRE + DCF'!$AD$41,('DRE + DCF'!$AE$38*(1-(L$18/$I12))*(1+L$18))/($I12-L$18)))+'DRE + DCF'!$S$41)/((1+$I12)^((5-$F$9)*3/12)) -> 71.494357 | M12: =(NPV($I12,'DRE + DCF'!$U$41:$AC$41,SUM('DRE + DCF'!$AD$41,('DRE + DCF'!$AE$38*(1-(M$18/$I12))*(1+M$18))/($I12-M$18)))+'DRE + DCF'!$S$41)/((1+$I12)^((5-$F$9)*3/12)) -> 71.593082 | N12: =(NPV($I12,'DRE + DCF'!$U$41:$AC$41,SUM('DRE + DCF'!$AD$41,('DRE + DCF'!$AE$38*(1-(N$18/$I12))*(1+N$18))/($I12-N$18)))+'DRE + DCF'!$S$41)/((1+$I12)^((5-$F$9)*3/12)) -> 71.691807 | O12: =(NPV($I12,'DRE + DCF'!$U$41:$AC$41,SUM('DRE + DCF'!$AD$41,('DRE + DCF'!$AE$38*(1-(O$18/$I12))*(1+O$18))/($I12-O$18)))+'DRE + DCF'!$S$41)/((1+$I12)^((5-$F$9)*3/12)) -> 71.790532 | P12: =(NPV($I12,'DRE + DCF'!$U$41:$AC$41,SUM('DRE + DCF'!$AD$41,('DRE + DCF'!$AE$38*(1-(P$18/$I12))*(1+P$18))/($I12-P$18)))+'DRE + DCF'!$S$41)/((1+$I12)^((5-$F$9)*3/12)) -> 71.889258 | Q12: =(NPV($I12,'DRE + DCF'!$U$41:$AC$41,SUM('DRE + DCF'!$AD$41,('DRE + DCF'!$AE$38*(1-(Q$18/$I12))*(1+Q$18))/($I12-Q$18)))+'DRE + DCF'!$S$41)/((1+$I12)^((5-$F$9)*3/12)) -> 71.987983 | ... S12: =(NPV($I12,'DRE + DCF'!$U$41:$AC$41,SUM('DRE + DCF'!$AD$41,('DRE + DCF'!$AE$38*(1-(S$18/$I12))*(1+S$18))/($I12-S$18)))+'DRE + DCF'!$S$41)/((1+$I12)^((5-$F$9)*3/12)) -> 72.185433
A13: Projeções - Receita | E13: Cotação | F13: 49.51 | I13: =AVERAGE(Ke!F16:P16) -> 0.16010913 | J13: =(NPV($I13,'DRE + DCF'!$U$41:$AC$41,SUM('DRE + DCF'!$AD$41,('DRE + DCF'!$AE$38*(1-(J$18/$I13))*(1+J$18))/($I13-J$18)))+'DRE + DCF'!$S$41)/((1+$I13)^((5-$F$9)*3/12)) -> 67.538666 | K13: =(NPV($I13,'DRE + DCF'!$U$41:$AC$41,SUM('DRE + DCF'!$AD$41,('DRE + DCF'!$AE$38*(1-(K$18/$I13))*(1+K$18))/($I13-K$18)))+'DRE + DCF'!$S$41)/((1+$I13)^((5-$F$9)*3/12)) -> 67.630166 | L13: =(NPV($I13,'DRE + DCF'!$U$41:$AC$41,SUM('DRE + DCF'!$AD$41,('DRE + DCF'!$AE$38*(1-(L$18/$I13))*(1+L$18))/($I13-L$18)))+'DRE + DCF'!$S$41)/((1+$I13)^((5-$F$9)*3/12)) -> 67.721666 | M13: =(NPV($I13,'DRE + DCF'!$U$41:$AC$41,SUM('DRE + DCF'!$AD$41,('DRE + DCF'!$AE$38*(1-(M$18/$I13))*(1+M$18))/($I13-M$18)))+'DRE + DCF'!$S$41)/((1+$I13)^((5-$F$9)*3/12)) -> 67.813166 | N13: =(NPV($I13,'DRE + DCF'!$U$41:$AC$41,SUM('DRE + DCF'!$AD$41,('DRE + DCF'!$AE$38*(1-(N$18/$I13))*(1+N$18))/($I13-N$18)))+'DRE + DCF'!$S$41)/((1+$I13)^((5-$F$9)*3/12)) -> 67.904667 | O13: =(NPV($I13,'DRE + DCF'!$U$41:$AC$41,SUM('DRE + DCF'!$AD$41,('DRE + DCF'!$AE$38*(1-(O$18/$I13))*(1+O$18))/($I13-O$18)))+'DRE + DCF'!$S$41)/((1+$I13)^((5-$F$9)*3/12)) -> 67.996167 | P13: =(NPV($I13,'DRE + DCF'!$U$41:$AC$41,SUM('DRE + DCF'!$AD$41,('DRE + DCF'!$AE$38*(1-(P$18/$I13))*(1+P$18))/($I13-P$18)))+'DRE + DCF'!$S$41)/((1+$I13)^((5-$F$9)*3/12)) -> 68.087667 | Q13: =(NPV($I13,'DRE + DCF'!$U$41:$AC$41,SUM('DRE + DCF'!$AD$41,('DRE + DCF'!$AE$38*(1-(Q$18/$I13))*(1+Q$18))/($I13-Q$18)))+'DRE + DCF'!$S$41)/((1+$I13)^((5-$F$9)*3/12)) -> 68.179167 | ... S13: =(NPV($I13,'DRE + DCF'!$U$41:$AC$41,SUM('DRE + DCF'!$AD$41,('DRE + DCF'!$AE$38*(1-(S$18/$I13))*(1+S$18))/($I13-S$18)))+'DRE + DCF'!$S$41)/((1+$I13)^((5-$F$9)*3/12)) -> 68.362167
A14: Painel de Índices | E14: Upside | F14: =F12/F13-1 -> 0.42323006 | I14: =I13+0.5% -> 0.16510913 | J14: =(NPV($I14,'DRE + DCF'!$U$41:$AC$41,SUM('DRE + DCF'!$AD$41,('DRE + DCF'!$AE$38*(1-(J$18/$I14))*(1+J$18))/($I14-J$18)))+'DRE + DCF'!$S$41)/((1+$I14)^((5-$F$9)*3/12)) -> 64.073075 | K14: =(NPV($I14,'DRE + DCF'!$U$41:$AC$41,SUM('DRE + DCF'!$AD$41,('DRE + DCF'!$AE$38*(1-(K$18/$I14))*(1+K$18))/($I14-K$18)))+'DRE + DCF'!$S$41)/((1+$I14)^((5-$F$9)*3/12)) -> 64.157978 | L14: =(NPV($I14,'DRE + DCF'!$U$41:$AC$41,SUM('DRE + DCF'!$AD$41,('DRE + DCF'!$AE$38*(1-(L$18/$I14))*(1+L$18))/($I14-L$18)))+'DRE + DCF'!$S$41)/((1+$I14)^((5-$F$9)*3/12)) -> 64.242881 | M14: =(NPV($I14,'DRE + DCF'!$U$41:$AC$41,SUM('DRE + DCF'!$AD$41,('DRE + DCF'!$AE$38*(1-(M$18/$I14))*(1+M$18))/($I14-M$18)))+'DRE + DCF'!$S$41)/((1+$I14)^((5-$F$9)*3/12)) -> 64.327784 | N14: =(NPV($I14,'DRE + DCF'!$U$41:$AC$41,SUM('DRE + DCF'!$AD$41,('DRE + DCF'!$AE$38*(1-(N$18/$I14))*(1+N$18))/($I14-N$18)))+'DRE + DCF'!$S$41)/((1+$I14)^((5-$F$9)*3/12)) -> 64.412687 | O14: =(NPV($I14,'DRE + DCF'!$U$41:$AC$41,SUM('DRE + DCF'!$AD$41,('DRE + DCF'!$AE$38*(1-(O$18/$I14))*(1+O$18))/($I14-O$18)))+'DRE + DCF'!$S$41)/((1+$I14)^((5-$F$9)*3/12)) -> 64.49759 | P14: =(NPV($I14,'DRE + DCF'!$U$41:$AC$41,SUM('DRE + DCF'!$AD$41,('DRE + DCF'!$AE$38*(1-(P$18/$I14))*(1+P$18))/($I14-P$18)))+'DRE + DCF'!$S$41)/((1+$I14)^((5-$F$9)*3/12)) -> 64.582493 | Q14: =(NPV($I14,'DRE + DCF'!$U$41:$AC$41,SUM('DRE + DCF'!$AD$41,('DRE + DCF'!$AE$38*(1-(Q$18/$I14))*(1+Q$18))/($I14-Q$18)))+'DRE + DCF'!$S$41)/((1+$I14)^((5-$F$9)*3/12)) -> 64.667395 | ... S14: =(NPV($I14,'DRE + DCF'!$U$41:$AC$41,SUM('DRE + DCF'!$AD$41,('DRE + DCF'!$AE$38*(1-(S$18/$I14))*(1+S$18))/($I14-S$18)))+'DRE + DCF'!$S$41)/((1+$I14)^((5-$F$9)*3/12)) -> 64.837201
A15: Projeções Trimestrais | E15: TIR | F15: =VLOOKUP(MIN(TIR!C13:C3382),TIR!C13:D3382,2,0) -> 0.19350623 | I15: =I14+0.5% -> 0.17010913 | J15: =(NPV($I15,'DRE + DCF'!$U$41:$AC$41,SUM('DRE + DCF'!$AD$41,('DRE + DCF'!$AE$38*(1-(J$18/$I15))*(1+J$18))/($I15-J$18)))+'DRE + DCF'!$S$41)/((1+$I15)^((5-$F$9)*3/12)) -> 60.871235 | K15: =(NPV($I15,'DRE + DCF'!$U$41:$AC$41,SUM('DRE + DCF'!$AD$41,('DRE + DCF'!$AE$38*(1-(K$18/$I15))*(1+K$18))/($I15-K$18)))+'DRE + DCF'!$S$41)/((1+$I15)^((5-$F$9)*3/12)) -> 60.950103 | L15: =(NPV($I15,'DRE + DCF'!$U$41:$AC$41,SUM('DRE + DCF'!$AD$41,('DRE + DCF'!$AE$38*(1-(L$18/$I15))*(1+L$18))/($I15-L$18)))+'DRE + DCF'!$S$41)/((1+$I15)^((5-$F$9)*3/12)) -> 61.028971 | M15: =(NPV($I15,'DRE + DCF'!$U$41:$AC$41,SUM('DRE + DCF'!$AD$41,('DRE + DCF'!$AE$38*(1-(M$18/$I15))*(1+M$18))/($I15-M$18)))+'DRE + DCF'!$S$41)/((1+$I15)^((5-$F$9)*3/12)) -> 61.10784 | N15: =(NPV($I15,'DRE + DCF'!$U$41:$AC$41,SUM('DRE + DCF'!$AD$41,('DRE + DCF'!$AE$38*(1-(N$18/$I15))*(1+N$18))/($I15-N$18)))+'DRE + DCF'!$S$41)/((1+$I15)^((5-$F$9)*3/12)) -> 61.186708 | O15: =(NPV($I15,'DRE + DCF'!$U$41:$AC$41,SUM('DRE + DCF'!$AD$41,('DRE + DCF'!$AE$38*(1-(O$18/$I15))*(1+O$18))/($I15-O$18)))+'DRE + DCF'!$S$41)/((1+$I15)^((5-$F$9)*3/12)) -> 61.265577 | P15: =(NPV($I15,'DRE + DCF'!$U$41:$AC$41,SUM('DRE + DCF'!$AD$41,('DRE + DCF'!$AE$38*(1-(P$18/$I15))*(1+P$18))/($I15-P$18)))+'DRE + DCF'!$S$41)/((1+$I15)^((5-$F$9)*3/12)) -> 61.344445 | Q15: =(NPV($I15,'DRE + DCF'!$U$41:$AC$41,SUM('DRE + DCF'!$AD$41,('DRE + DCF'!$AE$38*(1-(Q$18/$I15))*(1+Q$18))/($I15-Q$18)))+'DRE + DCF'!$S$41)/((1+$I15)^((5-$F$9)*3/12)) -> 61.423314 | ... S15: =(NPV($I15,'DRE + DCF'!$U$41:$AC$41,SUM('DRE + DCF'!$AD$41,('DRE + DCF'!$AE$38*(1-(S$18/$I15))*(1+S$18))/($I15-S$18)))+'DRE + DCF'!$S$41)/((1+$I15)^((5-$F$9)*3/12)) -> 61.58105
E16: Preço Teto | F16: =TIR!E12 -> 60.614178 | I16: =I15+0.5% -> 0.17510913 | J16: =(NPV($I16,'DRE + DCF'!$U$41:$AC$41,SUM('DRE + DCF'!$AD$41,('DRE + DCF'!$AE$38*(1-(J$18/$I16))*(1+J$18))/($I16-J$18)))+'DRE + DCF'!$S$41)/((1+$I16)^((5-$F$9)*3/12)) -> 57.907705 | K16: =(NPV($I16,'DRE + DCF'!$U$41:$AC$41,SUM('DRE + DCF'!$AD$41,('DRE + DCF'!$AE$38*(1-(K$18/$I16))*(1+K$18))/($I16-K$18)))+'DRE + DCF'!$S$41)/((1+$I16)^((5-$F$9)*3/12)) -> 57.981045 | L16: =(NPV($I16,'DRE + DCF'!$U$41:$AC$41,SUM('DRE + DCF'!$AD$41,('DRE + DCF'!$AE$38*(1-(L$18/$I16))*(1+L$18))/($I16-L$18)))+'DRE + DCF'!$S$41)/((1+$I16)^((5-$F$9)*3/12)) -> 58.054385 | M16: =(NPV($I16,'DRE + DCF'!$U$41:$AC$41,SUM('DRE + DCF'!$AD$41,('DRE + DCF'!$AE$38*(1-(M$18/$I16))*(1+M$18))/($I16-M$18)))+'DRE + DCF'!$S$41)/((1+$I16)^((5-$F$9)*3/12)) -> 58.127725 | N16: =(NPV($I16,'DRE + DCF'!$U$41:$AC$41,SUM('DRE + DCF'!$AD$41,('DRE + DCF'!$AE$38*(1-(N$18/$I16))*(1+N$18))/($I16-N$18)))+'DRE + DCF'!$S$41)/((1+$I16)^((5-$F$9)*3/12)) -> 58.201065 | O16: =(NPV($I16,'DRE + DCF'!$U$41:$AC$41,SUM('DRE + DCF'!$AD$41,('DRE + DCF'!$AE$38*(1-(O$18/$I16))*(1+O$18))/($I16-O$18)))+'DRE + DCF'!$S$41)/((1+$I16)^((5-$F$9)*3/12)) -> 58.274405 | P16: =(NPV($I16,'DRE + DCF'!$U$41:$AC$41,SUM('DRE + DCF'!$AD$41,('DRE + DCF'!$AE$38*(1-(P$18/$I16))*(1+P$18))/($I16-P$18)))+'DRE + DCF'!$S$41)/((1+$I16)^((5-$F$9)*3/12)) -> 58.347745 | Q16: =(NPV($I16,'DRE + DCF'!$U$41:$AC$41,SUM('DRE + DCF'!$AD$41,('DRE + DCF'!$AE$38*(1-(Q$18/$I16))*(1+Q$18))/($I16-Q$18)))+'DRE + DCF'!$S$41)/((1+$I16)^((5-$F$9)*3/12)) -> 58.421085 | ... S16: =(NPV($I16,'DRE + DCF'!$U$41:$AC$41,SUM('DRE + DCF'!$AD$41,('DRE + DCF'!$AE$38*(1-(S$18/$I16))*(1+S$18))/($I16-S$18)))+'DRE + DCF'!$S$41)/((1+$I16)^((5-$F$9)*3/12)) -> 58.567765
I17: =I16+0.5% -> 0.18010913 | J17: =(NPV($I17,'DRE + DCF'!$U$41:$AC$41,SUM('DRE + DCF'!$AD$41,('DRE + DCF'!$AE$38*(1-(J$18/$I17))*(1+J$18))/($I17-J$18)))+'DRE + DCF'!$S$41)/((1+$I17)^((5-$F$9)*3/12)) -> 55.160021 | K17: =(NPV($I17,'DRE + DCF'!$U$41:$AC$41,SUM('DRE + DCF'!$AD$41,('DRE + DCF'!$AE$38*(1-(K$18/$I17))*(1+K$18))/($I17-K$18)))+'DRE + DCF'!$S$41)/((1+$I17)^((5-$F$9)*3/12)) -> 55.228288 | L17: =(NPV($I17,'DRE + DCF'!$U$41:$AC$41,SUM('DRE + DCF'!$AD$41,('DRE + DCF'!$AE$38*(1-(L$18/$I17))*(1+L$18))/($I17-L$18)))+'DRE + DCF'!$S$41)/((1+$I17)^((5-$F$9)*3/12)) -> 55.296556 | M17: =(NPV($I17,'DRE + DCF'!$U$41:$AC$41,SUM('DRE + DCF'!$AD$41,('DRE + DCF'!$AE$38*(1-(M$18/$I17))*(1+M$18))/($I17-M$18)))+'DRE + DCF'!$S$41)/((1+$I17)^((5-$F$9)*3/12)) -> 55.364823 | N17: =(NPV($I17,'DRE + DCF'!$U$41:$AC$41,SUM('DRE + DCF'!$AD$41,('DRE + DCF'!$AE$38*(1-(N$18/$I17))*(1+N$18))/($I17-N$18)))+'DRE + DCF'!$S$41)/((1+$I17)^((5-$F$9)*3/12)) -> 55.43309 | O17: =(NPV($I17,'DRE + DCF'!$U$41:$AC$41,SUM('DRE + DCF'!$AD$41,('DRE + DCF'!$AE$38*(1-(O$18/$I17))*(1+O$18))/($I17-O$18)))+'DRE + DCF'!$S$41)/((1+$I17)^((5-$F$9)*3/12)) -> 55.501358 | P17: =(NPV($I17,'DRE + DCF'!$U$41:$AC$41,SUM('DRE + DCF'!$AD$41,('DRE + DCF'!$AE$38*(1-(P$18/$I17))*(1+P$18))/($I17-P$18)))+'DRE + DCF'!$S$41)/((1+$I17)^((5-$F$9)*3/12)) -> 55.569625 | Q17: =(NPV($I17,'DRE + DCF'!$U$41:$AC$41,SUM('DRE + DCF'!$AD$41,('DRE + DCF'!$AE$38*(1-(Q$18/$I17))*(1+Q$18))/($I17-Q$18)))+'DRE + DCF'!$S$41)/((1+$I17)^((5-$F$9)*3/12)) -> 55.637892 | ... S17: =(NPV($I17,'DRE + DCF'!$U$41:$AC$41,SUM('DRE + DCF'!$AD$41,('DRE + DCF'!$AE$38*(1-(S$18/$I17))*(1+S$18))/($I17-S$18)))+'DRE + DCF'!$S$41)/((1+$I17)^((5-$F$9)*3/12)) -> 55.774427
J18: =K18-0.25% -> 0.081156229 | K18: =L18-0.25% -> 0.083656229 | L18: =M18-0.25% -> 0.086156229 | M18: =N18-0.25% -> 0.088656229 | N18: ='DRE + DCF'!AG38 -> 0.091156229 | O18: =N18+0.25% -> 0.093656229 | P18: =O18+0.25% -> 0.096156229 | Q18: =P18+0.25% -> 0.098656229 | R18: =Q18+0.25% -> 0.10115623 | S18: =R18+0.25% -> 0.10365623
J19: Growth

Sheet Ke
K4: =Dashboard!$I$4 -> Banco do Brasil ($BBAS3)
A7: Páginas
A8: Dashboard
A9: Ke | E9: Atualizado em: 13/04/2023 | F9: 2023 | G9: =F9+1 -> 2024 | H9: =G9+1 -> 2025 | I9: =H9+1 -> 2026 | J9: =I9+1 -> 2027 | K9: =J9+1 -> 2028 | L9: =K9+1 -> 2029 | M9: =L9+1 -> 2030 | N9: =M9+1 -> 2031 | ... P9: =O9+1 -> 2033 | Q9: Descrição
A10: DRE + DCF | E10: DI | F10: 0.12008 | G10: 0.1082 | H10: 0.1062 | I10: 0.10765 | J10: 0.10959 | K10: 0.1113 | L10: 0.11248 | M10: 0.1132 | N10: 0.11362 | O10: 0.1139 | P10: 0.1139 | Q10: A taxa livre de risco no Brasil pode partir do DI, que é equivalente ao prêmio de um titulo IPCA+ do governo de mesmo prazo somado à inflação implicita.
A11: Contas Abertas | E11: CDS | F11: 0.003404 | G11: 0.005705487 | H11: 0.008640829 | I11: 0.012089975 | J11: 0.016020479 | K11: 0.019942676 | L11: 0.023348119 | M11: 0.026049827 | N11: 0.027900945 | O11: 0.028754619 | P11: 0.028463991 | Q11: Credit Default Swap (CDS)
A12: Balanço Patrimonial | E12: Inflação Implícita | F12: 0.0418 | G12: 0.04217 | H12: 0.04334 | I12: 0.04552 | J12: 0.04854 | K12: 0.05087 | L12: 0.05238 | M12: 0.0543 | N12: 0.05521 | O12: 0.05562 | P12: 0.05584
A13: Projeções - Receita | E13: Taxa Livre de Risco | F13: =F10-F11 -> 0.116676 | G13: =G10-G11 -> 0.10249451 | H13: =H10-H11 -> 0.097559171 | I13: =I10-I11 -> 0.095560025 | J13: =J10-J11 -> 0.093569521 | K13: =K10-K11 -> 0.091357324 | L13: =L10-L11 -> 0.089131881 | M13: =M10-M11 -> 0.087150173 | ... P13: =P10-P11 -> 0.085436009
A14: Painel de Índices | E14: Beta | F14: =SLOPE(H23:H766,I23:I766) -> 1.0229391 | G14: =F14 -> 1.0229391 | H14: =G14 -> 1.0229391 | I14: =H14 -> 1.0229391 | J14: =I14 -> 1.0229391 | K14: =J14 -> 1.0229391 | L14: =K14 -> 1.0229391 | M14: =L14 -> 1.0229391 | N14: =M14 -> 1.0229391 | ... P14: =O14 -> 1.0229391 | Q14: Beta Clássico
A15: Projeções Trimestrais | E15: Prêmio de Risco | F15: 0.065 | G15: 0.065 | H15: 0.065 | I15: 0.065 | J15: 0.065 | K15: 0.065 | L15: 0.065 | M15: 0.065 | N15: 0.065 | O15: 0.065 | P15: 0.065 | Q15: Dados Alternativos FGV: https://goo.gl/bBfwGq
E16: Custo de Capital Próprio (Ke) | F16: =F13+F14*F15 -> 0.18316704 | G16: =G13+G14*G15 -> 0.16898555 | H16: =H13+H14*H15 -> 0.16405021 | I16: =I13+I14*I15 -> 0.16205106 | J16: =J13+J14*J15 -> 0.16006056 | K16: =K13+K14*K15 -> 0.15784836 | L16: =L13+L14*L15 -> 0.15562292 | M16: =M13+M14*M15 -> 0.15364121 | ... P16: =P13+P14*P15 -> 0.15192705
E17: Desconto | F17: =(1+F16)^((5-Dashboard!$F$9)*3/12) -> 1.0429453 | G17: =F17*(1+G16) -> 1.2191879 | H17: =G17*(1+H16) -> 1.419196 | I17: =H17*(1+I16) -> 1.6491782 | J17: =I17*(1+J16) -> 1.9131466 | K17: =J17*(1+K16) -> 2.2151336 | L17: =K17*(1+L16) -> 2.5598592 | M17: =L17*(1+M16) -> 2.9531591 | N17: =M17*(1+N16) -> 3.4026597 | ... P17: =O17*(1+P16) -> 4.5139722
E21: Data | F21: Preço BBAS3 | G21: IBOV | H21: Variação BBAS3 | I21: Variação IBOV
E22: 44144 | F22: 26.152027 | G22: 103913 | H22: - | I22: -
E23: 44145 | F23: 27.487614 | G23: 105351 | H23: =F23/F22-1 -> 0.051070114 | I23: =G23/G22-1 -> 0.0138385
E24: 44146 | F24: 27.319668 | G24: 104532 | H24: =F24/F23-1 -> -0.0061098792 | I24: =G24/G23-1 -> -0.0077740126
E25: 44147 | F25: 26.176014 | G25: 102175 | H25: =F25/F24-1 -> -0.041861929 | I25: =G25/G24-1 -> -0.022548119
E26: 44148 | F26: 26.431938 | G26: 104512 | H26: =F26/F25-1 -> 0.0097770424 | I26: =G26/G25-1 -> 0.022872523
E27: 44151 | F27: 27.111734 | G27: 106430 | H27: =F27/F26-1 -> 0.025718735 | I27: =G27/G26-1 -> 0.01835196
E28: 44152 | F28: 27.509712 | G28: 107229 | H28: =F28/F27-1 -> 0.014679179 | I28: =G28/G27-1 -> 0.0075072818
E29: 44153 | F29: 27.574066 | G29: 106483 | H29: =F29/F28-1 -> 0.0023393193 | I29: =G29/G28-1 -> -0.0069570732
E30: 44154 | F30: 27.847555 | G30: 106517 | H30: =F30/F29-1 -> 0.0099183414 | I30: =G30/G29-1 -> 0.00031929979
E31: 44158 | F31: 27.767117 | G31: 107379 | H31: =F31/F30-1 -> -0.0028885121 | I31: =G31/G30-1 -> 0.0080926049
E32: 44159 | F32: 28.507145 | G32: 109786 | H32: =F32/F31-1 -> 0.026651236 | I32: =G32/G31-1 -> 0.022415929
E33: 44160 | F33: 28.426706 | G33: 110133 | H33: =F33/F32-1 -> -0.0028217136 | I33: =G33/G32-1 -> 0.0031606944
E34: 44161 | F34: 27.976252 | G34: 110227 | H34: =F34/F33-1 -> -0.015846155 | I34: =G34/G33-1 -> 0.00085351348
... E766: 45237 | F766: 51.02 | G766: 119268 | H766: =F766/F765-1 -> 0.011298295 | I766: =G766/G765-1 -> 0.0065914404

Sheet TIR
L4: =Dashboard!$I$4 -> Banco do Brasil ($BBAS3)
A7: Páginas
A8: Dashboard
A9: Ke
A10: DRE + DCF | C10: Delta | D10: TIR | E10: Preço Justo | F10: Valor da Perpetuidade | G10: Growth | H10: Ke | S10: Taxa de Desconto
A11: Contas Abertas | H11: 2023 | I11: 2024 | J11: 2025 | K11: 2026 | L11: 2027 | M11: 2028 | N11: 2029 | O11: 2030 | P11: 2031 | Q11: 2032 | R11: 2033 | S11: 2023 | T11: 2024 | U11: 2025 | V11: 2026 | W11: 2027 | X11: 2028 | Y11: 2029 | Z11: 2030 | AA11: 2031 | AB11: 2032 | AC11: 2033
A12: Balanço Patrimonial | C12: Preço Teto | D12: =AVERAGE(AVERAGE(Ke!$F$16:$P$16),MAX(Ke!F16:P16)) -> 0.17163809 | E12: {=SUM('DRE + DCF'!$S$41/TIR!S12,'DRE + DCF'!$U$41:$AD$41/TIR!T12:AC12,TIR!F12)} -> 60.614178 | F12: ='DRE + DCF'!$AE$38*'DRE + DCF'!$AE$39*(1+G12)/(R12-G12)/AC12 -> 34.027734 | G12: =R12*(1-'DRE + DCF'!$AE$39) -> 0.10298285 | H12: =$D12 -> 0.17163809 | I12: =$D12 -> 0.17163809 | J12: =$D12 -> 0.17163809 | K12: =$D12 -> 0.17163809 | L12: =$D12 -> 0.17163809 | M12: =$D12 -> 0.17163809 | N12: =$D12 -> 0.17163809 | O12: =$D12 -> 0.17163809 | ... R12: =$D12 -> 0.17163809 | S12: =(1+H12)^((5-Dashboard!$F$9)*3/12) -> 1.0403953 | T12: =(S12)*(1+I12) -> 1.2189667 | U12: =(T12)*(1+J12) -> 1.4281878 | V12: =(U12)*(1+K12) -> 1.6733193 | W12: =(V12)*(1+L12) -> 1.9605246 | X12: =(W12)*(1+M12) -> 2.2970253 | Y12: =(X12)*(1+N12) -> 2.6912823 | Z12: =(Y12)*(1+O12) -> 3.1532089 | AA12: =(Z12)*(1+P12) -> 3.6944196 | ... AC12: =(AB12)*(1+R12) -> 5.071462
A13: Projeções - Receita | C13: =ABS(E13-Dashboard!$F$13) -> 116.4543 | D13: ='DRE + DCF'!AG38+0.00005 -> 0.091206229 | E13: {=SUM('DRE + DCF'!$S$41/TIR!S13,'DRE + DCF'!$U$41:$AD$41/TIR!T13:AC13,TIR!F13)} -> 165.9643 | F13: ='DRE + DCF'!$AE$38*'DRE + DCF'!$AE$39*(1+G13)/(R13-G13)/AC13 -> 126.93467 | G13: =R13*(1-'DRE + DCF'!$AE$39) -> 0.054723737 | H13: =$D13 -> 0.091206229 | I13: =$D13 -> 0.091206229 | J13: =$D13 -> 0.091206229 | K13: =$D13 -> 0.091206229 | L13: =$D13 -> 0.091206229 | M13: =$D13 -> 0.091206229 | N13: =$D13 -> 0.091206229 | O13: =$D13 -> 0.091206229 | ... R13: =$D13 -> 0.091206229 | S13: =(1+H13)^((5-Dashboard!$F$9)*3/12) -> 1.0220607 | T13: =(S13)*(1+I13) -> 1.1152791 | U13: =(T13)*(1+J13) -> 1.2169994 | V13: =(U13)*(1+K13) -> 1.3279974 | W13: =(V13)*(1+L13) -> 1.449119 | X13: =(W13)*(1+M13) -> 1.5812877 | Y13: =(X13)*(1+N13) -> 1.725511 | Z13: =(Y13)*(1+O13) -> 1.8828883 | AA13: =(Z13)*(1+P13) -> 2.0546195 | ... AC13: =(AB13)*(1+R13) -> 2.4464992
A14: Painel de Índices | C14: =ABS(E14-Dashboard!$F$13) -> 116.183 | D14: =D13+0.0001 -> 0.091306229 | E14: {=SUM('DRE + DCF'!$S$41/TIR!S14,'DRE + DCF'!$U$41:$AD$41/TIR!T14:AC14,TIR!F14)} -> 165.693 | F14: ='DRE + DCF'!$AE$38*'DRE + DCF'!$AE$39*(1+G14)/(R14-G14)/AC14 -> 126.68382 | G14: =R14*(1-'DRE + DCF'!$AE$39) -> 0.054783737 | H14: =$D14 -> 0.091306229 | I14: =$D14 -> 0.091306229 | J14: =$D14 -> 0.091306229 | K14: =$D14 -> 0.091306229 | L14: =$D14 -> 0.091306229 | M14: =$D14 -> 0.091306229 | N14: =$D14 -> 0.091306229 | O14: =$D14 -> 0.091306229 | ... R14: =$D14 -> 0.091306229 | S14: =(1+H14)^((5-Dashboard!$F$9)*3/12) -> 1.0220842 | T14: =(S14)*(1+I14) -> 1.1154068 | U14: =(T14)*(1+J14) -> 1.2172504 | V14: =(U14)*(1+K14) -> 1.3283929 | W14: =(V14)*(1+L14) -> 1.4496835 | X14: =(W14)*(1+M14) -> 1.5820486 | Y14: =(X14)*(1+N14) -> 1.7264995 | Z14: =(Y14)*(1+O14) -> 1.8841397 | AA14: =(Z14)*(1+P14) -> 2.0561734 | ... AC14: =(AB14)*(1+R14) -> 2.4487982
A15: Projeções Trimestrais | C15: =ABS(E15-Dashboard!$F$13) -> 115.91237 | D15: =D14+0.0001 -> 0.091406229 | E15: {=SUM('DRE + DCF'!$S$41/TIR!S15,'DRE + DCF'!$U$41:$AD$41/TIR!T15:AC15,TIR!F15)} -> 165.42237 | F15: ='DRE + DCF'!$AE$38*'DRE + DCF'!$AE$39*(1+G15)/(R15-G15)/AC15 -> 126.43362 | G15: =R15*(1-'DRE + DCF'!$AE$39) -> 0.054843737 | H15: =$D15 -> 0.091406229 | I15: =$D15 -> 0.091406229 | J15: =$D15 -> 0.091406229 | K15: =$D15 -> 0.091406229 | L15: =$D15 -> 0.091406229 | M15: =$D15 -> 0.091406229 | N15: =$D15 -> 0.091406229 | O15: =$D15 -> 0.091406229 | ... R15: =$D15 -> 0.091406229 | S15: =(1+H15)^((5-Dashboard!$F$9)*3/12) -> 1.0221076 | T15: =(S15)*(1+I15) -> 1.1155346 | U15: =(T15)*(1+J15) -> 1.2175014 | V15: =(U15)*(1+K15) -> 1.3287886 | W15: =(V15)*(1+L15) -> 1.4502481 | X15: =(W15)*(1+M15) -> 1.5828099 | Y15: =(X15)*(1+N15) -> 1.7274885 | Z15: =(Y15)*(1+O15) -> 1.8853918 | AA15: =(Z15)*(1+P15) -> 2.0577283 | ... AC15: =(AB15)*(1+R15) -> 2.4510992
C16: =ABS(E16-Dashboard!$F$13) -> 115.64242 | D16: =D15+0.0001 -> 0.091506229 | E16: {=SUM('DRE + DCF'!$S$41/TIR!S16,'DRE + DCF'!$U$41:$AD$41/TIR!T16:AC16,TIR!F16)} -> 165.15242 | F16: ='DRE + DCF'!$AE$38*'DRE + DCF'!$AE$39*(1+G16)/(R16-G16)/AC16 -> 126.18408 | G16: =R16*(1-'DRE + DCF'!$AE$39) -> 0.054903737 | H16: =$D16 -> 0.091506229 | I16: =$D16 -> 0.091506229 | J16: =$D16 -> 0.091506229 | K16: =$D16 -> 0.091506229 | L16: =$D16 -> 0.091506229 | M16: =$D16 -> 0.091506229 | N16: =$D16 -> 0.091506229 | O16: =$D16 -> 0.091506229 | ... R16: =$D16 -> 0.091506229 | S16: =(1+H16)^((5-Dashboard!$F$9)*3/12) -> 1.022131 | T16: =(S16)*(1+I16) -> 1.1156623 | U16: =(T16)*(1+J16) -> 1.2177524 | V16: =(U16)*(1+K16) -> 1.3291843 | W16: =(V16)*(1+L16) -> 1.450813 | X16: =(W16)*(1+M16) -> 1.5835714 | Y16: =(X16)*(1+N16) -> 1.728478 | Z16: =(Y16)*(1+O16) -> 1.8866445 | AA16: =(Z16)*(1+P16) -> 2.0592843 | ... AC16: =(AB16)*(1+R16) -> 2.4534021
C17: =ABS(E17-Dashboard!$F$13) -> 115.37313 | D17: =D16+0.0001 -> 0.091606229 | E17: {=SUM('DRE + DCF'!$S$41/TIR!S17,'DRE + DCF'!$U$41:$AD$41/TIR!T17:AC17,TIR!F17)} -> 164.88313 | F17: ='DRE + DCF'!$AE$38*'DRE + DCF'!$AE$39*(1+G17)/(R17-G17)/AC17 -> 125.93519 | G17: =R17*(1-'DRE + DCF'!$AE$39) -> 0.054963737 | H17: =$D17 -> 0.091606229 | I17: =$D17 -> 0.091606229 | J17: =$D17 -> 0.091606229 | K17: =$D17 -> 0.091606229 | L17: =$D17 -> 0.091606229 | M17: =$D17 -> 0.091606229 | N17: =$D17 -> 0.091606229 | O17: =$D17 -> 0.091606229 | ... R17: =$D17 -> 0.091606229 | S17: =(1+H17)^((5-Dashboard!$F$9)*3/12) -> 1.0221544 | T17: =(S17)*(1+I17) -> 1.1157901 | U17: =(T17)*(1+J17) -> 1.2180034 | V17: =(U17)*(1+K17) -> 1.3295801 | W17: =(V17)*(1+L17) -> 1.451378 | X17: =(W17)*(1+M17) -> 1.5843332 | Y17: =(X17)*(1+N17) -> 1.729468 | Z17: =(Y17)*(1+O17) -> 1.887898 | AA17: =(Z17)*(1+P17) -> 2.0608413 | ... AC17: =(AB17)*(1+R17) -> 2.455707
C18: =ABS(E18-Dashboard!$F$13) -> 115.10451 | D18: =D17+0.0001 -> 0.091706229 | E18: {=SUM('DRE + DCF'!$S$41/TIR!S18,'DRE + DCF'!$U$41:$AD$41/TIR!T18:AC18,TIR!F18)} -> 164.61451 | F18: ='DRE + DCF'!$AE$38*'DRE + DCF'!$AE$39*(1+G18)/(R18-G18)/AC18 -> 125.68695 | G18: =R18*(1-'DRE + DCF'!$AE$39) -> 0.055023737 | H18: =$D18 -> 0.091706229 | I18: =$D18 -> 0.091706229 | J18: =$D18 -> 0.091706229 | K18: =$D18 -> 0.091706229 | L18: =$D18 -> 0.091706229 | M18: =$D18 -> 0.091706229 | N18: =$D18 -> 0.091706229 | O18: =$D18 -> 0.091706229 | ... R18: =$D18 -> 0.091706229 | S18: =(1+H18)^((5-Dashboard!$F$9)*3/12) -> 1.0221778 | T18: =(S18)*(1+I18) -> 1.1159179 | U18: =(T18)*(1+J18) -> 1.2182545 | V18: =(U18)*(1+K18) -> 1.329976 | W18: =(V18)*(1+L18) -> 1.4519431 | X18: =(W18)*(1+M18) -> 1.5850953 | Y18: =(X18)*(1+N18) -> 1.7304585 | Z18: =(Y18)*(1+O18) -> 1.8891523 | AA18: =(Z18)*(1+P18) -> 2.0623993 | ... AC18: =(AB18)*(1+R18) -> 2.4580139
C19: =ABS(E19-Dashboard!$F$13) -> 114.83656 | D19: =D18+0.0001 -> 0.091806229 | E19: {=SUM('DRE + DCF'!$S$41/TIR!S19,'DRE + DCF'!$U$41:$AD$41/TIR!T19:AC19,TIR!F19)} -> 164.34656 | F19: ='DRE + DCF'!$AE$38*'DRE + DCF'!$AE$39*(1+G19)/(R19-G19)/AC19 -> 125.43936 | G19: =R19*(1-'DRE + DCF'!$AE$39) -> 0.055083737 | H19: =$D19 -> 0.091806229 | I19: =$D19 -> 0.091806229 | J19: =$D19 -> 0.091806229 | K19: =$D19 -> 0.091806229 | L19: =$D19 -> 0.091806229 | M19: =$D19 -> 0.091806229 | N19: =$D19 -> 0.091806229 | O19: =$D19 -> 0.091806229 | ... R19: =$D19 -> 0.091806229 | S19: =(1+H19)^((5-Dashboard!$F$9)*3/12) -> 1.0222012 | T19: =(S19)*(1+I19) -> 1.1160457 | U19: =(T19)*(1+J19) -> 1.2185056 | V19: =(U19)*(1+K19) -> 1.330372 | W19: =(V19)*(1+L19) -> 1.4525084 | X19: =(W19)*(1+M19) -> 1.5858578 | Y19: =(X19)*(1+N19) -> 1.7314494 | Z19: =(Y19)*(1+O19) -> 1.8904072 | AA19: =(Z19)*(1+P19) -> 2.0639584 | ... AC19: =(AB19)*(1+R19) -> 2.4603227
C20: =ABS(E20-Dashboard!$F$13) -> 114.56926 | D20: =D19+0.0001 -> 0.091906229 | E20: {=SUM('DRE + DCF'!$S$41/TIR!S20,'DRE + DCF'!$U$41:$AD$41/TIR!T20:AC20,TIR!F20)} -> 164.07926 | F20: ='DRE + DCF'!$AE$38*'DRE + DCF'!$AE$39*(1+G20)/(R20-G20)/AC20 -> 125.19242 | G20: =R20*(1-'DRE + DCF'!$AE$39) -> 0.055143737 | H20: =$D20 -> 0.091906229 | I20: =$D20 -> 0.091906229 | J20: =$D20 -> 0.091906229 | K20: =$D20 -> 0.091906229 | L20: =$D20 -> 0.091906229 | M20: =$D20 -> 0.091906229 | N20: =$D20 -> 0.091906229 | O20: =$D20 -> 0.091906229 | ... R20: =$D20 -> 0.091906229 | S20: =(1+H20)^((5-Dashboard!$F$9)*3/12) -> 1.0222246 | T20: =(S20)*(1+I20) -> 1.1161734 | U20: =(T20)*(1+J20) -> 1.2187567 | V20: =(U20)*(1+K20) -> 1.3307681 | W20: =(V20)*(1+L20) -> 1.4530739 | X20: =(W20)*(1+M20) -> 1.5866205 | Y20: =(X20)*(1+N20) -> 1.7324408 | Z20: =(Y20)*(1+O20) -> 1.8916629 | AA20: =(Z20)*(1+P20) -> 2.0655185 | ... AC20: =(AB20)*(1+R20) -> 2.4626334
C21: =ABS(E21-Dashboard!$F$13) -> 114.30263 | D21: =D20+0.0001 -> 0.092006229 | E21: {=SUM('DRE + DCF'!$S$41/TIR!S21,'DRE + DCF'!$U$41:$AD$41/TIR!T21:AC21,TIR!F21)} -> 163.81263 | F21: ='DRE + DCF'!$AE$38*'DRE + DCF'!$AE$39*(1+G21)/(R21-G21)/AC21 -> 124.94612 | G21: =R21*(1-'DRE + DCF'!$AE$39) -> 0.055203737 | H21: =$D21 -> 0.092006229 | I21: =$D21 -> 0.092006229 | J21: =$D21 -> 0.092006229 | K21: =$D21 -> 0.092006229 | L21: =$D21 -> 0.092006229 | M21: =$D21 -> 0.092006229 | N21: =$D21 -> 0.092006229 | O21: =$D21 -> 0.092006229 | ... R21: =$D21 -> 0.092006229 | S21: =(1+H21)^((5-Dashboard!$F$9)*3/12) -> 1.022248 | T21: =(S21)*(1+I21) -> 1.1163012 | U21: =(T21)*(1+J21) -> 1.2190079 | V21: =(U21)*(1+K21) -> 1.3311642 | W21: =(V21)*(1+L21) -> 1.4536396 | X21: =(W21)*(1+M21) -> 1.5873835 | Y21: =(X21)*(1+N21) -> 1.7334326 | Z21: =(Y21)*(1+O21) -> 1.8929193 | AA21: =(Z21)*(1+P21) -> 2.0670796 | ... AC21: =(AB21)*(1+R21) -> 2.4649461
C22: =ABS(E22-Dashboard!$F$13) -> 114.03665 | D22: =D21+0.0001 -> 0.092106229 | E22: {=SUM('DRE + DCF'!$S$41/TIR!S22,'DRE + DCF'!$U$41:$AD$41/TIR!T22:AC22,TIR!F22)} -> 163.54665 | F22: ='DRE + DCF'!$AE$38*'DRE + DCF'!$AE$39*(1+G22)/(R22-G22)/AC22 -> 124.70046 | G22: =R22*(1-'DRE + DCF'!$AE$39) -> 0.055263737 | H22: =$D22 -> 0.092106229 | I22: =$D22 -> 0.092106229 | J22: =$D22 -> 0.092106229 | K22: =$D22 -> 0.092106229 | L22: =$D22 -> 0.092106229 | M22: =$D22 -> 0.092106229 | N22: =$D22 -> 0.092106229 | O22: =$D22 -> 0.092106229 | ... R22: =$D22 -> 0.092106229 | S22: =(1+H22)^((5-Dashboard!$F$9)*3/12) -> 1.0222714 | T22: =(S22)*(1+I22) -> 1.116429 | U22: =(T22)*(1+J22) -> 1.2192591 | V22: =(U22)*(1+K22) -> 1.3315604 | W22: =(V22)*(1+L22) -> 1.4542054 | X22: =(W22)*(1+M22) -> 1.5881468 | Y22: =(X22)*(1+N22) -> 1.734425 | Z22: =(Y22)*(1+O22) -> 1.8941763 | AA22: =(Z22)*(1+P22) -> 2.0686418 | ... AC22: =(AB22)*(1+R22) -> 2.4672608
C23: =ABS(E23-Dashboard!$F$13) -> 113.77133 | D23: =D22+0.0001 -> 0.092206229 | E23: {=SUM('DRE + DCF'!$S$41/TIR!S23,'DRE + DCF'!$U$41:$AD$41/TIR!T23:AC23,TIR!F23)} -> 163.28133 | F23: ='DRE + DCF'!$AE$38*'DRE + DCF'!$AE$39*(1+G23)/(R23-G23)/AC23 -> 124.45545 | G23: =R23*(1-'DRE + DCF'!$AE$39) -> 0.055323737 | H23: =$D23 -> 0.092206229 | I23: =$D23 -> 0.092206229 | J23: =$D23 -> 0.092206229 | K23: =$D23 -> 0.092206229 | L23: =$D23 -> 0.092206229 | M23: =$D23 -> 0.092206229 | N23: =$D23 -> 0.092206229 | O23: =$D23 -> 0.092206229 | ... R23: =$D23 -> 0.092206229 | S23: =(1+H23)^((5-Dashboard!$F$9)*3/12) -> 1.0222948 | T23: =(S23)*(1+I23) -> 1.1165568 | U23: =(T23)*(1+J23) -> 1.2195103 | V23: =(U23)*(1+K23) -> 1.3319567 | W23: =(V23)*(1+L23) -> 1.4547714 | X23: =(W23)*(1+M23) -> 1.5889104 | Y23: =(X23)*(1+N23) -> 1.7354178 | Z23: =(Y23)*(1+O23) -> 1.8954342 | AA23: =(Z23)*(1+P23) -> 2.070205 | ... AC23: =(AB23)*(1+R23) -> 2.4695775
C24: =ABS(E24-Dashboard!$F$13) -> 113.50667 | D24: =D23+0.0001 -> 0.092306229 | E24: {=SUM('DRE + DCF'!$S$41/TIR!S24,'DRE + DCF'!$U$41:$AD$41/TIR!T24:AC24,TIR!F24)} -> 163.01667 | F24: ='DRE + DCF'!$AE$38*'DRE + DCF'!$AE$39*(1+G24)/(R24-G24)/AC24 -> 124.21107 | G24: =R24*(1-'DRE + DCF'!$AE$39) -> 0.055383737 | H24: =$D24 -> 0.092306229 | I24: =$D24 -> 0.092306229 | J24: =$D24 -> 0.092306229 | K24: =$D24 -> 0.092306229 | L24: =$D24 -> 0.092306229 | M24: =$D24 -> 0.092306229 | N24: =$D24 -> 0.092306229 | O24: =$D24 -> 0.092306229 | ... R24: =$D24 -> 0.092306229 | S24: =(1+H24)^((5-Dashboard!$F$9)*3/12) -> 1.0223182 | T24: =(S24)*(1+I24) -> 1.1166846 | U24: =(T24)*(1+J24) -> 1.2197615 | V24: =(U24)*(1+K24) -> 1.3323531 | W24: =(V24)*(1+L24) -> 1.4553376 | X24: =(W24)*(1+M24) -> 1.5896743 | Y24: =(X24)*(1+N24) -> 1.7364111 | Z24: =(Y24)*(1+O24) -> 1.8966927 | AA24: =(Z24)*(1+P24) -> 2.0717693 | ... AC24: =(AB24)*(1+R24) -> 2.4718961
C25: =ABS(E25-Dashboard!$F$13) -> 113.24265 | D25: =D24+0.0001 -> 0.092406229 | E25: {=SUM('DRE + DCF'!$S$41/TIR!S25,'DRE + DCF'!$U$41:$AD$41/TIR!T25:AC25,TIR!F25)} -> 162.75265 | F25: ='DRE + DCF'!$AE$38*'DRE + DCF'!$AE$39*(1+G25)/(R25-G25)/AC25 -> 123.96733 | G25: =R25*(1-'DRE + DCF'!$AE$39) -> 0.055443737 | H25: =$D25 -> 0.092406229 | I25: =$D25 -> 0.092406229 | J25: =$D25 -> 0.092406229 | K25: =$D25 -> 0.092406229 | L25: =$D25 -> 0.092406229 | M25: =$D25 -> 0.092406229 | N25: =$D25 -> 0.092406229 | O25: =$D25 -> 0.092406229 | ... R25: =$D25 -> 0.092406229 | S25: =(1+H25)^((5-Dashboard!$F$9)*3/12) -> 1.0223416 | T25: =(S25)*(1+I25) -> 1.1168124 | U25: =(T25)*(1+J25) -> 1.2200128 | V25: =(U25)*(1+K25) -> 1.3327496 | W25: =(V25)*(1+L25) -> 1.4559039 | X25: =(W25)*(1+M25) -> 1.5904385 | Y25: =(X25)*(1+N25) -> 1.7374049 | Z25: =(Y25)*(1+O25) -> 1.897952 | AA25: =(Z25)*(1+P25) -> 2.0733345 | ... AC25: =(AB25)*(1+R25) -> 2.4742166
C26: =ABS(E26-Dashboard!$F$13) -> 112.97928 | D26: =D25+0.0001 -> 0.092506229 | E26: {=SUM('DRE + DCF'!$S$41/TIR!S26,'DRE + DCF'!$U$41:$AD$41/TIR!T26:AC26,TIR!F26)} -> 162.48928 | F26: ='DRE + DCF'!$AE$38*'DRE + DCF'!$AE$39*(1+G26)/(R26-G26)/AC26 -> 123.72422 | G26: =R26*(1-'DRE + DCF'!$AE$39) -> 0.055503737 | H26: =$D26 -> 0.092506229 | I26: =$D26 -> 0.092506229 | J26: =$D26 -> 0.092506229 | K26: =$D26 -> 0.092506229 | L26: =$D26 -> 0.092506229 | M26: =$D26 -> 0.092506229 | N26: =$D26 -> 0.092506229 | O26: =$D26 -> 0.092506229 | ... R26: =$D26 -> 0.092506229 | S26: =(1+H26)^((5-Dashboard!$F$9)*3/12) -> 1.022365 | T26: =(S26)*(1+I26) -> 1.1169401 | U26: =(T26)*(1+J26) -> 1.2202641 | V26: =(U26)*(1+K26) -> 1.3331461 | W26: =(V26)*(1+L26) -> 1.4564704 | X26: =(W26)*(1+M26) -> 1.591203 | Y26: =(X26)*(1+N26) -> 1.7383992 | Z26: =(Y26)*(1+O26) -> 1.8992119 | AA26: =(Z26)*(1+P26) -> 2.0749009 | ... AC26: =(AB26)*(1+R26) -> 2.4765391
C27: =ABS(E27-Dashboard!$F$13) -> 112.71656 | D27: =D26+0.0001 -> 0.092606229 | E27: {=SUM('DRE + DCF'!$S$41/TIR!S27,'DRE + DCF'!$U$41:$AD$41/TIR!T27:AC27,TIR!F27)} -> 162.22656 | F27: ='DRE + DCF'!$AE$38*'DRE + DCF'!$AE$39*(1+G27)/(R27-G27)/AC27 -> 123.48174 | G27: =R27*(1-'DRE + DCF'!$AE$39) -> 0.055563737 | H27: =$D27 -> 0.092606229 | I27: =$D27 -> 0.092606229 | J27: =$D27 -> 0.092606229 | K27: =$D27 -> 0.092606229 | L27: =$D27 -> 0.092606229 | M27: =$D27 -> 0.092606229 | N27: =$D27 -> 0.092606229 | O27: =$D27 -> 0.092606229 | ... R27: =$D27 -> 0.092606229 | S27: =(1+H27)^((5-Dashboard!$F$9)*3/12) -> 1.0223884 | T27: =(S27)*(1+I27) -> 1.1170679 | U27: =(T27)*(1+J27) -> 1.2205154 | V27: =(U27)*(1+K27) -> 1.3335427 | W27: =(V27)*(1+L27) -> 1.4570371 | X27: =(W27)*(1+M27) -> 1.5919678 | Y27: =(X27)*(1+N27) -> 1.7393939 | Z27: =(Y27)*(1+O27) -> 1.9004726 | AA27: =(Z27)*(1+P27) -> 2.0764682 | ... AC27: =(AB27)*(1+R27) -> 2.4788636
... C3382: =ABS(E3382-Dashboard!$F$13) -> 36.02201 | D3382: =D3381+0.0001 -> 0.42810623 | E3382: {=SUM('DRE + DCF'!$S$41/TIR!S3382,'DRE + DCF'!$U$41:$AD$41/TIR!T3382:AC3382,TIR!F3382)} -> 13.48799 | F3382: ='DRE + DCF'!$AE$38*'DRE + DCF'!$AE$39*(1+G3382)/(R3382-G3382)/AC3382 -> 2.0438664 | G3382: =R3382*(1-'DRE + DCF'!$AE$39) -> 0.25686374 | H3382: =$D3382 -> 0.42810623 | I3382: =$D3382 -> 0.42810623 | J3382: =$D3382 -> 0.42810623 | K3382: =$D3382 -> 0.42810623 | L3382: =$D3382 -> 0.42810623 | M3382: =$D3382 -> 0.42810623 | N3382: =$D3382 -> 0.42810623 | O3382: =$D3382 -> 0.42810623 | ... R3382: =$D3382 -> 0.42810623 | S3382: =(1+H3382)^((5-Dashboard!$F$9)*3/12) -> 1.0931761 | T3382: =(S3382)*(1+I3382) -> 1.5611716 | U3382: =(T3382)*(1+J3382) -> 2.2295189 | V3382: =(U3382)*(1+K3382) -> 3.1839898 | W3382: =(V3382)*(1+L3382) -> 4.5470757 | X3382: =(W3382)*(1+M3382) -> 6.4937071 | Y3382: =(X3382)*(1+N3382) -> 9.2737035 | Z3382: =(Y3382)*(1+O3382) -> 13.243834 | AA3382: =(Z3382)*(1+P3382) -> 18.913602 | ... AC3382: =(AB3382)*(1+R3382) -> 38.574052

Sheet DRE + DCF
O4: =Dashboard!$I$4 -> Banco do Brasil ($BBAS3)
A7: Páginas
A8: Dashboard
A9: Ke | F9: 2014 | G9: 2015 | H9: 2016 | I9: 2017 | J9: 2018 | K9: 2019 | L9: 2020 | M9: 2021 | N9: 2022 | O9: 1T23 | P9: 2T23 | Q9: 3T23 | R9: 4T23 | S9: YTG23 | T9: 2023 | U9: 2024 | V9: 2025 | W9: 2026 | X9: 2027 | Y9: 2028 | Z9: 2029 | AA9: 2030 | AB9: 2031 | AC9: 2032 | AD9: 2033
A10: DRE + DCF | E10: Margem Financeira Líquida | F10: ='Projeções - Receitas'!F26 -> 2.7953349e+10 | G10: ='Projeções - Receitas'!G26 -> 2.7970373e+10 | H10: ='Projeções - Receitas'!H26 -> 2.647592e+10 | I10: ='Projeções - Receitas'!I26 -> 3.1171212e+10 | J10: ='Projeções - Receitas'!J26 -> 3.4564593e+10 | K10: ='Projeções - Receitas'!K26 -> 3.9015565e+10 | L10: ='Projeções - Receitas'!L26 -> 3.4616132e+10 | M10: ='Projeções - Receitas'!M26 -> 4.6197474e+10 | ... AD10: ='Projeções - Receitas'!AD26 -> 1.4634777e+11
A11: Contas Abertas | E11: Crescimento da Margem Financeira Líquida (YoY)¹ | F11: - | G11: =G10/F10-1 -> 0.00060900094 | H11: =H10/G10-1 -> -0.05342984 | I11: =I10/H10-1 -> 0.17734197 | J11: =J10/I10-1 -> 0.10886264 | K11: =K10/J10-1 -> 0.1287726 | L11: =L10/K10-1 -> -0.11276098 | M11: =M10/L10-1 -> 0.33456488 | N11: =N10/M10-1 -> 0.22626163 | T11: =T10/N10-1 -> 0.11634429 | U11: =U10/T10-1 -> -0.15034234 | V11: =V10/U10-1 -> 0.10608002 | W11: =W10/V10-1 -> 0.10523679 | X11: =X10/W10-1 -> 0.10494344 | Y11: =Y10/X10-1 -> 0.10478402 | Z11: =Z10/Y10-1 -> 0.10468132 | AA11: =AA10/Z10-1 -> 0.098645632 | AB11: =AB10/AA10-1 -> 0.080743461 | ... AD11: =AD10/AC10-1 -> 0.28947583
A12: Balanço Patrimonial | E12: Outras Receitas Operacionais | F12: ='Projeções - Receitas'!F133 -> 2.1778487e+10 | G12: ='Projeções - Receitas'!G133 -> 2.2047848e+10 | H12: ='Projeções - Receitas'!H133 -> 2.3794116e+10 | I12: ='Projeções - Receitas'!I133 -> 2.5941416e+10 | J12: ='Projeções - Receitas'!J133 -> 2.7452372e+10 | K12: ='Projeções - Receitas'!K133 -> 2.9208671e+10 | L12: ='Projeções - Receitas'!L133 -> 2.8701888e+10 | M12: ='Projeções - Receitas'!M133 -> 2.9343336e+10 | ... AD12: ='Projeções - Receitas'!AD133 -> 5.236836e+10
A13: Projeções - Receita | E13: Crescimento das Outra Receitas Operacionais (YoY)¹ | F13: - | G13: =G12/F12-1 -> 0.012368192 | H13: =H12/G12-1 -> 0.079203561 | I13: =I12/H12-1 -> 0.090245008 | J13: =J12/I12-1 -> 0.058244951 | K13: =K12/J12-1 -> 0.063976216 | L13: =L12/K12-1 -> -0.017350426 | M13: =M12/L12-1 -> 0.02234863 | N13: =N12/M12-1 -> 0.10189156 | T13: =T12/N12-1 -> 0.053222714 | U13: =U12/T12-1 -> 0.037387643 | V13: =V12/U12-1 -> 0.038313091 | W13: =W12/V12-1 -> 0.039999925 | X13: =X12/W12-1 -> 0.042337703 | Y13: =Y12/X12-1 -> 0.044195098 | Z13: =Z12/Y12-1 -> 0.045464175 | AA13: =AA12/Z12-1 -> 0.04706543 | AB13: =AB12/AA12-1 -> 0.047920812 | ... AD13: =AD12/AC12-1 -> 0.048740615
A14: Painel de Índices | E14: Despesas Tributárias sobre Faturamento | F14: ='DRE CMN 4.720 - Contas Abertas'!F51 -> -4.0697476e+09 | G14: ='DRE CMN 4.720 - Contas Abertas'!G51 -> -4.3215667e+09 | H14: ='DRE CMN 4.720 - Contas Abertas'!H51 -> -5.1158347e+09 | I14: ='DRE CMN 4.720 - Contas Abertas'!I51 -> -5.0005496e+09 | J14: ='DRE CMN 4.720 - Contas Abertas'!J51 -> -4.5897923e+09 | K14: ='DRE CMN 4.720 - Contas Abertas'!K51 -> -4.4577427e+09 | L14: ='DRE CMN 4.720 - Contas Abertas'!L51 -> -4.8462431e+09 | M14: ='DRE CMN 4.720 - Contas Abertas'!M51 -> -5.0006834e+09 | ... Q14: ='DRE CMN 4.720 - Contas Abertas'!Q51 -> -1.808919e+09 | R14: ='Projeções Trimestrais'!I77 -> -1.7821939e+09 | S14: =R14 -> -1.7821939e+09 | T14: =SUM(O14:R14) -> -6.8804238e+09 | U14: =U15*SUM(U10,U12) -> -7.004858e+09 | V14: =V15*SUM(V10,V12) -> -7.5596373e+09 | W14: =W15*SUM(W10,W12) -> -8.1669782e+09 | X14: =X15*SUM(X10,X12) -> -8.8362041e+09 | Y14: =Y15*SUM(Y10,Y12) -> -9.5726068e+09 | Z14: =Z15*SUM(Z10,Z12) -> -1.0381295e+10 | AA14: =AA15*SUM(AA10,AA12) -> -1.1229261e+10 | AB14: =AB15*SUM(AB10,AB12) -> -1.2018614e+10 | ... AD14: =AD15*SUM(AD10,AD12) -> -1.5629575e+10
A15: Projeções Trimestrais | E15: Despesas Tributárias sobre Fauramento como % Total de Receitas | F15: =F14/SUM(F10,F12) -> -0.081833849 | G15: =G14/SUM(G10,G12) -> -0.086399848 | H15: =H14/SUM(H10,H12) -> -0.10176708 | I15: =I14/SUM(I10,I12) -> -0.087555936 | J15: =J14/SUM(J10,J12) -> -0.074008657 | K15: =K14/SUM(K10,K12) -> -0.065339577 | L15: =L14/SUM(L10,L12) -> -0.076538134 | M15: =M14/SUM(M10,M12) -> -0.066198435 | ... T15: =T14/SUM(T10,T12) -> -0.070717028 | U15: =AVERAGE($F$15:$N$15) -> -0.078652775 | V15: =AVERAGE($F$15:$N$15) -> -0.078652775 | W15: =AVERAGE($F$15:$N$15) -> -0.078652775 | X15: =AVERAGE($F$15:$N$15) -> -0.078652775 | Y15: =AVERAGE($F$15:$N$15) -> -0.078652775 | Z15: =AVERAGE($F$15:$N$15) -> -0.078652775 | AA15: =AVERAGE($F$15:$N$15) -> -0.078652775 | AB15: =AVERAGE($F$15:$N$15) -> -0.078652775 | ... AD15: =AVERAGE($F$15:$N$15) -> -0.078652775
E16: Margem de Contribuição | F16: =F10+F12+F14 -> 4.5662089e+10 | G16: =G10+G12+G14 -> 4.5696654e+10 | H16: =H10+H12+H14 -> 4.5154201e+10 | I16: =I10+I12+I14 -> 5.2112079e+10 | J16: =J10+J12+J14 -> 5.7427173e+10 | K16: =K10+K12+K14 -> 6.3766494e+10 | L16: =L10+L12+L14 -> 5.8471777e+10 | M16: =M10+M12+M14 -> 7.0540126e+10 | ... S16: =S10+S12+S14 -> 2.3244956e+10 | T16: =SUM(O16:R16) -> 9.0414725e+10 | U16: =U10+U12+U14 -> 8.2055674e+10 | V16: =V10+V12+V14 -> 8.855442e+10 | W16: =W10+W12+W14 -> 9.5668878e+10 | X16: =X10+X12+X14 -> 1.0350826e+11 | Y16: =Y10+Y12+Y14 -> 1.1213456e+11 | Z16: =Z10+Z12+Z14 -> 1.2160763e+11 | AA16: =AA10+AA12+AA14 -> 1.3154079e+11 | AB16: =AB10+AB12+AB14 -> 1.4078736e+11 | ... AD16: =AD10+AD12+AD14 -> 1.8308656e+11
E17: Crescimento das Margem de Contribuição (YoY)¹ | F17: - | G17: =G16/F16-1 -> 0.00075697494 | H17: =H16/G16-1 -> -0.011870728 | I17: =I16/H16-1 -> 0.15409146 | J17: =J16/I16-1 -> 0.10199352 | K17: =K16/J16-1 -> 0.11038887 | L17: =L16/K16-1 -> -0.083032897 | M17: =M16/L16-1 -> 0.20639615 | N17: =N16/M16-1 -> 0.17538379 | T17: =T16/N16-1 -> 0.090493893 | U17: =U16/T16-1 -> -0.092452323 | V17: =V16/U16-1 -> 0.079199221 | W17: =W16/V16-1 -> 0.080339955 | X17: =X16/W16-1 -> 0.0819429 | Y17: =Y16/X16-1 -> 0.083339256 | Z17: =Z16/Y16-1 -> 0.084479399 | AA17: =AA16/Z16-1 -> 0.081682107 | AB17: =AB16/AA16-1 -> 0.070294313 | ... AD17: =AD16/AC16-1 -> 0.21592075
E18: Outras Despesas/Receitas Operacionais | F18: =SUM('DRE CMN 4.720 - Contas Abertas'!F53,'DRE CMN 4.720 - Contas Abertas'!F56,'DRE CMN 4.720 - Contas Abertas'!F58,'DRE CMN 4.720 - Contas Abertas'!F61) -> -2.9084322e+10 | G18: =SUM('DRE CMN 4.720 - Contas Abertas'!G53,'DRE CMN 4.720 - Contas Abertas'!G56,'DRE CMN 4.720 - Contas Abertas'!G58,'DRE CMN 4.720 - Contas Abertas'!G61) -> -2.9928889e+10 | H18: =SUM('DRE CMN 4.720 - Contas Abertas'!H53,'DRE CMN 4.720 - Contas Abertas'!H56,'DRE CMN 4.720 - Contas Abertas'!H58,'DRE CMN 4.720 - Contas Abertas'!H61) -> -3.4437793e+10 | I18: =SUM('DRE CMN 4.720 - Contas Abertas'!I53,'DRE CMN 4.720 - Contas Abertas'!I56,'DRE CMN 4.720 - Contas Abertas'!I58,'DRE CMN 4.720 - Contas Abertas'!I61) -> -3.3548637e+10 | J18: =SUM('DRE CMN 4.720 - Contas Abertas'!J53,'DRE CMN 4.720 - Contas Abertas'!J56,'DRE CMN 4.720 - Contas Abertas'!J58,'DRE CMN 4.720 - Contas Abertas'!J61) -> -3.4325727e+10 | K18: =SUM('DRE CMN 4.720 - Contas Abertas'!K53,'DRE CMN 4.720 - Contas Abertas'!K56,'DRE CMN 4.720 - Contas Abertas'!K58,'DRE CMN 4.720 - Contas Abertas'!K61) -> -3.8851252e+10 | L18: =SUM('DRE CMN 4.720 - Contas Abertas'!L53,'DRE CMN 4.720 - Contas Abertas'!L56,'DRE CMN 4.720 - Contas Abertas'!L58,'DRE CMN 4.720 - Contas Abertas'!L61) -> -3.8370837e+10 | M18: =SUM('DRE CMN 4.720 - Contas Abertas'!M53,'DRE CMN 4.720 - Contas Abertas'!M56,'DRE CMN 4.720 - Contas Abertas'!M58,'DRE CMN 4.720 - Contas Abertas'!M61) -> -3.943413e+10 | ... Q18: =SUM('DRE CMN 4.720 - Contas Abertas'!Q53,'DRE CMN 4.720 - Contas Abertas'!Q56,'DRE CMN 4.720 - Contas Abertas'!Q58,'DRE CMN 4.720 - Contas Abertas'!Q61) -> -1.0060653e+10 | R18: ='Projeções Trimestrais'!I91 -> -9.7532449e+09 | S18: =R18 -> -9.7532449e+09 | T18: =SUM(O18:R18) -> -3.8009691e+10 | U18: =T18*(1+'Projeções - Receitas'!U11) -> -3.961256e+10 | V18: =U18*(1+'Projeções - Receitas'!V11) -> -4.1329369e+10 | W18: =V18*(1+'Projeções - Receitas'!W11) -> -4.3210681e+10 | X18: =W18*(1+'Projeções - Receitas'!X11) -> -4.5308128e+10 | Y18: =X18*(1+'Projeções - Receitas'!Y11) -> -4.7612952e+10 | Z18: =Y18*(1+'Projeções - Receitas'!Z11) -> -5.0106919e+10 | AA18: =Z18*(1+'Projeções - Receitas'!AA11) -> -5.2827724e+10 | AB18: =AA18*(1+'Projeções - Receitas'!AB11) -> -5.5744343e+10 | ... AD18: =AC18*(1+'Projeções - Receitas'!AD11) -> -6.213074e+10
E19: Despesas Operacionais como % de Outras Receitas Operacionais | F19: =F18/F12 -> -1.3354611 | G19: =G18/G12 -> -1.3574517 | H19: =H18/H12 -> -1.4473239 | I19: =I18/I12 -> -1.2932462 | J19: =J18/J12 -> -1.2503738 | K19: =K18/K12 -> -1.3301273 | L19: =L18/L12 -> -1.336875 | M19: =M18/M12 -> -1.3438871 | ... AD19: =AD18/AD12 -> -1.1864175
E20: Resultado Operacional | F20: =SUM(F16,F18) -> 1.6577767e+10 | G20: =SUM(G16,G18) -> 1.5767765e+10 | H20: =SUM(H16,H18) -> 1.0716408e+10 | I20: =SUM(I16,I18) -> 1.8563442e+10 | J20: =SUM(J16,J18) -> 2.3101445e+10 | K20: =SUM(K16,K18) -> 2.4915242e+10 | L20: =SUM(L16,L18) -> 2.010094e+10 | M20: =SUM(M16,M18) -> 3.1105996e+10 | ... AD20: =SUM(AD16,AD18) -> 1.2095582e+11
E21: Crescimento do Resultado Operacional (YoY)¹ | F21: - | G21: =G20/F20-1 -> -0.048860714 | H21: =H20/G20-1 -> -0.32035975 | I21: =I20/H20-1 -> 0.73224474 | J21: =J20/I20-1 -> 0.24445918 | K21: =K20/J20-1 -> 0.078514406 | L21: =L20/K20-1 -> -0.19322717 | M21: =M20/L20-1 -> 0.54748963 | N21: =N20/M20-1 -> 0.56108785 | T21: =T20/N20-1 -> 0.079199038 | U21: =U20/T20-1 -> -0.19009472 | V21: =V20/U20-1 -> 0.11266697 | W21: =W20/V20-1 -> 0.11081291 | X21: =X20/W20-1 -> 0.10945742 | Y21: =Y20/X20-1 -> 0.10861619 | Z21: =Z20/Y20-1 -> 0.10816677 | AA21: =AA20/Z20-1 -> 0.10087119 | AB21: =AB20/AA20-1 -> 0.080418044 | ... AD21: =AD20/AC20-1 -> 0.31861312
E22: Resultado Não Operacional | F22: ='DRE CMN 4.720 - Contas Abertas'!F69 -> 1.4382725e+08 | G22: ='DRE CMN 4.720 - Contas Abertas'!G69 -> 1.6606351e+08 | H22: ='DRE CMN 4.720 - Contas Abertas'!H69 -> 2.2713104e+08 | I22: ='DRE CMN 4.720 - Contas Abertas'!I69 -> 1.8627469e+08 | J22: ='DRE CMN 4.720 - Contas Abertas'!J69 -> 2.1793005e+08 | K22: ='DRE CMN 4.720 - Contas Abertas'!K69 -> 1.2321214e+08 | L22: ='DRE CMN 4.720 - Contas Abertas'!L69 -> 1.549019e+08 | M22: ='DRE CMN 4.720 - Contas Abertas'!M69 -> 2.460578e+08 | ... O22: ='DRE CMN 4.720 - Contas Abertas'!O69 -> 1.0686121e+08
E23: Resultado Antes do IR | F23: =F20+F22 -> 1.6721594e+10 | G23: =G20+G22 -> 1.5933829e+10 | H23: =H20+H22 -> 1.0943539e+10 | I23: =I20+I22 -> 1.8749716e+10 | J23: =J20+J22 -> 2.3319375e+10 | K23: =K20+K22 -> 2.5038454e+10 | L23: =L20+L22 -> 2.0255842e+10 | M23: =M20+M22 -> 3.1352054e+10 | ... AD23: =AD20+AD22 -> 1.2095582e+11
E24: Imposto de Renda e Contribuição Social | F24: ='DRE CMN 4.720 - Contas Abertas'!F71 -> -2.4363414e+09 | G24: ='DRE CMN 4.720 - Contas Abertas'!G71 -> -8.2814101e+08 | H24: ='DRE CMN 4.720 - Contas Abertas'!H71 -> -1.1790907e+09 | I24: ='DRE CMN 4.720 - Contas Abertas'!I71 -> -4.6035192e+09 | J24: ='DRE CMN 4.720 - Contas Abertas'!J71 -> -6.6956437e+09 | K24: ='DRE CMN 4.720 - Contas Abertas'!K71 -> -3.1404959e+09 | L24: ='DRE CMN 4.720 - Contas Abertas'!L71 -> -3.0934574e+09 | M24: ='DRE CMN 4.720 - Contas Abertas'!M71 -> -6.0804538e+09 | ... Q24: ='DRE CMN 4.720 - Contas Abertas'!Q71 -> -2.1393902e+09 | R24: =R25*R20 -> -2.6472351e+09 | S24: =R24 -> -2.6472351e+09 | T24: =SUM(O24:R24) -> -9.6857172e+09 | U24: =U25*U20 -> -7.8832821e+09 | V24: =V25*V20 -> -8.814604e+09 | W24: =W25*W20 -> -9.8392925e+09 | X24: =X25*X20 -> -1.0969437e+10 | Y24: =Y25*Y20 -> -1.2219831e+10 | Z24: =Z25*Z20 -> -1.3606921e+10 | AA24: =AA25*AA20 -> -1.5051366e+10 | AB24: =AB25*AB20 -> -1.6339448e+10 | ... AD24: =AD25*AD20 -> -2.661028e+10
E25: Imposto de Renda e Contribuição Social como % do Resultado Operacional | F25: =F24/F20 -> -0.14696439 | G25: =G24/G20 -> -0.05252114 | H25: =H24/H20 -> -0.11002667 | I25: =I24/I20 -> -0.24798846 | J25: =J24/J20 -> -0.28983657 | K25: =K24/K20 -> -0.12604718 | L25: =L24/L20 -> -0.15389616 | M25: =M24/M20 -> -0.1954753 | ... Q25: =Q24/Q20 -> -0.16502913 | R25: =AVERAGE($I$25:$Q$25) -> -0.19621196 | S25: =S24/S20 -> -0.19621196 | T25: =T24/T20 -> -0.18482418 | U25: =T25+(($AD$25-$N$25)/11) -> -0.1857376 | V25: =U25+(($AD$25-$N$25)/11) -> -0.18665102 | W25: =V25+(($AD$25-$N$25)/11) -> -0.18756444 | X25: =W25+(($AD$25-$N$25)/11) -> -0.18847787 | Y25: =X25+(($AD$25-$N$25)/11) -> -0.18939129 | Z25: =Y25+(($AD$25-$N$25)/11) -> -0.19030471 | AA25: =Z25+(($AD$25-$N$25)/11) -> -0.19121813 | AB25: =AA25+(($AD$25-$N$25)/11) -> -0.19213156 | AC25: =AB25+(($AD$25-$N$25)/11) -> -0.19304498 | AD25: -0.22
E26: Resultado Antes de Participações Estatutárias e Minoritárias | F26: =F23+F24 -> 1.4285253e+10 | G26: =G23+G24 -> 1.5105688e+10 | H26: =H23+H24 -> 9.7644484e+09 | I26: =I23+I24 -> 1.4146197e+10 | J26: =J23+J24 -> 1.6623732e+10 | K26: =K23+K24 -> 2.1897958e+10 | L26: =L23+L24 -> 1.7162384e+10 | M26: =M23+M24 -> 2.52716e+10 | ... O26: =O23+O24 -> 1.0452697e+10 | P26: =P20+P24 -> 1.0704683e+10 | Q26: =Q20+Q24 -> 1.0824322e+10 | R26: =R20+R24 -> 1.0844476e+10 | S26: =R26 -> 1.0844476e+10 | T26: =SUM(O26:R26) -> 4.2826178e+10 | U26: =U20+U24 -> 3.4559832e+10 | V26: =V20+V24 -> 3.8410447e+10 | W26: =W20+W24 -> 4.2618904e+10 | X26: =X20+X24 -> 4.7230698e+10 | Y26: =Y20+Y24 -> 5.2301781e+10 | Z26: =Z20+Z24 -> 5.7893785e+10 | AA26: =AA20+AA24 -> 6.3661702e+10 | AB26: =AB20+AB24 -> 6.8703571e+10 | ... AD26: =AD20+AD24 -> 9.434554e+10
E27: Participações Estatutárias no Lucro | F27: ='DRE CMN 4.720 - Contas Abertas'!F72 -> -1.4673351e+09 | G27: ='DRE CMN 4.720 - Contas Abertas'!G72 -> -1.7896844e+09 | H27: ='DRE CMN 4.720 - Contas Abertas'!H72 -> -9.1857229e+08 | I27: ='DRE CMN 4.720 - Contas Abertas'!I72 -> -1.4362506e+09 | J27: ='DRE CMN 4.720 - Contas Abertas'!J72 -> -1.714864e+09 | K27: ='DRE CMN 4.720 - Contas Abertas'!K72 -> -2.3467088e+09 | L27: ='DRE CMN 4.720 - Contas Abertas'!L72 -> -1.7020458e+09 | M27: ='DRE CMN 4.720 - Contas Abertas'!M72 -> -2.6449656e+09 | ... Q27: ='DRE CMN 4.720 - Contas Abertas'!Q72 -> -1.1187128e+09
E28: Participações Minoritárias | F28: ='DRE CMN 4.720 - Contas Abertas'!F73 -> -1.4751949e+09 | G28: ='DRE CMN 4.720 - Contas Abertas'!G73 -> -1.721658e+09 | H28: ='DRE CMN 4.720 - Contas Abertas'!H73 -> -1.675039e+09 | I28: ='DRE CMN 4.720 - Contas Abertas'!I73 -> -1.6500334e+09 | J28: ='DRE CMN 4.720 - Contas Abertas'!J73 -> -1.395849e+09 | K28: ='DRE CMN 4.720 - Contas Abertas'!K73 -> -1.7037475e+09 | L28: ='DRE CMN 4.720 - Contas Abertas'!L73 -> -1.5765221e+09 | M28: ='DRE CMN 4.720 - Contas Abertas'!M73 -> -1.6055132e+09 | ... Q28: ='DRE CMN 4.720 - Contas Abertas'!Q73 -> -9.6186417e+08
E29: Lucro dos Acionistas Ajustado dos Acionistas Controladores | F29: =SUM(F26:F28) -> 1.1342723e+10 | G29: =SUM(G26:G28) -> 1.1594346e+10 | H29: =SUM(H26:H28) -> 7.1708371e+09 | I29: =SUM(I26:I28) -> 1.1059913e+10 | J29: =SUM(J26:J28) -> 1.3513019e+10 | K29: =SUM(K26:K28) -> 1.7847502e+10 | L29: =SUM(L26:L28) -> 1.3883817e+10 | M29: =SUM(M26:M28) -> 2.1021121e+10 | ... Q29: =SUM(Q26:Q28) -> 8.7437455e+09 | R29: =R31 -> 8.7600253e+09 | S29: =R29 -> 8.7600253e+09 | T29: =SUM(O29:R29) -> 3.4787158e+10 | U29: =U33*U26 -> 2.8072511e+10 | V29: =V33*V26 -> 3.1200316e+10 | W29: =W33*W26 -> 3.4618792e+10 | X29: =X33*X26 -> 3.8364893e+10 | Y29: =Y33*Y26 -> 4.2484069e+10 | Z29: =Z33*Z26 -> 4.7026383e+10 | AA29: =AA33*AA26 -> 5.1711588e+10 | AB29: =AB33*AB26 -> 5.5807034e+10 | ... AD29: =AD33*AD26 -> 7.6635678e+10
E30: Itens Extraordinários | F30: ='DRE CMN 4.720 - Contas Abertas'!F75 -> -97174908 | G30: ='DRE CMN 4.720 - Contas Abertas'!G75 -> 2.8052129e+09 | H30: ='DRE CMN 4.720 - Contas Abertas'!H75 -> 8.6271862e+08 | I30: ='DRE CMN 4.720 - Contas Abertas'!I75 -> -49136775 | J30: ='DRE CMN 4.720 - Contas Abertas'!J75 -> -6.5099451e+08 | K30: ='DRE CMN 4.720 - Contas Abertas'!K75 -> 3.1456721e+08 | L30: ='DRE CMN 4.720 - Contas Abertas'!L75 -> -1.1864323e+09 | M30: ='DRE CMN 4.720 - Contas Abertas'!M75 -> -1.3107195e+09 | ... Q30: ='DRE CMN 4.720 - Contas Abertas'!Q75 -> -3.8865561e+08
E31: Lucro dos Acionistas dos Acionistas Controladores | F31: =F29+F30 -> 1.1245548e+10 | G31: =G29+G30 -> 1.4399558e+10 | H31: =H29+H30 -> 8.0335558e+09 | I31: =I29+I30 -> 1.1010776e+10 | J31: =J29+J30 -> 1.2862024e+10 | K31: =K29+K30 -> 1.8162069e+10 | L31: =L29+L30 -> 1.2697384e+10 | M31: =M29+M30 -> 1.9710402e+10 | ... Q31: =Q29+Q30 -> 8.3550899e+09 | R31: =R33*R26 -> 8.7600253e+09 | S31: =R31 -> 8.7600253e+09 | T31: =SUM(O31:R31) -> 3.3624756e+10 | U31: =U29 -> 2.8072511e+10 | V31: =V29 -> 3.1200316e+10 | W31: =W29 -> 3.4618792e+10 | X31: =X29 -> 3.8364893e+10 | Y31: =Y29 -> 4.2484069e+10 | Z31: =Z29 -> 4.7026383e+10 | AA31: =AA29 -> 5.1711588e+10 | AB31: =AB29 -> 5.5807034e+10 | ... AD31: =AD29 -> 7.6635678e+10
E32: Crescimento Lucro Líquido dos Acionistas Controladoresl (YoY)¹ | F32: - | G32: =G31/F31-1 -> 0.28046749 | H32: =H31/G31-1 -> -0.44209708 | I32: =I31/H31-1 -> 0.37059809 | J32: =J31/I31-1 -> 0.16813056 | K32: =K31/J31-1 -> 0.41206924 | L32: =L31/K31-1 -> -0.30088448 | M32: =M31/L31-1 -> 0.55231988 | N32: =N31/M31-1 -> 0.5733564 | T32: =T31/N31-1 -> 0.084267787 | U32: =U31/T31-1 -> -0.16512375 | V32: =V31/U31-1 -> 0.11141881 | W32: =W31/V31-1 -> 0.10956542 | X32: =X31/W31-1 -> 0.10821005 | Y32: =Y31/X31-1 -> 0.10736837 | Z32: =Z31/Y31-1 -> 0.10691804 | AA32: =AA31/Z31-1 -> 0.099629291 | AB32: =AB31/AA31-1 -> 0.079197841 | ... AD32: =AD31/AC31-1 -> 0.27456699
E33: % do Lucro Pertencente aos Acionistas | F33: =F29/F26 -> 0.79401625 | G33: =G29/G26 -> 0.76754833 | H33: =H29/H26 -> 0.7343822 | I33: =I29/I26 -> 0.78182942 | J33: =J29/J26 -> 0.81287517 | K33: =K29/K26 -> 0.81503041 | L33: =L29/L26 -> 0.80896781 | M33: =M29/M26 -> 0.83180809 | ... Q33: =Q29/Q26 -> 0.80778687 | R33: =Q33 -> 0.80778687 | S33: =S29/S26 -> 0.80778687 | T33: =T29/T26 -> 0.81228724 | U33: =T33 -> 0.81228724 | V33: =U33 -> 0.81228724 | W33: =V33 -> 0.81228724 | X33: =W33 -> 0.81228724 | Y33: =X33 -> 0.81228724 | Z33: =Y33 -> 0.81228724 | AA33: =Z33 -> 0.81228724 | AB33: =AA33 -> 0.81228724 | ... AD33: =AC33 -> 0.81228724
E34: 1 - Ano a Ano
F37: 2014 | G37: 2015 | H37: 2016 | I37: 2017 | J37: 2018 | K37: 2019 | L37: 2020 | M37: 2021 | N37: 2022 | O37: 1T23 | P37: 2T23 | Q37: 3T23 | R37: 4T23 | S37: YTG23 | T37: 2023 | U37: 2024 | V37: 2025 | W37: 2026 | X37: 2027 | Y37: 2028 | Z37: 2029 | AA37: 2030 | AB37: 2031 | AC37: 2032 | AD37: 2033 | AE37: Perpetuidade | AF37: ROE Perp. | AG37: Growth
E38: Lucro Líquido por Ação | F38: 4.04 | G38: 5.05 | H38: 2.84 | I38: 3.91 | J38: 4.54 | K38: 6.39 | L38: 4.39 | M38: 3.86 | N38: 10.79 | O38: 2.8640131 | P38: =P31/Dashboard!$F$11 -> 2.9094951 | Q38: =Q31/Dashboard!$F$11 -> 2.9277315 | R38: =R31/Dashboard!$F$11 -> 3.069626 | S38: =SUM(R38) -> 3.069626 | T38: =SUM(O38:R38) -> 11.770866 | U38: =U31/Dashboard!$F$11 -> 9.8369704 | V38: =V31/Dashboard!$F$11 -> 10.932994 | W38: =W31/Dashboard!$F$11 -> 12.130872 | X38: =X31/Dashboard!$F$11 -> 13.443554 | Y38: =Y31/Dashboard!$F$11 -> 14.886967 | Z38: =Z31/Dashboard!$F$11 -> 16.478652 | AA38: =AA31/Dashboard!$F$11 -> 18.120409 | AB38: =AB31/Dashboard!$F$11 -> 19.555506 | ... AD38: =AD31/Dashboard!$F$11 -> 26.854132 | AE38: =AD38 -> 26.854132 | AF38: =Ke!P16 -> 0.15192705 | AG38: =AF38*AE40 -> 0.091156229
E39: Índice Payout | F39: =F41/F38 -> 0.40019064 | G39: =G41/G38 -> 0.40711069 | H39: =H41/H38 -> 0.29750971 | I39: =I41/I38 -> 0.29653105 | J39: =J41/J38 -> 0.40818347 | K39: =K41/K38 -> 0.37586022 | L39: =L41/L38 -> 0.33511472 | M39: =M41/M38 -> 0.68334784 | ... Q39: =Q41/Q38 -> 0.38337122 | R39: =Q39 -> 0.38337122 | S39: =S41/S38 -> 0.38337122 | T39: =T41/T38 -> 0.38787832 | U39: 0.4 | V39: 0.4 | W39: 0.4 | X39: 0.4 | Y39: 0.4 | Z39: 0.4 | AA39: 0.4 | AB39: 0.4 | AC39: 0.4 | AD39: 0.4 | AE39: =AD39 -> 0.4
E40: Índice Reinvestimento | F40: =1-F39 -> 0.59980936 | G40: =1-G39 -> 0.59288931 | H40: =1-H39 -> 0.70249029 | I40: =1-I39 -> 0.70346895 | J40: =1-J39 -> 0.59181653 | K40: =1-K39 -> 0.62413978 | L40: =1-L39 -> 0.66488528 | M40: =1-M39 -> 0.31665216 | ... AD40: =1-AD39 -> 0.6 | AE40: =AD40 -> 0.6
E41: Proventos por Ação | F41: 1.6167702 | G41: 2.055909 | H41: 0.84492757 | I41: 1.1594364 | J41: 1.853153 | K41: 2.4017468 | L41: 1.4711536 | M41: 2.6377227 | N41: 4.137806 | O41: 1.1294415 | P41: 1.1370079 | Q41: 1.122408 | R41: =R38*R39 -> 1.1768063 | S41: =SUM(R41) -> 1.1768063 | T41: =SUM(O41:R41) -> 4.5656637 | U41: =U38*U39 -> 3.9347882 | V41: =V38*V39 -> 4.3731976 | W41: =W38*W39 -> 4.8523488 | X41: =X38*X39 -> 5.3774217 | Y41: =Y38*Y39 -> 5.9547868 | Z41: =Z38*Z39 -> 6.5914609 | AA41: =AA38*AA39 -> 7.2481635 | AB41: =AB38*AB39 -> 7.8222024 | ... AD41: =AD38*AD39 -> 10.741653 | AE41: =AE38*AE39*(1+AG38)/(Ke!P16-'DRE + DCF'!AG38) -> 192.86923
E42: Desconto Acumulado | S42: =Ke!F17 -> 1.0429453 | U42: =Ke!G17 -> 1.2191879 | V42: =Ke!H17 -> 1.419196 | W42: =Ke!I17 -> 1.6491782 | X42: =Ke!J17 -> 1.9131466 | Y42: =Ke!K17 -> 2.2151336 | Z42: =Ke!L17 -> 2.5598592 | AA42: =Ke!M17 -> 2.9531591 | AB42: =Ke!N17 -> 3.4026597 | ... AD42: =Ke!P17 -> 4.5139722
E43: Proventos por Ação Descontado | S43: =S41/S42 -> 1.128349 | U43: =U41/U42 -> 3.2273844 | V43: =V41/V42 -> 3.0814614 | W43: =W41/W42 -> 2.9422829 | X43: =X41/X42 -> 2.8107735 | Y43: =Y41/Y42 -> 2.6882291 | Z43: =Z41/Z42 -> 2.574931 | AA43: =AA41/AA42 -> 2.4543762 | AB43: =AB41/AB42 -> 2.2988495 | ... AD43: =AD41/AD42 -> 2.3796453 | AE43: =AE41/AD42 -> 42.727164
E44: ROE | F44: =F31/'Balanço Patrimonial'!F98 -> 0.13950009 | G44: =G31/'Balanço Patrimonial'!G98 -> 0.17660332 | H44: =H31/'Balanço Patrimonial'!H98 -> 0.092134535 | I44: =I31/'Balanço Patrimonial'!I98 -> 0.11153157 | J44: =J31/'Balanço Patrimonial'!J98 -> 0.12578642 | K44: =K31/'Balanço Patrimonial'!K98 -> 0.16729228 | L44: =L31/'Balanço Patrimonial'!L98 -> 0.10000215 | M44: =M31/'Balanço Patrimonial'!M98 -> 0.13606782 | ... O44: =O31/'Balanço Patrimonial'!O98 -> 0.048407164 | S44: =S31/(S50*10^6) -> 0.049797618 | T44: =T31/(T50*10^6) -> 0.19114474 | U44: =U31/(U50*10^6) -> 0.14563751 | V44: =V31/(V50*10^6) -> 0.1475358 | W44: =W31/(W50*10^6) -> 0.14905991 | X44: =X31/(X50*10^6) -> 0.15029352 | Y44: =Y31/(Y50*10^6) -> 0.15131978 | Z44: =Z31/(Z50*10^6) -> 0.15220238 | ... AD44: =AD31/(AD50*10^6) -> 0.16822989 | AE44: =AF38 -> 0.15192705
E49: Valores em Milhões | F49: 2014 | G49: 2015 | H49: 2016 | I49: 2017 | J49: 2018 | K49: 2019 | L49: 2020 | M49: 2021 | N49: 2022 | O49: 1T23 | P49: 2T23 | Q49: 3T23 | S49: YTG23 | T49: 2023 | U49: 2024 | V49: 2025 | W49: 2026 | X49: 2027 | Y49: 2028 | Z49: 2029 | AA49: 2030 | AB49: 2031 | AC49: 2032 | AD49: 2033 | AE49: Premissas
E50: Patrimônio Líquido | F50: ='Balanço Patrimonial'!F98/1000000 -> 80613.194 | G50: ='Balanço Patrimonial'!G98/1000000 -> 81536.173 | H50: ='Balanço Patrimonial'!H98/1000000 -> 87193.752 | I50: ='Balanço Patrimonial'!I98/1000000 -> 98723.401 | J50: ='Balanço Patrimonial'!J98/1000000 -> 102252.88 | K50: ='Balanço Patrimonial'!K98/1000000 -> 108564.89 | L50: ='Balanço Patrimonial'!L98/1000000 -> 126971.11 | M50: ='Balanço Patrimonial'!M98/1000000 -> 144857.19 | ... Q50: ='Balanço Patrimonial'!Q98/1000000 -> 170510.85 | S50: =Q50+S51 -> 175912.54 | T50: =S50 -> 175912.54 | U50: =U51+T50 -> 192756.04 | V50: =V51+U50 -> 211476.23 | W50: =W51+V50 -> 232247.51 | X50: =X51+W50 -> 255266.44 | Y50: =Y51+X50 -> 280756.89 | Z50: =Z51+Y50 -> 308972.72 | AA50: =AA51+Z50 -> 339999.67 | AB50: =AB51+AA50 -> 373483.89 | ... AD50: =AD51+AC50 -> 455541.4 | AE50: O aumento do Patrimônio Líquido será igual ao lucro retido.
E51: Lucro Retido | S51: =S40*S31/10^6 -> 5401.6837 | T51: =S51 -> 5401.6837 | U51: =U40*U31/10^6 -> 16843.506 | V51: =V40*V31/10^6 -> 18720.19 | W51: =W40*W31/10^6 -> 20771.275 | X51: =X40*X31/10^6 -> 23018.936 | Y51: =Y40*Y31/10^6 -> 25490.442 | Z51: =Z40*Z31/10^6 -> 28215.83 | AA51: =AA40*AA31/10^6 -> 31026.953 | AB51: =AB40*AB31/10^6 -> 33484.221 | ... AD51: =AD40*AD31/10^6 -> 45981.407 | AE51: Todo aumento do Patrimônio de Referência será dado pela retenção do lucro.
E52: Capital Nível 1 | F52: 89538.218 | G52: 95713.963 | H52: 90283.551 | I52: 95227.96 | J52: 95289.701 | K52: 96380.201 | L52: 132247.51 | M52: 141352.78 | N52: 158152.72 | O52: 161656.26 | P52: 156767.48 | Q52: 161673.25 | S52: =Q52+S51 -> 167074.93 | T52: =S52 -> 167074.93 | U52: =U51+T52 -> 183918.44 | V52: =V51+U52 -> 202638.63 | W52: =W51+V52 -> 223409.9 | X52: =X51+W52 -> 246428.84 | Y52: =Y51+X52 -> 271919.28 | Z52: =Z51+Y52 -> 300135.11 | AA52: =AA51+Z52 -> 331162.06 | AB52: =AB51+AA52 -> 364646.28 | ... AD52: =AD51+AC52 -> 446703.79
E53: Patrimônio de Referência (PR) | F53: 126588.49 | G53: 135551.2 | H53: 130453.21 | I53: 135511.42 | J53: 134178.48 | K53: 132150.43 | L53: 161924.48 | M53: 165648.21 | N53: 178688.55 | O53: 179258.4 | P53: 174369.62 | Q53: 179275.39 | S53: =Q53+S51 -> 184677.07 | T53: =S53 -> 184677.07 | U53: =T53+U51 -> 201520.58 | V53: =U53+V51 -> 220240.76 | W53: =V53+W51 -> 241012.04 | X53: =W53+X51 -> 264030.98 | Y53: =X53+Y51 -> 289521.42 | Z53: =Y53+Z51 -> 317737.25 | AA53: =Z53+AA51 -> 348764.2 | AB53: =AA53+AB51 -> 382248.42 | ... AD53: =AC53+AD51 -> 464305.93 | AE53: O Patrimônio de Referência será igual à multiplicação entre o RWA e o Basiléia projetados
E54: Patrimônio Líquido/Patrimônio de Referência | F54: =F50/F53 -> 0.63681301 | G54: =G50/G53 -> 0.6015157 | H54: =H50/H53 -> 0.66839101 | I54: =I50/I53 -> 0.72852457 | J54: =J50/J53 -> 0.76206616 | K54: =K50/K53 -> 0.82152508 | L54: =L50/L53 -> 0.78413782 | M54: =M50/M53 -> 0.87448687 | ... Q54: =Q50/Q53 -> 0.95111135 | S54: =S50/S53 -> 0.95254131 | T54: =T50/T53 -> 0.95254131 | U54: =U50/U53 -> 0.95650801 | V54: =V50/V53 -> 0.96020477 | W54: =W50/W53 -> 0.96363447 | X54: =X50/X53 -> 0.96680491 | Y54: =Y50/Y53 -> 0.96972752 | Z54: =Z50/Z53 -> 0.97241579 | ... AD54: =AD50/AD53 -> 0.98112337
E55: Ativos Ponderados pelo Risco (RWA) | F55: 785973.52 | G55: 840508.86 | H55: 705851.28 | I55: 689856.76 | J55: 711490.28 | K55: 711401.98 | L55: 766064.66 | M55: 932460.7 | N55: 1072894 | O55: 1107212.6 | P55: 1109309.8 | Q55: 1104000.6 | S55: =S56*S57 -> 1092975.1 | T55: =S55 -> 1092975.1 | U55: =U56*U57 -> 1130252.4 | V55: =V56*V57 -> 1265882.7 | W55: =W56*W57 -> 1417788.6 | X55: =X56*X57 -> 1587923.3 | Y55: =Y56*Y57 -> 1778474 | Z55: =Z56*Z57 -> 1991890.9 | AA55: =AA56*AA57 -> 2218966.5 | AB55: =AB56*AB57 -> 2431987.3 | ... AD55: =AD56*AD57 -> 2953278.3 | AE55: O RWA irá evoluir de acordo com a evolução dos Ativos Rentáveis, mantendo a relação constante entre RWA e Ativos Rentáveis
E56: Ativos Rentávels | F56: ='Projeções - Receitas'!F34/10^6 -> 1093207.9 | G56: ='Projeções - Receitas'!G34/10^6 -> 1194742.5 | H56: ='Projeções - Receitas'!H34/10^6 -> 1249380.8 | I56: ='Projeções - Receitas'!I34/10^6 -> 1249909.6 | J56: ='Projeções - Receitas'!J34/10^6 -> 1279762.9 | K56: ='Projeções - Receitas'!K34/10^6 -> 1338242.2 | L56: ='Projeções - Receitas'!L34/10^6 -> 1477760.3 | M56: ='Projeções - Receitas'!M34/10^6 -> 1664271.8 | ... Q56: ='Projeções - Receitas'!Q34/10^6 -> 1966323.6 | S56: ='Projeções - Receitas'!S34/10^6 -> 1946686.3 | T56: =S56 -> 1946686.3 | U56: ='Projeções - Receitas'!U34/10^6 -> 2180288.7 | V56: ='Projeções - Receitas'!V34/10^6 -> 2441923.4 | W56: ='Projeções - Receitas'!W34/10^6 -> 2734954.2 | X56: ='Projeções - Receitas'!X34/10^6 -> 3063148.7 | Y56: ='Projeções - Receitas'!Y34/10^6 -> 3430726.5 | Z56: ='Projeções - Receitas'!Z34/10^6 -> 3842413.7 | AA56: ='Projeções - Receitas'!AA34/10^6 -> 4280448.8 | AB56: ='Projeções - Receitas'!AB34/10^6 -> 4691371.9 | ... AD56: ='Projeções - Receitas'!AD34/10^6 -> 5696956.9
E57: Ativos Ponderados pelo Risco / Ativos Rentáveis | F57: =F55/F56 -> 0.71896068 | G57: =G55/G56 -> 0.70350631 | H57: =H55/H56 -> 0.56496087 | I57: =I55/I56 -> 0.55192533 | J57: =J55/J56 -> 0.55595478 | K57: =K55/K56 -> 0.53159436 | L57: =L55/L56 -> 0.51839575 | M57: =M55/M56 -> 0.5602815 | ... Q57: =Q55/Q56 -> 0.56145416 | S57: =Q57 -> 0.56145416 | T57: =S57 -> 0.56145416 | U57: =L57 -> 0.51839575 | V57: =U57 -> 0.51839575 | W57: =V57 -> 0.51839575 | X57: =W57 -> 0.51839575 | Y57: =X57 -> 0.51839575 | Z57: =Y57 -> 0.51839575 | AA57: =Z57 -> 0.51839575 | AB57: =AA57 -> 0.51839575 | AC57: =AB57 -> 0.51839575 | AD57: =AC57 -> 0.51839575
E58: Índice de Basileia (PR/RWA) | F58: =F53/F55 -> 0.16105948 | G58: =G53/G55 -> 0.16127278 | H58: =H53/H55 -> 0.18481685 | I58: =I53/I55 -> 0.19643415 | J58: =J53/J55 -> 0.18858794 | K58: =K53/K55 -> 0.18576056 | L58: =L53/L55 -> 0.21137182 | M58: =M53/M55 -> 0.17764632 | ... Q58: =Q53/Q55 -> 0.16238704 | S58: =S53/S55 -> 0.16896731 | T58: =T53/T55 -> 0.16896731 | U58: =U53/U55 -> 0.17829697 | V58: =V53/V55 -> 0.17398197 | W58: =W53/W55 -> 0.16999152 | X58: =X53/X55 -> 0.16627439 | Y58: =Y53/Y55 -> 0.16279204 | Z58: =Z53/Z55 -> 0.15951538 | ... AD58: =AD53/AD55 -> 0.15721713
E59: Indice de Basiléia Mínimo Exigido | S59: 0.115 | T59: 0.115 | U59: 0.115 | V59: 0.115 | W59: 0.115 | X59: 0.115 | Y59: 0.115 | Z59: 0.115 | AA59: 0.115 | AB59: 0.115 | AC59: 0.115 | AD59: 0.115
E60: Indice de Basiléia Alvo | S60: =P58 -> 0.15718748 | T60: =S60 -> 0.15718748 | U60: =T60 -> 0.15718748 | V60: =U60 -> 0.15718748 | W60: =V60 -> 0.15718748 | X60: =W60 -> 0.15718748 | Y60: =X60 -> 0.15718748 | Z60: =Y60 -> 0.15718748 | AA60: =Z60 -> 0.15718748 | ... AD60: =AC60 -> 0.15718748 | AE60: O Índice de Basiléia será igual ao apresentado em 2022.
E61: Patrimônio de Referência Mínimo Requerido | S61: =S59*S55 -> 125692.14 | T61: =S61 -> 125692.14 | U61: =U59*U55 -> 129979.03 | V61: =V59*V55 -> 145576.51 | W61: =W59*W55 -> 163045.69 | X61: =X59*X55 -> 182611.17 | Y61: =Y59*Y55 -> 204524.51 | Z61: =Z59*Z55 -> 229067.46 | AA61: =AA59*AA55 -> 255181.15 | AB61: =AB59*AB55 -> 279678.54 | ... AD61: =AD59*AD55 -> 339627
E62: Capital Nível I/RWA | F62: =F52/F55 -> 0.11392015 | G62: =G52/G55 -> 0.11387621 | H62: =H52/H55 -> 0.12790733 | I62: =I52/I55 -> 0.13804019 | J62: =J52/J55 -> 0.13392973 | K62: =K52/K55 -> 0.13547924 | L62: =L52/L55 -> 0.1726323 | M62: =M52/M55 -> 0.15159114 | ... Q62: =Q52/Q55 -> 0.14644308 | S62: =S52/S55 -> 0.15286252 | T62: =S62 -> 0.15286252 | U62: =U52/U55 -> 0.16272333 | V62: =V52/V55 -> 0.16007694 | W62: =W52/W55 -> 0.15757631 | X62: =X52/X55 -> 0.15518939 | Y62: =Y52/Y55 -> 0.15289471 | Z62: =Z52/Z55 -> 0.15067849 | AA62: =AA52/AA55 -> 0.14924158 | AB62: =AB52/AB55 -> 0.14993758 | ... AD62: =AD52/AD55 -> 0.15125692
E63: Indice de Capital Principal Mínimo Exigido | S63: 0.095 | T63: 0.095 | U63: 0.095 | V63: 0.095 | W63: 0.095 | X63: 0.095 | Y63: 0.095 | Z63: 0.095 | AA63: 0.095 | AB63: 0.095 | AC63: 0.095 | AD63: 0.095
E64: Capital Nível I Mínimo Requerido | S64: =S63*S55 -> 103832.64 | T64: =S64 -> 103832.64 | U64: =U63*U55 -> 107373.98 | V64: =V63*V55 -> 120258.86 | W64: =W63*W55 -> 134689.92 | X64: =X63*X55 -> 150852.71 | Y64: =Y63*Y55 -> 168955.03 | Z64: =Z63*Z55 -> 189229.64 | AA64: =AA63*AA55 -> 210801.82 | AB64: =AB63*AB55 -> 231038.79 | ... AD64: =AD63*AD55 -> 280561.44
E65: Patrimônio Líquido/Ativos Rentáveis | F65: =F50/F56 -> 0.073740038 | G65: =G50/G56 -> 0.068245815 | H65: =H50/H56 -> 0.06978957 | I65: =I50/I56 -> 0.078984435 | J65: =J50/J56 -> 0.079899866 | K65: =K50/K56 -> 0.081125 | L65: =L50/L56 -> 0.085921316 | M65: =M50/M56 -> 0.08703938 | ... Q65: =Q50/Q56 -> 0.08671556 | S65: =S50/S56 -> 0.090365116 | T65: =S65 -> 0.090365116 | U65: =U50/U56 -> 0.088408495 | V65: =V50/V56 -> 0.086602322 | W65: =W50/W56 -> 0.084918245 | X65: =X50/X56 -> 0.083334657 | Y65: =Y50/Y56 -> 0.081835986 | Z65: =Z50/Z56 -> 0.080411101 | AA65: =AA50/AA56 -> 0.079430845 | AB65: =AB50/AB56 -> 0.079610804 | ... AD65: =AD50/AD56 -> 0.079962233

Sheet DRE CMN 4.720 - Contas Abertas
H4: =Dashboard!$I$4 -> Banco do Brasil ($BBAS3)
A7: Páginas
A8: Dashboard
A9: Ke
A10: DRE + DCF | F10: 2014 | G10: 2015 | H10: 2016 | I10: 2017 | J10: 2018 | K10: 2019 | L10: 2020 | M10: 2021 | N10: 2022 | O10: 1T23 | P10: 2T23 | Q10: 3T23
A11: Contas Abertas | E11: Operações de Crédito | F11: 8.3368571e+10 | G11: 1.0713072e+11 | H11: 9.9083821e+10 | I11: 7.9844265e+10 | J11: 8.1556884e+10 | K11: 7.6119539e+10 | L11: 7.9898419e+10 | M11: 7.9600625e+10 | N11: 1.1221291e+11 | O11: 2.9841209e+10 | P11: 3.1539651e+10 | Q11: 3.7509068e+10
A12: Balanço Patrimonial | E12: Operações de Arrendamento Mercantil | F12: 1.3964768e+08 | G12: 1.8071405e+08 | H12: 1.4536389e+08 | I12: 1.0841224e+08 | J12: 67476869 | K12: 42234265 | L12: 28139079 | M12: 33247442 | N12: 58617849 | O12: 20618823 | P12: 26914963 | Q12: 30188147
A13: Projeções - Receita | E13: Resultado de Operações com TVM | F13: 4.219204e+10 | G13: 6.1847213e+10 | H13: 5.8124829e+10 | I13: 5.2240291e+10 | J13: 4.2045862e+10 | K13: 4.3197768e+10 | L13: 3.1828904e+10 | M13: 4.4018709e+10 | N13: 1.140166e+11 | O13: 3.000243e+10 | P13: 3.051e+10 | Q13: 3.3947343e+10
A14: Painel de Índices | E14: Resultado com Inst. Financeiros Derivativos | F14: 1.3031641e+08 | G14: 1.3802717e+09 | H14: -2.1796115e+09 | I14: -4.6527431e+08 | J14: 5.6893052e+08 | K14: 6.3963152e+08 | L14: 3.4257396e+09 | M14: 1.6101302e+09 | N14: -7.4079502e+08 | O14: 3.8923583e+08 | P14: -1.1418572e+09 | Q14: 6.306793e+08
A15: Projeções Trimestrais | E15: Resultado de Operações de Câmbio | F15: 5.3979338e+08 | G15: 2.7559346e+09 | H15: 1.9052617e+09 | I15: 9.1722863e+08 | J15: 1.9930032e+09 | K15: 1.0897918e+09 | L15: 9.2298667e+08 | M15: -16816851 | N15: 1.1448855e+09 | O15: -4.3516973e+08 | P15: 2.6578476e+08 | Q15: 1.1449866e+09
E16: Resultado das Aplicações Compulsórias | F16: 5.6685071e+09 | G16: 5.0974989e+09 | H16: 5.6084457e+09 | I16: 4.1031331e+09 | J16: 2.5192719e+09 | K16: 2.3281905e+09 | L16: 1.4747614e+09 | M16: 2.128665e+09 | N16: 6.7969609e+09 | O16: 1.8992379e+09 | P16: 1.9493848e+09 | Q16: 2.0239852e+09
E17: Ganho(Perda) Cambial sobre PL no Exterior | F17: 5.9156245e+08 | G17: 3.9662408e+09 | H17: -2.3582768e+09 | I17: 4.1375617e+08 | J17: 1.5666745e+09 | K17: 5.3892002e+08 | L17: 4.4776197e+09 | M17: 7.2262319e+08 | N17: -1.4224398e+09 | O17: -3.3769892e+08 | P17: -7.8783553e+08 | Q17: 4.4049397e+08
E18: Outras Receitas Op. com Caract. de Intermediação Financeira | F18: 3.98811e+08 | G18: 3.7252903e-09 | H18: 0 | I18: 0 | J18: 0 | K18: 0 | L18: 0 | M18: 0 | N18: 0 | O18: 0 | P18: 0 | Q18: 0
E19: Hedge Fiscal | F19: 5.3147242e+08 | G19: 3.0850063e+09 | H19: -1.8626858e+09 | I19: 3.7521493e+08 | J19: 1.4207394e+09 | K19: 4.0308316e+08 | L19: 3.8131083e+09 | M19: 4.8329712e+08 | N19: -69369113 | O19: -16468799 | P19: -38420925 | Q19: 21481877
E20: Total | F20: =SUM(F11:F19) -> 1.3356072e+11 | G20: =SUM(G11:G19) -> 1.854436e+11 | H20: =SUM(H11:H19) -> 1.5846715e+11 | I20: =SUM(I11:I19) -> 1.3753703e+11 | J20: =SUM(J11:J19) -> 1.3173884e+11 | K20: =SUM(K11:K19) -> 1.2435916e+11 | L20: =SUM(L11:L19) -> 1.2586968e+11 | M20: =SUM(M11:M19) -> 1.2858048e+11 | ... Q20: =SUM(Q11:Q19) -> 7.5748225e+10
F24: 2014 | G24: 2015 | H24: 2016 | I24: 2017 | J24: 2018 | K24: 2019 | L24: 2020 | M24: 2021 | N24: 2022 | O24: 1T23 | P24: 2T23 | Q24: 3T23
E25: Operações de Captação no Mercado | F25: -7.6340288e+10 | G25: -9.8250072e+10 | H25: -1.1240531e+11 | I25: -7.6028566e+10 | J25: -6.1232821e+10 | K25: -6.0572098e+10 | L25: -3.5908386e+10 | M25: -5.7809135e+10 | N25: -1.5955989e+11 | O25: -4.0557267e+10 | P25: -4.2045249e+10 | Q25: -4.7531864e+10
E26: Operações de Empréstimos, Cessões e Repasses | F26: -1.4795234e+10 | G26: -3.8177723e+10 | H26: 8.922221e+09 | I26: -8.6260338e+09 | J26: -2.0361472e+10 | K26: -9.840263e+09 | L26: -3.3422193e+10 | M26: -1.1466126e+10 | N26: 9.5944945e+08 | O26: 3.5487769e+08 | P26: 2.6088712e+09 | Q26: -4536588462
E27: Total | F27: =F25+F26 -> -9.1135522e+10 | G27: =G25+G26 -> -1.3642779e+11 | H27: =H25+H26 -> -1.0348309e+11 | I27: =I25+I26 -> -8.46546e+10 | J27: =J25+J26 -> -8.1594293e+10 | K27: =K25+K26 -> -7.0412361e+10 | L27: =L25+L26 -> -6.9330579e+10 | M27: =M25+M26 -> -6.9275261e+10 | ... Q27: =Q25+Q26 -> -5.2068452e+10
F31: 2014 | G31: 2015 | H31: 2016 | I31: 2017 | J31: 2018 | K31: 2019 | L31: 2020 | M31: 2021 | N31: 2022 | O31: 1T23 | P31: 2T23 | Q31: 3T23
E32: Receitas de Intermediação Financeira | F32: =F20 -> 1.3356072e+11 | G32: =G20 -> 1.854436e+11 | H32: =H20 -> 1.5846715e+11 | I32: =I20 -> 1.3753703e+11 | J32: =J20 -> 1.3173884e+11 | K32: =K20 -> 1.2435916e+11 | L32: =L20 -> 1.2586968e+11 | M32: =M20 -> 1.2858048e+11 | N32: =N20 -> 2.3199737e+11 | O32: 6.1363393e+10 | P32: 6.2323621e+10 | Q32: =Q20 -> 7.5748225e+10
E33: Despesas de Intermediação Financeira | F33: =F27 -> -9.1135522e+10 | G33: =G27 -> -1.3642779e+11 | H33: =H27 -> -1.0348309e+11 | I33: =I27 -> -8.46546e+10 | J33: =J27 -> -8.1594293e+10 | K33: =K27 -> -7.0412361e+10 | L33: =L27 -> -6.9330579e+10 | M33: =M27 -> -6.9275261e+10 | N33: =N27 -> -1.5860045e+11 | O33: -4.0202388e+10 | P33: -3.9436377e+10 | Q33: =Q27 -> -5.2068452e+10
E34: Margem Financeira Bruta | F34: =F32+F33 -> 4.2425199e+10 | G34: =G32+G33 -> 4.9015801e+10 | H34: =H32+H33 -> 5.4984054e+10 | I34: =I32+I33 -> 5.2882427e+10 | J34: =J32+J33 -> 5.0144549e+10 | K34: =K32+K33 -> 5.3946797e+10 | L34: =L32+L33 -> 5.6539099e+10 | M34: =M32+M33 -> 5.9305219e+10 | ... Q34: =Q32+Q33 -> 2.3679773e+10
E35: Margem Financeira Bruta (%) | F35: =F34/F32 -> 0.31764727 | G35: =G34/G32 -> 0.26431649 | H35: =H34/H32 -> 0.34697447 | I35: =I34/I32 -> 0.38449593 | J35: =J34/J32 -> 0.38063602 | K35: =K34/K32 -> 0.43379835 | L35: =L34/L32 -> 0.4491876 | M35: =M34/M32 -> 0.46123034 | ... Q35: =Q34/Q32 -> 0.31261159
E36: Provisão para Créditos de Liquidação Duvidosa | F36: =SUM(F37:F40) -> -1.4471849e+10 | G36: =SUM(G37:G40) -> -2.1045428e+10 | H36: =SUM(H37:H40) -> -2.8508133e+10 | I36: =SUM(I37:I40) -> -2.1711215e+10 | J36: =SUM(J37:J40) -> -1.5579956e+10 | K36: =SUM(K37:K40) -> -1.4931232e+10 | L36: =SUM(L37:L40) -> -2.1922968e+10 | M36: =SUM(M37:M40) -> -1.3107746e+10 | ... Q36: =SUM(Q37:Q40) -> -7.5163832e+09
E37: PCLD - Risco de Crédito | F37: -1.7351559e+10 | G37: -2.3670743e+10 | H37: -3.1551547e+10 | I37: -2.5265336e+10 | J37: -1.9649291e+10 | K37: -1.974798e+10 | L37: -2.5560798e+10 | M37: -1.7883941e+10 | N37: -2.3546752e+10 | O37: 1.8890398e+09 | P37: 2.1499258e+09 | Q37: -9.1636554e+09
E38: PCLD - Recuperação de Crédito | F38: 3.4915919e+09 | G38: 3.7171861e+09 | H38: 4.5714147e+09 | I38: 5.1715265e+09 | J38: 6.0076164e+09 | K38: 6.745422e+09 | L38: 7.3594121e+09 | M38: 7.8083509e+09 | N38: 8.7706307e+09 | O38: -4148323000 | P38: -8495466000 | Q38: 2.1311784e+09
E39: PCLD - Descontos Concedidos | F39: -5.8135609e+08 | G39: -8.9567691e+08 | H39: -1.3140008e+09 | I39: -1.4413371e+09 | J39: -1.4266788e+09 | K39: -1.1318816e+09 | L39: -1.0862668e+09 | M39: -2.1349016e+09 | N39: -1.1757733e+09 | O39: -3.5851379e+08 | P39: -4.908324e+08 | Q39: -3.9110512e+08
E40: PCLD - Imparidade | F40: -30526002 | G40: -1.9619461e+08 | H40: -2.1399997e+08 | I40: -1.760684e+08 | J40: -5.1160273e+08 | K40: -7.9679256e+08 | L40: -2.6353151e+09 | M40: -8.9725417e+08 | N40: -7.9484461e+08 | O40: -3.2370403e+09 | P40: -3.3995329e+08 | Q40: -92801144
E41: Margem Financeira Líquida (Resultado Bruto da Intermediação Financeira) | F41: =F34+F36 -> 2.7953349e+10 | G41: =G34+G36 -> 2.7970373e+10 | H41: =H34+H36 -> 2.647592e+10 | I41: =I34+I36 -> 3.1171212e+10 | J41: =J34+J36 -> 3.4564593e+10 | K41: =K34+K36 -> 3.9015565e+10 | L41: =L34+L36 -> 3.4616132e+10 | M41: =M34+M36 -> 4.6197474e+10 | ... Q41: =Q34+Q36 -> 1.616339e+10
E42: Margem Financeira Líquida (%) | F42: =F41/F32 -> 0.20929319 | G42: =G41/G32 -> 0.15082954 | H42: =H41/H32 -> 0.16707514 | I42: =I41/I32 -> 0.22663869 | J42: =J41/J32 -> 0.26237207 | K42: =K41/K32 -> 0.31373295 | L42: =L41/L32 -> 0.27501565 | M42: =M41/M32 -> 0.35928839 | ... Q42: =Q41/Q32 -> 0.21338308
F46: 2014 | G46: 2015 | H46: 2016 | I46: 2017 | J46: 2018 | K46: 2019 | L46: 2020 | M46: 2021 | N46: 2022 | O46: 1T23 | P46: 2T23 | Q46: 3T23
E47: Resultado Bruto da Intermediação Financeira | F47: =F41 -> 2.7953349e+10 | G47: =G41 -> 2.7970373e+10 | H47: =H41 -> 2.647592e+10 | I47: =I41 -> 3.1171212e+10 | J47: =J41 -> 3.4564593e+10 | K47: =K41 -> 3.9015565e+10 | L47: =L41 -> 3.4616132e+10 | M47: =M41 -> 4.6197474e+10 | ... Q47: =Q41 -> 1.616339e+10
E48: Outras Receitas Operacionais | F48: =SUM(F49:F50) -> 2.1778487e+10 | G48: =SUM(G49:G50) -> 2.2047848e+10 | H48: =SUM(H49:H50) -> 2.3794116e+10 | I48: =SUM(I49:I50) -> 2.5941416e+10 | J48: =SUM(J49:J50) -> 2.7452372e+10 | K48: =SUM(K49:K50) -> 2.9208671e+10 | L48: =SUM(L49:L50) -> 2.8701888e+10 | M48: =SUM(M49:M50) -> 2.9343336e+10 | ... Q48: =SUM(Q49:Q50) -> 8669894676
E49: Receitas de Prestação de Serviços | F49: 1.5408449e+10 | G49: 1.4861772e+10 | H49: 1.5304166e+10 | I49: 1.6305667e+10 | J49: 1.6972352e+10 | K49: 1.8129473e+10 | L49: 1.8336443e+10 | M49: 2.0384965e+10 | N49: 2.3529886e+10 | O49: 6.0080432e+09 | P49: 6.0244264e+09 | Q49: 6.3754497e+09
E50: Rendas de Tarifas Bancárias | F50: 6.3700382e+09 | G50: 7.1860752e+09 | H50: 8.4899496e+09 | I50: 9.6357487e+09 | J50: 1.048002e+10 | K50: 1.1079198e+10 | L50: 1.0365445e+10 | M50: 8.9583712e+09 | N50: 8.8032887e+09 | O50: 2.1236593e+09 | P50: 2.2615002e+09 | Q50: 2.294445e+09
E51: Despesas Tributárias sobre Faturamento | F51: -4.0697476e+09 | G51: -4.3215667e+09 | H51: -5.1158347e+09 | I51: -5.0005496e+09 | J51: -4.5897923e+09 | K51: -4.4577427e+09 | L51: -4.8462431e+09 | M51: -5.0006834e+09 | N51: -6.071643e+09 | O51: -1.5519192e+09 | P51: -1.7373917e+09 | Q51: -1.808919e+09
E52: Margem de Contribuição | F52: =SUM(F47:F48,F51) -> 4.5662089e+10 | G52: =SUM(G47:G48,G51) -> 4.5696654e+10 | H52: =SUM(H47:H48,H51) -> 4.5154201e+10 | I52: =SUM(I47:I48,I51) -> 5.2112079e+10 | J52: =SUM(J47:J48,J51) -> 5.7427173e+10 | K52: =SUM(K47:K48,K51) -> 6.3766494e+10 | L52: =SUM(L47:L48,L51) -> 5.8471777e+10 | M52: =SUM(M47:M48,M51) -> 7.0540126e+10 | ... Q52: =SUM(Q47:Q48,Q51) -> 2.3024365e+10
E53: Despesas Administrativas | F53: =SUM(F54:F55) -> -2.9859352e+10 | G53: -3.1645554e+10 | H53: -3.2817134e+10 | I53: -3.0468235e+10 | J53: -3.0679201e+10 | K53: -3.1536829e+10 | L53: -3.158339e+10 | M53: -3.2026217e+10 | N53: -3.3828294e+10 | O53: =SUM(O54:O55) -> -8.6977594e+09 | P53: =SUM(P54:P55) -> -9.0349377e+09 | Q53: =SUM(Q54:Q55) -> -9.1743342e+09
E54: Despesas de Pessoal | F54: -1.7537917e+10 | G54: -1.9232957e+10 | H54: -2.0237927e+10 | I54: -1.8975759e+10 | J54: -1.9520119e+10 | K54: -2.0200283e+10 | L54: -1.9973115e+10 | M54: -2.0210153e+10 | N54: -2.157003e+10 | O54: -5.6176935e+09 | P54: -5.7914926e+09 | Q54: -5.695751e+09
E55: Outras Despesas Administrativas | F55: -1.2321435e+10 | G55: -1.2412596e+10 | H55: -1.2579207e+10 | I55: -1.1492476e+10 | J55: -1.1159082e+10 | K55: -1.1336546e+10 | L55: -1.1610276e+10 | M55: -1.1816064e+10 | N55: -1.2258264e+10 | O55: -3.0800659e+09 | P55: -3.2434451e+09 | Q55: -3.4785831e+09
E56: Outras Despesas Tributárias | F56: -3.2592877e+08 | G56: -4.6696364e+08 | H56: -4.2551964e+08 | I56: -5.0213152e+08 | J56: -5.4034622e+08 | K56: -4.9899796e+08 | L56: -5.006885e+08 | M56: -7.1623729e+08 | N56: -9.2180287e+08 | O56: -3.1638492e+08 | P56: -3.3543291e+08 | Q56: -3.745084e+08
E57: Resultado Comercial | F57: =SUM(F52,F53,F56) -> 1.5476808e+10 | G57: =SUM(G52,G53,G56) -> 1.3584137e+10 | H57: =SUM(H52,H53,H56) -> 1.1911548e+10 | I57: =SUM(I52,I53,I56) -> 2.1141712e+10 | J57: =SUM(J52,J53,J56) -> 2.6207626e+10 | K57: =SUM(K52,K53,K56) -> 3.1730667e+10 | L57: =SUM(L52,L53,L56) -> 2.6387698e+10 | M57: =SUM(M52,M53,M56) -> 3.7797672e+10 | ... Q57: =SUM(Q52,Q53,Q56) -> 1.3475523e+10
E58: Provisões | F58: =SUM(F59:F60) -> -1.5688845e+09 | G58: =SUM(G59:G60) -> -1.9662034e+09 | H58: =SUM(H59:H60) -> -2.7472048e+09 | I58: =SUM(I59:I60) -> -2.7222882e+09 | J58: =SUM(J59:J60) -> -4.1405265e+09 | K58: =SUM(K59:K60) -> -7.1550604e+09 | L58: =SUM(L59:L60) -> -4.2094085e+09 | M58: =SUM(M59:M60) -> -6.4364864e+09 | ... Q58: =SUM(Q59:Q60) -> -1.584096e+09
E59: Demandas Cíveis | F59: -9.6293792e+08 | G59: -1.1956248e+09 | H59: -1.5896432e+09 | I59: -1.1151465e+09 | J59: -2.7580372e+09 | K59: -5.1234631e+09 | L59: -2.0346394e+09 | M59: -4.409746e+09 | N59: -3.5710729e+09 | O59: -7.9623031e+08 | P59: 2.2710035e+08 | Q59: -7.4547496e+08
E60: Demandas Trabalhistas | F60: -6.0594662e+08 | G60: -7.7057865e+08 | H60: -1.1575616e+09 | I60: -1.6071418e+09 | J60: -1.3824893e+09 | K60: -2.0315973e+09 | L60: -2.1747691e+09 | M60: -2.0267404e+09 | N60: -2.462051e+09 | O60: -6.6845232e+08 | P60: -1.1977381e+09 | Q60: -8.3862108e+08
E61: Outros Componentes do Resultado | F61: =SUM(F62:F63) -> 2.6698432e+09 | G61: =SUM(G62:G63) -> 4.149832e+09 | H61: =SUM(H62:H63) -> 1.5520646e+09 | I61: =SUM(I62:I63) -> 1.4401796e+08 | J61: =SUM(J62:J63) -> 1.034346e+09 | K61: =SUM(K62:K63) -> 3.39635e+08 | L61: =SUM(L62:L63) -> -2.0773497e+09 | M61: =SUM(M62:M63) -> -2.551896e+08 | ... Q61: =SUM(Q62:Q63) -> 1.0722859e+09
E62: Resultado de Participações em Coligadas e Controladas | F62: 3.3919583e+09 | G62: 3.8302289e+09 | H62: 4.2689941e+09 | I62: 3.9622612e+09 | J62: 3.7484223e+09 | K62: 4.0489254e+09 | L62: 3.1103988e+09 | M62: 3.2455064e+09 | N62: 5.4873374e+09 | O62: 1.6566822e+09 | P62: 1.8306671e+09 | Q62: 1.8852735e+09
E63: Resultado de Outras Receitas/Despesas Operacionais | F63: =SUM(F64:F67) -> -7.2211512e+08 | G63: =SUM(G64:G67) -> 3.1960318e+08 | H63: =SUM(H64:H67) -> -2.7169295e+09 | I63: =SUM(I64:I67) -> -3.8182432e+09 | J63: =SUM(J64:J67) -> -2.7140763e+09 | K63: =SUM(K64:K67) -> -3.7092904e+09 | L63: =SUM(L64:L67) -> -5.1877485e+09 | M63: =SUM(M64:M67) -> -3.500696e+09 | ... Q63: =SUM(Q64:Q67) -> -8.1298761e+08
E64: Outras Receitas Operacionais | F64: 6.6097268e+09 | G64: 8.6246984e+09 | H64: 8.1998668e+09 | I64: 7.5834082e+09 | J64: 6.4075478e+09 | K64: 6.5548864e+09 | L64: 4.4958406e+09 | M64: 5.1190644e+09 | N64: 9.0900672e+09 | O64: 1.9087473e+09 | P64: 1.5386367e+09 | Q64: 2.0059078e+09
E65: Previ - Plano de Benefícios 1 | F65: 1.3480609e+09 | G65: 3.5799959e+08 | H65: -3.8899164e+08 | I65: -2.5082993e+08 | J65: 6.4369686e+08 | K65: 50418578 | L65: -526213479 | M65: 1627228531 | N65: 2904250476 | O65: 884026728 | P65: 884026728 | Q65: 5.6740156e+08
E66: Previ - Atualização de Fundo Utilização | F66: 8.743087e+08 | G66: 1.3366515e+09 | H66: 1.0435924e+09 | I66: 6.3778991e+08 | J66: 7.962949e+08 | K66: 8.9338209e+08 | L66: 9.6184707e+08 | M66: 1.4815644e+09 | N66: 1.1582975e+09 | O66: 3.452738e+08 | P66: 2.2538586e+08 | Q66: 1.5983085e+08
E67: Outras Despesas Operacionais | F67: -9.5542116e+09 | G67: -9.9997463e+09 | H67: -1.1571397e+10 | I67: -1.1788611e+10 | J67: -1.0561616e+10 | K67: -1.1207977e+10 | L67: -1.0119223e+10 | M67: -1.1728553e+10 | N67: -1.220926e+10 | O67: -3.2916716e+09 | P67: -3.3577334e+09 | Q67: -3.5461278e+09
E68: Resultado Operacional | F68: =SUM(F57,F58,F61) -> 1.6577767e+10 | G68: =SUM(G57,G58,G61) -> 1.5767765e+10 | H68: =SUM(H57,H58,H61) -> 1.0716408e+10 | I68: =SUM(I57,I58,I61) -> 1.8563442e+10 | J68: =SUM(J57,J58,J61) -> 2.3101445e+10 | K68: =SUM(K57,K58,K61) -> 2.4915242e+10 | L68: =SUM(L57,L58,L61) -> 2.010094e+10 | M68: =SUM(M57,M58,M61) -> 3.1105996e+10 | ... Q68: =SUM(Q57,Q58,Q61) -> 1.2963713e+10
E69: Resultado Não Operacional | F69: 1.4382725e+08 | G69: 1.6606351e+08 | H69: 2.2713104e+08 | I69: 1.8627469e+08 | J69: 2.1793005e+08 | K69: 1.2321214e+08 | L69: 1.549019e+08 | M69: 2.460578e+08 | N69: 1.4116386e+08 | O69: 1.0686121e+08 | P69: 51228055 | Q69: 41061561
E70: Resultado Antes do IR | F70: =F68+F69 -> 1.6721594e+10 | G70: =G68+G69 -> 1.5933829e+10 | H70: =H68+H69 -> 1.0943539e+10 | I70: =I68+I69 -> 1.8749716e+10 | J70: =J68+J69 -> 2.3319375e+10 | K70: =K68+K69 -> 2.5038454e+10 | L70: =L68+L69 -> 2.0255842e+10 | M70: =M68+M69 -> 3.1352054e+10 | ... Q70: =Q68+Q69 -> 1.3004774e+10
E71: Imposto de Renda e Contribuição Social | F71: -2.4363414e+09 | G71: -8.2814101e+08 | H71: -1.1790907e+09 | I71: -4.6035192e+09 | J71: -6.6956437e+09 | K71: -3.1404959e+09 | L71: -3.0934574e+09 | M71: -6.0804538e+09 | N71: -1.0195117e+10 | O71: -2.564347e+09 | P71: -2.3347449e+09 | Q71: -2.1393902e+09
E72: Participações Estatutárias no Lucro | F72: -1.4673351e+09 | G72: -1.7896844e+09 | H72: -9.1857229e+08 | I72: -1.4362506e+09 | J72: -1.714864e+09 | K72: -2.3467088e+09 | L72: -1.7020458e+09 | M72: -2.6449656e+09 | N72: -4.058875e+09 | O72: -1.0888784e+09 | P72: -1.1195509e+09 | Q72: -1.1187128e+09
E73: Participações Minoritárias | F73: -1.4751949e+09 | G73: -1.721658e+09 | H73: -1.675039e+09 | I73: -1.6500334e+09 | J73: -1.395849e+09 | K73: -1.7037475e+09 | L73: -1.5765221e+09 | M73: -1.6055132e+09 | N73: -2.6318015e+09 | O73: -8.1428347e+08 | P73: -8.5127961e+08 | Q73: -9.6186417e+08
E74: Lucro Líquido Ajustado | F74: =SUM(F70,F71,F72:F73) -> 1.1342723e+10 | G74: =SUM(G70,G71,G72:G73) -> 1.1594346e+10 | H74: =SUM(H70,H71,H72:H73) -> 7.1708371e+09 | I74: =SUM(I70,I71,I72:I73) -> 1.1059913e+10 | J74: =SUM(J70,J71,J72:J73) -> 1.3513019e+10 | K74: =SUM(K70,K71,K72:K73) -> 1.7847502e+10 | L74: =SUM(L70,L71,L72:L73) -> 1.3883817e+10 | M74: =SUM(M70,M71,M72:M73) -> 2.1021121e+10 | ... Q74: =SUM(Q70,Q71,Q72:Q73) -> 8.7848071e+09
E75: Itens Extraordinários | F75: -97174908 | G75: 2.8052129e+09 | H75: 8.6271862e+08 | I75: -49136775 | J75: -6.5099451e+08 | K75: 3.1456721e+08 | L75: -1.1864323e+09 | M75: -1.3107195e+09 | N75: -8.0307646e+08 | O75: -3.429413e+08 | P75: -4.3080478e+08 | Q75: -3.8865561e+08
E76: Lucro Líquido | F76: =F74+F75 -> 1.1245548e+10 | G76: =G74+G75 -> 1.4399558e+10 | H76: =H74+H75 -> 8.0335558e+09 | I76: =I74+I75 -> 1.1010776e+10 | J76: =J74+J75 -> 1.2862024e+10 | K76: =K74+K75 -> 1.8162069e+10 | L76: =L74+L75 -> 1.2697384e+10 | M76: =M74+M75 -> 1.9710402e+10 | ... Q76: =Q74+Q75 -> 8.3961515e+09
F80: 2014 | G80: 2015 | H80: 2016 | I80: 2017 | J80: 2018 | K80: 2019 | L80: 2020 | M80: 2021 | N80: 2022 | O80: 1T23 | P80: 2T23 | Q80: 3T23
E81: Imposto de Renda e Contribuição Social sobre como % do Resultado Operacional | F81: =F71/F68 -> -0.14696439 | G81: =G71/G68 -> -0.05252114 | H81: =H71/H68 -> -0.11002667 | I81: =I71/I68 -> -0.24798846 | J81: =J71/J68 -> -0.28983657 | K81: =K71/K68 -> -0.12604718 | L81: =L71/L68 -> -0.15389616 | M81: =M71/M68 -> -0.1954753 | ... Q81: =Q71/Q68 -> -0.16502913
E82: Lucro Líquido pertencente ao BB como % do Lucro Líquido Total | F82: =F76/(F70+F71) -> 0.78721378 | G82: =G76/(G70+G71) -> 0.95325407 | H82: =H76/(H70+H71) -> 0.82273523 | I82: =I76/(I70+I71) -> 0.77835592 | J82: =J76/(J70+J71) -> 0.77371462 | K82: =K76/(K70+K71) -> 0.82939555 | L82: =L76/(L70+L71) -> 0.739838 | M82: =M76/(M70+M71) -> 0.77994277 | ... Q82: =Q76/(Q70+Q71) -> 0.77274319
E83: Índice Payout | F83: ='DRE + DCF'!F39 -> 0.40019064 | G83: ='DRE + DCF'!G39 -> 0.40711069 | H83: ='DRE + DCF'!H39 -> 0.29750971 | I83: ='DRE + DCF'!I39 -> 0.29653105 | J83: ='DRE + DCF'!J39 -> 0.40818347 | K83: ='DRE + DCF'!K39 -> 0.37586022 | L83: ='DRE + DCF'!L39 -> 0.33511472 | M83: ='DRE + DCF'!M39 -> 0.68334784 | ... Q83: ='DRE + DCF'!Q39 -> 0.38337122

Sheet Balanço Patrimonial
G4: =Dashboard!$I$4 -> Banco do Brasil ($BBAS3)
A7: Páginas
A8: Dashboard
A9: Ke
A10: DRE + DCF | E10: Data do Último Resultado: | F10: 2014 | G10: 2015 | H10: 2016 | I10: 2017 | J10: 2018 | K10: 2019 | L10: 2020 | M10: 2021 | N10: 2022 | O10: 1T23 | P10: 2T23 | Q10: 3T23
A11: Contas Abertas | E11: Ativo Total | F11: =F12+F51 -> 1.2905412e+12 | G11: =G12+G51 -> 1.4011288e+12 | H11: =H12+H51 -> 1.401377e+12 | I11: =I12+I51 -> 1.3692012e+12 | J11: =J12+J51 -> 1.4352702e+12 | K11: =K12+K51 -> 1.4810952e+12 | L11: =L12+L51 -> 1725671888000 | M11: =M12+M51 -> 1.932533e+12 | ... Q11: =Q12+Q51 -> 2.2489105e+12
A12: Balanço Patrimonial | E12: Ativo Circulante e Realizável a Longo Prazo | F12: =SUM(F13:F15,F20,F25:F26,F28,F31,F47) -> 1.2589618e+12 | G12: =SUM(G13:G15,G20,G25:G26,G28,G31,G47) -> 1.369026e+12 | H12: =SUM(H13:H15,H20,H25:H26,H28,H31,H47) -> 1.3682492e+12 | I12: =SUM(I13:I15,I20,I25:I26,I28,I31,I47) -> 1.3373694e+12 | J12: =SUM(J13:J15,J20,J25:J26,J28,J31,J47) -> 1.4049774e+12 | K12: =SUM(K13:K15,K20,K25:K26,K28,K31,K47) -> 1.4523325e+12 | L12: =SUM(L13:L15,L20,L25:L26,L28,L31,L47) -> 1.6949301e+12 | M12: =SUM(M13:M15,M20,M25:M26,M28,M31,M47) -> 1.8994392e+12 | ... Q12: =SUM(Q13:Q15,Q20,Q25:Q26,Q28,Q31,Q47) -> 2.2083591e+12
A13: Projeções - Receita | E13: Disponibilidades | F13: 1.335728e+10 | G13: 18054422000 | H13: 1.2805771e+10 | I13: 1.3480903e+10 | J13: 1.3614866e+10 | K13: 1.4187864e+10 | L13: 1.6812686e+10 | M13: 1.8054191e+10 | N13: 1.8310546e+10 | O13: 2.4989738e+10 | P13: 2.2541168e+10 | Q13: 2.3808411e+10
A14: Painel de Índices | E14: Aplicações Interfinanceiras de Liquidez | F14: 3.0248158e+11 | G14: 3.5274179e+11 | H14: 4.0571167e+11 | I14: 3.7302333e+11 | J14: 4.150916e+11 | K14: 4.2547736e+11 | L14: 5.1064579e+11 | M14: 5.2406617e+11 | N14: 4.1587344e+11 | O14: 4.5758394e+11 | P14: 4.325125e+11 | Q14: 5.5484548e+11
A15: Projeções Trimestrais | E15: TVM e Instrumentos Financeiros Derivativos | F15: 1.06419e+11 | G15: 1.1728505e+11 | H15: 1.2126868e+11 | I15: 1.3892257e+11 | J15: 1.5109646e+11 | K15: 2.029417e+11 | L15: 2.9844018e+11 | M15: 3.5018127e+11 | N15: 4.3008517e+11 | O15: =SUM(O16:O19) -> 4.3539995e+11 | P15: =SUM(P16:P19) -> 4.4641188e+11 | Q15: =SUM(Q16:Q19) -> 4.4653486e+11
E16: Títulos Disponíveis para Negociação | F16: N/D | G16: 7860341000 | H16: 6074220000 | I16: 7752533000 | J16: 6181752000 | K16: 5704898000 | L16: 17774471000 | M16: 16626979431 | N16: 1.033026e+10 | O16: 10849136000 | P16: 11624753000 | Q16: 9508560000
E17: Títulos Disponíveis para Venda | F17: N/D | G17: 1.0219811e+11 | H17: 1.0798629e+11 | I17: 123505120000 | J17: 1.2437556e+11 | K17: 1.7329161e+11 | L17: 2.5521482e+11 | M17: 3.0551787e+11 | N17: 3.6988044e+11 | O17: 371766432000 | P17: 376794677000 | Q17: 376664487000
E18: Títulos Mantidos até o Vencimento | F18: N/D | G18: 3.8645662e+09 | H18: 5.5956106e+09 | I18: 7.0099988e+09 | J18: 1.9855993e+10 | K18: 2.3124258e+10 | L18: 2.192356e+10 | M18: 2.5901379e+10 | N18: 4.82364e+10 | O18: 48894088000 | P18: 53113357000 | Q18: 56654006000
E19: Instrumentos Financeiros Derivativos | F19: 1.4933149e+09 | G19: 3.362032e+09 | H19: 1.6125633e+09 | I19: 6.5491737e+08 | J19: 6.8316154e+08 | K19: 8.2093538e+08 | L19: 3.5273356e+09 | M19: 2.1350354e+09 | N19: 1.6380689e+09 | O19: 3.8902943e+09 | P19: 4.8790948e+09 | Q19: 3.7078112e+09
E20: Relações Interfinanceiras | F20: 6.7211353e+10 | G20: 6.5408415e+10 | H20: 6.852333e+10 | I20: 78634618000 | J20: 6.8854968e+10 | K20: 7.4920182e+10 | L20: 6.9941221e+10 | M20: 9.0506338e+10 | N20: 1.1264762e+11 | O20: =SUM(O21,O24) -> 1.1824861e+11 | P20: =SUM(P21,P24) -> 1.2067852e+11 | Q20: =SUM(Q21,Q24) -> 1.2014622e+11
E21: Depósitos no Banco Central | F21: 6.3224237e+10 | G21: 6.0810918e+10 | H21: 6.3451094e+10 | I21: 6.9081139e+10 | J21: 5.9115354e+10 | K21: 6.5124107e+10 | L21: 6.0308542e+10 | M21: 7.5504036e+10 | N21: 9.5119085e+10 | O21: =SUM(O22:O23) -> 9.4994646e+10 | P21: =SUM(P22:P23) -> 9.7135227e+10 | Q21: =SUM(Q22:Q23) -> 9.9622647e+10
E22: Compuls. s/ Depósitos não Remunerados | F22: 1.4087806e+10 | G22: 8.0182299e+09 | H22: 1.1443864e+10 | I22: 1.1744668e+10 | J22: 1.0221107e+10 | K22: 1.295566e+10 | L22: 1.2908748e+10 | M22: 1.7617425e+10 | N22: 2.0204006e+10 | O22: 1.9796954e+10 | P22: 1.8350371e+10 | Q22: 1.4937881e+10
E23: Compuls. s/ Depósitos Remunerados | F23: 4.9136431e+10 | G23: 5.2792688e+10 | H23: 5.200723e+10 | I23: 5.7336471e+10 | J23: 4.8894247e+10 | K23: 5.2168447e+10 | L23: 4.7399794e+10 | M23: 5.788661e+10 | N23: 7.4915079e+10 | O23: 7.5197692e+10 | P23: 7.8784857e+10 | Q23: 8.4684765e+10
E24: Demais | F24: 3.987116e+09 | G24: 4.5974966e+09 | H24: 5.0722365e+09 | I24: 9.5534794e+09 | J24: 9.7396134e+09 | K24: 9.7960752e+09 | L24: 9.6326788e+09 | M24: 1.5002302e+10 | N24: 1.7528538e+10 | O24: 2.3253962e+10 | P24: 2.3543292e+10 | Q24: 2.0523571e+10
E25: Relações Interdependências | F25: 5.9294304e+08 | G25: 5.9767559e+08 | H25: 3.7652959e+08 | I25: 4.0486972e+08 | J25: 2.5474659e+08 | K25: 2.8694319e+08 | L25: 1.1715375e+08 | M25: 38658256 | N25: 65989379 | O25: 29813125 | P25: 20338827 | Q25: 16681113
E26: Empréstimos e Financiamentos | F26: 5.9491309e+11 | G26: 6.2787779e+11 | H26: 5.6492334e+11 | I26: 5.4428977e+11 | J26: 5.4898812e+11 | K26: 5.2888156e+11 | L26: 5.8144846e+11 | M26: 6.6171929e+11 | N26: 7.492403e+11 | O26: 7.6847829e+11 | P26: 7.7261595e+11 | Q26: 8.0087543e+11
E27: (Prov. p/ Créditos de Liquidação Duvidosa) | F27: -2.445486e+10 | G27: -3.2489941e+10 | H27: -3.4838451e+10 | I27: -3.5444029e+10 | J27: -3.2778037e+10 | K27: -3.7751311e+10 | L27: -4.2968298e+10 | M27: -4.230195e+10 | N27: -4.7831412e+10 | O27: -4.6223212e+10 | P27: -4.8299811e+10 | Q27: -5.0622758e+10
E28: Operações de Arrendamento Mercantil | F28: 8.4515472e+08 | G28: 8.2578924e+08 | H28: 5.6282296e+08 | I28: 378054000 | J28: 223460000 | K28: 1.87529e+08 | L28: 1.6877669e+08 | M28: 2.7833276e+08 | N28: 4.1132069e+08 | O28: =SUM(O29:O30) -> 4.7216369e+08 | P28: =SUM(P29:P30) -> 5.2152542e+08 | Q28: =SUM(Q29:Q30) -> 5.3012488e+08
E29: Op. de Arr. e Subarrend. a Receber | F29: 874835000 | G29: 874835000 | H29: 604196000 | I29: 398557000 | J29: 233714000 | K29: 1.9131137e+08 | L29: 1.7247782e+08 | M29: 2.8097112e+08 | N29: 4.1472613e+08 | O29: 4.7634211e+08 | P29: 5.2553762e+08 | Q29: 5.3476633e+08
E30: (PCLD de Arrendamento Mercantil) | F30: -29680283 | G30: -49045756 | H30: -41373041 | I30: -20503000 | J30: -10254000 | K30: -3782371.1 | L30: -3701126.4 | M30: -2638356.1 | N30: -3405439.8 | O30: -4178416.7 | P30: -4012198.7 | Q30: -4641452
E31: Outros Créditos | F31: 1.7260979e+11 | G31: 185738476000 | H31: 193605711000 | I31: 187694622000 | J31: 2.0618678e+11 | K31: 2.045371e+11 | L31: 2.1633036e+11 | M31: 2.5351771e+11 | N31: 2.6297466e+11 | O31: 2.6951011e+11 | P31: 2.6641073e+11 | Q31: 2.6070295e+11
E32: Créditos por Avais e Fianças Honrados | F32: 2.3536917e+08 | G32: 3.9755001e+08 | H32: 4.9454334e+08 | I32: 6.0173898e+08 | J32: 3.6273705e+08 | K32: 4.46862e+08 | L32: 2.2330637e+08 | M32: 87256062 | N32: 31022869 | O32: 32870741 | P32: 75686082 | Q32: 1.3018719e+08
E33: Carteira de Câmbio | F33: 1.7508464e+10 | G33: 2.1420123e+10 | H33: 1.7471545e+10 | I33: 1.9057714e+10 | J33: 2.5113541e+10 | K33: 1.6245614e+10 | L33: 1.8759183e+10 | M33: 2.249178e+10 | N33: 2.8986976e+10 | O33: 2.8512021e+10 | P33: 31111844321 | Q33: 2.7298305e+10
E34: Rendas a Receber | F34: 3.8605945e+09 | G34: 2.820834e+09 | H34: 2.6761279e+09 | I34: 2.9485307e+09 | J34: 3.4814041e+09 | K34: 3.674305e+09 | L34: 4296618511 | M34: 4.6573331e+09 | N34: 5.4581981e+09 | O34: 7.6509525e+09 | P34: 5.8053372e+09 | Q34: 6.4518541e+09
E35: Negociação e Intermediação de Valores | F35: 1.1448251e+09 | G35: 1.6531643e+09 | H35: 1.1068015e+09 | I35: 8.9117226e+08 | J35: 8.9196353e+08 | K35: 1.0092288e+09 | L35: 1.5149454e+09 | M35: 2.6363197e+09 | N35: 2.3683429e+09 | O35: 2.0396972e+09 | P35: 2.3138877e+09 | Q35: 3.1764721e+09
E36: Créditos Específicos | F36: 1.5500874e+09 | G36: 3.3460393e+08 | H36: 3.7823832e+08 | I36: 4.1680183e+08 | J36: 3.9290727e+08 | K36: 3.92908e+08 | L36: 3.9290804e+08 | M36: 494026.03 | N36: 0 | O36: 0 | P36: 0 | Q36: 0
E37: Crédito Tributário | F37: 2.5137751e+10 | G37: 3.9995482e+10 | H37: 4.2883504e+10 | I37: 3.9722336e+10 | J37: 3.8643121e+10 | K37: 5.9462932e+10 | L37: 5.9109146e+10 | M37: 5.6620005e+10 | N37: 5.5294024e+10 | O37: 5.5593777e+10 | P37: 5.6949153e+10 | Q37: 5.7804566e+10
E38: Ativo Atuarial | F38: 6130485000 | G38: -1475583000 | H38: -2201588000 | I38: 4382919000 | J38: 3584390000 | K38: -8232135000 | L38: 5862263000 | M38: 20233055000 | N38: 28830245249 | O38: 29438405000 | P38: 20797413000 | Q38: 21511171000
E39: Fundo Paridade | F39: 118889000 | G39: 120377000 | H39: 129900000 | I39: 102726000 | J39: 0 | K39: 0 | L39: 0 | M39: 0 | N39: 0 | O39: 0 | P39: 0 | Q39: 0
E40: Devedores por Depósitos em Garantia | F40: 3.6439395e+10 | G40: 4.3819012e+10 | H40: 5.0626392e+10 | I40: 5.5337091e+10 | J40: 5.6374198e+10 | K40: 5.2630037e+10 | L40: 5.3761258e+10 | M40: 5.4692142e+10 | N40: 3.5713451e+10 | O40: 3.6479222e+10 | P40: 3.7070635e+10 | Q40: 3.705894e+10
E41: Fundo de Destinação do Superávit - Previ | F41: 8.1552426e+09 | G41: 8.959543e+09 | H41: 9.4321097e+09 | I41: 9.499488e+09 | J41: 9.5117609e+09 | K41: 9.5723857e+09 | L41: 9.9123868e+09 | M41: 1.0795343e+10 | N41: 1.1315371e+10 | O41: =O42 -> 1.1507013e+10 | P41: 1.1579611e+10 | Q41: 1.1587229e+10
E42: Fundo de Utilização | F42: 8.1552426e+09 | G42: 8.959543e+09 | H42: 9.4321097e+09 | I42: 9.499488e+09 | J42: 9.5117609e+09 | K42: 9.5723857e+09 | L42: 9.9123868e+09 | M42: 1.0795343e+10 | N42: 1.1315371e+10 | O42: 1.1507013e+10 | P42: 1.1579611e+10 | Q42: 1.1587229e+10
E43: Diversos | F43: 7.4180496e+10 | G43: 7.0010583e+10 | H43: 7.3354917e+10 | I43: 5.7702068e+10 | J43: 7.17984e+10 | K43: 7.3574867e+10 | L43: 6.7305933e+10 | M43: 8.6911928e+10 | N43: 1.0119059e+11 | O43: 1.0401469e+11 | P43: 1.0653791e+11 | Q43: 1.0147661e+11
E44: (Provisão p/ Outros Créd. De Liq. Duvidosa) | F44: -1.8518061e+09 | G44: -2.3172134e+09 | H44: -2.7467805e+09 | I44: -2.9679627e+09 | J44: -3.9676458e+09 | K44: -4.239905e+09 | L44: -4.8075879e+09 | M44: -5.6079473e+09 | N44: -6.2135669e+09 | O44: =SUM(O45:O46) -> -5.7585433e+09 | P44: =P45+P46 -> -5.8307473e+09 | Q44: =Q45+Q46 -> -5.7923841e+09
E45: (Com Característica de Concessão de Crédito) | F45: -8.1042026e+08 | G45: -1.0295925e+09 | H45: -1.2548466e+09 | I45: -1.2842316e+09 | J45: -1.5429576e+09 | K45: -2.0447518e+09 | L45: -2.1968978e+09 | M45: -2.3611299e+09 | N45: -2.8622594e+09 | O45: -2.4277208e+09 | P45: -2.371129e+09 | Q45: -2.2040525e+09
E46: (Sem Característica de Concessão de Crédito) | F46: -1.0413859e+09 | G46: -1.2876209e+09 | H46: -1.491934e+09 | I46: -1.6837311e+09 | J46: -2.4246882e+09 | K46: -2.1951532e+09 | L46: -2.6106901e+09 | M46: -3.2468174e+09 | N46: -3.3513075e+09 | O46: -3.3308225e+09 | P46: -3.4596183e+09 | Q46: -3.5883316e+09
E47: Outros Valores e Bens | F47: 5.3157422e+08 | G47: 4.9662769e+08 | H47: 4.7137139e+08 | I47: 5.4067316e+08 | J47: 666387000 | K47: 9.1223348e+08 | L47: 1.0254959e+09 | M47: 1.0772617e+09 | N47: 1.0788934e+09 | O47: =SUM(O48:O50) -> 1.1491662e+09 | P47: =SUM(P48:P50) -> 9.3597086e+08 | Q47: =SUM(Q48:Q50) -> 8.9891e+08
E48: Bens Não de Uso Próprio e Mat. em Estoque | F48: 3.1630274e+08 | G48: 3.3253332e+08 | H48: 3.393018e+08 | I48: 4.1254315e+08 | J48: 5.5127634e+08 | K48: 7.6004498e+08 | L48: 8.4812661e+08 | M48: 8.4675828e+08 | N48: 6.7221888e+08 | O48: 5.9644771e+08 | P48: 5.4542032e+08 | Q48: 5.239268e+08
E49: (Provisões para Desvalorizações) | F49: -1.2932784e+08 | G49: -1.2093991e+08 | H49: -1.3756394e+08 | I49: -1.575865e+08 | J49: -1.5581802e+08 | K49: -1.5673564e+08 | L49: -1.622315e+08 | M49: -1.7570732e+08 | N49: -1.7710349e+08 | O49: -1.7553098e+08 | P49: -1.7694188e+08 | Q49: -1.71945e+08
E50: Despesas Antecipadas | F50: 3.4459933e+08 | G50: 2.8503428e+08 | H50: 2.6963352e+08 | I50: 2.857165e+08 | J50: 2.7092869e+08 | K50: 3.0892415e+08 | L50: 3.3960076e+08 | M50: 4.0621074e+08 | N50: 583778053 | O50: 7.2824945e+08 | P50: 567492418 | Q50: 5.4692819e+08
E51: Permanente | F51: =SUM(F52:F55) -> 3.1579444e+10 | G51: =SUM(G52:G55) -> 3.2102729e+10 | H51: =SUM(H52:H55) -> 3.3127743e+10 | I51: =SUM(I52:I55) -> 3.1831765e+10 | J51: =SUM(J52:J55) -> 3.029284e+10 | K51: =SUM(K52:K55) -> 2.8762693e+10 | L51: =SUM(L52:L55) -> 3.0741759e+10 | M51: =SUM(M52:M55) -> 3.3093763e+10 | ... Q51: =SUM(Q52:Q55) -> 4.0551472e+10
E52: Investimentos | F52: 1.3635105e+10 | G52: 1.5452248e+10 | H52: 1.6855006e+10 | I52: 1.7489733e+10 | J52: 1.6973191e+10 | K52: 1.4959449e+10 | L52: 1.6290239e+10 | M52: 1.7521269e+10 | N52: 1.8353643e+10 | O52: 1.9488781e+10 | P52: 2.0011221e+10 | Q52: 2.0282925e+10
E53: Imobilizado de Uso | F53: 7.0795428e+09 | G53: 7.3230344e+09 | H53: 7.5574776e+09 | I53: 7.4153019e+09 | J53: 7.5376175e+09 | K53: 7.8826945e+09 | L53: 8.2308537e+09 | M53: 8.5412358e+09 | N53: 8.8259183e+09 | O53: 8.6837733e+09 | P53: 9.5074815e+09 | Q53: 9.5872359e+09
E54: Intangível | F54: 1.0834838e+10 | G54: 9.3108716e+09 | H54: 8.7152603e+09 | I54: 6.9267294e+09 | J54: 5.7820317e+09 | K54: 5.9205495e+09 | L54: 6.2206656e+09 | M54: 7.0312582e+09 | N54: 1.1090645e+10 | O54: 1.0709876e+10 | P54: 1.0985058e+10 | Q54: 1.0681312e+10
E55: Diferido | F55: 29957155 | G55: 16575515 | H55: 0 | I55: 0 | J55: 0 | K55: 0 | L55: 0 | M55: 0 | N55: 0 | O55: 0 | P55: 0 | Q55: 0
E56: Passivo Total | F56: =F57 -> 1.2095026e+12 | G56: =G57 -> 1.3191334e+12 | H56: =H57 -> 1.313737e+12 | I56: =I57 -> 1.2700484e+12 | J56: =J57 -> 1.3325691e+12 | K56: =K57 -> 1.3724378e+12 | L56: =L57 -> 1.5984968e+12 | M56: =M57 -> 1.7874836e+12 | ... Q56: =Q57 -> 2.0783997e+12
E57: Circulante e Exigível a Longo Prazo | F57: =SUM(F58,F64,F66,F71:F73,F76,F82:F84) -> 1.2095026e+12 | G57: =SUM(G58,G64,G66,G71:G73,G76,G82:G84) -> 1.3191334e+12 | H57: =SUM(H58,H64,H66,H71:H73,H76,H82:H84) -> 1.313737e+12 | I57: =SUM(I58,I64,I66,I71:I73,I76,I82:I84) -> 1.2700484e+12 | J57: =SUM(J58,J64,J66,J71:J73,J76,J82:J84) -> 1.3325691e+12 | K57: =SUM(K58,K64,K66,K71:K73,K76,K82:K84) -> 1.3724378e+12 | L57: =SUM(L58,L64,L66,L71:L73,L76,L82:L84) -> 1.5984968e+12 | M57: =SUM(M58,M64,M66,M71:M73,M76,M82:M84) -> 1.7874836e+12 | ... Q57: =SUM(Q58,Q64,Q66,Q71:Q73,Q76,Q82:Q84) -> 2.0783997e+12
E58: Depósitos | F58: 4.6817606e+11 | G58: 4.6441972e+11 | H58: 4.4598069e+11 | I58: 4.5022936e+11 | J58: 4.8603677e+11 | K58: 5.1413078e+11 | L58: 6.2767115e+11 | M58: 6.9723836e+11 | N58: 7.7718433e+11 | O58: =SUM(O59:O63) -> 7.7485865e+11 | P58: =SUM(P59:P63) -> 7.9336234e+11 | Q58: =SUM(Q59:Q63) -> 7.9962072e+11
E59: Depósitos à Vista | F59: 7.4224354e+10 | G59: 6.654976e+10 | H59: 69349186000 | I59: 6.9981063e+10 | J59: 6.7810697e+10 | K59: 7.1066576e+10 | L59: 9.830741e+10 | M59: 1.1875834e+11 | N59: 1.0786038e+11 | O59: 1.0157873e+11 | P59: 1.0533415e+11 | Q59: 1.0537413e+11
E60: Depósitos de Poupança | F60: 148698889664 | G60: 1.5184528e+11 | H60: 1.5176334e+11 | I60: 1.6028987e+11 | J60: 1.7485474e+11 | K60: 1.8094285e+11 | L60: 2.1939633e+11 | M60: 2.2545275e+11 | N60: 2.1343581e+11 | O60: 2.0676806e+11 | P60: 2.0595254e+11 | Q60: 2.0650368e+11
E61: Depósitos Interfinanceiros | F61: 3.0353883e+10 | G61: 4.1482548e+10 | H61: 2.0664801e+10 | I61: 2.4152759e+10 | J61: 3.3668595e+10 | K61: 2.9128475e+10 | L61: 2.5686889e+10 | M61: 2.5968818e+10 | N61: 2.3921286e+10 | O61: 2.4135041e+10 | P61: 2.4831616e+10 | Q61: 2.5766718e+10
E62: Depósitos a Prazo | F62: 2.1489894e+11 | G62: 2.0454213e+11 | H62: 2.0415025e+11 | I62: 1.9562882e+11 | J62: 2.094915e+11 | K62: 2.3274971e+11 | L62: 2.838196e+11 | M62: 3.2664009e+11 | N62: 4.3155038e+11 | O62: 4.4202486e+11 | P62: 4.5690792e+11 | Q62: 4.6175423e+11
E63: Outros Depósitos | F63: 0 | G63: 0 | H63: 53111284 | I63: 1.768421e+08 | J63: 2.1123195e+08 | K63: 2.4316873e+08 | L63: 4.6092417e+08 | M63: 4.1836106e+08 | N63: 4.1647645e+08 | O63: 3.5195601e+08 | P63: 3.3612027e+08 | Q63: 2.2195448e+08
E64: Captações no Mercado Aberto | F64: 2.9392043e+11 | G64: 3.3352165e+11 | H64: 3.7463403e+11 | I64: 3.7624269e+11 | J64: 4.029012e+11 | K64: 4.0435533e+11 | L64: 5.0372282e+11 | M64: 6.2183675e+11 | N64: 5.644536e+11 | O64: 6.4140571e+11 | P64: 5.7483178e+11 | Q64: 6.9779687e+11
E65: Operações Compromissadas com Títulos Privados | F65: 4.8255571e+10 | G65: 5.2141994e+10 | H65: 2.5591345e+10 | I65: 2.3576205e+10 | J65: 1.7417544e+10 | K65: 1.2957635e+10 | L65: 1.3675125e+10 | M65: 1.3608116e+10 | N65: 1.0524493e+10 | O65: 7.3209364e+09 | P65: 7.6201414e+09 | Q65: 7.9807775e+09
E66: Recursos de Aceites e Emissão de Títulos | F66: 1.4759077e+11 | G66: 1.8856149e+11 | H66: 165166353000 | I66: 1.337658e+11 | J66: 1.248185e+11 | K66: 1.2965092e+11 | L66: 1.2476886e+11 | M66: 1.3220071e+11 | N66: 1.7491384e+11 | O66: =SUM(O67:O70) -> 1.9376339e+11 | P66: =SUM(P67:P70) -> 2.2259192e+11 | Q66: 2.3862637e+11
E67: Letras de Crédito do Agronegócio | F67: 1.023253e+11 | G67: 1.3482292e+11 | H67: 1.2496533e+11 | I67: 8.8897938e+10 | J67: 7.8937444e+10 | K67: 7.5882065e+10 | L67: 7.4210446e+10 | M67: 8.1396088e+10 | N67: 1.2224878e+11 | O67: 1.3733483e+11 | P67: 1.6146792e+11 | Q67: 174967586512
E68: Letras de Crédito Imobiliário | F68: 1.4155946e+10 | G68: 1.8121444e+10 | H68: 1.7073621e+10 | I68: 1.6885957e+10 | J68: 1.7264716e+10 | K68: 1.699268e+10 | L68: 1.2437868e+10 | M68: 1.2547847e+10 | N68: 1.2197438e+10 | O68: 1.2075309e+10 | P68: 1.3974362e+10 | Q68: 1.4510284e+10
E69: Demais Letras Bancárias | F69: 2.5491904e+09 | G69: 2.1060475e+09 | H69: 2.7341379e+09 | I69: 3.9771877e+09 | J69: 5.5368002e+09 | K69: 5.3026405e+09 | L69: 3.8010291e+08 | M69: 10739967 | N69: 4.5249945e+09 | O69: 7.7687122e+09 | P69: 9.0363072e+09 | Q69: 9.3651331e+09
E70: Obrigações por TVM no Exterior | F70: 28560340000 | G70: 3.351108e+10 | H70: 20393260000 | I70: 24004715000 | J70: 23079535000 | K70: 3.1473535e+10 | L70: 3.7740442e+10 | M70: 3.8246039e+10 | N70: 3.594263e+10 | O70: 3.6584538e+10 | P70: 3.8113329e+10 | Q70: 3.9783361e+10
E71: Relações Interfinanceiras | F71: 31462661 | G71: 30620518 | H71: 1075481 | I71: 1148907.8 | J71: 1637995.7 | K71: 1001268.1 | L71: 2.9951695e+10 | M71: 4.0647339e+10 | N71: 4.5648692e+10 | O71: 4.744227e+10 | P71: 4.9141915e+10 | Q71: 4.9053843e+10
E72: Relações Interdependências | F72: 5.272762e+09 | G72: 5.4387854e+09 | H72: 2.4500122e+09 | I72: 2.4955319e+09 | J72: 2.4907703e+09 | K72: 2.9718448e+09 | L72: 3.1099342e+09 | M72: 3.6590202e+09 | N72: 5.055894e+09 | O72: 6.0975688e+09 | P72: 5.2246129e+09 | Q72: 4.7541243e+09
E73: Obrigações por Empréstimos | F73: 2.0515565e+10 | G73: 2.965536e+10 | H73: 2.0409348e+10 | I73: 1.9572494e+10 | J73: 2.0986748e+10 | K73: 1.7966872e+10 | L73: 1.5552734e+10 | M73: 1.4887652e+10 | N73: 2.0395068e+10 | O73: =SUM(O74:O75) -> 1.8751909e+10 | P73: =SUM(P74:P75) -> 2.0253295e+10 | Q73: =SUM(Q74:Q75) -> 2.0401012e+10
E74: Empréstimos no País - Outras Instituições | F74: 0 | G74: 38494483 | H74: 0 | I74: 0 | J74: 0 | K74: 0 | L74: 0 | M74: 0 | N74: 0 | O74: 0 | P74: 0 | Q74: 0
E75: Empréstimos no Exterior | F75: 2.0515565e+10 | G75: 2.9616866e+10 | H75: 2.0409348e+10 | I75: 1.9572494e+10 | J75: 2.0986748e+10 | K75: 1.7966872e+10 | L75: 1.5552734e+10 | M75: 1.4887652e+10 | N75: 2.0395068e+10 | O75: 1.8751909e+10 | P75: 2.0253295e+10 | Q75: 2.0401012e+10
E76: Obrigações por Repasses | F76: 8.9156867e+10 | G76: 9.0065408e+10 | H76: 8.3082693e+10 | I76: 8.0884739e+10 | J76: 6.6731064e+10 | K76: 6.0908742e+10 | L76: 5.8331324e+10 | M76: 5.0844697e+10 | N76: 4.3991197e+10 | O76: =SUM(O77:O81) -> 4.3042033e+10 | P76: =SUM(P77:P81) -> 4.2241753e+10 | Q76: =SUM(Q77:Q81) -> 4.1723774e+10
E77: Tesouro Nacional | F77: 2.8461182e+08 | G77: 1.7814463e+08 | H77: 1.4924844e+08 | I77: 1.4526406e+08 | J77: 1.6555665e+08 | K77: 1.6721484e+08 | L77: 1.7299472e+08 | M77: 1.4296878e+08 | N77: 1.328281e+08 | O77: 1.7735697e+08 | P77: 1.7092876e+08 | Q77: 1.6330828e+08
E78: BNDES | F78: 4.3250643e+10 | G78: 3.7981403e+10 | H78: 3.2086856e+10 | I78: 2.6936191e+10 | J78: 2.1764812e+10 | K78: 1.7838581e+10 | L78: 1.9161196e+10 | M78: 1.6638212e+10 | N78: 1.3318066e+10 | O78: 1.3002006e+10 | P78: 1.2595167e+10 | Q78: 1.2139031e+10
E79: CEF | F79: 1.2359686e+10 | G79: 1.9690627e+10 | H79: 2.3758043e+10 | I79: 2.6558065e+10 | J79: 2.9413089e+10 | K79: 3.0936767e+10 | L79: 3.0259319e+10 | M79: 2.8303957e+10 | N79: 2.7332771e+10 | O79: 2.7125399e+10 | P79: 2.7129287e+10 | Q79: 2.7070607e+10
E80: Finame | F80: 3.2398036e+10 | G80: 2.9981346e+10 | H80: 2.476586e+10 | I80: 1.9775097e+10 | J80: 1.5138554e+10 | K80: 1.1932324e+10 | L80: 8.5873528e+09 | M80: 5.5588005e+09 | N80: 2.933975e+09 | O80: 2.481722e+09 | P80: 2.0689638e+09 | Q80: 1.9616845e+09
E81: Outras Instituições | F81: 8.6388867e+08 | G81: 2.2338866e+09 | H81: 2.322686e+09 | I81: 7.4701202e+09 | J81: 2.4905152e+08 | K81: 33854480 | L81: 1.5046152e+08 | M81: 2.0075923e+08 | N81: 2.7355728e+08 | O81: 2.555484e+08 | P81: 2.7740643e+08 | Q81: 3.8914434e+08
E82: Obrigações por Repasses do Exterior | F82: 477151.22 | G82: 10297970 | H82: 477151.22 | I82: 477151.22 | J82: 477151.22 | K82: 0 | L82: 0 | M82: 0 | N82: 0 | O82: 0 | P82: 0 | Q82: 0
E83: Instrumentos Financeiros Derivativos | F83: 2.6501841e+09 | G83: 3.2891745e+09 | H83: 1.8703914e+09 | I83: 7.8988735e+08 | J83: 8.0920138e+08 | K83: 9.6161244e+08 | L83: 3.049843e+09 | M83: 2.6039265e+09 | N83: 3.0454631e+09 | O83: 5.038004e+09 | P83: 5.110148e+09 | Q83: 4.1657902e+09
E84: Outras Obrigações | F84: 1.8218805e+11 | G84: 204140873000 | H84: 2.2014189e+11 | I84: 2.0606626e+11 | J84: 2.2779274e+11 | K84: 2.4149067e+11 | L84: 2.3233842e+11 | M84: 2.2356516e+11 | N84: 2.3068184e+11 | O84: =SUM(O85:O96) -> 2.1481203e+11 | P84: =SUM(P85:P96) -> 2.2271433e+11 | Q84: =SUM(Q85:Q96) -> 2.2225719e+11
E85: Cobrança e Arrec. de Tributos e Assemelhados | F85: 3.4690979e+08 | G85: 3.9822861e+08 | H85: 4.2746261e+08 | I85: 4.9316702e+08 | J85: 4.2678635e+08 | K85: 4.4906755e+08 | L85: 3.922422e+08 | M85: 4.8798729e+08 | N85: 4.6020611e+08 | O85: 5.3103205e+09 | P85: 4.2963031e+09 | Q85: 4.7084446e+09
E86: Carteira de Câmbio | F86: 2.11875e+10 | G86: 1.559994e+10 | H86: 2.3201288e+10 | I86: 9.7400278e+09 | J86: 3.2891617e+10 | K86: 3.1797425e+10 | L86: 5.1376936e+10 | M86: 3.8905708e+10 | N86: 5.5205592e+10 | O86: 3.9464384e+10 | P86: 5.2010459e+10 | Q86: 4.4072664e+10
E87: Sociais e Estatutárias | F87: 2.1853653e+09 | G87: 1.5883807e+09 | H87: 1.1262346e+09 | I87: 2.1778199e+09 | J87: 3.9627351e+09 | K87: 4.7902521e+09 | L87: 2.4861986e+09 | M87: 4.4602983e+09 | N87: 5.8415344e+09 | O87: 5.365703e+09 | P87: 5.6582917e+09 | Q87: 3.4791069e+09
E88: Fiscais e Previdenciárias | F88: 1.8939192e+10 | G88: 1.9934158e+10 | H88: 16026047000 | I88: 1.2375968e+10 | J88: 1.1557117e+10 | K88: 1.2571121e+10 | L88: 1.4158192e+10 | M88: 1.923885e+10 | N88: 2.0972583e+10 | O88: 1.8174827e+10 | P88: 1.6122073e+10 | Q88: 1.8400062e+10
E89: Negociação e Intermediação de Valores | F89: 5.8907811e+08 | G89: 6.7176138e+08 | H89: 4.0459361e+08 | I89: 1.2056481e+09 | J89: 9.7786348e+08 | K89: 1.1996596e+09 | L89: 1.1967e+09 | M89: 1.37487e+09 | N89: 1.252363e+09 | O89: 1.1932708e+09 | P89: 1.4172356e+09 | Q89: 2.3916485e+09
E90: Fundos Financeiros e de Desenvolvimento | F90: 1.0840397e+10 | G90: 1.5002524e+10 | H90: 1.4790525e+10 | I90: 1.679475e+10 | J90: 1.5522421e+10 | K90: 1.7012893e+10 | L90: 2.1650544e+10 | M90: 2.7029673e+10 | N90: 3.4475895e+10 | O90: 3.8983202e+10 | P90: 4.0143914e+10 | Q90: 4.1127307e+10
E91: Instrumentos Híbridos de Capital e Dívida | F91: 4.8657399e+09 | G91: 7.8665073e+09 | H91: 5.5253385e+09 | I91: 5.607779e+09 | J91: 4.308063e+09 | K91: 4.5272198e+09 | L91: 5.2771215e+08 | M91: 6.0481727e+08 | N91: 8.8335325e+08 | O91: 8.8487764e+08 | P91: 2.5697144e+08 | Q91: 7.158872e+08
E92: Operações Especiais | F92: 2152602.8 | G92: 2187043.6 | H92: 2202692.1 | I92: 2215630.5 | J92: 2215630.5 | K92: 2181127.3 | L92: 2181127.3 | M92: 2287566.4 | N92: 2217792.1 | O92: 2229564 | P92: 2240189 | Q92: 2251143.1
E93: FCO (Dívida Subordinada) | F93: 4.9413216e+10 | G93: 5.4017756e+10 | H93: 5.5101546e+10 | I93: 5.5681826e+10 | J93: 5.0570149e+10 | K93: 4.1626846e+10 | L93: 4.1744974e+10 | M93: 3.6218805e+10 | N93: 2.4493893e+10 | O93: 1.7602139e+10 | P93: 1.7602139e+10 | Q93: 1.7602139e+10
E94: Passivo Atuarial | F94: 5830331000 | G94: 6248098000 | H94: 7948422000 | I94: 8724130000 | J94: 9152351000 | K94: 13072731000 | L94: 12278703000 | M94: 9212441000 | N94: 8808892000 | O94: 8876312000 | P94: 10508019000 | Q94: 10508019000
E95: Diversas | F95: 4.6737641e+10 | G95: 5.5518029e+10 | H95: 7.0873737e+10 | I95: 6.749116e+10 | J95: 6.9335737e+10 | K95: 8.3915737e+10 | L95: 5.0373446e+10 | M95: 5.4895261e+10 | N95: 4.8830428e+10 | O95: 5.0116749e+10 | P95: 5.313516e+10 | Q95: 5.5473497e+10
E96: Instrumentos de dívidas elegíveis a capital | F96: 2.1250525e+10 | G96: 2.7293304e+10 | H96: 2.4714493e+10 | I96: 2.5771772e+10 | J96: 2.9085685e+10 | K96: 3.052554e+10 | L96: 3.6150595e+10 | M96: 3.113416e+10 | N96: 2.945488e+10 | O96: 2.8838019e+10 | P96: 2.1561527e+10 | Q96: 2.3776161e+10
E97: Resultados de Exercício Futuro | F97: 4.2537034e+08 | G97: 4.5920822e+08 | H97: 4.4626248e+08 | I97: 4.2937326e+08 | J97: 4.4823742e+08 | K97: 92496597 | L97: 2.0399033e+08 | M97: 1.9217409e+08 | N97: 0 | O97: - | P97: - | Q97: 0
E98: Patrimônio Líquido | F98: =SUM(F99:F104,F106:F108) -> 8.0613194e+10 | G98: =SUM(G99:G104,G106:G108) -> 8.1536173e+10 | H98: =SUM(H99:H104,H106:H108) -> 8.7193752e+10 | I98: =SUM(I99:I104,I106:I108) -> 9.8723401e+10 | J98: =SUM(J99:J104,J106:J108) -> 102252882000 | K98: =SUM(K99:K104,K106:K108) -> 108564894000 | L98: =SUM(L99:L104,L106:L108) -> 1.2697111e+11 | M98: =SUM(M99:M104,M106:M108) -> 1.4485719e+11 | ... Q98: =SUM(Q99:Q104,Q106:Q108) -> 1.7051085e+11
E99: Capital | F99: 54000000000 | G99: 60000000000 | H99: 67000000000 | I99: 6.6999999e+10 | J99: 67000000000 | K99: 67000000000 | L99: 9.0000023e+10 | M99: 9.0000023e+10 | N99: 9.0000023e+10 | O99: 9.0000023e+10 | P99: 1.19e+11 | Q99: 119000000000
E100: Instrumento Elegível ao Capital Principal | F100: 8.0999998e+09 | G100: 8.0999998e+09 | H100: 8.0999998e+09 | I100: 8.0999998e+09 | J100: 8100000000 | K100: 8100000000 | L100: 8100000000 | M100: 8100000000 | N100: 7.0999998e+09 | O100: 7.0999998e+09 | P100: 8100000000 | Q100: 7.0999998e+09
E101: Reservas de Capital | F101: 10773000 | G101: 14326000 | H101: 15509000 | I101: 12436000 | J101: 14692000 | K101: 1366443000 | L101: 1.3991514e+09 | M101: 1.4011765e+09 | N101: 1.4042524e+09 | O101: 1.4079026e+09 | P101: 1.4079026e+09 | Q101: 1.4079026e+09
E102: Reservas de Reavaliação | F102: 2805000 | G102: 2730000 | H102: 2660000 | I102: 2371000 | J102: 2240000 | K102: 2169000 | L102: 2040097.6 | M102: 0 | N102: 0 | O102: 0 | P102: 0 | Q102: 0
E103: Reservas de Lucros | F103: 26625511000 | G103: 29031090000 | H103: 27646569000 | I103: 35280691000 | J103: 42612582000 | K103: 53814656000 | L103: 3.9198468e+10 | M103: 5.118029e+10 | N103: 7.0142173e+10 | O103: 6.6919e+10 | P103: 5.0541777e+10 | Q103: 4.7338677e+10
E104: Ajustes de Avaliação Patrimonial | F104: -9597840000 | G104: -17042671000 | H104: -16929205000 | I104: -13219725000 | J104: -16154116000 | K104: -23282394000 | L104: -1.3851389e+10 | M104: -8.4095593e+09 | N104: -8.0951977e+09 | O104: -8.2709601e+09 | P104: -1.48534e+10 | Q104: -1.6755163e+10
E105: Planos de Benefícios | F105: -8.6800913e+09 | G105: -1.3918187e+10 | H105: -1.5492245e+10 | I105: -1.2442883e+10 | J105: -1.4085713e+10 | K105: -2.2162505e+10 | L105: -1.3765159e+10 | M105: -4.6990715e+09 | N105: -1.846077e+09 | O105: -1.846077e+09 | P105: -8.0742356e+09 | Q105: -8.0742356e+09
...

Sheet Projeções - Receitas
O4: =Dashboard!$I$4 -> Banco do Brasil ($BBAS3)
A7: Páginas
A8: Dashboard
A9: Ke | E9: Ano | F9: 2014 | G9: 2015 | H9: 2016 | I9: 2017 | J9: 2018 | K9: 2019 | L9: 2020 | M9: 2021 | N9: 2022 | O9: 1T23 | P9: 2T23 | Q9: 3T23 | R9: 4T23 | S9: YTG23 | T9: 2023 | U9: 2024 | V9: 2025 | W9: 2026 | X9: 2027 | Y9: 2028 | Z9: 2029 | AA9: 2030 | AB9: 2031 | AC9: 2032 | AD9: 2033
A10: DRE + DCF | E10: Selic Acumulada | F10: 0.109 | G10: 0.1273 | H10: 0.1402 | I10: 0.0994 | J10: 0.0643 | K10: 0.0596 | L10: 0.0276 | M10: 0.0442 | N10: 0.1233 | O10: =(1+1.12%)*(1+0.92%)*(1+1.17%)-1 -> 0.032442926 | P10: =(1+0.92%)*(1+1.12%)*(1+1.07%)-1 -> 0.031422423 | Q10: =(1+1.07%)*(1+1.14%)*(1+0.97%)-1 -> 0.032137533 | R10: {=(1+Ke!F10)/(PRODUCT(1+O10:Q10)) - 1} -> 0.019081341 | S10: =R10 -> 0.019081341 | T10: {=PRODUCT(1+O10:R10)-1} -> 0.12008 | U10: =Ke!G10 -> 0.1082 | V10: =Ke!H10 -> 0.1062 | W10: =Ke!I10 -> 0.10765 | X10: =Ke!J10 -> 0.10959 | Y10: =Ke!K10 -> 0.1113 | Z10: =Ke!L10 -> 0.11248 | AA10: =Ke!M10 -> 0.1132 | AB10: =Ke!N10 -> 0.11362 | ... AD10: =Ke!P10 -> 0.1139
A11: Contas Abertas | E11: Inflação | F11: 0.0641 | G11: 0.1067 | H11: 0.0629 | I11: 0.0295 | J11: 0.0375 | K11: 0.0431 | L11: 0.0452 | M11: 0.1006 | N11: 0.0579 | O11: =(1+0.53%)*(1+0.84%)*(1+0.71%)-1 -> 0.020942106 | P11: =(1+0.61%)*(1+0.23%)*(1-0.08%)-1 -> 0.0076072988 | Q11: =(1+0.12%)*(1+0.23%)*(1+0.26%)-1 -> 0.0061118672 | R11: {=(1+Ke!F12)/(PRODUCT(1+O11:Q11)) - 1} -> 0.006573891 | S11: =R11 -> 0.006573891 | T11: {=PRODUCT(1+O11:R11)-1} -> 0.0418 | U11: =Ke!G12 -> 0.04217 | V11: =Ke!H12 -> 0.04334 | W11: =Ke!I12 -> 0.04552 | X11: =Ke!J12 -> 0.04854 | Y11: =Ke!K12 -> 0.05087 | Z11: =Ke!L12 -> 0.05238 | AA11: =Ke!M12 -> 0.0543 | AB11: =Ke!N12 -> 0.05521 | ... AD11: =Ke!P12 -> 0.05584
A12: Balanço Patrimonial
A13: Projeções - Receita
A14: Painel de Índices
A15: Projeções Trimestrais | E15: Ano | F15: 2014 | G15: 2015 | H15: 2016 | I15: 2017 | J15: 2018 | K15: 2019 | L15: 2020 | M15: 2021 | N15: 2022 | O15: 1T23 | P15: 2T23 | Q15: 3T23 | R15: 4T23 | S15: YTG23 | T15: 2023 | U15: 2024 | V15: 2025 | W15: 2026 | X15: 2027 | Y15: 2028 | Z15: 2029 | AA15: 2030 | AB15: 2031 | AC15: 2032 | AD15: 2033 | AE15: CAFR 2014-2022 | AF15: Premissas
E16: Receita Líquida de Juros | F16: =F18+F20 -> 4.4467314e+10 | G16: =G18+G20 -> 5.0508895e+10 | H16: =H18+H20 -> 5.4668074e+10 | I16: =I18+I20 -> 5.0990431e+10 | J16: =J18+J20 -> 4.7930619e+10 | K16: =K18+K20 -> 5.3159907e+10 | L16: =L18+L20 -> 5.6019459e+10 | M16: =M18+M20 -> 5.8356231e+10 | ... R16: =R18+R20 -> 2.2513093e+10 | S16: =R16 -> 2.2513093e+10 | T16: =T18+T20 -> 8.9073521e+10 | U16: =U18+U20 -> 8.4659474e+10 | V16: =V18+V20 -> 9.4839162e+10 | W16: =W18+W20 -> 1.0620317e+11 | X16: =X18+X20 -> 1.1892255e+11 | Y16: =Y18+Y20 -> 1.3316857e+11 | Z16: =Z18+Z20 -> 1.4912972e+11 | AA16: =AA18+AA20 -> 1.6611754e+11 | ... AD16: =AD18+AD20 -> 2.2107323e+11 | AE16: =(N16/F16)^(1/8)-1 -> 0.062243586
E17: Margem Liquida de Juros | F17: =F16/F34 -> 0.04067599 | G17: =G16/G34 -> 0.042275969 | H17: =H16/H34 -> 0.043756133 | I17: =I16/I34 -> 0.040795296 | J17: =J16/J34 -> 0.037452734 | K17: =K16/K34 -> 0.039723683 | L17: =L16/L34 -> 0.037908353 | M17: =M16/M34 -> 0.035064123 | ... AD17: =AD16/AD34 -> 0.038805494
E18: Receita de Juros | F18: =F71 -> 1.2607778e+11 | G18: =G71 -> 1.5568947e+11 | H18: =H71 -> 1.7064309e+11 | I18: =I71 -> 1.4371103e+11 | J18: =J71 -> 1.1764526e+11 | K18: =K71 -> 1.1987773e+11 | L18: =L71 -> 9.672983e+10 | M18: =M71 -> 1.2093687e+11 | ... R18: =R71 -> 6.9063125e+10 | S18: =R18 -> 6.9063125e+10 | T18: =T71 -> 2.7028363e+11 | U18: =U71 -> 2.5253057e+11 | V18: =V71 -> 2.7991913e+11 | W18: =W71 -> 3.1587649e+11 | X18: =X71 -> 3.5732869e+11 | Y18: =Y71 -> 4.037098e+11 | Z18: =Z71 -> 4.5486129e+11 | AA18: =AA71 -> 5.0855504e+11 | ... AD18: =AD71 -> 6.79229e+11 | AE18: =(N18/F18)^(1/8)-1 -> 0.078693407
E19: Rentabilidade Média dos Ativos | F19: =F71/F34 -> 0.11532827 | G19: =G71/G34 -> 0.13031216 | H19: =H71/H34 -> 0.13658212 | I19: =I71/I34 -> 0.11497714 | J19: =J71/J34 -> 0.091927387 | K19: =K71/K34 -> 0.089578505 | L19: =L71/L34 -> 0.06545705 | M19: =M71/M34 -> 0.072666539 | ... AD19: =AD71/AD34 -> 0.11922663
E20: Despesas de Juros | F20: =F77 -> -8.1610463e+10 | G20: =G77 -> -1.0518057e+11 | H20: =H77 -> -1.1597501e+11 | I20: =I77 -> -9.2720601e+10 | J20: =J77 -> -6.9714638e+10 | K20: =K77 -> -6.6717824e+10 | L20: =L77 -> -4.0710371e+10 | M20: =M77 -> -6.2580641e+10 | ... R20: =R77 -> -4.6550032e+10 | S20: =R20 -> -4.6550032e+10 | T20: =T77 -> -1.812101e+11 | U20: =U77 -> -1.678711e+11 | V20: =V77 -> -1.8507997e+11 | W20: =W77 -> -2.0967332e+11 | X20: =X77 -> -2.3840614e+11 | Y20: =Y77 -> -2.7054123e+11 | Z20: =Z77 -> -3.0573157e+11 | AA20: =AA77 -> -3.424375e+11 | ... AD20: =AD77 -> -4.5815577e+11 | AE20: =(N20/F20)^(1/8)-1 -> 0.086966849
E21: Custo Médio dos Passivos | F21: =F77/F44 -> -0.080419697 | G21: =G77/G44 -> -0.093740384 | H21: =H77/H44 -> -0.1012528 | I21: =I77/I44 -> -0.080631113 | J21: =J77/J44 -> -0.059428443 | K21: =K77/K44 -> -0.055232035 | L21: =L77/L44 -> -0.031114772 | M21: =M77/M44 -> -0.043042644 | ... AD21: =AD77/AD44 -> -0.091849946
E22: Margem Financeira Bruta | F22: ='DRE CMN 4.720 - Contas Abertas'!F34 -> 4.2425199e+10 | G22: ='DRE CMN 4.720 - Contas Abertas'!G34 -> 4.9015801e+10 | H22: ='DRE CMN 4.720 - Contas Abertas'!H34 -> 5.4984054e+10 | I22: ='DRE CMN 4.720 - Contas Abertas'!I34 -> 5.2882427e+10 | J22: ='DRE CMN 4.720 - Contas Abertas'!J34 -> 5.0144549e+10 | K22: ='DRE CMN 4.720 - Contas Abertas'!K34 -> 5.3946797e+10 | L22: ='DRE CMN 4.720 - Contas Abertas'!L34 -> 5.6539099e+10 | M22: ='DRE CMN 4.720 - Contas Abertas'!M34 -> 5.9305219e+10 | ... Q22: ='DRE CMN 4.720 - Contas Abertas'!Q34 -> 2.3679773e+10 | R22: =R23*R16 -> 2.2513093e+10 | S22: =R22 -> 2.2513093e+10 | T22: =SUM(O22:R22) -> 9.0241115e+10 | U22: =U23*U16 -> 8.4659474e+10 | V22: =V23*V16 -> 9.4839162e+10 | W22: =W23*W16 -> 1.0620317e+11 | X22: =X23*X16 -> 1.1892255e+11 | Y22: =Y23*Y16 -> 1.3316857e+11 | Z22: =Z23*Z16 -> 1.4912972e+11 | AA22: =AA23*AA16 -> 1.6611754e+11 | AB22: =AB23*AB16 -> 1.8205653e+11 | ... AD22: =AD23*AD16 -> 2.2107323e+11 | AE22: =(N22/F22)^(1/8)-1 -> 0.070919311
E23: Margem Financeira Bruta como % da Receita Líquida de Juros | F23: =F22/F16 -> 0.95407603 | G23: =G22/G16 -> 0.97043899 | H23: =H22/H16 -> 1.00578 | I23: =I22/I16 -> 1.0371049 | J23: =J22/J16 -> 1.0461903 | K23: =K22/K16 -> 1.0148023 | L23: =L22/L16 -> 1.0092761 | M23: =M22/M16 -> 1.016262 | ... P23: =P22/P16 -> 0.99733912 | Q23: 1 | R23: 1 | S23: =S22/S16 -> 1 | T23: =T22/T16 -> 1.0131082 | U23: 1 | V23: =U23 -> 1 | W23: =V23 -> 1 | X23: =W23 -> 1 | Y23: =X23 -> 1 | Z23: =Y23 -> 1 | AA23: =Z23 -> 1 | AB23: =AA23 -> 1 | AC23: =AB23 -> 1 | AD23: =AC23 -> 1 | AF23: Média da Margem Financeira Bruta como % da Receita Líquida de Juros
E24: Provisão de Crédito para Liquidação Duvidosa (PCLD) | F24: ='DRE CMN 4.720 - Contas Abertas'!F36 -> -1.4471849e+10 | G24: ='DRE CMN 4.720 - Contas Abertas'!G36 -> -2.1045428e+10 | H24: ='DRE CMN 4.720 - Contas Abertas'!H36 -> -2.8508133e+10 | I24: ='DRE CMN 4.720 - Contas Abertas'!I36 -> -2.1711215e+10 | J24: ='DRE CMN 4.720 - Contas Abertas'!J36 -> -1.5579956e+10 | K24: ='DRE CMN 4.720 - Contas Abertas'!K36 -> -1.4931232e+10 | L24: ='DRE CMN 4.720 - Contas Abertas'!L36 -> -2.1922968e+10 | M24: ='DRE CMN 4.720 - Contas Abertas'!M36 -> -1.3107746e+10 | ... Q24: ='DRE CMN 4.720 - Contas Abertas'!Q36 -> -7.5163832e+09 | R24: =T24-SUM(O24:Q24) -> -6.4524536e+09 | S24: =R24 -> -6.4524536e+09 | T24: -27000000000 | U24: =U25*U38 -> -3.0926176e+10 | V24: =V25*V38 -> -3.5405835e+10 | W24: =W25*W38 -> -4.0515274e+10 | X24: =X25*X38 -> -4.6341135e+10 | Y24: =Y25*Y38 -> -5.2981783e+10 | Z24: =Z25*Z38 -> -6.0548874e+10 | AA24: =AA25*AA38 -> -6.879858e+10 | AB24: =AB25*AB38 -> -7.6879703e+10 | ... AD24: =AD25*AD38 -> -7.4725452e+10 | AE24: =(N24/F24)^(1/8)-1 -> 0.018417321 | AF24: Crescimento igual ao crescimento dos Ativos Rentáveis
E25: PCLD como % das Operações de Crédito + Leasing | F25: =F24/F38 -> -0.023366546 | G25: =G24/G38 -> -0.031086262 | H25: =H24/H38 -> -0.041597728 | I25: =I24/I38 -> -0.034231719 | J25: =J24/J38 -> -0.024823638 | K25: =K24/K38 -> -0.024083573 | L25: =L24/L38 -> -0.033446891 | M25: =M24/M38 -> -0.018272454 | ... T25: =T24/T38 -> -0.02954582 | U25: =T25+(($AD$25-$N$25)/11) -> -0.030216244 | V25: =U25+(($AD$25-$N$25)/11) -> -0.030886669 | W25: =V25+(($AD$25-$N$25)/11) -> -0.031557093 | X25: =W25+(($AD$25-$N$25)/11) -> -0.032227518 | Y25: =X25+(($AD$25-$N$25)/11) -> -0.032897942 | Z25: =Y25+(($AD$25-$N$25)/11) -> -0.033568367 | AA25: =Z25+(($AD$25-$N$25)/11) -> -0.034238791 | AB25: =AA25+(($AD$25-$N$25)/11) -> -0.034909216 | AC25: =AB25+(($AD$25-$N$25)/11) -> -0.03557964 | AD25: =AVERAGE($F$25:$N$25) -> -0.027941767 | AF25: Crescimento linear até atingir a média desde 2014. Simula um cenário de deteriorização da qualidade do crédito
E26: Margem Financeira Líquida | F26: =F22+F24 -> 2.7953349e+10 | G26: =G22+G24 -> 2.7970373e+10 | H26: =H22+H24 -> 2.647592e+10 | I26: =I22+I24 -> 3.1171212e+10 | J26: =J22+J24 -> 3.4564593e+10 | K26: =K22+K24 -> 3.9015565e+10 | L26: =L22+L24 -> 3.4616132e+10 | M26: =M22+M24 -> 4.6197474e+10 | ... AD26: =AD22+AD24 -> 1.4634777e+11 | AE26: =(N26/F26)^(1/8)-1 -> 0.092310074
E27: Margem Financeira Líquida como % da Margem Financeira Bruta | F27: =F26/F22 -> 0.65888553 | G27: =G26/G22 -> 0.57063992 | H27: =H26/H22 -> 0.48151998 | I27: =I26/I22 -> 0.58944367 | J27: =J26/J22 -> 0.68929911 | K27: =K26/K22 -> 0.72322301 | L27: =L26/L22 -> 0.61225121 | M27: =M26/M22 -> 0.77897821 | ... AD27: =AD26/AD22 -> 0.66198778
E28: Spread Global | F28: =F22/F34 -> 0.038807987 | G28: =G22/G34 -> 0.041026249 | H28: =H22/H34 -> 0.044009042 | I28: =I22/I34 -> 0.042309003 | J28: =J22/J34 -> 0.039182688 | K28: =K22/K34 -> 0.040311686 | L28: =L22/L34 -> 0.038259994 | M28: =M22/M34 -> 0.035634335 | ... AD28: =AD22/AD34 -> 0.038805494
E33: Ano | F33: 2014 | G33: 2015 | H33: 2016 | I33: 2017 | J33: 2018 | K33: 2019 | L33: 2020 | M33: 2021 | N33: 2022 | O33: 1T23 | P33: 2T23 | Q33: 3T23 | R33: 4T23 | S33: YTG23 | T33: 2023 | U33: 2024 | V33: 2025 | W33: 2026 | X33: 2027 | Y33: 2028 | Z33: 2029 | AA33: 2030 | AB33: 2031 | AC33: 2032 | AD33: 2033 | AE33: CAGR 2014-2022 | AF33: Premissas
E34: Ativos Rentáveis | F34: =SUM(F36,F38,F40,F42) -> 1.0932079e+12 | G34: =SUM(G36,G38,G40,G42) -> 1.1947425e+12 | H34: =SUM(H36,H38,H40,H42) -> 1.2493808e+12 | I34: =SUM(I36,I38,I40,I42) -> 1.2499096e+12 | J34: =SUM(J36,J38,J40,J42) -> 1.2797629e+12 | K34: =SUM(K36,K38,K40,K42) -> 1.3382422e+12 | L34: =SUM(L36,L38,L40,L42) -> 1.4777603e+12 | M34: =SUM(M36,M38,M40,M42) -> 1.6642718e+12 | ... Q34: =SUM(Q36,Q38,Q40,Q42) -> 1.9663236e+12 | R34: ='Projeções Trimestrais'!I21 -> 1.9466863e+12 | S34: =R34 -> 1.9466863e+12 | T34: =S34 -> 1.9466863e+12 | U34: =T34*(1+U35) -> 2.1802887e+12 | V34: =U34*(1+V35) -> 2.4419234e+12 | W34: =V34*(1+W35) -> 2.7349542e+12 | X34: =W34*(1+X35) -> 3.0631487e+12 | Y34: =X34*(1+Y35) -> 3.4307265e+12 | Z34: =Y34*(1+Z35) -> 3.8424137e+12 | AA34: =Z34*(1+AA35) -> 4.2804488e+12 | AB34: =AA34*(1+AB35) -> 4.6913719e+12 | ... AD34: =AC34*(1+AD35) -> 5.6969569e+12
E35: Crescimento dos Ativos Rentáveis | F35: 0 | G35: =G34/F34-1 -> 0.092877604 | H35: =H34/G34-1 -> 0.045732342 | I35: =I34/H34-1 -> 0.00042319847 | J35: =J34/I34-1 -> 0.023884366 | K35: =K34/J34-1 -> 0.045695406 | L35: =L34/K34-1 -> 0.10425478 | M35: =M34/L34-1 -> 0.12621228 | N35: =N34/M34-1 -> 0.10750079 | ... R35: =R34/Q34-1 -> -0.0099867907 | S35: =S34/O34-1 -> 0.041662315 | T35: =T34/N34-1 -> 0.056155067 | U35: =VLOOKUP(MIN('G Ativos Rentáveis'!E11:E251),'G Ativos Rentáveis'!E11:P251,12,FALSE) -> 0.12 | V35: =VLOOKUP(MIN('G Ativos Rentáveis'!F11:F251),'G Ativos Rentáveis'!F11:Q251,12,FALSE) -> 0.12 | W35: =VLOOKUP(MIN('G Ativos Rentáveis'!G11:G251),'G Ativos Rentáveis'!G11:R251,12,FALSE) -> 0.12 | X35: =VLOOKUP(MIN('G Ativos Rentáveis'!H11:H251),'G Ativos Rentáveis'!H11:S251,12,FALSE) -> 0.12 | Y35: =VLOOKUP(MIN('G Ativos Rentáveis'!I11:I251),'G Ativos Rentáveis'!I11:T251,12,FALSE) -> 0.12 | Z35: =VLOOKUP(MIN('G Ativos Rentáveis'!J11:J251),'G Ativos Rentáveis'!J11:U251,12,FALSE) -> 0.12 | AA35: =VLOOKUP(MIN('G Ativos Rentáveis'!K11:K251),'G Ativos Rentáveis'!K11:V251,12,FALSE) -> 0.114 | AB35: =VLOOKUP(MIN('G Ativos Rentáveis'!L11:L251),'G Ativos Rentáveis'!L11:W251,12,FALSE) -> 0.096 | ... AD35: =VLOOKUP(MIN('G Ativos Rentáveis'!N11:N251),'G Ativos Rentáveis'!N11:Y251,12,FALSE) -> 0.1095 | AE35: =(N34/F34)^(1/8)-1 -> 0.067476174
E36: Títs. e Vlrs. Mobiliários + Aplic. Interfinanceiras s/Hedge | F36: 4.0131769e+11 | G36: 4.5885411e+11 | H36: 5.0278132e+11 | I36: 5.5390949e+11 | J36: 5.9030889e+11 | K36: 6.6007087e+11 | L36: 7.6385266e+11 | M36: 8.8280082e+11 | N36: 9.4786936e+11 | O36: 8.918161e+11 | P36: 8.9778862e+11 | Q36: 9.468731e+11 | R36: =R37*R$34 -> 9.3741688e+11 | S36: =S37*S$34 -> 9.3741688e+11 | T36: =T37*T$34 -> 9.3741688e+11 | U36: =U37*U$34 -> 1.0499069e+12 | V36: =V37*V$34 -> 1.1758957e+12 | W36: =W37*W$34 -> 1.3170032e+12 | X36: =X37*X$34 -> 1.4750436e+12 | Y36: =Y37*Y$34 -> 1.6520488e+12 | ... AD36: =AD37*AD$34 -> 2.7433406e+12 | AE36: =(N36/F36)^(1/8)-1 -> 0.11341616
E37: % dos Ativos Rentáveis | F37: =F36/F$34 -> 0.36710097 | G37: =G36/G$34 -> 0.3840611 | H37: =H36/H$34 -> 0.40242439 | I37: =I36/I$34 -> 0.44315965 | J37: =J36/J$34 -> 0.46126428 | K37: =K36/K$34 -> 0.49323725 | L37: =L36/L$34 -> 0.51689889 | M37: =M36/M$34 -> 0.5304427 | ... Q37: =Q36/Q$34 -> 0.4815449 | R37: =Q37 -> 0.4815449 | S37: =R37 -> 0.4815449 | T37: =S37 -> 0.4815449 | U37: =T37 -> 0.4815449 | V37: =U37 -> 0.4815449 | W37: =V37 -> 0.4815449 | X37: =W37 -> 0.4815449 | Y37: =X37 -> 0.4815449 | ... AD37: =AC37 -> 0.4815449 | AF37: Percentual constante dos Ativos Rentáveis
E38: Operações de Crédito + Leasing | F38: 6.1934054e+11 | G38: 6.7700093e+11 | H38: 6.853291e+11 | I38: 6.3424263e+11 | J38: 6.2762582e+11 | K38: 6.1997579e+11 | L38: 6.5545607e+11 | M38: 7.1735005e+11 | N38: 8.1424901e+11 | O38: 8.8763943e+11 | P38: 9.0085397e+11 | Q38: 9.230532e+11 | R38: =R39*R$34 -> 9.1383486e+11 | S38: =S39*S$34 -> 9.1383486e+11 | T38: =T39*T$34 -> 9.1383486e+11 | U38: =U39*U$34 -> 1.023495e+12 | V38: =V39*V$34 -> 1.1463144e+12 | W38: =W39*W$34 -> 1.2838722e+12 | X38: =X39*X$34 -> 1.4379368e+12 | Y38: =Y39*Y$34 -> 1.6104893e+12 | ... AD38: =AD39*AD$34 -> 2.674328e+12 | AE38: =(N38/F38)^(1/8)-1 -> 0.034792962
E39: % dos Ativos Rentáveis | F39: =F38/F$34 -> 0.56653499 | G39: =G38/G$34 -> 0.56665009 | H39: =H38/H$34 -> 0.54853499 | I39: =I38/I$34 -> 0.50743081 | J39: =J38/J$34 -> 0.49042352 | K39: =K38/K$34 -> 0.46327624 | L39: =L38/L$34 -> 0.44354695 | M39: =M38/M$34 -> 0.43102938 | ... Q39: =Q38/Q$34 -> 0.46943097 | R39: =Q39 -> 0.46943097 | S39: =R39 -> 0.46943097 | T39: =S39 -> 0.46943097 | U39: =T39 -> 0.46943097 | V39: =U39 -> 0.46943097 | W39: =V39 -> 0.46943097 | X39: =W39 -> 0.46943097 | Y39: =X39 -> 0.46943097 | ... AD39: =AC39 -> 0.46943097 | AF39: Percentual constante dos Ativos Rentáveis
E40: Depósito Compulsório Rentável | F40: 6.7694103e+10 | G40: 4.8959301e+10 | H40: 5.3285564e+10 | I40: 5.3911175e+10 | J40: 5.3867868e+10 | K40: 4.9548251e+10 | L40: 4.8740432e+10 | M40: 5.2004126e+10 | N40: 6.9827717e+10 | O40: 7.489295e+10 | P40: 7.7736176e+10 | Q40: 8.1829801e+10 | R40: =R41*R$34 -> 8.1012584e+10 | S40: =S41*S$34 -> 8.1012584e+10 | T40: =T41*T$34 -> 8.1012584e+10 | U40: =U41*U$34 -> 9.0734094e+10 | V40: =V41*V$34 -> 1.0162218e+11 | W40: =W41*W$34 -> 1.1381685e+11 | X40: =X41*X$34 -> 1.2747487e+11 | Y40: =Y41*Y$34 -> 1.4277185e+11 | ... AD40: =AD41*AD$34 -> 2.3708247e+11 | AE40: =(N40/F40)^(1/8)-1 -> 0.003886527
E41: % dos Ativos Rentáveis | F41: =F40/F$34 -> 0.06192244 | G41: =G40/G$34 -> 0.040978958 | H41: =H40/H$34 -> 0.042649577 | I41: =I40/I$34 -> 0.043132061 | J41: =J40/J$34 -> 0.04209207 | K41: =K40/K$34 -> 0.037024877 | L41: =L40/L$34 -> 0.032982638 | M41: =M40/M$34 -> 0.031247376 | ... Q41: =Q40/Q$34 -> 0.041615633 | R41: =Q41 -> 0.041615633 | S41: =R41 -> 0.041615633 | T41: =S41 -> 0.041615633 | U41: =T41 -> 0.041615633 | V41: =U41 -> 0.041615633 | W41: =V41 -> 0.041615633 | X41: =W41 -> 0.041615633 | Y41: =X41 -> 0.041615633 | ... AD41: =AC41 -> 0.041615633 | AF41: Percentual constante dos Ativos Rentáveis
E42: Demais Ativos Rentáveis | F42: 4.8555943e+09 | G42: 9.9281244e+09 | H42: 7.9848483e+09 | I42: 7.8462747e+09 | J42: 7.9602908e+09 | K42: 8.6472361e+09 | L42: 9.7111324e+09 | M42: 1.21168e+10 | N42: 1.1236239e+10 | O42: 1.447822e+10 | P42: 1.4339477e+10 | Q42: 1.4567506e+10 | R42: =R43*R$34 -> 1.4422023e+10 | S42: =S43*S$34 -> 1.4422023e+10 | T42: =T43*T$34 -> 1.4422023e+10 | U42: =U43*U$34 -> 1.6152666e+10 | V42: =V43*V$34 -> 1.8090985e+10 | W42: =W43*W$34 -> 2.0261904e+10 | X42: =X43*X$34 -> 2.2693332e+10 | Y42: =Y43*Y$34 -> 2.5416532e+10 | ... AD42: =AD43*AD$34 -> 4.2205897e+10 | AE42: =(N42/F42)^(1/8)-1 -> 0.11057354
E43: % dos Ativos Rentáveis | F43: =F42/F$34 -> 0.0044416018 | G43: =G42/G$34 -> 0.0083098448 | H43: =H42/H$34 -> 0.0063910443 | I43: =I42/I$34 -> 0.0062774739 | J43: =J42/J$34 -> 0.0062201295 | K43: =K42/K$34 -> 0.0064616378 | L43: =L42/L$34 -> 0.0065715207 | M43: =M42/M$34 -> 0.0072805414 | ... Q43: =Q42/Q$34 -> 0.0074084985 | R43: =Q43 -> 0.0074084985 | S43: =R43 -> 0.0074084985 | T43: =S43 -> 0.0074084985 | U43: =T43 -> 0.0074084985 | V43: =U43 -> 0.0074084985 | W43: =V43 -> 0.0074084985 | X43: =W43 -> 0.0074084985 | Y43: =X43 -> 0.0074084985 | ... AD43: =AC43 -> 0.0074084985 | AF43: Percentual constante dos Ativos Rentáveis
E44: Passivos Onerosos | F44: =SUM(F46,F48,F50,F52,F54,F56,F58,F60,F62,F64) -> 1.0148069e+12 | G44: =SUM(G46,G48,G50,G52,G54,G56,G58,G60,G62,G64) -> 1.1220412e+12 | H44: =SUM(H46,H48,H50,H52,H54,H56,H58,H60,H62,H64) -> 1.1454006e+12 | I44: =SUM(I46,I48,I50,I52,I54,I56,I58,I60,I62,I64) -> 1.1499358e+12 | J44: =SUM(J46,J48,J50,J52,J54,J56,J58,J60,J62,J64) -> 1.1730854e+12 | K44: =SUM(K46,K48,K50,K52,K54,K56,K58,K60,K62,K64) -> 1.2079552e+12 | L44: =SUM(L46,L48,L50,L52,L54,L56,L58,L60,L62,L64) -> 1.3083937e+12 | M44: =SUM(M46,M48,M50,M52,M54,M56,M58,M60,M62,M64) -> 1.4539219e+12 | ... Q44: =SUM(Q46,Q48,Q50,Q52,Q54,Q56,Q58,Q60,Q62,Q64) -> 1.7148175e+12 | R44: 1.7044619e+12 | S44: =R44 -> 1.7044619e+12 | T44: =S44 -> 1.7044619e+12 | U44: =U66*U34 -> 1.9089973e+12 | V44: =V66*V34 -> 2.138077e+12 | W44: =W66*W34 -> 2.3946463e+12 | X44: =X66*X34 -> 2.6820038e+12 | Y44: =Y66*Y34 -> 3.0038443e+12 | Z44: =Z66*Z34 -> 3.3643056e+12 | AA44: =AA66*AA34 -> 3.7478364e+12 | AB44: =AB66*AB34 -> 4.1076287e+12 | ... AD44: =AD66*AD34 -> 4.9880897e+12 | AF44: Crescimento de acordo com a equação linear entre a regressão do crescimento dos Passivos Onerosos com o IPCA projetado.
E45: Crescimento dos Passivos Rentáveis | F45: 0 | G45: =G44/F44-1 -> 0.10566966 | H45: =H44/G44-1 -> 0.020818641 | I45: =I44/H44-1 -> 0.0039595015 | J45: =J44/I44-1 -> 0.02013122 | K45: =K44/J44-1 -> 0.029724865 | L45: =L44/K44-1 -> 0.083147545 | M45: =M44/L44-1 -> 0.11122659 | N45: =N44/M44-1 -> 0.10662158 | ... R45: =R44/Q44-1 -> -0.0060388866 | S45: =S44/O44-1 -> 0.041103062 | T45: =T44/N44-1 -> 0.059368599 | U45: =U44/T44-1 -> 0.12 | V45: =V44/U44-1 -> 0.12 | W45: =W44/V44-1 -> 0.12 | X45: =X44/W44-1 -> 0.12 | Y45: =Y44/X44-1 -> 0.12 | Z45: =Z44/Y44-1 -> 0.12 | AA45: =AA44/Z44-1 -> 0.114 | AB45: =AB44/AA44-1 -> 0.096 | ... AD45: =AD44/AC44-1 -> 0.1095 | AE45: =(N44/F44)^(1/8)-1 -> 0.05930153
E46: Depósitos de Poupança | F46: 1.4646403e+11 | G46: 1.4788648e+11 | H46: 1.4971005e+11 | I46: 1.5240295e+11 | J46: 1.6773025e+11 | K46: 1.7559403e+11 | L46: 1.9898395e+11 | M46: 2.2256894e+11 | N46: 2.1667923e+11 | O46: 2.0771297e+11 | P46: 2.0581958e+11 | Q46: 2.0631242e+11 | R46: =R47*R$44 -> 2.0506652e+11 | S46: =S47*S$44 -> 2.0506652e+11 | T46: =T47*T$44 -> 2.0506652e+11 | U46: =U47*U$44 -> 2.2967451e+11 | V46: =V47*V$44 -> 2.5723545e+11 | W46: =W47*W$44 -> 2.881037e+11 | X46: =X47*X$44 -> 3.2267615e+11 | Y46: =Y47*Y$44 -> 3.6139728e+11 | ... AD46: =AD47*AD$44 -> 6.0012501e+11 | AE46: =(N46/F46)^(1/8)-1 -> 0.05017285
E47: % dos Passivos Onerosos | F47: =F46/F$44 -> 0.144327 | G47: =G46/G$44 -> 0.1318013 | H47: =H46/H$44 -> 0.13070541 | I47: =I46/I$44 -> 0.13253171 | J47: =J46/J$44 -> 0.14298213 | K47: =K46/K$44 -> 0.14536469 | L47: =L46/L$44 -> 0.15208262 | M47: =M46/M$44 -> 0.15308178 | ... Q47: =Q46/Q$44 -> 0.12031159 | R47: =Q47 -> 0.12031159 | S47: =R47 -> 0.12031159 | T47: =S47 -> 0.12031159 | U47: =T47 -> 0.12031159 | V47: =U47 -> 0.12031159 | W47: =V47 -> 0.12031159 | X47: =W47 -> 0.12031159 | Y47: =X47 -> 0.12031159 | ... AD47: =AC47 -> 0.12031159 | AF47: Percentual constante dos Passivos Onerosos
E48: Depósitos Interfinanceiros | F48: 2.7207469e+10 | G48: 3.656844e+10 | H48: 2.9887806e+10 | I48: 1.9343964e+10 | J48: 3.1443421e+10 | K48: 3.2646892e+10 | L48: 2.9581525e+10 | M48: 2.6126828e+10 | N48: 2.4956742e+10 | O48: 2.392788e+10 | P48: 2.4995117e+10 | Q48: 2.5322074e+10 | R48: =R49*R$44 -> 2.5169157e+10 | S48: =S49*S$44 -> 2.5169157e+10 | T48: =T49*T$44 -> 2.5169157e+10 | U48: =U49*U$44 -> 2.8189456e+10 | V48: =V49*V$44 -> 3.1572191e+10 | W48: =W49*W$44 -> 3.5360854e+10 | X48: =X49*X$44 -> 3.9604156e+10 | Y48: =Y49*Y$44 -> 4.4356655e+10 | ... AD48: =AD49*AD$44 -> 7.3657272e+10 | AE48: =(N48/F48)^(1/8)-1 -> -0.0107354
E49: % dos Passivos Onerosos | F49: =F48/F$44 -> 0.026810489 | G49: =G48/G$44 -> 0.032590996 | H49: =H48/H$44 -> 0.026093759 | I49: =I48/I$44 -> 0.016821777 | J49: =J48/J$44 -> 0.026804035 | K49: =K48/K$44 -> 0.027026576 | L49: =L48/L$44 -> 0.02260904 | M49: =M48/M$44 -> 0.017969899 | ... Q49: =Q48/Q$44 -> 0.014766629 | R49: =Q49 -> 0.014766629 | S49: =R49 -> 0.014766629 | T49: =S49 -> 0.014766629 | U49: =T49 -> 0.014766629 | V49: =U49 -> 0.014766629 | W49: =V49 -> 0.014766629 | X49: =W49 -> 0.014766629 | Y49: =X49 -> 0.014766629 | ... AD49: =AC49 -> 0.014766629 | AF49: Percentual constante dos Passivos Onerosos
E50: Depósitos a Prazo | F50: 2.2824182e+11 | G50: 2.0511006e+11 | H50: 2.0282573e+11 | I50: 2.0147691e+11 | J50: 2.076279e+11 | K50: 2.2796272e+11 | L50: 2.6123723e+11 | M50: 3.0897114e+11 | N50: 3.8440384e+11 | O50: 4.3442595e+11 | P50: 4.5316415e+11 | Q50: 4.6126352e+11 | R50: =R51*R$44 -> 4.58478e+11 | S50: =S51*S$44 -> 4.58478e+11 | T50: =T51*T$44 -> 4.58478e+11 | U50: =U51*U$44 -> 5.1349536e+11 | V50: =V51*V$44 -> 5.751148e+11 | W50: =W51*W$44 -> 6.4412858e+11 | X50: =X51*X$44 -> 7.2142401e+11 | Y50: =Y51*Y$44 -> 8.0799489e+11 | ... AD50: =AD51*AD$44 -> 1.341731e+12 | AE50: =(N50/F50)^(1/8)-1 -> 0.067330849
E51: % dos Passivos Onerosos | F51: =F50/F$44 -> 0.22491158 | G51: =G50/G$44 -> 0.18280083 | H51: =H50/H$44 -> 0.17707843 | I51: =I50/I$44 -> 0.1752071 | J51: =J50/J$44 -> 0.176993 | K51: =K50/K$44 -> 0.18871786 | L51: =L50/L$44 -> 0.19966256 | M51: =M50/M$44 -> 0.21250877 | ... Q51: =Q50/Q$44 -> 0.26898694 | R51: =Q51 -> 0.26898694 | S51: =R51 -> 0.26898694 | T51: =S51 -> 0.26898694 | U51: =T51 -> 0.26898694 | V51: =U51 -> 0.26898694 | W51: =V51 -> 0.26898694 | X51: =W51 -> 0.26898694 | Y51: =X51 -> 0.26898694 | ... AD51: =AC51 -> 0.26898694 | AF51: Percentual constante dos Passivos Onerosos
E52: Captações no Mercado Aberto | F52: 2.8414858e+11 | G52: 3.277897e+11 | H52: 3.6863396e+11 | I52: 4.2100987e+11 | J52: 4.304584e+11 | K52: 4.6090792e+11 | L52: 5.1069786e+11 | M52: 6.038749e+11 | N52: 6.6976319e+11 | O52: 6.3532405e+11 | P52: 6.0646822e+11 | Q52: 6.4244093e+11 | R52: =R53*R$44 -> 6.3856131e+11 | S52: =S53*S$44 -> 6.3856131e+11 | T52: =T53*T$44 -> 6.3856131e+11 | U52: =U53*U$44 -> 7.1518866e+11 | V52: =V53*V$44 -> 8.010113e+11 | W52: =W53*W$44 -> 8.9713266e+11 | X52: =X53*X$44 -> 1.0047886e+12 | Y52: =Y53*Y$44 -> 1.1253632e+12 | ... AD52: =AD53*AD$44 -> 1.8687429e+12 | AE52: =(N52/F52)^(1/8)-1 -> 0.11313278
E53: % dos Passivos Onerosos | F53: =F52/F$44 -> 0.28000261 | G53: =G52/G$44 -> 0.29213695 | H53: =H52/H$44 -> 0.32183846 | I53: =I52/I$44 -> 0.36611598 | J53: =J52/J$44 -> 0.36694549 | K53: =K52/K$44 -> 0.38156044 | L53: =L52/L$44 -> 0.39032431 | M53: =M52/M$44 -> 0.41534206 | ... Q53: =Q52/Q$44 -> 0.37464099 | R53: =Q53 -> 0.37464099 | S53: =R53 -> 0.37464099 | T53: =S53 -> 0.37464099 | U53: =T53 -> 0.37464099 | V53: =U53 -> 0.37464099 | W53: =V53 -> 0.37464099 | X53: =W53 -> 0.37464099 | Y53: =X53 -> 0.37464099 | ... AD53: =AC53 -> 0.37464099 | AF53: Percentual constante dos Passivos Onerosos
E54: Obrigações por Empréstimos e Repasses no País | F54: 1.0620316e+11 | G54: 1.157593e+11 | H54: 1.1027276e+11 | I54: 1.0009223e+11 | J54: 9.5885777e+10 | K54: 8.1897435e+10 | L54: 7.5997612e+10 | M54: 6.9265208e+10 | N54: 6.5095156e+10 | O54: 6.2917615e+10 | P54: 6.313817e+10 | Q54: 6.2984529e+10 | R54: =R55*R$44 -> 6.2604172e+10 | S54: =S55*S$44 -> 6.2604172e+10 | T54: =T55*T$44 -> 6.2604172e+10 | U54: =U55*U$44 -> 7.0116673e+10 | V54: =V55*V$44 -> 7.8530674e+10 | W54: =W55*W$44 -> 8.7954355e+10 | X54: =X55*X$44 -> 9.8508877e+10 | Y54: =Y55*Y$44 -> 1.1032994e+11 | ... AD54: =AD55*AD$44 -> 1.8321045e+11 | AE54: =(N54/F54)^(1/8)-1 -> -0.059353581
E55: % dos Passivos Onerosos | F55: =F54/F$44 -> 0.10465356 | G55: =G54/G$44 -> 0.10316849 | H55: =H54/H$44 -> 0.096274409 | I55: =I54/I$44 -> 0.087041584 | J55: =J54/J$44 -> 0.081738105 | K55: =K54/K$44 -> 0.067798405 | L55: =L54/L$44 -> 0.058084667 | M55: =M54/M$44 -> 0.047640255 | ... Q55: =Q54/Q$44 -> 0.036729581 | R55: =Q55 -> 0.036729581 | S55: =R55 -> 0.036729581 | T55: =S55 -> 0.036729581 | U55: =T55 -> 0.036729581 | V55: =U55 -> 0.036729581 | W55: =V55 -> 0.036729581 | X55: =W55 -> 0.036729581 | Y55: =X55 -> 0.036729581 | ... AD55: =AC55 -> 0.036729581 | AF55: Percentual constante dos Passivos Onerosos
E56: Fundos Financeiros e de Desenv. | F56: 8.7824524e+09 | G56: 1.2994434e+10 | H56: 1.4567127e+10 | I56: 1.5287879e+10 | J56: 1.5714589e+10 | K56: 1.6022815e+10 | L56: 2.131147e+10 | M56: 2.6389051e+10 | N56: 3.2310661e+10 | O56: 3.8289206e+10 | P56: 3.9836321e+10 | Q56: 4.063823e+10 | R56: =R57*R$44 -> 4.0392821e+10 | S56: =S57*S$44 -> 4.0392821e+10 | T56: =T57*T$44 -> 4.0392821e+10 | U56: =U57*U$44 -> 4.5239959e+10 | V56: =V57*V$44 -> 5.0668754e+10 | W56: =W57*W$44 -> 5.6749005e+10 | X56: =X57*X$44 -> 6.3558885e+10 | Y56: =Y57*Y$44 -> 7.1185952e+10 | ... AD56: =AD57*AD$44 -> 1.1820916e+11 | AE56: =(N56/F56)^(1/8)-1 -> 0.17683684
E57: % dos Passivos Onerosos | F57: =F56/F$44 -> 0.0086543089 | G57: =G56/G$44 -> 0.011581067 | H57: =H56/H$44 -> 0.012717933 | I57: =I56/I$44 -> 0.01329455 | J57: =J56/J$44 -> 0.013395946 | K57: =K56/K$44 -> 0.013264412 | L57: =L56/L$44 -> 0.01628827 | M57: =M56/M$44 -> 0.018150254 | ... Q57: =Q56/Q$44 -> 0.023698283 | R57: =Q57 -> 0.023698283 | S57: =R57 -> 0.023698283 | T57: =S57 -> 0.023698283 | U57: =T57 -> 0.023698283 | V57: =U57 -> 0.023698283 | W57: =V57 -> 0.023698283 | X57: =W57 -> 0.023698283 | Y57: =X57 -> 0.023698283 | ... AD57: =AC57 -> 0.023698283 | AF57: Percentual constante dos Passivos Onerosos
E58: Dívida Subordinada | F58: 7.5700805e+10 | G58: 9.2102772e+10 | H58: 9.3219607e+10 | I58: 9.3409505e+10 | J58: 9.2401516e+10 | K58: 8.1144329e+10 | L58: 8.2900857e+10 | M58: 6.9677623e+10 | N58: 5.3839467e+10 | O58: 4.7650717e+10 | P58: 4.006214e+10 | Q58: 4.051873e+10 | R58: =R59*R$44 -> 4.0274042e+10 | S58: =S59*S$44 -> 4.0274042e+10 | T58: =T59*T$44 -> 4.0274042e+10 | U58: =U59*U$44 -> 4.5106927e+10 | V58: =V59*V$44 -> 5.0519758e+10 | W58: =W59*W$44 -> 5.6582129e+10 | X58: =X59*X$44 -> 6.3371984e+10 | Y58: =Y59*Y$44 -> 7.0976622e+10 | ... AD58: =AD59*AD$44 -> 1.1786156e+11 | AE58: =(N58/F58)^(1/8)-1 -> -0.041703214
E59: % dos Passivos Onerosos | F59: =F58/F$44 -> 0.074596266 | G59: =G58/G$44 -> 0.082085019 | H59: =H58/H$44 -> 0.081386032 | I59: =I58/I$44 -> 0.081230193 | J59: =J58/J$44 -> 0.078767937 | K59: =K58/K$44 -> 0.067174949 | L59: =L58/L$44 -> 0.063360789 | M59: =M58/M$44 -> 0.047923911 | ... Q59: =Q58/Q$44 -> 0.023628596 | R59: =Q59 -> 0.023628596 | S59: =R59 -> 0.023628596 | T59: =S59 -> 0.023628596 | U59: =T59 -> 0.023628596 | V59: =U59 -> 0.023628596 | W59: =V59 -> 0.023628596 | X59: =W59 -> 0.023628596 | Y59: =X59 -> 0.023628596 | ... AD59: =AC59 -> 0.023628596 | AF59: Percentual constante dos Passivos Onerosos
E60: Obrigações com T.V.M. no Exterior | F60: 3.0274893e+10 | G60: 3.5804835e+10 | H60: 2.2673441e+10 | I60: 2.250046e+10 | J60: 2.5452649e+10 | K60: 2.9146882e+10 | L60: 3.9669237e+10 | M60: 3.9862164e+10 | N60: 3.7727986e+10 | O60: 3.7342978e+10 | P60: 4.0562571e+10 | Q60: 4.0280042e+10 | R60: =R61*R$44 -> 4.0036795e+10 | S60: =S61*S$44 -> 4.0036795e+10 | T60: =T61*T$44 -> 4.0036795e+10 | U60: =U61*U$44 -> 4.484121e+10 | V60: =V61*V$44 -> 5.0222156e+10 | W60: =W61*W$44 -> 5.6248814e+10 | X60: =X61*X$44 -> 6.2998672e+10 | Y60: =Y61*Y$44 -> 7.0558513e+10 | ... AD60: =AD61*AD$44 -> 1.1716726e+11 | AE60: =(N60/F60)^(1/8)-1 -> 0.027892328
E61: % dos Passivos Onerosos | F61: =F60/F$44 -> 0.029833157 | G61: =G60/G$44 -> 0.031910446 | H61: =H60/H$44 -> 0.019795207 | I61: =I60/I$44 -> 0.01956671 | J61: =J60/J$44 -> 0.021697184 | K61: =K60/K$44 -> 0.024129109 | L61: =L60/L$44 -> 0.030319037 | M61: =M60/M$44 -> 0.027416992 | ... Q61: =Q60/Q$44 -> 0.023489404 | R61: =Q61 -> 0.023489404 | S61: =R61 -> 0.023489404 | T61: =S61 -> 0.023489404 | U61: =T61 -> 0.023489404 | V61: =U61 -> 0.023489404 | W61: =V61 -> 0.023489404 | X61: =W61 -> 0.023489404 | Y61: =X61 -> 0.023489404 | ... AD61: =AC61 -> 0.023489404 | AF61: Percentual constante dos Passivos Onerosos
E62: Letra de Crédito do Agronegócio | F62: 9.655942e+10 | G62: 1.2791068e+11 | H62: 1.3336033e+11 | I62: 1.0202654e+11 | J62: 8.4024304e+10 | K62: 8.1204161e+10 | L62: 7.3749374e+10 | M62: 7.4470099e+10 | N62: 1.0758206e+11 | O62: 1.3135886e+11 | P62: 1.5399421e+11 | Q62: 1.7140796e+11 | R62: =R63*R$44 -> 1.7037285e+11 | S62: =S63*S$44 -> 1.7037285e+11 | T62: =T63*T$44 -> 1.7037285e+11 | U62: =U63*U$44 -> 1.9081759e+11 | V62: =V63*V$44 -> 2.137157e+11 | W62: =W63*W$44 -> 2.3936158e+11 | X62: =X63*X$44 -> 2.6808497e+11 | Y62: =Y63*Y$44 -> 3.0025517e+11 | ... AD62: =AD63*AD$44 -> 4.9859433e+11 | AE62: =(N62/F62)^(1/8)-1 -> 0.01360362
E63: % dos Passivos Onerosos | F63: =F62/F$44 -> 0.095150537 | G63: =G62/G$44 -> 0.11399821 | H63: =H62/H$44 -> 0.11643118 | I63: =I62/I$44 -> 0.088723683 | J63: =J62/J$44 -> 0.071626759 | K63: =K62/K$44 -> 0.067224481 | L63: =L62/L$44 -> 0.056366347 | M63: =M62/M$44 -> 0.051220152 | ... Q63: =Q62/Q$44 -> 0.09995697 | R63: =Q63 -> 0.09995697 | S63: =R63 -> 0.09995697 | T63: =S63 -> 0.09995697 | U63: =T63 -> 0.09995697 | V63: =U63 -> 0.09995697 | W63: =V63 -> 0.09995697 | X63: =W63 -> 0.09995697 | Y63: =X63 -> 0.09995697 | ... AD63: =AC63 -> 0.09995697 | AF63: Percentual constante dos Passivos Onerosos
E64: Demais Letras Bancárias | F64: 1.1224265e+10 | G64: 2.0114488e+10 | H64: 2.024974e+10 | I64: 2.2385472e+10 | J64: 2.2346585e+10 | K64: 2.1428003e+10 | L64: 1.4264588e+10 | M64: 1.2715907e+10 | N64: 1.658298e+10 | O64: 1.8219011e+10 | P64: 2.2136092e+10 | Q64: 2.3649062e+10 | R64: =R65*R$44 -> 2.3506248e+10 | S64: =S65*S$44 -> 2.3506248e+10 | T64: =T65*T$44 -> 2.3506248e+10 | U64: =U65*U$44 -> 2.6326998e+10 | V64: =V65*V$44 -> 2.9486237e+10 | W64: =W65*W$44 -> 3.3024586e+10 | X64: =X65*X$44 -> 3.6987536e+10 | Y64: =Y65*Y$44 -> 4.142604e+10 | ... AD64: =AD65*AD$44 -> 6.8790785e+10 | AE64: =(N64/F64)^(1/8)-1 -> 0.04999706
E65: % dos Passivos Onerosos | F65: =F64/F$44 -> 0.011060493 | G65: =G64/G$44 -> 0.017926693 | H65: =H64/H$44 -> 0.017679177 | I65: =I64/I$44 -> 0.019466715 | J65: =J64/J$44 -> 0.01904941 | K65: =K64/K$44 -> 0.017739071 | L65: =L64/L$44 -> 0.010902367 | M65: =M64/M$44 -> 0.0087459359 | ... Q65: =Q64/Q$44 -> 0.013791008 | R65: =Q65 -> 0.013791008 | S65: =R65 -> 0.013791008 | T65: =S65 -> 0.013791008 | U65: =T65 -> 0.013791008 | V65: =U65 -> 0.013791008 | W65: =V65 -> 0.013791008 | X65: =W65 -> 0.013791008 | Y65: =X65 -> 0.013791008 | ... AD65: =AC65 -> 0.013791008 | AF65: Percentual constante dos Passivos Onerosos
E66: Passivos Onerosos / Ativos Rentáveis | F66: =F44/F34 -> 0.92828351 | G66: =G44/G34 -> 0.939149 | H66: =H44/H34 -> 0.91677456 | I66: =I44/I34 -> 0.92001518 | J66: =J44/J34 -> 0.91664278 | K66: =K44/K34 -> 0.90264321 | L66: =L44/L34 -> 0.88538967 | M66: =M44/M34 -> 0.87360843 | ... T66: =T44/T34 -> 0.8755709 | U66: =T66 -> 0.8755709 | V66: =U66 -> 0.8755709 | W66: =V66 -> 0.8755709 | X66: =W66 -> 0.8755709 | Y66: =X66 -> 0.8755709 | Z66: =Y66 -> 0.8755709 | AA66: =Z66 -> 0.8755709 | AB66: =AA66 -> 0.8755709 | ... AD66: =AC66 -> 0.8755709 | AF66: Relação entre Passivos Onerosos e Ativos Rentáveis constante
E70: Ano | F70: 2014 | G70: 2015 | H70: 2016 | I70: 2017 | J70: 2018 | K70: 2019 | L70: 2020 | M70: 2021 | N70: 2022 | O70: 1T23 | P70: 2T23 | Q70: 3T23 | R70: 4T23 | S70: YTG23 | T70: 2023 | U70: 2024 | V70: 2025 | W70: 2026 | X70: 2027 | Y70: 2028 | Z70: 2029 | AA70: 2030 | AB70: 2031 | AC70: 2032 | AD70: 2033 | AE70: CAGR 2014-2022
E71: Ativos Rentáveis | F71: =SUM(F73:F76) -> 1.2607778e+11 | G71: =SUM(G73:G76) -> 1.5568947e+11 | H71: =SUM(H73:H76) -> 1.7064309e+11 | I71: =SUM(I73:I76) -> 1.4371103e+11 | J71: =SUM(J73:J76) -> 1.1764526e+11 | K71: =SUM(K73:K76) -> 1.1987773e+11 | L71: =SUM(L73:L76) -> 9.672983e+10 | M71: =SUM(M73:M76) -> 1.2093687e+11 | ... AD71: =SUM(AD73:AD76) -> 6.79229e+11
E72: Crescimento dos Juros dos Ativos Rentáveis | F72: 0 | G72: =G71/F71-1 -> 0.23486844 | H72: =H71/G71-1 -> 0.096047719 | I72: =I71/H71-1 -> -0.15782681 | J72: =J71/I71-1 -> -0.1813763 | K72: =K71/J71-1 -> 0.018976317 | L72: =L71/K71-1 -> -0.19309592 | M72: =M71/L71-1 -> 0.25025415 | N72: =N71/M71-1 -> 0.9110146 | T72: =T71/N71-1 -> 0.16949131 | U72: =U71/T71-1 -> -0.065683059 | V72: =V71/U71-1 -> 0.10845641 | W72: =W71/V71-1 -> 0.12845626 | X72: =X71/W71-1 -> 0.13122911 | Y72: =Y71/X71-1 -> 0.12979957 | Z72: =Z71/Y71-1 -> 0.12670362 | AA72: =AA71/Z71-1 -> 0.11804423 | AB72: =AB71/AA71-1 -> 0.098312619 | ... AD72: =AD71/AC71-1 -> 0.1095 | AE72: =(N71/F71)^(1/8)-1 -> 0.078693407
E73: Títs. e Vlrs. Mobiliários + Aplic. Interfinanceiras s/Hedge | F73: 3.8769042e+10 | G73: 5.2411661e+10 | H73: 6.2898912e+10 | I73: 5.2074471e+10 | J73: 3.909547e+10 | K73: 4.263213e+10 | L73: 2.5786696e+10 | M73: 4.2329669e+10 | N73: 1.1445236e+11 | O73: 3.0325868e+10 | P73: 3.1367956e+10 | Q73: 3.3305475e+10 | R73: =R36*R94 -> 3.297286e+10 | S73: =R73 -> 3.297286e+10 | T73: =SUM(O73:R73) -> 1.2797216e+11 | U73: =U36*U94 -> 1.0601288e+11 | V73: =V36*V94 -> 1.1682105e+11 | W73: =W36*W94 -> 1.3239323e+11 | X73: =X36*X94 -> 1.5060855e+11 | Y73: =Y36*Y94 -> 1.7097994e+11 | Z73: =Z36*Z94 -> 1.9327386e+11 | AA73: =AA36*AA94 -> 2.1651451e+11 | AB73: =AB36*AB94 -> 2.3807184e+11 | ... AD73: =AD36*AD94 -> 2.8972695e+11 | AE73: =(N73/F73)^(1/8)-1 -> 0.14489975
E74: Operações de Crédito + Leasing | F74: 8.1384423e+10 | G74: 9.793673e+10 | H74: 1.0179154e+11 | I74: 8.7332362e+10 | J74: 7.5776474e+10 | K74: 7.4694146e+10 | L74: 6.9221474e+10 | M74: 7.6478538e+10 | N74: 1.0986281e+11 | O74: 3.2304148e+10 | P74: 3.3614104e+10 | Q74: 3.4430342e+10 | R74: =R38*R95 -> 3.4086493e+10 | S74: =R74 -> 3.4086493e+10 | T74: =SUM(O74:R74) -> 1.3443509e+11 | U74: =U38*U95 -> 1.3839878e+11 | V74: =V38*V95 -> 1.5415644e+11 | W74: =W38*W95 -> 1.7334557e+11 | X74: =X38*X95 -> 1.9518153e+11 | Y74: =Y38*Y95 -> 2.1962458e+11 | Z74: =Z38*Z95 -> 2.4676883e+11 | AA74: =AA38*AA95 -> 2.7543698e+11 | AB74: =AB38*AB95 -> 3.0222194e+11 | ... AD74: =AD38*AD95 -> 3.6728022e+11 | AE74: =(N74/F74)^(1/8)-1 -> 0.038218292
E75: Depósito Compulsório Rentável | F75: 5.6685071e+09 | G75: 5.0974989e+09 | H75: 5.6084457e+09 | I75: 4.1031331e+09 | J75: 2.5192719e+09 | K75: 2.3281905e+09 | L75: 1.4747614e+09 | M75: 1.9339776e+09 | N75: 6.4511353e+09 | O75: 1.8101992e+09 | P75: 1.911776e+09 | Q75: 1.8538933e+09 | R75: =R40*R96 -> 1.8353789e+09 | S75: =R75 -> 1.8353789e+09 | T75: =SUM(O75:R75) -> 7.4112474e+09 | U75: =U40*U96 -> 7.5772632e+09 | V75: =V40*V96 -> 8.340218e+09 | W75: =W40*W96 -> 9.4598533e+09 | X75: =X40*X96 -> 1.0773069e+10 | Y75: =Y40*Y96 -> 1.2241595e+10 | Z75: =Z40*Z96 -> 1.3846424e+10 | AA75: =AA40*AA96 -> 1.5517248e+10 | AB75: =AB40*AB96 -> 1.7065935e+10 | ... AD75: =AD40*AD96 -> 2.077177e+10 | AE75: =(N75/F75)^(1/8)-1 -> 0.016297674
E76: Demais Ativos Rentáveis | F76: 2.5580576e+08 | G76: 2.4357793e+08 | H76: 3.4418778e+08 | I76: 2.0106645e+08 | J76: 2.540411e+08 | K76: 2.2326418e+08 | L76: 2.4689921e+08 | M76: 1.9468741e+08 | N76: 3.4582564e+08 | O76: 89038741 | P76: 37608813 | Q76: 1.7009184e+08 | R76: =R42*R97 -> 1.6839317e+08 | S76: =R76 -> 1.6839317e+08 | T76: =SUM(O76:R76) -> 4.6513257e+08 | U76: =U42*U97 -> 5.4165074e+08 | V76: =V42*V97 -> 6.0142096e+08 | W76: =W42*W97 -> 6.778365e+08 | X76: =X42*X97 -> 7.6553799e+08 | Y76: =Y42*Y97 -> 8.6368233e+08 | Z76: =Z42*Z97 -> 9.7217764e+08 | AA76: =AA42*AA97 -> 1.0863049e+09 | AB76: =AB42*AB97 -> 1.1926994e+09 | ... AD76: =AD42*AD97 -> 1.4500593e+09 | AE76: =(N76/F76)^(1/8)-1 -> 0.038408797
E77: Passivos Onerosos | F77: =SUM(F79:F88) -> -8.1610463e+10 | G77: =SUM(G79:G88) -> -1.0518057e+11 | H77: =SUM(H79:H88) -> -1.1597501e+11 | I77: =SUM(I79:I88) -> -9.2720601e+10 | J77: =SUM(J79:J88) -> -6.9714638e+10 | K77: =SUM(K79:K88) -> -6.6717824e+10 | L77: =SUM(L79:L88) -> -4.0710371e+10 | M77: =SUM(M79:M88) -> -6.2580641e+10 | ... AD77: =SUM(AD79:AD88) -> -4.5815577e+11
E78: Crescimento dos Juros dos Passivos Onerosos | F78: 0 | G78: =G77/F77-1 -> 0.28881235 | H78: =H77/G77-1 -> 0.10262769 | I78: =I77/H77-1 -> -0.20051225 | J78: =J77/I77-1 -> -0.24812137 | K78: =K77/J77-1 -> -0.042986874 | L78: =L77/K77-1 -> -0.38981267 | M78: =M77/L77-1 -> 0.53721618 | N78: =N77/M77-1 -> 1.5411847 | T78: =T77/N77-1 -> 0.13947862 | U78: =U77/T77-1 -> -0.073610731 | V78: =V77/U77-1 -> 0.10251241 | W78: =W77/V77-1 -> 0.1328796 | X78: =X77/W77-1 -> 0.13703611 | Y78: =Y77/X77-1 -> 0.13479137 | Z78: =Z77/Y77-1 -> 0.13007387 | AA78: =AA77/Z77-1 -> 0.12005934 | AB78: =AB77/AA77-1 -> 0.09945869 | ... AD78: =AD77/AC77-1 -> 0.1095 | AE78: =(N77/F77)^(1/8)-1 -> 0.086966849
E79: Depósitos de Poupança | F79: -9.6667727e+09 | G79: -1.0912156e+10 | H79: -1.1467023e+10 | I79: -9.4209591e+09 | J79: -7.7810673e+09 | K79: -7.637773e+09 | L79: -5.1018505e+09 | M79: -7.286796e+09 | N79: -1.5935594e+10 | O79: -4.0091358e+09 | P79: -3.8790659e+09 | Q79: -3.939165e+09 | R79: =R46*R99 -> -3.9153768e+09 | S79: =R79 -> -3.9153768e+09 | T79: =SUM(O79:R79) -> -1.5742743e+10 | U79: =U46*U99 -> -1.4901113e+10 | V79: =V46*V99 -> -1.6447963e+10 | W79: =W46*W99 -> -1.8617641e+10 | X79: =X46*X99 -> -2.1145345e+10 | Y79: =Y46*Y99 -> -2.397262e+10 | Z79: =Z46*Z99 -> -2.7073338e+10 | AA79: =AA46*AA99 -> -3.0311959e+10 | AB79: =AB46*AB99 -> -3.3319253e+10 | ... AD79: =AD46*AD99 -> -4.0539967e+10 | AE79: =(N79/F79)^(1/8)-1 -> 0.064475927
E80: Depósitos Interfinanceiros | F80: -6.8441478e+08 | G80: -8.1634452e+08 | H80: -9.1534125e+08 | I80: -6.4964255e+08 | J80: -8.8114182e+08 | K80: -1.0688802e+09 | L80: -6.1062508e+08 | M80: -4.3337551e+08 | N80: -8.5319987e+08 | O80: -3.1194125e+08 | P80: -3.6750802e+08 | Q80: -4.0909726e+08 | R80: =R48*R100 -> -4.0662677e+08 | S80: =R80 -> -4.0662677e+08 | T80: =SUM(O80:R80) -> -1.4951733e+09 | U80: =U48*U100 -> -8.0463802e+08 | V80: =V48*V100 -> -8.9659684e+08 | W80: =W48*W100 -> -1.0079218e+09 | X80: =X48*X100 -> -1.1344668e+09 | Y80: =Y48*Y100 -> -1.2761257e+09 | Z80: =Z48*Z100 -> -1.4335292e+09 | AA80: =AA48*AA100 -> -1.5998529e+09 | AB80: =AB48*AB100 -> -1.7552938e+09 | ... AD80: =AD48*AD100 -> -2.1330387e+09 | AE80: =(N80/F80)^(1/8)-1 -> 0.027936827
E81: Depósitos a Prazo | F81: -1.9791368e+10 | G81: -2.003764e+10 | H81: -2.0240721e+10 | I81: -1.6336813e+10 | J81: -1.3323665e+10 | K81: -1.3722027e+10 | L81: -7.9941589e+09 | M81: -1.3923757e+10 | N81: -3.7140358e+10 | O81: -1.1636987e+10 | P81: -1.2384638e+10 | Q81: -1.3302384e+10 | R81: =R50*R101 -> -1.3222052e+10 | S81: =R81 -> -1.3222052e+10 | T81: =SUM(O81:R81) -> -5.0546062e+10 | U81: =U50*U101 -> -4.3990038e+10 | V81: =V50*V101 -> -4.8567531e+10 | W81: =W50*W101 -> -5.49651e+10 | X81: =X50*X101 -> -6.2414246e+10 | Y81: =Y50*Y101 -> -7.0746382e+10 | Z81: =Z50*Z101 -> -7.988703e+10 | AA81: =AA50*AA101 -> -8.943671e+10 | AB81: =AB50*AB101 -> -9.8305577e+10 | ... AD81: =AD50*AD101 -> -1.1960622e+11 | AE81: =(N81/F81)^(1/8)-1 -> 0.081860547
E82: Captações no Mercado Aberto | F82: -2.9804925e+10 | G82: -4.1733903e+10 | H82: -4.8809616e+10 | I82: -4.0412452e+10 | J82: -2.7602423e+10 | K82: -2.7533393e+10 | L82: -1.3858933e+10 | M82: -2.7510115e+10 | N82: -8.1197833e+10 | O82: -2.0586074e+10 | P82: -1.9498704e+10 | Q82: -2.0786003e+10 | R82: =R52*R102 -> -2.0660478e+10 | S82: =R82 -> -2.0660478e+10 | T82: =SUM(O82:R82) -> -8.153126e+10 | U82: =U52*U102 -> -7.5383961e+10 | V82: =V52*V102 -> -8.2905527e+10 | W82: =W52*W102 -> -9.4092091e+10 | X82: =X52*X102 -> -1.0723812e+11 | Y82: =Y52*Y102 -> -1.2193795e+11 | Z82: =Z52*Z102 -> -1.3798582e+11 | AA82: =AA52*AA102 -> -1.5467824e+11 | AB82: =AB52*AB102 -> -1.7014241e+11 | ... AD82: =AD52*AD102 -> -2.0710998e+11 | AE82: =(N82/F82)^(1/8)-1 -> 0.13346223
E83: Obrigações por Empréstimos e Repasses no País | F83: -6.1113934e+09 | G83: -7.0033901e+09 | H83: -7.7576749e+09 | I83: -7.0794716e+09 | J83: -6.5921038e+09 | K83: -5.9928818e+09 | L83: -5.0562812e+09 | M83: -4.1071571e+09 | N83: -5.3929151e+09 | O83: -1.5478864e+09 | P83: -1.5509781e+09 | Q83: -1.4689423e+09 | R83: =R54*R103 -> -1.4600715e+09 | S83: =R83 -> -1.4600715e+09 | T83: =SUM(O83:R83) -> -6.0278783e+09 | U83: =U54*U103 -> -4.8004437e+09 | V83: =V54*V103 -> -5.3708345e+09 | W83: =W54*W103 -> -6.0199325e+09 | X83: =X54*X103 -> -6.7492143e+09 | Y83: =Y54*Y103 -> -7.5659217e+09 | Z83: =Z54*Z103 -> -8.4790892e+09 | AA83: =AA54*AA103 -> -9.4492786e+09 | AB83: =AB54*AB103 -> -1.0358694e+10 | ... AD83: =AD54*AD103 -> -1.2580906e+10 | AE83: =(N83/F83)^(1/8)-1 -> -0.015512021
E84: Fundos Financeiros e de Desenv. | F84: -4.018738e+08 | G84: -1.0129593e+09 | H84: -2.195829e+09 | I84: -2.385837e+09 | J84: -2.4708466e+09 | K84: -6.453872e+08 | L84: -4.7451219e+08 | M84: -8.3453226e+08 | N84: -6.4104496e+08 | O84: -2.4365795e+08 | P84: -2.6521314e+08 | Q84: -1.2630184e+08 | R84: =R56*R104 -> -1.2553912e+08 | S84: =R84 -> -1.2553912e+08 | T84: =SUM(O84:R84) -> -7.6071206e+08 | U84: =U56*U104 -> -3.9795908e+09 | V84: =V56*V104 -> -4.4061934e+09 | W84: =W56*W104 -> -4.9763066e+09 | X84: =X56*X104 -> -5.6354556e+09 | Y84: =Y56*Y104 -> -6.37291e+09 | Z84: =Z56*Z104 -> -7.1849583e+09 | AA84: =AA56*AA104 -> -8.0361941e+09 | AB84: =AB56*AB104 -> -8.8282237e+09 | ... AD84: =AD56*AD104 -> -1.0737174e+10 | AE84: =(N84/F84)^(1/8)-1 -> 0.060107358
E85: Dívida Subordinada | F85: -4.5886265e+09 | G85: -6.593151e+09 | H85: -6.4200249e+09 | I85: -5.394787e+09 | J85: -4.4423134e+09 | K85: -3.7220787e+09 | L85: -3.8332303e+09 | M85: -3.3950982e+09 | N85: -3.2086275e+09 | O85: -8.4788771e+08 | P85: -7.8385246e+08 | Q85: -8.0771058e+08 | R85: =R58*R105 -> -8.0283291e+08 | S85: =R85 -> -8.0283291e+08 | T85: =SUM(O85:R85) -> -3.2422837e+09 | U85: =U58*U105 -> -2.7431273e+09 | V85: =V58*V105 -> -3.0497147e+09 | W85: =W58*W105 -> -3.4340218e+09 | X85: =X58*X105 -> -3.8735888e+09 | Y85: =Y58*Y105 -> -4.3655524e+09 | Z85: =Z58*Z105 -> -4.9103888e+09 | AA85: =AA58*AA105 -> -5.4844271e+09 | AB85: =AB58*AB105 -> -6.0200451e+09 | ... AD85: =AD58*AD105 -> -7.3178059e+09 | AE85: =(N85/F85)^(1/8)-1 -> -0.04373211
E86: Obrigações com T.V.M. no Exterior | F86: -1.0413955e+09 | G86: -1.1093356e+09 | H86: -8.4582714e+08 | I86: -8.6279143e+08 | J86: -1.1275886e+09 | K86: -1.4089375e+09 | L86: -1.5734089e+09 | M86: -1.5523296e+09 | N86: -1.6429956e+09 | O86: -5.164279e+08 | P86: -5.629646e+08 | Q86: -5.8879919e+08 | R86: =R60*R106 -> -5.852435e+08 | S86: =R86 -> -5.852435e+08 | T86: =SUM(O86:R86) -> -2.2534352e+09 | U86: =U60*U106 -> -1.719654e+09 | V86: =V60*V106 -> -1.9320072e+09 | W86: =W60*W106 -> -2.1589803e+09 | X86: =X60*X106 -> -2.4107638e+09 | Y86: =Y60*Y106 -> -2.6928545e+09 | Z86: =Z60*Z106 -> -3.0104317e+09 | AA86: =AA60*AA106 -> -3.349838e+09 | AB86: =AB60*AB106 -> -3.6690039e+09 | ... AD86: =AD60*AD106 -> -4.4534886e+09 | AE86: =(N86/F86)^(1/8)-1 -> 0.058650461
E87: Letra de Crédito do Agronegócio | F87: -8.8331453e+09 | G87: -1.4151742e+10 | H87: -1.5487657e+10 | I87: -8.7781046e+09 | J87: -4.6667514e+09 | K87: -4.2337205e+09 | L87: -1.8622622e+09 | M87: -3.0476573e+09 | N87: -1.1731279e+10 | O87: -3.8204702e+09 | P87: -4.3534776e+09 | Q87: -5.0178925e+09 | R87: =R62*R107 -> -4.98759e+09 | S87: =R87 -> -4.98759e+09 | T87: =SUM(O87:R87) -> -1.817943e+10 | U87: =U62*U107 -> -1.7723283e+10 | V87: =V62*V107 -> -1.9494702e+10 | W87: =W62*W107 -> -2.2122631e+10 | X87: =X62*X107 -> -2.5209755e+10 | Y87: =Y62*Y107 -> -2.8661807e+10 | Z87: =Z62*Z107 -> -3.2431146e+10 | AA87: =AA62*AA107 -> -3.6352553e+10 | AB87: =AB62*AB107 -> -3.9985774e+10 | ... AD87: =AD62*AD107 -> -4.8672706e+10 | AE87: =(N87/F87)^(1/8)-1 -> 0.036104945
E88: Demais Letras Bancárias | F88: -6.8654812e+08 | G88: -1.8099523e+09 | H88: -1.8352992e+09 | I88: -1.3997439e+09 | J88: -8.2673831e+08 | K88: -7.5274597e+08 | L88: -3.4510923e+08 | M88: -4.8982342e+08 | N88: -1.2851178e+09 | O88: -3.2361507e+08 | P88: -3.3673647e+08 | Q88: -3.8655493e+08 | R88: =R64*R108 -> -3.8422057e+08 | S88: =R88 -> -3.8422057e+08 | T88: =SUM(O88:R88) -> -1.431127e+09 | U88: =U64*U108 -> -1.8252473e+09 | V88: =V64*V108 -> -2.0088994e+09 | W88: =W64*W108 -> -2.2786939e+09 | X88: =X64*X108 -> -2.5951835e+09 | Y88: =Y64*Y108 -> -2.9491016e+09 | Z88: =Z64*Z108 -> -3.3358375e+09 | AA88: =AA64*AA108 -> -3.7384478e+09 | AB88: =AB64*AB108 -> -4.1116118e+09 | ... AD88: =AD64*AD108 -> -5.0044815e+09 | AE88: =(N88/F88)^(1/8)-1 -> 0.081518604
E92: Ano | F92: 2014 | G92: 2015 | H92: 2016 | I92: 2017 | J92: 2018 | K92: 2019 | L92: 2020 | M92: 2021 | N92: 2022 | O92: 1T23 | P92: 2T23 | Q92: 3T23 | R92: 4T23 | S92: YTG23 | T92: 2023 | U92: 2024 | V92: 2025 | W92: 2026 | X92: 2027 | Y92: 2028 | Z92: 2029 | AA92: 2030 | AB92: 2031 | AC92: 2032 | AD92: 2033
E93: Ativos Rentáveis | F93: =F71/F34 -> 0.11532827 | G93: =G71/G34 -> 0.13031216 | H93: =H71/H34 -> 0.13658212 | I93: =I71/I34 -> 0.11497714 | J93: =J71/J34 -> 0.091927387 | K93: =K71/K34 -> 0.089578505 | L93: =L71/L34 -> 0.06545705 | M93: =M71/M34 -> 0.072666539 | ... AD93: =AD71/AD34 -> 0.11922663
E94: Títs. e Vlrs. Mobiliários + Aplic. Interfinanceiras s/Hedge | F94: =F73/F36 -> 0.096604367 | G94: =G73/G36 -> 0.11422293 | H94: =H73/H36 -> 0.12510193 | I94: =I73/I36 -> 0.094012599 | J94: =J73/J36 -> 0.066228835 | K94: =K73/K36 -> 0.064587201 | L94: =L73/L36 -> 0.03375873 | M94: =M73/M36 -> 0.047949286 | ... Q94: =Q73/Q36 -> 0.035174169 | R94: =Q94 -> 0.035174169 | S94: =S73/S36 -> 0.035174169 | T94: =T73/T36 -> 0.13651574 | U94: =$F114+$G114*U$10 -> 0.1009736 | V94: =$F114+$G114*V$10 -> 0.099346435 | W94: =$F114+$G114*W$10 -> 0.10052613 | X94: =$F114+$G114*X$10 -> 0.10210447 | Y94: =$F114+$G114*Y$10 -> 0.10349569 | Z94: =$F114+$G114*Z$10 -> 0.10445572 | AA94: =$F114+$G114*AA$10 -> 0.1050415 | AB94: =$F114+$G114*AB$10 -> 0.1053832 | ... AD94: =$F114+$G114*AD$10 -> 0.105611
E95: Operações de Crédito + Leasing | F95: =F74/F38 -> 0.13140497 | G95: =G74/G38 -> 0.14466262 | H95: =H74/H38 -> 0.14852943 | I95: =I74/I38 -> 0.13769551 | J95: =J74/J38 -> 0.12073511 | K95: =K74/K38 -> 0.12047913 | L95: =L74/L38 -> 0.10560811 | M95: =M74/M38 -> 0.10661258 | ... Q95: =Q74/Q38 -> 0.037300496 | R95: =Q95 -> 0.037300496 | S95: =S74/S38 -> 0.037300496 | T95: =T74/T38 -> 0.14711092 | U95: =$F115+$G115*U$10 -> 0.13522174 | V95: =$F115+$G115*V$10 -> 0.13448007 | W95: =$F115+$G115*W$10 -> 0.13501778 | X95: =$F115+$G115*X$10 -> 0.13573721 | Y95: =$F115+$G115*Y$10 -> 0.13637134 | Z95: =$F115+$G115*Z$10 -> 0.13680893 | AA95: =$F115+$G115*AA$10 -> 0.13707593 | AB95: =$F115+$G115*AB$10 -> 0.13723168 | ... AD95: =$F115+$G115*AD$10 -> 0.13733552
E96: Depósito Compulsório Rentável | F96: =F75/F40 -> 0.083737089 | G96: =G75/G40 -> 0.10411707 | H96: =H75/H40 -> 0.10525263 | I96: =I75/I40 -> 0.076109138 | J96: =J75/J40 -> 0.046767619 | K96: =K75/K40 -> 0.046988348 | L96: =L75/L40 -> 0.030257454 | M96: =M75/M40 -> 0.037188926 | ... Q96: =Q75/Q40 -> 0.022655479 | R96: =Q96 -> 0.022655479 | S96: =S75/S40 -> 0.022655479 | T96: =T75/T40 -> 0.09148267 | U96: =$F116+$G116*U$10 -> 0.08351065 | V96: =$F116+$G116*V$10 -> 0.082070839 | W96: =$F116+$G116*W$10 -> 0.083114702 | X96: =$F116+$G116*X$10 -> 0.084511319 | Y96: =$F116+$G116*Y$10 -> 0.085742358 | Z96: =$F116+$G116*Z$10 -> 0.086591846 | AA96: =$F116+$G116*AA$10 -> 0.087110178 | AB96: =$F116+$G116*AB$10 -> 0.087412539 | ... AD96: =$F116+$G116*AD$10 -> 0.087614112
E97: Demais Ativos Rentáveis | F97: =F76/F42 -> 0.052682689 | G97: =G76/G42 -> 0.024534133 | H97: =H76/H42 -> 0.043105112 | I97: =I76/I42 -> 0.025625722 | J97: =J76/J42 -> 0.031913545 | K97: =K76/K42 -> 0.025819137 | L97: =L76/L42 -> 0.025424348 | M97: =M76/M42 -> 0.016067561 | ... Q97: =Q76/Q42 -> 0.011676113 | R97: =Q97 -> 0.011676113 | S97: =S76/S42 -> 0.011676113 | T97: =T76/T42 -> 0.032251548 | U97: =$F117+$G117*U$10 -> 0.033533211 | V97: =$F117+$G117*V$10 -> 0.033244234 | W97: =$F117+$G117*W$10 -> 0.033453742 | X97: =$F117+$G117*X$10 -> 0.033734049 | Y97: =$F117+$G117*Y$10 -> 0.033981124 | Z97: =$F117+$G117*Z$10 -> 0.03415162 | AA97: =$F117+$G117*AA$10 -> 0.034255652 | AB97: =$F117+$G117*AB$10 -> 0.034316337 | ... AD97: =$F117+$G117*AD$10 -> 0.034356794
E98: Passivos Onerosos | F98: =F77/F44 -> -0.080419697 | G98: =G77/G44 -> -0.093740384 | H98: =H77/H44 -> -0.1012528 | I98: =I77/I44 -> -0.080631113 | J98: =J77/J44 -> -0.059428443 | K98: =K77/K44 -> -0.055232035 | L98: =L77/L44 -> -0.031114772 | M98: =M77/M44 -> -0.043042644 | ... AD98: =AD77/AD44 -> -0.091849946
E99: Depósitos de Poupança | F99: =F79/F46 -> -0.066001 | G99: =G79/G46 -> -0.07378738 | H99: =H79/H46 -> -0.076594874 | I99: =I79/I46 -> -0.06181612 | J99: =J79/J46 -> -0.046390364 | K99: =K79/K46 -> -0.043496769 | L99: =L79/L46 -> -0.025639508 | M99: =M79/M46 -> -0.0327395 | ... Q99: =Q79/Q46 -> -0.019093203 | R99: =Q99 -> -0.019093203 | S99: =S79/S46 -> -0.019093203 | T99: =T79/T46 -> -0.076768958 | U99: =$F119+$G119*U$10 -> -0.064879265 | V99: =$F119+$G119*V$10 -> -0.063941275 | W99: =$F119+$G119*W$10 -> -0.064621318 | X99: =$F119+$G119*X$10 -> -0.065531168 | Y99: =$F119+$G119*Y$10 -> -0.06633315 | Z99: =$F119+$G119*Z$10 -> -0.066886565 | AA99: =$F119+$G119*AA$10 -> -0.067224241 | AB99: =$F119+$G119*AB$10 -> -0.067421219 | ... AD99: =$F119+$G119*AD$10 -> -0.067552538
E100: Depósitos Interfinanceiros | F100: =F80/F48 -> -0.0251554 | G100: =G80/G48 -> -0.022323745 | H100: =H80/H48 -> -0.03062591 | I100: =I80/I48 -> -0.033583735 | J100: =J80/J48 -> -0.02802309 | K100: =K80/K48 -> -0.032740641 | L100: =L80/L48 -> -0.020642109 | M100: =M80/M48 -> -0.016587376 | ... Q100: =Q80/Q48 -> -0.016155756 | R100: =Q100 -> -0.016155756 | S100: =S80/S48 -> -0.016155756 | T100: =T80/T48 -> -0.05940498 | U100: =$F120+$G120*U$10 -> -0.028543935 | V100: =$F120+$G120*V$10 -> -0.028398309 | W100: =$F120+$G120*W$10 -> -0.028503888 | X100: =$F120+$G120*X$10 -> -0.028645146 | Y100: =$F120+$G120*Y$10 -> -0.028769656 | Z100: =$F120+$G120*Z$10 -> -0.028855575 | AA100: =$F120+$G120*AA$10 -> -0.028908001 | AB100: =$F120+$G120*AB$10 -> -0.028938582 | ... AD100: =$F120+$G120*AD$10 -> -0.02895897
E101: Depósitos a Prazo | F101: =F81/F50 -> -0.086712278 | G101: =G81/G50 -> -0.097692134 | H101: =H81/H50 -> -0.099793651 | I101: =I81/I50 -> -0.081085283 | J101: =J81/J50 -> -0.064170876 | K101: =K81/K50 -> -0.060194168 | L101: =L81/L50 -> -0.030601147 | M101: =M81/M50 -> -0.04506491 | ... Q101: =Q81/Q50 -> -0.028839012 | R101: =Q101 -> -0.028839012 | S101: =S81/S50 -> -0.028839012 | T101: =T81/T50 -> -0.11024752 | U101: =$F121+$G121*U$10 -> -0.08566784 | V101: =$F121+$G121*V$10 -> -0.08444841 | W101: =$F121+$G121*W$10 -> -0.085332497 | X101: =$F121+$G121*X$10 -> -0.086515344 | Y101: =$F121+$G121*Y$10 -> -0.087557957 | Z101: =$F121+$G121*Z$10 -> -0.088277421 | AA101: =$F121+$G121*AA$10 -> -0.088716416 | AB101: =$F121+$G121*AB$10 -> -0.088972496 | ... AD101: =$F121+$G121*AD$10 -> -0.089143217
E102: Captações no Mercado Aberto | F102: =F82/F52 -> -0.10489204 | G102: =G82/G52 -> -0.12731914 | H102: =H82/H52 -> -0.13240673 | I102: =I82/I52 -> -0.095989321 | J102: =J82/J52 -> -0.064123323 | K102: =K82/K52 -> -0.059737295 | L102: =L82/L52 -> -0.027137244 | M102: =M82/M52 -> -0.045555983 | ... Q102: =Q82/Q52 -> -0.03235473 | R102: =Q102 -> -0.03235473 | S102: =S82/S52 -> -0.03235473 | T102: =T82/T52 -> -0.12767961 | U102: =$F122+$G122*U$10 -> -0.1054043 | V102: =$F122+$G122*V$10 -> -0.10350107 | W102: =$F122+$G122*W$10 -> -0.10488091 | X102: =$F122+$G122*X$10 -> -0.10672705 | Y102: =$F122+$G122*Y$10 -> -0.10835431 | Z102: =$F122+$G122*Z$10 -> -0.10947721 | AA102: =$F122+$G122*AA$10 -> -0.11016238 | AB102: =$F122+$G122*AB$10 -> -0.11056206 | ... AD102: =$F122+$G122*AD$10 -> -0.11082851
E103: Obrigações por Empréstimos e Repasses no País | F103: =F83/F54 -> -0.057544368 | G103: =G83/G54 -> -0.06049959 | H103: =H83/H54 -> -0.070349873 | I103: =I83/I54 -> -0.070729481 | J103: =J83/J54 -> -0.068749548 | K103: =K83/K54 -> -0.073175451 | L103: =L83/L54 -> -0.066532106 | M103: =M83/M54 -> -0.059296105 | ... Q103: =Q83/Q54 -> -0.023322272 | R103: =Q103 -> -0.023322272 | S103: =S83/S54 -> -0.023322272 | T103: =T83/T54 -> -0.096285567 | U103: =$F123+$G123*U$10 -> -0.068463655 | V103: =$F123+$G123*V$10 -> -0.06839155 | W103: =$F123+$G123*W$10 -> -0.068443826 | X103: =$F123+$G123*X$10 -> -0.068513767 | Y103: =$F123+$G123*Y$10 -> -0.068575416 | Z103: =$F123+$G123*Z$10 -> -0.068617958 | AA103: =$F123+$G123*AA$10 -> -0.068643915 | AB103: =$F123+$G123*AB$10 -> -0.068659057 | ... AD103: =$F123+$G123*AD$10 -> -0.068669152
E104: Fundos Financeiros e de Desenv. | F104: =F84/F56 -> -0.045758723 | G104: =G84/G56 -> -0.07795332 | H104: =H84/H56 -> -0.15073865 | I104: =I84/I56 -> -0.15606069 | J104: =J84/J56 -> -0.15723266 | K104: =K84/K56 -> -0.040279264 | L104: =L84/L56 -> -0.022265578 | M104: =M84/M56 -> -0.031624186 | ... Q104: =Q84/Q56 -> -0.0031079563 | R104: =Q104 -> -0.0031079563 | S104: =S84/S56 -> -0.0031079563 | T104: =T84/T56 -> -0.018832853 | U104: =$F124+$G124*U$10 -> -0.087966277 | V104: =$F124+$G124*V$10 -> -0.086960761 | W104: =$F124+$G124*W$10 -> -0.08768976 | X104: =$F124+$G124*X$10 -> -0.08866511 | Y104: =$F124+$G124*Y$10 -> -0.089524826 | Z104: =$F124+$G124*Z$10 -> -0.09011808 | AA104: =$F124+$G124*AA$10 -> -0.090480066 | AB104: =$F124+$G124*AB$10 -> -0.090691224 | ... AD104: =$F124+$G124*AD$10 -> -0.090831997
E105: Dívida Subordinada | F105: =F85/F58 -> -0.060615293 | G105: =G85/G58 -> -0.071584718 | H105: =H85/H58 -> -0.068869899 | I105: =I85/I58 -> -0.057754155 | J105: =J85/J58 -> -0.048076196 | K105: =K85/K58 -> -0.045869857 | L105: =L85/L58 -> -0.04623873 | M105: =M85/M58 -> -0.048725804 | ... Q105: =Q85/Q58 -> -0.019934252 | R105: =Q105 -> -0.019934252 | S105: =S85/S58 -> -0.019934252 | T105: =T85/T58 -> -0.080505545 | U105: =$F125+$G125*U$10 -> -0.060813883 | V105: =$F125+$G125*V$10 -> -0.060366772 | W105: =$F125+$G125*W$10 -> -0.060690927 | X105: =$F125+$G125*X$10 -> -0.061124625 | Y105: =$F125+$G125*Y$10 -> -0.061506905 | Z105: =$F125+$G125*Z$10 -> -0.061770701 | AA105: =$F125+$G125*AA$10 -> -0.061931661 | AB105: =$F125+$G125*AB$10 -> -0.062025554 | ... AD105: =$F125+$G125*AD$10 -> -0.06208815
E106: Obrigações com T.V.M. no Exterior | F106: =F86/F60 -> -0.03439799 | G106: =G86/G60 -> -0.030982843 | H106: =H86/H60 -> -0.037304754 | I106: =I86/I60 -> -0.038345503 | J106: =J86/J60 -> -0.044301424 | K106: =K86/K60 -> -0.048339217 | L106: =L86/L60 -> -0.039663201 | M106: =M86/M60 -> -0.038942432 | ... Q106: =Q86/Q60 -> -0.014617641 | R106: =Q106 -> -0.014617641 | S106: =S86/S60 -> -0.014617641 | T106: =T86/T60 -> -0.056284106 | U106: =$F126+$G126*U$10 -> -0.038349857 | V106: =$F126+$G126*V$10 -> -0.038469221 | W106: =$F126+$G126*W$10 -> -0.038382682 | X106: =$F126+$G126*X$10 -> -0.038266899 | Y106: =$F126+$G126*Y$10 -> -0.038164843 | Z106: =$F126+$G126*Z$10 -> -0.038094418 | AA106: =$F126+$G126*AA$10 -> -0.038051447 | AB106: =$F126+$G126*AB$10 -> -0.03802638 | ... AD106: =$F126+$G126*AD$10 -> -0.038009669
E107: Letra de Crédito do Agronegócio | F107: =F87/F62 -> -0.091478856 | G107: =G87/G62 -> -0.11063768 | H107: =H87/H62 -> -0.11613391 | I107: =I87/I62 -> -0.086037464 | J107: =J87/J62 -> -0.055540495 | K107: =K87/K62 -> -0.052136744 | L107: =L87/L62 -> -0.025251227 | M107: =M87/M62 -> -0.040924577 | ... Q107: =Q87/Q62 -> -0.029274559 | R107: =Q107 -> -0.029274559 | S107: =S87/S62 -> -0.029274559 | T107: =T87/T62 -> -0.1067038 | U107: =$F127+$G127*U$10 -> -0.092880762 | V107: =$F127+$G127*V$10 -> -0.091217923 | W107: =$F127+$G127*W$10 -> -0.092423481 | X107: =$F127+$G127*X$10 -> -0.094036435 | Y107: =$F127+$G127*Y$10 -> -0.095458163 | Z107: =$F127+$G127*Z$10 -> -0.096439238 | AA107: =$F127+$G127*AA$10 -> -0.09703786 | AB107: =$F127+$G127*AB$10 -> -0.097387057 | ... AD107: =$F127+$G127*AD$10 -> -0.097619854
E108: Demais Letras Bancárias | F108: =F88/F64 -> -0.061166422 | G108: =G88/G64 -> -0.089982517 | H108: =H88/H64 -> -0.090633223 | I108: =I88/I64 -> -0.062529124 | J108: =J88/J64 -> -0.036996182 | K108: =K88/K64 -> -0.035129077 | L108: =L88/L64 -> -0.024193424 | M108: =M88/M64 -> -0.038520524 | ... Q108: =Q88/Q64 -> -0.016345466 | R108: =Q108 -> -0.016345466 | S108: =S88/S64 -> -0.016345466 | T108: =T88/T64 -> -0.060882836 | U108: =$F128+$G128*U$10 -> -0.06932987 | V108: =$F128+$G128*V$10 -> -0.068130069 | W108: =$F128+$G128*W$10 -> -0.068999925 | X108: =$F128+$G128*X$10 -> -0.070163731 | Y108: =$F128+$G128*Y$10 -> -0.07118956 | Z108: =$F128+$G128*Z$10 -> -0.071897443 | AA108: =$F128+$G128*AA$10 -> -0.072329371 | AB108: =$F128+$G128*AB$10 -> -0.072581329 | ... AD108: =$F128+$G128*AD$10 -> -0.072749301
F112: Coeficiente Linear | G112: Coeficiente Angular | H112: R Quadrado | K112: Coeficiente Linear | L112: Coeficiente Angular | M112: R Quadrado
E113: Ativos Rentáveis | F113: =INTERCEPT(F93:N93,$F$10:$N$10) -> 0.048748123 | G113: =SLOPE(F93:N93,$F$10:$N$10) -> 0.63339241 | H113: =RSQ(F93:N93,$F$10:$N$10) -> 0.98988096 | J113: Crescimento dos Ativos Rentáveis
E114: Títs. e Vlrs. Mobiliários + Aplic. Interfinanceiras s/Hedge | F114: =INTERCEPT(F94:N94,$F$10:$N$10) -> 0.012944212 | G114: =SLOPE(F94:N94,$F$10:$N$10) -> 0.81358025 | H114: =RSQ(F94:N94,$F$10:$N$10) -> 0.98799889 | J114: Regressão com Selic | K114: =INTERCEPT($G$35:$N$35,G10:N10) -> 0.086204996 | L114: =SLOPE($G$35:$N$35,G10:N10) -> -0.20857152 | M114: =RSQ($G$35:$N$35,G10:N10) -> 0.037913501
E115: Operações de Crédito + Leasing | F115: =INTERCEPT(F95:N95,$F$10:$N$10) -> 0.095097087 | G115: =SLOPE(F95:N95,$F$10:$N$10) -> 0.37083784 | H115: =RSQ(F95:N95,$F$10:$N$10) -> 0.93228415 | J115: Rregressão com IPCA | K115: =INTERCEPT($G$35:$N$35,G11:N11) -> 0.0027883996 | L115: =SLOPE($G$35:$N$35,G11:N11) -> 1.0845543 | M115: =RSQ($G$35:$N$35,G11:N11) -> 0.47268862
E116: Depósito Compulsório Rentável | F116: =INTERCEPT(F96:N96,$F$10:$N$10) -> 0.0056168568 | G116: =SLOPE(F96:N96,$F$10:$N$10) -> 0.71990567 | H116: =RSQ(F96:N96,$F$10:$N$10) -> 0.98460402 | J116: Crescimento dos Passivos Onerosos
E117: Demais Ativos Rentáveis | F117: =INTERCEPT(F97:N97,$F$10:$N$10) -> 0.017899584 | G117: =SLOPE(F97:N97,$F$10:$N$10) -> 0.14448823 | H117: =RSQ(F97:N97,$F$10:$N$10) -> 0.2807737 | J117: Regressão com Selic | K117: =INTERCEPT($G$45:$N$45,G10:N10) -> 0.067531657 | L117: =SLOPE($G$45:$N$45,G10:N10) -> -0.085950802 | M117: =RSQ($G$45:$N$45,G10:N10) -> 0.0063444455
E118: Passivos Onerosos | F118: =INTERCEPT(F98:N98,$F$10:$N$10) -> -0.016458585 | G118: =SLOPE(F98:N98,$F$10:$N$10) -> -0.62344366 | H118: =RSQ(F98:N98,$F$10:$N$10) -> 0.98430092 | J118: Regressão com IPCA | K118: =INTERCEPT($G$45:$N$45,G11:N11) -> -0.010651444 | L118: =SLOPE($G$45:$N$45,G11:N11) -> 1.1719304 | M118: =RSQ($G$45:$N$45,G11:N11) -> 0.54385869
...

Sheet G Ativos Rentáveis
BF4: =Dashboard!I4 -> Banco do Brasil ($BBAS3)
A7: Páginas
A8: Dashboard
A9: Ke | D9: DELTA | O9: CRESCIMENTO DO VOLUME DE ATIVOS RENTÁVEIS | Z9: ÍNDICE DE BASILÉIA | AK9: ATIVOS RENTÁVEIS TOTAIS | AV9: PASSIVOS ONEROSOS TOTAIS | BG9: MARGEM FINANCEIRA LÍQUIDA | BR9: LUCRO LÍQUIDO | CC9: PATRIMÔNIO DE REFERÊNCIA | CN9: ATIVOS PONDERADOS PELO RISCO | DA9: 2023 | DB9: 2024 | DC9: 2025 | DD9: 2026 | DE9: 2027 | DF9: 2028 | DG9: 2029 | DH9: 2030 | DI9: 2031 | DJ9: 2032 | DK9: 2033
A10: DRE + DCF | D10: Delta 23 | E10: Delta 24 | F10: Delta 25 | G10: Delta 26 | H10: Delta 27 | I10: Delta 28 | J10: Delta 29 | K10: Delta 30 | L10: Delta 31 | M10: Delta 32 | N10: Delta 33 | O10: Crescimento 23 | P10: Crescimento 24 | Q10: Crescimento 25 | R10: Crescimento 26 | S10: Crescimento 27 | T10: Crescimento 28 | U10: Crescimento 29 | V10: Crescimento 30 | W10: Crescimento 31 | X10: Crescimento 32 | Y10: Crescimento 33 | Z10: Basileia 23 | AA10: Basileia 24 | AB10: Basileia 25 | AC10: Basileia 26 | AD10: Basileia 27 | AE10: Basileia 28 | AF10: Basileia 29 | AG10: Basileia 30 | AH10: Basileia 31 | AI10: Basileia 32 | AJ10: Basileia 33 | AK10: Ativos Rentáveis 23 | AL10: Ativos Rentáveis 24 | AM10: Ativos Rentáveis 25 | AN10: Ativos Rentáveis 26 | AO10: Ativos Rentáveis 27 | AP10: Ativos Rentáveis 28 | AQ10: Ativos Rentáveis 29 | AR10: Ativos Rentáveis 30 | AS10: Ativos Rentáveis 31 | AT10: Ativos Rentáveis 32 | AU10: Ativos Rentáveis 33 | AV10: Passivos Onerosos 23 | AW10: Passivos Onerosos 24 | AX10: Passivos Onerosos 25 | AY10: Passivos Onerosos 26 | AZ10: Passivos Onerosos 27 | BA10: Passivos Onerosos 28 | BB10: Passivos Onerosos 29 | BC10: Passivos Onerosos 30 | BD10: Passivos Onerosos 31 | BE10: Passivos Onerosos 32 | BF10: Passivos Onerosos 33 | BG10: MFL 23 | BH10: MFL 24 | BI10: MFL 25 | BJ10: MFL 26 | BK10: MFL 27 | BL10: MFL 28 | BM10: MFL 29 | BN10: MFL 30 | BO10: MFL 31 | BP10: MFL 32 | BQ10: MFL 33 | BR10: Lucro Líquido 23 | BS10: Lucro Líquido 24 | BT10: Lucro Líquido 25 | BU10: Lucro Líquido 26 | BV10: Lucro Líquido 27 | BW10: Lucro Líquido 28 | BX10: Lucro Líquido 29 | BY10: Lucro Líquido 30 | BZ10: Lucro Líquido 31 | CA10: Lucro Líquido 32 | CB10: Lucro Líquido 33 | CC10: PR 23 | CD10: PR 24 | CE10: PR 25 | CF10: PR 26 | CG10: PR 27 | CH10: PR 28 | CI10: PR 29 | CJ10: PR 30 | CK10: PR 31 | CL10: PR 32 | CM10: PR 33 | CN10: RWA 23 | CO10: RWA 24 | CP10: RWA 25 | CQ10: RWA 26 | CR10: RWA 27 | CS10: RWA 28 | CT10: RWA 29 | CU10: RWA 30 | CV10: RWA 31 | CW10: RWA 32 | CX10: RWA 33 | CZ10: Títs. e Vlrs. Mobiliários + Aplic. Interfinanceiras s/Hedge | DA10: ='Projeções - Receitas'!T37 -> 0.4815449 | DB10: ='Projeções - Receitas'!U37 -> 0.4815449 | DC10: ='Projeções - Receitas'!V37 -> 0.4815449 | DD10: ='Projeções - Receitas'!W37 -> 0.4815449 | DE10: ='Projeções - Receitas'!X37 -> 0.4815449 | DF10: ='Projeções - Receitas'!Y37 -> 0.4815449 | DG10: ='Projeções - Receitas'!Z37 -> 0.4815449 | DH10: ='Projeções - Receitas'!AA37 -> 0.4815449 | ... DK10: ='Projeções - Receitas'!AD37 -> 0.4815449
A11: Contas Abertas | D11: =ABS(Z11-DA$46) -> 0.027977945 | E11: =ABS(AA11-DB$46) -> 0.025264576 | F11: =ABS(AB11-DC$46) -> 0.035614643 | G11: =ABS(AC11-DD$46) -> 0.031174741 | H11: =ABS(AD11-DE$46) -> 0.027041078 | I11: =ABS(AE11-DF$46) -> 0.023170216 | J11: =ABS(AF11-DG$46) -> 0.019529486 | K11: =ABS(AG11-DH$46) -> 0.016088743 | ... N11: =ABS(AJ11-DK$46) -> 0.015344395 | O11: 0 | P11: 0 | Q11: 0 | R11: 0 | S11: 0 | T11: 0 | U11: 0 | V11: 0 | W11: 0 | X11: 0 | Y11: 0 | Z11: =CC11/CN11 -> 0.18516542 | AA11: =CD11/CO11 -> 0.18245205 | AB11: =CE11/CP11 -> 0.19280212 | AC11: =CF11/CQ11 -> 0.18836222 | AD11: =CG11/CR11 -> 0.18422856 | AE11: =CH11/CS11 -> 0.18035769 | AF11: =CI11/CT11 -> 0.17671696 | AG11: =CJ11/CU11 -> 0.17327622 | ... AJ11: =CM11/CX11 -> 0.17253187 | AK11: =(1+O11)*'Projeções - Receitas'!N$34 -> 1.8431823e+12 | AL11: =(1+P11)*'Projeções - Receitas'!T$34 -> 1.9466863e+12 | AM11: =(1+Q11)*'Projeções - Receitas'!U$34 -> 2.1802887e+12 | AN11: =(1+R11)*'Projeções - Receitas'!V$34 -> 2.4419234e+12 | AO11: =(1+S11)*'Projeções - Receitas'!W$34 -> 2.7349542e+12 | AP11: =(1+T11)*'Projeções - Receitas'!X$34 -> 3.0631487e+12 | AQ11: =(1+U11)*'Projeções - Receitas'!Y$34 -> 3.4307265e+12 | AR11: =(1+V11)*'Projeções - Receitas'!Z$34 -> 3.8424137e+12 | AS11: =(1+W11)*'Projeções - Receitas'!AA$34 -> 4.2804488e+12 | ... AU11: =(1+Y11)*'Projeções - Receitas'!AC$34 -> 5.1347066e+12 | AV11: =AK11*DA$49 -> 1.6138368e+12 | AW11: =AL11*DB$49 -> 1.7044619e+12 | AX11: =AM11*DC$49 -> 1.9089973e+12 | AY11: =AN11*DD$49 -> 2.138077e+12 | AZ11: =AO11*DE$49 -> 2.3946463e+12 | BA11: =AP11*DF$49 -> 2.6820038e+12 | BB11: =AQ11*DG$49 -> 3.0038443e+12 | BC11: =AR11*DH$49 -> 3.3643056e+12 | ... BF11: =AU11*DK$49 -> 4.4957996e+12 | BG11: =(AK11*SUMPRODUCT(DA$10:DA$13,DA$28:DA$31)+AV11*SUMPRODUCT(DA$14:DA$23,DA$32:DA$41))*'Projeções - Receitas'!T$23+(AK11*DA$11*'Projeções - Receitas'!T$25) -> 5.9878627e+10 | BH11: =(AL11*SUMPRODUCT(DB$10:DB$13,DB$28:DB$31)+AW11*SUMPRODUCT(DB$14:DB$23,DB$32:DB$41))*'Projeções - Receitas'!U$23+(AL11*DB$11*'Projeções - Receitas'!U$25) -> 4.7976159e+10 | BI11: =(AM11*SUMPRODUCT(DC$10:DC$13,DC$28:DC$31)+AX11*SUMPRODUCT(DC$14:DC$23,DC$32:DC$41))*'Projeções - Receitas'!V$23+(AM11*DC$11*'Projeções - Receitas'!V$25) -> 5.3065471e+10 | BJ11: =(AN11*SUMPRODUCT(DD$10:DD$13,DD$28:DD$31)+AY11*SUMPRODUCT(DD$14:DD$23,DD$32:DD$41))*'Projeções - Receitas'!W$23+(AN11*DD$11*'Projeções - Receitas'!W$25) -> 5.8649911e+10 | BK11: =(AO11*SUMPRODUCT(DE$10:DE$13,DE$28:DE$31)+AZ11*SUMPRODUCT(DE$14:DE$23,DE$32:DE$41))*'Projeções - Receitas'!X$23+(AO11*DE$11*'Projeções - Receitas'!X$25) -> 6.4804834e+10 | BL11: =(AP11*SUMPRODUCT(DF$10:DF$13,DF$28:DF$31)+BA11*SUMPRODUCT(DF$14:DF$23,DF$32:DF$41))*'Projeções - Receitas'!Y$23+(AP11*DF$11*'Projeções - Receitas'!Y$25) -> 7.1595345e+10 | BM11: =(AQ11*SUMPRODUCT(DG$10:DG$13,DG$28:DG$31)+BB11*SUMPRODUCT(DG$14:DG$23,DG$32:DG$41))*'Projeções - Receitas'!Z$23+(AQ11*DG$11*'Projeções - Receitas'!Z$25) -> 7.909004e+10 | BN11: =(AR11*SUMPRODUCT(DH$10:DH$13,DH$28:DH$31)+BC11*SUMPRODUCT(DH$14:DH$23,DH$32:DH$41))*'Projeções - Receitas'!AA$23+(AR11*DH$11*'Projeções - Receitas'!AA$25) -> 8.7359927e+10 | ... BQ11: =(AU11*SUMPRODUCT(DK$10:DK$13,DK$28:DK$31)+BF11*SUMPRODUCT(DK$14:DK$23,DK$32:DK$41))*'Projeções - Receitas'!AD$23+(AU11*DK$11*'Projeções - Receitas'!AD$25) -> 1.3190426e+11 | BR11: =((BG11+'DRE + DCF'!T$12)*(1+'DRE + DCF'!T$15)+'DRE + DCF'!T$18)*(1+'DRE + DCF'!T$25)*'DRE + DCF'!T$33 -> 3.2631312e+10 | BS11: =((BH11+'DRE + DCF'!U$12)*(1+'DRE + DCF'!U$15)+'DRE + DCF'!U$18)*(1+'DRE + DCF'!U$25)*'DRE + DCF'!U$33 -> 2.4564151e+10 | BT11: =((BI11+'DRE + DCF'!V$12)*(1+'DRE + DCF'!V$15)+'DRE + DCF'!V$18)*(1+'DRE + DCF'!V$25)*'DRE + DCF'!V$33 -> 2.7324143e+10 | BU11: =((BJ11+'DRE + DCF'!W$12)*(1+'DRE + DCF'!W$15)+'DRE + DCF'!W$18)*(1+'DRE + DCF'!W$25)*'DRE + DCF'!W$33 -> 3.0339514e+10 | BV11: =((BK11+'DRE + DCF'!X$12)*(1+'DRE + DCF'!X$15)+'DRE + DCF'!X$18)*(1+'DRE + DCF'!X$25)*'DRE + DCF'!X$33 -> 3.3641849e+10 | BW11: =((BL11+'DRE + DCF'!Y$12)*(1+'DRE + DCF'!Y$15)+'DRE + DCF'!Y$18)*(1+'DRE + DCF'!Y$25)*'DRE + DCF'!Y$33 -> 3.7271999e+10 | BX11: =((BM11+'DRE + DCF'!Z$12)*(1+'DRE + DCF'!Z$15)+'DRE + DCF'!Z$18)*(1+'DRE + DCF'!Z$25)*'DRE + DCF'!Z$33 -> 4.1275194e+10 | BY11: =((BN11+'DRE + DCF'!AA$12)*(1+'DRE + DCF'!AA$15)+'DRE + DCF'!AA$18)*(1+'DRE + DCF'!AA$25)*'DRE + DCF'!AA$33 -> 4.5683474e+10 | ... CB11: =((BQ11+'DRE + DCF'!AD$12)*(1+'DRE + DCF'!AD$15)+'DRE + DCF'!AD$18)*(1+'DRE + DCF'!AD$25)*'DRE + DCF'!AD$33 -> 6.8204263e+10 | CC11: =BR11*(1-DA$47)+('DRE + DCF'!N$53*10^6) -> 1.9866288e+11 | CD11: =BS11*(1-DB$47)+('DRE + DCF'!T$53*10^6) -> 1.9941556e+11 | CE11: =BT11*(1-DC$47)+('DRE + DCF'!U$53*10^6) -> 2.1791506e+11 | CF11: =BU11*(1-DD$47)+('DRE + DCF'!V$53*10^6) -> 2.3844447e+11 | CG11: =BV11*(1-DE$47)+('DRE + DCF'!W$53*10^6) -> 2.6119715e+11 | CH11: =BW11*(1-DF$47)+('DRE + DCF'!X$53*10^6) -> 2.8639418e+11 | CI11: =BX11*(1-DG$47)+('DRE + DCF'!Y$53*10^6) -> 3.1428653e+11 | CJ11: =BY11*(1-DH$47)+('DRE + DCF'!Z$53*10^6) -> 3.4514733e+11 | CK11: =BZ11*(1-DI$47)+('DRE + DCF'!AA$53*10^6) -> 3.7890643e+11 | ... CM11: =CB11*(1-DK$47)+('DRE + DCF'!AC$53*10^6) -> 4.5924708e+11 | CN11: =AK11*DA$48 -> 1.072894e+12 | CO11: =AL11*DB$48 -> 1.0929751e+12 | CP11: =AM11*DC$48 -> 1.1302524e+12 | CQ11: =AN11*DD$48 -> 1.2658827e+12 | CR11: =AO11*DE$48 -> 1.4177886e+12 | CS11: =AP11*DF$48 -> 1.5879233e+12 | CT11: =AQ11*DG$48 -> 1.778474e+12 | CU11: =AR11*DH$48 -> 1.9918909e+12 | ... CX11: =AU11*DK$48 -> 2.6618101e+12 | CZ11: Operações de Crédito + Leasing | DA11: ='Projeções - Receitas'!T39 -> 0.46943097 | DB11: ='Projeções - Receitas'!U39 -> 0.46943097 | DC11: ='Projeções - Receitas'!V39 -> 0.46943097 | DD11: ='Projeções - Receitas'!W39 -> 0.46943097 | DE11: ='Projeções - Receitas'!X39 -> 0.46943097 | DF11: ='Projeções - Receitas'!Y39 -> 0.46943097 | DG11: ='Projeções - Receitas'!Z39 -> 0.46943097 | DH11: ='Projeções - Receitas'!AA39 -> 0.46943097 | ... DK11: ='Projeções - Receitas'!AD39 -> 0.46943097
A12: Balanço Patrimonial | D12: =ABS(Z12-DA$46) -> 0.027895914 | E12: =ABS(AA12-DB$46) -> 0.025181416 | F12: =ABS(AB12-DC$46) -> 0.035526859 | G12: =ABS(AC12-DD$46) -> 0.031089054 | H12: =ABS(AD12-DE$46) -> 0.026957334 | I12: =ABS(AE12-DF$46) -> 0.023088283 | J12: =ABS(AF12-DG$46) -> 0.019449252 | K12: =ABS(AG12-DH$46) -> 0.016010108 | ... N12: =ABS(AJ12-DK$46) -> 0.015266846 | O12: =O11+0.0005 -> 0.0005 | P12: =P11+0.0005 -> 0.0005 | Q12: =Q11+0.0005 -> 0.0005 | R12: =R11+0.0005 -> 0.0005 | S12: =S11+0.0005 -> 0.0005 | T12: =T11+0.0005 -> 0.0005 | U12: =U11+0.0005 -> 0.0005 | V12: =V11+0.0005 -> 0.0005 | ... Y12: =Y11+0.0005 -> 0.0005 | Z12: =CC12/CN12 -> 0.18508339 | AA12: =CD12/CO12 -> 0.18236889 | AB12: =CE12/CP12 -> 0.19271434 | AC12: =CF12/CQ12 -> 0.18827653 | AD12: =CG12/CR12 -> 0.18414481 | AE12: =CH12/CS12 -> 0.18027576 | AF12: =CI12/CT12 -> 0.17663673 | AG12: =CJ12/CU12 -> 0.17319759 | ... AJ12: =CM12/CX12 -> 0.17245432 | AK12: =(1+O12)*'Projeções - Receitas'!N$34 -> 1.8441039e+12 | AL12: =(1+P12)*'Projeções - Receitas'!T$34 -> 1.9476597e+12 | AM12: =(1+Q12)*'Projeções - Receitas'!U$34 -> 2.1813789e+12 | AN12: =(1+R12)*'Projeções - Receitas'!V$34 -> 2.4431443e+12 | AO12: =(1+S12)*'Projeções - Receitas'!W$34 -> 2.7363216e+12 | AP12: =(1+T12)*'Projeções - Receitas'!X$34 -> 3.0646802e+12 | AQ12: =(1+U12)*'Projeções - Receitas'!Y$34 -> 3.4324419e+12 | AR12: =(1+V12)*'Projeções - Receitas'!Z$34 -> 3.8443349e+12 | AS12: =(1+W12)*'Projeções - Receitas'!AA$34 -> 4.2825891e+12 | ... AU12: =(1+Y12)*'Projeções - Receitas'!AC$34 -> 5.1372739e+12 | AV12: =AK12*DA$49 -> 1.6146437e+12 | AW12: =AL12*DB$49 -> 1.7053141e+12 | AX12: =AM12*DC$49 -> 1.9099518e+12 | AY12: =AN12*DD$49 -> 2.1391461e+12 | AZ12: =AO12*DE$49 -> 2.3958436e+12 | BA12: =AP12*DF$49 -> 2.6833448e+12 | BB12: =AQ12*DG$49 -> 3.0053462e+12 | BC12: =AR12*DH$49 -> 3.3659877e+12 | ... BF12: =AU12*DK$49 -> 4.4980475e+12 | BG12: =(AK12*SUMPRODUCT(DA$10:DA$13,DA$28:DA$31)+AV12*SUMPRODUCT(DA$14:DA$23,DA$32:DA$41))*'Projeções - Receitas'!T$23+(AK12*DA$11*'Projeções - Receitas'!T$25) -> 5.9908566e+10 | BH12: =(AL12*SUMPRODUCT(DB$10:DB$13,DB$28:DB$31)+AW12*SUMPRODUCT(DB$14:DB$23,DB$32:DB$41))*'Projeções - Receitas'!U$23+(AL12*DB$11*'Projeções - Receitas'!U$25) -> 4.8000147e+10 | BI12: =(AM12*SUMPRODUCT(DC$10:DC$13,DC$28:DC$31)+AX12*SUMPRODUCT(DC$14:DC$23,DC$32:DC$41))*'Projeções - Receitas'!V$23+(AM12*DC$11*'Projeções - Receitas'!V$25) -> 5.3092004e+10 | BJ12: =(AN12*SUMPRODUCT(DD$10:DD$13,DD$28:DD$31)+AY12*SUMPRODUCT(DD$14:DD$23,DD$32:DD$41))*'Projeções - Receitas'!W$23+(AN12*DD$11*'Projeções - Receitas'!W$25) -> 5.8679236e+10 | BK12: =(AO12*SUMPRODUCT(DE$10:DE$13,DE$28:DE$31)+AZ12*SUMPRODUCT(DE$14:DE$23,DE$32:DE$41))*'Projeções - Receitas'!X$23+(AO12*DE$11*'Projeções - Receitas'!X$25) -> 6.4837237e+10 | BL12: =(AP12*SUMPRODUCT(DF$10:DF$13,DF$28:DF$31)+BA12*SUMPRODUCT(DF$14:DF$23,DF$32:DF$41))*'Projeções - Receitas'!Y$23+(AP12*DF$11*'Projeções - Receitas'!Y$25) -> 7.1631143e+10 | BM12: =(AQ12*SUMPRODUCT(DG$10:DG$13,DG$28:DG$31)+BB12*SUMPRODUCT(DG$14:DG$23,DG$32:DG$41))*'Projeções - Receitas'!Z$23+(AQ12*DG$11*'Projeções - Receitas'!Z$25) -> 7.9129585e+10 | BN12: =(AR12*SUMPRODUCT(DH$10:DH$13,DH$28:DH$31)+BC12*SUMPRODUCT(DH$14:DH$23,DH$32:DH$41))*'Projeções - Receitas'!AA$23+(AR12*DH$11*'Projeções - Receitas'!AA$25) -> 8.7403607e+10 | ... BQ12: =(AU12*SUMPRODUCT(DK$10:DK$13,DK$28:DK$31)+BF12*SUMPRODUCT(DK$14:DK$23,DK$32:DK$41))*'Projeções - Receitas'!AD$23+(AU12*DK$11*'Projeções - Receitas'!AD$25) -> 1.3197021e+11 | BR12: =((BG12+'DRE + DCF'!T$12)*(1+'DRE + DCF'!T$15)+'DRE + DCF'!T$18)*(1+'DRE + DCF'!T$25)*'DRE + DCF'!T$33 -> 3.2649735e+10 | BS12: =((BH12+'DRE + DCF'!U$12)*(1+'DRE + DCF'!U$15)+'DRE + DCF'!U$18)*(1+'DRE + DCF'!U$25)*'DRE + DCF'!U$33 -> 2.4578769e+10 | BT12: =((BI12+'DRE + DCF'!V$12)*(1+'DRE + DCF'!V$15)+'DRE + DCF'!V$18)*(1+'DRE + DCF'!V$25)*'DRE + DCF'!V$33 -> 2.7340294e+10 | BU12: =((BJ12+'DRE + DCF'!W$12)*(1+'DRE + DCF'!W$15)+'DRE + DCF'!W$18)*(1+'DRE + DCF'!W$25)*'DRE + DCF'!W$33 -> 3.0357344e+10 | BV12: =((BK12+'DRE + DCF'!X$12)*(1+'DRE + DCF'!X$15)+'DRE + DCF'!X$18)*(1+'DRE + DCF'!X$25)*'DRE + DCF'!X$33 -> 3.3661529e+10 | BW12: =((BL12+'DRE + DCF'!Y$12)*(1+'DRE + DCF'!Y$15)+'DRE + DCF'!Y$18)*(1+'DRE + DCF'!Y$25)*'DRE + DCF'!Y$33 -> 3.7293716e+10 | BX12: =((BM12+'DRE + DCF'!Z$12)*(1+'DRE + DCF'!Z$15)+'DRE + DCF'!Z$18)*(1+'DRE + DCF'!Z$25)*'DRE + DCF'!Z$33 -> 4.1299158e+10 | BY12: =((BN12+'DRE + DCF'!AA$12)*(1+'DRE + DCF'!AA$15)+'DRE + DCF'!AA$18)*(1+'DRE + DCF'!AA$25)*'DRE + DCF'!AA$33 -> 4.5709913e+10 | ... CB12: =((BQ12+'DRE + DCF'!AD$12)*(1+'DRE + DCF'!AD$15)+'DRE + DCF'!AD$18)*(1+'DRE + DCF'!AD$25)*'DRE + DCF'!AD$33 -> 6.8242762e+10 | CC12: =BR12*(1-DA$47)+('DRE + DCF'!N$53*10^6) -> 1.9867416e+11 | CD12: =BS12*(1-DB$47)+('DRE + DCF'!T$53*10^6) -> 1.9942433e+11 | CE12: =BT12*(1-DC$47)+('DRE + DCF'!U$53*10^6) -> 2.1792475e+11 | CF12: =BU12*(1-DD$47)+('DRE + DCF'!V$53*10^6) -> 2.3845517e+11 | CG12: =BV12*(1-DE$47)+('DRE + DCF'!W$53*10^6) -> 2.6120896e+11 | CH12: =BW12*(1-DF$47)+('DRE + DCF'!X$53*10^6) -> 2.8640721e+11 | CI12: =BX12*(1-DG$47)+('DRE + DCF'!Y$53*10^6) -> 3.1430091e+11 | CJ12: =BY12*(1-DH$47)+('DRE + DCF'!Z$53*10^6) -> 3.451632e+11 | CK12: =BZ12*(1-DI$47)+('DRE + DCF'!AA$53*10^6) -> 3.7892383e+11 | ... CM12: =CB12*(1-DK$47)+('DRE + DCF'!AC$53*10^6) -> 4.5927018e+11 | CN12: =AK12*DA$48 -> 1.0734305e+12 | CO12: =AL12*DB$48 -> 1.0935216e+12 | CP12: =AM12*DC$48 -> 1.1308175e+12 | CQ12: =AN12*DD$48 -> 1.2665156e+12 | CR12: =AO12*DE$48 -> 1.4184975e+12 | CS12: =AP12*DF$48 -> 1.5887172e+12 | CT12: =AQ12*DG$48 -> 1.7793633e+12 | CU12: =AR12*DH$48 -> 1.9928869e+12 | ... CX12: =AU12*DK$48 -> 2.663141e+12 | CZ12: Depósito Compulsório Rentável | DA12: ='Projeções - Receitas'!T41 -> 0.041615633 | DB12: ='Projeções - Receitas'!U41 -> 0.041615633 | DC12: ='Projeções - Receitas'!V41 -> 0.041615633 | DD12: ='Projeções - Receitas'!W41 -> 0.041615633 | DE12: ='Projeções - Receitas'!X41 -> 0.041615633 | DF12: ='Projeções - Receitas'!Y41 -> 0.041615633 | DG12: ='Projeções - Receitas'!Z41 -> 0.041615633 | DH12: ='Projeções - Receitas'!AA41 -> 0.041615633 | ... DK12: ='Projeções - Receitas'!AD41 -> 0.041615633
A13: Projeções - Receita | D13: =ABS(Z13-DA$46) -> 0.027813965 | E13: =ABS(AA13-DB$46) -> 0.02509834 | F13: =ABS(AB13-DC$46) -> 0.035439163 | G13: =ABS(AC13-DD$46) -> 0.031003452 | H13: =ABS(AD13-DE$46) -> 0.026873673 | I13: =ABS(AE13-DF$46) -> 0.023006433 | J13: =ABS(AF13-DG$46) -> 0.019369099 | K13: =ABS(AG13-DH$46) -> 0.015931552 | ... N13: =ABS(AJ13-DK$46) -> 0.015189375 | O13: =O12+0.0005 -> 0.001 | P13: =P12+0.0005 -> 0.001 | Q13: =Q12+0.0005 -> 0.001 | R13: =R12+0.0005 -> 0.001 | S13: =S12+0.0005 -> 0.001 | T13: =T12+0.0005 -> 0.001 | U13: =U12+0.0005 -> 0.001 | V13: =V12+0.0005 -> 0.001 | ... Y13: =Y12+0.0005 -> 0.001 | Z13: =CC13/CN13 -> 0.18500144 | AA13: =CD13/CO13 -> 0.18228582 | AB13: =CE13/CP13 -> 0.19262664 | AC13: =CF13/CQ13 -> 0.18819093 | AD13: =CG13/CR13 -> 0.18406115 | AE13: =CH13/CS13 -> 0.18019391 | AF13: =CI13/CT13 -> 0.17655658 | AG13: =CJ13/CU13 -> 0.17311903 | ... AJ13: =CM13/CX13 -> 0.17237685 | AK13: =(1+O13)*'Projeções - Receitas'!N$34 -> 1.8450255e+12 | AL13: =(1+P13)*'Projeções - Receitas'!T$34 -> 1.948633e+12 | AM13: =(1+Q13)*'Projeções - Receitas'!U$34 -> 2.182469e+12 | AN13: =(1+R13)*'Projeções - Receitas'!V$34 -> 2.4443653e+12 | AO13: =(1+S13)*'Projeções - Receitas'!W$34 -> 2.7376891e+12 | AP13: =(1+T13)*'Projeções - Receitas'!X$34 -> 3.0662118e+12 | AQ13: =(1+U13)*'Projeções - Receitas'!Y$34 -> 3.4341572e+12 | AR13: =(1+V13)*'Projeções - Receitas'!Z$34 -> 3.8462561e+12 | AS13: =(1+W13)*'Projeções - Receitas'!AA$34 -> 4.2847293e+12 | ... AU13: =(1+Y13)*'Projeções - Receitas'!AC$34 -> 5.1398413e+12 | AV13: =AK13*DA$49 -> 1.6154506e+12 | AW13: =AL13*DB$49 -> 1.7061664e+12 | AX13: =AM13*DC$49 -> 1.9109063e+12 | AY13: =AN13*DD$49 -> 2.1402151e+12 | AZ13: =AO13*DE$49 -> 2.3970409e+12 | BA13: =AP13*DF$49 -> 2.6846858e+12 | BB13: =AQ13*DG$49 -> 3.0068481e+12 | BC13: =AR13*DH$49 -> 3.3676699e+12 | ... BF13: =AU13*DK$49 -> 4.5002954e+12 | BG13: =(AK13*SUMPRODUCT(DA$10:DA$13,DA$28:DA$31)+AV13*SUMPRODUCT(DA$14:DA$23,DA$32:DA$41))*'Projeções - Receitas'!T$23+(AK13*DA$11*'Projeções - Receitas'!T$25) -> 5.9938506e+10 | BH13: =(AL13*SUMPRODUCT(DB$10:DB$13,DB$28:DB$31)+AW13*SUMPRODUCT(DB$14:DB$23,DB$32:DB$41))*'Projeções - Receitas'!U$23+(AL13*DB$11*'Projeções - Receitas'!U$25) -> 4.8024135e+10 | BI13: =(AM13*SUMPRODUCT(DC$10:DC$13,DC$28:DC$31)+AX13*SUMPRODUCT(DC$14:DC$23,DC$32:DC$41))*'Projeções - Receitas'!V$23+(AM13*DC$11*'Projeções - Receitas'!V$25) -> 5.3118536e+10 | BJ13: =(AN13*SUMPRODUCT(DD$10:DD$13,DD$28:DD$31)+AY13*SUMPRODUCT(DD$14:DD$23,DD$32:DD$41))*'Projeções - Receitas'!W$23+(AN13*DD$11*'Projeções - Receitas'!W$25) -> 5.8708561e+10 | BK13: =(AO13*SUMPRODUCT(DE$10:DE$13,DE$28:DE$31)+AZ13*SUMPRODUCT(DE$14:DE$23,DE$32:DE$41))*'Projeções - Receitas'!X$23+(AO13*DE$11*'Projeções - Receitas'!X$25) -> 6.4869639e+10 | BL13: =(AP13*SUMPRODUCT(DF$10:DF$13,DF$28:DF$31)+BA13*SUMPRODUCT(DF$14:DF$23,DF$32:DF$41))*'Projeções - Receitas'!Y$23+(AP13*DF$11*'Projeções - Receitas'!Y$25) -> 7.1666941e+10 | BM13: =(AQ13*SUMPRODUCT(DG$10:DG$13,DG$28:DG$31)+BB13*SUMPRODUCT(DG$14:DG$23,DG$32:DG$41))*'Projeções - Receitas'!Z$23+(AQ13*DG$11*'Projeções - Receitas'!Z$25) -> 7.916913e+10 | BN13: =(AR13*SUMPRODUCT(DH$10:DH$13,DH$28:DH$31)+BC13*SUMPRODUCT(DH$14:DH$23,DH$32:DH$41))*'Projeções - Receitas'!AA$23+(AR13*DH$11*'Projeções - Receitas'!AA$25) -> 8.7447287e+10 | ... BQ13: =(AU13*SUMPRODUCT(DK$10:DK$13,DK$28:DK$31)+BF13*SUMPRODUCT(DK$14:DK$23,DK$32:DK$41))*'Projeções - Receitas'!AD$23+(AU13*DK$11*'Projeções - Receitas'!AD$25) -> 1.3203616e+11 | BR13: =((BG13+'DRE + DCF'!T$12)*(1+'DRE + DCF'!T$15)+'DRE + DCF'!T$18)*(1+'DRE + DCF'!T$25)*'DRE + DCF'!T$33 -> 3.2668157e+10 | BS13: =((BH13+'DRE + DCF'!U$12)*(1+'DRE + DCF'!U$15)+'DRE + DCF'!U$18)*(1+'DRE + DCF'!U$25)*'DRE + DCF'!U$33 -> 2.4593388e+10 | BT13: =((BI13+'DRE + DCF'!V$12)*(1+'DRE + DCF'!V$15)+'DRE + DCF'!V$18)*(1+'DRE + DCF'!V$25)*'DRE + DCF'!V$33 -> 2.7356445e+10 | BU13: =((BJ13+'DRE + DCF'!W$12)*(1+'DRE + DCF'!W$15)+'DRE + DCF'!W$18)*(1+'DRE + DCF'!W$25)*'DRE + DCF'!W$33 -> 3.0375175e+10 | BV13: =((BK13+'DRE + DCF'!X$12)*(1+'DRE + DCF'!X$15)+'DRE + DCF'!X$18)*(1+'DRE + DCF'!X$25)*'DRE + DCF'!X$33 -> 3.3681208e+10 | BW13: =((BL13+'DRE + DCF'!Y$12)*(1+'DRE + DCF'!Y$15)+'DRE + DCF'!Y$18)*(1+'DRE + DCF'!Y$25)*'DRE + DCF'!Y$33 -> 3.7315433e+10 | BX13: =((BM13+'DRE + DCF'!Z$12)*(1+'DRE + DCF'!Z$15)+'DRE + DCF'!Z$18)*(1+'DRE + DCF'!Z$25)*'DRE + DCF'!Z$33 -> 4.1323121e+10 | BY13: =((BN13+'DRE + DCF'!AA$12)*(1+'DRE + DCF'!AA$15)+'DRE + DCF'!AA$18)*(1+'DRE + DCF'!AA$25)*'DRE + DCF'!AA$33 -> 4.5736352e+10 | ... CB13: =((BQ13+'DRE + DCF'!AD$12)*(1+'DRE + DCF'!AD$15)+'DRE + DCF'!AD$18)*(1+'DRE + DCF'!AD$25)*'DRE + DCF'!AD$33 -> 6.8281262e+10 | CC13: =BR13*(1-DA$47)+('DRE + DCF'!N$53*10^6) -> 1.9868543e+11 | CD13: =BS13*(1-DB$47)+('DRE + DCF'!T$53*10^6) -> 1.994331e+11 | CE13: =BT13*(1-DC$47)+('DRE + DCF'!U$53*10^6) -> 2.1793444e+11 | CF13: =BU13*(1-DD$47)+('DRE + DCF'!V$53*10^6) -> 2.3846587e+11 | CG13: =BV13*(1-DE$47)+('DRE + DCF'!W$53*10^6) -> 2.6122076e+11 | CH13: =BW13*(1-DF$47)+('DRE + DCF'!X$53*10^6) -> 2.8642024e+11 | CI13: =BX13*(1-DG$47)+('DRE + DCF'!Y$53*10^6) -> 3.1431529e+11 | CJ13: =BY13*(1-DH$47)+('DRE + DCF'!Z$53*10^6) -> 3.4517906e+11 | CK13: =BZ13*(1-DI$47)+('DRE + DCF'!AA$53*10^6) -> 3.7894124e+11 | ... CM13: =CB13*(1-DK$47)+('DRE + DCF'!AC$53*10^6) -> 4.5929328e+11 | CN13: =AK13*DA$48 -> 1.0739669e+12 | CO13: =AL13*DB$48 -> 1.0940681e+12 | CP13: =AM13*DC$48 -> 1.1313827e+12 | CQ13: =AN13*DD$48 -> 1.2671486e+12 | CR13: =AO13*DE$48 -> 1.4192064e+12 | CS13: =AP13*DF$48 -> 1.5895112e+12 | CT13: =AQ13*DG$48 -> 1.7802525e+12 | CU13: =AR13*DH$48 -> 1.9938828e+12 | ... CX13: =AU13*DK$48 -> 2.6644719e+12 | CZ13: Demais Ativos Rentáveis | DA13: ='Projeções - Receitas'!T43 -> 0.0074084985 | DB13: ='Projeções - Receitas'!U43 -> 0.0074084985 | DC13: ='Projeções - Receitas'!V43 -> 0.0074084985 | DD13: ='Projeções - Receitas'!W43 -> 0.0074084985 | DE13: ='Projeções - Receitas'!X43 -> 0.0074084985 | DF13: ='Projeções - Receitas'!Y43 -> 0.0074084985 | DG13: ='Projeções - Receitas'!Z43 -> 0.0074084985 | DH13: ='Projeções - Receitas'!AA43 -> 0.0074084985 | ... DK13: ='Projeções - Receitas'!AD43 -> 0.0074084985
